Workbook

Sheet README
A1: BitMach Master Model | v3 detailed EPC, vendor finance and debt structure
A2: This version adds engineer-friendly electrical CAPEX detail, vendor-style miner finance, EPC tranches, external funding and an amortization tab.
A3: What this workbook does | B3: Builds a formula-driven model for (i) the first 12 months of Phase 1 cash flow and burn, and (ii) a simplified 10-year site / solar / compute ramp to 2GW.
A4: Updated / new tabs | B4: Purpose
A5: CAPEX_Electrical_Detail | B5: Exact Hamar T2603-24 electrical quote packages, scope quantities, adders for unpriced items, and normalization into fixed/site + variable/MW electrical CAPEX.
A6: 12M_Miner_Vendor | B6: M7DS hardware basis with supplier-style payment mechanics: deposit, vendor-financed balance, monthly principal and interest schedule.
A7: 12M_EPC_Tranches | B7: Gross monthly electrical EPC basis and assumed EPC payment tranches / retention finance.
A8: 12M_Funding | B8: Equity and senior debt draw schedule sized to monthly funding need, net of arrangement fees.
A9: Debt_Amortization | B9: Indicative 60-month senior debt schedule with interest capitalized during grace and amortization thereafter.
A10: 12M_Capex / 12M_Cashflow | B10: Now reference the detailed sheets rather than generic hard-coded timing heuristics for the main hardware / EPC cash spend.

Sheet Control
A1: Control Centre | Edit blue cells only
A2: Core assumptions, logistics, staffing and optional revenue controls.
A3: Driver | B3: Unit | C3: Base Case | D3: Notes
A4: FX (ZAR/USD) | B4: ZAR/USD | C4: 17 | D4: April 2026 investor materials use R17.00/USD for Phase 1 capital framing.
A5: Opening cash | B5: ZAR'000 | C5: 0 | D5: Leave at 0 to see pure burn before financing.
A6: BTC price start | B6: USD/BTC | C6: 75000 | D6: Conservative editable placeholder.
A7: BTC annual growth | B7: % | C7: 0.1 | D7: Editable market assumption.
A8: Network hash start | B8: TH/s | C8: 900000000 | D8: Editable network assumption.
A9: Network hash annual growth | B9: % | C9: 0.15 | D9: Editable market assumption.
A10: Block subsidy | B10: BTC/block | C10: 3.125 | D10: Protocol input.
A11: Fee factor on subsidy | B11: % | C11: 0.1 | D11: Protocol / pool-fee uplift assumption.
A12: Blocks per day | B12: blocks/day | C12: 144 | D12: Protocol input.
A13: Tax rate | B13: % | C13: 0.27 | D13: Placeholder corporate tax rate.
A14: Uptime | B14: % | C14: 0.95 | D14: Operational uptime.
A15: General annual inflation | B15: % | C15: 0.05 | D15: 10Y model escalation.
... A31: Miner efficiency | B31: J/T | C31: 12.5 | D31: Management instruction: use M7DS at 12.5J/T.
A32: Miner power | B32: W/miner | C32: =C30*C31 | D32: Formula = hashrate × J/T.
A33: Miner price | B33: USD/miner | C33: 5915 | D33: From latest uploaded workbook; editable.
A34: Aux load | B34: % | C34: 0.05 | D34: Cooling / container auxiliaries.
A35: Miner slots per XS2400 | B35: miners/container | C35: 240 | D35: HeatCore XS2400 working basis.
A36: Hydro container cost | B36: USD/container | C36: 350000 | D36: Hydro container placeholder; replace with quote.
A37: Container gross MW | B37: MW/container | C37: =(C35*C32/1000000)*(1+C34) | D37: Formula from miner power, slot count and aux load.
A38: Miner maintenance | B38: ZAR/miner/year | C38: 2000 | D38: Recurring maintenance per miner.
A39: Electrical/BOS capex | B39: ZAR'000/MW | C39: =CAPEX_Electrical_Detail!$C$28 | D39: All-in electrical EPC per MW from detailed Hamar quote basis incl adders. Summary use only; monthly/annual sheets now use fixed/site + variable/MW.
A40: Ocean freight | B40: USD/container | C40: 8000 | D40: Editable logistics placeholder.
A41: Port/clearing | B41: ZAR'000/container | C41: 150 | D41: Editable logistics placeholder.
A42: Inland trucking | B42: ZAR'000/container | C42: 120 | D42: Editable logistics placeholder.
A43: Crane/rigging | B43: ZAR'000/container | C43: 100 | D43: Editable logistics placeholder.
A44: Cargo insurance | B44: % | C44: 0.01 | D44: Editable cargo insurance assumption.
A45: Import duty | B45: % | C45: 0.05 | D45: Editable customs placeholder.
A46: Initial spare parts | B46: % | C46: 0.02 | D46: Initial spares as % of hardware capex.
A47: Tools & equipment initial | B47: ZAR'000/site | C47: 750 | D47: Tools, meters, accessories and small equipment.
A48: Office setup / deposits | B48: ZAR'000 | C48: 600 | D48: Corporate office setup / deposits.
A49: Software / SCADA setup | B49: ZAR'000 | C49: 1500 | D49: Initial systems setup.
A50: Legal setup total | B50: ZAR'000 | C50: 1200 | D50: Initial legal documentation.
A51: Staff hardware setup | B51: ZAR'000/FTE | C51: 35 | D51: Laptop / phone / PPE / provisioning.
... A87: Annual DR equivalent hours/day | B87: hours/day | C87: 1.5 | D87: Annual DR hours placeholder.
A89: Detailed EPC & financing assumptions
A90: Electrical site-fixed share | B90: % of all-in 20MW electrical EPC | C90: 0.25 | D90: Use to split the Hamar 20MW quote into fixed/site cost and variable/MW cost.
A91: Harmonic mitigation allowance | B91: % of quoted electrical EPC | C91: 0.05 | D91: Quote explicitly excludes harmonic mitigation pending Stage 3 spectra; editable allowance.
A92: Lighting / small power allowance | B92: % of quoted electrical EPC | C92: 0.01 | D92: Quote shows lighting blank; editable allowance.
A93: Instrumentation / SCADA allowance | B93: % of quoted electrical EPC | C93: 0.01 | D93: Quote shows instrumentation blank; editable allowance.
A94: Earthing / lightning allowance | B94: % of quoted electrical EPC | C94: 0.02 | D94: Concept basis requires earthing / lightning and wet/high-humidity suitability.
A95: Civil / drainage / fencing allowance | B95: % of quoted electrical EPC | C95: 0.03 | D95: Brownfield enabling works not fully priced in the electrical quote.
A96: Brownfield site similarity factor | B96: x | C96: 1 | D96: 1.00 = use Grootvlei basis as-is for comparable sites; adjust for easier / harder sites.
A97: Miner order lead time | B97: months | C97: 2 | D97: Deposit paid ahead of commissioning.
A98: Miner deposit | B98: % of gross miner order | C98: 0.6 | D98: From attached supplier contract mechanics.
A99: Miner vendor-financed balance | B99: % of gross miner order | C99: 0.4 | D99: From attached supplier contract mechanics.
A100: Miner vendor finance tenor | B100: months | C100: 6 | D100: From attached supplier contract mechanics.
A101: Miner vendor finance interest | B101: % p.a. | C101: 0.06 | D101: Simple annual rate in attached supplier contract.
... A120: Container final payment | B120: % of gross container order | C120: 0.5 | D120: Editable cash timing assumption.

Sheet CAPEX_Electrical_Detail
A1: Detailed Electrical CAPEX Basis | Grootvlei Phase 1
A2: Exact Hamar T2603-24 electrical EPC quote packages are used as the cost basis; unpriced items are layered in as explicit editable adders.
A4: Package | B4: Unit | C4: 20MW basis (ZAR'000) | D4: Source / notes
A5: Preliminary & general costs | B5: ZAR'000 | C5: 7142.5 | D5: Exact Hamar summary sheet value.
A6: Engineering & design - engineering | B6: ZAR'000 | C6: 1449.2 | D6: Exact Hamar summary sheet value.
A7: Engineering & design - drafting / DO | B7: ZAR'000 | C7: 358.4 | D7: Exact Hamar summary sheet value.
A8: Main equipment package | B8: ZAR'000 | C8: 49215.7 | D8: Package includes essential board substation, 100kVA board, control room, RMUs, mini-subs, 100kVA transformer and busduct.
A9: Racking & accessories | B9: ZAR'000 | C9: 204.22016 | D9: Exact Hamar BOQ subtotal.
A10: Cabling | B10: ZAR'000 | C10: 28884.259 | D10: Exact Hamar BOQ subtotal.
A11: Cable terminations | B11: ZAR'000 | C11: 873.42903 | D11: Exact Hamar BOQ subtotal.
A12: Contingency | B12: ZAR'000 | C12: 2500 | D12: Exact Hamar summary sheet value.
A13: Quoted electrical EPC subtotal | C13: =SUM(C5:C12) | D13: Exact costed packages from the 25 March 2026 Hamar quotation.
A15: Unpriced / under-specified adders
A16: Harmonic mitigation allowance | B16: ZAR'000 | C16: =C13*Control!$C$91 | D16: Concept comments say harmonic mitigation is required but not allowed for in the preliminary offer.
A17: Lighting / small power allowance | B17: ZAR'000 | C17: =C13*Control!$C$92 | D17: Lighting line in quote is blank; editable allowance.
A18: Instrumentation / SCADA allowance | B18: ZAR'000 | C18: =C13*Control!$C$93 | D18: Instrumentation line in quote is blank; editable allowance.
A19: Earthing / lightning allowance | B19: ZAR'000 | C19: =C13*Control!$C$94 | D19: Concept basis requires earthing / lightning and wet/high-humidity suitability.
A20: Civil / drainage / fencing allowance | B20: ZAR'000 | C20: =C13*Control!$C$95 | D20: Brownfield electrical quote does not fully price all enabling works.
A21: Adders subtotal | C21: =SUM(C16:C20) | D21: All editable adders above.
A22: Brownfield similarity factor | B22: x | C22: =Control!$C$96 | D22: 1.00 = use Grootvlei basis; adjust if another site is easier or harder.
A23: All-in electrical EPC | 20MW | B23: ZAR'000 | C23: =(C13+C21)*C22 | D23: Exact quote subtotal plus adders, multiplied by the site similarity factor.
A26: Fixed/site cost | B26: ZAR'000/site | C26: =C23*Control!$C$90 | D26: Editable fixed/site share assumption applied to the all-in 20MW electrical EPC basis.
A27: Variable electrical EPC | B27: ZAR'000/MW | C27: =C23*(1-Control!$C$90)/20 | D27: Variable portion used to scale incremental MW.
A28: All-in electrical EPC | B28: ZAR'000/MW | C28: =C23/20 | D28: For reference only.
A30: Quoted scope composition / quantities
A31: Item | B31: Qty | C31: Unit | D31: Notes
A32: 3m containerised substation for essential board | B32: 1 | C32: ea | D32: Main equipment package
A33: 3m substation switchgear (100kVA board with feeders) | B33: 1 | C33: ea | D33: Main equipment package
A34: 6m containerised control room | B34: 1 | C34: ea | D34: Main equipment package
A35: Schneider RMU | B35: 3 | C35: ea | D35: Main equipment package
A36: 2MVA mini sub | B36: 20 | C36: ea | D36: Main equipment package
A37: 100kVA transformer | B37: 1 | C37: ea | D37: Main equipment package
A38: Busducting from transformer to container (20m) | B38: 12 | C38: ea | D38: Main equipment package
A39: 3c x 35mm² 6.6/11kV XLPE cable | B39: 150 | C39: m | D39: Cabling subtotal
A40: 1c x 150mm² 6.6/11kV XLPE cable | B40: 2100 | C40: m | D40: Cabling subtotal
A41: 1c x 500mm² 6.6/11kV XLPE cable | B41: 9000 | C41: m | D41: Cabling subtotal
A42: 1c x 70mm² G/Y insulated earth | B42: 11250 | C42: m | D42: Cabling subtotal
A43: 3c x 35mm² 6.6/11kV XLPE cable joint | B43: 2 | C43: joint | D43: Cable termination subtotal
... A45: 1c x 500mm² 6.6/11kV XLPE cable joint | B45: 18 | C45: joint | D45: Cable termination subtotal
A48: Scope boundary note | D48: Hamar email thread states the EPC scope includes all electrical works from the 6.6kV feeders to the 400V connection at the BitMach containers, including the essential section and the DX-issued metering scope.
A49: Design note | D49: The concept comments note that harmonic mitigation is required but was not allowed for in the preliminary offer pending detailed miner harmonic data.

Sheet 12M_Deployment
A1: 12-Month Phase 1 Deployment
A2: Edit only the blue MW schedule rows. Base case: Grootvlei ramps first, AMSA follows, and AMSA solar comes online during the ramp.
D3: 1 | E3: 2 | F3: 3 | G3: 4 | H3: 5 | I3: 6 | J3: 7 | K3: 8 | L3: 9 | M3: 10 | N3: 11 | O3: 12
D4: Jan-26 | E4: Feb-26 | F4: Mar-26 | G4: Apr-26 | H4: May-26 | I4: Jun-26 | J4: Jul-26 | K4: Aug-26 | L4: Sep-26 | M4: Oct-26 | N4: Nov-26 | O4: Dec-26
A5: Days in month | B5: days | D5: 31 | E5: 28 | F5: 31 | G5: 30 | H5: 31 | I5: 30 | J5: 31 | K5: 31 | L5: 30 | M5: 31 | N5: 30 | O5: 31
A7: Grootvlei closing MW | B7: MW | D7: 0 | E7: 0 | F7: 5 | G7: 10 | H7: 15 | I7: 15 | J7: 15 | K7: 15 | L7: 15 | M7: 15 | N7: 15 | O7: 15
A8: AMSA closing MW | B8: MW | D8: 0 | E8: 0 | F8: 0 | G8: 0 | H8: 0 | I8: 5 | J8: 5 | K8: 5 | L8: 5 | M8: 5 | N8: 5 | O8: 5
A9: AMSA solar closing MW | B9: MW | D9: 0 | E9: 0 | F9: 0 | G9: 0 | H9: 10 | I9: 10 | J9: 10 | K9: 10 | L9: 10 | M9: 10 | N9: 10 | O9: 10
A12: Grootvlei opening MW | B12: MW | D12: 0 | E12: =D7 | F12: =E7 | G12: =F7 | H12: =G7 | I12: =H7 | J12: =I7 | K12: =J7 | L12: =K7 | ... O12: =N7
A13: AMSA opening MW | B13: MW | D13: 0 | E13: =D8 | F13: =E8 | G13: =F8 | H13: =G8 | I13: =H8 | J13: =I8 | K13: =J8 | L13: =K8 | ... O13: =N8
A14: AMSA solar opening MW | B14: MW | D14: 0 | E14: =D9 | F14: =E9 | G14: =F9 | H14: =G9 | I14: =H9 | J14: =I9 | K14: =J9 | L14: =K9 | ... O14: =N9
A16: Grootvlei average MW | B16: MW | D16: =(D12+D7)/2 | E16: =(E12+E7)/2 | F16: =(F12+F7)/2 | G16: =(G12+G7)/2 | H16: =(H12+H7)/2 | I16: =(I12+I7)/2 | J16: =(J12+J7)/2 | K16: =(K12+K7)/2 | ... O16: =(O12+O7)/2
A17: AMSA average MW | B17: MW | D17: =(D13+D8)/2 | E17: =(E13+E8)/2 | F17: =(F13+F8)/2 | G17: =(G13+G8)/2 | H17: =(H13+H8)/2 | I17: =(I13+I8)/2 | J17: =(J13+J8)/2 | K17: =(K13+K8)/2 | ... O17: =(O13+O8)/2
A18: AMSA average solar MW | B18: MW | D18: =(D14+D9)/2 | E18: =(E14+E9)/2 | F18: =(F14+F9)/2 | G18: =(G14+G9)/2 | H18: =(H14+H9)/2 | I18: =(I14+I9)/2 | J18: =(J14+J9)/2 | K18: =(K14+K9)/2 | ... O18: =(O14+O9)/2
A19: Total average MW | B19: MW | D19: =D16+D17 | E19: =E16+E17 | F19: =F16+F17 | G19: =G16+G17 | H19: =H16+H17 | I19: =I16+I17 | J19: =J16+J17 | K19: =K16+K17 | ... O19: =O16+O17
A21: Grootvlei new MW | B21: MW | D21: =MAX(D7-D12,0) | E21: =MAX(E7-E12,0) | F21: =MAX(F7-F12,0) | G21: =MAX(G7-G12,0) | H21: =MAX(H7-H12,0) | I21: =MAX(I7-I12,0) | J21: =MAX(J7-J12,0) | K21: =MAX(K7-K12,0) | ... O21: =MAX(O7-O12,0)
A22: AMSA new MW | B22: MW | D22: =MAX(D8-D13,0) | E22: =MAX(E8-E13,0) | F22: =MAX(F8-F13,0) | G22: =MAX(G8-G13,0) | H22: =MAX(H8-H13,0) | I22: =MAX(I8-I13,0) | J22: =MAX(J8-J13,0) | K22: =MAX(K8-K13,0) | ... O22: =MAX(O8-O13,0)
A23: AMSA solar new MW | B23: MW | D23: =MAX(D9-D14,0) | E23: =MAX(E9-E14,0) | F23: =MAX(F9-F14,0) | G23: =MAX(G9-G14,0) | H23: =MAX(H9-H14,0) | I23: =MAX(I9-I14,0) | J23: =MAX(J9-J14,0) | K23: =MAX(K9-K14,0) | ... O23: =MAX(O9-O14,0)
A24: Total new MW | B24: MW | D24: =D21+D22 | E24: =E21+E22 | F24: =F21+F22 | G24: =G21+G22 | H24: =H21+H22 | I24: =I21+I22 | J24: =J21+J22 | K24: =K21+K22 | ... O24: =O21+O22
A26: Grootvlei active site | B26: flag | D26: =IF(D16>0,1,0) | E26: =IF(E16>0,1,0) | F26: =IF(F16>0,1,0) | G26: =IF(G16>0,1,0) | H26: =IF(H16>0,1,0) | I26: =IF(I16>0,1,0) | J26: =IF(J16>0,1,0) | K26: =IF(K16>0,1,0) | ... O26: =IF(O16>0,1,0)
A27: AMSA active site | B27: flag | D27: =IF(D17>0,1,0) | E27: =IF(E17>0,1,0) | F27: =IF(F17>0,1,0) | G27: =IF(G17>0,1,0) | H27: =IF(H17>0,1,0) | I27: =IF(I17>0,1,0) | J27: =IF(J17>0,1,0) | K27: =IF(K17>0,1,0) | ... O27: =IF(O17>0,1,0)
A28: Total active sites | B28: count | D28: =D26+D27 | E28: =E26+E27 | F28: =F26+F27 | G28: =G26+G27 | H28: =H26+H27 | I28: =I26+I27 | J28: =J26+J27 | K28: =K26+K27 | ... O28: =O26+O27
A30: Grootvlei site start | B30: flag | D30: =IF(D12=0,IF(D7>0,1,0),0) | E30: =IF(E12=0,IF(E7>0,1,0),0) | F30: =IF(F12=0,IF(F7>0,1,0),0) | G30: =IF(G12=0,IF(G7>0,1,0),0) | H30: =IF(H12=0,IF(H7>0,1,0),0) | I30: =IF(I12=0,IF(I7>0,1,0),0) | J30: =IF(J12=0,IF(J7>0,1,0),0) | K30: =IF(K12=0,IF(K7>0,1,0),0) | ... O30: =IF(O12=0,IF(O7>0,1,0),0)
A31: AMSA site start | B31: flag | D31: =IF(D13=0,IF(D8>0,1,0),0) | E31: =IF(E13=0,IF(E8>0,1,0),0) | F31: =IF(F13=0,IF(F8>0,1,0),0) | G31: =IF(G13=0,IF(G8>0,1,0),0) | H31: =IF(H13=0,IF(H8>0,1,0),0) | I31: =IF(I13=0,IF(I8>0,1,0),0) | J31: =IF(J13=0,IF(J8>0,1,0),0) | K31: =IF(K13=0,IF(K8>0,1,0),0) | ... O31: =IF(O13=0,IF(O8>0,1,0),0)
A32: Total site starts | B32: count | D32: =D30+D31 | E32: =E30+E31 | F32: =F30+F31 | G32: =G30+G31 | H32: =H30+H31 | I32: =I30+I31 | J32: =J30+J31 | K32: =K30+K31 | ... O32: =O30+O31
A34: Grootvlei closing containers | B34: containers | D34: =ROUNDUP(D7/Control!$C$37,0) | E34: =ROUNDUP(E7/Control!$C$37,0) | F34: =ROUNDUP(F7/Control!$C$37,0) | G34: =ROUNDUP(G7/Control!$C$37,0) | H34: =ROUNDUP(H7/Control!$C$37,0) | I34: =ROUNDUP(I7/Control!$C$37,0) | J34: =ROUNDUP(J7/Control!$C$37,0) | K34: =ROUNDUP(K7/Control!$C$37,0) | ... O34: =ROUNDUP(O7/Control!$C$37,0)
A35: AMSA closing containers | B35: containers | D35: =ROUNDUP(D8/Control!$C$37,0) | E35: =ROUNDUP(E8/Control!$C$37,0) | F35: =ROUNDUP(F8/Control!$C$37,0) | G35: =ROUNDUP(G8/Control!$C$37,0) | H35: =ROUNDUP(H8/Control!$C$37,0) | I35: =ROUNDUP(I8/Control!$C$37,0) | J35: =ROUNDUP(J8/Control!$C$37,0) | K35: =ROUNDUP(K8/Control!$C$37,0) | ... O35: =ROUNDUP(O8/Control!$C$37,0)
A36: Total closing containers | B36: containers | D36: =D34+D35 | E36: =E34+E35 | F36: =F34+F35 | G36: =G34+G35 | H36: =H34+H35 | I36: =I34+I35 | J36: =J34+J35 | K36: =K34+K35 | ... O36: =O34+O35
A38: Grootvlei opening containers | B38: containers | D38: 0 | E38: =D34 | F38: =E34 | G38: =F34 | H38: =G34 | I38: =H34 | J38: =I34 | K38: =J34 | L38: =K34 | ... O38: =N34
A39: AMSA opening containers | B39: containers | D39: 0 | E39: =D35 | F39: =E35 | G39: =F35 | H39: =G35 | I39: =H35 | J39: =I35 | K39: =J35 | L39: =K35 | ... O39: =N35
A40: Total opening containers | B40: containers | D40: =D38+D39 | E40: =E38+E39 | F40: =F38+F39 | G40: =G38+G39 | H40: =H38+H39 | I40: =I38+I39 | J40: =J38+J39 | K40: =K38+K39 | ... O40: =O38+O39
A42: Grootvlei new containers | B42: containers | D42: =MAX(D34-D38,0) | E42: =MAX(E34-E38,0) | F42: =MAX(F34-F38,0) | G42: =MAX(G34-G38,0) | H42: =MAX(H34-H38,0) | I42: =MAX(I34-I38,0) | J42: =MAX(J34-J38,0) | K42: =MAX(K34-K38,0) | ... O42: =MAX(O34-O38,0)
A43: AMSA new containers | B43: containers | D43: =MAX(D35-D39,0) | E43: =MAX(E35-E39,0) | F43: =MAX(F35-F39,0) | G43: =MAX(G35-G39,0) | H43: =MAX(H35-H39,0) | I43: =MAX(I35-I39,0) | J43: =MAX(J35-J39,0) | K43: =MAX(K35-K39,0) | ... O43: =MAX(O35-O39,0)
A44: Total new containers | B44: containers | D44: =D42+D43 | E44: =E42+E43 | F44: =F42+F43 | G44: =G42+G43 | H44: =H42+H43 | I44: =I42+I43 | J44: =J42+J43 | K44: =K42+K43 | ... O44: =O42+O43
A46: Grootvlei closing site FTE | B46: FTE | D46: =D26*Control!$C$54+D7*Control!$C$56+D7*Control!$C$58 | E46: =E26*Control!$C$54+E7*Control!$C$56+E7*Control!$C$58 | F46: =F26*Control!$C$54+F7*Control!$C$56+F7*Control!$C$58 | G46: =G26*Control!$C$54+G7*Control!$C$56+G7*Control!$C$58 | H46: =H26*Control!$C$54+H7*Control!$C$56+H7*Control!$C$58 | I46: =I26*Control!$C$54+I7*Control!$C$56+I7*Control!$C$58 | J46: =J26*Control!$C$54+J7*Control!$C$56+J7*Control!$C$58 | K46: =K26*Control!$C$54+K7*Control!$C$56+K7*Control!$C$58 | ... O46: =O26*Control!$C$54+O7*Control!$C$56+O7*Control!$C$58
A47: AMSA closing site FTE | B47: FTE | D47: =D27*Control!$C$54+D8*Control!$C$56+D8*Control!$C$58 | E47: =E27*Control!$C$54+E8*Control!$C$56+E8*Control!$C$58 | F47: =F27*Control!$C$54+F8*Control!$C$56+F8*Control!$C$58 | G47: =G27*Control!$C$54+G8*Control!$C$56+G8*Control!$C$58 | H47: =H27*Control!$C$54+H8*Control!$C$56+H8*Control!$C$58 | I47: =I27*Control!$C$54+I8*Control!$C$56+I8*Control!$C$58 | J47: =J27*Control!$C$54+J8*Control!$C$56+J8*Control!$C$58 | K47: =K27*Control!$C$54+K8*Control!$C$56+K8*Control!$C$58 | ... O47: =O27*Control!$C$54+O8*Control!$C$56+O8*Control!$C$58
A48: Total closing site FTE | B48: FTE | D48: =D46+D47 | E48: =E46+E47 | F48: =F46+F47 | G48: =G46+G47 | H48: =H46+H47 | I48: =I46+I47 | J48: =J46+J47 | K48: =K46+K47 | ... O48: =O46+O47
A49: Total closing FTE incl corporate | B49: FTE | D49: =D48+Control!$C$52 | E49: =E48+Control!$C$52 | F49: =F48+Control!$C$52 | G49: =G48+Control!$C$52 | H49: =H48+Control!$C$52 | I49: =I48+Control!$C$52 | J49: =J48+Control!$C$52 | K49: =K48+Control!$C$52 | ... O49: =O48+Control!$C$52
A51: Total opening FTE incl corporate | B51: FTE | D51: =Control!$C$52 | E51: =D49 | F51: =E49 | G51: =F49 | H51: =G49 | I51: =H49 | J51: =I49 | K51: =J49 | L51: =K49 | ... O51: =N49
A52: New FTE onboarded | B52: FTE | D52: =MAX(D49-D51,0) | E52: =MAX(E49-E51,0) | F52: =MAX(F49-F51,0) | G52: =MAX(G49-G51,0) | H52: =MAX(H49-H51,0) | I52: =MAX(I49-I51,0) | J52: =MAX(J49-J51,0) | K52: =MAX(K49-K51,0) | ... O52: =MAX(O49-O51,0)
A54: Grootvlei average miners | B54: miners | D54: =(D16/(1+Control!$C$34))*1000000/Control!$C$32 | E54: =(E16/(1+Control!$C$34))*1000000/Control!$C$32 | F54: =(F16/(1+Control!$C$34))*1000000/Control!$C$32 | G54: =(G16/(1+Control!$C$34))*1000000/Control!$C$32 | H54: =(H16/(1+Control!$C$34))*1000000/Control!$C$32 | I54: =(I16/(1+Control!$C$34))*1000000/Control!$C$32 | J54: =(J16/(1+Control!$C$34))*1000000/Control!$C$32 | K54: =(K16/(1+Control!$C$34))*1000000/Control!$C$32 | ... O54: =(O16/(1+Control!$C$34))*1000000/Control!$C$32
A55: AMSA average miners | B55: miners | D55: =(D17/(1+Control!$C$34))*1000000/Control!$C$32 | E55: =(E17/(1+Control!$C$34))*1000000/Control!$C$32 | F55: =(F17/(1+Control!$C$34))*1000000/Control!$C$32 | G55: =(G17/(1+Control!$C$34))*1000000/Control!$C$32 | H55: =(H17/(1+Control!$C$34))*1000000/Control!$C$32 | I55: =(I17/(1+Control!$C$34))*1000000/Control!$C$32 | J55: =(J17/(1+Control!$C$34))*1000000/Control!$C$32 | K55: =(K17/(1+Control!$C$34))*1000000/Control!$C$32 | ... O55: =(O17/(1+Control!$C$34))*1000000/Control!$C$32
A56: Total average miners | B56: miners | D56: =D54+D55 | E56: =E54+E55 | F56: =F54+F55 | G56: =G54+G55 | H56: =H54+H55 | I56: =I54+I55 | J56: =J54+J55 | K56: =K54+K55 | ... O56: =O54+O55
A58: Grootvlei effective hashrate | B58: TH/s | D58: =D54*Control!$C$30*(Control!$C$21/24)*Control!$C$14 | E58: =E54*Control!$C$30*(Control!$C$21/24)*Control!$C$14 | F58: =F54*Control!$C$30*(Control!$C$21/24)*Control!$C$14 | G58: =G54*Control!$C$30*(Control!$C$21/24)*Control!$C$14 | H58: =H54*Control!$C$30*(Control!$C$21/24)*Control!$C$14 | I58: =I54*Control!$C$30*(Control!$C$21/24)*Control!$C$14 | J58: =J54*Control!$C$30*(Control!$C$21/24)*Control!$C$14 | K58: =K54*Control!$C$30*(Control!$C$21/24)*Control!$C$14 | ... O58: =O54*Control!$C$30*(Control!$C$21/24)*Control!$C$14
A59: AMSA effective hashrate | B59: TH/s | D59: =D55*Control!$C$30*((Control!$C$22+Control!$C$23)/24)*Control!$C$14 | E59: =E55*Control!$C$30*((Control!$C$22+Control!$C$23)/24)*Control!$C$14 | F59: =F55*Control!$C$30*((Control!$C$22+Control!$C$23)/24)*Control!$C$14 | G59: =G55*Control!$C$30*((Control!$C$22+Control!$C$23)/24)*Control!$C$14 | H59: =H55*Control!$C$30*((Control!$C$22+Control!$C$23)/24)*Control!$C$14 | I59: =I55*Control!$C$30*((Control!$C$22+Control!$C$23)/24)*Control!$C$14 | J59: =J55*Control!$C$30*((Control!$C$22+Control!$C$23)/24)*Control!$C$14 | K59: =K55*Control!$C$30*((Control!$C$22+Control!$C$23)/24)*Control!$C$14 | ... O59: =O55*Control!$C$30*((Control!$C$22+Control!$C$23)/24)*Control!$C$14
A60: Total effective hashrate | B60: TH/s | D60: =D58+D59 | E60: =E58+E59 | F60: =F58+F59 | G60: =G58+G59 | H60: =H58+H59 | I60: =I58+I59 | J60: =J58+J59 | K60: =K58+K59 | ... O60: =O58+O59
A62: Grootvlei Eskom energy | B62: MWh | D62: =D16*Control!$C$21*D5*Control!$C$14 | E62: =E16*Control!$C$21*E5*Control!$C$14 | F62: =F16*Control!$C$21*F5*Control!$C$14 | G62: =G16*Control!$C$21*G5*Control!$C$14 | H62: =H16*Control!$C$21*H5*Control!$C$14 | I62: =I16*Control!$C$21*I5*Control!$C$14 | J62: =J16*Control!$C$21*J5*Control!$C$14 | K62: =K16*Control!$C$21*K5*Control!$C$14 | ... O62: =O16*Control!$C$21*O5*Control!$C$14
A63: AMSA total energy | B63: MWh | D63: =D17*(Control!$C$22+Control!$C$23)*D5*Control!$C$14 | E63: =E17*(Control!$C$22+Control!$C$23)*E5*Control!$C$14 | F63: =F17*(Control!$C$22+Control!$C$23)*F5*Control!$C$14 | G63: =G17*(Control!$C$22+Control!$C$23)*G5*Control!$C$14 | H63: =H17*(Control!$C$22+Control!$C$23)*H5*Control!$C$14 | I63: =I17*(Control!$C$22+Control!$C$23)*I5*Control!$C$14 | J63: =J17*(Control!$C$22+Control!$C$23)*J5*Control!$C$14 | K63: =K17*(Control!$C$22+Control!$C$23)*K5*Control!$C$14 | ... O63: =O17*(Control!$C$22+Control!$C$23)*O5*Control!$C$14
A64: AMSA solar energy used | B64: MWh | D64: =MIN(D17,D18)*Control!$C$23*D5*Control!$C$14 | E64: =MIN(E17,E18)*Control!$C$23*E5*Control!$C$14 | F64: =MIN(F17,F18)*Control!$C$23*F5*Control!$C$14 | G64: =MIN(G17,G18)*Control!$C$23*G5*Control!$C$14 | H64: =MIN(H17,H18)*Control!$C$23*H5*Control!$C$14 | I64: =MIN(I17,I18)*Control!$C$23*I5*Control!$C$14 | J64: =MIN(J17,J18)*Control!$C$23*J5*Control!$C$14 | K64: =MIN(K17,K18)*Control!$C$23*K5*Control!$C$14 | ... O64: =MIN(O17,O18)*Control!$C$23*O5*Control!$C$14
A65: AMSA Eskom energy | B65: MWh | D65: =D63-D64 | E65: =E63-E64 | F65: =F63-F64 | G65: =G63-G64 | H65: =H63-H64 | I65: =I63-I64 | J65: =J63-J64 | K65: =K63-K64 | ... O65: =O63-O64
A66: Total energy used | B66: MWh | D66: =D62+D63 | E66: =E62+E63 | F66: =F62+F63 | G66: =G62+G63 | H66: =H62+H63 | I66: =I62+I63 | J66: =J62+J63 | K66: =K62+K63 | ... O66: =O62+O63
A67: Total Eskom energy used | B67: MWh | D67: =D62+D65 | E67: =E62+E65 | F67: =F62+F65 | G67: =G62+G65 | H67: =H62+H65 | I67: =I62+I65 | J67: =J62+J65 | K67: =K62+K65 | ... O67: =O62+O65
A68: Total solar energy used | B68: MWh | D68: =D64 | E68: =E64 | F68: =F64 | G68: =G64 | H68: =H64 | I68: =I64 | J68: =J64 | K68: =K64 | ... O68: =O64

Sheet 12M_Revenue
A1: 12-Month Revenue Build
A2: BTC revenue is base case. Demand response and hyperscaler rows are built, but default to OFF in base case.
D3: 1 | E3: 2 | F3: 3 | G3: 4 | H3: 5 | I3: 6 | J3: 7 | K3: 8 | L3: 9 | M3: 10 | N3: 11 | O3: 12
D4: Jan-26 | E4: Feb-26 | F4: Mar-26 | G4: Apr-26 | H4: May-26 | I4: Jun-26 | J4: Jul-26 | K4: Aug-26 | L4: Sep-26 | M4: Oct-26 | N4: Nov-26 | O4: Dec-26
A5: BTC price (USD) | B5: USD/BTC | D5: =Control!$C$6 | E5: =D5*(1+Control!$C$7)^(1/12) | F5: =E5*(1+Control!$C$7)^(1/12) | G5: =F5*(1+Control!$C$7)^(1/12) | H5: =G5*(1+Control!$C$7)^(1/12) | I5: =H5*(1+Control!$C$7)^(1/12) | J5: =I5*(1+Control!$C$7)^(1/12) | K5: =J5*(1+Control!$C$7)^(1/12) | L5: =K5*(1+Control!$C$7)^(1/12) | ... O5: =N5*(1+Control!$C$7)^(1/12)
A6: BTC price (ZAR) | B6: ZAR/BTC | D6: =D5*Control!$C$4 | E6: =E5*Control!$C$4 | F6: =F5*Control!$C$4 | G6: =G5*Control!$C$4 | H6: =H5*Control!$C$4 | I6: =I5*Control!$C$4 | J6: =J5*Control!$C$4 | K6: =K5*Control!$C$4 | ... O6: =O5*Control!$C$4
A7: Network hash (TH/s) | B7: TH/s | D7: =Control!$C$8 | E7: =D7*(1+Control!$C$9)^(1/12) | F7: =E7*(1+Control!$C$9)^(1/12) | G7: =F7*(1+Control!$C$9)^(1/12) | H7: =G7*(1+Control!$C$9)^(1/12) | I7: =H7*(1+Control!$C$9)^(1/12) | J7: =I7*(1+Control!$C$9)^(1/12) | K7: =J7*(1+Control!$C$9)^(1/12) | L7: =K7*(1+Control!$C$9)^(1/12) | ... O7: =N7*(1+Control!$C$9)^(1/12)
A8: Network BTC mined | B8: BTC/month | D8: ='12M_Deployment'!D5*Control!$C$12*Control!$C$10*(1+Control!$C$11) | E8: ='12M_Deployment'!E5*Control!$C$12*Control!$C$10*(1+Control!$C$11) | F8: ='12M_Deployment'!F5*Control!$C$12*Control!$C$10*(1+Control!$C$11) | G8: ='12M_Deployment'!G5*Control!$C$12*Control!$C$10*(1+Control!$C$11) | H8: ='12M_Deployment'!H5*Control!$C$12*Control!$C$10*(1+Control!$C$11) | I8: ='12M_Deployment'!I5*Control!$C$12*Control!$C$10*(1+Control!$C$11) | J8: ='12M_Deployment'!J5*Control!$C$12*Control!$C$10*(1+Control!$C$11) | K8: ='12M_Deployment'!K5*Control!$C$12*Control!$C$10*(1+Control!$C$11) | ... O8: ='12M_Deployment'!O5*Control!$C$12*Control!$C$10*(1+Control!$C$11)
A10: Grootvlei BTC mined | B10: BTC/month | D10: ='12M_Deployment'!D58/D7*D8 | E10: ='12M_Deployment'!E58/E7*E8 | F10: ='12M_Deployment'!F58/F7*F8 | G10: ='12M_Deployment'!G58/G7*G8 | H10: ='12M_Deployment'!H58/H7*H8 | I10: ='12M_Deployment'!I58/I7*I8 | J10: ='12M_Deployment'!J58/J7*J8 | K10: ='12M_Deployment'!K58/K7*K8 | ... O10: ='12M_Deployment'!O58/O7*O8
A11: AMSA BTC mined | B11: BTC/month | D11: ='12M_Deployment'!D59/D7*D8 | E11: ='12M_Deployment'!E59/E7*E8 | F11: ='12M_Deployment'!F59/F7*F8 | G11: ='12M_Deployment'!G59/G7*G8 | H11: ='12M_Deployment'!H59/H7*H8 | I11: ='12M_Deployment'!I59/I7*I8 | J11: ='12M_Deployment'!J59/J7*J8 | K11: ='12M_Deployment'!K59/K7*K8 | ... O11: ='12M_Deployment'!O59/O7*O8
A12: Total BTC mined | B12: BTC/month | D12: =D10+D11 | E12: =E10+E11 | F12: =F10+F11 | G12: =G10+G11 | H12: =H10+H11 | I12: =I10+I11 | J12: =J10+J11 | K12: =K10+K11 | ... O12: =O10+O11
A13: BTC revenue | B13: ZAR'000 | D13: =D12*D6/1000 | E13: =E12*E6/1000 | F13: =F12*F6/1000 | G13: =G12*G6/1000 | H13: =H12*H6/1000 | I13: =I12*I6/1000 | J13: =J12*J6/1000 | K13: =K12*K6/1000 | ... O13: =O12*O6/1000
A15: Demand response revenue - base case | B15: ZAR'000 | D15: =IF(Control!$C$71=1,D16,0) | E15: =IF(Control!$C$71=1,E16,0) | F15: =IF(Control!$C$71=1,F16,0) | G15: =IF(Control!$C$71=1,G16,0) | H15: =IF(Control!$C$71=1,H16,0) | I15: =IF(Control!$C$71=1,I16,0) | J15: =IF(Control!$C$71=1,J16,0) | K15: =IF(Control!$C$71=1,K16,0) | ... O15: =IF(Control!$C$71=1,O16,0)
A16: Demand response revenue - upside | B16: ZAR'000 | D16: =IF(D$3>=Control!$C$72,'12M_Deployment'!D19*Control!$C$74*'12M_Deployment'!D5*Control!$C$75*Control!$C$73,0) | E16: =IF(E$3>=Control!$C$72,'12M_Deployment'!E19*Control!$C$74*'12M_Deployment'!E5*Control!$C$75*Control!$C$73,0) | F16: =IF(F$3>=Control!$C$72,'12M_Deployment'!F19*Control!$C$74*'12M_Deployment'!F5*Control!$C$75*Control!$C$73,0) | G16: =IF(G$3>=Control!$C$72,'12M_Deployment'!G19*Control!$C$74*'12M_Deployment'!G5*Control!$C$75*Control!$C$73,0) | H16: =IF(H$3>=Control!$C$72,'12M_Deployment'!H19*Control!$C$74*'12M_Deployment'!H5*Control!$C$75*Control!$C$73,0) | I16: =IF(I$3>=Control!$C$72,'12M_Deployment'!I19*Control!$C$74*'12M_Deployment'!I5*Control!$C$75*Control!$C$73,0) | J16: =IF(J$3>=Control!$C$72,'12M_Deployment'!J19*Control!$C$74*'12M_Deployment'!J5*Control!$C$75*Control!$C$73,0) | K16: =IF(K$3>=Control!$C$72,'12M_Deployment'!K19*Control!$C$74*'12M_Deployment'!K5*Control!$C$75*Control!$C$73,0) | ... O16: =IF(O$3>=Control!$C$72,'12M_Deployment'!O19*Control!$C$74*'12M_Deployment'!O5*Control!$C$75*Control!$C$73,0)
A18: Hyperscaler revenue - base case | B18: ZAR'000 | D18: =IF(Control!$C$76=1,D19,0) | E18: =IF(Control!$C$76=1,E19,0) | F18: =IF(Control!$C$76=1,F19,0) | G18: =IF(Control!$C$76=1,G19,0) | H18: =IF(Control!$C$76=1,H19,0) | I18: =IF(Control!$C$76=1,I19,0) | J18: =IF(Control!$C$76=1,J19,0) | K18: =IF(Control!$C$76=1,K19,0) | ... O18: =IF(Control!$C$76=1,O19,0)
A19: Hyperscaler revenue - upside | B19: ZAR'000 | D19: =IF(D$3>=Control!$C$77,Control!$C$78*Control!$C$79*'12M_Deployment'!D5*Control!$C$80*Control!$C$4/1000,0) | E19: =IF(E$3>=Control!$C$77,Control!$C$78*Control!$C$79*'12M_Deployment'!E5*Control!$C$80*Control!$C$4/1000,0) | F19: =IF(F$3>=Control!$C$77,Control!$C$78*Control!$C$79*'12M_Deployment'!F5*Control!$C$80*Control!$C$4/1000,0) | G19: =IF(G$3>=Control!$C$77,Control!$C$78*Control!$C$79*'12M_Deployment'!G5*Control!$C$80*Control!$C$4/1000,0) | H19: =IF(H$3>=Control!$C$77,Control!$C$78*Control!$C$79*'12M_Deployment'!H5*Control!$C$80*Control!$C$4/1000,0) | I19: =IF(I$3>=Control!$C$77,Control!$C$78*Control!$C$79*'12M_Deployment'!I5*Control!$C$80*Control!$C$4/1000,0) | J19: =IF(J$3>=Control!$C$77,Control!$C$78*Control!$C$79*'12M_Deployment'!J5*Control!$C$80*Control!$C$4/1000,0) | K19: =IF(K$3>=Control!$C$77,Control!$C$78*Control!$C$79*'12M_Deployment'!K5*Control!$C$80*Control!$C$4/1000,0) | ... O19: =IF(O$3>=Control!$C$77,Control!$C$78*Control!$C$79*'12M_Deployment'!O5*Control!$C$80*Control!$C$4/1000,0)
A21: Total revenue - base case | B21: ZAR'000 | D21: =D13+D15+D18 | E21: =E13+E15+E18 | F21: =F13+F15+F18 | G21: =G13+G15+G18 | H21: =H13+H15+H18 | I21: =I13+I15+I18 | J21: =J13+J15+J18 | K21: =K13+K15+K18 | ... O21: =O13+O15+O18
A22: Total revenue - with upside | B22: ZAR'000 | D22: =D13+D16+D19 | E22: =E13+E16+E19 | F22: =F13+F16+F19 | G22: =G13+G16+G19 | H22: =H13+H16+H19 | I22: =I13+I16+I19 | J22: =J13+J16+J19 | K22: =K13+K16+K19 | ... O22: =O13+O16+O19

Sheet 12M_Opex
A1: 12-Month Operating Cost Build
A2: Covers site energy cost, payroll, benefits, travel, software, legal, office, tools, security, insurance and utilities.
D3: 1 | E3: 2 | F3: 3 | G3: 4 | H3: 5 | I3: 6 | J3: 7 | K3: 8 | L3: 9 | M3: 10 | N3: 11 | O3: 12
D4: Jan-26 | E4: Feb-26 | F4: Mar-26 | G4: Apr-26 | H4: May-26 | I4: Jun-26 | J4: Jul-26 | K4: Aug-26 | L4: Sep-26 | M4: Oct-26 | N4: Nov-26 | O4: Dec-26
A5: Grootvlei electricity cost | B5: ZAR'000 | D5: ='12M_Deployment'!D62*Control!$C$25 | E5: ='12M_Deployment'!E62*Control!$C$25 | F5: ='12M_Deployment'!F62*Control!$C$25 | G5: ='12M_Deployment'!G62*Control!$C$25 | H5: ='12M_Deployment'!H62*Control!$C$25 | I5: ='12M_Deployment'!I62*Control!$C$25 | J5: ='12M_Deployment'!J62*Control!$C$25 | K5: ='12M_Deployment'!K62*Control!$C$25 | ... O5: ='12M_Deployment'!O62*Control!$C$25
A6: AMSA Eskom electricity cost | B6: ZAR'000 | D6: ='12M_Deployment'!D65*Control!$C$26 | E6: ='12M_Deployment'!E65*Control!$C$26 | F6: ='12M_Deployment'!F65*Control!$C$26 | G6: ='12M_Deployment'!G65*Control!$C$26 | H6: ='12M_Deployment'!H65*Control!$C$26 | I6: ='12M_Deployment'!I65*Control!$C$26 | J6: ='12M_Deployment'!J65*Control!$C$26 | K6: ='12M_Deployment'!K65*Control!$C$26 | ... O6: ='12M_Deployment'!O65*Control!$C$26
A7: AMSA solar O&M | B7: ZAR'000 | D7: ='12M_Deployment'!D18*Control!$C$27*Control!$C$28/12 | E7: ='12M_Deployment'!E18*Control!$C$27*Control!$C$28/12 | F7: ='12M_Deployment'!F18*Control!$C$27*Control!$C$28/12 | G7: ='12M_Deployment'!G18*Control!$C$27*Control!$C$28/12 | H7: ='12M_Deployment'!H18*Control!$C$27*Control!$C$28/12 | I7: ='12M_Deployment'!I18*Control!$C$27*Control!$C$28/12 | J7: ='12M_Deployment'!J18*Control!$C$27*Control!$C$28/12 | K7: ='12M_Deployment'!K18*Control!$C$27*Control!$C$28/12 | ... O7: ='12M_Deployment'!O18*Control!$C$27*Control!$C$28/12
A8: Total energy cost | B8: ZAR'000 | D8: =D5+D6+D7 | E8: =E5+E6+E7 | F8: =F5+F6+F7 | G8: =G5+G6+G7 | H8: =H5+H6+H7 | I8: =I5+I6+I7 | J8: =J5+J6+J7 | K8: =K5+K6+K7 | ... O8: =O5+O6+O7
A10: Corporate payroll | B10: ZAR'000 | D10: =Control!$C$52*Control!$C$53/12 | E10: =Control!$C$52*Control!$C$53/12 | F10: =Control!$C$52*Control!$C$53/12 | G10: =Control!$C$52*Control!$C$53/12 | H10: =Control!$C$52*Control!$C$53/12 | I10: =Control!$C$52*Control!$C$53/12 | J10: =Control!$C$52*Control!$C$53/12 | K10: =Control!$C$52*Control!$C$53/12 | ... O10: =Control!$C$52*Control!$C$53/12
A11: Site management payroll | B11: ZAR'000 | D11: ='12M_Deployment'!D28*Control!$C$54*Control!$C$55/12 | E11: ='12M_Deployment'!E28*Control!$C$54*Control!$C$55/12 | F11: ='12M_Deployment'!F28*Control!$C$54*Control!$C$55/12 | G11: ='12M_Deployment'!G28*Control!$C$54*Control!$C$55/12 | H11: ='12M_Deployment'!H28*Control!$C$54*Control!$C$55/12 | I11: ='12M_Deployment'!I28*Control!$C$54*Control!$C$55/12 | J11: ='12M_Deployment'!J28*Control!$C$54*Control!$C$55/12 | K11: ='12M_Deployment'!K28*Control!$C$54*Control!$C$55/12 | ... O11: ='12M_Deployment'!O28*Control!$C$54*Control!$C$55/12
A12: Technician payroll | B12: ZAR'000 | D12: ='12M_Deployment'!D19*Control!$C$56*Control!$C$57/12 | E12: ='12M_Deployment'!E19*Control!$C$56*Control!$C$57/12 | F12: ='12M_Deployment'!F19*Control!$C$56*Control!$C$57/12 | G12: ='12M_Deployment'!G19*Control!$C$56*Control!$C$57/12 | H12: ='12M_Deployment'!H19*Control!$C$56*Control!$C$57/12 | I12: ='12M_Deployment'!I19*Control!$C$56*Control!$C$57/12 | J12: ='12M_Deployment'!J19*Control!$C$56*Control!$C$57/12 | K12: ='12M_Deployment'!K19*Control!$C$56*Control!$C$57/12 | ... O12: ='12M_Deployment'!O19*Control!$C$56*Control!$C$57/12
A13: Electrician payroll | B13: ZAR'000 | D13: ='12M_Deployment'!D19*Control!$C$58*Control!$C$59/12 | E13: ='12M_Deployment'!E19*Control!$C$58*Control!$C$59/12 | F13: ='12M_Deployment'!F19*Control!$C$58*Control!$C$59/12 | G13: ='12M_Deployment'!G19*Control!$C$58*Control!$C$59/12 | H13: ='12M_Deployment'!H19*Control!$C$58*Control!$C$59/12 | I13: ='12M_Deployment'!I19*Control!$C$58*Control!$C$59/12 | J13: ='12M_Deployment'!J19*Control!$C$58*Control!$C$59/12 | K13: ='12M_Deployment'!K19*Control!$C$58*Control!$C$59/12 | ... O13: ='12M_Deployment'!O19*Control!$C$58*Control!$C$59/12
A14: Gross payroll | B14: ZAR'000 | D14: =SUM(D10:D13) | E14: =SUM(E10:E13) | F14: =SUM(F10:F13) | G14: =SUM(G10:G13) | H14: =SUM(H10:H13) | I14: =SUM(I10:I13) | J14: =SUM(J10:J13) | K14: =SUM(K10:K13) | ... O14: =SUM(O10:O13)
A15: Benefits | B15: ZAR'000 | D15: =D14*Control!$C$60 | E15: =E14*Control!$C$60 | F15: =F14*Control!$C$60 | G15: =G14*Control!$C$60 | H15: =H14*Control!$C$60 | I15: =I14*Control!$C$60 | J15: =J14*Control!$C$60 | K15: =K14*Control!$C$60 | ... O15: =O14*Control!$C$60
A16: Salaries & benefits | B16: ZAR'000 | D16: =D14+D15 | E16: =E14+E15 | F16: =F14+F15 | G16: =G14+G15 | H16: =H14+H15 | I16: =I14+I15 | J16: =J14+J15 | K16: =K14+K15 | ... O16: =O14+O15
A17: Travel / accommodation | B17: ZAR'000 | D17: =D14*Control!$C$61+'12M_Deployment'!D32*Control!$C$62 | E17: =E14*Control!$C$61+'12M_Deployment'!E32*Control!$C$62 | F17: =F14*Control!$C$61+'12M_Deployment'!F32*Control!$C$62 | G17: =G14*Control!$C$61+'12M_Deployment'!G32*Control!$C$62 | H17: =H14*Control!$C$61+'12M_Deployment'!H32*Control!$C$62 | I17: =I14*Control!$C$61+'12M_Deployment'!I32*Control!$C$62 | J17: =J14*Control!$C$61+'12M_Deployment'!J32*Control!$C$62 | K17: =K14*Control!$C$61+'12M_Deployment'!K32*Control!$C$62 | ... O17: =O14*Control!$C$61+'12M_Deployment'!O32*Control!$C$62
A18: Software / storage / monitoring | B18: ZAR'000 | D18: ='12M_Deployment'!D49*Control!$C$63+'12M_Deployment'!D28*Control!$C$64+Control!$C$67 | E18: ='12M_Deployment'!E49*Control!$C$63+'12M_Deployment'!E28*Control!$C$64+Control!$C$67 | F18: ='12M_Deployment'!F49*Control!$C$63+'12M_Deployment'!F28*Control!$C$64+Control!$C$67 | G18: ='12M_Deployment'!G49*Control!$C$63+'12M_Deployment'!G28*Control!$C$64+Control!$C$67 | H18: ='12M_Deployment'!H49*Control!$C$63+'12M_Deployment'!H28*Control!$C$64+Control!$C$67 | I18: ='12M_Deployment'!I49*Control!$C$63+'12M_Deployment'!I28*Control!$C$64+Control!$C$67 | J18: ='12M_Deployment'!J49*Control!$C$63+'12M_Deployment'!J28*Control!$C$64+Control!$C$67 | K18: ='12M_Deployment'!K49*Control!$C$63+'12M_Deployment'!K28*Control!$C$64+Control!$C$67 | ... O18: ='12M_Deployment'!O49*Control!$C$63+'12M_Deployment'!O28*Control!$C$64+Control!$C$67
A19: Legal fees | B19: ZAR'000 | D19: =Control!$C$65 | E19: =Control!$C$65 | F19: =Control!$C$65 | G19: =Control!$C$65 | H19: =Control!$C$65 | I19: =Control!$C$65 | J19: =Control!$C$65 | K19: =Control!$C$65 | ... O19: =Control!$C$65
A20: Office rent | B20: ZAR'000 | D20: =Control!$C$66 | E20: =Control!$C$66 | F20: =Control!$C$66 | G20: =Control!$C$66 | H20: =Control!$C$66 | I20: =Control!$C$66 | J20: =Control!$C$66 | K20: =Control!$C$66 | ... O20: =Control!$C$66
A21: Tools / consumables recurring | B21: ZAR'000 | D21: ='12M_Deployment'!D19*Control!$C$68 | E21: ='12M_Deployment'!E19*Control!$C$68 | F21: ='12M_Deployment'!F19*Control!$C$68 | G21: ='12M_Deployment'!G19*Control!$C$68 | H21: ='12M_Deployment'!H19*Control!$C$68 | I21: ='12M_Deployment'!I19*Control!$C$68 | J21: ='12M_Deployment'!J19*Control!$C$68 | K21: ='12M_Deployment'!K19*Control!$C$68 | ... O21: ='12M_Deployment'!O19*Control!$C$68
A22: Security & operating insurance | B22: ZAR'000 | D22: ='12M_Deployment'!D28*Control!$C$69 | E22: ='12M_Deployment'!E28*Control!$C$69 | F22: ='12M_Deployment'!F28*Control!$C$69 | G22: ='12M_Deployment'!G28*Control!$C$69 | H22: ='12M_Deployment'!H28*Control!$C$69 | I22: ='12M_Deployment'!I28*Control!$C$69 | J22: ='12M_Deployment'!J28*Control!$C$69 | K22: ='12M_Deployment'!K28*Control!$C$69 | ... O22: ='12M_Deployment'!O28*Control!$C$69
A23: Other utilities / water | B23: ZAR'000 | D23: ='12M_Deployment'!D19*Control!$C$70 | E23: ='12M_Deployment'!E19*Control!$C$70 | F23: ='12M_Deployment'!F19*Control!$C$70 | G23: ='12M_Deployment'!G19*Control!$C$70 | H23: ='12M_Deployment'!H19*Control!$C$70 | I23: ='12M_Deployment'!I19*Control!$C$70 | J23: ='12M_Deployment'!J19*Control!$C$70 | K23: ='12M_Deployment'!K19*Control!$C$70 | ... O23: ='12M_Deployment'!O19*Control!$C$70
A24: Total cash opex | B24: ZAR'000 | D24: =SUM(D8,D16:D23) | E24: =SUM(E8,E16:E23) | F24: =SUM(F8,F16:F23) | G24: =SUM(G8,G16:G23) | H24: =SUM(H8,H16:H23) | I24: =SUM(I8,I16:I23) | J24: =SUM(J8,J16:J23) | K24: =SUM(K8,K16:K23) | ... O24: =SUM(O8,O16:O23)
A25: EBITDA - base case | B25: ZAR'000 | D25: ='12M_Revenue'!D21-D24 | E25: ='12M_Revenue'!E21-E24 | F25: ='12M_Revenue'!F21-F24 | G25: ='12M_Revenue'!G21-G24 | H25: ='12M_Revenue'!H21-H24 | I25: ='12M_Revenue'!I21-I24 | J25: ='12M_Revenue'!J21-J24 | K25: ='12M_Revenue'!K21-K24 | ... O25: ='12M_Revenue'!O21-O24
A26: EBITDA - with upside | B26: ZAR'000 | D26: ='12M_Revenue'!D22-D24 | E26: ='12M_Revenue'!E22-E24 | F26: ='12M_Revenue'!F22-F24 | G26: ='12M_Revenue'!G22-G24 | H26: ='12M_Revenue'!H22-H24 | I26: ='12M_Revenue'!I22-I24 | J26: ='12M_Revenue'!J22-J24 | K26: ='12M_Revenue'!K22-K24 | ... O26: ='12M_Revenue'!O22-O24

Sheet 12M_Capex
A1: 12-Month Capex & Deployment Spend
A2: This sheet now pulls detailed electrical EPC and miner vendor finance logic from dedicated tabs. Edit a few assumptions in Control and the full cash-timing logic updates.
D3: 1 | E3: 2 | F3: 3 | G3: 4 | H3: 5 | I3: 6 | J3: 7 | K3: 8 | L3: 9 | M3: 10 | N3: 11 | O3: 12
D4: Jan-26 | E4: Feb-26 | F4: Mar-26 | G4: Apr-26 | H4: May-26 | I4: Jun-26 | J4: Jul-26 | K4: Aug-26 | L4: Sep-26 | M4: Oct-26 | N4: Nov-26 | O4: Dec-26
A5: New MW commissioned | B5: MW | D5: ='12M_Deployment'!D24 | E5: ='12M_Deployment'!E24 | F5: ='12M_Deployment'!F24 | G5: ='12M_Deployment'!G24 | H5: ='12M_Deployment'!H24 | I5: ='12M_Deployment'!I24 | J5: ='12M_Deployment'!J24 | K5: ='12M_Deployment'!K24 | ... O5: ='12M_Deployment'!O24
A6: New containers commissioned | B6: containers | D6: ='12M_Deployment'!D44 | E6: ='12M_Deployment'!E44 | F6: ='12M_Deployment'!F44 | G6: ='12M_Deployment'!G44 | H6: ='12M_Deployment'!H44 | I6: ='12M_Deployment'!I44 | J6: ='12M_Deployment'!J44 | K6: ='12M_Deployment'!K44 | ... O6: ='12M_Deployment'!O44
A7: New solar MW | B7: MW | D7: ='12M_Deployment'!D23 | E7: ='12M_Deployment'!E23 | F7: ='12M_Deployment'!F23 | G7: ='12M_Deployment'!G23 | H7: ='12M_Deployment'!H23 | I7: ='12M_Deployment'!I23 | J7: ='12M_Deployment'!J23 | K7: ='12M_Deployment'!K23 | ... O7: ='12M_Deployment'!O23
A8: New FTE onboarded | B8: FTE | D8: ='12M_Deployment'!D52 | E8: ='12M_Deployment'!E52 | F8: ='12M_Deployment'!F52 | G8: ='12M_Deployment'!G52 | H8: ='12M_Deployment'!H52 | I8: ='12M_Deployment'!I52 | J8: ='12M_Deployment'!J52 | K8: ='12M_Deployment'!K52 | ... O8: ='12M_Deployment'!O52
A10: ASIC hardware capex basis | B10: ZAR'000 | D10: =('12M_Deployment'!D24/(1+Control!$C$34))*1000000/Control!$C$32*Control!$C$33*Control!$C$4/1000 | E10: =('12M_Deployment'!E24/(1+Control!$C$34))*1000000/Control!$C$32*Control!$C$33*Control!$C$4/1000 | F10: =('12M_Deployment'!F24/(1+Control!$C$34))*1000000/Control!$C$32*Control!$C$33*Control!$C$4/1000 | G10: =('12M_Deployment'!G24/(1+Control!$C$34))*1000000/Control!$C$32*Control!$C$33*Control!$C$4/1000 | H10: =('12M_Deployment'!H24/(1+Control!$C$34))*1000000/Control!$C$32*Control!$C$33*Control!$C$4/1000 | I10: =('12M_Deployment'!I24/(1+Control!$C$34))*1000000/Control!$C$32*Control!$C$33*Control!$C$4/1000 | J10: =('12M_Deployment'!J24/(1+Control!$C$34))*1000000/Control!$C$32*Control!$C$33*Control!$C$4/1000 | K10: =('12M_Deployment'!K24/(1+Control!$C$34))*1000000/Control!$C$32*Control!$C$33*Control!$C$4/1000 | ... O10: =('12M_Deployment'!O24/(1+Control!$C$34))*1000000/Control!$C$32*Control!$C$33*Control!$C$4/1000
A11: Hydro container capex basis | B11: ZAR'000 | D11: ='12M_Deployment'!D44*Control!$C$36*Control!$C$4/1000 | E11: ='12M_Deployment'!E44*Control!$C$36*Control!$C$4/1000 | F11: ='12M_Deployment'!F44*Control!$C$36*Control!$C$4/1000 | G11: ='12M_Deployment'!G44*Control!$C$36*Control!$C$4/1000 | H11: ='12M_Deployment'!H44*Control!$C$36*Control!$C$4/1000 | I11: ='12M_Deployment'!I44*Control!$C$36*Control!$C$4/1000 | J11: ='12M_Deployment'!J44*Control!$C$36*Control!$C$4/1000 | K11: ='12M_Deployment'!K44*Control!$C$36*Control!$C$4/1000 | ... O11: ='12M_Deployment'!O44*Control!$C$36*Control!$C$4/1000
A12: Electrical EPC basis (fixed/site + variable/MW) | B12: ZAR'000 | D12: ='12M_Deployment'!D32*CAPEX_Electrical_Detail!$C$26+'12M_Deployment'!D24*CAPEX_Electrical_Detail!$C$27 | E12: ='12M_Deployment'!E32*CAPEX_Electrical_Detail!$C$26+'12M_Deployment'!E24*CAPEX_Electrical_Detail!$C$27 | F12: ='12M_Deployment'!F32*CAPEX_Electrical_Detail!$C$26+'12M_Deployment'!F24*CAPEX_Electrical_Detail!$C$27 | G12: ='12M_Deployment'!G32*CAPEX_Electrical_Detail!$C$26+'12M_Deployment'!G24*CAPEX_Electrical_Detail!$C$27 | H12: ='12M_Deployment'!H32*CAPEX_Electrical_Detail!$C$26+'12M_Deployment'!H24*CAPEX_Electrical_Detail!$C$27 | I12: ='12M_Deployment'!I32*CAPEX_Electrical_Detail!$C$26+'12M_Deployment'!I24*CAPEX_Electrical_Detail!$C$27 | J12: ='12M_Deployment'!J32*CAPEX_Electrical_Detail!$C$26+'12M_Deployment'!J24*CAPEX_Electrical_Detail!$C$27 | K12: ='12M_Deployment'!K32*CAPEX_Electrical_Detail!$C$26+'12M_Deployment'!K24*CAPEX_Electrical_Detail!$C$27 | ... O12: ='12M_Deployment'!O32*CAPEX_Electrical_Detail!$C$26+'12M_Deployment'!O24*CAPEX_Electrical_Detail!$C$27
A13: Solar PV capex basis | B13: ZAR'000 | D13: ='12M_Deployment'!D23*Control!$C$27 | E13: ='12M_Deployment'!E23*Control!$C$27 | F13: ='12M_Deployment'!F23*Control!$C$27 | G13: ='12M_Deployment'!G23*Control!$C$27 | H13: ='12M_Deployment'!H23*Control!$C$27 | I13: ='12M_Deployment'!I23*Control!$C$27 | J13: ='12M_Deployment'!J23*Control!$C$27 | K13: ='12M_Deployment'!K23*Control!$C$27 | ... O13: ='12M_Deployment'!O23*Control!$C$27
A14: Initial spare parts basis | B14: ZAR'000 | D14: =D10*Control!$C$46 | E14: =E10*Control!$C$46 | F14: =F10*Control!$C$46 | G14: =G10*Control!$C$46 | H14: =H10*Control!$C$46 | I14: =I10*Control!$C$46 | J14: =J10*Control!$C$46 | K14: =K10*Control!$C$46 | ... O14: =O10*Control!$C$46
A15: Tools/equipment initial basis | B15: ZAR'000 | D15: ='12M_Deployment'!D32*Control!$C$47 | E15: ='12M_Deployment'!E32*Control!$C$47 | F15: ='12M_Deployment'!F32*Control!$C$47 | G15: ='12M_Deployment'!G32*Control!$C$47 | H15: ='12M_Deployment'!H32*Control!$C$47 | I15: ='12M_Deployment'!I32*Control!$C$47 | J15: ='12M_Deployment'!J32*Control!$C$47 | K15: ='12M_Deployment'!K32*Control!$C$47 | ... O15: ='12M_Deployment'!O32*Control!$C$47
A16: Staff hardware basis | B16: ZAR'000 | D16: ='12M_Deployment'!D52*Control!$C$51 | E16: ='12M_Deployment'!E52*Control!$C$51 | F16: ='12M_Deployment'!F52*Control!$C$51 | G16: ='12M_Deployment'!G52*Control!$C$51 | H16: ='12M_Deployment'!H52*Control!$C$51 | I16: ='12M_Deployment'!I52*Control!$C$51 | J16: ='12M_Deployment'!J52*Control!$C$51 | K16: ='12M_Deployment'!K52*Control!$C$51 | ... O16: ='12M_Deployment'!O52*Control!$C$51
A17: Freight basis | B17: ZAR'000 | D17: ='12M_Deployment'!D44*Control!$C$40*Control!$C$4/1000 | E17: ='12M_Deployment'!E44*Control!$C$40*Control!$C$4/1000 | F17: ='12M_Deployment'!F44*Control!$C$40*Control!$C$4/1000 | G17: ='12M_Deployment'!G44*Control!$C$40*Control!$C$4/1000 | H17: ='12M_Deployment'!H44*Control!$C$40*Control!$C$4/1000 | I17: ='12M_Deployment'!I44*Control!$C$40*Control!$C$4/1000 | J17: ='12M_Deployment'!J44*Control!$C$40*Control!$C$4/1000 | K17: ='12M_Deployment'!K44*Control!$C$40*Control!$C$4/1000 | ... O17: ='12M_Deployment'!O44*Control!$C$40*Control!$C$4/1000
A18: Port/clearing basis | B18: ZAR'000 | D18: ='12M_Deployment'!D44*Control!$C$41 | E18: ='12M_Deployment'!E44*Control!$C$41 | F18: ='12M_Deployment'!F44*Control!$C$41 | G18: ='12M_Deployment'!G44*Control!$C$41 | H18: ='12M_Deployment'!H44*Control!$C$41 | I18: ='12M_Deployment'!I44*Control!$C$41 | J18: ='12M_Deployment'!J44*Control!$C$41 | K18: ='12M_Deployment'!K44*Control!$C$41 | ... O18: ='12M_Deployment'!O44*Control!$C$41
A19: Inland trucking basis | B19: ZAR'000 | D19: ='12M_Deployment'!D44*Control!$C$42 | E19: ='12M_Deployment'!E44*Control!$C$42 | F19: ='12M_Deployment'!F44*Control!$C$42 | G19: ='12M_Deployment'!G44*Control!$C$42 | H19: ='12M_Deployment'!H44*Control!$C$42 | I19: ='12M_Deployment'!I44*Control!$C$42 | J19: ='12M_Deployment'!J44*Control!$C$42 | K19: ='12M_Deployment'!K44*Control!$C$42 | ... O19: ='12M_Deployment'!O44*Control!$C$42
A20: Crane/rigging basis | B20: ZAR'000 | D20: ='12M_Deployment'!D44*Control!$C$43 | E20: ='12M_Deployment'!E44*Control!$C$43 | F20: ='12M_Deployment'!F44*Control!$C$43 | G20: ='12M_Deployment'!G44*Control!$C$43 | H20: ='12M_Deployment'!H44*Control!$C$43 | I20: ='12M_Deployment'!I44*Control!$C$43 | J20: ='12M_Deployment'!J44*Control!$C$43 | K20: ='12M_Deployment'!K44*Control!$C$43 | ... O20: ='12M_Deployment'!O44*Control!$C$43
A21: Cargo insurance basis | B21: ZAR'000 | D21: =(D10+D11)*Control!$C$44 | E21: =(E10+E11)*Control!$C$44 | F21: =(F10+F11)*Control!$C$44 | G21: =(G10+G11)*Control!$C$44 | H21: =(H10+H11)*Control!$C$44 | I21: =(I10+I11)*Control!$C$44 | J21: =(J10+J11)*Control!$C$44 | K21: =(K10+K11)*Control!$C$44 | ... O21: =(O10+O11)*Control!$C$44
A22: Import duty basis | B22: ZAR'000 | D22: =(D10+D11)*Control!$C$45 | E22: =(E10+E11)*Control!$C$45 | F22: =(F10+F11)*Control!$C$45 | G22: =(G10+G11)*Control!$C$45 | H22: =(H10+H11)*Control!$C$45 | I22: =(I10+I11)*Control!$C$45 | J22: =(J10+J11)*Control!$C$45 | K22: =(K10+K11)*Control!$C$45 | ... O22: =(O10+O11)*Control!$C$45
A23: Office/software/legal setup basis | B23: ZAR'000 | D23: =IF(D$3=1,Control!$C$48+Control!$C$49+Control!$C$50,0) | E23: =IF(E$3=1,Control!$C$48+Control!$C$49+Control!$C$50,0) | F23: =IF(F$3=1,Control!$C$48+Control!$C$49+Control!$C$50,0) | G23: =IF(G$3=1,Control!$C$48+Control!$C$49+Control!$C$50,0) | H23: =IF(H$3=1,Control!$C$48+Control!$C$49+Control!$C$50,0) | I23: =IF(I$3=1,Control!$C$48+Control!$C$49+Control!$C$50,0) | J23: =IF(J$3=1,Control!$C$48+Control!$C$49+Control!$C$50,0) | K23: =IF(K$3=1,Control!$C$48+Control!$C$49+Control!$C$50,0) | ... O23: =IF(O$3=1,Control!$C$48+Control!$C$49+Control!$C$50,0)
A26: ASIC hardware cash spend (deposit + vendor installments) | B26: ZAR'000 | D26: ='12M_Miner_Vendor'!D14 | E26: ='12M_Miner_Vendor'!E14 | F26: ='12M_Miner_Vendor'!F14 | G26: ='12M_Miner_Vendor'!G14 | H26: ='12M_Miner_Vendor'!H14 | I26: ='12M_Miner_Vendor'!I14 | J26: ='12M_Miner_Vendor'!J14 | K26: ='12M_Miner_Vendor'!K14 | ... O26: ='12M_Miner_Vendor'!O14
A27: Hydro container cash spend (editable staged terms) | B27: ZAR'000 | D27: =IFERROR(OFFSET(D11,0,Control!$C$117)*Control!$C$118,0)+IF(Control!$C$117>0,IFERROR(OFFSET(D11,0,Control!$C$117-1)*Control!$C$119,0),0)+D11*Control!$C$120 | E27: =IFERROR(OFFSET(E11,0,Control!$C$117)*Control!$C$118,0)+IF(Control!$C$117>0,IFERROR(OFFSET(E11,0,Control!$C$117-1)*Control!$C$119,0),0)+E11*Control!$C$120 | F27: =IFERROR(OFFSET(F11,0,Control!$C$117)*Control!$C$118,0)+IF(Control!$C$117>0,IFERROR(OFFSET(F11,0,Control!$C$117-1)*Control!$C$119,0),0)+F11*Control!$C$120 | G27: =IFERROR(OFFSET(G11,0,Control!$C$117)*Control!$C$118,0)+IF(Control!$C$117>0,IFERROR(OFFSET(G11,0,Control!$C$117-1)*Control!$C$119,0),0)+G11*Control!$C$120 | H27: =IFERROR(OFFSET(H11,0,Control!$C$117)*Control!$C$118,0)+IF(Control!$C$117>0,IFERROR(OFFSET(H11,0,Control!$C$117-1)*Control!$C$119,0),0)+H11*Control!$C$120 | I27: =IFERROR(OFFSET(I11,0,Control!$C$117)*Control!$C$118,0)+IF(Control!$C$117>0,IFERROR(OFFSET(I11,0,Control!$C$117-1)*Control!$C$119,0),0)+I11*Control!$C$120 | J27: =IFERROR(OFFSET(J11,0,Control!$C$117)*Control!$C$118,0)+IF(Control!$C$117>0,IFERROR(OFFSET(J11,0,Control!$C$117-1)*Control!$C$119,0),0)+J11*Control!$C$120 | K27: =IFERROR(OFFSET(K11,0,Control!$C$117)*Control!$C$118,0)+IF(Control!$C$117>0,IFERROR(OFFSET(K11,0,Control!$C$117-1)*Control!$C$119,0),0)+K11*Control!$C$120 | ... O27: =IFERROR(OFFSET(O11,0,Control!$C$117)*Control!$C$118,0)+IF(Control!$C$117>0,IFERROR(OFFSET(O11,0,Control!$C$117-1)*Control!$C$119,0),0)+O11*Control!$C$120
A28: Electrical EPC cash spend (tranches + financed retention) | B28: ZAR'000 | D28: ='12M_EPC_Tranches'!D14 | E28: ='12M_EPC_Tranches'!E14 | F28: ='12M_EPC_Tranches'!F14 | G28: ='12M_EPC_Tranches'!G14 | H28: ='12M_EPC_Tranches'!H14 | I28: ='12M_EPC_Tranches'!I14 | J28: ='12M_EPC_Tranches'!J14 | K28: ='12M_EPC_Tranches'!K14 | ... O28: ='12M_EPC_Tranches'!O14
A29: Solar PV cash spend | B29: ZAR'000 | D29: =0.2*F13+0.5*E13+0.3*D13 | E29: =0.2*G13+0.5*F13+0.3*E13 | F29: =0.2*H13+0.5*G13+0.3*F13 | G29: =0.2*I13+0.5*H13+0.3*G13 | H29: =0.2*J13+0.5*I13+0.3*H13 | I29: =0.2*K13+0.5*J13+0.3*I13 | J29: =0.2*L13+0.5*K13+0.3*J13 | K29: =0.2*M13+0.5*L13+0.3*K13 | ... M29: =0.2*O13+0.5*N13+0.3*M13 | N29: =0.5*O13+0.3*N13 | O29: =0.3*O13
A30: Initial spare parts cash spend | B30: ZAR'000 | D30: =D14 | E30: =E14 | F30: =F14 | G30: =G14 | H30: =H14 | I30: =I14 | J30: =J14 | K30: =K14 | ... O30: =O14
A31: Tools/equipment initial cash spend | B31: ZAR'000 | D31: =D15 | E31: =E15 | F31: =F15 | G31: =G15 | H31: =H15 | I31: =I15 | J31: =J15 | K31: =K15 | ... O31: =O15
A32: Staff hardware cash spend | B32: ZAR'000 | D32: =D16 | E32: =E16 | F32: =F16 | G32: =G16 | H32: =H16 | I32: =I16 | J32: =J16 | K32: =K16 | ... O32: =O16
A33: Freight cash spend | B33: ZAR'000 | D33: =E17 | E33: =F17 | F33: =G17 | G33: =H17 | H33: =I17 | I33: =J17 | J33: =K17 | K33: =L17 | ... N33: =O17 | O33: 0
A34: Port/clearing cash spend | B34: ZAR'000 | D34: =E18 | E34: =F18 | F34: =G18 | G34: =H18 | H34: =I18 | I34: =J18 | J34: =K18 | K34: =L18 | ... N34: =O18 | O34: 0
A35: Inland trucking cash spend | B35: ZAR'000 | D35: =E19 | E35: =F19 | F35: =G19 | G35: =H19 | H35: =I19 | I35: =J19 | J35: =K19 | K35: =L19 | ... N35: =O19 | O35: 0
A36: Crane/rigging cash spend | B36: ZAR'000 | D36: =D20 | E36: =E20 | F36: =F20 | G36: =G20 | H36: =H20 | I36: =I20 | J36: =J20 | K36: =K20 | ... O36: =O20
A37: Cargo insurance cash spend | B37: ZAR'000 | D37: =E21 | E37: =F21 | F37: =G21 | G37: =H21 | H37: =I21 | I37: =J21 | J37: =K21 | K37: =L21 | ... N37: =O21 | O37: 0
A38: Import duty cash spend | B38: ZAR'000 | D38: =E22 | E38: =F22 | F38: =G22 | G38: =H22 | H38: =I22 | I38: =J22 | J38: =K22 | K38: =L22 | ... N38: =O22 | O38: 0
A39: Office/software/legal setup cash spend | B39: ZAR'000 | D39: =D23 | E39: =E23 | F39: =F23 | G39: =G23 | H39: =H23 | I39: =I23 | J39: =J23 | K39: =K23 | ... O39: =O23
A40: Total capex cash spend | B40: ZAR'000 | D40: =SUM(D26:D39) | E40: =SUM(E26:E39) | F40: =SUM(F26:F39) | G40: =SUM(G26:G39) | H40: =SUM(H26:H39) | I40: =SUM(I26:I39) | J40: =SUM(J26:J39) | K40: =SUM(K26:K39) | ... O40: =SUM(O26:O39)
A41: Cumulative capex spend | B41: ZAR'000 | D41: =D40 | E41: =D41+E40 | F41: =E41+F40 | G41: =F41+G40 | H41: =G41+H40 | I41: =H41+I40 | J41: =I41+J40 | K41: =J41+K40 | L41: =K41+L40 | ... O41: =N41+O40

Sheet 12M_Miner_Vendor
A1: 12-Month Miner Commercial Schedule
A2: Uses M7DS technical / price assumptions from the model, and applies supplier-style payment mechanics from the attached contract as a placeholder until a final M7DS-specific term sheet is inserted.
D3: 1 | E3: 2 | F3: 3 | G3: 4 | H3: 5 | I3: 6 | J3: 7 | K3: 8 | L3: 9 | M3: 10 | N3: 11 | O3: 12
D4: ='12M_Deployment'!D4 | E4: ='12M_Deployment'!E4 | F4: ='12M_Deployment'!F4 | G4: ='12M_Deployment'!G4 | H4: ='12M_Deployment'!H4 | I4: ='12M_Deployment'!I4 | J4: ='12M_Deployment'!J4 | K4: ='12M_Deployment'!K4 | ... O4: ='12M_Deployment'!O4
A5: New MW commissioned | B5: MW | D5: ='12M_Deployment'!D24 | E5: ='12M_Deployment'!E24 | F5: ='12M_Deployment'!F24 | G5: ='12M_Deployment'!G24 | H5: ='12M_Deployment'!H24 | I5: ='12M_Deployment'!I24 | J5: ='12M_Deployment'!J24 | K5: ='12M_Deployment'!K24 | ... O5: ='12M_Deployment'!O24
A6: Gross hardware capex basis | B6: ZAR'000 | D6: =(D5/(1+Control!$C$34))*1000000/Control!$C$32*Control!$C$33*Control!$C$4/1000 | E6: =(E5/(1+Control!$C$34))*1000000/Control!$C$32*Control!$C$33*Control!$C$4/1000 | F6: =(F5/(1+Control!$C$34))*1000000/Control!$C$32*Control!$C$33*Control!$C$4/1000 | G6: =(G5/(1+Control!$C$34))*1000000/Control!$C$32*Control!$C$33*Control!$C$4/1000 | H6: =(H5/(1+Control!$C$34))*1000000/Control!$C$32*Control!$C$33*Control!$C$4/1000 | I6: =(I5/(1+Control!$C$34))*1000000/Control!$C$32*Control!$C$33*Control!$C$4/1000 | J6: =(J5/(1+Control!$C$34))*1000000/Control!$C$32*Control!$C$33*Control!$C$4/1000 | K6: =(K5/(1+Control!$C$34))*1000000/Control!$C$32*Control!$C$33*Control!$C$4/1000 | ... O6: =(O5/(1+Control!$C$34))*1000000/Control!$C$32*Control!$C$33*Control!$C$4/1000
A7: New miners commissioned | B7: miners | D7: =(D5/(1+Control!$C$34))*1000000/Control!$C$32 | E7: =(E5/(1+Control!$C$34))*1000000/Control!$C$32 | F7: =(F5/(1+Control!$C$34))*1000000/Control!$C$32 | G7: =(G5/(1+Control!$C$34))*1000000/Control!$C$32 | H7: =(H5/(1+Control!$C$34))*1000000/Control!$C$32 | I7: =(I5/(1+Control!$C$34))*1000000/Control!$C$32 | J7: =(J5/(1+Control!$C$34))*1000000/Control!$C$32 | K7: =(K5/(1+Control!$C$34))*1000000/Control!$C$32 | ... O7: =(O5/(1+Control!$C$34))*1000000/Control!$C$32
A9: Deposit cash due | B9: ZAR'000 | D9: =IFERROR(OFFSET(D6,0,Control!$C$97)*Control!$C$98,0) | E9: =IFERROR(OFFSET(E6,0,Control!$C$97)*Control!$C$98,0) | F9: =IFERROR(OFFSET(F6,0,Control!$C$97)*Control!$C$98,0) | G9: =IFERROR(OFFSET(G6,0,Control!$C$97)*Control!$C$98,0) | H9: =IFERROR(OFFSET(H6,0,Control!$C$97)*Control!$C$98,0) | I9: =IFERROR(OFFSET(I6,0,Control!$C$97)*Control!$C$98,0) | J9: =IFERROR(OFFSET(J6,0,Control!$C$97)*Control!$C$98,0) | K9: =IFERROR(OFFSET(K6,0,Control!$C$97)*Control!$C$98,0) | ... O9: =IFERROR(OFFSET(O6,0,Control!$C$97)*Control!$C$98,0)
A10: Vendor-financed principal originated | B10: ZAR'000 | D10: =D6*Control!$C$99 | E10: =E6*Control!$C$99 | F10: =F6*Control!$C$99 | G10: =G6*Control!$C$99 | H10: =H6*Control!$C$99 | I10: =I6*Control!$C$99 | J10: =J6*Control!$C$99 | K10: =K6*Control!$C$99 | ... O10: =O6*Control!$C$99
A11: Opening vendor payable | B11: ZAR'000 | D11: =0 | E11: =D15 | F11: =E15 | G11: =F15 | H11: =G15 | I11: =H15 | J11: =I15 | K11: =J15 | L11: =K15 | ... O11: =N15
A12: Scheduled principal | B12: ZAR'000 | D12: =SUM(D20:D31) | E12: =SUM(E20:E31) | F12: =SUM(F20:F31) | G12: =SUM(G20:G31) | H12: =SUM(H20:H31) | I12: =SUM(I20:I31) | J12: =SUM(J20:J31) | K12: =SUM(K20:K31) | ... O12: =SUM(O20:O31)
A13: Scheduled interest | B13: ZAR'000 | D13: =SUM(D35:D46) | E13: =SUM(E35:E46) | F13: =SUM(F35:F46) | G13: =SUM(G35:G46) | H13: =SUM(H35:H46) | I13: =SUM(I35:I46) | J13: =SUM(J35:J46) | K13: =SUM(K35:K46) | ... O13: =SUM(O35:O46)
A14: Total hardware cash payment | B14: ZAR'000 | D14: =D9+D12+D13 | E14: =E9+E12+E13 | F14: =F9+F12+F13 | G14: =G9+G12+G13 | H14: =H9+H12+H13 | I14: =I9+I12+I13 | J14: =J9+J12+J13 | K14: =K9+K12+K13 | ... O14: =O9+O12+O13
A15: Closing vendor payable | B15: ZAR'000 | D15: =D11+D10-D12 | E15: =E11+E10-E12 | F15: =F11+F10-F12 | G15: =G11+G10-G12 | H15: =H11+H10-H12 | I15: =I11+I10-I12 | J15: =J11+J10-J12 | K15: =K11+K10-K12 | ... O15: =O11+O10-O12
A17: Principal by origination month
A18: Origin month | B18: Source tranche | D18: Month 1 | E18: Month 2 | F18: Month 3 | G18: Month 4 | H18: Month 5 | I18: Month 6 | J18: Month 7 | K18: Month 8 | L18: Month 9 | M18: Month 10 | N18: Month 11 | O18: Month 12
A20: Origin 1 | B20: =D4 | D20: =IF(AND(D$3>=D$3,D$3<D$3+Control!$C$100),D$10/Control!$C$100,0) | E20: =IF(AND(E$3>=D$3,E$3<D$3+Control!$C$100),D$10/Control!$C$100,0) | F20: =IF(AND(F$3>=D$3,F$3<D$3+Control!$C$100),D$10/Control!$C$100,0) | G20: =IF(AND(G$3>=D$3,G$3<D$3+Control!$C$100),D$10/Control!$C$100,0) | H20: =IF(AND(H$3>=D$3,H$3<D$3+Control!$C$100),D$10/Control!$C$100,0) | I20: =IF(AND(I$3>=D$3,I$3<D$3+Control!$C$100),D$10/Control!$C$100,0) | J20: =IF(AND(J$3>=D$3,J$3<D$3+Control!$C$100),D$10/Control!$C$100,0) | K20: =IF(AND(K$3>=D$3,K$3<D$3+Control!$C$100),D$10/Control!$C$100,0) | L20: =IF(AND(L$3>=D$3,L$3<D$3+Control!$C$100),D$10/Control!$C$100,0) | M20: =IF(AND(M$3>=D$3,M$3<D$3+Control!$C$100),D$10/Control!$C$100,0) | N20: =IF(AND(N$3>=D$3,N$3<D$3+Control!$C$100),D$10/Control!$C$100,0) | O20: =IF(AND(O$3>=D$3,O$3<D$3+Control!$C$100),D$10/Control!$C$100,0)
A21: Origin 2 | B21: =E4 | D21: =IF(AND(D$3>=E$3,D$3<E$3+Control!$C$100),E$10/Control!$C$100,0) | E21: =IF(AND(E$3>=E$3,E$3<E$3+Control!$C$100),E$10/Control!$C$100,0) | F21: =IF(AND(F$3>=E$3,F$3<E$3+Control!$C$100),E$10/Control!$C$100,0) | G21: =IF(AND(G$3>=E$3,G$3<E$3+Control!$C$100),E$10/Control!$C$100,0) | H21: =IF(AND(H$3>=E$3,H$3<E$3+Control!$C$100),E$10/Control!$C$100,0) | I21: =IF(AND(I$3>=E$3,I$3<E$3+Control!$C$100),E$10/Control!$C$100,0) | J21: =IF(AND(J$3>=E$3,J$3<E$3+Control!$C$100),E$10/Control!$C$100,0) | K21: =IF(AND(K$3>=E$3,K$3<E$3+Control!$C$100),E$10/Control!$C$100,0) | L21: =IF(AND(L$3>=E$3,L$3<E$3+Control!$C$100),E$10/Control!$C$100,0) | M21: =IF(AND(M$3>=E$3,M$3<E$3+Control!$C$100),E$10/Control!$C$100,0) | N21: =IF(AND(N$3>=E$3,N$3<E$3+Control!$C$100),E$10/Control!$C$100,0) | O21: =IF(AND(O$3>=E$3,O$3<E$3+Control!$C$100),E$10/Control!$C$100,0)
A22: Origin 3 | B22: =F4 | D22: =IF(AND(D$3>=F$3,D$3<F$3+Control!$C$100),F$10/Control!$C$100,0) | E22: =IF(AND(E$3>=F$3,E$3<F$3+Control!$C$100),F$10/Control!$C$100,0) | F22: =IF(AND(F$3>=F$3,F$3<F$3+Control!$C$100),F$10/Control!$C$100,0) | G22: =IF(AND(G$3>=F$3,G$3<F$3+Control!$C$100),F$10/Control!$C$100,0) | H22: =IF(AND(H$3>=F$3,H$3<F$3+Control!$C$100),F$10/Control!$C$100,0) | I22: =IF(AND(I$3>=F$3,I$3<F$3+Control!$C$100),F$10/Control!$C$100,0) | J22: =IF(AND(J$3>=F$3,J$3<F$3+Control!$C$100),F$10/Control!$C$100,0) | K22: =IF(AND(K$3>=F$3,K$3<F$3+Control!$C$100),F$10/Control!$C$100,0) | L22: =IF(AND(L$3>=F$3,L$3<F$3+Control!$C$100),F$10/Control!$C$100,0) | M22: =IF(AND(M$3>=F$3,M$3<F$3+Control!$C$100),F$10/Control!$C$100,0) | N22: =IF(AND(N$3>=F$3,N$3<F$3+Control!$C$100),F$10/Control!$C$100,0) | O22: =IF(AND(O$3>=F$3,O$3<F$3+Control!$C$100),F$10/Control!$C$100,0)
A23: Origin 4 | B23: =G4 | D23: =IF(AND(D$3>=G$3,D$3<G$3+Control!$C$100),G$10/Control!$C$100,0) | E23: =IF(AND(E$3>=G$3,E$3<G$3+Control!$C$100),G$10/Control!$C$100,0) | F23: =IF(AND(F$3>=G$3,F$3<G$3+Control!$C$100),G$10/Control!$C$100,0) | G23: =IF(AND(G$3>=G$3,G$3<G$3+Control!$C$100),G$10/Control!$C$100,0) | H23: =IF(AND(H$3>=G$3,H$3<G$3+Control!$C$100),G$10/Control!$C$100,0) | I23: =IF(AND(I$3>=G$3,I$3<G$3+Control!$C$100),G$10/Control!$C$100,0) | J23: =IF(AND(J$3>=G$3,J$3<G$3+Control!$C$100),G$10/Control!$C$100,0) | K23: =IF(AND(K$3>=G$3,K$3<G$3+Control!$C$100),G$10/Control!$C$100,0) | L23: =IF(AND(L$3>=G$3,L$3<G$3+Control!$C$100),G$10/Control!$C$100,0) | M23: =IF(AND(M$3>=G$3,M$3<G$3+Control!$C$100),G$10/Control!$C$100,0) | N23: =IF(AND(N$3>=G$3,N$3<G$3+Control!$C$100),G$10/Control!$C$100,0) | O23: =IF(AND(O$3>=G$3,O$3<G$3+Control!$C$100),G$10/Control!$C$100,0)
A24: Origin 5 | B24: =H4 | D24: =IF(AND(D$3>=H$3,D$3<H$3+Control!$C$100),H$10/Control!$C$100,0) | E24: =IF(AND(E$3>=H$3,E$3<H$3+Control!$C$100),H$10/Control!$C$100,0) | F24: =IF(AND(F$3>=H$3,F$3<H$3+Control!$C$100),H$10/Control!$C$100,0) | G24: =IF(AND(G$3>=H$3,G$3<H$3+Control!$C$100),H$10/Control!$C$100,0) | H24: =IF(AND(H$3>=H$3,H$3<H$3+Control!$C$100),H$10/Control!$C$100,0) | I24: =IF(AND(I$3>=H$3,I$3<H$3+Control!$C$100),H$10/Control!$C$100,0) | J24: =IF(AND(J$3>=H$3,J$3<H$3+Control!$C$100),H$10/Control!$C$100,0) | K24: =IF(AND(K$3>=H$3,K$3<H$3+Control!$C$100),H$10/Control!$C$100,0) | L24: =IF(AND(L$3>=H$3,L$3<H$3+Control!$C$100),H$10/Control!$C$100,0) | M24: =IF(AND(M$3>=H$3,M$3<H$3+Control!$C$100),H$10/Control!$C$100,0) | N24: =IF(AND(N$3>=H$3,N$3<H$3+Control!$C$100),H$10/Control!$C$100,0) | O24: =IF(AND(O$3>=H$3,O$3<H$3+Control!$C$100),H$10/Control!$C$100,0)
A25: Origin 6 | B25: =I4 | D25: =IF(AND(D$3>=I$3,D$3<I$3+Control!$C$100),I$10/Control!$C$100,0) | E25: =IF(AND(E$3>=I$3,E$3<I$3+Control!$C$100),I$10/Control!$C$100,0) | F25: =IF(AND(F$3>=I$3,F$3<I$3+Control!$C$100),I$10/Control!$C$100,0) | G25: =IF(AND(G$3>=I$3,G$3<I$3+Control!$C$100),I$10/Control!$C$100,0) | H25: =IF(AND(H$3>=I$3,H$3<I$3+Control!$C$100),I$10/Control!$C$100,0) | I25: =IF(AND(I$3>=I$3,I$3<I$3+Control!$C$100),I$10/Control!$C$100,0) | J25: =IF(AND(J$3>=I$3,J$3<I$3+Control!$C$100),I$10/Control!$C$100,0) | K25: =IF(AND(K$3>=I$3,K$3<I$3+Control!$C$100),I$10/Control!$C$100,0) | L25: =IF(AND(L$3>=I$3,L$3<I$3+Control!$C$100),I$10/Control!$C$100,0) | M25: =IF(AND(M$3>=I$3,M$3<I$3+Control!$C$100),I$10/Control!$C$100,0) | N25: =IF(AND(N$3>=I$3,N$3<I$3+Control!$C$100),I$10/Control!$C$100,0) | O25: =IF(AND(O$3>=I$3,O$3<I$3+Control!$C$100),I$10/Control!$C$100,0)
A26: Origin 7 | B26: =J4 | D26: =IF(AND(D$3>=J$3,D$3<J$3+Control!$C$100),J$10/Control!$C$100,0) | E26: =IF(AND(E$3>=J$3,E$3<J$3+Control!$C$100),J$10/Control!$C$100,0) | F26: =IF(AND(F$3>=J$3,F$3<J$3+Control!$C$100),J$10/Control!$C$100,0) | G26: =IF(AND(G$3>=J$3,G$3<J$3+Control!$C$100),J$10/Control!$C$100,0) | H26: =IF(AND(H$3>=J$3,H$3<J$3+Control!$C$100),J$10/Control!$C$100,0) | I26: =IF(AND(I$3>=J$3,I$3<J$3+Control!$C$100),J$10/Control!$C$100,0) | J26: =IF(AND(J$3>=J$3,J$3<J$3+Control!$C$100),J$10/Control!$C$100,0) | K26: =IF(AND(K$3>=J$3,K$3<J$3+Control!$C$100),J$10/Control!$C$100,0) | L26: =IF(AND(L$3>=J$3,L$3<J$3+Control!$C$100),J$10/Control!$C$100,0) | M26: =IF(AND(M$3>=J$3,M$3<J$3+Control!$C$100),J$10/Control!$C$100,0) | N26: =IF(AND(N$3>=J$3,N$3<J$3+Control!$C$100),J$10/Control!$C$100,0) | O26: =IF(AND(O$3>=J$3,O$3<J$3+Control!$C$100),J$10/Control!$C$100,0)
A27: Origin 8 | B27: =K4 | D27: =IF(AND(D$3>=K$3,D$3<K$3+Control!$C$100),K$10/Control!$C$100,0) | E27: =IF(AND(E$3>=K$3,E$3<K$3+Control!$C$100),K$10/Control!$C$100,0) | F27: =IF(AND(F$3>=K$3,F$3<K$3+Control!$C$100),K$10/Control!$C$100,0) | G27: =IF(AND(G$3>=K$3,G$3<K$3+Control!$C$100),K$10/Control!$C$100,0) | H27: =IF(AND(H$3>=K$3,H$3<K$3+Control!$C$100),K$10/Control!$C$100,0) | I27: =IF(AND(I$3>=K$3,I$3<K$3+Control!$C$100),K$10/Control!$C$100,0) | J27: =IF(AND(J$3>=K$3,J$3<K$3+Control!$C$100),K$10/Control!$C$100,0) | K27: =IF(AND(K$3>=K$3,K$3<K$3+Control!$C$100),K$10/Control!$C$100,0) | L27: =IF(AND(L$3>=K$3,L$3<K$3+Control!$C$100),K$10/Control!$C$100,0) | M27: =IF(AND(M$3>=K$3,M$3<K$3+Control!$C$100),K$10/Control!$C$100,0) | N27: =IF(AND(N$3>=K$3,N$3<K$3+Control!$C$100),K$10/Control!$C$100,0) | O27: =IF(AND(O$3>=K$3,O$3<K$3+Control!$C$100),K$10/Control!$C$100,0)
A28: Origin 9 | B28: =L4 | D28: =IF(AND(D$3>=L$3,D$3<L$3+Control!$C$100),L$10/Control!$C$100,0) | E28: =IF(AND(E$3>=L$3,E$3<L$3+Control!$C$100),L$10/Control!$C$100,0) | F28: =IF(AND(F$3>=L$3,F$3<L$3+Control!$C$100),L$10/Control!$C$100,0) | G28: =IF(AND(G$3>=L$3,G$3<L$3+Control!$C$100),L$10/Control!$C$100,0) | H28: =IF(AND(H$3>=L$3,H$3<L$3+Control!$C$100),L$10/Control!$C$100,0) | I28: =IF(AND(I$3>=L$3,I$3<L$3+Control!$C$100),L$10/Control!$C$100,0) | J28: =IF(AND(J$3>=L$3,J$3<L$3+Control!$C$100),L$10/Control!$C$100,0) | K28: =IF(AND(K$3>=L$3,K$3<L$3+Control!$C$100),L$10/Control!$C$100,0) | L28: =IF(AND(L$3>=L$3,L$3<L$3+Control!$C$100),L$10/Control!$C$100,0) | M28: =IF(AND(M$3>=L$3,M$3<L$3+Control!$C$100),L$10/Control!$C$100,0) | N28: =IF(AND(N$3>=L$3,N$3<L$3+Control!$C$100),L$10/Control!$C$100,0) | O28: =IF(AND(O$3>=L$3,O$3<L$3+Control!$C$100),L$10/Control!$C$100,0)
A29: Origin 10 | B29: =M4 | D29: =IF(AND(D$3>=M$3,D$3<M$3+Control!$C$100),M$10/Control!$C$100,0) | E29: =IF(AND(E$3>=M$3,E$3<M$3+Control!$C$100),M$10/Control!$C$100,0) | F29: =IF(AND(F$3>=M$3,F$3<M$3+Control!$C$100),M$10/Control!$C$100,0) | G29: =IF(AND(G$3>=M$3,G$3<M$3+Control!$C$100),M$10/Control!$C$100,0) | H29: =IF(AND(H$3>=M$3,H$3<M$3+Control!$C$100),M$10/Control!$C$100,0) | I29: =IF(AND(I$3>=M$3,I$3<M$3+Control!$C$100),M$10/Control!$C$100,0) | J29: =IF(AND(J$3>=M$3,J$3<M$3+Control!$C$100),M$10/Control!$C$100,0) | K29: =IF(AND(K$3>=M$3,K$3<M$3+Control!$C$100),M$10/Control!$C$100,0) | L29: =IF(AND(L$3>=M$3,L$3<M$3+Control!$C$100),M$10/Control!$C$100,0) | M29: =IF(AND(M$3>=M$3,M$3<M$3+Control!$C$100),M$10/Control!$C$100,0) | N29: =IF(AND(N$3>=M$3,N$3<M$3+Control!$C$100),M$10/Control!$C$100,0) | O29: =IF(AND(O$3>=M$3,O$3<M$3+Control!$C$100),M$10/Control!$C$100,0)
A30: Origin 11 | B30: =N4 | D30: =IF(AND(D$3>=N$3,D$3<N$3+Control!$C$100),N$10/Control!$C$100,0) | E30: =IF(AND(E$3>=N$3,E$3<N$3+Control!$C$100),N$10/Control!$C$100,0) | F30: =IF(AND(F$3>=N$3,F$3<N$3+Control!$C$100),N$10/Control!$C$100,0) | G30: =IF(AND(G$3>=N$3,G$3<N$3+Control!$C$100),N$10/Control!$C$100,0) | H30: =IF(AND(H$3>=N$3,H$3<N$3+Control!$C$100),N$10/Control!$C$100,0) | I30: =IF(AND(I$3>=N$3,I$3<N$3+Control!$C$100),N$10/Control!$C$100,0) | J30: =IF(AND(J$3>=N$3,J$3<N$3+Control!$C$100),N$10/Control!$C$100,0) | K30: =IF(AND(K$3>=N$3,K$3<N$3+Control!$C$100),N$10/Control!$C$100,0) | L30: =IF(AND(L$3>=N$3,L$3<N$3+Control!$C$100),N$10/Control!$C$100,0) | M30: =IF(AND(M$3>=N$3,M$3<N$3+Control!$C$100),N$10/Control!$C$100,0) | N30: =IF(AND(N$3>=N$3,N$3<N$3+Control!$C$100),N$10/Control!$C$100,0) | O30: =IF(AND(O$3>=N$3,O$3<N$3+Control!$C$100),N$10/Control!$C$100,0)
A31: Origin 12 | B31: =O4 | D31: =IF(AND(D$3>=O$3,D$3<O$3+Control!$C$100),O$10/Control!$C$100,0) | E31: =IF(AND(E$3>=O$3,E$3<O$3+Control!$C$100),O$10/Control!$C$100,0) | F31: =IF(AND(F$3>=O$3,F$3<O$3+Control!$C$100),O$10/Control!$C$100,0) | G31: =IF(AND(G$3>=O$3,G$3<O$3+Control!$C$100),O$10/Control!$C$100,0) | H31: =IF(AND(H$3>=O$3,H$3<O$3+Control!$C$100),O$10/Control!$C$100,0) | I31: =IF(AND(I$3>=O$3,I$3<O$3+Control!$C$100),O$10/Control!$C$100,0) | J31: =IF(AND(J$3>=O$3,J$3<O$3+Control!$C$100),O$10/Control!$C$100,0) | K31: =IF(AND(K$3>=O$3,K$3<O$3+Control!$C$100),O$10/Control!$C$100,0) | L31: =IF(AND(L$3>=O$3,L$3<O$3+Control!$C$100),O$10/Control!$C$100,0) | M31: =IF(AND(M$3>=O$3,M$3<O$3+Control!$C$100),O$10/Control!$C$100,0) | N31: =IF(AND(N$3>=O$3,N$3<O$3+Control!$C$100),O$10/Control!$C$100,0) | O31: =IF(AND(O$3>=O$3,O$3<O$3+Control!$C$100),O$10/Control!$C$100,0)
A33: Interest by origination month
A34: Origin month | B34: Source tranche | D34: Month 1 | E34: Month 2 | F34: Month 3 | G34: Month 4 | H34: Month 5 | I34: Month 6 | J34: Month 7 | K34: Month 8 | L34: Month 9 | M34: Month 10 | N34: Month 11 | O34: Month 12
A35: Origin 1 | B35: =D4 | D35: =IF(AND(D$3>=D$3,D$3<D$3+Control!$C$100),(D$10-(D$10/Control!$C$100)*(D$3-D$3))*Control!$C$101/12,0) | E35: =IF(AND(E$3>=D$3,E$3<D$3+Control!$C$100),(D$10-(D$10/Control!$C$100)*(E$3-D$3))*Control!$C$101/12,0) | F35: =IF(AND(F$3>=D$3,F$3<D$3+Control!$C$100),(D$10-(D$10/Control!$C$100)*(F$3-D$3))*Control!$C$101/12,0) | G35: =IF(AND(G$3>=D$3,G$3<D$3+Control!$C$100),(D$10-(D$10/Control!$C$100)*(G$3-D$3))*Control!$C$101/12,0) | H35: =IF(AND(H$3>=D$3,H$3<D$3+Control!$C$100),(D$10-(D$10/Control!$C$100)*(H$3-D$3))*Control!$C$101/12,0) | I35: =IF(AND(I$3>=D$3,I$3<D$3+Control!$C$100),(D$10-(D$10/Control!$C$100)*(I$3-D$3))*Control!$C$101/12,0) | J35: =IF(AND(J$3>=D$3,J$3<D$3+Control!$C$100),(D$10-(D$10/Control!$C$100)*(J$3-D$3))*Control!$C$101/12,0) | K35: =IF(AND(K$3>=D$3,K$3<D$3+Control!$C$100),(D$10-(D$10/Control!$C$100)*(K$3-D$3))*Control!$C$101/12,0) | L35: =IF(AND(L$3>=D$3,L$3<D$3+Control!$C$100),(D$10-(D$10/Control!$C$100)*(L$3-D$3))*Control!$C$101/12,0) | M35: =IF(AND(M$3>=D$3,M$3<D$3+Control!$C$100),(D$10-(D$10/Control!$C$100)*(M$3-D$3))*Control!$C$101/12,0) | N35: =IF(AND(N$3>=D$3,N$3<D$3+Control!$C$100),(D$10-(D$10/Control!$C$100)*(N$3-D$3))*Control!$C$101/12,0) | O35: =IF(AND(O$3>=D$3,O$3<D$3+Control!$C$100),(D$10-(D$10/Control!$C$100)*(O$3-D$3))*Control!$C$101/12,0)
A36: Origin 2 | B36: =E4 | D36: =IF(AND(D$3>=E$3,D$3<E$3+Control!$C$100),(E$10-(E$10/Control!$C$100)*(D$3-E$3))*Control!$C$101/12,0) | E36: =IF(AND(E$3>=E$3,E$3<E$3+Control!$C$100),(E$10-(E$10/Control!$C$100)*(E$3-E$3))*Control!$C$101/12,0) | F36: =IF(AND(F$3>=E$3,F$3<E$3+Control!$C$100),(E$10-(E$10/Control!$C$100)*(F$3-E$3))*Control!$C$101/12,0) | G36: =IF(AND(G$3>=E$3,G$3<E$3+Control!$C$100),(E$10-(E$10/Control!$C$100)*(G$3-E$3))*Control!$C$101/12,0) | H36: =IF(AND(H$3>=E$3,H$3<E$3+Control!$C$100),(E$10-(E$10/Control!$C$100)*(H$3-E$3))*Control!$C$101/12,0) | I36: =IF(AND(I$3>=E$3,I$3<E$3+Control!$C$100),(E$10-(E$10/Control!$C$100)*(I$3-E$3))*Control!$C$101/12,0) | J36: =IF(AND(J$3>=E$3,J$3<E$3+Control!$C$100),(E$10-(E$10/Control!$C$100)*(J$3-E$3))*Control!$C$101/12,0) | K36: =IF(AND(K$3>=E$3,K$3<E$3+Control!$C$100),(E$10-(E$10/Control!$C$100)*(K$3-E$3))*Control!$C$101/12,0) | L36: =IF(AND(L$3>=E$3,L$3<E$3+Control!$C$100),(E$10-(E$10/Control!$C$100)*(L$3-E$3))*Control!$C$101/12,0) | M36: =IF(AND(M$3>=E$3,M$3<E$3+Control!$C$100),(E$10-(E$10/Control!$C$100)*(M$3-E$3))*Control!$C$101/12,0) | N36: =IF(AND(N$3>=E$3,N$3<E$3+Control!$C$100),(E$10-(E$10/Control!$C$100)*(N$3-E$3))*Control!$C$101/12,0) | O36: =IF(AND(O$3>=E$3,O$3<E$3+Control!$C$100),(E$10-(E$10/Control!$C$100)*(O$3-E$3))*Control!$C$101/12,0)
A37: Origin 3 | B37: =F4 | D37: =IF(AND(D$3>=F$3,D$3<F$3+Control!$C$100),(F$10-(F$10/Control!$C$100)*(D$3-F$3))*Control!$C$101/12,0) | E37: =IF(AND(E$3>=F$3,E$3<F$3+Control!$C$100),(F$10-(F$10/Control!$C$100)*(E$3-F$3))*Control!$C$101/12,0) | F37: =IF(AND(F$3>=F$3,F$3<F$3+Control!$C$100),(F$10-(F$10/Control!$C$100)*(F$3-F$3))*Control!$C$101/12,0) | G37: =IF(AND(G$3>=F$3,G$3<F$3+Control!$C$100),(F$10-(F$10/Control!$C$100)*(G$3-F$3))*Control!$C$101/12,0) | H37: =IF(AND(H$3>=F$3,H$3<F$3+Control!$C$100),(F$10-(F$10/Control!$C$100)*(H$3-F$3))*Control!$C$101/12,0) | I37: =IF(AND(I$3>=F$3,I$3<F$3+Control!$C$100),(F$10-(F$10/Control!$C$100)*(I$3-F$3))*Control!$C$101/12,0) | J37: =IF(AND(J$3>=F$3,J$3<F$3+Control!$C$100),(F$10-(F$10/Control!$C$100)*(J$3-F$3))*Control!$C$101/12,0) | K37: =IF(AND(K$3>=F$3,K$3<F$3+Control!$C$100),(F$10-(F$10/Control!$C$100)*(K$3-F$3))*Control!$C$101/12,0) | L37: =IF(AND(L$3>=F$3,L$3<F$3+Control!$C$100),(F$10-(F$10/Control!$C$100)*(L$3-F$3))*Control!$C$101/12,0) | M37: =IF(AND(M$3>=F$3,M$3<F$3+Control!$C$100),(F$10-(F$10/Control!$C$100)*(M$3-F$3))*Control!$C$101/12,0) | N37: =IF(AND(N$3>=F$3,N$3<F$3+Control!$C$100),(F$10-(F$10/Control!$C$100)*(N$3-F$3))*Control!$C$101/12,0) | O37: =IF(AND(O$3>=F$3,O$3<F$3+Control!$C$100),(F$10-(F$10/Control!$C$100)*(O$3-F$3))*Control!$C$101/12,0)
A38: Origin 4 | B38: =G4 | D38: =IF(AND(D$3>=G$3,D$3<G$3+Control!$C$100),(G$10-(G$10/Control!$C$100)*(D$3-G$3))*Control!$C$101/12,0) | E38: =IF(AND(E$3>=G$3,E$3<G$3+Control!$C$100),(G$10-(G$10/Control!$C$100)*(E$3-G$3))*Control!$C$101/12,0) | F38: =IF(AND(F$3>=G$3,F$3<G$3+Control!$C$100),(G$10-(G$10/Control!$C$100)*(F$3-G$3))*Control!$C$101/12,0) | G38: =IF(AND(G$3>=G$3,G$3<G$3+Control!$C$100),(G$10-(G$10/Control!$C$100)*(G$3-G$3))*Control!$C$101/12,0) | H38: =IF(AND(H$3>=G$3,H$3<G$3+Control!$C$100),(G$10-(G$10/Control!$C$100)*(H$3-G$3))*Control!$C$101/12,0) | I38: =IF(AND(I$3>=G$3,I$3<G$3+Control!$C$100),(G$10-(G$10/Control!$C$100)*(I$3-G$3))*Control!$C$101/12,0) | J38: =IF(AND(J$3>=G$3,J$3<G$3+Control!$C$100),(G$10-(G$10/Control!$C$100)*(J$3-G$3))*Control!$C$101/12,0) | K38: =IF(AND(K$3>=G$3,K$3<G$3+Control!$C$100),(G$10-(G$10/Control!$C$100)*(K$3-G$3))*Control!$C$101/12,0) | L38: =IF(AND(L$3>=G$3,L$3<G$3+Control!$C$100),(G$10-(G$10/Control!$C$100)*(L$3-G$3))*Control!$C$101/12,0) | M38: =IF(AND(M$3>=G$3,M$3<G$3+Control!$C$100),(G$10-(G$10/Control!$C$100)*(M$3-G$3))*Control!$C$101/12,0) | N38: =IF(AND(N$3>=G$3,N$3<G$3+Control!$C$100),(G$10-(G$10/Control!$C$100)*(N$3-G$3))*Control!$C$101/12,0) | O38: =IF(AND(O$3>=G$3,O$3<G$3+Control!$C$100),(G$10-(G$10/Control!$C$100)*(O$3-G$3))*Control!$C$101/12,0)
A39: Origin 5 | B39: =H4 | D39: =IF(AND(D$3>=H$3,D$3<H$3+Control!$C$100),(H$10-(H$10/Control!$C$100)*(D$3-H$3))*Control!$C$101/12,0) | E39: =IF(AND(E$3>=H$3,E$3<H$3+Control!$C$100),(H$10-(H$10/Control!$C$100)*(E$3-H$3))*Control!$C$101/12,0) | F39: =IF(AND(F$3>=H$3,F$3<H$3+Control!$C$100),(H$10-(H$10/Control!$C$100)*(F$3-H$3))*Control!$C$101/12,0) | G39: =IF(AND(G$3>=H$3,G$3<H$3+Control!$C$100),(H$10-(H$10/Control!$C$100)*(G$3-H$3))*Control!$C$101/12,0) | H39: =IF(AND(H$3>=H$3,H$3<H$3+Control!$C$100),(H$10-(H$10/Control!$C$100)*(H$3-H$3))*Control!$C$101/12,0) | I39: =IF(AND(I$3>=H$3,I$3<H$3+Control!$C$100),(H$10-(H$10/Control!$C$100)*(I$3-H$3))*Control!$C$101/12,0) | J39: =IF(AND(J$3>=H$3,J$3<H$3+Control!$C$100),(H$10-(H$10/Control!$C$100)*(J$3-H$3))*Control!$C$101/12,0) | K39: =IF(AND(K$3>=H$3,K$3<H$3+Control!$C$100),(H$10-(H$10/Control!$C$100)*(K$3-H$3))*Control!$C$101/12,0) | L39: =IF(AND(L$3>=H$3,L$3<H$3+Control!$C$100),(H$10-(H$10/Control!$C$100)*(L$3-H$3))*Control!$C$101/12,0) | M39: =IF(AND(M$3>=H$3,M$3<H$3+Control!$C$100),(H$10-(H$10/Control!$C$100)*(M$3-H$3))*Control!$C$101/12,0) | N39: =IF(AND(N$3>=H$3,N$3<H$3+Control!$C$100),(H$10-(H$10/Control!$C$100)*(N$3-H$3))*Control!$C$101/12,0) | O39: =IF(AND(O$3>=H$3,O$3<H$3+Control!$C$100),(H$10-(H$10/Control!$C$100)*(O$3-H$3))*Control!$C$101/12,0)
A40: Origin 6 | B40: =I4 | D40: =IF(AND(D$3>=I$3,D$3<I$3+Control!$C$100),(I$10-(I$10/Control!$C$100)*(D$3-I$3))*Control!$C$101/12,0) | E40: =IF(AND(E$3>=I$3,E$3<I$3+Control!$C$100),(I$10-(I$10/Control!$C$100)*(E$3-I$3))*Control!$C$101/12,0) | F40: =IF(AND(F$3>=I$3,F$3<I$3+Control!$C$100),(I$10-(I$10/Control!$C$100)*(F$3-I$3))*Control!$C$101/12,0) | G40: =IF(AND(G$3>=I$3,G$3<I$3+Control!$C$100),(I$10-(I$10/Control!$C$100)*(G$3-I$3))*Control!$C$101/12,0) | H40: =IF(AND(H$3>=I$3,H$3<I$3+Control!$C$100),(I$10-(I$10/Control!$C$100)*(H$3-I$3))*Control!$C$101/12,0) | I40: =IF(AND(I$3>=I$3,I$3<I$3+Control!$C$100),(I$10-(I$10/Control!$C$100)*(I$3-I$3))*Control!$C$101/12,0) | J40: =IF(AND(J$3>=I$3,J$3<I$3+Control!$C$100),(I$10-(I$10/Control!$C$100)*(J$3-I$3))*Control!$C$101/12,0) | K40: =IF(AND(K$3>=I$3,K$3<I$3+Control!$C$100),(I$10-(I$10/Control!$C$100)*(K$3-I$3))*Control!$C$101/12,0) | L40: =IF(AND(L$3>=I$3,L$3<I$3+Control!$C$100),(I$10-(I$10/Control!$C$100)*(L$3-I$3))*Control!$C$101/12,0) | M40: =IF(AND(M$3>=I$3,M$3<I$3+Control!$C$100),(I$10-(I$10/Control!$C$100)*(M$3-I$3))*Control!$C$101/12,0) | N40: =IF(AND(N$3>=I$3,N$3<I$3+Control!$C$100),(I$10-(I$10/Control!$C$100)*(N$3-I$3))*Control!$C$101/12,0) | O40: =IF(AND(O$3>=I$3,O$3<I$3+Control!$C$100),(I$10-(I$10/Control!$C$100)*(O$3-I$3))*Control!$C$101/12,0)
A41: Origin 7 | B41: =J4 | D41: =IF(AND(D$3>=J$3,D$3<J$3+Control!$C$100),(J$10-(J$10/Control!$C$100)*(D$3-J$3))*Control!$C$101/12,0) | E41: =IF(AND(E$3>=J$3,E$3<J$3+Control!$C$100),(J$10-(J$10/Control!$C$100)*(E$3-J$3))*Control!$C$101/12,0) | F41: =IF(AND(F$3>=J$3,F$3<J$3+Control!$C$100),(J$10-(J$10/Control!$C$100)*(F$3-J$3))*Control!$C$101/12,0) | G41: =IF(AND(G$3>=J$3,G$3<J$3+Control!$C$100),(J$10-(J$10/Control!$C$100)*(G$3-J$3))*Control!$C$101/12,0) | H41: =IF(AND(H$3>=J$3,H$3<J$3+Control!$C$100),(J$10-(J$10/Control!$C$100)*(H$3-J$3))*Control!$C$101/12,0) | I41: =IF(AND(I$3>=J$3,I$3<J$3+Control!$C$100),(J$10-(J$10/Control!$C$100)*(I$3-J$3))*Control!$C$101/12,0) | J41: =IF(AND(J$3>=J$3,J$3<J$3+Control!$C$100),(J$10-(J$10/Control!$C$100)*(J$3-J$3))*Control!$C$101/12,0) | K41: =IF(AND(K$3>=J$3,K$3<J$3+Control!$C$100),(J$10-(J$10/Control!$C$100)*(K$3-J$3))*Control!$C$101/12,0) | L41: =IF(AND(L$3>=J$3,L$3<J$3+Control!$C$100),(J$10-(J$10/Control!$C$100)*(L$3-J$3))*Control!$C$101/12,0) | M41: =IF(AND(M$3>=J$3,M$3<J$3+Control!$C$100),(J$10-(J$10/Control!$C$100)*(M$3-J$3))*Control!$C$101/12,0) | N41: =IF(AND(N$3>=J$3,N$3<J$3+Control!$C$100),(J$10-(J$10/Control!$C$100)*(N$3-J$3))*Control!$C$101/12,0) | O41: =IF(AND(O$3>=J$3,O$3<J$3+Control!$C$100),(J$10-(J$10/Control!$C$100)*(O$3-J$3))*Control!$C$101/12,0)
A42: Origin 8 | B42: =K4 | D42: =IF(AND(D$3>=K$3,D$3<K$3+Control!$C$100),(K$10-(K$10/Control!$C$100)*(D$3-K$3))*Control!$C$101/12,0) | E42: =IF(AND(E$3>=K$3,E$3<K$3+Control!$C$100),(K$10-(K$10/Control!$C$100)*(E$3-K$3))*Control!$C$101/12,0) | F42: =IF(AND(F$3>=K$3,F$3<K$3+Control!$C$100),(K$10-(K$10/Control!$C$100)*(F$3-K$3))*Control!$C$101/12,0) | G42: =IF(AND(G$3>=K$3,G$3<K$3+Control!$C$100),(K$10-(K$10/Control!$C$100)*(G$3-K$3))*Control!$C$101/12,0) | H42: =IF(AND(H$3>=K$3,H$3<K$3+Control!$C$100),(K$10-(K$10/Control!$C$100)*(H$3-K$3))*Control!$C$101/12,0) | I42: =IF(AND(I$3>=K$3,I$3<K$3+Control!$C$100),(K$10-(K$10/Control!$C$100)*(I$3-K$3))*Control!$C$101/12,0) | J42: =IF(AND(J$3>=K$3,J$3<K$3+Control!$C$100),(K$10-(K$10/Control!$C$100)*(J$3-K$3))*Control!$C$101/12,0) | K42: =IF(AND(K$3>=K$3,K$3<K$3+Control!$C$100),(K$10-(K$10/Control!$C$100)*(K$3-K$3))*Control!$C$101/12,0) | L42: =IF(AND(L$3>=K$3,L$3<K$3+Control!$C$100),(K$10-(K$10/Control!$C$100)*(L$3-K$3))*Control!$C$101/12,0) | M42: =IF(AND(M$3>=K$3,M$3<K$3+Control!$C$100),(K$10-(K$10/Control!$C$100)*(M$3-K$3))*Control!$C$101/12,0) | N42: =IF(AND(N$3>=K$3,N$3<K$3+Control!$C$100),(K$10-(K$10/Control!$C$100)*(N$3-K$3))*Control!$C$101/12,0) | O42: =IF(AND(O$3>=K$3,O$3<K$3+Control!$C$100),(K$10-(K$10/Control!$C$100)*(O$3-K$3))*Control!$C$101/12,0)
A43: Origin 9 | B43: =L4 | D43: =IF(AND(D$3>=L$3,D$3<L$3+Control!$C$100),(L$10-(L$10/Control!$C$100)*(D$3-L$3))*Control!$C$101/12,0) | E43: =IF(AND(E$3>=L$3,E$3<L$3+Control!$C$100),(L$10-(L$10/Control!$C$100)*(E$3-L$3))*Control!$C$101/12,0) | F43: =IF(AND(F$3>=L$3,F$3<L$3+Control!$C$100),(L$10-(L$10/Control!$C$100)*(F$3-L$3))*Control!$C$101/12,0) | G43: =IF(AND(G$3>=L$3,G$3<L$3+Control!$C$100),(L$10-(L$10/Control!$C$100)*(G$3-L$3))*Control!$C$101/12,0) | H43: =IF(AND(H$3>=L$3,H$3<L$3+Control!$C$100),(L$10-(L$10/Control!$C$100)*(H$3-L$3))*Control!$C$101/12,0) | I43: =IF(AND(I$3>=L$3,I$3<L$3+Control!$C$100),(L$10-(L$10/Control!$C$100)*(I$3-L$3))*Control!$C$101/12,0) | J43: =IF(AND(J$3>=L$3,J$3<L$3+Control!$C$100),(L$10-(L$10/Control!$C$100)*(J$3-L$3))*Control!$C$101/12,0) | K43: =IF(AND(K$3>=L$3,K$3<L$3+Control!$C$100),(L$10-(L$10/Control!$C$100)*(K$3-L$3))*Control!$C$101/12,0) | L43: =IF(AND(L$3>=L$3,L$3<L$3+Control!$C$100),(L$10-(L$10/Control!$C$100)*(L$3-L$3))*Control!$C$101/12,0) | M43: =IF(AND(M$3>=L$3,M$3<L$3+Control!$C$100),(L$10-(L$10/Control!$C$100)*(M$3-L$3))*Control!$C$101/12,0) | N43: =IF(AND(N$3>=L$3,N$3<L$3+Control!$C$100),(L$10-(L$10/Control!$C$100)*(N$3-L$3))*Control!$C$101/12,0) | O43: =IF(AND(O$3>=L$3,O$3<L$3+Control!$C$100),(L$10-(L$10/Control!$C$100)*(O$3-L$3))*Control!$C$101/12,0)
A44: Origin 10 | B44: =M4 | D44: =IF(AND(D$3>=M$3,D$3<M$3+Control!$C$100),(M$10-(M$10/Control!$C$100)*(D$3-M$3))*Control!$C$101/12,0) | E44: =IF(AND(E$3>=M$3,E$3<M$3+Control!$C$100),(M$10-(M$10/Control!$C$100)*(E$3-M$3))*Control!$C$101/12,0) | F44: =IF(AND(F$3>=M$3,F$3<M$3+Control!$C$100),(M$10-(M$10/Control!$C$100)*(F$3-M$3))*Control!$C$101/12,0) | G44: =IF(AND(G$3>=M$3,G$3<M$3+Control!$C$100),(M$10-(M$10/Control!$C$100)*(G$3-M$3))*Control!$C$101/12,0) | H44: =IF(AND(H$3>=M$3,H$3<M$3+Control!$C$100),(M$10-(M$10/Control!$C$100)*(H$3-M$3))*Control!$C$101/12,0) | I44: =IF(AND(I$3>=M$3,I$3<M$3+Control!$C$100),(M$10-(M$10/Control!$C$100)*(I$3-M$3))*Control!$C$101/12,0) | J44: =IF(AND(J$3>=M$3,J$3<M$3+Control!$C$100),(M$10-(M$10/Control!$C$100)*(J$3-M$3))*Control!$C$101/12,0) | K44: =IF(AND(K$3>=M$3,K$3<M$3+Control!$C$100),(M$10-(M$10/Control!$C$100)*(K$3-M$3))*Control!$C$101/12,0) | L44: =IF(AND(L$3>=M$3,L$3<M$3+Control!$C$100),(M$10-(M$10/Control!$C$100)*(L$3-M$3))*Control!$C$101/12,0) | M44: =IF(AND(M$3>=M$3,M$3<M$3+Control!$C$100),(M$10-(M$10/Control!$C$100)*(M$3-M$3))*Control!$C$101/12,0) | N44: =IF(AND(N$3>=M$3,N$3<M$3+Control!$C$100),(M$10-(M$10/Control!$C$100)*(N$3-M$3))*Control!$C$101/12,0) | O44: =IF(AND(O$3>=M$3,O$3<M$3+Control!$C$100),(M$10-(M$10/Control!$C$100)*(O$3-M$3))*Control!$C$101/12,0)
A45: Origin 11 | B45: =N4 | D45: =IF(AND(D$3>=N$3,D$3<N$3+Control!$C$100),(N$10-(N$10/Control!$C$100)*(D$3-N$3))*Control!$C$101/12,0) | E45: =IF(AND(E$3>=N$3,E$3<N$3+Control!$C$100),(N$10-(N$10/Control!$C$100)*(E$3-N$3))*Control!$C$101/12,0) | F45: =IF(AND(F$3>=N$3,F$3<N$3+Control!$C$100),(N$10-(N$10/Control!$C$100)*(F$3-N$3))*Control!$C$101/12,0) | G45: =IF(AND(G$3>=N$3,G$3<N$3+Control!$C$100),(N$10-(N$10/Control!$C$100)*(G$3-N$3))*Control!$C$101/12,0) | H45: =IF(AND(H$3>=N$3,H$3<N$3+Control!$C$100),(N$10-(N$10/Control!$C$100)*(H$3-N$3))*Control!$C$101/12,0) | I45: =IF(AND(I$3>=N$3,I$3<N$3+Control!$C$100),(N$10-(N$10/Control!$C$100)*(I$3-N$3))*Control!$C$101/12,0) | J45: =IF(AND(J$3>=N$3,J$3<N$3+Control!$C$100),(N$10-(N$10/Control!$C$100)*(J$3-N$3))*Control!$C$101/12,0) | K45: =IF(AND(K$3>=N$3,K$3<N$3+Control!$C$100),(N$10-(N$10/Control!$C$100)*(K$3-N$3))*Control!$C$101/12,0) | L45: =IF(AND(L$3>=N$3,L$3<N$3+Control!$C$100),(N$10-(N$10/Control!$C$100)*(L$3-N$3))*Control!$C$101/12,0) | M45: =IF(AND(M$3>=N$3,M$3<N$3+Control!$C$100),(N$10-(N$10/Control!$C$100)*(M$3-N$3))*Control!$C$101/12,0) | N45: =IF(AND(N$3>=N$3,N$3<N$3+Control!$C$100),(N$10-(N$10/Control!$C$100)*(N$3-N$3))*Control!$C$101/12,0) | O45: =IF(AND(O$3>=N$3,O$3<N$3+Control!$C$100),(N$10-(N$10/Control!$C$100)*(O$3-N$3))*Control!$C$101/12,0)
A46: Origin 12 | B46: =O4 | D46: =IF(AND(D$3>=O$3,D$3<O$3+Control!$C$100),(O$10-(O$10/Control!$C$100)*(D$3-O$3))*Control!$C$101/12,0) | E46: =IF(AND(E$3>=O$3,E$3<O$3+Control!$C$100),(O$10-(O$10/Control!$C$100)*(E$3-O$3))*Control!$C$101/12,0) | F46: =IF(AND(F$3>=O$3,F$3<O$3+Control!$C$100),(O$10-(O$10/Control!$C$100)*(F$3-O$3))*Control!$C$101/12,0) | G46: =IF(AND(G$3>=O$3,G$3<O$3+Control!$C$100),(O$10-(O$10/Control!$C$100)*(G$3-O$3))*Control!$C$101/12,0) | H46: =IF(AND(H$3>=O$3,H$3<O$3+Control!$C$100),(O$10-(O$10/Control!$C$100)*(H$3-O$3))*Control!$C$101/12,0) | I46: =IF(AND(I$3>=O$3,I$3<O$3+Control!$C$100),(O$10-(O$10/Control!$C$100)*(I$3-O$3))*Control!$C$101/12,0) | J46: =IF(AND(J$3>=O$3,J$3<O$3+Control!$C$100),(O$10-(O$10/Control!$C$100)*(J$3-O$3))*Control!$C$101/12,0) | K46: =IF(AND(K$3>=O$3,K$3<O$3+Control!$C$100),(O$10-(O$10/Control!$C$100)*(K$3-O$3))*Control!$C$101/12,0) | L46: =IF(AND(L$3>=O$3,L$3<O$3+Control!$C$100),(O$10-(O$10/Control!$C$100)*(L$3-O$3))*Control!$C$101/12,0) | M46: =IF(AND(M$3>=O$3,M$3<O$3+Control!$C$100),(O$10-(O$10/Control!$C$100)*(M$3-O$3))*Control!$C$101/12,0) | N46: =IF(AND(N$3>=O$3,N$3<O$3+Control!$C$100),(O$10-(O$10/Control!$C$100)*(N$3-O$3))*Control!$C$101/12,0) | O46: =IF(AND(O$3>=O$3,O$3<O$3+Control!$C$100),(O$10-(O$10/Control!$C$100)*(O$3-O$3))*Control!$C$101/12,0)
A48: Commercial note | D48: Attached supplier contract mechanics used in the model: 60% deposit, 40% balance over 6 monthly installments, 6% simple annual interest, EXW delivery, and buyer-borne logistics / insurance.
A49: Transparency note | D49: The attached commercial document itself references M73s hardware, not M7DS. In this model, the financing mechanics are used as the placeholder commercial template, while the selected hardware remains WhatsMiner M7DS per management instruction.

Sheet 12M_EPC_Tranches
A1: 12-Month Electrical EPC Tranches
A2: Uses the Hamar 20MW electrical EPC basis and assumed EPC payment mechanics. Scope note: 6.6kV feeders to 400V container connections, including essential section and DX metering scope.
D3: 1 | E3: 2 | F3: 3 | G3: 4 | H3: 5 | I3: 6 | J3: 7 | K3: 8 | L3: 9 | M3: 10 | N3: 11 | O3: 12
D4: ='12M_Deployment'!D4 | E4: ='12M_Deployment'!E4 | F4: ='12M_Deployment'!F4 | G4: ='12M_Deployment'!G4 | H4: ='12M_Deployment'!H4 | I4: ='12M_Deployment'!I4 | J4: ='12M_Deployment'!J4 | K4: ='12M_Deployment'!K4 | ... O4: ='12M_Deployment'!O4
A5: Gross electrical EPC basis | B5: ZAR'000 | D5: ='12M_Deployment'!D32*CAPEX_Electrical_Detail!$C$26+'12M_Deployment'!D24*CAPEX_Electrical_Detail!$C$27 | E5: ='12M_Deployment'!E32*CAPEX_Electrical_Detail!$C$26+'12M_Deployment'!E24*CAPEX_Electrical_Detail!$C$27 | F5: ='12M_Deployment'!F32*CAPEX_Electrical_Detail!$C$26+'12M_Deployment'!F24*CAPEX_Electrical_Detail!$C$27 | G5: ='12M_Deployment'!G32*CAPEX_Electrical_Detail!$C$26+'12M_Deployment'!G24*CAPEX_Electrical_Detail!$C$27 | H5: ='12M_Deployment'!H32*CAPEX_Electrical_Detail!$C$26+'12M_Deployment'!H24*CAPEX_Electrical_Detail!$C$27 | I5: ='12M_Deployment'!I32*CAPEX_Electrical_Detail!$C$26+'12M_Deployment'!I24*CAPEX_Electrical_Detail!$C$27 | J5: ='12M_Deployment'!J32*CAPEX_Electrical_Detail!$C$26+'12M_Deployment'!J24*CAPEX_Electrical_Detail!$C$27 | K5: ='12M_Deployment'!K32*CAPEX_Electrical_Detail!$C$26+'12M_Deployment'!K24*CAPEX_Electrical_Detail!$C$27 | ... O5: ='12M_Deployment'!O32*CAPEX_Electrical_Detail!$C$26+'12M_Deployment'!O24*CAPEX_Electrical_Detail!$C$27
A6: Deposit cash due | B6: ZAR'000 | D6: =IFERROR(OFFSET(D5,0,Control!$C$102)*Control!$C$103,0) | E6: =IFERROR(OFFSET(E5,0,Control!$C$102)*Control!$C$103,0) | F6: =IFERROR(OFFSET(F5,0,Control!$C$102)*Control!$C$103,0) | G6: =IFERROR(OFFSET(G5,0,Control!$C$102)*Control!$C$103,0) | H6: =IFERROR(OFFSET(H5,0,Control!$C$102)*Control!$C$103,0) | I6: =IFERROR(OFFSET(I5,0,Control!$C$102)*Control!$C$103,0) | J6: =IFERROR(OFFSET(J5,0,Control!$C$102)*Control!$C$103,0) | K6: =IFERROR(OFFSET(K5,0,Control!$C$102)*Control!$C$103,0) | ... O6: =IFERROR(OFFSET(O5,0,Control!$C$102)*Control!$C$103,0)
A7: Procurement / progress payment | B7: ZAR'000 | D7: =IF(Control!$C$102>0,IFERROR(OFFSET(D5,0,Control!$C$102-1)*Control!$C$104,0),0) | E7: =IF(Control!$C$102>0,IFERROR(OFFSET(E5,0,Control!$C$102-1)*Control!$C$104,0),0) | F7: =IF(Control!$C$102>0,IFERROR(OFFSET(F5,0,Control!$C$102-1)*Control!$C$104,0),0) | G7: =IF(Control!$C$102>0,IFERROR(OFFSET(G5,0,Control!$C$102-1)*Control!$C$104,0),0) | H7: =IF(Control!$C$102>0,IFERROR(OFFSET(H5,0,Control!$C$102-1)*Control!$C$104,0),0) | I7: =IF(Control!$C$102>0,IFERROR(OFFSET(I5,0,Control!$C$102-1)*Control!$C$104,0),0) | J7: =IF(Control!$C$102>0,IFERROR(OFFSET(J5,0,Control!$C$102-1)*Control!$C$104,0),0) | K7: =IF(Control!$C$102>0,IFERROR(OFFSET(K5,0,Control!$C$102-1)*Control!$C$104,0),0) | ... O7: =IF(Control!$C$102>0,IFERROR(OFFSET(O5,0,Control!$C$102-1)*Control!$C$104,0),0)
A8: Installation payment | B8: ZAR'000 | D8: =D5*Control!$C$105 | E8: =E5*Control!$C$105 | F8: =F5*Control!$C$105 | G8: =G5*Control!$C$105 | H8: =H5*Control!$C$105 | I8: =I5*Control!$C$105 | J8: =J5*Control!$C$105 | K8: =K5*Control!$C$105 | ... O8: =O5*Control!$C$105
A9: Commissioning / hand-over payment | B9: ZAR'000 | D9: =IF(D$3>1,OFFSET(D5,0,-1)*Control!$C$106,0) | E9: =IF(E$3>1,OFFSET(E5,0,-1)*Control!$C$106,0) | F9: =IF(F$3>1,OFFSET(F5,0,-1)*Control!$C$106,0) | G9: =IF(G$3>1,OFFSET(G5,0,-1)*Control!$C$106,0) | H9: =IF(H$3>1,OFFSET(H5,0,-1)*Control!$C$106,0) | I9: =IF(I$3>1,OFFSET(I5,0,-1)*Control!$C$106,0) | J9: =IF(J$3>1,OFFSET(J5,0,-1)*Control!$C$106,0) | K9: =IF(K$3>1,OFFSET(K5,0,-1)*Control!$C$106,0) | ... O9: =IF(O$3>1,OFFSET(O5,0,-1)*Control!$C$106,0)
A10: Vendor-financed retention originated | B10: ZAR'000 | D10: =D5*Control!$C$107 | E10: =E5*Control!$C$107 | F10: =F5*Control!$C$107 | G10: =G5*Control!$C$107 | H10: =H5*Control!$C$107 | I10: =I5*Control!$C$107 | J10: =J5*Control!$C$107 | K10: =K5*Control!$C$107 | ... O10: =O5*Control!$C$107
A11: Opening EPC payable | B11: ZAR'000 | D11: =0 | E11: =D15 | F11: =E15 | G11: =F15 | H11: =G15 | I11: =H15 | J11: =I15 | K11: =J15 | L11: =K15 | ... O11: =N15
A12: Scheduled principal | B12: ZAR'000 | D12: =SUM(D20:D31) | E12: =SUM(E20:E31) | F12: =SUM(F20:F31) | G12: =SUM(G20:G31) | H12: =SUM(H20:H31) | I12: =SUM(I20:I31) | J12: =SUM(J20:J31) | K12: =SUM(K20:K31) | ... O12: =SUM(O20:O31)
A13: Scheduled interest | B13: ZAR'000 | D13: =SUM(D35:D46) | E13: =SUM(E35:E46) | F13: =SUM(F35:F46) | G13: =SUM(G35:G46) | H13: =SUM(H35:H46) | I13: =SUM(I35:I46) | J13: =SUM(J35:J46) | K13: =SUM(K35:K46) | ... O13: =SUM(O35:O46)
A14: Total EPC cash payment | B14: ZAR'000 | D14: =D6+D7+D8+D9+D12+D13 | E14: =E6+E7+E8+E9+E12+E13 | F14: =F6+F7+F8+F9+F12+F13 | G14: =G6+G7+G8+G9+G12+G13 | H14: =H6+H7+H8+H9+H12+H13 | I14: =I6+I7+I8+I9+I12+I13 | J14: =J6+J7+J8+J9+J12+J13 | K14: =K6+K7+K8+K9+K12+K13 | ... O14: =O6+O7+O8+O9+O12+O13
A15: Closing EPC payable | B15: ZAR'000 | D15: =D11+D10-D12 | E15: =E11+E10-E12 | F15: =F11+F10-F12 | G15: =G11+G10-G12 | H15: =H11+H10-H12 | I15: =I11+I10-I12 | J15: =J11+J10-J12 | K15: =K11+K10-K12 | ... O15: =O11+O10-O12
A17: Principal by origination month
A18: Origin month | B18: Source tranche | D18: Month 1 | E18: Month 2 | F18: Month 3 | G18: Month 4 | H18: Month 5 | I18: Month 6 | J18: Month 7 | K18: Month 8 | L18: Month 9 | M18: Month 10 | N18: Month 11 | O18: Month 12
A20: Origin 1 | B20: =D4 | D20: =IF(AND(D$3>D$3,D$3<=D$3+Control!$C$108),D$10/Control!$C$108,0) | E20: =IF(AND(E$3>D$3,E$3<=D$3+Control!$C$108),D$10/Control!$C$108,0) | F20: =IF(AND(F$3>D$3,F$3<=D$3+Control!$C$108),D$10/Control!$C$108,0) | G20: =IF(AND(G$3>D$3,G$3<=D$3+Control!$C$108),D$10/Control!$C$108,0) | H20: =IF(AND(H$3>D$3,H$3<=D$3+Control!$C$108),D$10/Control!$C$108,0) | I20: =IF(AND(I$3>D$3,I$3<=D$3+Control!$C$108),D$10/Control!$C$108,0) | J20: =IF(AND(J$3>D$3,J$3<=D$3+Control!$C$108),D$10/Control!$C$108,0) | K20: =IF(AND(K$3>D$3,K$3<=D$3+Control!$C$108),D$10/Control!$C$108,0) | L20: =IF(AND(L$3>D$3,L$3<=D$3+Control!$C$108),D$10/Control!$C$108,0) | M20: =IF(AND(M$3>D$3,M$3<=D$3+Control!$C$108),D$10/Control!$C$108,0) | N20: =IF(AND(N$3>D$3,N$3<=D$3+Control!$C$108),D$10/Control!$C$108,0) | O20: =IF(AND(O$3>D$3,O$3<=D$3+Control!$C$108),D$10/Control!$C$108,0)
A21: Origin 2 | B21: =E4 | D21: =IF(AND(D$3>E$3,D$3<=E$3+Control!$C$108),E$10/Control!$C$108,0) | E21: =IF(AND(E$3>E$3,E$3<=E$3+Control!$C$108),E$10/Control!$C$108,0) | F21: =IF(AND(F$3>E$3,F$3<=E$3+Control!$C$108),E$10/Control!$C$108,0) | G21: =IF(AND(G$3>E$3,G$3<=E$3+Control!$C$108),E$10/Control!$C$108,0) | H21: =IF(AND(H$3>E$3,H$3<=E$3+Control!$C$108),E$10/Control!$C$108,0) | I21: =IF(AND(I$3>E$3,I$3<=E$3+Control!$C$108),E$10/Control!$C$108,0) | J21: =IF(AND(J$3>E$3,J$3<=E$3+Control!$C$108),E$10/Control!$C$108,0) | K21: =IF(AND(K$3>E$3,K$3<=E$3+Control!$C$108),E$10/Control!$C$108,0) | L21: =IF(AND(L$3>E$3,L$3<=E$3+Control!$C$108),E$10/Control!$C$108,0) | M21: =IF(AND(M$3>E$3,M$3<=E$3+Control!$C$108),E$10/Control!$C$108,0) | N21: =IF(AND(N$3>E$3,N$3<=E$3+Control!$C$108),E$10/Control!$C$108,0) | O21: =IF(AND(O$3>E$3,O$3<=E$3+Control!$C$108),E$10/Control!$C$108,0)
A22: Origin 3 | B22: =F4 | D22: =IF(AND(D$3>F$3,D$3<=F$3+Control!$C$108),F$10/Control!$C$108,0) | E22: =IF(AND(E$3>F$3,E$3<=F$3+Control!$C$108),F$10/Control!$C$108,0) | F22: =IF(AND(F$3>F$3,F$3<=F$3+Control!$C$108),F$10/Control!$C$108,0) | G22: =IF(AND(G$3>F$3,G$3<=F$3+Control!$C$108),F$10/Control!$C$108,0) | H22: =IF(AND(H$3>F$3,H$3<=F$3+Control!$C$108),F$10/Control!$C$108,0) | I22: =IF(AND(I$3>F$3,I$3<=F$3+Control!$C$108),F$10/Control!$C$108,0) | J22: =IF(AND(J$3>F$3,J$3<=F$3+Control!$C$108),F$10/Control!$C$108,0) | K22: =IF(AND(K$3>F$3,K$3<=F$3+Control!$C$108),F$10/Control!$C$108,0) | L22: =IF(AND(L$3>F$3,L$3<=F$3+Control!$C$108),F$10/Control!$C$108,0) | M22: =IF(AND(M$3>F$3,M$3<=F$3+Control!$C$108),F$10/Control!$C$108,0) | N22: =IF(AND(N$3>F$3,N$3<=F$3+Control!$C$108),F$10/Control!$C$108,0) | O22: =IF(AND(O$3>F$3,O$3<=F$3+Control!$C$108),F$10/Control!$C$108,0)
A23: Origin 4 | B23: =G4 | D23: =IF(AND(D$3>G$3,D$3<=G$3+Control!$C$108),G$10/Control!$C$108,0) | E23: =IF(AND(E$3>G$3,E$3<=G$3+Control!$C$108),G$10/Control!$C$108,0) | F23: =IF(AND(F$3>G$3,F$3<=G$3+Control!$C$108),G$10/Control!$C$108,0) | G23: =IF(AND(G$3>G$3,G$3<=G$3+Control!$C$108),G$10/Control!$C$108,0) | H23: =IF(AND(H$3>G$3,H$3<=G$3+Control!$C$108),G$10/Control!$C$108,0) | I23: =IF(AND(I$3>G$3,I$3<=G$3+Control!$C$108),G$10/Control!$C$108,0) | J23: =IF(AND(J$3>G$3,J$3<=G$3+Control!$C$108),G$10/Control!$C$108,0) | K23: =IF(AND(K$3>G$3,K$3<=G$3+Control!$C$108),G$10/Control!$C$108,0) | L23: =IF(AND(L$3>G$3,L$3<=G$3+Control!$C$108),G$10/Control!$C$108,0) | M23: =IF(AND(M$3>G$3,M$3<=G$3+Control!$C$108),G$10/Control!$C$108,0) | N23: =IF(AND(N$3>G$3,N$3<=G$3+Control!$C$108),G$10/Control!$C$108,0) | O23: =IF(AND(O$3>G$3,O$3<=G$3+Control!$C$108),G$10/Control!$C$108,0)
A24: Origin 5 | B24: =H4 | D24: =IF(AND(D$3>H$3,D$3<=H$3+Control!$C$108),H$10/Control!$C$108,0) | E24: =IF(AND(E$3>H$3,E$3<=H$3+Control!$C$108),H$10/Control!$C$108,0) | F24: =IF(AND(F$3>H$3,F$3<=H$3+Control!$C$108),H$10/Control!$C$108,0) | G24: =IF(AND(G$3>H$3,G$3<=H$3+Control!$C$108),H$10/Control!$C$108,0) | H24: =IF(AND(H$3>H$3,H$3<=H$3+Control!$C$108),H$10/Control!$C$108,0) | I24: =IF(AND(I$3>H$3,I$3<=H$3+Control!$C$108),H$10/Control!$C$108,0) | J24: =IF(AND(J$3>H$3,J$3<=H$3+Control!$C$108),H$10/Control!$C$108,0) | K24: =IF(AND(K$3>H$3,K$3<=H$3+Control!$C$108),H$10/Control!$C$108,0) | L24: =IF(AND(L$3>H$3,L$3<=H$3+Control!$C$108),H$10/Control!$C$108,0) | M24: =IF(AND(M$3>H$3,M$3<=H$3+Control!$C$108),H$10/Control!$C$108,0) | N24: =IF(AND(N$3>H$3,N$3<=H$3+Control!$C$108),H$10/Control!$C$108,0) | O24: =IF(AND(O$3>H$3,O$3<=H$3+Control!$C$108),H$10/Control!$C$108,0)
A25: Origin 6 | B25: =I4 | D25: =IF(AND(D$3>I$3,D$3<=I$3+Control!$C$108),I$10/Control!$C$108,0) | E25: =IF(AND(E$3>I$3,E$3<=I$3+Control!$C$108),I$10/Control!$C$108,0) | F25: =IF(AND(F$3>I$3,F$3<=I$3+Control!$C$108),I$10/Control!$C$108,0) | G25: =IF(AND(G$3>I$3,G$3<=I$3+Control!$C$108),I$10/Control!$C$108,0) | H25: =IF(AND(H$3>I$3,H$3<=I$3+Control!$C$108),I$10/Control!$C$108,0) | I25: =IF(AND(I$3>I$3,I$3<=I$3+Control!$C$108),I$10/Control!$C$108,0) | J25: =IF(AND(J$3>I$3,J$3<=I$3+Control!$C$108),I$10/Control!$C$108,0) | K25: =IF(AND(K$3>I$3,K$3<=I$3+Control!$C$108),I$10/Control!$C$108,0) | L25: =IF(AND(L$3>I$3,L$3<=I$3+Control!$C$108),I$10/Control!$C$108,0) | M25: =IF(AND(M$3>I$3,M$3<=I$3+Control!$C$108),I$10/Control!$C$108,0) | N25: =IF(AND(N$3>I$3,N$3<=I$3+Control!$C$108),I$10/Control!$C$108,0) | O25: =IF(AND(O$3>I$3,O$3<=I$3+Control!$C$108),I$10/Control!$C$108,0)
A26: Origin 7 | B26: =J4 | D26: =IF(AND(D$3>J$3,D$3<=J$3+Control!$C$108),J$10/Control!$C$108,0) | E26: =IF(AND(E$3>J$3,E$3<=J$3+Control!$C$108),J$10/Control!$C$108,0) | F26: =IF(AND(F$3>J$3,F$3<=J$3+Control!$C$108),J$10/Control!$C$108,0) | G26: =IF(AND(G$3>J$3,G$3<=J$3+Control!$C$108),J$10/Control!$C$108,0) | H26: =IF(AND(H$3>J$3,H$3<=J$3+Control!$C$108),J$10/Control!$C$108,0) | I26: =IF(AND(I$3>J$3,I$3<=J$3+Control!$C$108),J$10/Control!$C$108,0) | J26: =IF(AND(J$3>J$3,J$3<=J$3+Control!$C$108),J$10/Control!$C$108,0) | K26: =IF(AND(K$3>J$3,K$3<=J$3+Control!$C$108),J$10/Control!$C$108,0) | L26: =IF(AND(L$3>J$3,L$3<=J$3+Control!$C$108),J$10/Control!$C$108,0) | M26: =IF(AND(M$3>J$3,M$3<=J$3+Control!$C$108),J$10/Control!$C$108,0) | N26: =IF(AND(N$3>J$3,N$3<=J$3+Control!$C$108),J$10/Control!$C$108,0) | O26: =IF(AND(O$3>J$3,O$3<=J$3+Control!$C$108),J$10/Control!$C$108,0)
A27: Origin 8 | B27: =K4 | D27: =IF(AND(D$3>K$3,D$3<=K$3+Control!$C$108),K$10/Control!$C$108,0) | E27: =IF(AND(E$3>K$3,E$3<=K$3+Control!$C$108),K$10/Control!$C$108,0) | F27: =IF(AND(F$3>K$3,F$3<=K$3+Control!$C$108),K$10/Control!$C$108,0) | G27: =IF(AND(G$3>K$3,G$3<=K$3+Control!$C$108),K$10/Control!$C$108,0) | H27: =IF(AND(H$3>K$3,H$3<=K$3+Control!$C$108),K$10/Control!$C$108,0) | I27: =IF(AND(I$3>K$3,I$3<=K$3+Control!$C$108),K$10/Control!$C$108,0) | J27: =IF(AND(J$3>K$3,J$3<=K$3+Control!$C$108),K$10/Control!$C$108,0) | K27: =IF(AND(K$3>K$3,K$3<=K$3+Control!$C$108),K$10/Control!$C$108,0) | L27: =IF(AND(L$3>K$3,L$3<=K$3+Control!$C$108),K$10/Control!$C$108,0) | M27: =IF(AND(M$3>K$3,M$3<=K$3+Control!$C$108),K$10/Control!$C$108,0) | N27: =IF(AND(N$3>K$3,N$3<=K$3+Control!$C$108),K$10/Control!$C$108,0) | O27: =IF(AND(O$3>K$3,O$3<=K$3+Control!$C$108),K$10/Control!$C$108,0)
A28: Origin 9 | B28: =L4 | D28: =IF(AND(D$3>L$3,D$3<=L$3+Control!$C$108),L$10/Control!$C$108,0) | E28: =IF(AND(E$3>L$3,E$3<=L$3+Control!$C$108),L$10/Control!$C$108,0) | F28: =IF(AND(F$3>L$3,F$3<=L$3+Control!$C$108),L$10/Control!$C$108,0) | G28: =IF(AND(G$3>L$3,G$3<=L$3+Control!$C$108),L$10/Control!$C$108,0) | H28: =IF(AND(H$3>L$3,H$3<=L$3+Control!$C$108),L$10/Control!$C$108,0) | I28: =IF(AND(I$3>L$3,I$3<=L$3+Control!$C$108),L$10/Control!$C$108,0) | J28: =IF(AND(J$3>L$3,J$3<=L$3+Control!$C$108),L$10/Control!$C$108,0) | K28: =IF(AND(K$3>L$3,K$3<=L$3+Control!$C$108),L$10/Control!$C$108,0) | L28: =IF(AND(L$3>L$3,L$3<=L$3+Control!$C$108),L$10/Control!$C$108,0) | M28: =IF(AND(M$3>L$3,M$3<=L$3+Control!$C$108),L$10/Control!$C$108,0) | N28: =IF(AND(N$3>L$3,N$3<=L$3+Control!$C$108),L$10/Control!$C$108,0) | O28: =IF(AND(O$3>L$3,O$3<=L$3+Control!$C$108),L$10/Control!$C$108,0)
A29: Origin 10 | B29: =M4 | D29: =IF(AND(D$3>M$3,D$3<=M$3+Control!$C$108),M$10/Control!$C$108,0) | E29: =IF(AND(E$3>M$3,E$3<=M$3+Control!$C$108),M$10/Control!$C$108,0) | F29: =IF(AND(F$3>M$3,F$3<=M$3+Control!$C$108),M$10/Control!$C$108,0) | G29: =IF(AND(G$3>M$3,G$3<=M$3+Control!$C$108),M$10/Control!$C$108,0) | H29: =IF(AND(H$3>M$3,H$3<=M$3+Control!$C$108),M$10/Control!$C$108,0) | I29: =IF(AND(I$3>M$3,I$3<=M$3+Control!$C$108),M$10/Control!$C$108,0) | J29: =IF(AND(J$3>M$3,J$3<=M$3+Control!$C$108),M$10/Control!$C$108,0) | K29: =IF(AND(K$3>M$3,K$3<=M$3+Control!$C$108),M$10/Control!$C$108,0) | L29: =IF(AND(L$3>M$3,L$3<=M$3+Control!$C$108),M$10/Control!$C$108,0) | M29: =IF(AND(M$3>M$3,M$3<=M$3+Control!$C$108),M$10/Control!$C$108,0) | N29: =IF(AND(N$3>M$3,N$3<=M$3+Control!$C$108),M$10/Control!$C$108,0) | O29: =IF(AND(O$3>M$3,O$3<=M$3+Control!$C$108),M$10/Control!$C$108,0)
A30: Origin 11 | B30: =N4 | D30: =IF(AND(D$3>N$3,D$3<=N$3+Control!$C$108),N$10/Control!$C$108,0) | E30: =IF(AND(E$3>N$3,E$3<=N$3+Control!$C$108),N$10/Control!$C$108,0) | F30: =IF(AND(F$3>N$3,F$3<=N$3+Control!$C$108),N$10/Control!$C$108,0) | G30: =IF(AND(G$3>N$3,G$3<=N$3+Control!$C$108),N$10/Control!$C$108,0) | H30: =IF(AND(H$3>N$3,H$3<=N$3+Control!$C$108),N$10/Control!$C$108,0) | I30: =IF(AND(I$3>N$3,I$3<=N$3+Control!$C$108),N$10/Control!$C$108,0) | J30: =IF(AND(J$3>N$3,J$3<=N$3+Control!$C$108),N$10/Control!$C$108,0) | K30: =IF(AND(K$3>N$3,K$3<=N$3+Control!$C$108),N$10/Control!$C$108,0) | L30: =IF(AND(L$3>N$3,L$3<=N$3+Control!$C$108),N$10/Control!$C$108,0) | M30: =IF(AND(M$3>N$3,M$3<=N$3+Control!$C$108),N$10/Control!$C$108,0) | N30: =IF(AND(N$3>N$3,N$3<=N$3+Control!$C$108),N$10/Control!$C$108,0) | O30: =IF(AND(O$3>N$3,O$3<=N$3+Control!$C$108),N$10/Control!$C$108,0)
A31: Origin 12 | B31: =O4 | D31: =IF(AND(D$3>O$3,D$3<=O$3+Control!$C$108),O$10/Control!$C$108,0) | E31: =IF(AND(E$3>O$3,E$3<=O$3+Control!$C$108),O$10/Control!$C$108,0) | F31: =IF(AND(F$3>O$3,F$3<=O$3+Control!$C$108),O$10/Control!$C$108,0) | G31: =IF(AND(G$3>O$3,G$3<=O$3+Control!$C$108),O$10/Control!$C$108,0) | H31: =IF(AND(H$3>O$3,H$3<=O$3+Control!$C$108),O$10/Control!$C$108,0) | I31: =IF(AND(I$3>O$3,I$3<=O$3+Control!$C$108),O$10/Control!$C$108,0) | J31: =IF(AND(J$3>O$3,J$3<=O$3+Control!$C$108),O$10/Control!$C$108,0) | K31: =IF(AND(K$3>O$3,K$3<=O$3+Control!$C$108),O$10/Control!$C$108,0) | L31: =IF(AND(L$3>O$3,L$3<=O$3+Control!$C$108),O$10/Control!$C$108,0) | M31: =IF(AND(M$3>O$3,M$3<=O$3+Control!$C$108),O$10/Control!$C$108,0) | N31: =IF(AND(N$3>O$3,N$3<=O$3+Control!$C$108),O$10/Control!$C$108,0) | O31: =IF(AND(O$3>O$3,O$3<=O$3+Control!$C$108),O$10/Control!$C$108,0)
A33: Interest by origination month
A34: Origin month | B34: Source tranche | D34: Month 1 | E34: Month 2 | F34: Month 3 | G34: Month 4 | H34: Month 5 | I34: Month 6 | J34: Month 7 | K34: Month 8 | L34: Month 9 | M34: Month 10 | N34: Month 11 | O34: Month 12
A35: Origin 1 | B35: =D4 | D35: =IF(AND(D$3>D$3,D$3<=D$3+Control!$C$108),(D$10-(D$10/Control!$C$108)*(D$3-D$3-1))*Control!$C$109/12,0) | E35: =IF(AND(E$3>D$3,E$3<=D$3+Control!$C$108),(D$10-(D$10/Control!$C$108)*(E$3-D$3-1))*Control!$C$109/12,0) | F35: =IF(AND(F$3>D$3,F$3<=D$3+Control!$C$108),(D$10-(D$10/Control!$C$108)*(F$3-D$3-1))*Control!$C$109/12,0) | G35: =IF(AND(G$3>D$3,G$3<=D$3+Control!$C$108),(D$10-(D$10/Control!$C$108)*(G$3-D$3-1))*Control!$C$109/12,0) | H35: =IF(AND(H$3>D$3,H$3<=D$3+Control!$C$108),(D$10-(D$10/Control!$C$108)*(H$3-D$3-1))*Control!$C$109/12,0) | I35: =IF(AND(I$3>D$3,I$3<=D$3+Control!$C$108),(D$10-(D$10/Control!$C$108)*(I$3-D$3-1))*Control!$C$109/12,0) | J35: =IF(AND(J$3>D$3,J$3<=D$3+Control!$C$108),(D$10-(D$10/Control!$C$108)*(J$3-D$3-1))*Control!$C$109/12,0) | K35: =IF(AND(K$3>D$3,K$3<=D$3+Control!$C$108),(D$10-(D$10/Control!$C$108)*(K$3-D$3-1))*Control!$C$109/12,0) | L35: =IF(AND(L$3>D$3,L$3<=D$3+Control!$C$108),(D$10-(D$10/Control!$C$108)*(L$3-D$3-1))*Control!$C$109/12,0) | M35: =IF(AND(M$3>D$3,M$3<=D$3+Control!$C$108),(D$10-(D$10/Control!$C$108)*(M$3-D$3-1))*Control!$C$109/12,0) | N35: =IF(AND(N$3>D$3,N$3<=D$3+Control!$C$108),(D$10-(D$10/Control!$C$108)*(N$3-D$3-1))*Control!$C$109/12,0) | O35: =IF(AND(O$3>D$3,O$3<=D$3+Control!$C$108),(D$10-(D$10/Control!$C$108)*(O$3-D$3-1))*Control!$C$109/12,0)
A36: Origin 2 | B36: =E4 | D36: =IF(AND(D$3>E$3,D$3<=E$3+Control!$C$108),(E$10-(E$10/Control!$C$108)*(D$3-E$3-1))*Control!$C$109/12,0) | E36: =IF(AND(E$3>E$3,E$3<=E$3+Control!$C$108),(E$10-(E$10/Control!$C$108)*(E$3-E$3-1))*Control!$C$109/12,0) | F36: =IF(AND(F$3>E$3,F$3<=E$3+Control!$C$108),(E$10-(E$10/Control!$C$108)*(F$3-E$3-1))*Control!$C$109/12,0) | G36: =IF(AND(G$3>E$3,G$3<=E$3+Control!$C$108),(E$10-(E$10/Control!$C$108)*(G$3-E$3-1))*Control!$C$109/12,0) | H36: =IF(AND(H$3>E$3,H$3<=E$3+Control!$C$108),(E$10-(E$10/Control!$C$108)*(H$3-E$3-1))*Control!$C$109/12,0) | I36: =IF(AND(I$3>E$3,I$3<=E$3+Control!$C$108),(E$10-(E$10/Control!$C$108)*(I$3-E$3-1))*Control!$C$109/12,0) | J36: =IF(AND(J$3>E$3,J$3<=E$3+Control!$C$108),(E$10-(E$10/Control!$C$108)*(J$3-E$3-1))*Control!$C$109/12,0) | K36: =IF(AND(K$3>E$3,K$3<=E$3+Control!$C$108),(E$10-(E$10/Control!$C$108)*(K$3-E$3-1))*Control!$C$109/12,0) | L36: =IF(AND(L$3>E$3,L$3<=E$3+Control!$C$108),(E$10-(E$10/Control!$C$108)*(L$3-E$3-1))*Control!$C$109/12,0) | M36: =IF(AND(M$3>E$3,M$3<=E$3+Control!$C$108),(E$10-(E$10/Control!$C$108)*(M$3-E$3-1))*Control!$C$109/12,0) | N36: =IF(AND(N$3>E$3,N$3<=E$3+Control!$C$108),(E$10-(E$10/Control!$C$108)*(N$3-E$3-1))*Control!$C$109/12,0) | O36: =IF(AND(O$3>E$3,O$3<=E$3+Control!$C$108),(E$10-(E$10/Control!$C$108)*(O$3-E$3-1))*Control!$C$109/12,0)
A37: Origin 3 | B37: =F4 | D37: =IF(AND(D$3>F$3,D$3<=F$3+Control!$C$108),(F$10-(F$10/Control!$C$108)*(D$3-F$3-1))*Control!$C$109/12,0) | E37: =IF(AND(E$3>F$3,E$3<=F$3+Control!$C$108),(F$10-(F$10/Control!$C$108)*(E$3-F$3-1))*Control!$C$109/12,0) | F37: =IF(AND(F$3>F$3,F$3<=F$3+Control!$C$108),(F$10-(F$10/Control!$C$108)*(F$3-F$3-1))*Control!$C$109/12,0) | G37: =IF(AND(G$3>F$3,G$3<=F$3+Control!$C$108),(F$10-(F$10/Control!$C$108)*(G$3-F$3-1))*Control!$C$109/12,0) | H37: =IF(AND(H$3>F$3,H$3<=F$3+Control!$C$108),(F$10-(F$10/Control!$C$108)*(H$3-F$3-1))*Control!$C$109/12,0) | I37: =IF(AND(I$3>F$3,I$3<=F$3+Control!$C$108),(F$10-(F$10/Control!$C$108)*(I$3-F$3-1))*Control!$C$109/12,0) | J37: =IF(AND(J$3>F$3,J$3<=F$3+Control!$C$108),(F$10-(F$10/Control!$C$108)*(J$3-F$3-1))*Control!$C$109/12,0) | K37: =IF(AND(K$3>F$3,K$3<=F$3+Control!$C$108),(F$10-(F$10/Control!$C$108)*(K$3-F$3-1))*Control!$C$109/12,0) | L37: =IF(AND(L$3>F$3,L$3<=F$3+Control!$C$108),(F$10-(F$10/Control!$C$108)*(L$3-F$3-1))*Control!$C$109/12,0) | M37: =IF(AND(M$3>F$3,M$3<=F$3+Control!$C$108),(F$10-(F$10/Control!$C$108)*(M$3-F$3-1))*Control!$C$109/12,0) | N37: =IF(AND(N$3>F$3,N$3<=F$3+Control!$C$108),(F$10-(F$10/Control!$C$108)*(N$3-F$3-1))*Control!$C$109/12,0) | O37: =IF(AND(O$3>F$3,O$3<=F$3+Control!$C$108),(F$10-(F$10/Control!$C$108)*(O$3-F$3-1))*Control!$C$109/12,0)
A38: Origin 4 | B38: =G4 | D38: =IF(AND(D$3>G$3,D$3<=G$3+Control!$C$108),(G$10-(G$10/Control!$C$108)*(D$3-G$3-1))*Control!$C$109/12,0) | E38: =IF(AND(E$3>G$3,E$3<=G$3+Control!$C$108),(G$10-(G$10/Control!$C$108)*(E$3-G$3-1))*Control!$C$109/12,0) | F38: =IF(AND(F$3>G$3,F$3<=G$3+Control!$C$108),(G$10-(G$10/Control!$C$108)*(F$3-G$3-1))*Control!$C$109/12,0) | G38: =IF(AND(G$3>G$3,G$3<=G$3+Control!$C$108),(G$10-(G$10/Control!$C$108)*(G$3-G$3-1))*Control!$C$109/12,0) | H38: =IF(AND(H$3>G$3,H$3<=G$3+Control!$C$108),(G$10-(G$10/Control!$C$108)*(H$3-G$3-1))*Control!$C$109/12,0) | I38: =IF(AND(I$3>G$3,I$3<=G$3+Control!$C$108),(G$10-(G$10/Control!$C$108)*(I$3-G$3-1))*Control!$C$109/12,0) | J38: =IF(AND(J$3>G$3,J$3<=G$3+Control!$C$108),(G$10-(G$10/Control!$C$108)*(J$3-G$3-1))*Control!$C$109/12,0) | K38: =IF(AND(K$3>G$3,K$3<=G$3+Control!$C$108),(G$10-(G$10/Control!$C$108)*(K$3-G$3-1))*Control!$C$109/12,0) | L38: =IF(AND(L$3>G$3,L$3<=G$3+Control!$C$108),(G$10-(G$10/Control!$C$108)*(L$3-G$3-1))*Control!$C$109/12,0) | M38: =IF(AND(M$3>G$3,M$3<=G$3+Control!$C$108),(G$10-(G$10/Control!$C$108)*(M$3-G$3-1))*Control!$C$109/12,0) | N38: =IF(AND(N$3>G$3,N$3<=G$3+Control!$C$108),(G$10-(G$10/Control!$C$108)*(N$3-G$3-1))*Control!$C$109/12,0) | O38: =IF(AND(O$3>G$3,O$3<=G$3+Control!$C$108),(G$10-(G$10/Control!$C$108)*(O$3-G$3-1))*Control!$C$109/12,0)
A39: Origin 5 | B39: =H4 | D39: =IF(AND(D$3>H$3,D$3<=H$3+Control!$C$108),(H$10-(H$10/Control!$C$108)*(D$3-H$3-1))*Control!$C$109/12,0) | E39: =IF(AND(E$3>H$3,E$3<=H$3+Control!$C$108),(H$10-(H$10/Control!$C$108)*(E$3-H$3-1))*Control!$C$109/12,0) | F39: =IF(AND(F$3>H$3,F$3<=H$3+Control!$C$108),(H$10-(H$10/Control!$C$108)*(F$3-H$3-1))*Control!$C$109/12,0) | G39: =IF(AND(G$3>H$3,G$3<=H$3+Control!$C$108),(H$10-(H$10/Control!$C$108)*(G$3-H$3-1))*Control!$C$109/12,0) | H39: =IF(AND(H$3>H$3,H$3<=H$3+Control!$C$108),(H$10-(H$10/Control!$C$108)*(H$3-H$3-1))*Control!$C$109/12,0) | I39: =IF(AND(I$3>H$3,I$3<=H$3+Control!$C$108),(H$10-(H$10/Control!$C$108)*(I$3-H$3-1))*Control!$C$109/12,0) | J39: =IF(AND(J$3>H$3,J$3<=H$3+Control!$C$108),(H$10-(H$10/Control!$C$108)*(J$3-H$3-1))*Control!$C$109/12,0) | K39: =IF(AND(K$3>H$3,K$3<=H$3+Control!$C$108),(H$10-(H$10/Control!$C$108)*(K$3-H$3-1))*Control!$C$109/12,0) | L39: =IF(AND(L$3>H$3,L$3<=H$3+Control!$C$108),(H$10-(H$10/Control!$C$108)*(L$3-H$3-1))*Control!$C$109/12,0) | M39: =IF(AND(M$3>H$3,M$3<=H$3+Control!$C$108),(H$10-(H$10/Control!$C$108)*(M$3-H$3-1))*Control!$C$109/12,0) | N39: =IF(AND(N$3>H$3,N$3<=H$3+Control!$C$108),(H$10-(H$10/Control!$C$108)*(N$3-H$3-1))*Control!$C$109/12,0) | O39: =IF(AND(O$3>H$3,O$3<=H$3+Control!$C$108),(H$10-(H$10/Control!$C$108)*(O$3-H$3-1))*Control!$C$109/12,0)
A40: Origin 6 | B40: =I4 | D40: =IF(AND(D$3>I$3,D$3<=I$3+Control!$C$108),(I$10-(I$10/Control!$C$108)*(D$3-I$3-1))*Control!$C$109/12,0) | E40: =IF(AND(E$3>I$3,E$3<=I$3+Control!$C$108),(I$10-(I$10/Control!$C$108)*(E$3-I$3-1))*Control!$C$109/12,0) | F40: =IF(AND(F$3>I$3,F$3<=I$3+Control!$C$108),(I$10-(I$10/Control!$C$108)*(F$3-I$3-1))*Control!$C$109/12,0) | G40: =IF(AND(G$3>I$3,G$3<=I$3+Control!$C$108),(I$10-(I$10/Control!$C$108)*(G$3-I$3-1))*Control!$C$109/12,0) | H40: =IF(AND(H$3>I$3,H$3<=I$3+Control!$C$108),(I$10-(I$10/Control!$C$108)*(H$3-I$3-1))*Control!$C$109/12,0) | I40: =IF(AND(I$3>I$3,I$3<=I$3+Control!$C$108),(I$10-(I$10/Control!$C$108)*(I$3-I$3-1))*Control!$C$109/12,0) | J40: =IF(AND(J$3>I$3,J$3<=I$3+Control!$C$108),(I$10-(I$10/Control!$C$108)*(J$3-I$3-1))*Control!$C$109/12,0) | K40: =IF(AND(K$3>I$3,K$3<=I$3+Control!$C$108),(I$10-(I$10/Control!$C$108)*(K$3-I$3-1))*Control!$C$109/12,0) | L40: =IF(AND(L$3>I$3,L$3<=I$3+Control!$C$108),(I$10-(I$10/Control!$C$108)*(L$3-I$3-1))*Control!$C$109/12,0) | M40: =IF(AND(M$3>I$3,M$3<=I$3+Control!$C$108),(I$10-(I$10/Control!$C$108)*(M$3-I$3-1))*Control!$C$109/12,0) | N40: =IF(AND(N$3>I$3,N$3<=I$3+Control!$C$108),(I$10-(I$10/Control!$C$108)*(N$3-I$3-1))*Control!$C$109/12,0) | O40: =IF(AND(O$3>I$3,O$3<=I$3+Control!$C$108),(I$10-(I$10/Control!$C$108)*(O$3-I$3-1))*Control!$C$109/12,0)
A41: Origin 7 | B41: =J4 | D41: =IF(AND(D$3>J$3,D$3<=J$3+Control!$C$108),(J$10-(J$10/Control!$C$108)*(D$3-J$3-1))*Control!$C$109/12,0) | E41: =IF(AND(E$3>J$3,E$3<=J$3+Control!$C$108),(J$10-(J$10/Control!$C$108)*(E$3-J$3-1))*Control!$C$109/12,0) | F41: =IF(AND(F$3>J$3,F$3<=J$3+Control!$C$108),(J$10-(J$10/Control!$C$108)*(F$3-J$3-1))*Control!$C$109/12,0) | G41: =IF(AND(G$3>J$3,G$3<=J$3+Control!$C$108),(J$10-(J$10/Control!$C$108)*(G$3-J$3-1))*Control!$C$109/12,0) | H41: =IF(AND(H$3>J$3,H$3<=J$3+Control!$C$108),(J$10-(J$10/Control!$C$108)*(H$3-J$3-1))*Control!$C$109/12,0) | I41: =IF(AND(I$3>J$3,I$3<=J$3+Control!$C$108),(J$10-(J$10/Control!$C$108)*(I$3-J$3-1))*Control!$C$109/12,0) | J41: =IF(AND(J$3>J$3,J$3<=J$3+Control!$C$108),(J$10-(J$10/Control!$C$108)*(J$3-J$3-1))*Control!$C$109/12,0) | K41: =IF(AND(K$3>J$3,K$3<=J$3+Control!$C$108),(J$10-(J$10/Control!$C$108)*(K$3-J$3-1))*Control!$C$109/12,0) | L41: =IF(AND(L$3>J$3,L$3<=J$3+Control!$C$108),(J$10-(J$10/Control!$C$108)*(L$3-J$3-1))*Control!$C$109/12,0) | M41: =IF(AND(M$3>J$3,M$3<=J$3+Control!$C$108),(J$10-(J$10/Control!$C$108)*(M$3-J$3-1))*Control!$C$109/12,0) | N41: =IF(AND(N$3>J$3,N$3<=J$3+Control!$C$108),(J$10-(J$10/Control!$C$108)*(N$3-J$3-1))*Control!$C$109/12,0) | O41: =IF(AND(O$3>J$3,O$3<=J$3+Control!$C$108),(J$10-(J$10/Control!$C$108)*(O$3-J$3-1))*Control!$C$109/12,0)
A42: Origin 8 | B42: =K4 | D42: =IF(AND(D$3>K$3,D$3<=K$3+Control!$C$108),(K$10-(K$10/Control!$C$108)*(D$3-K$3-1))*Control!$C$109/12,0) | E42: =IF(AND(E$3>K$3,E$3<=K$3+Control!$C$108),(K$10-(K$10/Control!$C$108)*(E$3-K$3-1))*Control!$C$109/12,0) | F42: =IF(AND(F$3>K$3,F$3<=K$3+Control!$C$108),(K$10-(K$10/Control!$C$108)*(F$3-K$3-1))*Control!$C$109/12,0) | G42: =IF(AND(G$3>K$3,G$3<=K$3+Control!$C$108),(K$10-(K$10/Control!$C$108)*(G$3-K$3-1))*Control!$C$109/12,0) | H42: =IF(AND(H$3>K$3,H$3<=K$3+Control!$C$108),(K$10-(K$10/Control!$C$108)*(H$3-K$3-1))*Control!$C$109/12,0) | I42: =IF(AND(I$3>K$3,I$3<=K$3+Control!$C$108),(K$10-(K$10/Control!$C$108)*(I$3-K$3-1))*Control!$C$109/12,0) | J42: =IF(AND(J$3>K$3,J$3<=K$3+Control!$C$108),(K$10-(K$10/Control!$C$108)*(J$3-K$3-1))*Control!$C$109/12,0) | K42: =IF(AND(K$3>K$3,K$3<=K$3+Control!$C$108),(K$10-(K$10/Control!$C$108)*(K$3-K$3-1))*Control!$C$109/12,0) | L42: =IF(AND(L$3>K$3,L$3<=K$3+Control!$C$108),(K$10-(K$10/Control!$C$108)*(L$3-K$3-1))*Control!$C$109/12,0) | M42: =IF(AND(M$3>K$3,M$3<=K$3+Control!$C$108),(K$10-(K$10/Control!$C$108)*(M$3-K$3-1))*Control!$C$109/12,0) | N42: =IF(AND(N$3>K$3,N$3<=K$3+Control!$C$108),(K$10-(K$10/Control!$C$108)*(N$3-K$3-1))*Control!$C$109/12,0) | O42: =IF(AND(O$3>K$3,O$3<=K$3+Control!$C$108),(K$10-(K$10/Control!$C$108)*(O$3-K$3-1))*Control!$C$109/12,0)
A43: Origin 9 | B43: =L4 | D43: =IF(AND(D$3>L$3,D$3<=L$3+Control!$C$108),(L$10-(L$10/Control!$C$108)*(D$3-L$3-1))*Control!$C$109/12,0) | E43: =IF(AND(E$3>L$3,E$3<=L$3+Control!$C$108),(L$10-(L$10/Control!$C$108)*(E$3-L$3-1))*Control!$C$109/12,0) | F43: =IF(AND(F$3>L$3,F$3<=L$3+Control!$C$108),(L$10-(L$10/Control!$C$108)*(F$3-L$3-1))*Control!$C$109/12,0) | G43: =IF(AND(G$3>L$3,G$3<=L$3+Control!$C$108),(L$10-(L$10/Control!$C$108)*(G$3-L$3-1))*Control!$C$109/12,0) | H43: =IF(AND(H$3>L$3,H$3<=L$3+Control!$C$108),(L$10-(L$10/Control!$C$108)*(H$3-L$3-1))*Control!$C$109/12,0) | I43: =IF(AND(I$3>L$3,I$3<=L$3+Control!$C$108),(L$10-(L$10/Control!$C$108)*(I$3-L$3-1))*Control!$C$109/12,0) | J43: =IF(AND(J$3>L$3,J$3<=L$3+Control!$C$108),(L$10-(L$10/Control!$C$108)*(J$3-L$3-1))*Control!$C$109/12,0) | K43: =IF(AND(K$3>L$3,K$3<=L$3+Control!$C$108),(L$10-(L$10/Control!$C$108)*(K$3-L$3-1))*Control!$C$109/12,0) | L43: =IF(AND(L$3>L$3,L$3<=L$3+Control!$C$108),(L$10-(L$10/Control!$C$108)*(L$3-L$3-1))*Control!$C$109/12,0) | M43: =IF(AND(M$3>L$3,M$3<=L$3+Control!$C$108),(L$10-(L$10/Control!$C$108)*(M$3-L$3-1))*Control!$C$109/12,0) | N43: =IF(AND(N$3>L$3,N$3<=L$3+Control!$C$108),(L$10-(L$10/Control!$C$108)*(N$3-L$3-1))*Control!$C$109/12,0) | O43: =IF(AND(O$3>L$3,O$3<=L$3+Control!$C$108),(L$10-(L$10/Control!$C$108)*(O$3-L$3-1))*Control!$C$109/12,0)
A44: Origin 10 | B44: =M4 | D44: =IF(AND(D$3>M$3,D$3<=M$3+Control!$C$108),(M$10-(M$10/Control!$C$108)*(D$3-M$3-1))*Control!$C$109/12,0) | E44: =IF(AND(E$3>M$3,E$3<=M$3+Control!$C$108),(M$10-(M$10/Control!$C$108)*(E$3-M$3-1))*Control!$C$109/12,0) | F44: =IF(AND(F$3>M$3,F$3<=M$3+Control!$C$108),(M$10-(M$10/Control!$C$108)*(F$3-M$3-1))*Control!$C$109/12,0) | G44: =IF(AND(G$3>M$3,G$3<=M$3+Control!$C$108),(M$10-(M$10/Control!$C$108)*(G$3-M$3-1))*Control!$C$109/12,0) | H44: =IF(AND(H$3>M$3,H$3<=M$3+Control!$C$108),(M$10-(M$10/Control!$C$108)*(H$3-M$3-1))*Control!$C$109/12,0) | I44: =IF(AND(I$3>M$3,I$3<=M$3+Control!$C$108),(M$10-(M$10/Control!$C$108)*(I$3-M$3-1))*Control!$C$109/12,0) | J44: =IF(AND(J$3>M$3,J$3<=M$3+Control!$C$108),(M$10-(M$10/Control!$C$108)*(J$3-M$3-1))*Control!$C$109/12,0) | K44: =IF(AND(K$3>M$3,K$3<=M$3+Control!$C$108),(M$10-(M$10/Control!$C$108)*(K$3-M$3-1))*Control!$C$109/12,0) | L44: =IF(AND(L$3>M$3,L$3<=M$3+Control!$C$108),(M$10-(M$10/Control!$C$108)*(L$3-M$3-1))*Control!$C$109/12,0) | M44: =IF(AND(M$3>M$3,M$3<=M$3+Control!$C$108),(M$10-(M$10/Control!$C$108)*(M$3-M$3-1))*Control!$C$109/12,0) | N44: =IF(AND(N$3>M$3,N$3<=M$3+Control!$C$108),(M$10-(M$10/Control!$C$108)*(N$3-M$3-1))*Control!$C$109/12,0) | O44: =IF(AND(O$3>M$3,O$3<=M$3+Control!$C$108),(M$10-(M$10/Control!$C$108)*(O$3-M$3-1))*Control!$C$109/12,0)
A45: Origin 11 | B45: =N4 | D45: =IF(AND(D$3>N$3,D$3<=N$3+Control!$C$108),(N$10-(N$10/Control!$C$108)*(D$3-N$3-1))*Control!$C$109/12,0) | E45: =IF(AND(E$3>N$3,E$3<=N$3+Control!$C$108),(N$10-(N$10/Control!$C$108)*(E$3-N$3-1))*Control!$C$109/12,0) | F45: =IF(AND(F$3>N$3,F$3<=N$3+Control!$C$108),(N$10-(N$10/Control!$C$108)*(F$3-N$3-1))*Control!$C$109/12,0) | G45: =IF(AND(G$3>N$3,G$3<=N$3+Control!$C$108),(N$10-(N$10/Control!$C$108)*(G$3-N$3-1))*Control!$C$109/12,0) | H45: =IF(AND(H$3>N$3,H$3<=N$3+Control!$C$108),(N$10-(N$10/Control!$C$108)*(H$3-N$3-1))*Control!$C$109/12,0) | I45: =IF(AND(I$3>N$3,I$3<=N$3+Control!$C$108),(N$10-(N$10/Control!$C$108)*(I$3-N$3-1))*Control!$C$109/12,0) | J45: =IF(AND(J$3>N$3,J$3<=N$3+Control!$C$108),(N$10-(N$10/Control!$C$108)*(J$3-N$3-1))*Control!$C$109/12,0) | K45: =IF(AND(K$3>N$3,K$3<=N$3+Control!$C$108),(N$10-(N$10/Control!$C$108)*(K$3-N$3-1))*Control!$C$109/12,0) | L45: =IF(AND(L$3>N$3,L$3<=N$3+Control!$C$108),(N$10-(N$10/Control!$C$108)*(L$3-N$3-1))*Control!$C$109/12,0) | M45: =IF(AND(M$3>N$3,M$3<=N$3+Control!$C$108),(N$10-(N$10/Control!$C$108)*(M$3-N$3-1))*Control!$C$109/12,0) | N45: =IF(AND(N$3>N$3,N$3<=N$3+Control!$C$108),(N$10-(N$10/Control!$C$108)*(N$3-N$3-1))*Control!$C$109/12,0) | O45: =IF(AND(O$3>N$3,O$3<=N$3+Control!$C$108),(N$10-(N$10/Control!$C$108)*(O$3-N$3-1))*Control!$C$109/12,0)
A46: Origin 12 | B46: =O4 | D46: =IF(AND(D$3>O$3,D$3<=O$3+Control!$C$108),(O$10-(O$10/Control!$C$108)*(D$3-O$3-1))*Control!$C$109/12,0) | E46: =IF(AND(E$3>O$3,E$3<=O$3+Control!$C$108),(O$10-(O$10/Control!$C$108)*(E$3-O$3-1))*Control!$C$109/12,0) | F46: =IF(AND(F$3>O$3,F$3<=O$3+Control!$C$108),(O$10-(O$10/Control!$C$108)*(F$3-O$3-1))*Control!$C$109/12,0) | G46: =IF(AND(G$3>O$3,G$3<=O$3+Control!$C$108),(O$10-(O$10/Control!$C$108)*(G$3-O$3-1))*Control!$C$109/12,0) | H46: =IF(AND(H$3>O$3,H$3<=O$3+Control!$C$108),(O$10-(O$10/Control!$C$108)*(H$3-O$3-1))*Control!$C$109/12,0) | I46: =IF(AND(I$3>O$3,I$3<=O$3+Control!$C$108),(O$10-(O$10/Control!$C$108)*(I$3-O$3-1))*Control!$C$109/12,0) | J46: =IF(AND(J$3>O$3,J$3<=O$3+Control!$C$108),(O$10-(O$10/Control!$C$108)*(J$3-O$3-1))*Control!$C$109/12,0) | K46: =IF(AND(K$3>O$3,K$3<=O$3+Control!$C$108),(O$10-(O$10/Control!$C$108)*(K$3-O$3-1))*Control!$C$109/12,0) | L46: =IF(AND(L$3>O$3,L$3<=O$3+Control!$C$108),(O$10-(O$10/Control!$C$108)*(L$3-O$3-1))*Control!$C$109/12,0) | M46: =IF(AND(M$3>O$3,M$3<=O$3+Control!$C$108),(O$10-(O$10/Control!$C$108)*(M$3-O$3-1))*Control!$C$109/12,0) | N46: =IF(AND(N$3>O$3,N$3<=O$3+Control!$C$108),(O$10-(O$10/Control!$C$108)*(N$3-O$3-1))*Control!$C$109/12,0) | O46: =IF(AND(O$3>O$3,O$3<=O$3+Control!$C$108),(O$10-(O$10/Control!$C$108)*(O$3-O$3-1))*Control!$C$109/12,0)
A48: Scope note | D48: Hamar email thread: the EPC scope includes all electrical works from the 6.6kV feeders to the 400V connection at the BitMach containers, and includes the essential section and DX-issued metering scope.
A49: Engineering note | D49: Concept comments: harmonic mitigation is required for the non-linear mining load, but was not allowed for in the preliminary offer because detailed harmonic spectra were not yet available.

Sheet 12M_Cashflow
A1: 12-Month Cash Flow & Burn
A2: Base case still excludes DR and hyperscaler revenue unless switched on; external funding is now formula-driven via the 12M_Funding sheet.
D3: 1 | E3: 2 | F3: 3 | G3: 4 | H3: 5 | I3: 6 | J3: 7 | K3: 8 | L3: 9 | M3: 10 | N3: 11 | O3: 12
D4: Jan-26 | E4: Feb-26 | F4: Mar-26 | G4: Apr-26 | H4: May-26 | I4: Jun-26 | J4: Jul-26 | K4: Aug-26 | L4: Sep-26 | M4: Oct-26 | N4: Nov-26 | O4: Dec-26
A5: Revenue - base case | B5: ZAR'000 | D5: ='12M_Revenue'!D21 | E5: ='12M_Revenue'!E21 | F5: ='12M_Revenue'!F21 | G5: ='12M_Revenue'!G21 | H5: ='12M_Revenue'!H21 | I5: ='12M_Revenue'!I21 | J5: ='12M_Revenue'!J21 | K5: ='12M_Revenue'!K21 | ... O5: ='12M_Revenue'!O21
A6: Revenue - with upside | B6: ZAR'000 | D6: ='12M_Revenue'!D22 | E6: ='12M_Revenue'!E22 | F6: ='12M_Revenue'!F22 | G6: ='12M_Revenue'!G22 | H6: ='12M_Revenue'!H22 | I6: ='12M_Revenue'!I22 | J6: ='12M_Revenue'!J22 | K6: ='12M_Revenue'!K22 | ... O6: ='12M_Revenue'!O22
A7: Cash opex | B7: ZAR'000 | D7: ='12M_Opex'!D24 | E7: ='12M_Opex'!E24 | F7: ='12M_Opex'!F24 | G7: ='12M_Opex'!G24 | H7: ='12M_Opex'!H24 | I7: ='12M_Opex'!I24 | J7: ='12M_Opex'!J24 | K7: ='12M_Opex'!K24 | ... O7: ='12M_Opex'!O24
A8: EBITDA - base case | B8: ZAR'000 | D8: ='12M_Opex'!D25 | E8: ='12M_Opex'!E25 | F8: ='12M_Opex'!F25 | G8: ='12M_Opex'!G25 | H8: ='12M_Opex'!H25 | I8: ='12M_Opex'!I25 | J8: ='12M_Opex'!J25 | K8: ='12M_Opex'!K25 | ... O8: ='12M_Opex'!O25
A9: Capex cash spend | B9: ZAR'000 | D9: ='12M_Capex'!D40 | E9: ='12M_Capex'!E40 | F9: ='12M_Capex'!F40 | G9: ='12M_Capex'!G40 | H9: ='12M_Capex'!H40 | I9: ='12M_Capex'!I40 | J9: ='12M_Capex'!J40 | K9: ='12M_Capex'!K40 | ... O9: ='12M_Capex'!O40
A10: Unlevered cash flow - base case | B10: ZAR'000 | D10: =D5-D7-D9 | E10: =E5-E7-E9 | F10: =F5-F7-F9 | G10: =G5-G7-G9 | H10: =H5-H7-H9 | I10: =I5-I7-I9 | J10: =J5-J7-J9 | K10: =K5-K7-K9 | ... O10: =O5-O7-O9
A11: Unlevered cash flow - with upside | B11: ZAR'000 | D11: =D6-D7-D9 | E11: =E6-E7-E9 | F11: =F6-F7-F9 | G11: =G6-G7-G9 | H11: =H6-H7-H9 | I11: =I6-I7-I9 | J11: =J6-J7-J9 | K11: =K6-K7-K9 | ... O11: =O6-O7-O9
A12: Net external funding input | B12: ZAR'000 | D12: ='12M_Funding'!D11 | E12: ='12M_Funding'!E11 | F12: ='12M_Funding'!F11 | G12: ='12M_Funding'!G11 | H12: ='12M_Funding'!H11 | I12: ='12M_Funding'!I11 | J12: ='12M_Funding'!J11 | K12: ='12M_Funding'!K11 | ... O12: ='12M_Funding'!O11
A13: Opening cash | B13: ZAR'000 | D13: =Control!$C$5 | E13: =D14 | F13: =E14 | G13: =F14 | H13: =G14 | I13: =H14 | J13: =I14 | K13: =J14 | L13: =K14 | ... O13: =N14
A14: Ending cash | B14: ZAR'000 | D14: =D13+D10+D12 | E14: =E13+E10+E12 | F14: =F13+F10+F12 | G14: =G13+G10+G12 | H14: =H13+H10+H12 | I14: =I13+I10+I12 | J14: =J13+J10+J12 | K14: =K13+K10+K12 | ... O14: =O13+O10+O12
A15: Cumulative burn before funding | B15: ZAR'000 | D15: =D10 | E15: =D15+E10 | F15: =E15+F10 | G15: =F15+G10 | H15: =G15+H10 | I15: =H15+I10 | J15: =I15+J10 | K15: =J15+K10 | L15: =K15+L10 | ... O15: =N15+O10
A16: Peak funding required | B16: ZAR'000 | D16: =MAX(0,-D15) | E16: =MAX(D16,MAX(0,-E15)) | F16: =MAX(E16,MAX(0,-F15)) | G16: =MAX(F16,MAX(0,-G15)) | H16: =MAX(G16,MAX(0,-H15)) | I16: =MAX(H16,MAX(0,-I15)) | J16: =MAX(I16,MAX(0,-J15)) | K16: =MAX(J16,MAX(0,-K15)) | L16: =MAX(K16,MAX(0,-L15)) | ... O16: =MAX(N16,MAX(0,-O15))
A17: Equity draw | B17: ZAR'000 | D17: ='12M_Funding'!D8 | E17: ='12M_Funding'!E8 | F17: ='12M_Funding'!F8 | G17: ='12M_Funding'!G8 | H17: ='12M_Funding'!H8 | I17: ='12M_Funding'!I8 | J17: ='12M_Funding'!J8 | K17: ='12M_Funding'!K8 | ... O17: ='12M_Funding'!O8
A18: Senior debt draw | B18: ZAR'000 | D18: ='12M_Funding'!D9 | E18: ='12M_Funding'!E9 | F18: ='12M_Funding'!F9 | G18: ='12M_Funding'!G9 | H18: ='12M_Funding'!H9 | I18: ='12M_Funding'!I9 | J18: ='12M_Funding'!J9 | K18: ='12M_Funding'!K9 | ... O18: ='12M_Funding'!O9
A19: Phase 1 Year-1 Summary
A20: Total BTC mined | B20: BTC | C20: =SUM('12M_Revenue'!D12:O12)
A21: Total revenue - base | B21: ZAR'000 | C21: =SUM('12M_Cashflow'!D5:O5)
A22: Total cash opex | B22: ZAR'000 | C22: =SUM('12M_Cashflow'!D7:O7)
A23: Total capex cash spend | B23: ZAR'000 | C23: =SUM('12M_Cashflow'!D9:O9)
A24: Year-1 unlevered cash burn | B24: ZAR'000 | C24: =SUM('12M_Cashflow'!D10:O10)
A25: Peak funding required | B25: ZAR'000 | C25: =MAX('12M_Cashflow'!D16:O16)
A26: Total external funding | B26: ZAR'000 | C26: =SUM('12M_Cashflow'!D12:O12)
A27: Total equity drawn | B27: ZAR'000 | C27: =SUM('12M_Cashflow'!D17:O17)
A28: Total senior debt drawn | B28: ZAR'000 | C28: =SUM('12M_Cashflow'!D18:O18)
A29: Ending cash in month 12 | B29: ZAR'000 | C29: ='12M_Cashflow'!O14

Sheet 12M_Funding
A1: 12-Month External Funding Schedule
A2: This sheet sizes external equity and senior debt draws to the monthly funding need after vendor-style miner and EPC payment structures.
D3: 1 | E3: 2 | F3: 3 | G3: 4 | H3: 5 | I3: 6 | J3: 7 | K3: 8 | L3: 9 | M3: 10 | N3: 11 | O3: 12
D4: ='12M_Deployment'!D4 | E4: ='12M_Deployment'!E4 | F4: ='12M_Deployment'!F4 | G4: ='12M_Deployment'!G4 | H4: ='12M_Deployment'!H4 | I4: ='12M_Deployment'!I4 | J4: ='12M_Deployment'!J4 | K4: ='12M_Deployment'!K4 | ... O4: ='12M_Deployment'!O4
A5: Opening cash before external funding | B5: ZAR'000 | D5: ='12M_Cashflow'!D13 | E5: ='12M_Cashflow'!E13 | F5: ='12M_Cashflow'!F13 | G5: ='12M_Cashflow'!G13 | H5: ='12M_Cashflow'!H13 | I5: ='12M_Cashflow'!I13 | J5: ='12M_Cashflow'!J13 | K5: ='12M_Cashflow'!K13 | ... O5: ='12M_Cashflow'!O13
A6: Unlevered cash flow before external funding | B6: ZAR'000 | D6: ='12M_Cashflow'!D10 | E6: ='12M_Cashflow'!E10 | F6: ='12M_Cashflow'!F10 | G6: ='12M_Cashflow'!G10 | H6: ='12M_Cashflow'!H10 | I6: ='12M_Cashflow'!I10 | J6: ='12M_Cashflow'!J10 | K6: ='12M_Cashflow'!K10 | ... O6: ='12M_Cashflow'!O10
A7: Required net external funding | B7: ZAR'000 | D7: =MAX(Control!$C$116-(D5+D6),0) | E7: =MAX(Control!$C$116-(E5+E6),0) | F7: =MAX(Control!$C$116-(F5+F6),0) | G7: =MAX(Control!$C$116-(G5+G6),0) | H7: =MAX(Control!$C$116-(H5+H6),0) | I7: =MAX(Control!$C$116-(I5+I6),0) | J7: =MAX(Control!$C$116-(J5+J6),0) | K7: =MAX(Control!$C$116-(K5+K6),0) | ... O7: =MAX(Control!$C$116-(O5+O6),0)
A8: Equity draw | B8: ZAR'000 | D8: =IF((Control!$C$110+Control!$C$111)=0,0,D7*Control!$C$110/(Control!$C$110+Control!$C$111)) | E8: =IF((Control!$C$110+Control!$C$111)=0,0,E7*Control!$C$110/(Control!$C$110+Control!$C$111)) | F8: =IF((Control!$C$110+Control!$C$111)=0,0,F7*Control!$C$110/(Control!$C$110+Control!$C$111)) | G8: =IF((Control!$C$110+Control!$C$111)=0,0,G7*Control!$C$110/(Control!$C$110+Control!$C$111)) | H8: =IF((Control!$C$110+Control!$C$111)=0,0,H7*Control!$C$110/(Control!$C$110+Control!$C$111)) | I8: =IF((Control!$C$110+Control!$C$111)=0,0,I7*Control!$C$110/(Control!$C$110+Control!$C$111)) | J8: =IF((Control!$C$110+Control!$C$111)=0,0,J7*Control!$C$110/(Control!$C$110+Control!$C$111)) | K8: =IF((Control!$C$110+Control!$C$111)=0,0,K7*Control!$C$110/(Control!$C$110+Control!$C$111)) | ... O8: =IF((Control!$C$110+Control!$C$111)=0,0,O7*Control!$C$110/(Control!$C$110+Control!$C$111))
A9: Senior debt gross draw | B9: ZAR'000 | D9: =IF(Control!$C$111>0,(D7-D8)/(1-Control!$C$115),0) | E9: =IF(Control!$C$111>0,(E7-E8)/(1-Control!$C$115),0) | F9: =IF(Control!$C$111>0,(F7-F8)/(1-Control!$C$115),0) | G9: =IF(Control!$C$111>0,(G7-G8)/(1-Control!$C$115),0) | H9: =IF(Control!$C$111>0,(H7-H8)/(1-Control!$C$115),0) | I9: =IF(Control!$C$111>0,(I7-I8)/(1-Control!$C$115),0) | J9: =IF(Control!$C$111>0,(J7-J8)/(1-Control!$C$115),0) | K9: =IF(Control!$C$111>0,(K7-K8)/(1-Control!$C$115),0) | ... O9: =IF(Control!$C$111>0,(O7-O8)/(1-Control!$C$115),0)
A10: Debt arrangement fee | B10: ZAR'000 | D10: =D9*Control!$C$115 | E10: =E9*Control!$C$115 | F10: =F9*Control!$C$115 | G10: =G9*Control!$C$115 | H10: =H9*Control!$C$115 | I10: =I9*Control!$C$115 | J10: =J9*Control!$C$115 | K10: =K9*Control!$C$115 | ... O10: =O9*Control!$C$115
A11: Net external funding input | B11: ZAR'000 | D11: =D8+D9-D10 | E11: =E8+E9-E10 | F11: =F8+F9-F10 | G11: =G8+G9-G10 | H11: =H8+H9-H10 | I11: =I8+I9-I10 | J11: =J8+J9-J10 | K11: =K8+K9-K10 | ... O11: =O8+O9-O10
A12: Closing cash after external funding | B12: ZAR'000 | D12: =D5+D6+D11 | E12: =E5+E6+E11 | F12: =F5+F6+F11 | G12: =G5+G6+G11 | H12: =H5+H6+H11 | I12: =I5+I6+I11 | J12: =J5+J6+J11 | K12: =K5+K6+K11 | ... O12: =O5+O6+O11
A13: Cumulative equity drawn | B13: ZAR'000 | D13: =D8 | E13: =D13+E8 | F13: =E13+F8 | G13: =F13+G8 | H13: =G13+H8 | I13: =H13+I8 | J13: =I13+J8 | K13: =J13+K8 | L13: =K13+L8 | ... O13: =N13+O8
A14: Cumulative senior debt drawn | B14: ZAR'000 | D14: =D9 | E14: =D14+E9 | F14: =E14+F9 | G14: =F14+G9 | H14: =G14+H9 | I14: =H14+I9 | J14: =I14+J9 | K14: =J14+K9 | L14: =K14+L9 | ... O14: =N14+O9

Sheet Debt_Amortization
A1: Senior Debt Amortization Schedule
A2: By default, interest capitalizes during the grace period and is paid in cash only once amortization starts. Adjust tenor, grace and rate in Control.
D3: 1 | E3: 2 | F3: 3 | G3: 4 | H3: 5 | I3: 6 | J3: 7 | K3: 8 | L3: 9 | M3: 10 | N3: 11 | O3: 12 | P3: 13 | Q3: 14 | R3: 15 | S3: 16 | T3: 17 | U3: 18 | V3: 19 | W3: 20 | X3: 21 | Y3: 22 | Z3: 23 | AA3: 24 | AB3: 25 | AC3: 26 | AD3: 27 | AE3: 28 | AF3: 29 | AG3: 30 | AH3: 31 | AI3: 32 | AJ3: 33 | AK3: 34 | AL3: 35 | AM3: 36 | AN3: 37 | AO3: 38 | AP3: 39 | AQ3: 40 | AR3: 41 | AS3: 42 | AT3: 43 | AU3: 44 | AV3: 45 | AW3: 46 | AX3: 47 | AY3: 48 | AZ3: 49 | BA3: 50 | BB3: 51 | BC3: 52 | BD3: 53 | BE3: 54 | BF3: 55 | BG3: 56 | BH3: 57 | BI3: 58 | BJ3: 59 | BK3: 60
D4: Jan-26 | E4: Feb-26 | F4: Mar-26 | G4: Apr-26 | H4: May-26 | I4: Jun-26 | J4: Jul-26 | K4: Aug-26 | L4: Sep-26 | M4: Oct-26 | N4: Nov-26 | O4: Dec-26 | P4: Jan-27 | Q4: Feb-27 | R4: Mar-27 | S4: Apr-27 | T4: May-27 | U4: Jun-27 | V4: Jul-27 | W4: Aug-27 | X4: Sep-27 | Y4: Oct-27 | Z4: Nov-27 | AA4: Dec-27 | AB4: Jan-28 | AC4: Feb-28 | AD4: Mar-28 | AE4: Apr-28 | AF4: May-28 | AG4: Jun-28 | AH4: Jul-28 | AI4: Aug-28 | AJ4: Sep-28 | AK4: Oct-28 | AL4: Nov-28 | AM4: Dec-28 | AN4: Jan-29 | AO4: Feb-29 | AP4: Mar-29 | AQ4: Apr-29 | AR4: May-29 | AS4: Jun-29 | AT4: Jul-29 | AU4: Aug-29 | AV4: Sep-29 | AW4: Oct-29 | AX4: Nov-29 | AY4: Dec-29 | AZ4: Jan-30 | BA4: Feb-30 | BB4: Mar-30 | BC4: Apr-30 | BD4: May-30 | BE4: Jun-30 | BF4: Jul-30 | BG4: Aug-30 | BH4: Sep-30 | BI4: Oct-30 | BJ4: Nov-30 | BK4: Dec-30
A5: Opening debt balance | B5: ZAR'000 | D5: =0 | E5: =D10 | F5: =E10 | G5: =F10 | H5: =G10 | I5: =H10 | J5: =I10 | K5: =J10 | L5: =K10 | ... BK5: =BJ10
A6: New senior debt draw | B6: ZAR'000 | D6: ='12M_Funding'!D9 | E6: ='12M_Funding'!E9 | F6: ='12M_Funding'!F9 | G6: ='12M_Funding'!G9 | H6: ='12M_Funding'!H9 | I6: ='12M_Funding'!I9 | J6: ='12M_Funding'!J9 | K6: ='12M_Funding'!K9 | ... O6: ='12M_Funding'!O9 | P6: =0 | Q6: =0 | R6: =0 | S6: =0 | T6: =0 | U6: =0 | V6: =0 | W6: =0 | ... BK6: =0
A7: Interest accrued | B7: ZAR'000 | D7: =(D5+D6/2)*Control!$C$112/12 | E7: =(E5+E6/2)*Control!$C$112/12 | F7: =(F5+F6/2)*Control!$C$112/12 | G7: =(G5+G6/2)*Control!$C$112/12 | H7: =(H5+H6/2)*Control!$C$112/12 | I7: =(I5+I6/2)*Control!$C$112/12 | J7: =(J5+J6/2)*Control!$C$112/12 | K7: =(K5+K6/2)*Control!$C$112/12 | ... BK7: =(BK5+BK6/2)*Control!$C$112/12
A8: Scheduled principal | B8: ZAR'000 | D8: =IF(D$3<=Control!$C$114,0,MIN(INDEX($D$10:$BM$10,1,Control!$C$114)/(Control!$C$113-Control!$C$114),D5+D6)) | E8: =IF(E$3<=Control!$C$114,0,MIN(INDEX($D$10:$BM$10,1,Control!$C$114)/(Control!$C$113-Control!$C$114),E5+E6)) | F8: =IF(F$3<=Control!$C$114,0,MIN(INDEX($D$10:$BM$10,1,Control!$C$114)/(Control!$C$113-Control!$C$114),F5+F6)) | G8: =IF(G$3<=Control!$C$114,0,MIN(INDEX($D$10:$BM$10,1,Control!$C$114)/(Control!$C$113-Control!$C$114),G5+G6)) | H8: =IF(H$3<=Control!$C$114,0,MIN(INDEX($D$10:$BM$10,1,Control!$C$114)/(Control!$C$113-Control!$C$114),H5+H6)) | I8: =IF(I$3<=Control!$C$114,0,MIN(INDEX($D$10:$BM$10,1,Control!$C$114)/(Control!$C$113-Control!$C$114),I5+I6)) | J8: =IF(J$3<=Control!$C$114,0,MIN(INDEX($D$10:$BM$10,1,Control!$C$114)/(Control!$C$113-Control!$C$114),J5+J6)) | K8: =IF(K$3<=Control!$C$114,0,MIN(INDEX($D$10:$BM$10,1,Control!$C$114)/(Control!$C$113-Control!$C$114),K5+K6)) | ... BK8: =IF(BK$3<=Control!$C$114,0,MIN(INDEX($D$10:$BM$10,1,Control!$C$114)/(Control!$C$113-Control!$C$114),BK5+BK6))
A9: Debt service cash | B9: ZAR'000 | D9: =IF(D$3<=Control!$C$114,0,D7+D8) | E9: =IF(E$3<=Control!$C$114,0,E7+E8) | F9: =IF(F$3<=Control!$C$114,0,F7+F8) | G9: =IF(G$3<=Control!$C$114,0,G7+G8) | H9: =IF(H$3<=Control!$C$114,0,H7+H8) | I9: =IF(I$3<=Control!$C$114,0,I7+I8) | J9: =IF(J$3<=Control!$C$114,0,J7+J8) | K9: =IF(K$3<=Control!$C$114,0,K7+K8) | ... BK9: =IF(BK$3<=Control!$C$114,0,BK7+BK8)
A10: Closing debt balance | B10: ZAR'000 | D10: =IF(D$3<=Control!$C$114,D5+D6+D7-D8,D5+D6-D8) | E10: =IF(E$3<=Control!$C$114,E5+E6+E7-E8,E5+E6-E8) | F10: =IF(F$3<=Control!$C$114,F5+F6+F7-F8,F5+F6-F8) | G10: =IF(G$3<=Control!$C$114,G5+G6+G7-G8,G5+G6-G8) | H10: =IF(H$3<=Control!$C$114,H5+H6+H7-H8,H5+H6-H8) | I10: =IF(I$3<=Control!$C$114,I5+I6+I7-I8,I5+I6-I8) | J10: =IF(J$3<=Control!$C$114,J5+J6+J7-J8,J5+J6-J8) | K10: =IF(K$3<=Control!$C$114,K5+K6+K7-K8,K5+K6-K8) | ... BK10: =IF(BK$3<=Control!$C$114,BK5+BK6+BK7-BK8,BK5+BK6-BK8)
A11: Cumulative draws | B11: ZAR'000 | D11: =D6 | E11: =D11+E6 | F11: =E11+F6 | G11: =F11+G6 | H11: =G11+H6 | I11: =H11+I6 | J11: =I11+J6 | K11: =J11+K6 | L11: =K11+L6 | ... BK11: =BJ11+BK6
A12: Cumulative interest | B12: ZAR'000 | D12: =D7 | E12: =D12+E7 | F12: =E12+F7 | G12: =F12+G7 | H12: =G12+H7 | I12: =H12+I7 | J12: =I12+J7 | K12: =J12+K7 | L12: =K12+L7 | ... BK12: =BJ12+BK7

Sheet 10Y_Ramp
A1: 10-Year Site & Solar Ramp
A2: Blue rows are the long-dated platform build assumptions. Base case reaches 2GW by 2034/2035.
D3: 2026 | E3: 2027 | F3: 2028 | G3: 2029 | H3: 2030 | I3: 2031 | J3: 2032 | K3: 2033 | L3: 2034 | M3: 2035
D4: 2026 | E4: 2027 | F4: 2028 | G4: 2029 | H4: 2030 | I4: 2031 | J4: 2032 | K4: 2033 | L4: 2034 | M4: 2035
A7: Grootvlei compute MW | B7: MW | D7: 15 | E7: 40 | F7: 60 | G7: 80 | H7: 100 | I7: 120 | J7: 140 | K7: 160 | L7: 180 | M7: 200
A8: AMSA VB compute MW | B8: MW | D8: 5 | E8: 40 | F8: 120 | G8: 200 | H8: 220 | I8: 230 | J8: 240 | K8: 250 | L8: 250 | M8: 250
A9: AMSA Newcastle compute MW | B9: MW | D9: 0 | E9: 20 | F9: 80 | G9: 150 | H9: 220 | I9: 300 | J9: 360 | K9: 430 | L9: 500 | M9: 500
A10: Saldanha compute MW | B10: MW | D10: 0 | E10: 20 | F10: 80 | G10: 120 | H10: 220 | I10: 300 | J10: 360 | K10: 430 | L10: 500 | M10: 500
A11: Komati compute MW | B11: MW | D11: 0 | E11: 60 | F11: 130 | G11: 150 | H11: 440 | I11: 450 | J11: 500 | K11: 530 | L11: 570 | M11: 550
A12: Total compute MW | B12: MW | D12: =SUM(D7:D11) | E12: =SUM(E7:E11) | F12: =SUM(F7:F11) | G12: =SUM(G7:G11) | H12: =SUM(H7:H11) | I12: =SUM(I7:I11) | J12: =SUM(J7:J11) | K12: =SUM(K7:K11) | ... M12: =SUM(M7:M11)
A15: AMSA VB solar MW | B15: MW | D15: 10 | E15: 180 | F15: 250 | G15: 250 | H15: 250 | I15: 250 | J15: 250 | K15: 250 | L15: 250 | M15: 250
A16: AMSA Newcastle solar MW | B16: MW | D16: 0 | E16: 0 | F16: 50 | G16: 100 | H16: 150 | I16: 200 | J16: 250 | K16: 250 | L16: 250 | M16: 250
A17: Saldanha solar MW | B17: MW | D17: 0 | E17: 0 | F17: 0 | G17: 50 | H17: 100 | I17: 150 | J17: 200 | K17: 250 | L17: 250 | M17: 250
A18: Komati solar MW | B18: MW | D18: 0 | E18: 0 | F18: 0 | G18: 20 | H18: 40 | I18: 60 | J18: 80 | K18: 100 | L18: 120 | M18: 150
A19: Total solar MW | B19: MW | D19: =SUM(D15:D18) | E19: =SUM(E15:E18) | F19: =SUM(F15:F18) | G19: =SUM(G15:G18) | H19: =SUM(H15:H18) | I19: =SUM(I15:I18) | J19: =SUM(J15:J18) | K19: =SUM(K15:K18) | ... M19: =SUM(M15:M18)

Sheet 10Y_Model
A1: 10-Year Platform Model
A2: Simplified annual portfolio model. Phase 1 monthly sheet is the authoritative view for year one; this annual view supports strategic sizing and stress tests.
D3: 2026 | E3: 2027 | F3: 2028 | G3: 2029 | H3: 2030 | I3: 2031 | J3: 2032 | K3: 2033 | L3: 2034 | M3: 2035
D4: 2026 | E4: 2027 | F4: 2028 | G4: 2029 | H4: 2030 | I4: 2031 | J4: 2032 | K4: 2033 | L4: 2034 | M4: 2035
A5: Total compute MW | B5: MW | D5: ='10Y_Ramp'!D12 | E5: ='10Y_Ramp'!E12 | F5: ='10Y_Ramp'!F12 | G5: ='10Y_Ramp'!G12 | H5: ='10Y_Ramp'!H12 | I5: ='10Y_Ramp'!I12 | J5: ='10Y_Ramp'!J12 | K5: ='10Y_Ramp'!K12 | ... M5: ='10Y_Ramp'!M12
A6: Total solar MW | B6: MW | D6: ='10Y_Ramp'!D19 | E6: ='10Y_Ramp'!E19 | F6: ='10Y_Ramp'!F19 | G6: ='10Y_Ramp'!G19 | H6: ='10Y_Ramp'!H19 | I6: ='10Y_Ramp'!I19 | J6: ='10Y_Ramp'!J19 | K6: ='10Y_Ramp'!K19 | ... M6: ='10Y_Ramp'!M19
A7: Installed miners | B7: miners | D7: =(D5/(1+Control!$C$34))*1000000/Control!$C$32 | E7: =(E5/(1+Control!$C$34))*1000000/Control!$C$32 | F7: =(F5/(1+Control!$C$34))*1000000/Control!$C$32 | G7: =(G5/(1+Control!$C$34))*1000000/Control!$C$32 | H7: =(H5/(1+Control!$C$34))*1000000/Control!$C$32 | I7: =(I5/(1+Control!$C$34))*1000000/Control!$C$32 | J7: =(J5/(1+Control!$C$34))*1000000/Control!$C$32 | K7: =(K5/(1+Control!$C$34))*1000000/Control!$C$32 | ... M7: =(M5/(1+Control!$C$34))*1000000/Control!$C$32
A8: Effective hashrate | B8: TH/s | D8: =(('10Y_Ramp'!D7/(1+Control!$C$34))*1000000/Control!$C$32)*Control!$C$30*(Control!$C$21/24)*Control!$C$14+(('10Y_Ramp'!D8/(1+Control!$C$34))*1000000/Control!$C$32)*Control!$C$30*((Control!$C$22+Control!$C$23)/24)*Control!$C$14+(('10Y_Ramp'!D9/(1+Control!$C$34))*1000000/Control!$C$32)*Control!$C$30*((Control!$C$22+Control!$C$23)/24)*Control!$C$14+(('10Y_Ramp'!D10/(1+Control!$C$34))*1000000/Control!$C$32)*Control!$C$30*((Control!$C$22+Control!$C$23)/24)*Control!$C$14+(('10Y_Ramp'!D11/(1+Control!$C$34))*1000000/Control!$C$32)*Control!$C$30*((Control!$C$22+Control!$C$23)/24)*Control!$C$14 | E8: =(('10Y_Ramp'!E7/(1+Control!$C$34))*1000000/Control!$C$32)*Control!$C$30*(Control!$C$21/24)*Control!$C$14+(('10Y_Ramp'!E8/(1+Control!$C$34))*1000000/Control!$C$32)*Control!$C$30*((Control!$C$22+Control!$C$23)/24)*Control!$C$14+(('10Y_Ramp'!E9/(1+Control!$C$34))*1000000/Control!$C$32)*Control!$C$30*((Control!$C$22+Control!$C$23)/24)*Control!$C$14+(('10Y_Ramp'!E10/(1+Control!$C$34))*1000000/Control!$C$32)*Control!$C$30*((Control!$C$22+Control!$C$23)/24)*Control!$C$14+(('10Y_Ramp'!E11/(1+Control!$C$34))*1000000/Control!$C$32)*Control!$C$30*((Control!$C$22+Control!$C$23)/24)*Control!$C$14 | F8: =(('10Y_Ramp'!F7/(1+Control!$C$34))*1000000/Control!$C$32)*Control!$C$30*(Control!$C$21/24)*Control!$C$14+(('10Y_Ramp'!F8/(1+Control!$C$34))*1000000/Control!$C$32)*Control!$C$30*((Control!$C$22+Control!$C$23)/24)*Control!$C$14+(('10Y_Ramp'!F9/(1+Control!$C$34))*1000000/Control!$C$32)*Control!$C$30*((Control!$C$22+Control!$C$23)/24)*Control!$C$14+(('10Y_Ramp'!F10/(1+Control!$C$34))*1000000/Control!$C$32)*Control!$C$30*((Control!$C$22+Control!$C$23)/24)*Control!$C$14+(('10Y_Ramp'!F11/(1+Control!$C$34))*1000000/Control!$C$32)*Control!$C$30*((Control!$C$22+Control!$C$23)/24)*Control!$C$14 | G8: =(('10Y_Ramp'!G7/(1+Control!$C$34))*1000000/Control!$C$32)*Control!$C$30*(Control!$C$21/24)*Control!$C$14+(('10Y_Ramp'!G8/(1+Control!$C$34))*1000000/Control!$C$32)*Control!$C$30*((Control!$C$22+Control!$C$23)/24)*Control!$C$14+(('10Y_Ramp'!G9/(1+Control!$C$34))*1000000/Control!$C$32)*Control!$C$30*((Control!$C$22+Control!$C$23)/24)*Control!$C$14+(('10Y_Ramp'!G10/(1+Control!$C$34))*1000000/Control!$C$32)*Control!$C$30*((Control!$C$22+Control!$C$23)/24)*Control!$C$14+(('10Y_Ramp'!G11/(1+Control!$C$34))*1000000/Control!$C$32)*Control!$C$30*((Control!$C$22+Control!$C$23)/24)*Control!$C$14 | H8: =(('10Y_Ramp'!H7/(1+Control!$C$34))*1000000/Control!$C$32)*Control!$C$30*(Control!$C$21/24)*Control!$C$14+(('10Y_Ramp'!H8/(1+Control!$C$34))*1000000/Control!$C$32)*Control!$C$30*((Control!$C$22+Control!$C$23)/24)*Control!$C$14+(('10Y_Ramp'!H9/(1+Control!$C$34))*1000000/Control!$C$32)*Control!$C$30*((Control!$C$22+Control!$C$23)/24)*Control!$C$14+(('10Y_Ramp'!H10/(1+Control!$C$34))*1000000/Control!$C$32)*Control!$C$30*((Control!$C$22+Control!$C$23)/24)*Control!$C$14+(('10Y_Ramp'!H11/(1+Control!$C$34))*1000000/Control!$C$32)*Control!$C$30*((Control!$C$22+Control!$C$23)/24)*Control!$C$14 | I8: =(('10Y_Ramp'!I7/(1+Control!$C$34))*1000000/Control!$C$32)*Control!$C$30*(Control!$C$21/24)*Control!$C$14+(('10Y_Ramp'!I8/(1+Control!$C$34))*1000000/Control!$C$32)*Control!$C$30*((Control!$C$22+Control!$C$23)/24)*Control!$C$14+(('10Y_Ramp'!I9/(1+Control!$C$34))*1000000/Control!$C$32)*Control!$C$30*((Control!$C$22+Control!$C$23)/24)*Control!$C$14+(('10Y_Ramp'!I10/(1+Control!$C$34))*1000000/Control!$C$32)*Control!$C$30*((Control!$C$22+Control!$C$23)/24)*Control!$C$14+(('10Y_Ramp'!I11/(1+Control!$C$34))*1000000/Control!$C$32)*Control!$C$30*((Control!$C$22+Control!$C$23)/24)*Control!$C$14 | J8: =(('10Y_Ramp'!J7/(1+Control!$C$34))*1000000/Control!$C$32)*Control!$C$30*(Control!$C$21/24)*Control!$C$14+(('10Y_Ramp'!J8/(1+Control!$C$34))*1000000/Control!$C$32)*Control!$C$30*((Control!$C$22+Control!$C$23)/24)*Control!$C$14+(('10Y_Ramp'!J9/(1+Control!$C$34))*1000000/Control!$C$32)*Control!$C$30*((Control!$C$22+Control!$C$23)/24)*Control!$C$14+(('10Y_Ramp'!J10/(1+Control!$C$34))*1000000/Control!$C$32)*Control!$C$30*((Control!$C$22+Control!$C$23)/24)*Control!$C$14+(('10Y_Ramp'!J11/(1+Control!$C$34))*1000000/Control!$C$32)*Control!$C$30*((Control!$C$22+Control!$C$23)/24)*Control!$C$14 | K8: =(('10Y_Ramp'!K7/(1+Control!$C$34))*1000000/Control!$C$32)*Control!$C$30*(Control!$C$21/24)*Control!$C$14+(('10Y_Ramp'!K8/(1+Control!$C$34))*1000000/Control!$C$32)*Control!$C$30*((Control!$C$22+Control!$C$23)/24)*Control!$C$14+(('10Y_Ramp'!K9/(1+Control!$C$34))*1000000/Control!$C$32)*Control!$C$30*((Control!$C$22+Control!$C$23)/24)*Control!$C$14+(('10Y_Ramp'!K10/(1+Control!$C$34))*1000000/Control!$C$32)*Control!$C$30*((Control!$C$22+Control!$C$23)/24)*Control!$C$14+(('10Y_Ramp'!K11/(1+Control!$C$34))*1000000/Control!$C$32)*Control!$C$30*((Control!$C$22+Control!$C$23)/24)*Control!$C$14 | ... M8: =(('10Y_Ramp'!M7/(1+Control!$C$34))*1000000/Control!$C$32)*Control!$C$30*(Control!$C$21/24)*Control!$C$14+(('10Y_Ramp'!M8/(1+Control!$C$34))*1000000/Control!$C$32)*Control!$C$30*((Control!$C$22+Control!$C$23)/24)*Control!$C$14+(('10Y_Ramp'!M9/(1+Control!$C$34))*1000000/Control!$C$32)*Control!$C$30*((Control!$C$22+Control!$C$23)/24)*Control!$C$14+(('10Y_Ramp'!M10/(1+Control!$C$34))*1000000/Control!$C$32)*Control!$C$30*((Control!$C$22+Control!$C$23)/24)*Control!$C$14+(('10Y_Ramp'!M11/(1+Control!$C$34))*1000000/Control!$C$32)*Control!$C$30*((Control!$C$22+Control!$C$23)/24)*Control!$C$14
A9: BTC mined | B9: BTC/yr | D9: =D8/Control!$C$8*(Control!$C$12*365*Control!$C$10*(1+Control!$C$11)) | E9: =E8/E41*(Control!$C$12*365*Control!$C$10*(1+Control!$C$11)) | F9: =F8/F41*(Control!$C$12*365*Control!$C$10*(1+Control!$C$11)) | G9: =G8/G41*(Control!$C$12*365*Control!$C$10*(1+Control!$C$11)) | H9: =H8/H41*(Control!$C$12*365*Control!$C$10*(1+Control!$C$11)) | I9: =I8/I41*(Control!$C$12*365*Control!$C$10*(1+Control!$C$11)) | J9: =J8/J41*(Control!$C$12*365*Control!$C$10*(1+Control!$C$11)) | K9: =K8/K41*(Control!$C$12*365*Control!$C$10*(1+Control!$C$11)) | L9: =L8/L41*(Control!$C$12*365*Control!$C$10*(1+Control!$C$11)) | M9: =M8/M41*(Control!$C$12*365*Control!$C$10*(1+Control!$C$11))
A10: BTC revenue | B10: ZAR'000 | D10: =D9*Control!$C$6*Control!$C$4/1000 | E10: =E9*E40*Control!$C$4/1000 | F10: =F9*F40*Control!$C$4/1000 | G10: =G9*G40*Control!$C$4/1000 | H10: =H9*H40*Control!$C$4/1000 | I10: =I9*I40*Control!$C$4/1000 | J10: =J9*J40*Control!$C$4/1000 | K10: =K9*K40*Control!$C$4/1000 | L10: =L9*L40*Control!$C$4/1000 | M10: =M9*M40*Control!$C$4/1000
A11: DR revenue - base case | B11: ZAR'000 | D11: =IF(Control!$C$85=1,D5*Control!$C$87*365*Control!$C$86,0) | E11: =IF(Control!$C$85=1,E5*Control!$C$87*365*Control!$C$86,0) | F11: =IF(Control!$C$85=1,F5*Control!$C$87*365*Control!$C$86,0) | G11: =IF(Control!$C$85=1,G5*Control!$C$87*365*Control!$C$86,0) | H11: =IF(Control!$C$85=1,H5*Control!$C$87*365*Control!$C$86,0) | I11: =IF(Control!$C$85=1,I5*Control!$C$87*365*Control!$C$86,0) | J11: =IF(Control!$C$85=1,J5*Control!$C$87*365*Control!$C$86,0) | K11: =IF(Control!$C$85=1,K5*Control!$C$87*365*Control!$C$86,0) | ... M11: =IF(Control!$C$85=1,M5*Control!$C$87*365*Control!$C$86,0)
A12: AI/Hyperscaler revenue - base case | B12: ZAR'000 | D12: =IF(AND(Control!$C$81=1,D$4>=Control!$C$82),D5*Control!$C$83*24*365*Control!$C$84*Control!$C$4/1000,0) | E12: =IF(AND(Control!$C$81=1,E$4>=Control!$C$82),E5*Control!$C$83*24*365*Control!$C$84*Control!$C$4/1000,0) | F12: =IF(AND(Control!$C$81=1,F$4>=Control!$C$82),F5*Control!$C$83*24*365*Control!$C$84*Control!$C$4/1000,0) | G12: =IF(AND(Control!$C$81=1,G$4>=Control!$C$82),G5*Control!$C$83*24*365*Control!$C$84*Control!$C$4/1000,0) | H12: =IF(AND(Control!$C$81=1,H$4>=Control!$C$82),H5*Control!$C$83*24*365*Control!$C$84*Control!$C$4/1000,0) | I12: =IF(AND(Control!$C$81=1,I$4>=Control!$C$82),I5*Control!$C$83*24*365*Control!$C$84*Control!$C$4/1000,0) | J12: =IF(AND(Control!$C$81=1,J$4>=Control!$C$82),J5*Control!$C$83*24*365*Control!$C$84*Control!$C$4/1000,0) | K12: =IF(AND(Control!$C$81=1,K$4>=Control!$C$82),K5*Control!$C$83*24*365*Control!$C$84*Control!$C$4/1000,0) | ... M12: =IF(AND(Control!$C$81=1,M$4>=Control!$C$82),M5*Control!$C$83*24*365*Control!$C$84*Control!$C$4/1000,0)
A13: Total revenue - base case | B13: ZAR'000 | D13: =SUM(D10:D12) | E13: =SUM(E10:E12) | F13: =SUM(F10:F12) | G13: =SUM(G10:G12) | H13: =SUM(H10:H12) | I13: =SUM(I10:I12) | J13: =SUM(J10:J12) | K13: =SUM(K10:K12) | ... M13: =SUM(M10:M12)
A15: GVL energy cost | B15: ZAR'000 | D15: ='10Y_Ramp'!D7*Control!$C$21*365*Control!$C$14*Control!$C$25 | E15: ='10Y_Ramp'!E7*Control!$C$21*365*Control!$C$14*Control!$C$25 | F15: ='10Y_Ramp'!F7*Control!$C$21*365*Control!$C$14*Control!$C$25 | G15: ='10Y_Ramp'!G7*Control!$C$21*365*Control!$C$14*Control!$C$25 | H15: ='10Y_Ramp'!H7*Control!$C$21*365*Control!$C$14*Control!$C$25 | I15: ='10Y_Ramp'!I7*Control!$C$21*365*Control!$C$14*Control!$C$25 | J15: ='10Y_Ramp'!J7*Control!$C$21*365*Control!$C$14*Control!$C$25 | K15: ='10Y_Ramp'!K7*Control!$C$21*365*Control!$C$14*Control!$C$25 | ... M15: ='10Y_Ramp'!M7*Control!$C$21*365*Control!$C$14*Control!$C$25
A16: AMSA VB energy cost | B16: ZAR'000 | D16: =(('10Y_Ramp'!D8*(Control!$C$22+Control!$C$23)*365*Control!$C$14)-(MIN('10Y_Ramp'!D8,'10Y_Ramp'!D15)*Control!$C$23*365*Control!$C$14))*Control!$C$26 | E16: =(('10Y_Ramp'!E8*(Control!$C$22+Control!$C$23)*365*Control!$C$14)-(MIN('10Y_Ramp'!E8,'10Y_Ramp'!E15)*Control!$C$23*365*Control!$C$14))*Control!$C$26 | F16: =(('10Y_Ramp'!F8*(Control!$C$22+Control!$C$23)*365*Control!$C$14)-(MIN('10Y_Ramp'!F8,'10Y_Ramp'!F15)*Control!$C$23*365*Control!$C$14))*Control!$C$26 | G16: =(('10Y_Ramp'!G8*(Control!$C$22+Control!$C$23)*365*Control!$C$14)-(MIN('10Y_Ramp'!G8,'10Y_Ramp'!G15)*Control!$C$23*365*Control!$C$14))*Control!$C$26 | H16: =(('10Y_Ramp'!H8*(Control!$C$22+Control!$C$23)*365*Control!$C$14)-(MIN('10Y_Ramp'!H8,'10Y_Ramp'!H15)*Control!$C$23*365*Control!$C$14))*Control!$C$26 | I16: =(('10Y_Ramp'!I8*(Control!$C$22+Control!$C$23)*365*Control!$C$14)-(MIN('10Y_Ramp'!I8,'10Y_Ramp'!I15)*Control!$C$23*365*Control!$C$14))*Control!$C$26 | J16: =(('10Y_Ramp'!J8*(Control!$C$22+Control!$C$23)*365*Control!$C$14)-(MIN('10Y_Ramp'!J8,'10Y_Ramp'!J15)*Control!$C$23*365*Control!$C$14))*Control!$C$26 | K16: =(('10Y_Ramp'!K8*(Control!$C$22+Control!$C$23)*365*Control!$C$14)-(MIN('10Y_Ramp'!K8,'10Y_Ramp'!K15)*Control!$C$23*365*Control!$C$14))*Control!$C$26 | ... M16: =(('10Y_Ramp'!M8*(Control!$C$22+Control!$C$23)*365*Control!$C$14)-(MIN('10Y_Ramp'!M8,'10Y_Ramp'!M15)*Control!$C$23*365*Control!$C$14))*Control!$C$26
A17: Newcastle energy cost | B17: ZAR'000 | D17: =(('10Y_Ramp'!D9*(Control!$C$22+Control!$C$23)*365*Control!$C$14)-(MIN('10Y_Ramp'!D9,'10Y_Ramp'!D16)*Control!$C$23*365*Control!$C$14))*Control!$C$25 | E17: =(('10Y_Ramp'!E9*(Control!$C$22+Control!$C$23)*365*Control!$C$14)-(MIN('10Y_Ramp'!E9,'10Y_Ramp'!E16)*Control!$C$23*365*Control!$C$14))*Control!$C$25 | F17: =(('10Y_Ramp'!F9*(Control!$C$22+Control!$C$23)*365*Control!$C$14)-(MIN('10Y_Ramp'!F9,'10Y_Ramp'!F16)*Control!$C$23*365*Control!$C$14))*Control!$C$25 | G17: =(('10Y_Ramp'!G9*(Control!$C$22+Control!$C$23)*365*Control!$C$14)-(MIN('10Y_Ramp'!G9,'10Y_Ramp'!G16)*Control!$C$23*365*Control!$C$14))*Control!$C$25 | H17: =(('10Y_Ramp'!H9*(Control!$C$22+Control!$C$23)*365*Control!$C$14)-(MIN('10Y_Ramp'!H9,'10Y_Ramp'!H16)*Control!$C$23*365*Control!$C$14))*Control!$C$25 | I17: =(('10Y_Ramp'!I9*(Control!$C$22+Control!$C$23)*365*Control!$C$14)-(MIN('10Y_Ramp'!I9,'10Y_Ramp'!I16)*Control!$C$23*365*Control!$C$14))*Control!$C$25 | J17: =(('10Y_Ramp'!J9*(Control!$C$22+Control!$C$23)*365*Control!$C$14)-(MIN('10Y_Ramp'!J9,'10Y_Ramp'!J16)*Control!$C$23*365*Control!$C$14))*Control!$C$25 | K17: =(('10Y_Ramp'!K9*(Control!$C$22+Control!$C$23)*365*Control!$C$14)-(MIN('10Y_Ramp'!K9,'10Y_Ramp'!K16)*Control!$C$23*365*Control!$C$14))*Control!$C$25 | ... M17: =(('10Y_Ramp'!M9*(Control!$C$22+Control!$C$23)*365*Control!$C$14)-(MIN('10Y_Ramp'!M9,'10Y_Ramp'!M16)*Control!$C$23*365*Control!$C$14))*Control!$C$25
A18: Saldanha energy cost | B18: ZAR'000 | D18: =(('10Y_Ramp'!D10*(Control!$C$22+Control!$C$23)*365*Control!$C$14)-(MIN('10Y_Ramp'!D10,'10Y_Ramp'!D17)*Control!$C$23*365*Control!$C$14))*Control!$C$25 | E18: =(('10Y_Ramp'!E10*(Control!$C$22+Control!$C$23)*365*Control!$C$14)-(MIN('10Y_Ramp'!E10,'10Y_Ramp'!E17)*Control!$C$23*365*Control!$C$14))*Control!$C$25 | F18: =(('10Y_Ramp'!F10*(Control!$C$22+Control!$C$23)*365*Control!$C$14)-(MIN('10Y_Ramp'!F10,'10Y_Ramp'!F17)*Control!$C$23*365*Control!$C$14))*Control!$C$25 | G18: =(('10Y_Ramp'!G10*(Control!$C$22+Control!$C$23)*365*Control!$C$14)-(MIN('10Y_Ramp'!G10,'10Y_Ramp'!G17)*Control!$C$23*365*Control!$C$14))*Control!$C$25 | H18: =(('10Y_Ramp'!H10*(Control!$C$22+Control!$C$23)*365*Control!$C$14)-(MIN('10Y_Ramp'!H10,'10Y_Ramp'!H17)*Control!$C$23*365*Control!$C$14))*Control!$C$25 | I18: =(('10Y_Ramp'!I10*(Control!$C$22+Control!$C$23)*365*Control!$C$14)-(MIN('10Y_Ramp'!I10,'10Y_Ramp'!I17)*Control!$C$23*365*Control!$C$14))*Control!$C$25 | J18: =(('10Y_Ramp'!J10*(Control!$C$22+Control!$C$23)*365*Control!$C$14)-(MIN('10Y_Ramp'!J10,'10Y_Ramp'!J17)*Control!$C$23*365*Control!$C$14))*Control!$C$25 | K18: =(('10Y_Ramp'!K10*(Control!$C$22+Control!$C$23)*365*Control!$C$14)-(MIN('10Y_Ramp'!K10,'10Y_Ramp'!K17)*Control!$C$23*365*Control!$C$14))*Control!$C$25 | ... M18: =(('10Y_Ramp'!M10*(Control!$C$22+Control!$C$23)*365*Control!$C$14)-(MIN('10Y_Ramp'!M10,'10Y_Ramp'!M17)*Control!$C$23*365*Control!$C$14))*Control!$C$25
A19: Komati energy cost | B19: ZAR'000 | D19: =(('10Y_Ramp'!D11*(Control!$C$22+Control!$C$23)*365*Control!$C$14)-(MIN('10Y_Ramp'!D11,'10Y_Ramp'!D18)*Control!$C$23*365*Control!$C$14))*Control!$C$25 | E19: =(('10Y_Ramp'!E11*(Control!$C$22+Control!$C$23)*365*Control!$C$14)-(MIN('10Y_Ramp'!E11,'10Y_Ramp'!E18)*Control!$C$23*365*Control!$C$14))*Control!$C$25 | F19: =(('10Y_Ramp'!F11*(Control!$C$22+Control!$C$23)*365*Control!$C$14)-(MIN('10Y_Ramp'!F11,'10Y_Ramp'!F18)*Control!$C$23*365*Control!$C$14))*Control!$C$25 | G19: =(('10Y_Ramp'!G11*(Control!$C$22+Control!$C$23)*365*Control!$C$14)-(MIN('10Y_Ramp'!G11,'10Y_Ramp'!G18)*Control!$C$23*365*Control!$C$14))*Control!$C$25 | H19: =(('10Y_Ramp'!H11*(Control!$C$22+Control!$C$23)*365*Control!$C$14)-(MIN('10Y_Ramp'!H11,'10Y_Ramp'!H18)*Control!$C$23*365*Control!$C$14))*Control!$C$25 | I19: =(('10Y_Ramp'!I11*(Control!$C$22+Control!$C$23)*365*Control!$C$14)-(MIN('10Y_Ramp'!I11,'10Y_Ramp'!I18)*Control!$C$23*365*Control!$C$14))*Control!$C$25 | J19: =(('10Y_Ramp'!J11*(Control!$C$22+Control!$C$23)*365*Control!$C$14)-(MIN('10Y_Ramp'!J11,'10Y_Ramp'!J18)*Control!$C$23*365*Control!$C$14))*Control!$C$25 | K19: =(('10Y_Ramp'!K11*(Control!$C$22+Control!$C$23)*365*Control!$C$14)-(MIN('10Y_Ramp'!K11,'10Y_Ramp'!K18)*Control!$C$23*365*Control!$C$14))*Control!$C$25 | ... M19: =(('10Y_Ramp'!M11*(Control!$C$22+Control!$C$23)*365*Control!$C$14)-(MIN('10Y_Ramp'!M11,'10Y_Ramp'!M18)*Control!$C$23*365*Control!$C$14))*Control!$C$25
A20: Solar O&M | B20: ZAR'000 | D20: ='10Y_Ramp'!D19*Control!$C$27*Control!$C$28 | E20: ='10Y_Ramp'!E19*Control!$C$27*Control!$C$28 | F20: ='10Y_Ramp'!F19*Control!$C$27*Control!$C$28 | G20: ='10Y_Ramp'!G19*Control!$C$27*Control!$C$28 | H20: ='10Y_Ramp'!H19*Control!$C$27*Control!$C$28 | I20: ='10Y_Ramp'!I19*Control!$C$27*Control!$C$28 | J20: ='10Y_Ramp'!J19*Control!$C$27*Control!$C$28 | K20: ='10Y_Ramp'!K19*Control!$C$27*Control!$C$28 | ... M20: ='10Y_Ramp'!M19*Control!$C$27*Control!$C$28
A21: Total energy cost | B21: ZAR'000 | D21: =SUM(D15:D20) | E21: =SUM(E15:E20) | F21: =SUM(F15:F20) | G21: =SUM(G15:G20) | H21: =SUM(H15:H20) | I21: =SUM(I15:I20) | J21: =SUM(J15:J20) | K21: =SUM(K15:K20) | ... M21: =SUM(M15:M20)
A23: Salaries & benefits | B23: ZAR'000 | D23: =(Control!$C$52*Control!$C$53)+(((IF(D7>0,1,0)+IF(D8>0,1,0)+IF(D9>0,1,0)+IF(D10>0,1,0)+IF(D11>0,1,0))*Control!$C$54*Control!$C$55)+(D5*Control!$C$56*Control!$C$57)+(D5*Control!$C$58*Control!$C$59))*(1+Control!$C$60) | E23: =(Control!$C$52*Control!$C$53)+(((IF(E7>0,1,0)+IF(E8>0,1,0)+IF(E9>0,1,0)+IF(E10>0,1,0)+IF(E11>0,1,0))*Control!$C$54*Control!$C$55)+(E5*Control!$C$56*Control!$C$57)+(E5*Control!$C$58*Control!$C$59))*(1+Control!$C$60) | F23: =(Control!$C$52*Control!$C$53)+(((IF(F7>0,1,0)+IF(F8>0,1,0)+IF(F9>0,1,0)+IF(F10>0,1,0)+IF(F11>0,1,0))*Control!$C$54*Control!$C$55)+(F5*Control!$C$56*Control!$C$57)+(F5*Control!$C$58*Control!$C$59))*(1+Control!$C$60) | G23: =(Control!$C$52*Control!$C$53)+(((IF(G7>0,1,0)+IF(G8>0,1,0)+IF(G9>0,1,0)+IF(G10>0,1,0)+IF(G11>0,1,0))*Control!$C$54*Control!$C$55)+(G5*Control!$C$56*Control!$C$57)+(G5*Control!$C$58*Control!$C$59))*(1+Control!$C$60) | H23: =(Control!$C$52*Control!$C$53)+(((IF(H7>0,1,0)+IF(H8>0,1,0)+IF(H9>0,1,0)+IF(H10>0,1,0)+IF(H11>0,1,0))*Control!$C$54*Control!$C$55)+(H5*Control!$C$56*Control!$C$57)+(H5*Control!$C$58*Control!$C$59))*(1+Control!$C$60) | I23: =(Control!$C$52*Control!$C$53)+(((IF(I7>0,1,0)+IF(I8>0,1,0)+IF(I9>0,1,0)+IF(I10>0,1,0)+IF(I11>0,1,0))*Control!$C$54*Control!$C$55)+(I5*Control!$C$56*Control!$C$57)+(I5*Control!$C$58*Control!$C$59))*(1+Control!$C$60) | J23: =(Control!$C$52*Control!$C$53)+(((IF(J7>0,1,0)+IF(J8>0,1,0)+IF(J9>0,1,0)+IF(J10>0,1,0)+IF(J11>0,1,0))*Control!$C$54*Control!$C$55)+(J5*Control!$C$56*Control!$C$57)+(J5*Control!$C$58*Control!$C$59))*(1+Control!$C$60) | K23: =(Control!$C$52*Control!$C$53)+(((IF(K7>0,1,0)+IF(K8>0,1,0)+IF(K9>0,1,0)+IF(K10>0,1,0)+IF(K11>0,1,0))*Control!$C$54*Control!$C$55)+(K5*Control!$C$56*Control!$C$57)+(K5*Control!$C$58*Control!$C$59))*(1+Control!$C$60) | ... M23: =(Control!$C$52*Control!$C$53)+(((IF(M7>0,1,0)+IF(M8>0,1,0)+IF(M9>0,1,0)+IF(M10>0,1,0)+IF(M11>0,1,0))*Control!$C$54*Control!$C$55)+(M5*Control!$C$56*Control!$C$57)+(M5*Control!$C$58*Control!$C$59))*(1+Control!$C$60)
A24: Admin / travel / software / office / legal | B24: ZAR'000 | D24: =(D23/(1+Control!$C$60))*Control!$C$61+((Control!$C$52+(IF(D7>0,1,0)+IF(D8>0,1,0)+IF(D9>0,1,0)+IF(D10>0,1,0)+IF(D11>0,1,0))*Control!$C$54+(D5*Control!$C$56)+(D5*Control!$C$58))*Control!$C$63*12)+(((IF(D7>0,1,0)+IF(D8>0,1,0)+IF(D9>0,1,0)+IF(D10>0,1,0)+IF(D11>0,1,0))*Control!$C$64*12))+(Control!$C$67*12)+(Control!$C$66*12)+(Control!$C$65*12) | E24: =(E23/(1+Control!$C$60))*Control!$C$61+((Control!$C$52+(IF(E7>0,1,0)+IF(E8>0,1,0)+IF(E9>0,1,0)+IF(E10>0,1,0)+IF(E11>0,1,0))*Control!$C$54+(E5*Control!$C$56)+(E5*Control!$C$58))*Control!$C$63*12)+(((IF(E7>0,1,0)+IF(E8>0,1,0)+IF(E9>0,1,0)+IF(E10>0,1,0)+IF(E11>0,1,0))*Control!$C$64*12))+(Control!$C$67*12)+(Control!$C$66*12)+(Control!$C$65*12) | F24: =(F23/(1+Control!$C$60))*Control!$C$61+((Control!$C$52+(IF(F7>0,1,0)+IF(F8>0,1,0)+IF(F9>0,1,0)+IF(F10>0,1,0)+IF(F11>0,1,0))*Control!$C$54+(F5*Control!$C$56)+(F5*Control!$C$58))*Control!$C$63*12)+(((IF(F7>0,1,0)+IF(F8>0,1,0)+IF(F9>0,1,0)+IF(F10>0,1,0)+IF(F11>0,1,0))*Control!$C$64*12))+(Control!$C$67*12)+(Control!$C$66*12)+(Control!$C$65*12) | G24: =(G23/(1+Control!$C$60))*Control!$C$61+((Control!$C$52+(IF(G7>0,1,0)+IF(G8>0,1,0)+IF(G9>0,1,0)+IF(G10>0,1,0)+IF(G11>0,1,0))*Control!$C$54+(G5*Control!$C$56)+(G5*Control!$C$58))*Control!$C$63*12)+(((IF(G7>0,1,0)+IF(G8>0,1,0)+IF(G9>0,1,0)+IF(G10>0,1,0)+IF(G11>0,1,0))*Control!$C$64*12))+(Control!$C$67*12)+(Control!$C$66*12)+(Control!$C$65*12) | H24: =(H23/(1+Control!$C$60))*Control!$C$61+((Control!$C$52+(IF(H7>0,1,0)+IF(H8>0,1,0)+IF(H9>0,1,0)+IF(H10>0,1,0)+IF(H11>0,1,0))*Control!$C$54+(H5*Control!$C$56)+(H5*Control!$C$58))*Control!$C$63*12)+(((IF(H7>0,1,0)+IF(H8>0,1,0)+IF(H9>0,1,0)+IF(H10>0,1,0)+IF(H11>0,1,0))*Control!$C$64*12))+(Control!$C$67*12)+(Control!$C$66*12)+(Control!$C$65*12) | I24: =(I23/(1+Control!$C$60))*Control!$C$61+((Control!$C$52+(IF(I7>0,1,0)+IF(I8>0,1,0)+IF(I9>0,1,0)+IF(I10>0,1,0)+IF(I11>0,1,0))*Control!$C$54+(I5*Control!$C$56)+(I5*Control!$C$58))*Control!$C$63*12)+(((IF(I7>0,1,0)+IF(I8>0,1,0)+IF(I9>0,1,0)+IF(I10>0,1,0)+IF(I11>0,1,0))*Control!$C$64*12))+(Control!$C$67*12)+(Control!$C$66*12)+(Control!$C$65*12) | J24: =(J23/(1+Control!$C$60))*Control!$C$61+((Control!$C$52+(IF(J7>0,1,0)+IF(J8>0,1,0)+IF(J9>0,1,0)+IF(J10>0,1,0)+IF(J11>0,1,0))*Control!$C$54+(J5*Control!$C$56)+(J5*Control!$C$58))*Control!$C$63*12)+(((IF(J7>0,1,0)+IF(J8>0,1,0)+IF(J9>0,1,0)+IF(J10>0,1,0)+IF(J11>0,1,0))*Control!$C$64*12))+(Control!$C$67*12)+(Control!$C$66*12)+(Control!$C$65*12) | K24: =(K23/(1+Control!$C$60))*Control!$C$61+((Control!$C$52+(IF(K7>0,1,0)+IF(K8>0,1,0)+IF(K9>0,1,0)+IF(K10>0,1,0)+IF(K11>0,1,0))*Control!$C$54+(K5*Control!$C$56)+(K5*Control!$C$58))*Control!$C$63*12)+(((IF(K7>0,1,0)+IF(K8>0,1,0)+IF(K9>0,1,0)+IF(K10>0,1,0)+IF(K11>0,1,0))*Control!$C$64*12))+(Control!$C$67*12)+(Control!$C$66*12)+(Control!$C$65*12) | ... M24: =(M23/(1+Control!$C$60))*Control!$C$61+((Control!$C$52+(IF(M7>0,1,0)+IF(M8>0,1,0)+IF(M9>0,1,0)+IF(M10>0,1,0)+IF(M11>0,1,0))*Control!$C$54+(M5*Control!$C$56)+(M5*Control!$C$58))*Control!$C$63*12)+(((IF(M7>0,1,0)+IF(M8>0,1,0)+IF(M9>0,1,0)+IF(M10>0,1,0)+IF(M11>0,1,0))*Control!$C$64*12))+(Control!$C$67*12)+(Control!$C$66*12)+(Control!$C$65*12)
A25: Security / tools / utilities | B25: ZAR'000 | D25: =((IF(D7>0,1,0)+IF(D8>0,1,0)+IF(D9>0,1,0)+IF(D10>0,1,0)+IF(D11>0,1,0))*Control!$C$69*12)+(D5*Control!$C$68*12)+(D5*Control!$C$70*12) | E25: =((IF(E7>0,1,0)+IF(E8>0,1,0)+IF(E9>0,1,0)+IF(E10>0,1,0)+IF(E11>0,1,0))*Control!$C$69*12)+(E5*Control!$C$68*12)+(E5*Control!$C$70*12) | F25: =((IF(F7>0,1,0)+IF(F8>0,1,0)+IF(F9>0,1,0)+IF(F10>0,1,0)+IF(F11>0,1,0))*Control!$C$69*12)+(F5*Control!$C$68*12)+(F5*Control!$C$70*12) | G25: =((IF(G7>0,1,0)+IF(G8>0,1,0)+IF(G9>0,1,0)+IF(G10>0,1,0)+IF(G11>0,1,0))*Control!$C$69*12)+(G5*Control!$C$68*12)+(G5*Control!$C$70*12) | H25: =((IF(H7>0,1,0)+IF(H8>0,1,0)+IF(H9>0,1,0)+IF(H10>0,1,0)+IF(H11>0,1,0))*Control!$C$69*12)+(H5*Control!$C$68*12)+(H5*Control!$C$70*12) | I25: =((IF(I7>0,1,0)+IF(I8>0,1,0)+IF(I9>0,1,0)+IF(I10>0,1,0)+IF(I11>0,1,0))*Control!$C$69*12)+(I5*Control!$C$68*12)+(I5*Control!$C$70*12) | J25: =((IF(J7>0,1,0)+IF(J8>0,1,0)+IF(J9>0,1,0)+IF(J10>0,1,0)+IF(J11>0,1,0))*Control!$C$69*12)+(J5*Control!$C$68*12)+(J5*Control!$C$70*12) | K25: =((IF(K7>0,1,0)+IF(K8>0,1,0)+IF(K9>0,1,0)+IF(K10>0,1,0)+IF(K11>0,1,0))*Control!$C$69*12)+(K5*Control!$C$68*12)+(K5*Control!$C$70*12) | ... M25: =((IF(M7>0,1,0)+IF(M8>0,1,0)+IF(M9>0,1,0)+IF(M10>0,1,0)+IF(M11>0,1,0))*Control!$C$69*12)+(M5*Control!$C$68*12)+(M5*Control!$C$70*12)
A26: Total cash opex | B26: ZAR'000 | D26: =D21+D23+D24+D25 | E26: =E21+E23+E24+E25 | F26: =F21+F23+F24+F25 | G26: =G21+G23+G24+G25 | H26: =H21+H23+H24+H25 | I26: =I21+I23+I24+I25 | J26: =J21+J23+J24+J25 | K26: =K21+K23+K24+K25 | ... M26: =M21+M23+M24+M25
A27: EBITDA | B27: ZAR'000 | D27: =D13-D26 | E27: =E13-E26 | F27: =F13-F26 | G27: =G13-G26 | H27: =H13-H26 | I27: =I13-I26 | J27: =J13-J26 | K27: =K13-K26 | ... M27: =M13-M26
A29: New MW | B29: MW | D29: ='10Y_Ramp'!D12 | E29: =MAX('10Y_Ramp'!E12-'10Y_Ramp'!D12,0) | F29: =MAX('10Y_Ramp'!F12-'10Y_Ramp'!E12,0) | G29: =MAX('10Y_Ramp'!G12-'10Y_Ramp'!F12,0) | H29: =MAX('10Y_Ramp'!H12-'10Y_Ramp'!G12,0) | I29: =MAX('10Y_Ramp'!I12-'10Y_Ramp'!H12,0) | J29: =MAX('10Y_Ramp'!J12-'10Y_Ramp'!I12,0) | K29: =MAX('10Y_Ramp'!K12-'10Y_Ramp'!J12,0) | L29: =MAX('10Y_Ramp'!L12-'10Y_Ramp'!K12,0) | M29: =MAX('10Y_Ramp'!M12-'10Y_Ramp'!L12,0)
A30: New solar MW | B30: MW | D30: ='10Y_Ramp'!D19 | E30: =MAX('10Y_Ramp'!E19-'10Y_Ramp'!D19,0) | F30: =MAX('10Y_Ramp'!F19-'10Y_Ramp'!E19,0) | G30: =MAX('10Y_Ramp'!G19-'10Y_Ramp'!F19,0) | H30: =MAX('10Y_Ramp'!H19-'10Y_Ramp'!G19,0) | I30: =MAX('10Y_Ramp'!I19-'10Y_Ramp'!H19,0) | J30: =MAX('10Y_Ramp'!J19-'10Y_Ramp'!I19,0) | K30: =MAX('10Y_Ramp'!K19-'10Y_Ramp'!J19,0) | L30: =MAX('10Y_Ramp'!L19-'10Y_Ramp'!K19,0) | M30: =MAX('10Y_Ramp'!M19-'10Y_Ramp'!L19,0)
A31: New containers | B31: containers | D31: =ROUNDUP(D29/Control!$C$37,0) | E31: =ROUNDUP(E29/Control!$C$37,0) | F31: =ROUNDUP(F29/Control!$C$37,0) | G31: =ROUNDUP(G29/Control!$C$37,0) | H31: =ROUNDUP(H29/Control!$C$37,0) | I31: =ROUNDUP(I29/Control!$C$37,0) | J31: =ROUNDUP(J29/Control!$C$37,0) | K31: =ROUNDUP(K29/Control!$C$37,0) | ... M31: =ROUNDUP(M29/Control!$C$37,0)
A32: Miner capex | B32: ZAR'000 | D32: =(D29/(1+Control!$C$34))*1000000/Control!$C$32*Control!$C$33*Control!$C$4/1000 | E32: =(E29/(1+Control!$C$34))*1000000/Control!$C$32*Control!$C$33*Control!$C$4/1000 | F32: =(F29/(1+Control!$C$34))*1000000/Control!$C$32*Control!$C$33*Control!$C$4/1000 | G32: =(G29/(1+Control!$C$34))*1000000/Control!$C$32*Control!$C$33*Control!$C$4/1000 | H32: =(H29/(1+Control!$C$34))*1000000/Control!$C$32*Control!$C$33*Control!$C$4/1000 | I32: =(I29/(1+Control!$C$34))*1000000/Control!$C$32*Control!$C$33*Control!$C$4/1000 | J32: =(J29/(1+Control!$C$34))*1000000/Control!$C$32*Control!$C$33*Control!$C$4/1000 | K32: =(K29/(1+Control!$C$34))*1000000/Control!$C$32*Control!$C$33*Control!$C$4/1000 | ... M32: =(M29/(1+Control!$C$34))*1000000/Control!$C$32*Control!$C$33*Control!$C$4/1000
A33: Container capex | B33: ZAR'000 | D33: =D31*Control!$C$36*Control!$C$4/1000 | E33: =E31*Control!$C$36*Control!$C$4/1000 | F33: =F31*Control!$C$36*Control!$C$4/1000 | G33: =G31*Control!$C$36*Control!$C$4/1000 | H33: =H31*Control!$C$36*Control!$C$4/1000 | I33: =I31*Control!$C$36*Control!$C$4/1000 | J33: =J31*Control!$C$36*Control!$C$4/1000 | K33: =K31*Control!$C$36*Control!$C$4/1000 | ... M33: =M31*Control!$C$36*Control!$C$4/1000
A34: Electrical EPC capex (site-fixed + variable/MW) | B34: ZAR'000 | D34: =(IF('10Y_Ramp'!D7>0,1,0)+IF('10Y_Ramp'!D8>0,1,0)+IF('10Y_Ramp'!D9>0,1,0)+IF('10Y_Ramp'!D10>0,1,0)+IF('10Y_Ramp'!D11>0,1,0))*CAPEX_Electrical_Detail!$C$26+D29*CAPEX_Electrical_Detail!$C$27 | E34: =(IF(AND('10Y_Ramp'!D7=0,'10Y_Ramp'!E7>0),1,0)+IF(AND('10Y_Ramp'!D8=0,'10Y_Ramp'!E8>0),1,0)+IF(AND('10Y_Ramp'!D9=0,'10Y_Ramp'!E9>0),1,0)+IF(AND('10Y_Ramp'!D10=0,'10Y_Ramp'!E10>0),1,0)+IF(AND('10Y_Ramp'!D11=0,'10Y_Ramp'!E11>0),1,0))*CAPEX_Electrical_Detail!$C$26+E29*CAPEX_Electrical_Detail!$C$27 | F34: =(IF(AND('10Y_Ramp'!E7=0,'10Y_Ramp'!F7>0),1,0)+IF(AND('10Y_Ramp'!E8=0,'10Y_Ramp'!F8>0),1,0)+IF(AND('10Y_Ramp'!E9=0,'10Y_Ramp'!F9>0),1,0)+IF(AND('10Y_Ramp'!E10=0,'10Y_Ramp'!F10>0),1,0)+IF(AND('10Y_Ramp'!E11=0,'10Y_Ramp'!F11>0),1,0))*CAPEX_Electrical_Detail!$C$26+F29*CAPEX_Electrical_Detail!$C$27 | G34: =(IF(AND('10Y_Ramp'!F7=0,'10Y_Ramp'!G7>0),1,0)+IF(AND('10Y_Ramp'!F8=0,'10Y_Ramp'!G8>0),1,0)+IF(AND('10Y_Ramp'!F9=0,'10Y_Ramp'!G9>0),1,0)+IF(AND('10Y_Ramp'!F10=0,'10Y_Ramp'!G10>0),1,0)+IF(AND('10Y_Ramp'!F11=0,'10Y_Ramp'!G11>0),1,0))*CAPEX_Electrical_Detail!$C$26+G29*CAPEX_Electrical_Detail!$C$27 | H34: =(IF(AND('10Y_Ramp'!G7=0,'10Y_Ramp'!H7>0),1,0)+IF(AND('10Y_Ramp'!G8=0,'10Y_Ramp'!H8>0),1,0)+IF(AND('10Y_Ramp'!G9=0,'10Y_Ramp'!H9>0),1,0)+IF(AND('10Y_Ramp'!G10=0,'10Y_Ramp'!H10>0),1,0)+IF(AND('10Y_Ramp'!G11=0,'10Y_Ramp'!H11>0),1,0))*CAPEX_Electrical_Detail!$C$26+H29*CAPEX_Electrical_Detail!$C$27 | I34: =(IF(AND('10Y_Ramp'!H7=0,'10Y_Ramp'!I7>0),1,0)+IF(AND('10Y_Ramp'!H8=0,'10Y_Ramp'!I8>0),1,0)+IF(AND('10Y_Ramp'!H9=0,'10Y_Ramp'!I9>0),1,0)+IF(AND('10Y_Ramp'!H10=0,'10Y_Ramp'!I10>0),1,0)+IF(AND('10Y_Ramp'!H11=0,'10Y_Ramp'!I11>0),1,0))*CAPEX_Electrical_Detail!$C$26+I29*CAPEX_Electrical_Detail!$C$27 | J34: =(IF(AND('10Y_Ramp'!I7=0,'10Y_Ramp'!J7>0),1,0)+IF(AND('10Y_Ramp'!I8=0,'10Y_Ramp'!J8>0),1,0)+IF(AND('10Y_Ramp'!I9=0,'10Y_Ramp'!J9>0),1,0)+IF(AND('10Y_Ramp'!I10=0,'10Y_Ramp'!J10>0),1,0)+IF(AND('10Y_Ramp'!I11=0,'10Y_Ramp'!J11>0),1,0))*CAPEX_Electrical_Detail!$C$26+J29*CAPEX_Electrical_Detail!$C$27 | K34: =(IF(AND('10Y_Ramp'!J7=0,'10Y_Ramp'!K7>0),1,0)+IF(AND('10Y_Ramp'!J8=0,'10Y_Ramp'!K8>0),1,0)+IF(AND('10Y_Ramp'!J9=0,'10Y_Ramp'!K9>0),1,0)+IF(AND('10Y_Ramp'!J10=0,'10Y_Ramp'!K10>0),1,0)+IF(AND('10Y_Ramp'!J11=0,'10Y_Ramp'!K11>0),1,0))*CAPEX_Electrical_Detail!$C$26+K29*CAPEX_Electrical_Detail!$C$27 | L34: =(IF(AND('10Y_Ramp'!K7=0,'10Y_Ramp'!L7>0),1,0)+IF(AND('10Y_Ramp'!K8=0,'10Y_Ramp'!L8>0),1,0)+IF(AND('10Y_Ramp'!K9=0,'10Y_Ramp'!L9>0),1,0)+IF(AND('10Y_Ramp'!K10=0,'10Y_Ramp'!L10>0),1,0)+IF(AND('10Y_Ramp'!K11=0,'10Y_Ramp'!L11>0),1,0))*CAPEX_Electrical_Detail!$C$26+L29*CAPEX_Electrical_Detail!$C$27 | M34: =(IF(AND('10Y_Ramp'!L7=0,'10Y_Ramp'!M7>0),1,0)+IF(AND('10Y_Ramp'!L8=0,'10Y_Ramp'!M8>0),1,0)+IF(AND('10Y_Ramp'!L9=0,'10Y_Ramp'!M9>0),1,0)+IF(AND('10Y_Ramp'!L10=0,'10Y_Ramp'!M10>0),1,0)+IF(AND('10Y_Ramp'!L11=0,'10Y_Ramp'!M11>0),1,0))*CAPEX_Electrical_Detail!$C$26+M29*CAPEX_Electrical_Detail!$C$27
A35: Solar capex | B35: ZAR'000 | D35: =D30*Control!$C$27 | E35: =E30*Control!$C$27 | F35: =F30*Control!$C$27 | G35: =G30*Control!$C$27 | H35: =H30*Control!$C$27 | I35: =I30*Control!$C$27 | J35: =J30*Control!$C$27 | K35: =K30*Control!$C$27 | ... M35: =M30*Control!$C$27
A36: Logistics / duties / spares | B36: ZAR'000 | D36: =(D31*Control!$C$40*Control!$C$4/1000)+(D31*(Control!$C$41+Control!$C$42+Control!$C$43))+((D32+D33)*(Control!$C$44+Control!$C$45+Control!$C$46))+((IF(D7>0,1,0)+IF(D8>0,1,0)+IF(D9>0,1,0)+IF(D10>0,1,0)+IF(D11>0,1,0))*Control!$C$47*0.25) | E36: =(E31*Control!$C$40*Control!$C$4/1000)+(E31*(Control!$C$41+Control!$C$42+Control!$C$43))+((E32+E33)*(Control!$C$44+Control!$C$45+Control!$C$46))+((IF(E7>0,1,0)+IF(E8>0,1,0)+IF(E9>0,1,0)+IF(E10>0,1,0)+IF(E11>0,1,0))*Control!$C$47*0.25) | F36: =(F31*Control!$C$40*Control!$C$4/1000)+(F31*(Control!$C$41+Control!$C$42+Control!$C$43))+((F32+F33)*(Control!$C$44+Control!$C$45+Control!$C$46))+((IF(F7>0,1,0)+IF(F8>0,1,0)+IF(F9>0,1,0)+IF(F10>0,1,0)+IF(F11>0,1,0))*Control!$C$47*0.25) | G36: =(G31*Control!$C$40*Control!$C$4/1000)+(G31*(Control!$C$41+Control!$C$42+Control!$C$43))+((G32+G33)*(Control!$C$44+Control!$C$45+Control!$C$46))+((IF(G7>0,1,0)+IF(G8>0,1,0)+IF(G9>0,1,0)+IF(G10>0,1,0)+IF(G11>0,1,0))*Control!$C$47*0.25) | H36: =(H31*Control!$C$40*Control!$C$4/1000)+(H31*(Control!$C$41+Control!$C$42+Control!$C$43))+((H32+H33)*(Control!$C$44+Control!$C$45+Control!$C$46))+((IF(H7>0,1,0)+IF(H8>0,1,0)+IF(H9>0,1,0)+IF(H10>0,1,0)+IF(H11>0,1,0))*Control!$C$47*0.25) | I36: =(I31*Control!$C$40*Control!$C$4/1000)+(I31*(Control!$C$41+Control!$C$42+Control!$C$43))+((I32+I33)*(Control!$C$44+Control!$C$45+Control!$C$46))+((IF(I7>0,1,0)+IF(I8>0,1,0)+IF(I9>0,1,0)+IF(I10>0,1,0)+IF(I11>0,1,0))*Control!$C$47*0.25) | J36: =(J31*Control!$C$40*Control!$C$4/1000)+(J31*(Control!$C$41+Control!$C$42+Control!$C$43))+((J32+J33)*(Control!$C$44+Control!$C$45+Control!$C$46))+((IF(J7>0,1,0)+IF(J8>0,1,0)+IF(J9>0,1,0)+IF(J10>0,1,0)+IF(J11>0,1,0))*Control!$C$47*0.25) | K36: =(K31*Control!$C$40*Control!$C$4/1000)+(K31*(Control!$C$41+Control!$C$42+Control!$C$43))+((K32+K33)*(Control!$C$44+Control!$C$45+Control!$C$46))+((IF(K7>0,1,0)+IF(K8>0,1,0)+IF(K9>0,1,0)+IF(K10>0,1,0)+IF(K11>0,1,0))*Control!$C$47*0.25) | ... M36: =(M31*Control!$C$40*Control!$C$4/1000)+(M31*(Control!$C$41+Control!$C$42+Control!$C$43))+((M32+M33)*(Control!$C$44+Control!$C$45+Control!$C$46))+((IF(M7>0,1,0)+IF(M8>0,1,0)+IF(M9>0,1,0)+IF(M10>0,1,0)+IF(M11>0,1,0))*Control!$C$47*0.25)
A37: Total capex | B37: ZAR'000 | D37: =D32+D33+D34+D35+D36 | E37: =E32+E33+E34+E35+E36 | F37: =F32+F33+F34+F35+F36 | G37: =G32+G33+G34+G35+G36 | H37: =H32+H33+H34+H35+H36 | I37: =I32+I33+I34+I35+I36 | J37: =J32+J33+J34+J35+J36 | K37: =K32+K33+K34+K35+K36 | ... M37: =M32+M33+M34+M35+M36
A38: Annual cash flow before financing | B38: ZAR'000 | D38: =D27-D37 | E38: =E27-E37 | F38: =F27-F37 | G38: =G27-G37 | H38: =H27-H37 | I38: =I27-I37 | J38: =J27-J37 | K38: =K27-K37 | ... M38: =M27-M37
D40: =Control!$C$6 | E40: =D40*(1+Control!$C$7) | F40: =E40*(1+Control!$C$7) | G40: =F40*(1+Control!$C$7) | H40: =G40*(1+Control!$C$7) | I40: =H40*(1+Control!$C$7) | J40: =I40*(1+Control!$C$7) | K40: =J40*(1+Control!$C$7) | L40: =K40*(1+Control!$C$7) | M40: =L40*(1+Control!$C$7)
D41: =Control!$C$8 | E41: =D41*(1+Control!$C$9) | F41: =E41*(1+Control!$C$9) | G41: =F41*(1+Control!$C$9) | H41: =G41*(1+Control!$C$9) | I41: =H41*(1+Control!$C$9) | J41: =I41*(1+Control!$C$9) | K41: =J41*(1+Control!$C$9) | L41: =K41*(1+Control!$C$9) | M41: =L41*(1+Control!$C$9)

Sheet Checks
A1: Model Checks
A3: Check | B3: Formula / Output | C3: Interpretation | D3: Status
A4: Phase 1 total MW closes at 20 | B4: ='12M_Deployment'!O8+'12M_Deployment'!O7 | C4: Should equal 20MW | D4: =IF(B4=20,"PASS","CHECK")
A5: M7DS efficiency input | B5: =Control!C31 | C5: Should equal 12.5 J/T | D5: =IF(B5=12.5,"PASS","CHECK")
A6: Base-case DR revenue | B6: =SUM('12M_Revenue'!D15:O15) | C6: Should be 0 if DR flag is off | D6: =IF(B6=0,"PASS","CHECK")
A7: Base-case hyperscaler revenue | B7: =SUM('12M_Revenue'!D18:O18) | C7: Should be 0 if hyperscaler flag is off | D7: =IF(B7=0,"PASS","CHECK")
A8: 10Y ramp hits 2GW | B8: ='10Y_Ramp'!M12 | C8: Should equal 2,000MW | D8: =IF(B8=2000,"PASS","CHECK")
A9: No negative ending cash if funding added | B9: =MIN('12M_Cashflow'!D14:O14) | C9: Without funding this can be negative; add funding if needed | D9: =IF(B9>=0,"FUNDED","BURN")
A10: Phase 1 year-1 BTC mined | B10: ='12M_Cashflow'!C20 | C10: Informational | D10: INFO
A11: Peak funding required | B11: ='12M_Cashflow'!C25 | C11: Informational | D11: INFO
A12: Electrical EPC basis date | B12: 25 Mar 2026 | C12: T2603-24 quote date | D12: INFO
A13: Miner vendor finance shares sum to 100% | B13: =Control!C98+Control!C99 | C13: Should equal 1.00 | D13: =IF(ABS(B13-1)<0.0001,"PASS","CHECK")
A14: EPC tranche shares sum to 100% | B14: =Control!C103+Control!C104+Control!C105+Control!C106+Control!C107 | C14: Should equal 1.00 | D14: =IF(ABS(B14-1)<0.0001,"PASS","CHECK")
A15: External funding shares sum to 100% | B15: =Control!C110+Control!C111 | C15: Should equal 1.00 | D15: =IF(ABS(B15-1)<0.0001,"PASS","CHECK")
A16: Funding sheet closes to cashflow | B16: ='12M_Funding'!O12-'12M_Cashflow'!O14 | C16: Should equal 0 | D16: =IF(ABS(B16)<0.0001,"PASS","CHECK")
A17: Year-1 ending cash after funding | B17: ='12M_Cashflow'!C29 | C17: Informational | D17: INFO
