Workbook

Sheet Dashboard
A1: BitMach | Simplified 20MW Phase 1 Model (36 months)
A2: Equity-first base case for management and investor conversations. Detailed master model remains separate; optional revenue and debt are included only as editable upside levers.
A4: Headline KPIs
A5: Phase 1 envelope (MW) | D5: Site split (GVL / AMSA MW) | G5: 36M BTC mined | J5: 36M revenue (base)
A6: =Inputs!C7 -> 20 | D6: =Inputs!C8&" / "&Inputs!C9 -> 15 / 5 | G6: =SUM(Annual_Summary!C11:E11) -> 649.36229 | J6: =SUM(Annual_Summary!C12:E12) -> 1036384.4
A8: Peak funding required | D8: Total equity required | G8: Year 3 EBITDA | J8: End-36M cash
A9: =Annual_Summary!C25 -> 470888.25 | D9: =Annual_Summary!C26 -> 470888.25 | G9: =Annual_Summary!E15 -> 255462.49 | J9: =Annual_Summary!E21 -> 589548.42
A11: Implied payback (yrs) | D11: Year 1 capex | G11: Year 2 unlevered CF | J11: Optionality toggles
A12: =IF(Annual_Summary!E15=0,"",SUM(Annual_Summary!C17:E17)/Annual_Summary!E15) -> 1.9783947 | D12: =Annual_Summary!C17 -> 505405.63 | G12: =Annual_Summary!D18 -> 232752.44 | J12: =IF(AND(Inputs!C82=0,Inputs!C87=0),"DR OFF / HYP OFF","UPSIDE ON") -> DR OFF / HYP OFF
A16: Annual output summary | G16: Site deployment and revenue architecture
A17: Metric | B17: Year 1 | C17: Year 2 | D17: Year 3 | E17: 36M total | F17: Comment | G17: Topic | H17: Base case | I17: Why it matters | J17: Edit at | K17: Current phase footprint | L17: MW
A18: Year-end gross MW | B18: =Annual_Summary!C7 -> 20 | C18: =Annual_Summary!D7 -> 20 | D18: =Annual_Summary!E7 -> 20 | E18: =D18 -> 20 | F18: Gross compute MW in place | G18: Grootvlei compute | H18: 15MW by month 5 | 22h/day | I18: Primary production node and Eskom brownfield anchor | J18: Inputs / Deployment_36M | K18: Phase 1 total gross | L18: =Inputs!C7 -> 20
A19: BTC mined | B19: =Annual_Summary!C11 -> 177.7338 | C19: =Annual_Summary!D11 -> 247.36135 | D19: =Annual_Summary!E11 -> 224.26714 | E19: =SUM(B19:D19) -> 649.36229 | F19: Bitcoin produced | G19: AMSA compute | H19: 5MW by month 6 | I19: Adds industrial diversification and solar blend pathway | J19: Inputs / Deployment_36M | K19: Year-end Grootvlei | L19: =Annual_Summary!C8 -> 15
A20: Revenue (base) | B20: =Annual_Summary!C12 -> 246952.8 | C20: =Annual_Summary!D12 -> 386487.07 | D20: =Annual_Summary!E12 -> 402944.55 | E20: =SUM(B20:D20) -> 1036384.4 | F20: BTC revenue only | G20: AMSA solar | H20: 10MW from month 5 | I20: Reduces blended energy cost materially | J20: Inputs / Deployment_36M | K20: Year-end AMSA | L20: =Annual_Summary!C9 -> 5
A21: Cash opex | B21: =Annual_Summary!C14 -> 111101.93 | C21: =Annual_Summary!D14 -> 153734.63 | D21: =Annual_Summary!E14 -> 147482.06 | E21: =SUM(B21:D21) -> 412318.62 | F21: Cash operating cost | G21: Revenue stack | H21: BTC base; DR + hyperscaler optional | I21: Keeps base case conservative for investors/lenders | J21: Revenue_36M toggles | K21: Year-end AMSA solar | L21: =Annual_Summary!C10 -> 10
A22: EBITDA (base) | B22: =Annual_Summary!C15 -> 135850.87 | C22: =Annual_Summary!D15 -> 232752.44 | D22: =Annual_Summary!E15 -> 255462.49 | E22: =SUM(B22:D22) -> 624065.8 | F22: Revenue less opex | G22: Funding stack | H22: 100% equity default | I22: Aligns with current Phase 1 raise framing | J22: Inputs / Funding_36M | K22: Peak funding | L22: =Annual_Summary!C25 -> 470888.25
A23: Capex spend | B23: =Annual_Summary!C17 -> 505405.63 | C23: =Annual_Summary!D17 -> 0 | D23: =Annual_Summary!E17 -> 0 | E23: =SUM(B23:D23) -> 505405.63 | F23: Cash capital deployed | G23: Operating model | H23: 98% uptime; 22h GVL; 12h + 9h AMSA | I23: Separates uptime from site operating windows | J23: Inputs | K23: Total equity | L23: =Annual_Summary!C26 -> 470888.25
A24: Unlevered cash flow | B24: =Annual_Summary!C18 -> -369554.77 | C24: =Annual_Summary!D18 -> 232752.44 | D24: =Annual_Summary!E18 -> 255462.49 | E24: =SUM(B24:D24) -> 118660.17 | F24: Base-case free cash flow before funding | G24: Investor use | H24: Use Dashboard + Annual_Summary only | I24: Detailed monthly tabs remain internal | J24: Sources_Notes | K24: Y3 EBITDA | L24: =Annual_Summary!E15 -> 255462.49
G25: Editable choice | H25: Still easy to switch to a 10 / 10 split | I25: Scenario flexibility without breaking formulas | J25: Inputs / Deployment_36M | K25: Implied payback | L25: =IF(Annual_Summary!E15=0,"",SUM(Annual_Summary!C17:E17)/Annual_Summary!E15) -> 1.9783947
A27: Base-case assumptions | G27: Model framing and cautions
A28: Driver | B28: Value | C28: Unit | D28: Where to edit | E28: Model role | F28: Comment | G28: 1) This workbook is intentionally smaller than the detailed master model. 2) Base case excludes demand-response and hyperscaler resale revenue. 3) Debt is off by default to match the current Phase 1 equity raise framing. 4) The latest April 2026 deck uses a 15MW Grootvlei / 5MW AMSA split, but the workbook is editable if management wants a 10 / 10 variant.
A29: Technical uptime | B29: =Inputs!C10 -> 0.98 | C29: % | D29: Inputs!C10 | E29: Production conversion | F29: User confirmed 98% is realistic.
A30: Grootvlei hours/day | B30: =Inputs!C12 -> 22 | C30: hours | D30: Inputs!C12 | E30: Availability profile | F30: User confirmed 22h/day is aligned with current negotiations.
A31: AMSA Eskom hours/day | B31: =Inputs!C13 -> 12 | C31: hours | D31: Inputs!C13 | E31: Grid supply profile | F31: Editable.
A32: AMSA solar hours/day | B32: =Inputs!C14 -> 9 | C32: hours | D32: Inputs!C14 | E32: Solar contribution | F32: Editable.
A33: BTC price start | B33: =Inputs!C21 -> 75000 | C33: USD/BTC | D33: Inputs!C21 | E33: Top-line driver | F33: Editable.
A34: Network growth p.a. | B34: =Inputs!C24 -> 0.1 | C34: % | D34: Inputs!C24 | E34: Difficulty sensitivity | F34: Editable stress point.
A35: Year 1 tariffs (GVL / AMSA) | B35: =TEXT(Inputs!C29,"0.00")&" / "&TEXT(Inputs!C32,"0.00") -> 1.00 / 0.90 | C35: R/kWh | D35: Inputs tariffs | E35: Primary IRR driver | F35: Keeping conservative

Sheet Inputs
A1: BitMach Phase 1 (20MW) | Simplified 36-Month Model
A2: Scaled-down fundraising model for the first 20MW only. Core case is conservative; optionality is visible but off by default.
A3: Driver | B3: Unit | C3: Value | D3: Notes
A4: MODEL ASSUMPTIONS | D4: Editable blue cells. Defaults aim to be conservative and bankable.
A5: Model start date | B5: date | C5: 46204 | D5: Editable. Relative 36-month model start.
A6: Horizon months | B6: months | C6: 36 | D6: Fixed workbook horizon.
A7: Phase 1 total gross MW | B7: MW | C7: 20 | D7: Scaled-down Phase 1 only.
A8: Grootvlei target MW | B8: MW | C8: 15 | D8: Latest investor deck uses 15MW Grootvlei + 5MW AMSA; change these two cells to 10/10 if management wants the older Nedbank memo framing.
A9: AMSA target MW | B9: MW | C9: 5 | D9: Editable site split.
A10: Technical uptime | B10: % | C10: 0.98 | D10: MARA achieves 99.9%
A11: Aux load | B11: % | C11: 0.05 | D11: Cooling / container auxiliaries.
A12: Grootvlei hours/day | B12: hours/day | C12: 22 | D12: 22h/day remains consistent with Eskom negotiations.
A13: AMSA Eskom hours/day | B13: hours/day | C13: 12 | D13: Grid-supplied runtime leg.
A14: AMSA solar hours/day | B14: hours/day | C14: 9 | D14: Solar-supplied runtime leg.
A15: AMSA solar MW in Phase 1 | B15: MW | C15: 10 | D15: Conservative Year-1 placeholder; keep editable.
A16: Solar COD month | B16: month# | C16: 5 | D16: Solar available during ramp-up.
... A18: Salary annual inflation | B18: % | C18: 0.05 | D18: Used for payroll escalation.
A19: BITCOIN / NETWORK | D19: Core market assumptions.
A20: FX (ZAR/USD) | B20: ZAR/USD | C20: 17 | D20: April 2026 investor materials use R17.00/USD.
A21: BTC price start | B21: USD/BTC | C21: 75000 | D21: Editable spot / entry assumption.
A22: BTC annual growth | B22: % | C22: 0.15 | D22: Base case market growth.
A23: Network hash start | B23: TH/s | C23: 900000000 | D23: Editable.
A24: Network hash annual growth | B24: % | C24: 0.1 | D24: Base case difficulty / network growth.
A25: Blocks per day | B25: blocks/day | C25: 144 | D25: Protocol input.
A26: Block subsidy | B26: BTC/block | C26: 3.125 | D26: Protocol input.
A27: Fee factor on subsidy | B27: % | C27: 0.15 | D27: Pool fee / transaction fee uplift.
A28: SITE PRICING | D28: Explicit yearly tariffs rather than a hidden blend.
A29: Grootvlei tariff - Year 1 | B29: R/kWh | C29: 1 | D29: Proof-phase conservative tariff.
A30: Grootvlei tariff - Year 2 | B30: R/kWh | C30: 0.95 | D30: Partial improvement after proof of flexibility.
A31: Grootvlei tariff - Year 3 | B31: R/kWh | C31: 0.9 | D31: Future-state improvement placeholder; editable.
A32: AMSA Eskom tariff - Year 1 | B32: R/kWh | C32: 0.9 | D32: AMSA grid leg.
A33: AMSA Eskom tariff - Year 2 | B33: R/kWh | C33: 0.85 | D33: AMSA grid leg.
A34: AMSA Eskom tariff - Year 3 | B34: R/kWh | C34: 0.8 | D34: AMSA grid leg.
A35: Solar capex | B35: ZAR'000/MW | C35: 7000 | D35: Conservative placeholder.
A36: Solar O&M | B36: % p.a. | C36: 0.02 | D36: Annual O&M as % of solar capex.
A37: HARDWARE | D37: Default set to the internally consistent working basis currently used in the detailed master model; editable if Bitmain terms are finalized.
A38: Miner hashrate | B38: TH/miner | C38: 700 | D38: Editable. Current working base.
A39: Miner efficiency | B39: J/T | C39: 12.5 | D39: Editable. Current working base.
A40: Miner power | B40: W/miner | C40: =C38*C39 -> 8750 | D40: Formula = hashrate x J/T.
A41: Miner price | B41: USD/miner | C41: 5915 | D41: Editable hardware pricing.
A42: Miner useful life | B42: years | C42: 4 | D42: For replacement reserve framing only.
A43: Miner slots per container | B43: miners/container | C43: 240 | D43: Working hydro container basis.
A44: Hydro container cost | B44: USD/container | C44: 350000 | D44: Editable placeholder.
A45: Container gross MW | B45: MW/container | C45: =(C43*C40/1000000)/(1-C11) -> 2.2105263 | D45: Formula from miner power, slot count and aux load.
A46: CAPEX BASIS | D46: Fixed + variable capex and deployment logistics.
A47: Electrical site fixed capex | B47: ZAR'000/site | C47: 25375.758 | D47: Derived from the detailed EPC quote normalization in the master model.
A48: Electrical variable capex | B48: ZAR'000/MW | C48: 3806.3638 | D48: Derived from the detailed EPC quote normalization in the master model.
A49: Initial spare parts | B49: % of hardware+containers | C49: 0.02 | D49: One-off initial spares.
A50: Tools & equipment initial | B50: ZAR'000/site | C50: 750 | D50: One-off tools/accessories.
A51: Office setup / deposits | B51: ZAR'000 | C51: 350 | D51: One-off corporate setup.
A52: Software / SCADA setup | B52: ZAR'000 | C52: 1500 | D52: One-off systems setup.
A53: Legal setup total | B53: ZAR'000 | C53: 600 | D53: One-off documentation / structuring.
A54: Ocean freight | B54: USD/container | C54: 8000 | D54: Editable logistics placeholder.
A55: Port / clearing | B55: ZAR'000/container | C55: 150 | D55: Editable logistics placeholder.
A56: Inland trucking | B56: ZAR'000/container | C56: 70 | D56: Editable logistics placeholder.
A57: Crane / rigging | B57: ZAR'000/container | C57: 50 | D57: Editable logistics placeholder.
A58: Cargo insurance | B58: % of hardware+containers | C58: 0.01 | D58: Editable logistics assumption.
A59: Import duty | B59: % of hardware+containers | C59: 0.05 | D59: Editable duty assumption.
A60: PEOPLE / OPEX | D60: Recurring people and overhead assumptions.
A61: Staff hardware setup | B61: ZAR'000/FTE | C61: 35 | D61: Laptop / phone / PPE provisioning.
A62: Fixed corporate FTE | B62: FTE | C62: 4 | D62: Corporate team for Phase 1.
A63: Corporate salary | B63: ZAR'000/FTE/yr | C63: 1000 | D63: Fully loaded CTC.
A64: Site management FTE/site | B64: FTE/site | C64: 2 | D64: Manager + supervisor.
A65: Site management salary | B65: ZAR'000/FTE/yr | C65: 700 | D65: Fully loaded CTC.
A66: Technicians FTE/MW | B66: FTE/MW | C66: 0.35 | D66: Hydro site technician intensity.
A67: Technician salary | B67: ZAR'000/FTE/yr | C67: 350 | D67: Fully loaded CTC.
A68: Electricians FTE/MW | B68: FTE/MW | C68: 0.08 | D68: Electricians per MW.
A69: Electrician salary | B69: ZAR'000/FTE/yr | C69: 450 | D69: Fully loaded CTC.
A70: Benefits load | B70: % | C70: 0.2 | D70: Benefits / payroll load.
A71: Travel & accommodation | B71: % of gross payroll | C71: 0.06 | D71: Recurring travel as % of payroll.
A72: Site mobilization travel | B72: ZAR'000/site start | C72: 250 | D72: One-off mobilization / commissioning travel.
... A80: Other utilities / water | B80: ZAR'000/MW/mo | C80: 10 | D80: Water treatment and misc utilities.
A81: OPTIONALITY / UPSIDE | D81: All off by default in the conservative case.
A82: Include demand response? | B82: 0/1 | C82: 0 | D82: 0 = off / 1 = on.
A83: DR start month | B83: month# | C83: 7 | D83: Start month if toggled on.
A84: DR price | B84: R/kWh | C84: 0.25 | D84: Placeholder paid availability price.
A85: DR equivalent hours/day | B85: hours/day | C85: 1.5 | D85: Equivalent paid availability window.
A86: DR paid utilisation | B86: % | C86: 0.5 | D86: Share of availability window actually paid.
A87: Include hyperscaler resale? | B87: 0/1 | C87: 0 | D87: 0 = off / 1 = on.
A88: Hyperscaler start month | B88: month# | C88: 25 | D88: Year-3 optionality by default.
A89: Hyperscaler MW sold | B89: MW | C89: 2 | D89: Pilot resale / tenant MW.
A90: Hyperscaler hours/day | B90: hours/day | C90: 16 | D90: Pilot tenant runtime.
A91: Hyperscaler sale price | B91: USD/MWh | C91: 130 | D91: Placeholder resale tariff.
A92: FUNDING / CASH TIMING | D92: Keep simple: staged payments and editable funding mix.
A93: Equity share of external funding | B93: % | C93: 1 | D93: Default for this simplified 20MW model = equity-funded Phase 1; user can reintroduce debt later.
A94: Senior debt share of external funding | B94: % | C94: 0 | D94: Set to 0% by default to align with current Phase 1 equity raise framing.
A95: Senior debt interest | B95: % p.a. | C95: 0.13 | D95: Indicative project debt placeholder.
A96: Senior debt tenor | B96: months | C96: 60 | D96: Indicative term.
A97: Senior debt grace period | B97: months | C97: 12 | D97: Interest capitalizes during grace.
A98: Arrangement fee | B98: % of gross debt draw | C98: 0.01 | D98: Debt arrangement fee.
A99: Minimum cash buffer | B99: ZAR'000 | C99: 0 | D99: Raise if financiers want a liquidity reserve.
A100: Miner deposit | B100: % of hardware basis | C100: 0.6 | D100: Staged payment.
A101: Miner final payment | B101: % of hardware basis | C101: 0.4 | D101: Staged payment.
A102: Miner order lead time | B102: months | C102: 2 | D102: Deposit paid this many months before COD.
A103: Container deposit | B103: % of container basis | C103: 0.2 | D103: Staged payment.
A104: Container progress | B104: % of container basis | C104: 0.3 | D104: Staged payment.
... A111: EPC order lead time | B111: months | C111: 2 | D111: Deposit paid this many months before COD.

Sheet Deployment_36M
A1: Deployment_36M | Editable site ramp for the first 20MW only
A2: Edit only the three closing-MW rows (Grootvlei, AMSA, AMSA solar). Everything else is formula-driven. Default ramp = 0/0/5/10/15/20MW gross over the first six months.
A4: Metric | B4: Unit | C4: Notes
A5: Date | B5: date | C5: From Inputs start date | D5: =Inputs!C5 -> 46204 | E5: =EDATE(D5,1) -> 46235 | F5: =EDATE(E5,1) -> 46266 | G5: =EDATE(F5,1) -> 46296 | H5: =EDATE(G5,1) -> 46327 | I5: =EDATE(H5,1) -> 46357 | J5: =EDATE(I5,1) -> 46388 | K5: =EDATE(J5,1) -> 46419 | L5: =EDATE(K5,1) -> 46447 | ... AM5: =EDATE(AL5,1) -> 47270
A6: Days in month | B6: days | C6: Calendar days | D6: =DAY(EOMONTH(D5,0)) -> 31 | E6: =DAY(EOMONTH(E5,0)) -> 31 | F6: =DAY(EOMONTH(F5,0)) -> 30 | G6: =DAY(EOMONTH(G5,0)) -> 31 | H6: =DAY(EOMONTH(H5,0)) -> 30 | I6: =DAY(EOMONTH(I5,0)) -> 31 | J6: =DAY(EOMONTH(J5,0)) -> 31 | K6: =DAY(EOMONTH(K5,0)) -> 28 | ... AM6: =DAY(EOMONTH(AM5,0)) -> 30
A8: Grootvlei closing MW | B8: MW | C8: Editable | D8: 0 | E8: 0 | F8: 5 | G8: 10 | H8: 15 | I8: 15 | J8: 15 | K8: 15 | L8: 15 | M8: 15 | N8: 15 | O8: 15 | P8: 15 | Q8: 15 | R8: 15 | S8: 15 | T8: 15 | U8: 15 | V8: 15 | W8: 15 | X8: 15 | Y8: 15 | Z8: 15 | AA8: 15 | AB8: 15 | AC8: 15 | AD8: 15 | AE8: 15 | AF8: 15 | AG8: 15 | AH8: 15 | AI8: 15 | AJ8: 15 | AK8: 15 | AL8: 15 | AM8: 15
A9: AMSA closing MW | B9: MW | C9: Editable | D9: 0 | E9: 0 | F9: 0 | G9: 0 | H9: 0 | I9: 5 | J9: 5 | K9: 5 | L9: 5 | M9: 5 | N9: 5 | O9: 5 | P9: 5 | Q9: 5 | R9: 5 | S9: 5 | T9: 5 | U9: 5 | V9: 5 | W9: 5 | X9: 5 | Y9: 5 | Z9: 5 | AA9: 5 | AB9: 5 | AC9: 5 | AD9: 5 | AE9: 5 | AF9: 5 | AG9: 5 | AH9: 5 | AI9: 5 | AJ9: 5 | AK9: 5 | AL9: 5 | AM9: 5
A10: AMSA solar closing MW | B10: MW | C10: Editable | D10: 0 | E10: 0 | F10: 0 | G10: 0 | H10: 10 | I10: 10 | J10: 10 | K10: 10 | L10: 10 | M10: 10 | N10: 10 | O10: 10 | P10: 10 | Q10: 10 | R10: 10 | S10: 10 | T10: 10 | U10: 10 | V10: 10 | W10: 10 | X10: 10 | Y10: 10 | Z10: 10 | AA10: 10 | AB10: 10 | AC10: 10 | AD10: 10 | AE10: 10 | AF10: 10 | AG10: 10 | AH10: 10 | AI10: 10 | AJ10: 10 | AK10: 10 | AL10: 10 | AM10: 10
A13: Grootvlei opening MW | B13: MW | C13: Formula | D13: =0 -> 0 | E13: =D8 -> 0 | F13: =E8 -> 0 | G13: =F8 -> 5 | H13: =G8 -> 10 | I13: =H8 -> 15 | J13: =I8 -> 15 | K13: =J8 -> 15 | L13: =K8 -> 15 | ... AM13: =AL8 -> 15
A14: AMSA opening MW | B14: MW | C14: Formula | D14: =0 -> 0 | E14: =D9 -> 0 | F14: =E9 -> 0 | G14: =F9 -> 0 | H14: =G9 -> 0 | I14: =H9 -> 0 | J14: =I9 -> 5 | K14: =J9 -> 5 | L14: =K9 -> 5 | ... AM14: =AL9 -> 5
A15: AMSA solar opening MW | B15: MW | C15: Formula | D15: =0 -> 0 | E15: =D10 -> 0 | F15: =E10 -> 0 | G15: =F10 -> 0 | H15: =G10 -> 0 | I15: =H10 -> 10 | J15: =I10 -> 10 | K15: =J10 -> 10 | L15: =K10 -> 10 | ... AM15: =AL10 -> 10
A18: Grootvlei average MW | B18: MW | C18: Formula | D18: =(D13+D8)/2 -> 0 | E18: =(E13+E8)/2 -> 0 | F18: =(F13+F8)/2 -> 2.5 | G18: =(G13+G8)/2 -> 7.5 | H18: =(H13+H8)/2 -> 12.5 | I18: =(I13+I8)/2 -> 15 | J18: =(J13+J8)/2 -> 15 | K18: =(K13+K8)/2 -> 15 | ... AM18: =(AM13+AM8)/2 -> 15
A19: AMSA average MW | B19: MW | C19: Formula | D19: =(D14+D9)/2 -> 0 | E19: =(E14+E9)/2 -> 0 | F19: =(F14+F9)/2 -> 0 | G19: =(G14+G9)/2 -> 0 | H19: =(H14+H9)/2 -> 0 | I19: =(I14+I9)/2 -> 2.5 | J19: =(J14+J9)/2 -> 5 | K19: =(K14+K9)/2 -> 5 | ... AM19: =(AM14+AM9)/2 -> 5
A20: AMSA average solar MW | B20: MW | C20: Formula | D20: =(D15+D10)/2 -> 0 | E20: =(E15+E10)/2 -> 0 | F20: =(F15+F10)/2 -> 0 | G20: =(G15+G10)/2 -> 0 | H20: =(H15+H10)/2 -> 5 | I20: =(I15+I10)/2 -> 10 | J20: =(J15+J10)/2 -> 10 | K20: =(K15+K10)/2 -> 10 | ... AM20: =(AM15+AM10)/2 -> 10
A21: Total average MW | B21: MW | C21: Formula | D21: =D18+D19 -> 0 | E21: =E18+E19 -> 0 | F21: =F18+F19 -> 2.5 | G21: =G18+G19 -> 7.5 | H21: =H18+H19 -> 12.5 | I21: =I18+I19 -> 17.5 | J21: =J18+J19 -> 20 | K21: =K18+K19 -> 20 | ... AM21: =AM18+AM19 -> 20
A24: Grootvlei new MW | B24: MW | C24: Formula | D24: =MAX(0,D8-D13) -> 0 | E24: =MAX(0,E8-E13) -> 0 | F24: =MAX(0,F8-F13) -> 5 | G24: =MAX(0,G8-G13) -> 5 | H24: =MAX(0,H8-H13) -> 5 | I24: =MAX(0,I8-I13) -> 0 | J24: =MAX(0,J8-J13) -> 0 | K24: =MAX(0,K8-K13) -> 0 | ... AM24: =MAX(0,AM8-AM13) -> 0
A25: AMSA new MW | B25: MW | C25: Formula | D25: =MAX(0,D9-D14) -> 0 | E25: =MAX(0,E9-E14) -> 0 | F25: =MAX(0,F9-F14) -> 0 | G25: =MAX(0,G9-G14) -> 0 | H25: =MAX(0,H9-H14) -> 0 | I25: =MAX(0,I9-I14) -> 5 | J25: =MAX(0,J9-J14) -> 0 | K25: =MAX(0,K9-K14) -> 0 | ... AM25: =MAX(0,AM9-AM14) -> 0
A26: AMSA solar new MW | B26: MW | C26: Formula | D26: =MAX(0,D10-D15) -> 0 | E26: =MAX(0,E10-E15) -> 0 | F26: =MAX(0,F10-F15) -> 0 | G26: =MAX(0,G10-G15) -> 0 | H26: =MAX(0,H10-H15) -> 10 | I26: =MAX(0,I10-I15) -> 0 | J26: =MAX(0,J10-J15) -> 0 | K26: =MAX(0,K10-K15) -> 0 | ... AM26: =MAX(0,AM10-AM15) -> 0
A27: Total new MW | B27: MW | C27: Formula | D27: =D24+D25 -> 0 | E27: =E24+E25 -> 0 | F27: =F24+F25 -> 5 | G27: =G24+G25 -> 5 | H27: =H24+H25 -> 5 | I27: =I24+I25 -> 5 | J27: =J24+J25 -> 0 | K27: =K24+K25 -> 0 | ... AM27: =AM24+AM25 -> 0
A30: Grootvlei active site | B30: flag | C30: Formula | D30: =IF(D8>0,1,0) -> 0 | E30: =IF(E8>0,1,0) -> 0 | F30: =IF(F8>0,1,0) -> 1 | G30: =IF(G8>0,1,0) -> 1 | H30: =IF(H8>0,1,0) -> 1 | I30: =IF(I8>0,1,0) -> 1 | J30: =IF(J8>0,1,0) -> 1 | K30: =IF(K8>0,1,0) -> 1 | ... AM30: =IF(AM8>0,1,0) -> 1
A31: AMSA active site | B31: flag | C31: Formula | D31: =IF(D9>0,1,0) -> 0 | E31: =IF(E9>0,1,0) -> 0 | F31: =IF(F9>0,1,0) -> 0 | G31: =IF(G9>0,1,0) -> 0 | H31: =IF(H9>0,1,0) -> 0 | I31: =IF(I9>0,1,0) -> 1 | J31: =IF(J9>0,1,0) -> 1 | K31: =IF(K9>0,1,0) -> 1 | ... AM31: =IF(AM9>0,1,0) -> 1
A32: Total active sites | B32: count | C32: Formula | D32: =D30+D31 -> 0 | E32: =E30+E31 -> 0 | F32: =F30+F31 -> 1 | G32: =G30+G31 -> 1 | H32: =H30+H31 -> 1 | I32: =I30+I31 -> 2 | J32: =J30+J31 -> 2 | K32: =K30+K31 -> 2 | ... AM32: =AM30+AM31 -> 2
A35: Grootvlei site start | B35: flag | C35: Formula | D35: =IF(AND(D8>0,D13=0),1,0) -> 0 | E35: =IF(AND(E8>0,E13=0),1,0) -> 0 | F35: =IF(AND(F8>0,F13=0),1,0) -> 1 | G35: =IF(AND(G8>0,G13=0),1,0) -> 0 | H35: =IF(AND(H8>0,H13=0),1,0) -> 0 | I35: =IF(AND(I8>0,I13=0),1,0) -> 0 | J35: =IF(AND(J8>0,J13=0),1,0) -> 0 | K35: =IF(AND(K8>0,K13=0),1,0) -> 0 | ... AM35: =IF(AND(AM8>0,AM13=0),1,0) -> 0
A36: AMSA site start | B36: flag | C36: Formula | D36: =IF(AND(D9>0,D14=0),1,0) -> 0 | E36: =IF(AND(E9>0,E14=0),1,0) -> 0 | F36: =IF(AND(F9>0,F14=0),1,0) -> 0 | G36: =IF(AND(G9>0,G14=0),1,0) -> 0 | H36: =IF(AND(H9>0,H14=0),1,0) -> 0 | I36: =IF(AND(I9>0,I14=0),1,0) -> 1 | J36: =IF(AND(J9>0,J14=0),1,0) -> 0 | K36: =IF(AND(K9>0,K14=0),1,0) -> 0 | ... AM36: =IF(AND(AM9>0,AM14=0),1,0) -> 0
A37: Total site starts | B37: count | C37: Formula | D37: =D35+D36 -> 0 | E37: =E35+E36 -> 0 | F37: =F35+F36 -> 1 | G37: =G35+G36 -> 0 | H37: =H35+H36 -> 0 | I37: =I35+I36 -> 1 | J37: =J35+J36 -> 0 | K37: =K35+K36 -> 0 | ... AM37: =AM35+AM36 -> 0
A40: Grootvlei closing containers | B40: containers | C40: Formula | D40: =ROUNDUP(D8/Inputs!C45,0) -> 0 | E40: =ROUNDUP(E8/Inputs!C45,0) -> 0 | F40: =ROUNDUP(F8/Inputs!C45,0) -> 3 | G40: =ROUNDUP(G8/Inputs!C45,0) -> 5 | H40: =ROUNDUP(H8/Inputs!C45,0) -> 7 | I40: =ROUNDUP(I8/Inputs!C45,0) -> 7 | J40: =ROUNDUP(J8/Inputs!C45,0) -> 7 | K40: =ROUNDUP(K8/Inputs!C45,0) -> 7 | L40: =ROUNDUP(L8/Inputs!C45,0) -> 7 | M40: =ROUNDUP(M8/Inputs!C45,0) -> 7 | N40: =ROUNDUP(N8/Inputs!C45,0) -> 7 | O40: =ROUNDUP(O8/Inputs!C45,0) -> 7 | P40: =ROUNDUP(P8/Inputs!C45,0) -> 7 | Q40: =ROUNDUP(Q8/Inputs!C45,0) -> 7 | R40: =ROUNDUP(R8/Inputs!C45,0) -> 7 | S40: =ROUNDUP(S8/Inputs!C45,0) -> 7 | T40: =ROUNDUP(T8/Inputs!C45,0) -> 7 | U40: =ROUNDUP(U8/Inputs!C45,0) -> 7 | V40: =ROUNDUP(V8/Inputs!C45,0) -> 7 | W40: =ROUNDUP(W8/Inputs!C45,0) -> 7 | X40: =ROUNDUP(X8/Inputs!C45,0) -> 7 | Y40: =ROUNDUP(Y8/Inputs!C45,0) -> 7 | Z40: =ROUNDUP(Z8/Inputs!C45,0) -> 7 | AA40: =ROUNDUP(AA8/Inputs!C45,0) -> 7 | AB40: =ROUNDUP(AB8/Inputs!C45,0) -> 7 | AC40: =ROUNDUP(AC8/Inputs!C45,0) -> 7 | AD40: =ROUNDUP(AD8/Inputs!C45,0) -> 7 | AE40: =ROUNDUP(AE8/Inputs!C45,0) -> 7 | AF40: =ROUNDUP(AF8/Inputs!C45,0) -> 7 | AG40: =ROUNDUP(AG8/Inputs!C45,0) -> 7 | AH40: =ROUNDUP(AH8/Inputs!C45,0) -> 7 | AI40: =ROUNDUP(AI8/Inputs!C45,0) -> 7 | AJ40: =ROUNDUP(AJ8/Inputs!C45,0) -> 7 | AK40: =ROUNDUP(AK8/Inputs!C45,0) -> 7 | AL40: =ROUNDUP(AL8/Inputs!C45,0) -> 7 | AM40: =ROUNDUP(AM8/Inputs!C45,0) -> 7
A41: AMSA closing containers | B41: containers | C41: Formula | D41: =ROUNDUP(D9/Inputs!C45,0) -> 0 | E41: =ROUNDUP(E9/Inputs!C45,0) -> 0 | F41: =ROUNDUP(F9/Inputs!C45,0) -> 0 | G41: =ROUNDUP(G9/Inputs!C45,0) -> 0 | H41: =ROUNDUP(H9/Inputs!C45,0) -> 0 | I41: =ROUNDUP(I9/Inputs!C45,0) -> 3 | J41: =ROUNDUP(J9/Inputs!C45,0) -> 3 | K41: =ROUNDUP(K9/Inputs!C45,0) -> 3 | L41: =ROUNDUP(L9/Inputs!C45,0) -> 3 | M41: =ROUNDUP(M9/Inputs!C45,0) -> 3 | N41: =ROUNDUP(N9/Inputs!C45,0) -> 3 | O41: =ROUNDUP(O9/Inputs!C45,0) -> 3 | P41: =ROUNDUP(P9/Inputs!C45,0) -> 3 | Q41: =ROUNDUP(Q9/Inputs!C45,0) -> 3 | R41: =ROUNDUP(R9/Inputs!C45,0) -> 3 | S41: =ROUNDUP(S9/Inputs!C45,0) -> 3 | T41: =ROUNDUP(T9/Inputs!C45,0) -> 3 | U41: =ROUNDUP(U9/Inputs!C45,0) -> 3 | V41: =ROUNDUP(V9/Inputs!C45,0) -> 3 | W41: =ROUNDUP(W9/Inputs!C45,0) -> 3 | X41: =ROUNDUP(X9/Inputs!C45,0) -> 3 | Y41: =ROUNDUP(Y9/Inputs!C45,0) -> 3 | Z41: =ROUNDUP(Z9/Inputs!C45,0) -> 3 | AA41: =ROUNDUP(AA9/Inputs!C45,0) -> 3 | AB41: =ROUNDUP(AB9/Inputs!C45,0) -> 3 | AC41: =ROUNDUP(AC9/Inputs!C45,0) -> 3 | AD41: =ROUNDUP(AD9/Inputs!C45,0) -> 3 | AE41: =ROUNDUP(AE9/Inputs!C45,0) -> 3 | AF41: =ROUNDUP(AF9/Inputs!C45,0) -> 3 | AG41: =ROUNDUP(AG9/Inputs!C45,0) -> 3 | AH41: =ROUNDUP(AH9/Inputs!C45,0) -> 3 | AI41: =ROUNDUP(AI9/Inputs!C45,0) -> 3 | AJ41: =ROUNDUP(AJ9/Inputs!C45,0) -> 3 | AK41: =ROUNDUP(AK9/Inputs!C45,0) -> 3 | AL41: =ROUNDUP(AL9/Inputs!C45,0) -> 3 | AM41: =ROUNDUP(AM9/Inputs!C45,0) -> 3
A42: Total closing containers | B42: containers | C42: Formula | D42: =D40+D41 -> 0 | E42: =E40+E41 -> 0 | F42: =F40+F41 -> 3 | G42: =G40+G41 -> 5 | H42: =H40+H41 -> 7 | I42: =I40+I41 -> 10 | J42: =J40+J41 -> 10 | K42: =K40+K41 -> 10 | ... AM42: =AM40+AM41 -> 10
A45: Grootvlei opening containers | B45: containers | C45: Formula | D45: =0 -> 0 | E45: =D40 -> 0 | F45: =E40 -> 0 | G45: =F40 -> 3 | H45: =G40 -> 5 | I45: =H40 -> 7 | J45: =I40 -> 7 | K45: =J40 -> 7 | L45: =K40 -> 7 | ... AM45: =AL40 -> 7
A46: AMSA opening containers | B46: containers | C46: Formula | D46: =0 -> 0 | E46: =D41 -> 0 | F46: =E41 -> 0 | G46: =F41 -> 0 | H46: =G41 -> 0 | I46: =H41 -> 0 | J46: =I41 -> 3 | K46: =J41 -> 3 | L46: =K41 -> 3 | ... AM46: =AL41 -> 3
A47: Total opening containers | B47: containers | C47: Formula | D47: =0 -> 0 | E47: =D42 -> 0 | F47: =E42 -> 0 | G47: =F42 -> 3 | H47: =G42 -> 5 | I47: =H42 -> 7 | J47: =I42 -> 10 | K47: =J42 -> 10 | L47: =K42 -> 10 | ... AM47: =AL42 -> 10
A50: Grootvlei new containers | B50: containers | C50: Formula | D50: =MAX(0,D40-D45) -> 0 | E50: =MAX(0,E40-E45) -> 0 | F50: =MAX(0,F40-F45) -> 3 | G50: =MAX(0,G40-G45) -> 2 | H50: =MAX(0,H40-H45) -> 2 | I50: =MAX(0,I40-I45) -> 0 | J50: =MAX(0,J40-J45) -> 0 | K50: =MAX(0,K40-K45) -> 0 | ... AM50: =MAX(0,AM40-AM45) -> 0
A51: AMSA new containers | B51: containers | C51: Formula | D51: =MAX(0,D41-D46) -> 0 | E51: =MAX(0,E41-E46) -> 0 | F51: =MAX(0,F41-F46) -> 0 | G51: =MAX(0,G41-G46) -> 0 | H51: =MAX(0,H41-H46) -> 0 | I51: =MAX(0,I41-I46) -> 3 | J51: =MAX(0,J41-J46) -> 0 | K51: =MAX(0,K41-K46) -> 0 | ... AM51: =MAX(0,AM41-AM46) -> 0
A52: Total new containers | B52: containers | C52: Formula | D52: =D50+D51 -> 0 | E52: =E50+E51 -> 0 | F52: =F50+F51 -> 3 | G52: =G50+G51 -> 2 | H52: =H50+H51 -> 2 | I52: =I50+I51 -> 3 | J52: =J50+J51 -> 0 | K52: =K50+K51 -> 0 | ... AM52: =AM50+AM51 -> 0
A55: New site FTE onboarded | B55: FTE | C55: Formula | D55: =(D37*Inputs!C64)+(D27*(Inputs!C66+Inputs!C68)) -> 0 | E55: =(E37*Inputs!C64)+(E27*(Inputs!C66+Inputs!C68)) -> 0 | F55: =(F37*Inputs!C64)+(F27*(Inputs!C66+Inputs!C68)) -> 4.15 | G55: =(G37*Inputs!C64)+(G27*(Inputs!C66+Inputs!C68)) -> 2.15 | H55: =(H37*Inputs!C64)+(H27*(Inputs!C66+Inputs!C68)) -> 2.15 | I55: =(I37*Inputs!C64)+(I27*(Inputs!C66+Inputs!C68)) -> 4.15 | J55: =(J37*Inputs!C64)+(J27*(Inputs!C66+Inputs!C68)) -> 0 | K55: =(K37*Inputs!C64)+(K27*(Inputs!C66+Inputs!C68)) -> 0 | L55: =(L37*Inputs!C64)+(L27*(Inputs!C66+Inputs!C68)) -> 0 | M55: =(M37*Inputs!C64)+(M27*(Inputs!C66+Inputs!C68)) -> 0 | N55: =(N37*Inputs!C64)+(N27*(Inputs!C66+Inputs!C68)) -> 0 | O55: =(O37*Inputs!C64)+(O27*(Inputs!C66+Inputs!C68)) -> 0 | P55: =(P37*Inputs!C64)+(P27*(Inputs!C66+Inputs!C68)) -> 0 | Q55: =(Q37*Inputs!C64)+(Q27*(Inputs!C66+Inputs!C68)) -> 0 | R55: =(R37*Inputs!C64)+(R27*(Inputs!C66+Inputs!C68)) -> 0 | S55: =(S37*Inputs!C64)+(S27*(Inputs!C66+Inputs!C68)) -> 0 | T55: =(T37*Inputs!C64)+(T27*(Inputs!C66+Inputs!C68)) -> 0 | U55: =(U37*Inputs!C64)+(U27*(Inputs!C66+Inputs!C68)) -> 0 | V55: =(V37*Inputs!C64)+(V27*(Inputs!C66+Inputs!C68)) -> 0 | W55: =(W37*Inputs!C64)+(W27*(Inputs!C66+Inputs!C68)) -> 0 | X55: =(X37*Inputs!C64)+(X27*(Inputs!C66+Inputs!C68)) -> 0 | Y55: =(Y37*Inputs!C64)+(Y27*(Inputs!C66+Inputs!C68)) -> 0 | Z55: =(Z37*Inputs!C64)+(Z27*(Inputs!C66+Inputs!C68)) -> 0 | AA55: =(AA37*Inputs!C64)+(AA27*(Inputs!C66+Inputs!C68)) -> 0 | AB55: =(AB37*Inputs!C64)+(AB27*(Inputs!C66+Inputs!C68)) -> 0 | AC55: =(AC37*Inputs!C64)+(AC27*(Inputs!C66+Inputs!C68)) -> 0 | AD55: =(AD37*Inputs!C64)+(AD27*(Inputs!C66+Inputs!C68)) -> 0 | AE55: =(AE37*Inputs!C64)+(AE27*(Inputs!C66+Inputs!C68)) -> 0 | AF55: =(AF37*Inputs!C64)+(AF27*(Inputs!C66+Inputs!C68)) -> 0 | AG55: =(AG37*Inputs!C64)+(AG27*(Inputs!C66+Inputs!C68)) -> 0 | AH55: =(AH37*Inputs!C64)+(AH27*(Inputs!C66+Inputs!C68)) -> 0 | AI55: =(AI37*Inputs!C64)+(AI27*(Inputs!C66+Inputs!C68)) -> 0 | AJ55: =(AJ37*Inputs!C64)+(AJ27*(Inputs!C66+Inputs!C68)) -> 0 | AK55: =(AK37*Inputs!C64)+(AK27*(Inputs!C66+Inputs!C68)) -> 0 | AL55: =(AL37*Inputs!C64)+(AL27*(Inputs!C66+Inputs!C68)) -> 0 | AM55: =(AM37*Inputs!C64)+(AM27*(Inputs!C66+Inputs!C68)) -> 0
A56: Cumulative site FTE onboarded | B56: FTE | C56: Formula | D56: =D55 -> 0 | E56: =D56+E55 -> 0 | F56: =E56+F55 -> 4.15 | G56: =F56+G55 -> 6.3 | H56: =G56+H55 -> 8.45 | I56: =H56+I55 -> 12.6 | J56: =I56+J55 -> 12.6 | K56: =J56+K55 -> 12.6 | L56: =K56+L55 -> 12.6 | ... AM56: =AL56+AM55 -> 12.6

Sheet Revenue_36M
A1: Revenue_36M | Bitcoin anchor revenue plus visible optionality lines
A2: Base-case cashflow uses BTC revenue only. Demand response and hyperscaler rows are formula-driven but off by default in Inputs.
A4: Metric | B4: Unit | C4: Notes
A5: Date | B5: date | C5: Linked from deployment | D5: =Deployment_36M!D5 -> 46204 | E5: =Deployment_36M!E5 -> 46235 | F5: =Deployment_36M!F5 -> 46266 | G5: =Deployment_36M!G5 -> 46296 | H5: =Deployment_36M!H5 -> 46327 | I5: =Deployment_36M!I5 -> 46357 | J5: =Deployment_36M!J5 -> 46388 | K5: =Deployment_36M!K5 -> 46419 | ... AM5: =Deployment_36M!AM5 -> 47270
A6: Days in month | B6: days | C6: Linked from deployment | D6: =Deployment_36M!D6 -> 31 | E6: =Deployment_36M!E6 -> 31 | F6: =Deployment_36M!F6 -> 30 | G6: =Deployment_36M!G6 -> 31 | H6: =Deployment_36M!H6 -> 30 | I6: =Deployment_36M!I6 -> 31 | J6: =Deployment_36M!J6 -> 31 | K6: =Deployment_36M!K6 -> 28 | ... AM6: =Deployment_36M!AM6 -> 30
A8: BTC price (USD) | B8: USD/BTC | C8: Monthly compounding from annual growth | D8: =Inputs!C21 -> 75000 | E8: =D8*POWER(1+Inputs!C22,1/12) -> 75878.619 | F8: =E8*POWER(1+Inputs!C22,1/12) -> 76767.53 | G8: =F8*POWER(1+Inputs!C22,1/12) -> 77666.856 | H8: =G8*POWER(1+Inputs!C22,1/12) -> 78576.716 | I8: =H8*POWER(1+Inputs!C22,1/12) -> 79497.236 | J8: =I8*POWER(1+Inputs!C22,1/12) -> 80428.54 | K8: =J8*POWER(1+Inputs!C22,1/12) -> 81370.753 | L8: =K8*POWER(1+Inputs!C22,1/12) -> 82324.005 | M8: =L8*POWER(1+Inputs!C22,1/12) -> 83288.424 | N8: =M8*POWER(1+Inputs!C22,1/12) -> 84264.141 | O8: =N8*POWER(1+Inputs!C22,1/12) -> 85251.288 | P8: =O8*POWER(1+Inputs!C22,1/12) -> 86250 | Q8: =P8*POWER(1+Inputs!C22,1/12) -> 87260.412 | R8: =Q8*POWER(1+Inputs!C22,1/12) -> 88282.66 | S8: =R8*POWER(1+Inputs!C22,1/12) -> 89316.884 | T8: =S8*POWER(1+Inputs!C22,1/12) -> 90363.224 | U8: =T8*POWER(1+Inputs!C22,1/12) -> 91421.822 | V8: =U8*POWER(1+Inputs!C22,1/12) -> 92492.821 | W8: =V8*POWER(1+Inputs!C22,1/12) -> 93576.366 | X8: =W8*POWER(1+Inputs!C22,1/12) -> 94672.606 | Y8: =X8*POWER(1+Inputs!C22,1/12) -> 95781.687 | Z8: =Y8*POWER(1+Inputs!C22,1/12) -> 96903.762 | AA8: =Z8*POWER(1+Inputs!C22,1/12) -> 98038.981 | AB8: =AA8*POWER(1+Inputs!C22,1/12) -> 99187.5 | AC8: =AB8*POWER(1+Inputs!C22,1/12) -> 100349.47 | AD8: =AC8*POWER(1+Inputs!C22,1/12) -> 101525.06 | AE8: =AD8*POWER(1+Inputs!C22,1/12) -> 102714.42 | AF8: =AE8*POWER(1+Inputs!C22,1/12) -> 103917.71 | AG8: =AF8*POWER(1+Inputs!C22,1/12) -> 105135.09 | AH8: =AG8*POWER(1+Inputs!C22,1/12) -> 106366.74 | AI8: =AH8*POWER(1+Inputs!C22,1/12) -> 107612.82 | AJ8: =AI8*POWER(1+Inputs!C22,1/12) -> 108873.5 | AK8: =AJ8*POWER(1+Inputs!C22,1/12) -> 110148.94 | AL8: =AK8*POWER(1+Inputs!C22,1/12) -> 111439.33 | AM8: =AL8*POWER(1+Inputs!C22,1/12) -> 112744.83
A9: BTC price (ZAR) | B9: ZAR/BTC | C9: USD price x FX | D9: =D8*Inputs!C20 -> 1275000 | E9: =E8*Inputs!C20 -> 1289936.5 | F9: =F8*Inputs!C20 -> 1305048 | G9: =G8*Inputs!C20 -> 1320336.5 | H9: =H8*Inputs!C20 -> 1335804.2 | I9: =I8*Inputs!C20 -> 1351453 | J9: =J8*Inputs!C20 -> 1367285.2 | K9: =K8*Inputs!C20 -> 1383302.8 | L9: =L8*Inputs!C20 -> 1399508.1 | M9: =M8*Inputs!C20 -> 1415903.2 | N9: =N8*Inputs!C20 -> 1432490.4 | O9: =O8*Inputs!C20 -> 1449271.9 | P9: =P8*Inputs!C20 -> 1466250 | Q9: =Q8*Inputs!C20 -> 1483427 | R9: =R8*Inputs!C20 -> 1500805.2 | S9: =S8*Inputs!C20 -> 1518387 | T9: =T8*Inputs!C20 -> 1536174.8 | U9: =U8*Inputs!C20 -> 1554171 | V9: =V8*Inputs!C20 -> 1572378 | W9: =W8*Inputs!C20 -> 1590798.2 | X9: =X8*Inputs!C20 -> 1609434.3 | Y9: =Y8*Inputs!C20 -> 1628288.7 | Z9: =Z8*Inputs!C20 -> 1647364 | AA9: =AA8*Inputs!C20 -> 1666662.7 | AB9: =AB8*Inputs!C20 -> 1686187.5 | AC9: =AC8*Inputs!C20 -> 1705941 | AD9: =AD8*Inputs!C20 -> 1725926 | AE9: =AE8*Inputs!C20 -> 1746145.1 | AF9: =AF8*Inputs!C20 -> 1766601 | AG9: =AG8*Inputs!C20 -> 1787296.6 | AH9: =AH8*Inputs!C20 -> 1808234.6 | AI9: =AI8*Inputs!C20 -> 1829418 | AJ9: =AJ8*Inputs!C20 -> 1850849.4 | AK9: =AK8*Inputs!C20 -> 1872532 | AL9: =AL8*Inputs!C20 -> 1894468.5 | AM9: =AM8*Inputs!C20 -> 1916662.1
A10: Network hash | B10: TH/s | C10: Monthly compounding from annual growth | D10: =Inputs!C23 -> 900000000 | E10: =D10*POWER(1+Inputs!C24,1/12) -> 9.0717673e+08 | F10: =E10*POWER(1+Inputs!C24,1/12) -> 9.1441068e+08 | G10: =F10*POWER(1+Inputs!C24,1/12) -> 9.2170232e+08 | H10: =G10*POWER(1+Inputs!C24,1/12) -> 9.290521e+08 | I10: =H10*POWER(1+Inputs!C24,1/12) -> 9.364605e+08 | J10: =I10*POWER(1+Inputs!C24,1/12) -> 9.4392796e+08 | K10: =J10*POWER(1+Inputs!C24,1/12) -> 9.5145498e+08 | L10: =K10*POWER(1+Inputs!C24,1/12) -> 9.5904201e+08 | M10: =L10*POWER(1+Inputs!C24,1/12) -> 9.6668955e+08 | N10: =M10*POWER(1+Inputs!C24,1/12) -> 9.7439807e+08 | O10: =N10*POWER(1+Inputs!C24,1/12) -> 9.8216805e+08 | P10: =O10*POWER(1+Inputs!C24,1/12) -> 9.9e+08 | Q10: =P10*POWER(1+Inputs!C24,1/12) -> 9.978944e+08 | R10: =Q10*POWER(1+Inputs!C24,1/12) -> 1.0058517e+09 | S10: =R10*POWER(1+Inputs!C24,1/12) -> 1.0138726e+09 | T10: =S10*POWER(1+Inputs!C24,1/12) -> 1.0219573e+09 | U10: =T10*POWER(1+Inputs!C24,1/12) -> 1.0301065e+09 | V10: =U10*POWER(1+Inputs!C24,1/12) -> 1.0383208e+09 | W10: =V10*POWER(1+Inputs!C24,1/12) -> 1.0466005e+09 | X10: =W10*POWER(1+Inputs!C24,1/12) -> 1.0549462e+09 | Y10: =X10*POWER(1+Inputs!C24,1/12) -> 1.0633585e+09 | Z10: =Y10*POWER(1+Inputs!C24,1/12) -> 1.0718379e+09 | AA10: =Z10*POWER(1+Inputs!C24,1/12) -> 1.0803849e+09 | AB10: =AA10*POWER(1+Inputs!C24,1/12) -> 1.089e+09 | AC10: =AB10*POWER(1+Inputs!C24,1/12) -> 1.0976838e+09 | AD10: =AC10*POWER(1+Inputs!C24,1/12) -> 1.1064369e+09 | AE10: =AD10*POWER(1+Inputs!C24,1/12) -> 1.1152598e+09 | AF10: =AE10*POWER(1+Inputs!C24,1/12) -> 1.124153e+09 | AG10: =AF10*POWER(1+Inputs!C24,1/12) -> 1.1331172e+09 | AH10: =AG10*POWER(1+Inputs!C24,1/12) -> 1.1421528e+09 | AI10: =AH10*POWER(1+Inputs!C24,1/12) -> 1.1512605e+09 | AJ10: =AI10*POWER(1+Inputs!C24,1/12) -> 1.1604408e+09 | AK10: =AJ10*POWER(1+Inputs!C24,1/12) -> 1.1696944e+09 | AL10: =AK10*POWER(1+Inputs!C24,1/12) -> 1.1790217e+09 | AM10: =AL10*POWER(1+Inputs!C24,1/12) -> 1.1884233e+09
A11: Network BTC mined | B11: BTC/month | C11: Blocks/day x subsidy x fee factor x days | D11: =D6*Inputs!C25*Inputs!C26*(1+Inputs!C27) -> 16042.5 | E11: =E6*Inputs!C25*Inputs!C26*(1+Inputs!C27) -> 16042.5 | F11: =F6*Inputs!C25*Inputs!C26*(1+Inputs!C27) -> 15525 | G11: =G6*Inputs!C25*Inputs!C26*(1+Inputs!C27) -> 16042.5 | H11: =H6*Inputs!C25*Inputs!C26*(1+Inputs!C27) -> 15525 | I11: =I6*Inputs!C25*Inputs!C26*(1+Inputs!C27) -> 16042.5 | J11: =J6*Inputs!C25*Inputs!C26*(1+Inputs!C27) -> 16042.5 | K11: =K6*Inputs!C25*Inputs!C26*(1+Inputs!C27) -> 14490 | L11: =L6*Inputs!C25*Inputs!C26*(1+Inputs!C27) -> 16042.5 | M11: =M6*Inputs!C25*Inputs!C26*(1+Inputs!C27) -> 15525 | N11: =N6*Inputs!C25*Inputs!C26*(1+Inputs!C27) -> 16042.5 | O11: =O6*Inputs!C25*Inputs!C26*(1+Inputs!C27) -> 15525 | P11: =P6*Inputs!C25*Inputs!C26*(1+Inputs!C27) -> 16042.5 | Q11: =Q6*Inputs!C25*Inputs!C26*(1+Inputs!C27) -> 16042.5 | R11: =R6*Inputs!C25*Inputs!C26*(1+Inputs!C27) -> 15525 | S11: =S6*Inputs!C25*Inputs!C26*(1+Inputs!C27) -> 16042.5 | T11: =T6*Inputs!C25*Inputs!C26*(1+Inputs!C27) -> 15525 | U11: =U6*Inputs!C25*Inputs!C26*(1+Inputs!C27) -> 16042.5 | V11: =V6*Inputs!C25*Inputs!C26*(1+Inputs!C27) -> 16042.5 | W11: =W6*Inputs!C25*Inputs!C26*(1+Inputs!C27) -> 15007.5 | X11: =X6*Inputs!C25*Inputs!C26*(1+Inputs!C27) -> 16042.5 | Y11: =Y6*Inputs!C25*Inputs!C26*(1+Inputs!C27) -> 15525 | Z11: =Z6*Inputs!C25*Inputs!C26*(1+Inputs!C27) -> 16042.5 | AA11: =AA6*Inputs!C25*Inputs!C26*(1+Inputs!C27) -> 15525 | AB11: =AB6*Inputs!C25*Inputs!C26*(1+Inputs!C27) -> 16042.5 | AC11: =AC6*Inputs!C25*Inputs!C26*(1+Inputs!C27) -> 16042.5 | AD11: =AD6*Inputs!C25*Inputs!C26*(1+Inputs!C27) -> 15525 | AE11: =AE6*Inputs!C25*Inputs!C26*(1+Inputs!C27) -> 16042.5 | AF11: =AF6*Inputs!C25*Inputs!C26*(1+Inputs!C27) -> 15525 | AG11: =AG6*Inputs!C25*Inputs!C26*(1+Inputs!C27) -> 16042.5 | AH11: =AH6*Inputs!C25*Inputs!C26*(1+Inputs!C27) -> 16042.5 | AI11: =AI6*Inputs!C25*Inputs!C26*(1+Inputs!C27) -> 14490 | AJ11: =AJ6*Inputs!C25*Inputs!C26*(1+Inputs!C27) -> 16042.5 | AK11: =AK6*Inputs!C25*Inputs!C26*(1+Inputs!C27) -> 15525 | AL11: =AL6*Inputs!C25*Inputs!C26*(1+Inputs!C27) -> 16042.5 | AM11: =AM6*Inputs!C25*Inputs!C26*(1+Inputs!C27) -> 15525
A14: Grootvlei BTC mined | B14: BTC/month | C14: Uses Grootvlei avg MW, 22h/day and technical uptime | D14: =IF(Deployment_36M!D18=0,0,(Deployment_36M!D18*(1-Inputs!C11)*1000000/Inputs!C40*Inputs!C38*Inputs!C10*Inputs!C12/24/D10*D11) ) -> 0 | E14: =IF(Deployment_36M!E18=0,0,(Deployment_36M!E18*(1-Inputs!C11)*1000000/Inputs!C40*Inputs!C38*Inputs!C10*Inputs!C12/24/E10*E11) ) -> 0 | F14: =IF(Deployment_36M!F18=0,0,(Deployment_36M!F18*(1-Inputs!C11)*1000000/Inputs!C40*Inputs!C38*Inputs!C10*Inputs!C12/24/F10*F11) ) -> 2.8978869 | G14: =IF(Deployment_36M!G18=0,0,(Deployment_36M!G18*(1-Inputs!C11)*1000000/Inputs!C40*Inputs!C38*Inputs!C10*Inputs!C12/24/G10*G11) ) -> 8.9123809 | H14: =IF(Deployment_36M!H18=0,0,(Deployment_36M!H18*(1-Inputs!C11)*1000000/Inputs!C40*Inputs!C38*Inputs!C10*Inputs!C12/24/H10*H11) ) -> 14.261088 | I14: =IF(Deployment_36M!I18=0,0,(Deployment_36M!I18*(1-Inputs!C11)*1000000/Inputs!C40*Inputs!C38*Inputs!C10*Inputs!C12/24/I10*I11) ) -> 17.543852 | J14: =IF(Deployment_36M!J18=0,0,(Deployment_36M!J18*(1-Inputs!C11)*1000000/Inputs!C40*Inputs!C38*Inputs!C10*Inputs!C12/24/J10*J11) ) -> 17.405061 | K14: =IF(Deployment_36M!K18=0,0,(Deployment_36M!K18*(1-Inputs!C11)*1000000/Inputs!C40*Inputs!C38*Inputs!C10*Inputs!C12/24/K10*K11) ) -> 15.596333 | L14: =IF(Deployment_36M!L18=0,0,(Deployment_36M!L18*(1-Inputs!C11)*1000000/Inputs!C40*Inputs!C38*Inputs!C10*Inputs!C12/24/L10*L11) ) -> 17.130766 | M14: =IF(Deployment_36M!M18=0,0,(Deployment_36M!M18*(1-Inputs!C11)*1000000/Inputs!C40*Inputs!C38*Inputs!C10*Inputs!C12/24/M10*M11) ) -> 16.44701 | N14: =IF(Deployment_36M!N18=0,0,(Deployment_36M!N18*(1-Inputs!C11)*1000000/Inputs!C40*Inputs!C38*Inputs!C10*Inputs!C12/24/N10*N11) ) -> 16.860793 | O14: =IF(Deployment_36M!O18=0,0,(Deployment_36M!O18*(1-Inputs!C11)*1000000/Inputs!C40*Inputs!C38*Inputs!C10*Inputs!C12/24/O10*O11) ) -> 16.187813 | P14: =IF(Deployment_36M!P18=0,0,(Deployment_36M!P18*(1-Inputs!C11)*1000000/Inputs!C40*Inputs!C38*Inputs!C10*Inputs!C12/24/P10*P11) ) -> 16.595075 | Q14: =IF(Deployment_36M!Q18=0,0,(Deployment_36M!Q18*(1-Inputs!C11)*1000000/Inputs!C40*Inputs!C38*Inputs!C10*Inputs!C12/24/Q10*Q11) ) -> 16.46379 | R14: =IF(Deployment_36M!R18=0,0,(Deployment_36M!R18*(1-Inputs!C11)*1000000/Inputs!C40*Inputs!C38*Inputs!C10*Inputs!C12/24/R10*R11) ) -> 15.806656 | S14: =IF(Deployment_36M!S18=0,0,(Deployment_36M!S18*(1-Inputs!C11)*1000000/Inputs!C40*Inputs!C38*Inputs!C10*Inputs!C12/24/S10*S11) ) -> 16.204329 | T14: =IF(Deployment_36M!T18=0,0,(Deployment_36M!T18*(1-Inputs!C11)*1000000/Inputs!C40*Inputs!C38*Inputs!C10*Inputs!C12/24/T10*T11) ) -> 15.55755 | U14: =IF(Deployment_36M!U18=0,0,(Deployment_36M!U18*(1-Inputs!C11)*1000000/Inputs!C40*Inputs!C38*Inputs!C10*Inputs!C12/24/U10*U11) ) -> 15.948956 | V14: =IF(Deployment_36M!V18=0,0,(Deployment_36M!V18*(1-Inputs!C11)*1000000/Inputs!C40*Inputs!C38*Inputs!C10*Inputs!C12/24/V10*V11) ) -> 15.822783 | W14: =IF(Deployment_36M!W18=0,0,(Deployment_36M!W18*(1-Inputs!C11)*1000000/Inputs!C40*Inputs!C38*Inputs!C10*Inputs!C12/24/W10*W11) ) -> 14.684859 | X14: =IF(Deployment_36M!X18=0,0,(Deployment_36M!X18*(1-Inputs!C11)*1000000/Inputs!C40*Inputs!C38*Inputs!C10*Inputs!C12/24/X10*X11) ) -> 15.573424 | Y14: =IF(Deployment_36M!Y18=0,0,(Deployment_36M!Y18*(1-Inputs!C11)*1000000/Inputs!C40*Inputs!C38*Inputs!C10*Inputs!C12/24/Y10*Y11) ) -> 14.951827 | Z14: =IF(Deployment_36M!Z18=0,0,(Deployment_36M!Z18*(1-Inputs!C11)*1000000/Inputs!C40*Inputs!C38*Inputs!C10*Inputs!C12/24/Z10*Z11) ) -> 15.327994 | AA14: =IF(Deployment_36M!AA18=0,0,(Deployment_36M!AA18*(1-Inputs!C11)*1000000/Inputs!C40*Inputs!C38*Inputs!C10*Inputs!C12/24/AA10*AA11) ) -> 14.716193 | AB14: =IF(Deployment_36M!AB18=0,0,(Deployment_36M!AB18*(1-Inputs!C11)*1000000/Inputs!C40*Inputs!C38*Inputs!C10*Inputs!C12/24/AB10*AB11) ) -> 15.086432 | AC14: =IF(Deployment_36M!AC18=0,0,(Deployment_36M!AC18*(1-Inputs!C11)*1000000/Inputs!C40*Inputs!C38*Inputs!C10*Inputs!C12/24/AC10*AC11) ) -> 14.967082 | AD14: =IF(Deployment_36M!AD18=0,0,(Deployment_36M!AD18*(1-Inputs!C11)*1000000/Inputs!C40*Inputs!C38*Inputs!C10*Inputs!C12/24/AD10*AD11) ) -> 14.369687 | AE14: =IF(Deployment_36M!AE18=0,0,(Deployment_36M!AE18*(1-Inputs!C11)*1000000/Inputs!C40*Inputs!C38*Inputs!C10*Inputs!C12/24/AE10*AE11) ) -> 14.731208 | AF14: =IF(Deployment_36M!AF18=0,0,(Deployment_36M!AF18*(1-Inputs!C11)*1000000/Inputs!C40*Inputs!C38*Inputs!C10*Inputs!C12/24/AF10*AF11) ) -> 14.143228 | AG14: =IF(Deployment_36M!AG18=0,0,(Deployment_36M!AG18*(1-Inputs!C11)*1000000/Inputs!C40*Inputs!C38*Inputs!C10*Inputs!C12/24/AG10*AG11) ) -> 14.499051 | AH14: =IF(Deployment_36M!AH18=0,0,(Deployment_36M!AH18*(1-Inputs!C11)*1000000/Inputs!C40*Inputs!C38*Inputs!C10*Inputs!C12/24/AH10*AH11) ) -> 14.384348 | AI14: =IF(Deployment_36M!AI18=0,0,(Deployment_36M!AI18*(1-Inputs!C11)*1000000/Inputs!C40*Inputs!C38*Inputs!C10*Inputs!C12/24/AI10*AI11) ) -> 12.889532 | AJ14: =IF(Deployment_36M!AJ18=0,0,(Deployment_36M!AJ18*(1-Inputs!C11)*1000000/Inputs!C40*Inputs!C38*Inputs!C10*Inputs!C12/24/AJ10*AJ11) ) -> 14.157658 | AK14: =IF(Deployment_36M!AK18=0,0,(Deployment_36M!AK18*(1-Inputs!C11)*1000000/Inputs!C40*Inputs!C38*Inputs!C10*Inputs!C12/24/AK10*AK11) ) -> 13.59257 | AL14: =IF(Deployment_36M!AL18=0,0,(Deployment_36M!AL18*(1-Inputs!C11)*1000000/Inputs!C40*Inputs!C38*Inputs!C10*Inputs!C12/24/AL10*AL11) ) -> 13.93454 | AM14: =IF(Deployment_36M!AM18=0,0,(Deployment_36M!AM18*(1-Inputs!C11)*1000000/Inputs!C40*Inputs!C38*Inputs!C10*Inputs!C12/24/AM10*AM11) ) -> 13.378358
A15: AMSA BTC mined | B15: BTC/month | C15: Uses AMSA avg MW and combined grid + solar operating hours | D15: =IF(Deployment_36M!D19=0,0,(Deployment_36M!D19*(1-Inputs!C11)*1000000/Inputs!C40*Inputs!C38*Inputs!C10*(Inputs!C13+Inputs!C14)/24/D10*D11) ) -> 0 | E15: =IF(Deployment_36M!E19=0,0,(Deployment_36M!E19*(1-Inputs!C11)*1000000/Inputs!C40*Inputs!C38*Inputs!C10*(Inputs!C13+Inputs!C14)/24/E10*E11) ) -> 0 | F15: =IF(Deployment_36M!F19=0,0,(Deployment_36M!F19*(1-Inputs!C11)*1000000/Inputs!C40*Inputs!C38*Inputs!C10*(Inputs!C13+Inputs!C14)/24/F10*F11) ) -> 0 | G15: =IF(Deployment_36M!G19=0,0,(Deployment_36M!G19*(1-Inputs!C11)*1000000/Inputs!C40*Inputs!C38*Inputs!C10*(Inputs!C13+Inputs!C14)/24/G10*G11) ) -> 0 | H15: =IF(Deployment_36M!H19=0,0,(Deployment_36M!H19*(1-Inputs!C11)*1000000/Inputs!C40*Inputs!C38*Inputs!C10*(Inputs!C13+Inputs!C14)/24/H10*H11) ) -> 0 | I15: =IF(Deployment_36M!I19=0,0,(Deployment_36M!I19*(1-Inputs!C11)*1000000/Inputs!C40*Inputs!C38*Inputs!C10*(Inputs!C13+Inputs!C14)/24/I10*I11) ) -> 2.7910673 | J15: =IF(Deployment_36M!J19=0,0,(Deployment_36M!J19*(1-Inputs!C11)*1000000/Inputs!C40*Inputs!C38*Inputs!C10*(Inputs!C13+Inputs!C14)/24/J10*J11) ) -> 5.5379741 | K15: =IF(Deployment_36M!K19=0,0,(Deployment_36M!K19*(1-Inputs!C11)*1000000/Inputs!C40*Inputs!C38*Inputs!C10*(Inputs!C13+Inputs!C14)/24/K10*K11) ) -> 4.9624697 | L15: =IF(Deployment_36M!L19=0,0,(Deployment_36M!L19*(1-Inputs!C11)*1000000/Inputs!C40*Inputs!C38*Inputs!C10*(Inputs!C13+Inputs!C14)/24/L10*L11) ) -> 5.4506983 | M15: =IF(Deployment_36M!M19=0,0,(Deployment_36M!M19*(1-Inputs!C11)*1000000/Inputs!C40*Inputs!C38*Inputs!C10*(Inputs!C13+Inputs!C14)/24/M10*M11) ) -> 5.2331395 | N15: =IF(Deployment_36M!N19=0,0,(Deployment_36M!N19*(1-Inputs!C11)*1000000/Inputs!C40*Inputs!C38*Inputs!C10*(Inputs!C13+Inputs!C14)/24/N10*N11) ) -> 5.3647978 | O15: =IF(Deployment_36M!O19=0,0,(Deployment_36M!O19*(1-Inputs!C11)*1000000/Inputs!C40*Inputs!C38*Inputs!C10*(Inputs!C13+Inputs!C14)/24/O10*O11) ) -> 5.1506677 | P15: =IF(Deployment_36M!P19=0,0,(Deployment_36M!P19*(1-Inputs!C11)*1000000/Inputs!C40*Inputs!C38*Inputs!C10*(Inputs!C13+Inputs!C14)/24/P10*P11) ) -> 5.2802511 | Q15: =IF(Deployment_36M!Q19=0,0,(Deployment_36M!Q19*(1-Inputs!C11)*1000000/Inputs!C40*Inputs!C38*Inputs!C10*(Inputs!C13+Inputs!C14)/24/Q10*Q11) ) -> 5.2384788 | R15: =IF(Deployment_36M!R19=0,0,(Deployment_36M!R19*(1-Inputs!C11)*1000000/Inputs!C40*Inputs!C38*Inputs!C10*(Inputs!C13+Inputs!C14)/24/R10*R11) ) -> 5.0293905 | S15: =IF(Deployment_36M!S19=0,0,(Deployment_36M!S19*(1-Inputs!C11)*1000000/Inputs!C40*Inputs!C38*Inputs!C10*(Inputs!C13+Inputs!C14)/24/S10*S11) ) -> 5.1559228 | T15: =IF(Deployment_36M!T19=0,0,(Deployment_36M!T19*(1-Inputs!C11)*1000000/Inputs!C40*Inputs!C38*Inputs!C10*(Inputs!C13+Inputs!C14)/24/T10*T11) ) -> 4.9501297 | U15: =IF(Deployment_36M!U19=0,0,(Deployment_36M!U19*(1-Inputs!C11)*1000000/Inputs!C40*Inputs!C38*Inputs!C10*(Inputs!C13+Inputs!C14)/24/U10*U11) ) -> 5.0746679 | V15: =IF(Deployment_36M!V19=0,0,(Deployment_36M!V19*(1-Inputs!C11)*1000000/Inputs!C40*Inputs!C38*Inputs!C10*(Inputs!C13+Inputs!C14)/24/V10*V11) ) -> 5.0345219 | W15: =IF(Deployment_36M!W19=0,0,(Deployment_36M!W19*(1-Inputs!C11)*1000000/Inputs!C40*Inputs!C38*Inputs!C10*(Inputs!C13+Inputs!C14)/24/W10*W11) ) -> 4.6724552 | X15: =IF(Deployment_36M!X19=0,0,(Deployment_36M!X19*(1-Inputs!C11)*1000000/Inputs!C40*Inputs!C38*Inputs!C10*(Inputs!C13+Inputs!C14)/24/X10*X11) ) -> 4.9551802 | Y15: =IF(Deployment_36M!Y19=0,0,(Deployment_36M!Y19*(1-Inputs!C11)*1000000/Inputs!C40*Inputs!C38*Inputs!C10*(Inputs!C13+Inputs!C14)/24/Y10*Y11) ) -> 4.7573995 | Z15: =IF(Deployment_36M!Z19=0,0,(Deployment_36M!Z19*(1-Inputs!C11)*1000000/Inputs!C40*Inputs!C38*Inputs!C10*(Inputs!C13+Inputs!C14)/24/Z10*Z11) ) -> 4.8770889 | AA15: =IF(Deployment_36M!AA19=0,0,(Deployment_36M!AA19*(1-Inputs!C11)*1000000/Inputs!C40*Inputs!C38*Inputs!C10*(Inputs!C13+Inputs!C14)/24/AA10*AA11) ) -> 4.6824252 | AB15: =IF(Deployment_36M!AB19=0,0,(Deployment_36M!AB19*(1-Inputs!C11)*1000000/Inputs!C40*Inputs!C38*Inputs!C10*(Inputs!C13+Inputs!C14)/24/AB10*AB11) ) -> 4.8002283 | AC15: =IF(Deployment_36M!AC19=0,0,(Deployment_36M!AC19*(1-Inputs!C11)*1000000/Inputs!C40*Inputs!C38*Inputs!C10*(Inputs!C13+Inputs!C14)/24/AC10*AC11) ) -> 4.7622534 | AD15: =IF(Deployment_36M!AD19=0,0,(Deployment_36M!AD19*(1-Inputs!C11)*1000000/Inputs!C40*Inputs!C38*Inputs!C10*(Inputs!C13+Inputs!C14)/24/AD10*AD11) ) -> 4.5721732 | AE15: =IF(Deployment_36M!AE19=0,0,(Deployment_36M!AE19*(1-Inputs!C11)*1000000/Inputs!C40*Inputs!C38*Inputs!C10*(Inputs!C13+Inputs!C14)/24/AE10*AE11) ) -> 4.6872026 | AF15: =IF(Deployment_36M!AF19=0,0,(Deployment_36M!AF19*(1-Inputs!C11)*1000000/Inputs!C40*Inputs!C38*Inputs!C10*(Inputs!C13+Inputs!C14)/24/AF10*AF11) ) -> 4.5001179 | AG15: =IF(Deployment_36M!AG19=0,0,(Deployment_36M!AG19*(1-Inputs!C11)*1000000/Inputs!C40*Inputs!C38*Inputs!C10*(Inputs!C13+Inputs!C14)/24/AG10*AG11) ) -> 4.6133345 | AH15: =IF(Deployment_36M!AH19=0,0,(Deployment_36M!AH19*(1-Inputs!C11)*1000000/Inputs!C40*Inputs!C38*Inputs!C10*(Inputs!C13+Inputs!C14)/24/AH10*AH11) ) -> 4.5768381 | AI15: =IF(Deployment_36M!AI19=0,0,(Deployment_36M!AI19*(1-Inputs!C11)*1000000/Inputs!C40*Inputs!C38*Inputs!C10*(Inputs!C13+Inputs!C14)/24/AI10*AI11) ) -> 4.1012146 | AJ15: =IF(Deployment_36M!AJ19=0,0,(Deployment_36M!AJ19*(1-Inputs!C11)*1000000/Inputs!C40*Inputs!C38*Inputs!C10*(Inputs!C13+Inputs!C14)/24/AJ10*AJ11) ) -> 4.5047093 | AK15: =IF(Deployment_36M!AK19=0,0,(Deployment_36M!AK19*(1-Inputs!C11)*1000000/Inputs!C40*Inputs!C38*Inputs!C10*(Inputs!C13+Inputs!C14)/24/AK10*AK11) ) -> 4.3249087 | AL15: =IF(Deployment_36M!AL19=0,0,(Deployment_36M!AL19*(1-Inputs!C11)*1000000/Inputs!C40*Inputs!C38*Inputs!C10*(Inputs!C13+Inputs!C14)/24/AL10*AL11) ) -> 4.4337172 | AM15: =IF(Deployment_36M!AM19=0,0,(Deployment_36M!AM19*(1-Inputs!C11)*1000000/Inputs!C40*Inputs!C38*Inputs!C10*(Inputs!C13+Inputs!C14)/24/AM10*AM11) ) -> 4.2567501
A16: Total BTC mined | B16: BTC/month | C16: Sum of sites | D16: =D14+D15 -> 0 | E16: =E14+E15 -> 0 | F16: =F14+F15 -> 2.8978869 | G16: =G14+G15 -> 8.9123809 | H16: =H14+H15 -> 14.261088 | I16: =I14+I15 -> 20.334919 | J16: =J14+J15 -> 22.943036 | K16: =K14+K15 -> 20.558803 | ... AM16: =AM14+AM15 -> 17.635108
A17: BTC revenue | B17: ZAR'000 | C17: Base-case anchor revenue | D17: =D16*D9/1000 -> 0 | E17: =E16*E9/1000 -> 0 | F17: =F16*F9/1000 -> 3781.8816 | G17: =G16*G9/1000 -> 11767.342 | H17: =H16*H9/1000 -> 19050.021 | I17: =I16*I9/1000 -> 27481.688 | J17: =J16*J9/1000 -> 31369.672 | K17: =K16*K9/1000 -> 28439.05 | ... AM17: =AM16*AM9/1000 -> 33800.542
A18: Demand response revenue | B18: ZAR'000 | C18: Optionality line; off by default | D18: =IF(AND(Inputs!C82=1,1>=Inputs!C83),Deployment_36M!D21*Inputs!C85*D6*1000*Inputs!C84*Inputs!C86/1000,0) -> 0 | E18: =IF(AND(Inputs!C82=1,2>=Inputs!C83),Deployment_36M!E21*Inputs!C85*E6*1000*Inputs!C84*Inputs!C86/1000,0) -> 0 | F18: =IF(AND(Inputs!C82=1,3>=Inputs!C83),Deployment_36M!F21*Inputs!C85*F6*1000*Inputs!C84*Inputs!C86/1000,0) -> 0 | G18: =IF(AND(Inputs!C82=1,4>=Inputs!C83),Deployment_36M!G21*Inputs!C85*G6*1000*Inputs!C84*Inputs!C86/1000,0) -> 0 | H18: =IF(AND(Inputs!C82=1,5>=Inputs!C83),Deployment_36M!H21*Inputs!C85*H6*1000*Inputs!C84*Inputs!C86/1000,0) -> 0 | I18: =IF(AND(Inputs!C82=1,6>=Inputs!C83),Deployment_36M!I21*Inputs!C85*I6*1000*Inputs!C84*Inputs!C86/1000,0) -> 0 | J18: =IF(AND(Inputs!C82=1,7>=Inputs!C83),Deployment_36M!J21*Inputs!C85*J6*1000*Inputs!C84*Inputs!C86/1000,0) -> 0 | K18: =IF(AND(Inputs!C82=1,8>=Inputs!C83),Deployment_36M!K21*Inputs!C85*K6*1000*Inputs!C84*Inputs!C86/1000,0) -> 0 | L18: =IF(AND(Inputs!C82=1,9>=Inputs!C83),Deployment_36M!L21*Inputs!C85*L6*1000*Inputs!C84*Inputs!C86/1000,0) -> 0 | M18: =IF(AND(Inputs!C82=1,10>=Inputs!C83),Deployment_36M!M21*Inputs!C85*M6*1000*Inputs!C84*Inputs!C86/1000,0) -> 0 | N18: =IF(AND(Inputs!C82=1,11>=Inputs!C83),Deployment_36M!N21*Inputs!C85*N6*1000*Inputs!C84*Inputs!C86/1000,0) -> 0 | O18: =IF(AND(Inputs!C82=1,12>=Inputs!C83),Deployment_36M!O21*Inputs!C85*O6*1000*Inputs!C84*Inputs!C86/1000,0) -> 0 | P18: =IF(AND(Inputs!C82=1,13>=Inputs!C83),Deployment_36M!P21*Inputs!C85*P6*1000*Inputs!C84*Inputs!C86/1000,0) -> 0 | Q18: =IF(AND(Inputs!C82=1,14>=Inputs!C83),Deployment_36M!Q21*Inputs!C85*Q6*1000*Inputs!C84*Inputs!C86/1000,0) -> 0 | R18: =IF(AND(Inputs!C82=1,15>=Inputs!C83),Deployment_36M!R21*Inputs!C85*R6*1000*Inputs!C84*Inputs!C86/1000,0) -> 0 | S18: =IF(AND(Inputs!C82=1,16>=Inputs!C83),Deployment_36M!S21*Inputs!C85*S6*1000*Inputs!C84*Inputs!C86/1000,0) -> 0 | T18: =IF(AND(Inputs!C82=1,17>=Inputs!C83),Deployment_36M!T21*Inputs!C85*T6*1000*Inputs!C84*Inputs!C86/1000,0) -> 0 | U18: =IF(AND(Inputs!C82=1,18>=Inputs!C83),Deployment_36M!U21*Inputs!C85*U6*1000*Inputs!C84*Inputs!C86/1000,0) -> 0 | V18: =IF(AND(Inputs!C82=1,19>=Inputs!C83),Deployment_36M!V21*Inputs!C85*V6*1000*Inputs!C84*Inputs!C86/1000,0) -> 0 | W18: =IF(AND(Inputs!C82=1,20>=Inputs!C83),Deployment_36M!W21*Inputs!C85*W6*1000*Inputs!C84*Inputs!C86/1000,0) -> 0 | X18: =IF(AND(Inputs!C82=1,21>=Inputs!C83),Deployment_36M!X21*Inputs!C85*X6*1000*Inputs!C84*Inputs!C86/1000,0) -> 0 | Y18: =IF(AND(Inputs!C82=1,22>=Inputs!C83),Deployment_36M!Y21*Inputs!C85*Y6*1000*Inputs!C84*Inputs!C86/1000,0) -> 0 | Z18: =IF(AND(Inputs!C82=1,23>=Inputs!C83),Deployment_36M!Z21*Inputs!C85*Z6*1000*Inputs!C84*Inputs!C86/1000,0) -> 0 | AA18: =IF(AND(Inputs!C82=1,24>=Inputs!C83),Deployment_36M!AA21*Inputs!C85*AA6*1000*Inputs!C84*Inputs!C86/1000,0) -> 0 | AB18: =IF(AND(Inputs!C82=1,25>=Inputs!C83),Deployment_36M!AB21*Inputs!C85*AB6*1000*Inputs!C84*Inputs!C86/1000,0) -> 0 | AC18: =IF(AND(Inputs!C82=1,26>=Inputs!C83),Deployment_36M!AC21*Inputs!C85*AC6*1000*Inputs!C84*Inputs!C86/1000,0) -> 0 | AD18: =IF(AND(Inputs!C82=1,27>=Inputs!C83),Deployment_36M!AD21*Inputs!C85*AD6*1000*Inputs!C84*Inputs!C86/1000,0) -> 0 | AE18: =IF(AND(Inputs!C82=1,28>=Inputs!C83),Deployment_36M!AE21*Inputs!C85*AE6*1000*Inputs!C84*Inputs!C86/1000,0) -> 0 | AF18: =IF(AND(Inputs!C82=1,29>=Inputs!C83),Deployment_36M!AF21*Inputs!C85*AF6*1000*Inputs!C84*Inputs!C86/1000,0) -> 0 | AG18: =IF(AND(Inputs!C82=1,30>=Inputs!C83),Deployment_36M!AG21*Inputs!C85*AG6*1000*Inputs!C84*Inputs!C86/1000,0) -> 0 | AH18: =IF(AND(Inputs!C82=1,31>=Inputs!C83),Deployment_36M!AH21*Inputs!C85*AH6*1000*Inputs!C84*Inputs!C86/1000,0) -> 0 | AI18: =IF(AND(Inputs!C82=1,32>=Inputs!C83),Deployment_36M!AI21*Inputs!C85*AI6*1000*Inputs!C84*Inputs!C86/1000,0) -> 0 | AJ18: =IF(AND(Inputs!C82=1,33>=Inputs!C83),Deployment_36M!AJ21*Inputs!C85*AJ6*1000*Inputs!C84*Inputs!C86/1000,0) -> 0 | AK18: =IF(AND(Inputs!C82=1,34>=Inputs!C83),Deployment_36M!AK21*Inputs!C85*AK6*1000*Inputs!C84*Inputs!C86/1000,0) -> 0 | AL18: =IF(AND(Inputs!C82=1,35>=Inputs!C83),Deployment_36M!AL21*Inputs!C85*AL6*1000*Inputs!C84*Inputs!C86/1000,0) -> 0 | AM18: =IF(AND(Inputs!C82=1,36>=Inputs!C83),Deployment_36M!AM21*Inputs!C85*AM6*1000*Inputs!C84*Inputs!C86/1000,0) -> 0
A19: Hyperscaler resale revenue | B19: ZAR'000 | C19: Optionality line; off by default | D19: =IF(AND(Inputs!C87=1,1>=Inputs!C88),MIN(Deployment_36M!D21,Inputs!C89)*Inputs!C90*D6*Inputs!C91*Inputs!C20,0)/1000 -> 0 | E19: =IF(AND(Inputs!C87=1,2>=Inputs!C88),MIN(Deployment_36M!E21,Inputs!C89)*Inputs!C90*E6*Inputs!C91*Inputs!C20,0)/1000 -> 0 | F19: =IF(AND(Inputs!C87=1,3>=Inputs!C88),MIN(Deployment_36M!F21,Inputs!C89)*Inputs!C90*F6*Inputs!C91*Inputs!C20,0)/1000 -> 0 | G19: =IF(AND(Inputs!C87=1,4>=Inputs!C88),MIN(Deployment_36M!G21,Inputs!C89)*Inputs!C90*G6*Inputs!C91*Inputs!C20,0)/1000 -> 0 | H19: =IF(AND(Inputs!C87=1,5>=Inputs!C88),MIN(Deployment_36M!H21,Inputs!C89)*Inputs!C90*H6*Inputs!C91*Inputs!C20,0)/1000 -> 0 | I19: =IF(AND(Inputs!C87=1,6>=Inputs!C88),MIN(Deployment_36M!I21,Inputs!C89)*Inputs!C90*I6*Inputs!C91*Inputs!C20,0)/1000 -> 0 | J19: =IF(AND(Inputs!C87=1,7>=Inputs!C88),MIN(Deployment_36M!J21,Inputs!C89)*Inputs!C90*J6*Inputs!C91*Inputs!C20,0)/1000 -> 0 | K19: =IF(AND(Inputs!C87=1,8>=Inputs!C88),MIN(Deployment_36M!K21,Inputs!C89)*Inputs!C90*K6*Inputs!C91*Inputs!C20,0)/1000 -> 0 | L19: =IF(AND(Inputs!C87=1,9>=Inputs!C88),MIN(Deployment_36M!L21,Inputs!C89)*Inputs!C90*L6*Inputs!C91*Inputs!C20,0)/1000 -> 0 | M19: =IF(AND(Inputs!C87=1,10>=Inputs!C88),MIN(Deployment_36M!M21,Inputs!C89)*Inputs!C90*M6*Inputs!C91*Inputs!C20,0)/1000 -> 0 | N19: =IF(AND(Inputs!C87=1,11>=Inputs!C88),MIN(Deployment_36M!N21,Inputs!C89)*Inputs!C90*N6*Inputs!C91*Inputs!C20,0)/1000 -> 0 | O19: =IF(AND(Inputs!C87=1,12>=Inputs!C88),MIN(Deployment_36M!O21,Inputs!C89)*Inputs!C90*O6*Inputs!C91*Inputs!C20,0)/1000 -> 0 | P19: =IF(AND(Inputs!C87=1,13>=Inputs!C88),MIN(Deployment_36M!P21,Inputs!C89)*Inputs!C90*P6*Inputs!C91*Inputs!C20,0)/1000 -> 0 | Q19: =IF(AND(Inputs!C87=1,14>=Inputs!C88),MIN(Deployment_36M!Q21,Inputs!C89)*Inputs!C90*Q6*Inputs!C91*Inputs!C20,0)/1000 -> 0 | R19: =IF(AND(Inputs!C87=1,15>=Inputs!C88),MIN(Deployment_36M!R21,Inputs!C89)*Inputs!C90*R6*Inputs!C91*Inputs!C20,0)/1000 -> 0 | S19: =IF(AND(Inputs!C87=1,16>=Inputs!C88),MIN(Deployment_36M!S21,Inputs!C89)*Inputs!C90*S6*Inputs!C91*Inputs!C20,0)/1000 -> 0 | T19: =IF(AND(Inputs!C87=1,17>=Inputs!C88),MIN(Deployment_36M!T21,Inputs!C89)*Inputs!C90*T6*Inputs!C91*Inputs!C20,0)/1000 -> 0 | U19: =IF(AND(Inputs!C87=1,18>=Inputs!C88),MIN(Deployment_36M!U21,Inputs!C89)*Inputs!C90*U6*Inputs!C91*Inputs!C20,0)/1000 -> 0 | V19: =IF(AND(Inputs!C87=1,19>=Inputs!C88),MIN(Deployment_36M!V21,Inputs!C89)*Inputs!C90*V6*Inputs!C91*Inputs!C20,0)/1000 -> 0 | W19: =IF(AND(Inputs!C87=1,20>=Inputs!C88),MIN(Deployment_36M!W21,Inputs!C89)*Inputs!C90*W6*Inputs!C91*Inputs!C20,0)/1000 -> 0 | X19: =IF(AND(Inputs!C87=1,21>=Inputs!C88),MIN(Deployment_36M!X21,Inputs!C89)*Inputs!C90*X6*Inputs!C91*Inputs!C20,0)/1000 -> 0 | Y19: =IF(AND(Inputs!C87=1,22>=Inputs!C88),MIN(Deployment_36M!Y21,Inputs!C89)*Inputs!C90*Y6*Inputs!C91*Inputs!C20,0)/1000 -> 0 | Z19: =IF(AND(Inputs!C87=1,23>=Inputs!C88),MIN(Deployment_36M!Z21,Inputs!C89)*Inputs!C90*Z6*Inputs!C91*Inputs!C20,0)/1000 -> 0 | AA19: =IF(AND(Inputs!C87=1,24>=Inputs!C88),MIN(Deployment_36M!AA21,Inputs!C89)*Inputs!C90*AA6*Inputs!C91*Inputs!C20,0)/1000 -> 0 | AB19: =IF(AND(Inputs!C87=1,25>=Inputs!C88),MIN(Deployment_36M!AB21,Inputs!C89)*Inputs!C90*AB6*Inputs!C91*Inputs!C20,0)/1000 -> 0 | AC19: =IF(AND(Inputs!C87=1,26>=Inputs!C88),MIN(Deployment_36M!AC21,Inputs!C89)*Inputs!C90*AC6*Inputs!C91*Inputs!C20,0)/1000 -> 0 | AD19: =IF(AND(Inputs!C87=1,27>=Inputs!C88),MIN(Deployment_36M!AD21,Inputs!C89)*Inputs!C90*AD6*Inputs!C91*Inputs!C20,0)/1000 -> 0 | AE19: =IF(AND(Inputs!C87=1,28>=Inputs!C88),MIN(Deployment_36M!AE21,Inputs!C89)*Inputs!C90*AE6*Inputs!C91*Inputs!C20,0)/1000 -> 0 | AF19: =IF(AND(Inputs!C87=1,29>=Inputs!C88),MIN(Deployment_36M!AF21,Inputs!C89)*Inputs!C90*AF6*Inputs!C91*Inputs!C20,0)/1000 -> 0 | AG19: =IF(AND(Inputs!C87=1,30>=Inputs!C88),MIN(Deployment_36M!AG21,Inputs!C89)*Inputs!C90*AG6*Inputs!C91*Inputs!C20,0)/1000 -> 0 | AH19: =IF(AND(Inputs!C87=1,31>=Inputs!C88),MIN(Deployment_36M!AH21,Inputs!C89)*Inputs!C90*AH6*Inputs!C91*Inputs!C20,0)/1000 -> 0 | AI19: =IF(AND(Inputs!C87=1,32>=Inputs!C88),MIN(Deployment_36M!AI21,Inputs!C89)*Inputs!C90*AI6*Inputs!C91*Inputs!C20,0)/1000 -> 0 | AJ19: =IF(AND(Inputs!C87=1,33>=Inputs!C88),MIN(Deployment_36M!AJ21,Inputs!C89)*Inputs!C90*AJ6*Inputs!C91*Inputs!C20,0)/1000 -> 0 | AK19: =IF(AND(Inputs!C87=1,34>=Inputs!C88),MIN(Deployment_36M!AK21,Inputs!C89)*Inputs!C90*AK6*Inputs!C91*Inputs!C20,0)/1000 -> 0 | AL19: =IF(AND(Inputs!C87=1,35>=Inputs!C88),MIN(Deployment_36M!AL21,Inputs!C89)*Inputs!C90*AL6*Inputs!C91*Inputs!C20,0)/1000 -> 0 | AM19: =IF(AND(Inputs!C87=1,36>=Inputs!C88),MIN(Deployment_36M!AM21,Inputs!C89)*Inputs!C90*AM6*Inputs!C91*Inputs!C20,0)/1000 -> 0
A20: Total revenue - base case | B20: ZAR'000 | C20: Base case used in Funding sheet | D20: =D17 -> 0 | E20: =E17 -> 0 | F20: =F17 -> 3781.8816 | G20: =G17 -> 11767.342 | H20: =H17 -> 19050.021 | I20: =I17 -> 27481.688 | J20: =J17 -> 31369.672 | K20: =K17 -> 28439.05 | ... AM20: =AM17 -> 33800.542
A21: Total revenue - with optionality | B21: ZAR'000 | C21: BTC + toggled optionality | D21: =D17+D18+D19 -> 0 | E21: =E17+E18+E19 -> 0 | F21: =F17+F18+F19 -> 3781.8816 | G21: =G17+G18+G19 -> 11767.342 | H21: =H17+H18+H19 -> 19050.021 | I21: =I17+I18+I19 -> 27481.688 | J21: =J17+J18+J19 -> 31369.672 | K21: =K17+K18+K19 -> 28439.05 | ... AM21: =AM17+AM18+AM19 -> 33800.542

Sheet Opex_36M
A1: Opex_36M | Site energy, people and recurring operating costs
A2: Energy cost is the dominant driver. Payroll and recurring overheads remain visible but simplified.
A4: Metric | B4: Unit | C4: Notes
A5: Date | B5: date | C5: Linked from deployment | D5: =Deployment_36M!D5 -> 46204 | E5: =Deployment_36M!E5 -> 46235 | F5: =Deployment_36M!F5 -> 46266 | G5: =Deployment_36M!G5 -> 46296 | H5: =Deployment_36M!H5 -> 46327 | I5: =Deployment_36M!I5 -> 46357 | J5: =Deployment_36M!J5 -> 46388 | K5: =Deployment_36M!K5 -> 46419 | ... AM5: =Deployment_36M!AM5 -> 47270
A6: Days in month | B6: days | C6: Linked from deployment | D6: =Deployment_36M!D6 -> 31 | E6: =Deployment_36M!E6 -> 31 | F6: =Deployment_36M!F6 -> 30 | G6: =Deployment_36M!G6 -> 31 | H6: =Deployment_36M!H6 -> 30 | I6: =Deployment_36M!I6 -> 31 | J6: =Deployment_36M!J6 -> 31 | K6: =Deployment_36M!K6 -> 28 | ... AM6: =Deployment_36M!AM6 -> 30
A8: Grootvlei electricity cost | B8: ZAR'000 | C8: Gross MW x hours/day x tariff x uptime | D8: =Deployment_36M!D18*Inputs!C12*D6*1000*Inputs!C29*Inputs!C10/1000 -> 0 | E8: =Deployment_36M!E18*Inputs!C12*E6*1000*Inputs!C29*Inputs!C10/1000 -> 0 | F8: =Deployment_36M!F18*Inputs!C12*F6*1000*Inputs!C29*Inputs!C10/1000 -> 1617 | G8: =Deployment_36M!G18*Inputs!C12*G6*1000*Inputs!C29*Inputs!C10/1000 -> 5012.7 | H8: =Deployment_36M!H18*Inputs!C12*H6*1000*Inputs!C29*Inputs!C10/1000 -> 8085 | I8: =Deployment_36M!I18*Inputs!C12*I6*1000*Inputs!C29*Inputs!C10/1000 -> 10025.4 | J8: =Deployment_36M!J18*Inputs!C12*J6*1000*Inputs!C29*Inputs!C10/1000 -> 10025.4 | K8: =Deployment_36M!K18*Inputs!C12*K6*1000*Inputs!C29*Inputs!C10/1000 -> 9055.2 | L8: =Deployment_36M!L18*Inputs!C12*L6*1000*Inputs!C29*Inputs!C10/1000 -> 10025.4 | M8: =Deployment_36M!M18*Inputs!C12*M6*1000*Inputs!C29*Inputs!C10/1000 -> 9702 | N8: =Deployment_36M!N18*Inputs!C12*N6*1000*Inputs!C29*Inputs!C10/1000 -> 10025.4 | O8: =Deployment_36M!O18*Inputs!C12*O6*1000*Inputs!C29*Inputs!C10/1000 -> 9702 | P8: =Deployment_36M!P18*Inputs!C12*P6*1000*Inputs!C30*Inputs!C10/1000 -> 9524.13 | Q8: =Deployment_36M!Q18*Inputs!C12*Q6*1000*Inputs!C30*Inputs!C10/1000 -> 9524.13 | R8: =Deployment_36M!R18*Inputs!C12*R6*1000*Inputs!C30*Inputs!C10/1000 -> 9216.9 | S8: =Deployment_36M!S18*Inputs!C12*S6*1000*Inputs!C30*Inputs!C10/1000 -> 9524.13 | T8: =Deployment_36M!T18*Inputs!C12*T6*1000*Inputs!C30*Inputs!C10/1000 -> 9216.9 | U8: =Deployment_36M!U18*Inputs!C12*U6*1000*Inputs!C30*Inputs!C10/1000 -> 9524.13 | V8: =Deployment_36M!V18*Inputs!C12*V6*1000*Inputs!C30*Inputs!C10/1000 -> 9524.13 | W8: =Deployment_36M!W18*Inputs!C12*W6*1000*Inputs!C30*Inputs!C10/1000 -> 8909.67 | X8: =Deployment_36M!X18*Inputs!C12*X6*1000*Inputs!C30*Inputs!C10/1000 -> 9524.13 | Y8: =Deployment_36M!Y18*Inputs!C12*Y6*1000*Inputs!C30*Inputs!C10/1000 -> 9216.9 | Z8: =Deployment_36M!Z18*Inputs!C12*Z6*1000*Inputs!C30*Inputs!C10/1000 -> 9524.13 | AA8: =Deployment_36M!AA18*Inputs!C12*AA6*1000*Inputs!C30*Inputs!C10/1000 -> 9216.9 | AB8: =Deployment_36M!AB18*Inputs!C12*AB6*1000*Inputs!C31*Inputs!C10/1000 -> 9022.86 | AC8: =Deployment_36M!AC18*Inputs!C12*AC6*1000*Inputs!C31*Inputs!C10/1000 -> 9022.86 | AD8: =Deployment_36M!AD18*Inputs!C12*AD6*1000*Inputs!C31*Inputs!C10/1000 -> 8731.8 | AE8: =Deployment_36M!AE18*Inputs!C12*AE6*1000*Inputs!C31*Inputs!C10/1000 -> 9022.86 | AF8: =Deployment_36M!AF18*Inputs!C12*AF6*1000*Inputs!C31*Inputs!C10/1000 -> 8731.8 | AG8: =Deployment_36M!AG18*Inputs!C12*AG6*1000*Inputs!C31*Inputs!C10/1000 -> 9022.86 | AH8: =Deployment_36M!AH18*Inputs!C12*AH6*1000*Inputs!C31*Inputs!C10/1000 -> 9022.86 | AI8: =Deployment_36M!AI18*Inputs!C12*AI6*1000*Inputs!C31*Inputs!C10/1000 -> 8149.68 | AJ8: =Deployment_36M!AJ18*Inputs!C12*AJ6*1000*Inputs!C31*Inputs!C10/1000 -> 9022.86 | AK8: =Deployment_36M!AK18*Inputs!C12*AK6*1000*Inputs!C31*Inputs!C10/1000 -> 8731.8 | AL8: =Deployment_36M!AL18*Inputs!C12*AL6*1000*Inputs!C31*Inputs!C10/1000 -> 9022.86 | AM8: =Deployment_36M!AM18*Inputs!C12*AM6*1000*Inputs!C31*Inputs!C10/1000 -> 8731.8
A9: AMSA Eskom electricity cost | B9: ZAR'000 | C9: Grid leg only | D9: =Deployment_36M!D19*Inputs!C13*D6*1000*Inputs!C32*Inputs!C10/1000 -> 0 | E9: =Deployment_36M!E19*Inputs!C13*E6*1000*Inputs!C32*Inputs!C10/1000 -> 0 | F9: =Deployment_36M!F19*Inputs!C13*F6*1000*Inputs!C32*Inputs!C10/1000 -> 0 | G9: =Deployment_36M!G19*Inputs!C13*G6*1000*Inputs!C32*Inputs!C10/1000 -> 0 | H9: =Deployment_36M!H19*Inputs!C13*H6*1000*Inputs!C32*Inputs!C10/1000 -> 0 | I9: =Deployment_36M!I19*Inputs!C13*I6*1000*Inputs!C32*Inputs!C10/1000 -> 820.26 | J9: =Deployment_36M!J19*Inputs!C13*J6*1000*Inputs!C32*Inputs!C10/1000 -> 1640.52 | K9: =Deployment_36M!K19*Inputs!C13*K6*1000*Inputs!C32*Inputs!C10/1000 -> 1481.76 | L9: =Deployment_36M!L19*Inputs!C13*L6*1000*Inputs!C32*Inputs!C10/1000 -> 1640.52 | M9: =Deployment_36M!M19*Inputs!C13*M6*1000*Inputs!C32*Inputs!C10/1000 -> 1587.6 | N9: =Deployment_36M!N19*Inputs!C13*N6*1000*Inputs!C32*Inputs!C10/1000 -> 1640.52 | O9: =Deployment_36M!O19*Inputs!C13*O6*1000*Inputs!C32*Inputs!C10/1000 -> 1587.6 | P9: =Deployment_36M!P19*Inputs!C13*P6*1000*Inputs!C33*Inputs!C10/1000 -> 1549.38 | Q9: =Deployment_36M!Q19*Inputs!C13*Q6*1000*Inputs!C33*Inputs!C10/1000 -> 1549.38 | R9: =Deployment_36M!R19*Inputs!C13*R6*1000*Inputs!C33*Inputs!C10/1000 -> 1499.4 | S9: =Deployment_36M!S19*Inputs!C13*S6*1000*Inputs!C33*Inputs!C10/1000 -> 1549.38 | T9: =Deployment_36M!T19*Inputs!C13*T6*1000*Inputs!C33*Inputs!C10/1000 -> 1499.4 | U9: =Deployment_36M!U19*Inputs!C13*U6*1000*Inputs!C33*Inputs!C10/1000 -> 1549.38 | V9: =Deployment_36M!V19*Inputs!C13*V6*1000*Inputs!C33*Inputs!C10/1000 -> 1549.38 | W9: =Deployment_36M!W19*Inputs!C13*W6*1000*Inputs!C33*Inputs!C10/1000 -> 1449.42 | X9: =Deployment_36M!X19*Inputs!C13*X6*1000*Inputs!C33*Inputs!C10/1000 -> 1549.38 | Y9: =Deployment_36M!Y19*Inputs!C13*Y6*1000*Inputs!C33*Inputs!C10/1000 -> 1499.4 | Z9: =Deployment_36M!Z19*Inputs!C13*Z6*1000*Inputs!C33*Inputs!C10/1000 -> 1549.38 | AA9: =Deployment_36M!AA19*Inputs!C13*AA6*1000*Inputs!C33*Inputs!C10/1000 -> 1499.4 | AB9: =Deployment_36M!AB19*Inputs!C13*AB6*1000*Inputs!C34*Inputs!C10/1000 -> 1458.24 | AC9: =Deployment_36M!AC19*Inputs!C13*AC6*1000*Inputs!C34*Inputs!C10/1000 -> 1458.24 | AD9: =Deployment_36M!AD19*Inputs!C13*AD6*1000*Inputs!C34*Inputs!C10/1000 -> 1411.2 | AE9: =Deployment_36M!AE19*Inputs!C13*AE6*1000*Inputs!C34*Inputs!C10/1000 -> 1458.24 | AF9: =Deployment_36M!AF19*Inputs!C13*AF6*1000*Inputs!C34*Inputs!C10/1000 -> 1411.2 | AG9: =Deployment_36M!AG19*Inputs!C13*AG6*1000*Inputs!C34*Inputs!C10/1000 -> 1458.24 | AH9: =Deployment_36M!AH19*Inputs!C13*AH6*1000*Inputs!C34*Inputs!C10/1000 -> 1458.24 | AI9: =Deployment_36M!AI19*Inputs!C13*AI6*1000*Inputs!C34*Inputs!C10/1000 -> 1317.12 | AJ9: =Deployment_36M!AJ19*Inputs!C13*AJ6*1000*Inputs!C34*Inputs!C10/1000 -> 1458.24 | AK9: =Deployment_36M!AK19*Inputs!C13*AK6*1000*Inputs!C34*Inputs!C10/1000 -> 1411.2 | AL9: =Deployment_36M!AL19*Inputs!C13*AL6*1000*Inputs!C34*Inputs!C10/1000 -> 1458.24 | AM9: =Deployment_36M!AM19*Inputs!C13*AM6*1000*Inputs!C34*Inputs!C10/1000 -> 1411.2
A10: AMSA solar O&M | B10: ZAR'000 | C10: Solar capex x O&M% | D10: =Deployment_36M!D20*Inputs!C35*Inputs!C36/12 -> 0 | E10: =Deployment_36M!E20*Inputs!C35*Inputs!C36/12 -> 0 | F10: =Deployment_36M!F20*Inputs!C35*Inputs!C36/12 -> 0 | G10: =Deployment_36M!G20*Inputs!C35*Inputs!C36/12 -> 0 | H10: =Deployment_36M!H20*Inputs!C35*Inputs!C36/12 -> 58.333333 | I10: =Deployment_36M!I20*Inputs!C35*Inputs!C36/12 -> 116.66667 | J10: =Deployment_36M!J20*Inputs!C35*Inputs!C36/12 -> 116.66667 | K10: =Deployment_36M!K20*Inputs!C35*Inputs!C36/12 -> 116.66667 | L10: =Deployment_36M!L20*Inputs!C35*Inputs!C36/12 -> 116.66667 | M10: =Deployment_36M!M20*Inputs!C35*Inputs!C36/12 -> 116.66667 | N10: =Deployment_36M!N20*Inputs!C35*Inputs!C36/12 -> 116.66667 | O10: =Deployment_36M!O20*Inputs!C35*Inputs!C36/12 -> 116.66667 | P10: =Deployment_36M!P20*Inputs!C35*Inputs!C36/12 -> 116.66667 | Q10: =Deployment_36M!Q20*Inputs!C35*Inputs!C36/12 -> 116.66667 | R10: =Deployment_36M!R20*Inputs!C35*Inputs!C36/12 -> 116.66667 | S10: =Deployment_36M!S20*Inputs!C35*Inputs!C36/12 -> 116.66667 | T10: =Deployment_36M!T20*Inputs!C35*Inputs!C36/12 -> 116.66667 | U10: =Deployment_36M!U20*Inputs!C35*Inputs!C36/12 -> 116.66667 | V10: =Deployment_36M!V20*Inputs!C35*Inputs!C36/12 -> 116.66667 | W10: =Deployment_36M!W20*Inputs!C35*Inputs!C36/12 -> 116.66667 | X10: =Deployment_36M!X20*Inputs!C35*Inputs!C36/12 -> 116.66667 | Y10: =Deployment_36M!Y20*Inputs!C35*Inputs!C36/12 -> 116.66667 | Z10: =Deployment_36M!Z20*Inputs!C35*Inputs!C36/12 -> 116.66667 | AA10: =Deployment_36M!AA20*Inputs!C35*Inputs!C36/12 -> 116.66667 | AB10: =Deployment_36M!AB20*Inputs!C35*Inputs!C36/12 -> 116.66667 | AC10: =Deployment_36M!AC20*Inputs!C35*Inputs!C36/12 -> 116.66667 | AD10: =Deployment_36M!AD20*Inputs!C35*Inputs!C36/12 -> 116.66667 | AE10: =Deployment_36M!AE20*Inputs!C35*Inputs!C36/12 -> 116.66667 | AF10: =Deployment_36M!AF20*Inputs!C35*Inputs!C36/12 -> 116.66667 | AG10: =Deployment_36M!AG20*Inputs!C35*Inputs!C36/12 -> 116.66667 | AH10: =Deployment_36M!AH20*Inputs!C35*Inputs!C36/12 -> 116.66667 | AI10: =Deployment_36M!AI20*Inputs!C35*Inputs!C36/12 -> 116.66667 | AJ10: =Deployment_36M!AJ20*Inputs!C35*Inputs!C36/12 -> 116.66667 | AK10: =Deployment_36M!AK20*Inputs!C35*Inputs!C36/12 -> 116.66667 | AL10: =Deployment_36M!AL20*Inputs!C35*Inputs!C36/12 -> 116.66667 | AM10: =Deployment_36M!AM20*Inputs!C35*Inputs!C36/12 -> 116.66667
A11: Total energy cost | B11: ZAR'000 | C11: Energy is the main operating cost | D11: =D8+D9+D10 -> 0 | E11: =E8+E9+E10 -> 0 | F11: =F8+F9+F10 -> 1617 | G11: =G8+G9+G10 -> 5012.7 | H11: =H8+H9+H10 -> 8143.3333 | I11: =I8+I9+I10 -> 10962.327 | J11: =J8+J9+J10 -> 11782.587 | K11: =K8+K9+K10 -> 10653.627 | ... AM11: =AM8+AM9+AM10 -> 10259.667
A14: Corporate payroll | B14: ZAR'000 | C14: Fixed corporate team | D14: =Inputs!C62*Inputs!C63*(1+Inputs!C18)^0/12 -> 333.33333 | E14: =Inputs!C62*Inputs!C63*(1+Inputs!C18)^0/12 -> 333.33333 | F14: =Inputs!C62*Inputs!C63*(1+Inputs!C18)^0/12 -> 333.33333 | G14: =Inputs!C62*Inputs!C63*(1+Inputs!C18)^0/12 -> 333.33333 | H14: =Inputs!C62*Inputs!C63*(1+Inputs!C18)^0/12 -> 333.33333 | I14: =Inputs!C62*Inputs!C63*(1+Inputs!C18)^0/12 -> 333.33333 | J14: =Inputs!C62*Inputs!C63*(1+Inputs!C18)^0/12 -> 333.33333 | K14: =Inputs!C62*Inputs!C63*(1+Inputs!C18)^0/12 -> 333.33333 | L14: =Inputs!C62*Inputs!C63*(1+Inputs!C18)^0/12 -> 333.33333 | M14: =Inputs!C62*Inputs!C63*(1+Inputs!C18)^0/12 -> 333.33333 | N14: =Inputs!C62*Inputs!C63*(1+Inputs!C18)^0/12 -> 333.33333 | O14: =Inputs!C62*Inputs!C63*(1+Inputs!C18)^0/12 -> 333.33333 | P14: =Inputs!C62*Inputs!C63*(1+Inputs!C18)^1/12 -> 350 | Q14: =Inputs!C62*Inputs!C63*(1+Inputs!C18)^1/12 -> 350 | R14: =Inputs!C62*Inputs!C63*(1+Inputs!C18)^1/12 -> 350 | S14: =Inputs!C62*Inputs!C63*(1+Inputs!C18)^1/12 -> 350 | T14: =Inputs!C62*Inputs!C63*(1+Inputs!C18)^1/12 -> 350 | U14: =Inputs!C62*Inputs!C63*(1+Inputs!C18)^1/12 -> 350 | V14: =Inputs!C62*Inputs!C63*(1+Inputs!C18)^1/12 -> 350 | W14: =Inputs!C62*Inputs!C63*(1+Inputs!C18)^1/12 -> 350 | X14: =Inputs!C62*Inputs!C63*(1+Inputs!C18)^1/12 -> 350 | Y14: =Inputs!C62*Inputs!C63*(1+Inputs!C18)^1/12 -> 350 | Z14: =Inputs!C62*Inputs!C63*(1+Inputs!C18)^1/12 -> 350 | AA14: =Inputs!C62*Inputs!C63*(1+Inputs!C18)^1/12 -> 350 | AB14: =Inputs!C62*Inputs!C63*(1+Inputs!C18)^2/12 -> 367.5 | AC14: =Inputs!C62*Inputs!C63*(1+Inputs!C18)^2/12 -> 367.5 | AD14: =Inputs!C62*Inputs!C63*(1+Inputs!C18)^2/12 -> 367.5 | AE14: =Inputs!C62*Inputs!C63*(1+Inputs!C18)^2/12 -> 367.5 | AF14: =Inputs!C62*Inputs!C63*(1+Inputs!C18)^2/12 -> 367.5 | AG14: =Inputs!C62*Inputs!C63*(1+Inputs!C18)^2/12 -> 367.5 | AH14: =Inputs!C62*Inputs!C63*(1+Inputs!C18)^2/12 -> 367.5 | AI14: =Inputs!C62*Inputs!C63*(1+Inputs!C18)^2/12 -> 367.5 | AJ14: =Inputs!C62*Inputs!C63*(1+Inputs!C18)^2/12 -> 367.5 | AK14: =Inputs!C62*Inputs!C63*(1+Inputs!C18)^2/12 -> 367.5 | AL14: =Inputs!C62*Inputs!C63*(1+Inputs!C18)^2/12 -> 367.5 | AM14: =Inputs!C62*Inputs!C63*(1+Inputs!C18)^2/12 -> 367.5
A15: Site management payroll | B15: ZAR'000 | C15: 2 FTE per active site | D15: =Deployment_36M!D32*Inputs!C64*Inputs!C65*(1+Inputs!C18)^0/12 -> 0 | E15: =Deployment_36M!E32*Inputs!C64*Inputs!C65*(1+Inputs!C18)^0/12 -> 0 | F15: =Deployment_36M!F32*Inputs!C64*Inputs!C65*(1+Inputs!C18)^0/12 -> 116.66667 | G15: =Deployment_36M!G32*Inputs!C64*Inputs!C65*(1+Inputs!C18)^0/12 -> 116.66667 | H15: =Deployment_36M!H32*Inputs!C64*Inputs!C65*(1+Inputs!C18)^0/12 -> 116.66667 | I15: =Deployment_36M!I32*Inputs!C64*Inputs!C65*(1+Inputs!C18)^0/12 -> 233.33333 | J15: =Deployment_36M!J32*Inputs!C64*Inputs!C65*(1+Inputs!C18)^0/12 -> 233.33333 | K15: =Deployment_36M!K32*Inputs!C64*Inputs!C65*(1+Inputs!C18)^0/12 -> 233.33333 | L15: =Deployment_36M!L32*Inputs!C64*Inputs!C65*(1+Inputs!C18)^0/12 -> 233.33333 | M15: =Deployment_36M!M32*Inputs!C64*Inputs!C65*(1+Inputs!C18)^0/12 -> 233.33333 | N15: =Deployment_36M!N32*Inputs!C64*Inputs!C65*(1+Inputs!C18)^0/12 -> 233.33333 | O15: =Deployment_36M!O32*Inputs!C64*Inputs!C65*(1+Inputs!C18)^0/12 -> 233.33333 | P15: =Deployment_36M!P32*Inputs!C64*Inputs!C65*(1+Inputs!C18)^1/12 -> 245 | Q15: =Deployment_36M!Q32*Inputs!C64*Inputs!C65*(1+Inputs!C18)^1/12 -> 245 | R15: =Deployment_36M!R32*Inputs!C64*Inputs!C65*(1+Inputs!C18)^1/12 -> 245 | S15: =Deployment_36M!S32*Inputs!C64*Inputs!C65*(1+Inputs!C18)^1/12 -> 245 | T15: =Deployment_36M!T32*Inputs!C64*Inputs!C65*(1+Inputs!C18)^1/12 -> 245 | U15: =Deployment_36M!U32*Inputs!C64*Inputs!C65*(1+Inputs!C18)^1/12 -> 245 | V15: =Deployment_36M!V32*Inputs!C64*Inputs!C65*(1+Inputs!C18)^1/12 -> 245 | W15: =Deployment_36M!W32*Inputs!C64*Inputs!C65*(1+Inputs!C18)^1/12 -> 245 | X15: =Deployment_36M!X32*Inputs!C64*Inputs!C65*(1+Inputs!C18)^1/12 -> 245 | Y15: =Deployment_36M!Y32*Inputs!C64*Inputs!C65*(1+Inputs!C18)^1/12 -> 245 | Z15: =Deployment_36M!Z32*Inputs!C64*Inputs!C65*(1+Inputs!C18)^1/12 -> 245 | AA15: =Deployment_36M!AA32*Inputs!C64*Inputs!C65*(1+Inputs!C18)^1/12 -> 245 | AB15: =Deployment_36M!AB32*Inputs!C64*Inputs!C65*(1+Inputs!C18)^2/12 -> 257.25 | AC15: =Deployment_36M!AC32*Inputs!C64*Inputs!C65*(1+Inputs!C18)^2/12 -> 257.25 | AD15: =Deployment_36M!AD32*Inputs!C64*Inputs!C65*(1+Inputs!C18)^2/12 -> 257.25 | AE15: =Deployment_36M!AE32*Inputs!C64*Inputs!C65*(1+Inputs!C18)^2/12 -> 257.25 | AF15: =Deployment_36M!AF32*Inputs!C64*Inputs!C65*(1+Inputs!C18)^2/12 -> 257.25 | AG15: =Deployment_36M!AG32*Inputs!C64*Inputs!C65*(1+Inputs!C18)^2/12 -> 257.25 | AH15: =Deployment_36M!AH32*Inputs!C64*Inputs!C65*(1+Inputs!C18)^2/12 -> 257.25 | AI15: =Deployment_36M!AI32*Inputs!C64*Inputs!C65*(1+Inputs!C18)^2/12 -> 257.25 | AJ15: =Deployment_36M!AJ32*Inputs!C64*Inputs!C65*(1+Inputs!C18)^2/12 -> 257.25 | AK15: =Deployment_36M!AK32*Inputs!C64*Inputs!C65*(1+Inputs!C18)^2/12 -> 257.25 | AL15: =Deployment_36M!AL32*Inputs!C64*Inputs!C65*(1+Inputs!C18)^2/12 -> 257.25 | AM15: =Deployment_36M!AM32*Inputs!C64*Inputs!C65*(1+Inputs!C18)^2/12 -> 257.25
A16: Technician payroll | B16: ZAR'000 | C16: Variable with average MW | D16: =Deployment_36M!D21*Inputs!C66*Inputs!C67*(1+Inputs!C18)^0/12 -> 0 | E16: =Deployment_36M!E21*Inputs!C66*Inputs!C67*(1+Inputs!C18)^0/12 -> 0 | F16: =Deployment_36M!F21*Inputs!C66*Inputs!C67*(1+Inputs!C18)^0/12 -> 25.520833 | G16: =Deployment_36M!G21*Inputs!C66*Inputs!C67*(1+Inputs!C18)^0/12 -> 76.5625 | H16: =Deployment_36M!H21*Inputs!C66*Inputs!C67*(1+Inputs!C18)^0/12 -> 127.60417 | I16: =Deployment_36M!I21*Inputs!C66*Inputs!C67*(1+Inputs!C18)^0/12 -> 178.64583 | J16: =Deployment_36M!J21*Inputs!C66*Inputs!C67*(1+Inputs!C18)^0/12 -> 204.16667 | K16: =Deployment_36M!K21*Inputs!C66*Inputs!C67*(1+Inputs!C18)^0/12 -> 204.16667 | L16: =Deployment_36M!L21*Inputs!C66*Inputs!C67*(1+Inputs!C18)^0/12 -> 204.16667 | M16: =Deployment_36M!M21*Inputs!C66*Inputs!C67*(1+Inputs!C18)^0/12 -> 204.16667 | N16: =Deployment_36M!N21*Inputs!C66*Inputs!C67*(1+Inputs!C18)^0/12 -> 204.16667 | O16: =Deployment_36M!O21*Inputs!C66*Inputs!C67*(1+Inputs!C18)^0/12 -> 204.16667 | P16: =Deployment_36M!P21*Inputs!C66*Inputs!C67*(1+Inputs!C18)^1/12 -> 214.375 | Q16: =Deployment_36M!Q21*Inputs!C66*Inputs!C67*(1+Inputs!C18)^1/12 -> 214.375 | R16: =Deployment_36M!R21*Inputs!C66*Inputs!C67*(1+Inputs!C18)^1/12 -> 214.375 | S16: =Deployment_36M!S21*Inputs!C66*Inputs!C67*(1+Inputs!C18)^1/12 -> 214.375 | T16: =Deployment_36M!T21*Inputs!C66*Inputs!C67*(1+Inputs!C18)^1/12 -> 214.375 | U16: =Deployment_36M!U21*Inputs!C66*Inputs!C67*(1+Inputs!C18)^1/12 -> 214.375 | V16: =Deployment_36M!V21*Inputs!C66*Inputs!C67*(1+Inputs!C18)^1/12 -> 214.375 | W16: =Deployment_36M!W21*Inputs!C66*Inputs!C67*(1+Inputs!C18)^1/12 -> 214.375 | X16: =Deployment_36M!X21*Inputs!C66*Inputs!C67*(1+Inputs!C18)^1/12 -> 214.375 | Y16: =Deployment_36M!Y21*Inputs!C66*Inputs!C67*(1+Inputs!C18)^1/12 -> 214.375 | Z16: =Deployment_36M!Z21*Inputs!C66*Inputs!C67*(1+Inputs!C18)^1/12 -> 214.375 | AA16: =Deployment_36M!AA21*Inputs!C66*Inputs!C67*(1+Inputs!C18)^1/12 -> 214.375 | AB16: =Deployment_36M!AB21*Inputs!C66*Inputs!C67*(1+Inputs!C18)^2/12 -> 225.09375 | AC16: =Deployment_36M!AC21*Inputs!C66*Inputs!C67*(1+Inputs!C18)^2/12 -> 225.09375 | AD16: =Deployment_36M!AD21*Inputs!C66*Inputs!C67*(1+Inputs!C18)^2/12 -> 225.09375 | AE16: =Deployment_36M!AE21*Inputs!C66*Inputs!C67*(1+Inputs!C18)^2/12 -> 225.09375 | AF16: =Deployment_36M!AF21*Inputs!C66*Inputs!C67*(1+Inputs!C18)^2/12 -> 225.09375 | AG16: =Deployment_36M!AG21*Inputs!C66*Inputs!C67*(1+Inputs!C18)^2/12 -> 225.09375 | AH16: =Deployment_36M!AH21*Inputs!C66*Inputs!C67*(1+Inputs!C18)^2/12 -> 225.09375 | AI16: =Deployment_36M!AI21*Inputs!C66*Inputs!C67*(1+Inputs!C18)^2/12 -> 225.09375 | AJ16: =Deployment_36M!AJ21*Inputs!C66*Inputs!C67*(1+Inputs!C18)^2/12 -> 225.09375 | AK16: =Deployment_36M!AK21*Inputs!C66*Inputs!C67*(1+Inputs!C18)^2/12 -> 225.09375 | AL16: =Deployment_36M!AL21*Inputs!C66*Inputs!C67*(1+Inputs!C18)^2/12 -> 225.09375 | AM16: =Deployment_36M!AM21*Inputs!C66*Inputs!C67*(1+Inputs!C18)^2/12 -> 225.09375
A17: Electrician payroll | B17: ZAR'000 | C17: Variable with average MW | D17: =Deployment_36M!D21*Inputs!C68*Inputs!C69*(1+Inputs!C18)^0/12 -> 0 | E17: =Deployment_36M!E21*Inputs!C68*Inputs!C69*(1+Inputs!C18)^0/12 -> 0 | F17: =Deployment_36M!F21*Inputs!C68*Inputs!C69*(1+Inputs!C18)^0/12 -> 7.5 | G17: =Deployment_36M!G21*Inputs!C68*Inputs!C69*(1+Inputs!C18)^0/12 -> 22.5 | H17: =Deployment_36M!H21*Inputs!C68*Inputs!C69*(1+Inputs!C18)^0/12 -> 37.5 | I17: =Deployment_36M!I21*Inputs!C68*Inputs!C69*(1+Inputs!C18)^0/12 -> 52.5 | J17: =Deployment_36M!J21*Inputs!C68*Inputs!C69*(1+Inputs!C18)^0/12 -> 60 | K17: =Deployment_36M!K21*Inputs!C68*Inputs!C69*(1+Inputs!C18)^0/12 -> 60 | L17: =Deployment_36M!L21*Inputs!C68*Inputs!C69*(1+Inputs!C18)^0/12 -> 60 | M17: =Deployment_36M!M21*Inputs!C68*Inputs!C69*(1+Inputs!C18)^0/12 -> 60 | N17: =Deployment_36M!N21*Inputs!C68*Inputs!C69*(1+Inputs!C18)^0/12 -> 60 | O17: =Deployment_36M!O21*Inputs!C68*Inputs!C69*(1+Inputs!C18)^0/12 -> 60 | P17: =Deployment_36M!P21*Inputs!C68*Inputs!C69*(1+Inputs!C18)^1/12 -> 63 | Q17: =Deployment_36M!Q21*Inputs!C68*Inputs!C69*(1+Inputs!C18)^1/12 -> 63 | R17: =Deployment_36M!R21*Inputs!C68*Inputs!C69*(1+Inputs!C18)^1/12 -> 63 | S17: =Deployment_36M!S21*Inputs!C68*Inputs!C69*(1+Inputs!C18)^1/12 -> 63 | T17: =Deployment_36M!T21*Inputs!C68*Inputs!C69*(1+Inputs!C18)^1/12 -> 63 | U17: =Deployment_36M!U21*Inputs!C68*Inputs!C69*(1+Inputs!C18)^1/12 -> 63 | V17: =Deployment_36M!V21*Inputs!C68*Inputs!C69*(1+Inputs!C18)^1/12 -> 63 | W17: =Deployment_36M!W21*Inputs!C68*Inputs!C69*(1+Inputs!C18)^1/12 -> 63 | X17: =Deployment_36M!X21*Inputs!C68*Inputs!C69*(1+Inputs!C18)^1/12 -> 63 | Y17: =Deployment_36M!Y21*Inputs!C68*Inputs!C69*(1+Inputs!C18)^1/12 -> 63 | Z17: =Deployment_36M!Z21*Inputs!C68*Inputs!C69*(1+Inputs!C18)^1/12 -> 63 | AA17: =Deployment_36M!AA21*Inputs!C68*Inputs!C69*(1+Inputs!C18)^1/12 -> 63 | AB17: =Deployment_36M!AB21*Inputs!C68*Inputs!C69*(1+Inputs!C18)^2/12 -> 66.15 | AC17: =Deployment_36M!AC21*Inputs!C68*Inputs!C69*(1+Inputs!C18)^2/12 -> 66.15 | AD17: =Deployment_36M!AD21*Inputs!C68*Inputs!C69*(1+Inputs!C18)^2/12 -> 66.15 | AE17: =Deployment_36M!AE21*Inputs!C68*Inputs!C69*(1+Inputs!C18)^2/12 -> 66.15 | AF17: =Deployment_36M!AF21*Inputs!C68*Inputs!C69*(1+Inputs!C18)^2/12 -> 66.15 | AG17: =Deployment_36M!AG21*Inputs!C68*Inputs!C69*(1+Inputs!C18)^2/12 -> 66.15 | AH17: =Deployment_36M!AH21*Inputs!C68*Inputs!C69*(1+Inputs!C18)^2/12 -> 66.15 | AI17: =Deployment_36M!AI21*Inputs!C68*Inputs!C69*(1+Inputs!C18)^2/12 -> 66.15 | AJ17: =Deployment_36M!AJ21*Inputs!C68*Inputs!C69*(1+Inputs!C18)^2/12 -> 66.15 | AK17: =Deployment_36M!AK21*Inputs!C68*Inputs!C69*(1+Inputs!C18)^2/12 -> 66.15 | AL17: =Deployment_36M!AL21*Inputs!C68*Inputs!C69*(1+Inputs!C18)^2/12 -> 66.15 | AM17: =Deployment_36M!AM21*Inputs!C68*Inputs!C69*(1+Inputs!C18)^2/12 -> 66.15
A18: Gross payroll | B18: ZAR'000 | C18: Sum of payroll lines | D18: =D14+D15+D16+D17 -> 333.33333 | E18: =E14+E15+E16+E17 -> 333.33333 | F18: =F14+F15+F16+F17 -> 483.02083 | G18: =G14+G15+G16+G17 -> 549.0625 | H18: =H14+H15+H16+H17 -> 615.10417 | I18: =I14+I15+I16+I17 -> 797.8125 | J18: =J14+J15+J16+J17 -> 830.83333 | K18: =K14+K15+K16+K17 -> 830.83333 | ... AM18: =AM14+AM15+AM16+AM17 -> 915.99375
A19: Benefits | B19: ZAR'000 | C19: Benefits load on gross payroll | D19: =D18*Inputs!C70 -> 66.666667 | E19: =E18*Inputs!C70 -> 66.666667 | F19: =F18*Inputs!C70 -> 96.604167 | G19: =G18*Inputs!C70 -> 109.8125 | H19: =H18*Inputs!C70 -> 123.02083 | I19: =I18*Inputs!C70 -> 159.5625 | J19: =J18*Inputs!C70 -> 166.16667 | K19: =K18*Inputs!C70 -> 166.16667 | L19: =L18*Inputs!C70 -> 166.16667 | M19: =M18*Inputs!C70 -> 166.16667 | N19: =N18*Inputs!C70 -> 166.16667 | O19: =O18*Inputs!C70 -> 166.16667 | P19: =P18*Inputs!C70 -> 174.475 | Q19: =Q18*Inputs!C70 -> 174.475 | R19: =R18*Inputs!C70 -> 174.475 | S19: =S18*Inputs!C70 -> 174.475 | T19: =T18*Inputs!C70 -> 174.475 | U19: =U18*Inputs!C70 -> 174.475 | V19: =V18*Inputs!C70 -> 174.475 | W19: =W18*Inputs!C70 -> 174.475 | X19: =X18*Inputs!C70 -> 174.475 | Y19: =Y18*Inputs!C70 -> 174.475 | Z19: =Z18*Inputs!C70 -> 174.475 | AA19: =AA18*Inputs!C70 -> 174.475 | AB19: =AB18*Inputs!C70 -> 183.19875 | AC19: =AC18*Inputs!C70 -> 183.19875 | AD19: =AD18*Inputs!C70 -> 183.19875 | AE19: =AE18*Inputs!C70 -> 183.19875 | AF19: =AF18*Inputs!C70 -> 183.19875 | AG19: =AG18*Inputs!C70 -> 183.19875 | AH19: =AH18*Inputs!C70 -> 183.19875 | AI19: =AI18*Inputs!C70 -> 183.19875 | AJ19: =AJ18*Inputs!C70 -> 183.19875 | AK19: =AK18*Inputs!C70 -> 183.19875 | AL19: =AL18*Inputs!C70 -> 183.19875 | AM19: =AM18*Inputs!C70 -> 183.19875
A20: Salaries & benefits | B20: ZAR'000 | C20: Gross payroll + benefits | D20: =D18+D19 -> 400 | E20: =E18+E19 -> 400 | F20: =F18+F19 -> 579.625 | G20: =G18+G19 -> 658.875 | H20: =H18+H19 -> 738.125 | I20: =I18+I19 -> 957.375 | J20: =J18+J19 -> 997 | K20: =K18+K19 -> 997 | ... AM20: =AM18+AM19 -> 1099.1925
A21: Travel / accommodation | B21: ZAR'000 | C21: Recurring % plus site-start mobilization | D21: =D18*Inputs!C71+Deployment_36M!D37*Inputs!C72 -> 20 | E21: =E18*Inputs!C71+Deployment_36M!E37*Inputs!C72 -> 20 | F21: =F18*Inputs!C71+Deployment_36M!F37*Inputs!C72 -> 278.98125 | G21: =G18*Inputs!C71+Deployment_36M!G37*Inputs!C72 -> 32.94375 | H21: =H18*Inputs!C71+Deployment_36M!H37*Inputs!C72 -> 36.90625 | I21: =I18*Inputs!C71+Deployment_36M!I37*Inputs!C72 -> 297.86875 | J21: =J18*Inputs!C71+Deployment_36M!J37*Inputs!C72 -> 49.85 | K21: =K18*Inputs!C71+Deployment_36M!K37*Inputs!C72 -> 49.85 | L21: =L18*Inputs!C71+Deployment_36M!L37*Inputs!C72 -> 49.85 | M21: =M18*Inputs!C71+Deployment_36M!M37*Inputs!C72 -> 49.85 | N21: =N18*Inputs!C71+Deployment_36M!N37*Inputs!C72 -> 49.85 | O21: =O18*Inputs!C71+Deployment_36M!O37*Inputs!C72 -> 49.85 | P21: =P18*Inputs!C71+Deployment_36M!P37*Inputs!C72 -> 52.3425 | Q21: =Q18*Inputs!C71+Deployment_36M!Q37*Inputs!C72 -> 52.3425 | R21: =R18*Inputs!C71+Deployment_36M!R37*Inputs!C72 -> 52.3425 | S21: =S18*Inputs!C71+Deployment_36M!S37*Inputs!C72 -> 52.3425 | T21: =T18*Inputs!C71+Deployment_36M!T37*Inputs!C72 -> 52.3425 | U21: =U18*Inputs!C71+Deployment_36M!U37*Inputs!C72 -> 52.3425 | V21: =V18*Inputs!C71+Deployment_36M!V37*Inputs!C72 -> 52.3425 | W21: =W18*Inputs!C71+Deployment_36M!W37*Inputs!C72 -> 52.3425 | X21: =X18*Inputs!C71+Deployment_36M!X37*Inputs!C72 -> 52.3425 | Y21: =Y18*Inputs!C71+Deployment_36M!Y37*Inputs!C72 -> 52.3425 | Z21: =Z18*Inputs!C71+Deployment_36M!Z37*Inputs!C72 -> 52.3425 | AA21: =AA18*Inputs!C71+Deployment_36M!AA37*Inputs!C72 -> 52.3425 | AB21: =AB18*Inputs!C71+Deployment_36M!AB37*Inputs!C72 -> 54.959625 | AC21: =AC18*Inputs!C71+Deployment_36M!AC37*Inputs!C72 -> 54.959625 | AD21: =AD18*Inputs!C71+Deployment_36M!AD37*Inputs!C72 -> 54.959625 | AE21: =AE18*Inputs!C71+Deployment_36M!AE37*Inputs!C72 -> 54.959625 | AF21: =AF18*Inputs!C71+Deployment_36M!AF37*Inputs!C72 -> 54.959625 | AG21: =AG18*Inputs!C71+Deployment_36M!AG37*Inputs!C72 -> 54.959625 | AH21: =AH18*Inputs!C71+Deployment_36M!AH37*Inputs!C72 -> 54.959625 | AI21: =AI18*Inputs!C71+Deployment_36M!AI37*Inputs!C72 -> 54.959625 | AJ21: =AJ18*Inputs!C71+Deployment_36M!AJ37*Inputs!C72 -> 54.959625 | AK21: =AK18*Inputs!C71+Deployment_36M!AK37*Inputs!C72 -> 54.959625 | AL21: =AL18*Inputs!C71+Deployment_36M!AL37*Inputs!C72 -> 54.959625 | AM21: =AM18*Inputs!C71+Deployment_36M!AM37*Inputs!C72 -> 54.959625
A22: Software / storage / monitoring | B22: ZAR'000 | C22: SaaS + site monitoring + cloud | D22: =((Inputs!C62+Deployment_36M!D56)*Inputs!C73+Deployment_36M!D32*Inputs!C74+Inputs!C75)*(1+Inputs!C17)^0 -> 18 | E22: =((Inputs!C62+Deployment_36M!E56)*Inputs!C73+Deployment_36M!E32*Inputs!C74+Inputs!C75)*(1+Inputs!C17)^0 -> 18 | F22: =((Inputs!C62+Deployment_36M!F56)*Inputs!C73+Deployment_36M!F32*Inputs!C74+Inputs!C75)*(1+Inputs!C17)^0 -> 72.525 | G22: =((Inputs!C62+Deployment_36M!G56)*Inputs!C73+Deployment_36M!G32*Inputs!C74+Inputs!C75)*(1+Inputs!C17)^0 -> 80.05 | H22: =((Inputs!C62+Deployment_36M!H56)*Inputs!C73+Deployment_36M!H32*Inputs!C74+Inputs!C75)*(1+Inputs!C17)^0 -> 87.575 | I22: =((Inputs!C62+Deployment_36M!I56)*Inputs!C73+Deployment_36M!I32*Inputs!C74+Inputs!C75)*(1+Inputs!C17)^0 -> 142.1 | J22: =((Inputs!C62+Deployment_36M!J56)*Inputs!C73+Deployment_36M!J32*Inputs!C74+Inputs!C75)*(1+Inputs!C17)^0 -> 142.1 | K22: =((Inputs!C62+Deployment_36M!K56)*Inputs!C73+Deployment_36M!K32*Inputs!C74+Inputs!C75)*(1+Inputs!C17)^0 -> 142.1 | L22: =((Inputs!C62+Deployment_36M!L56)*Inputs!C73+Deployment_36M!L32*Inputs!C74+Inputs!C75)*(1+Inputs!C17)^0 -> 142.1 | M22: =((Inputs!C62+Deployment_36M!M56)*Inputs!C73+Deployment_36M!M32*Inputs!C74+Inputs!C75)*(1+Inputs!C17)^0 -> 142.1 | N22: =((Inputs!C62+Deployment_36M!N56)*Inputs!C73+Deployment_36M!N32*Inputs!C74+Inputs!C75)*(1+Inputs!C17)^0 -> 142.1 | O22: =((Inputs!C62+Deployment_36M!O56)*Inputs!C73+Deployment_36M!O32*Inputs!C74+Inputs!C75)*(1+Inputs!C17)^0 -> 142.1 | P22: =((Inputs!C62+Deployment_36M!P56)*Inputs!C73+Deployment_36M!P32*Inputs!C74+Inputs!C75)*(1+Inputs!C17)^1 -> 149.205 | Q22: =((Inputs!C62+Deployment_36M!Q56)*Inputs!C73+Deployment_36M!Q32*Inputs!C74+Inputs!C75)*(1+Inputs!C17)^1 -> 149.205 | R22: =((Inputs!C62+Deployment_36M!R56)*Inputs!C73+Deployment_36M!R32*Inputs!C74+Inputs!C75)*(1+Inputs!C17)^1 -> 149.205 | S22: =((Inputs!C62+Deployment_36M!S56)*Inputs!C73+Deployment_36M!S32*Inputs!C74+Inputs!C75)*(1+Inputs!C17)^1 -> 149.205 | T22: =((Inputs!C62+Deployment_36M!T56)*Inputs!C73+Deployment_36M!T32*Inputs!C74+Inputs!C75)*(1+Inputs!C17)^1 -> 149.205 | U22: =((Inputs!C62+Deployment_36M!U56)*Inputs!C73+Deployment_36M!U32*Inputs!C74+Inputs!C75)*(1+Inputs!C17)^1 -> 149.205 | V22: =((Inputs!C62+Deployment_36M!V56)*Inputs!C73+Deployment_36M!V32*Inputs!C74+Inputs!C75)*(1+Inputs!C17)^1 -> 149.205 | W22: =((Inputs!C62+Deployment_36M!W56)*Inputs!C73+Deployment_36M!W32*Inputs!C74+Inputs!C75)*(1+Inputs!C17)^1 -> 149.205 | X22: =((Inputs!C62+Deployment_36M!X56)*Inputs!C73+Deployment_36M!X32*Inputs!C74+Inputs!C75)*(1+Inputs!C17)^1 -> 149.205 | Y22: =((Inputs!C62+Deployment_36M!Y56)*Inputs!C73+Deployment_36M!Y32*Inputs!C74+Inputs!C75)*(1+Inputs!C17)^1 -> 149.205 | Z22: =((Inputs!C62+Deployment_36M!Z56)*Inputs!C73+Deployment_36M!Z32*Inputs!C74+Inputs!C75)*(1+Inputs!C17)^1 -> 149.205 | AA22: =((Inputs!C62+Deployment_36M!AA56)*Inputs!C73+Deployment_36M!AA32*Inputs!C74+Inputs!C75)*(1+Inputs!C17)^1 -> 149.205 | AB22: =((Inputs!C62+Deployment_36M!AB56)*Inputs!C73+Deployment_36M!AB32*Inputs!C74+Inputs!C75)*(1+Inputs!C17)^2 -> 156.66525 | AC22: =((Inputs!C62+Deployment_36M!AC56)*Inputs!C73+Deployment_36M!AC32*Inputs!C74+Inputs!C75)*(1+Inputs!C17)^2 -> 156.66525 | AD22: =((Inputs!C62+Deployment_36M!AD56)*Inputs!C73+Deployment_36M!AD32*Inputs!C74+Inputs!C75)*(1+Inputs!C17)^2 -> 156.66525 | AE22: =((Inputs!C62+Deployment_36M!AE56)*Inputs!C73+Deployment_36M!AE32*Inputs!C74+Inputs!C75)*(1+Inputs!C17)^2 -> 156.66525 | AF22: =((Inputs!C62+Deployment_36M!AF56)*Inputs!C73+Deployment_36M!AF32*Inputs!C74+Inputs!C75)*(1+Inputs!C17)^2 -> 156.66525 | AG22: =((Inputs!C62+Deployment_36M!AG56)*Inputs!C73+Deployment_36M!AG32*Inputs!C74+Inputs!C75)*(1+Inputs!C17)^2 -> 156.66525 | AH22: =((Inputs!C62+Deployment_36M!AH56)*Inputs!C73+Deployment_36M!AH32*Inputs!C74+Inputs!C75)*(1+Inputs!C17)^2 -> 156.66525 | AI22: =((Inputs!C62+Deployment_36M!AI56)*Inputs!C73+Deployment_36M!AI32*Inputs!C74+Inputs!C75)*(1+Inputs!C17)^2 -> 156.66525 | AJ22: =((Inputs!C62+Deployment_36M!AJ56)*Inputs!C73+Deployment_36M!AJ32*Inputs!C74+Inputs!C75)*(1+Inputs!C17)^2 -> 156.66525 | AK22: =((Inputs!C62+Deployment_36M!AK56)*Inputs!C73+Deployment_36M!AK32*Inputs!C74+Inputs!C75)*(1+Inputs!C17)^2 -> 156.66525 | AL22: =((Inputs!C62+Deployment_36M!AL56)*Inputs!C73+Deployment_36M!AL32*Inputs!C74+Inputs!C75)*(1+Inputs!C17)^2 -> 156.66525 | AM22: =((Inputs!C62+Deployment_36M!AM56)*Inputs!C73+Deployment_36M!AM32*Inputs!C74+Inputs!C75)*(1+Inputs!C17)^2 -> 156.66525
A23: Legal fees | B23: ZAR'000 | C23: Recurring retainer | D23: =Inputs!C76*(1+Inputs!C17)^0 -> 75 | E23: =Inputs!C76*(1+Inputs!C17)^0 -> 75 | F23: =Inputs!C76*(1+Inputs!C17)^0 -> 75 | G23: =Inputs!C76*(1+Inputs!C17)^0 -> 75 | H23: =Inputs!C76*(1+Inputs!C17)^0 -> 75 | I23: =Inputs!C76*(1+Inputs!C17)^0 -> 75 | J23: =Inputs!C76*(1+Inputs!C17)^0 -> 75 | K23: =Inputs!C76*(1+Inputs!C17)^0 -> 75 | L23: =Inputs!C76*(1+Inputs!C17)^0 -> 75 | M23: =Inputs!C76*(1+Inputs!C17)^0 -> 75 | N23: =Inputs!C76*(1+Inputs!C17)^0 -> 75 | O23: =Inputs!C76*(1+Inputs!C17)^0 -> 75 | P23: =Inputs!C76*(1+Inputs!C17)^1 -> 78.75 | Q23: =Inputs!C76*(1+Inputs!C17)^1 -> 78.75 | R23: =Inputs!C76*(1+Inputs!C17)^1 -> 78.75 | S23: =Inputs!C76*(1+Inputs!C17)^1 -> 78.75 | T23: =Inputs!C76*(1+Inputs!C17)^1 -> 78.75 | U23: =Inputs!C76*(1+Inputs!C17)^1 -> 78.75 | V23: =Inputs!C76*(1+Inputs!C17)^1 -> 78.75 | W23: =Inputs!C76*(1+Inputs!C17)^1 -> 78.75 | X23: =Inputs!C76*(1+Inputs!C17)^1 -> 78.75 | Y23: =Inputs!C76*(1+Inputs!C17)^1 -> 78.75 | Z23: =Inputs!C76*(1+Inputs!C17)^1 -> 78.75 | AA23: =Inputs!C76*(1+Inputs!C17)^1 -> 78.75 | AB23: =Inputs!C76*(1+Inputs!C17)^2 -> 82.6875 | AC23: =Inputs!C76*(1+Inputs!C17)^2 -> 82.6875 | AD23: =Inputs!C76*(1+Inputs!C17)^2 -> 82.6875 | AE23: =Inputs!C76*(1+Inputs!C17)^2 -> 82.6875 | AF23: =Inputs!C76*(1+Inputs!C17)^2 -> 82.6875 | AG23: =Inputs!C76*(1+Inputs!C17)^2 -> 82.6875 | AH23: =Inputs!C76*(1+Inputs!C17)^2 -> 82.6875 | AI23: =Inputs!C76*(1+Inputs!C17)^2 -> 82.6875 | AJ23: =Inputs!C76*(1+Inputs!C17)^2 -> 82.6875 | AK23: =Inputs!C76*(1+Inputs!C17)^2 -> 82.6875 | AL23: =Inputs!C76*(1+Inputs!C17)^2 -> 82.6875 | AM23: =Inputs!C76*(1+Inputs!C17)^2 -> 82.6875
A24: Office rent | B24: ZAR'000 | C24: Recurring office rent | D24: =Inputs!C77*(1+Inputs!C17)^0 -> 10 | E24: =Inputs!C77*(1+Inputs!C17)^0 -> 10 | F24: =Inputs!C77*(1+Inputs!C17)^0 -> 10 | G24: =Inputs!C77*(1+Inputs!C17)^0 -> 10 | H24: =Inputs!C77*(1+Inputs!C17)^0 -> 10 | I24: =Inputs!C77*(1+Inputs!C17)^0 -> 10 | J24: =Inputs!C77*(1+Inputs!C17)^0 -> 10 | K24: =Inputs!C77*(1+Inputs!C17)^0 -> 10 | L24: =Inputs!C77*(1+Inputs!C17)^0 -> 10 | M24: =Inputs!C77*(1+Inputs!C17)^0 -> 10 | N24: =Inputs!C77*(1+Inputs!C17)^0 -> 10 | O24: =Inputs!C77*(1+Inputs!C17)^0 -> 10 | P24: =Inputs!C77*(1+Inputs!C17)^1 -> 10.5 | Q24: =Inputs!C77*(1+Inputs!C17)^1 -> 10.5 | R24: =Inputs!C77*(1+Inputs!C17)^1 -> 10.5 | S24: =Inputs!C77*(1+Inputs!C17)^1 -> 10.5 | T24: =Inputs!C77*(1+Inputs!C17)^1 -> 10.5 | U24: =Inputs!C77*(1+Inputs!C17)^1 -> 10.5 | V24: =Inputs!C77*(1+Inputs!C17)^1 -> 10.5 | W24: =Inputs!C77*(1+Inputs!C17)^1 -> 10.5 | X24: =Inputs!C77*(1+Inputs!C17)^1 -> 10.5 | Y24: =Inputs!C77*(1+Inputs!C17)^1 -> 10.5 | Z24: =Inputs!C77*(1+Inputs!C17)^1 -> 10.5 | AA24: =Inputs!C77*(1+Inputs!C17)^1 -> 10.5 | AB24: =Inputs!C77*(1+Inputs!C17)^2 -> 11.025 | AC24: =Inputs!C77*(1+Inputs!C17)^2 -> 11.025 | AD24: =Inputs!C77*(1+Inputs!C17)^2 -> 11.025 | AE24: =Inputs!C77*(1+Inputs!C17)^2 -> 11.025 | AF24: =Inputs!C77*(1+Inputs!C17)^2 -> 11.025 | AG24: =Inputs!C77*(1+Inputs!C17)^2 -> 11.025 | AH24: =Inputs!C77*(1+Inputs!C17)^2 -> 11.025 | AI24: =Inputs!C77*(1+Inputs!C17)^2 -> 11.025 | AJ24: =Inputs!C77*(1+Inputs!C17)^2 -> 11.025 | AK24: =Inputs!C77*(1+Inputs!C17)^2 -> 11.025 | AL24: =Inputs!C77*(1+Inputs!C17)^2 -> 11.025 | AM24: =Inputs!C77*(1+Inputs!C17)^2 -> 11.025
A25: Tools / consumables recurring | B25: ZAR'000 | C25: Filters and consumables | D25: =Deployment_36M!D21*Inputs!C78*(1+Inputs!C17)^0 -> 0 | E25: =Deployment_36M!E21*Inputs!C78*(1+Inputs!C17)^0 -> 0 | F25: =Deployment_36M!F21*Inputs!C78*(1+Inputs!C17)^0 -> 20 | G25: =Deployment_36M!G21*Inputs!C78*(1+Inputs!C17)^0 -> 60 | H25: =Deployment_36M!H21*Inputs!C78*(1+Inputs!C17)^0 -> 100 | I25: =Deployment_36M!I21*Inputs!C78*(1+Inputs!C17)^0 -> 140 | J25: =Deployment_36M!J21*Inputs!C78*(1+Inputs!C17)^0 -> 160 | K25: =Deployment_36M!K21*Inputs!C78*(1+Inputs!C17)^0 -> 160 | L25: =Deployment_36M!L21*Inputs!C78*(1+Inputs!C17)^0 -> 160 | M25: =Deployment_36M!M21*Inputs!C78*(1+Inputs!C17)^0 -> 160 | N25: =Deployment_36M!N21*Inputs!C78*(1+Inputs!C17)^0 -> 160 | O25: =Deployment_36M!O21*Inputs!C78*(1+Inputs!C17)^0 -> 160 | P25: =Deployment_36M!P21*Inputs!C78*(1+Inputs!C17)^1 -> 168 | Q25: =Deployment_36M!Q21*Inputs!C78*(1+Inputs!C17)^1 -> 168 | R25: =Deployment_36M!R21*Inputs!C78*(1+Inputs!C17)^1 -> 168 | S25: =Deployment_36M!S21*Inputs!C78*(1+Inputs!C17)^1 -> 168 | T25: =Deployment_36M!T21*Inputs!C78*(1+Inputs!C17)^1 -> 168 | U25: =Deployment_36M!U21*Inputs!C78*(1+Inputs!C17)^1 -> 168 | V25: =Deployment_36M!V21*Inputs!C78*(1+Inputs!C17)^1 -> 168 | W25: =Deployment_36M!W21*Inputs!C78*(1+Inputs!C17)^1 -> 168 | X25: =Deployment_36M!X21*Inputs!C78*(1+Inputs!C17)^1 -> 168 | Y25: =Deployment_36M!Y21*Inputs!C78*(1+Inputs!C17)^1 -> 168 | Z25: =Deployment_36M!Z21*Inputs!C78*(1+Inputs!C17)^1 -> 168 | AA25: =Deployment_36M!AA21*Inputs!C78*(1+Inputs!C17)^1 -> 168 | AB25: =Deployment_36M!AB21*Inputs!C78*(1+Inputs!C17)^2 -> 176.4 | AC25: =Deployment_36M!AC21*Inputs!C78*(1+Inputs!C17)^2 -> 176.4 | AD25: =Deployment_36M!AD21*Inputs!C78*(1+Inputs!C17)^2 -> 176.4 | AE25: =Deployment_36M!AE21*Inputs!C78*(1+Inputs!C17)^2 -> 176.4 | AF25: =Deployment_36M!AF21*Inputs!C78*(1+Inputs!C17)^2 -> 176.4 | AG25: =Deployment_36M!AG21*Inputs!C78*(1+Inputs!C17)^2 -> 176.4 | AH25: =Deployment_36M!AH21*Inputs!C78*(1+Inputs!C17)^2 -> 176.4 | AI25: =Deployment_36M!AI21*Inputs!C78*(1+Inputs!C17)^2 -> 176.4 | AJ25: =Deployment_36M!AJ21*Inputs!C78*(1+Inputs!C17)^2 -> 176.4 | AK25: =Deployment_36M!AK21*Inputs!C78*(1+Inputs!C17)^2 -> 176.4 | AL25: =Deployment_36M!AL21*Inputs!C78*(1+Inputs!C17)^2 -> 176.4 | AM25: =Deployment_36M!AM21*Inputs!C78*(1+Inputs!C17)^2 -> 176.4
A26: Security & operating insurance | B26: ZAR'000 | C26: Per active site | D26: =Deployment_36M!D32*Inputs!C79*(1+Inputs!C17)^0 -> 0 | E26: =Deployment_36M!E32*Inputs!C79*(1+Inputs!C17)^0 -> 0 | F26: =Deployment_36M!F32*Inputs!C79*(1+Inputs!C17)^0 -> 40 | G26: =Deployment_36M!G32*Inputs!C79*(1+Inputs!C17)^0 -> 40 | H26: =Deployment_36M!H32*Inputs!C79*(1+Inputs!C17)^0 -> 40 | I26: =Deployment_36M!I32*Inputs!C79*(1+Inputs!C17)^0 -> 80 | J26: =Deployment_36M!J32*Inputs!C79*(1+Inputs!C17)^0 -> 80 | K26: =Deployment_36M!K32*Inputs!C79*(1+Inputs!C17)^0 -> 80 | L26: =Deployment_36M!L32*Inputs!C79*(1+Inputs!C17)^0 -> 80 | M26: =Deployment_36M!M32*Inputs!C79*(1+Inputs!C17)^0 -> 80 | N26: =Deployment_36M!N32*Inputs!C79*(1+Inputs!C17)^0 -> 80 | O26: =Deployment_36M!O32*Inputs!C79*(1+Inputs!C17)^0 -> 80 | P26: =Deployment_36M!P32*Inputs!C79*(1+Inputs!C17)^1 -> 84 | Q26: =Deployment_36M!Q32*Inputs!C79*(1+Inputs!C17)^1 -> 84 | R26: =Deployment_36M!R32*Inputs!C79*(1+Inputs!C17)^1 -> 84 | S26: =Deployment_36M!S32*Inputs!C79*(1+Inputs!C17)^1 -> 84 | T26: =Deployment_36M!T32*Inputs!C79*(1+Inputs!C17)^1 -> 84 | U26: =Deployment_36M!U32*Inputs!C79*(1+Inputs!C17)^1 -> 84 | V26: =Deployment_36M!V32*Inputs!C79*(1+Inputs!C17)^1 -> 84 | W26: =Deployment_36M!W32*Inputs!C79*(1+Inputs!C17)^1 -> 84 | X26: =Deployment_36M!X32*Inputs!C79*(1+Inputs!C17)^1 -> 84 | Y26: =Deployment_36M!Y32*Inputs!C79*(1+Inputs!C17)^1 -> 84 | Z26: =Deployment_36M!Z32*Inputs!C79*(1+Inputs!C17)^1 -> 84 | AA26: =Deployment_36M!AA32*Inputs!C79*(1+Inputs!C17)^1 -> 84 | AB26: =Deployment_36M!AB32*Inputs!C79*(1+Inputs!C17)^2 -> 88.2 | AC26: =Deployment_36M!AC32*Inputs!C79*(1+Inputs!C17)^2 -> 88.2 | AD26: =Deployment_36M!AD32*Inputs!C79*(1+Inputs!C17)^2 -> 88.2 | AE26: =Deployment_36M!AE32*Inputs!C79*(1+Inputs!C17)^2 -> 88.2 | AF26: =Deployment_36M!AF32*Inputs!C79*(1+Inputs!C17)^2 -> 88.2 | AG26: =Deployment_36M!AG32*Inputs!C79*(1+Inputs!C17)^2 -> 88.2 | AH26: =Deployment_36M!AH32*Inputs!C79*(1+Inputs!C17)^2 -> 88.2 | AI26: =Deployment_36M!AI32*Inputs!C79*(1+Inputs!C17)^2 -> 88.2 | AJ26: =Deployment_36M!AJ32*Inputs!C79*(1+Inputs!C17)^2 -> 88.2 | AK26: =Deployment_36M!AK32*Inputs!C79*(1+Inputs!C17)^2 -> 88.2 | AL26: =Deployment_36M!AL32*Inputs!C79*(1+Inputs!C17)^2 -> 88.2 | AM26: =Deployment_36M!AM32*Inputs!C79*(1+Inputs!C17)^2 -> 88.2
A27: Other utilities / water | B27: ZAR'000 | C27: Variable with average MW | D27: =Deployment_36M!D21*Inputs!C80*(1+Inputs!C17)^0 -> 0 | E27: =Deployment_36M!E21*Inputs!C80*(1+Inputs!C17)^0 -> 0 | F27: =Deployment_36M!F21*Inputs!C80*(1+Inputs!C17)^0 -> 25 | G27: =Deployment_36M!G21*Inputs!C80*(1+Inputs!C17)^0 -> 75 | H27: =Deployment_36M!H21*Inputs!C80*(1+Inputs!C17)^0 -> 125 | I27: =Deployment_36M!I21*Inputs!C80*(1+Inputs!C17)^0 -> 175 | J27: =Deployment_36M!J21*Inputs!C80*(1+Inputs!C17)^0 -> 200 | K27: =Deployment_36M!K21*Inputs!C80*(1+Inputs!C17)^0 -> 200 | L27: =Deployment_36M!L21*Inputs!C80*(1+Inputs!C17)^0 -> 200 | M27: =Deployment_36M!M21*Inputs!C80*(1+Inputs!C17)^0 -> 200 | N27: =Deployment_36M!N21*Inputs!C80*(1+Inputs!C17)^0 -> 200 | O27: =Deployment_36M!O21*Inputs!C80*(1+Inputs!C17)^0 -> 200 | P27: =Deployment_36M!P21*Inputs!C80*(1+Inputs!C17)^1 -> 210 | Q27: =Deployment_36M!Q21*Inputs!C80*(1+Inputs!C17)^1 -> 210 | R27: =Deployment_36M!R21*Inputs!C80*(1+Inputs!C17)^1 -> 210 | S27: =Deployment_36M!S21*Inputs!C80*(1+Inputs!C17)^1 -> 210 | T27: =Deployment_36M!T21*Inputs!C80*(1+Inputs!C17)^1 -> 210 | U27: =Deployment_36M!U21*Inputs!C80*(1+Inputs!C17)^1 -> 210 | V27: =Deployment_36M!V21*Inputs!C80*(1+Inputs!C17)^1 -> 210 | W27: =Deployment_36M!W21*Inputs!C80*(1+Inputs!C17)^1 -> 210 | X27: =Deployment_36M!X21*Inputs!C80*(1+Inputs!C17)^1 -> 210 | Y27: =Deployment_36M!Y21*Inputs!C80*(1+Inputs!C17)^1 -> 210 | Z27: =Deployment_36M!Z21*Inputs!C80*(1+Inputs!C17)^1 -> 210 | AA27: =Deployment_36M!AA21*Inputs!C80*(1+Inputs!C17)^1 -> 210 | AB27: =Deployment_36M!AB21*Inputs!C80*(1+Inputs!C17)^2 -> 220.5 | AC27: =Deployment_36M!AC21*Inputs!C80*(1+Inputs!C17)^2 -> 220.5 | AD27: =Deployment_36M!AD21*Inputs!C80*(1+Inputs!C17)^2 -> 220.5 | AE27: =Deployment_36M!AE21*Inputs!C80*(1+Inputs!C17)^2 -> 220.5 | AF27: =Deployment_36M!AF21*Inputs!C80*(1+Inputs!C17)^2 -> 220.5 | AG27: =Deployment_36M!AG21*Inputs!C80*(1+Inputs!C17)^2 -> 220.5 | AH27: =Deployment_36M!AH21*Inputs!C80*(1+Inputs!C17)^2 -> 220.5 | AI27: =Deployment_36M!AI21*Inputs!C80*(1+Inputs!C17)^2 -> 220.5 | AJ27: =Deployment_36M!AJ21*Inputs!C80*(1+Inputs!C17)^2 -> 220.5 | AK27: =Deployment_36M!AK21*Inputs!C80*(1+Inputs!C17)^2 -> 220.5 | AL27: =Deployment_36M!AL21*Inputs!C80*(1+Inputs!C17)^2 -> 220.5 | AM27: =Deployment_36M!AM21*Inputs!C80*(1+Inputs!C17)^2 -> 220.5
A28: Total cash opex | B28: ZAR'000 | C28: Operating cash cost | D28: =D11+D20+D21+D22+D23+D24+D25+D26+D27 -> 523 | E28: =E11+E20+E21+E22+E23+E24+E25+E26+E27 -> 523 | F28: =F11+F20+F21+F22+F23+F24+F25+F26+F27 -> 2718.1312 | G28: =G11+G20+G21+G22+G23+G24+G25+G26+G27 -> 6044.5688 | H28: =H11+H20+H21+H22+H23+H24+H25+H26+H27 -> 9355.9396 | I28: =I11+I20+I21+I22+I23+I24+I25+I26+I27 -> 12839.67 | J28: =J11+J20+J21+J22+J23+J24+J25+J26+J27 -> 13496.537 | K28: =K11+K20+K21+K22+K23+K24+K25+K26+K27 -> 12367.577 | ... AM28: =AM11+AM20+AM21+AM22+AM23+AM24+AM25+AM26+AM27 -> 12149.297
A29: EBITDA - base case | B29: ZAR'000 | C29: Base case = BTC only | D29: =Revenue_36M!D20-D28 -> -523 | E29: =Revenue_36M!E20-E28 -> -523 | F29: =Revenue_36M!F20-F28 -> 1063.7503 | G29: =Revenue_36M!G20-G28 -> 5722.7734 | H29: =Revenue_36M!H20-H28 -> 9694.0813 | I29: =Revenue_36M!I20-I28 -> 14642.018 | J29: =Revenue_36M!J20-J28 -> 17873.136 | K29: =Revenue_36M!K20-K28 -> 16071.473 | ... AM29: =Revenue_36M!AM20-AM28 -> 21651.246
A30: EBITDA - with optionality | B30: ZAR'000 | C30: BTC + toggled optionality | D30: =Revenue_36M!D21-D28 -> -523 | E30: =Revenue_36M!E21-E28 -> -523 | F30: =Revenue_36M!F21-F28 -> 1063.7503 | G30: =Revenue_36M!G21-G28 -> 5722.7734 | H30: =Revenue_36M!H21-H28 -> 9694.0813 | I30: =Revenue_36M!I21-I28 -> 14642.018 | J30: =Revenue_36M!J21-J28 -> 17873.136 | K30: =Revenue_36M!K21-K28 -> 16071.473 | ... AM30: =Revenue_36M!AM21-AM28 -> 21651.246

Sheet Capex_36M
A1: Capex_36M | Simplified staged payment model for Phase 1 buildout
A2: Designed to stay compact. Hardware, container and EPC cash timing uses staged payments rather than the full legal vendor schedule in the detailed master model.
A4: Metric | B4: Unit | C4: Notes
A5: Date | B5: date | C5: Linked from deployment | D5: =Deployment_36M!D5 -> 46204 | E5: =Deployment_36M!E5 -> 46235 | F5: =Deployment_36M!F5 -> 46266 | G5: =Deployment_36M!G5 -> 46296 | H5: =Deployment_36M!H5 -> 46327 | I5: =Deployment_36M!I5 -> 46357 | J5: =Deployment_36M!J5 -> 46388 | K5: =Deployment_36M!K5 -> 46419 | ... AM5: =Deployment_36M!AM5 -> 47270
A6: Days in month | B6: days | C6: Linked from deployment | D6: =Deployment_36M!D6 -> 31 | E6: =Deployment_36M!E6 -> 31 | F6: =Deployment_36M!F6 -> 30 | G6: =Deployment_36M!G6 -> 31 | H6: =Deployment_36M!H6 -> 30 | I6: =Deployment_36M!I6 -> 31 | J6: =Deployment_36M!J6 -> 31 | K6: =Deployment_36M!K6 -> 28 | ... AM6: =Deployment_36M!AM6 -> 30
A8: New MW commissioned | B8: MW | C8: Linked from deployment | D8: =Deployment_36M!D27 -> 0 | E8: =Deployment_36M!E27 -> 0 | F8: =Deployment_36M!F27 -> 5 | G8: =Deployment_36M!G27 -> 5 | H8: =Deployment_36M!H27 -> 5 | I8: =Deployment_36M!I27 -> 5 | J8: =Deployment_36M!J27 -> 0 | K8: =Deployment_36M!K27 -> 0 | ... AM8: =Deployment_36M!AM27 -> 0
A9: New containers commissioned | B9: containers | C9: Linked from deployment | D9: =Deployment_36M!D52 -> 0 | E9: =Deployment_36M!E52 -> 0 | F9: =Deployment_36M!F52 -> 3 | G9: =Deployment_36M!G52 -> 2 | H9: =Deployment_36M!H52 -> 2 | I9: =Deployment_36M!I52 -> 3 | J9: =Deployment_36M!J52 -> 0 | K9: =Deployment_36M!K52 -> 0 | ... AM9: =Deployment_36M!AM52 -> 0
A10: New solar MW | B10: MW | C10: Linked from deployment | D10: =Deployment_36M!D26 -> 0 | E10: =Deployment_36M!E26 -> 0 | F10: =Deployment_36M!F26 -> 0 | G10: =Deployment_36M!G26 -> 0 | H10: =Deployment_36M!H26 -> 10 | I10: =Deployment_36M!I26 -> 0 | J10: =Deployment_36M!J26 -> 0 | K10: =Deployment_36M!K26 -> 0 | ... AM10: =Deployment_36M!AM26 -> 0
A11: New site FTE onboarded | B11: FTE | C11: Linked from deployment | D11: =Deployment_36M!D55 -> 0 | E11: =Deployment_36M!E55 -> 0 | F11: =Deployment_36M!F55 -> 4.15 | G11: =Deployment_36M!G55 -> 2.15 | H11: =Deployment_36M!H55 -> 2.15 | I11: =Deployment_36M!I55 -> 4.15 | J11: =Deployment_36M!J55 -> 0 | K11: =Deployment_36M!K55 -> 0 | ... AM11: =Deployment_36M!AM55 -> 0
A14: ASIC hardware capex basis | B14: ZAR'000 | C14: Per new commissioned MW | D14: =D8*(1-Inputs!C11)*1000000/Inputs!C40*Inputs!C41*Inputs!C20/1000 -> 0 | E14: =E8*(1-Inputs!C11)*1000000/Inputs!C40*Inputs!C41*Inputs!C20/1000 -> 0 | F14: =F8*(1-Inputs!C11)*1000000/Inputs!C40*Inputs!C41*Inputs!C20/1000 -> 54587 | G14: =G8*(1-Inputs!C11)*1000000/Inputs!C40*Inputs!C41*Inputs!C20/1000 -> 54587 | H14: =H8*(1-Inputs!C11)*1000000/Inputs!C40*Inputs!C41*Inputs!C20/1000 -> 54587 | I14: =I8*(1-Inputs!C11)*1000000/Inputs!C40*Inputs!C41*Inputs!C20/1000 -> 54587 | J14: =J8*(1-Inputs!C11)*1000000/Inputs!C40*Inputs!C41*Inputs!C20/1000 -> 0 | K14: =K8*(1-Inputs!C11)*1000000/Inputs!C40*Inputs!C41*Inputs!C20/1000 -> 0 | L14: =L8*(1-Inputs!C11)*1000000/Inputs!C40*Inputs!C41*Inputs!C20/1000 -> 0 | M14: =M8*(1-Inputs!C11)*1000000/Inputs!C40*Inputs!C41*Inputs!C20/1000 -> 0 | N14: =N8*(1-Inputs!C11)*1000000/Inputs!C40*Inputs!C41*Inputs!C20/1000 -> 0 | O14: =O8*(1-Inputs!C11)*1000000/Inputs!C40*Inputs!C41*Inputs!C20/1000 -> 0 | P14: =P8*(1-Inputs!C11)*1000000/Inputs!C40*Inputs!C41*Inputs!C20/1000 -> 0 | Q14: =Q8*(1-Inputs!C11)*1000000/Inputs!C40*Inputs!C41*Inputs!C20/1000 -> 0 | R14: =R8*(1-Inputs!C11)*1000000/Inputs!C40*Inputs!C41*Inputs!C20/1000 -> 0 | S14: =S8*(1-Inputs!C11)*1000000/Inputs!C40*Inputs!C41*Inputs!C20/1000 -> 0 | T14: =T8*(1-Inputs!C11)*1000000/Inputs!C40*Inputs!C41*Inputs!C20/1000 -> 0 | U14: =U8*(1-Inputs!C11)*1000000/Inputs!C40*Inputs!C41*Inputs!C20/1000 -> 0 | V14: =V8*(1-Inputs!C11)*1000000/Inputs!C40*Inputs!C41*Inputs!C20/1000 -> 0 | W14: =W8*(1-Inputs!C11)*1000000/Inputs!C40*Inputs!C41*Inputs!C20/1000 -> 0 | X14: =X8*(1-Inputs!C11)*1000000/Inputs!C40*Inputs!C41*Inputs!C20/1000 -> 0 | Y14: =Y8*(1-Inputs!C11)*1000000/Inputs!C40*Inputs!C41*Inputs!C20/1000 -> 0 | Z14: =Z8*(1-Inputs!C11)*1000000/Inputs!C40*Inputs!C41*Inputs!C20/1000 -> 0 | AA14: =AA8*(1-Inputs!C11)*1000000/Inputs!C40*Inputs!C41*Inputs!C20/1000 -> 0 | AB14: =AB8*(1-Inputs!C11)*1000000/Inputs!C40*Inputs!C41*Inputs!C20/1000 -> 0 | AC14: =AC8*(1-Inputs!C11)*1000000/Inputs!C40*Inputs!C41*Inputs!C20/1000 -> 0 | AD14: =AD8*(1-Inputs!C11)*1000000/Inputs!C40*Inputs!C41*Inputs!C20/1000 -> 0 | AE14: =AE8*(1-Inputs!C11)*1000000/Inputs!C40*Inputs!C41*Inputs!C20/1000 -> 0 | AF14: =AF8*(1-Inputs!C11)*1000000/Inputs!C40*Inputs!C41*Inputs!C20/1000 -> 0 | AG14: =AG8*(1-Inputs!C11)*1000000/Inputs!C40*Inputs!C41*Inputs!C20/1000 -> 0 | AH14: =AH8*(1-Inputs!C11)*1000000/Inputs!C40*Inputs!C41*Inputs!C20/1000 -> 0 | AI14: =AI8*(1-Inputs!C11)*1000000/Inputs!C40*Inputs!C41*Inputs!C20/1000 -> 0 | AJ14: =AJ8*(1-Inputs!C11)*1000000/Inputs!C40*Inputs!C41*Inputs!C20/1000 -> 0 | AK14: =AK8*(1-Inputs!C11)*1000000/Inputs!C40*Inputs!C41*Inputs!C20/1000 -> 0 | AL14: =AL8*(1-Inputs!C11)*1000000/Inputs!C40*Inputs!C41*Inputs!C20/1000 -> 0 | AM14: =AM8*(1-Inputs!C11)*1000000/Inputs!C40*Inputs!C41*Inputs!C20/1000 -> 0
A15: Hydro container capex basis | B15: ZAR'000 | C15: Per new commissioned container | D15: =D9*Inputs!C44*Inputs!C20/1000 -> 0 | E15: =E9*Inputs!C44*Inputs!C20/1000 -> 0 | F15: =F9*Inputs!C44*Inputs!C20/1000 -> 17850 | G15: =G9*Inputs!C44*Inputs!C20/1000 -> 11900 | H15: =H9*Inputs!C44*Inputs!C20/1000 -> 11900 | I15: =I9*Inputs!C44*Inputs!C20/1000 -> 17850 | J15: =J9*Inputs!C44*Inputs!C20/1000 -> 0 | K15: =K9*Inputs!C44*Inputs!C20/1000 -> 0 | L15: =L9*Inputs!C44*Inputs!C20/1000 -> 0 | M15: =M9*Inputs!C44*Inputs!C20/1000 -> 0 | N15: =N9*Inputs!C44*Inputs!C20/1000 -> 0 | O15: =O9*Inputs!C44*Inputs!C20/1000 -> 0 | P15: =P9*Inputs!C44*Inputs!C20/1000 -> 0 | Q15: =Q9*Inputs!C44*Inputs!C20/1000 -> 0 | R15: =R9*Inputs!C44*Inputs!C20/1000 -> 0 | S15: =S9*Inputs!C44*Inputs!C20/1000 -> 0 | T15: =T9*Inputs!C44*Inputs!C20/1000 -> 0 | U15: =U9*Inputs!C44*Inputs!C20/1000 -> 0 | V15: =V9*Inputs!C44*Inputs!C20/1000 -> 0 | W15: =W9*Inputs!C44*Inputs!C20/1000 -> 0 | X15: =X9*Inputs!C44*Inputs!C20/1000 -> 0 | Y15: =Y9*Inputs!C44*Inputs!C20/1000 -> 0 | Z15: =Z9*Inputs!C44*Inputs!C20/1000 -> 0 | AA15: =AA9*Inputs!C44*Inputs!C20/1000 -> 0 | AB15: =AB9*Inputs!C44*Inputs!C20/1000 -> 0 | AC15: =AC9*Inputs!C44*Inputs!C20/1000 -> 0 | AD15: =AD9*Inputs!C44*Inputs!C20/1000 -> 0 | AE15: =AE9*Inputs!C44*Inputs!C20/1000 -> 0 | AF15: =AF9*Inputs!C44*Inputs!C20/1000 -> 0 | AG15: =AG9*Inputs!C44*Inputs!C20/1000 -> 0 | AH15: =AH9*Inputs!C44*Inputs!C20/1000 -> 0 | AI15: =AI9*Inputs!C44*Inputs!C20/1000 -> 0 | AJ15: =AJ9*Inputs!C44*Inputs!C20/1000 -> 0 | AK15: =AK9*Inputs!C44*Inputs!C20/1000 -> 0 | AL15: =AL9*Inputs!C44*Inputs!C20/1000 -> 0 | AM15: =AM9*Inputs!C44*Inputs!C20/1000 -> 0
A16: Electrical EPC basis | B16: ZAR'000 | C16: Site-fixed + variable/MW | D16: =D8*Inputs!C48+Deployment_36M!D37*Inputs!C47 -> 0 | E16: =E8*Inputs!C48+Deployment_36M!E37*Inputs!C47 -> 0 | F16: =F8*Inputs!C48+Deployment_36M!F37*Inputs!C47 -> 44407.577 | G16: =G8*Inputs!C48+Deployment_36M!G37*Inputs!C47 -> 19031.819 | H16: =H8*Inputs!C48+Deployment_36M!H37*Inputs!C47 -> 19031.819 | I16: =I8*Inputs!C48+Deployment_36M!I37*Inputs!C47 -> 44407.577 | J16: =J8*Inputs!C48+Deployment_36M!J37*Inputs!C47 -> 0 | K16: =K8*Inputs!C48+Deployment_36M!K37*Inputs!C47 -> 0 | L16: =L8*Inputs!C48+Deployment_36M!L37*Inputs!C47 -> 0 | M16: =M8*Inputs!C48+Deployment_36M!M37*Inputs!C47 -> 0 | N16: =N8*Inputs!C48+Deployment_36M!N37*Inputs!C47 -> 0 | O16: =O8*Inputs!C48+Deployment_36M!O37*Inputs!C47 -> 0 | P16: =P8*Inputs!C48+Deployment_36M!P37*Inputs!C47 -> 0 | Q16: =Q8*Inputs!C48+Deployment_36M!Q37*Inputs!C47 -> 0 | R16: =R8*Inputs!C48+Deployment_36M!R37*Inputs!C47 -> 0 | S16: =S8*Inputs!C48+Deployment_36M!S37*Inputs!C47 -> 0 | T16: =T8*Inputs!C48+Deployment_36M!T37*Inputs!C47 -> 0 | U16: =U8*Inputs!C48+Deployment_36M!U37*Inputs!C47 -> 0 | V16: =V8*Inputs!C48+Deployment_36M!V37*Inputs!C47 -> 0 | W16: =W8*Inputs!C48+Deployment_36M!W37*Inputs!C47 -> 0 | X16: =X8*Inputs!C48+Deployment_36M!X37*Inputs!C47 -> 0 | Y16: =Y8*Inputs!C48+Deployment_36M!Y37*Inputs!C47 -> 0 | Z16: =Z8*Inputs!C48+Deployment_36M!Z37*Inputs!C47 -> 0 | AA16: =AA8*Inputs!C48+Deployment_36M!AA37*Inputs!C47 -> 0 | AB16: =AB8*Inputs!C48+Deployment_36M!AB37*Inputs!C47 -> 0 | AC16: =AC8*Inputs!C48+Deployment_36M!AC37*Inputs!C47 -> 0 | AD16: =AD8*Inputs!C48+Deployment_36M!AD37*Inputs!C47 -> 0 | AE16: =AE8*Inputs!C48+Deployment_36M!AE37*Inputs!C47 -> 0 | AF16: =AF8*Inputs!C48+Deployment_36M!AF37*Inputs!C47 -> 0 | AG16: =AG8*Inputs!C48+Deployment_36M!AG37*Inputs!C47 -> 0 | AH16: =AH8*Inputs!C48+Deployment_36M!AH37*Inputs!C47 -> 0 | AI16: =AI8*Inputs!C48+Deployment_36M!AI37*Inputs!C47 -> 0 | AJ16: =AJ8*Inputs!C48+Deployment_36M!AJ37*Inputs!C47 -> 0 | AK16: =AK8*Inputs!C48+Deployment_36M!AK37*Inputs!C47 -> 0 | AL16: =AL8*Inputs!C48+Deployment_36M!AL37*Inputs!C47 -> 0 | AM16: =AM8*Inputs!C48+Deployment_36M!AM37*Inputs!C47 -> 0
A17: Solar PV capex basis | B17: ZAR'000 | C17: Per new solar MW | D17: =D10*Inputs!C35 -> 0 | E17: =E10*Inputs!C35 -> 0 | F17: =F10*Inputs!C35 -> 0 | G17: =G10*Inputs!C35 -> 0 | H17: =H10*Inputs!C35 -> 70000 | I17: =I10*Inputs!C35 -> 0 | J17: =J10*Inputs!C35 -> 0 | K17: =K10*Inputs!C35 -> 0 | L17: =L10*Inputs!C35 -> 0 | M17: =M10*Inputs!C35 -> 0 | N17: =N10*Inputs!C35 -> 0 | O17: =O10*Inputs!C35 -> 0 | P17: =P10*Inputs!C35 -> 0 | Q17: =Q10*Inputs!C35 -> 0 | R17: =R10*Inputs!C35 -> 0 | S17: =S10*Inputs!C35 -> 0 | T17: =T10*Inputs!C35 -> 0 | U17: =U10*Inputs!C35 -> 0 | V17: =V10*Inputs!C35 -> 0 | W17: =W10*Inputs!C35 -> 0 | X17: =X10*Inputs!C35 -> 0 | Y17: =Y10*Inputs!C35 -> 0 | Z17: =Z10*Inputs!C35 -> 0 | AA17: =AA10*Inputs!C35 -> 0 | AB17: =AB10*Inputs!C35 -> 0 | AC17: =AC10*Inputs!C35 -> 0 | AD17: =AD10*Inputs!C35 -> 0 | AE17: =AE10*Inputs!C35 -> 0 | AF17: =AF10*Inputs!C35 -> 0 | AG17: =AG10*Inputs!C35 -> 0 | AH17: =AH10*Inputs!C35 -> 0 | AI17: =AI10*Inputs!C35 -> 0 | AJ17: =AJ10*Inputs!C35 -> 0 | AK17: =AK10*Inputs!C35 -> 0 | AL17: =AL10*Inputs!C35 -> 0 | AM17: =AM10*Inputs!C35 -> 0
A18: Initial spare parts basis | B18: ZAR'000 | C18: % of hardware + containers | D18: =(D14+D15)*Inputs!C49 -> 0 | E18: =(E14+E15)*Inputs!C49 -> 0 | F18: =(F14+F15)*Inputs!C49 -> 1448.74 | G18: =(G14+G15)*Inputs!C49 -> 1329.74 | H18: =(H14+H15)*Inputs!C49 -> 1329.74 | I18: =(I14+I15)*Inputs!C49 -> 1448.74 | J18: =(J14+J15)*Inputs!C49 -> 0 | K18: =(K14+K15)*Inputs!C49 -> 0 | L18: =(L14+L15)*Inputs!C49 -> 0 | M18: =(M14+M15)*Inputs!C49 -> 0 | N18: =(N14+N15)*Inputs!C49 -> 0 | O18: =(O14+O15)*Inputs!C49 -> 0 | P18: =(P14+P15)*Inputs!C49 -> 0 | Q18: =(Q14+Q15)*Inputs!C49 -> 0 | R18: =(R14+R15)*Inputs!C49 -> 0 | S18: =(S14+S15)*Inputs!C49 -> 0 | T18: =(T14+T15)*Inputs!C49 -> 0 | U18: =(U14+U15)*Inputs!C49 -> 0 | V18: =(V14+V15)*Inputs!C49 -> 0 | W18: =(W14+W15)*Inputs!C49 -> 0 | X18: =(X14+X15)*Inputs!C49 -> 0 | Y18: =(Y14+Y15)*Inputs!C49 -> 0 | Z18: =(Z14+Z15)*Inputs!C49 -> 0 | AA18: =(AA14+AA15)*Inputs!C49 -> 0 | AB18: =(AB14+AB15)*Inputs!C49 -> 0 | AC18: =(AC14+AC15)*Inputs!C49 -> 0 | AD18: =(AD14+AD15)*Inputs!C49 -> 0 | AE18: =(AE14+AE15)*Inputs!C49 -> 0 | AF18: =(AF14+AF15)*Inputs!C49 -> 0 | AG18: =(AG14+AG15)*Inputs!C49 -> 0 | AH18: =(AH14+AH15)*Inputs!C49 -> 0 | AI18: =(AI14+AI15)*Inputs!C49 -> 0 | AJ18: =(AJ14+AJ15)*Inputs!C49 -> 0 | AK18: =(AK14+AK15)*Inputs!C49 -> 0 | AL18: =(AL14+AL15)*Inputs!C49 -> 0 | AM18: =(AM14+AM15)*Inputs!C49 -> 0
A19: Tools / equipment initial basis | B19: ZAR'000 | C19: Per site start | D19: =Deployment_36M!D37*Inputs!C50 -> 0 | E19: =Deployment_36M!E37*Inputs!C50 -> 0 | F19: =Deployment_36M!F37*Inputs!C50 -> 750 | G19: =Deployment_36M!G37*Inputs!C50 -> 0 | H19: =Deployment_36M!H37*Inputs!C50 -> 0 | I19: =Deployment_36M!I37*Inputs!C50 -> 750 | J19: =Deployment_36M!J37*Inputs!C50 -> 0 | K19: =Deployment_36M!K37*Inputs!C50 -> 0 | L19: =Deployment_36M!L37*Inputs!C50 -> 0 | M19: =Deployment_36M!M37*Inputs!C50 -> 0 | N19: =Deployment_36M!N37*Inputs!C50 -> 0 | O19: =Deployment_36M!O37*Inputs!C50 -> 0 | P19: =Deployment_36M!P37*Inputs!C50 -> 0 | Q19: =Deployment_36M!Q37*Inputs!C50 -> 0 | R19: =Deployment_36M!R37*Inputs!C50 -> 0 | S19: =Deployment_36M!S37*Inputs!C50 -> 0 | T19: =Deployment_36M!T37*Inputs!C50 -> 0 | U19: =Deployment_36M!U37*Inputs!C50 -> 0 | V19: =Deployment_36M!V37*Inputs!C50 -> 0 | W19: =Deployment_36M!W37*Inputs!C50 -> 0 | X19: =Deployment_36M!X37*Inputs!C50 -> 0 | Y19: =Deployment_36M!Y37*Inputs!C50 -> 0 | Z19: =Deployment_36M!Z37*Inputs!C50 -> 0 | AA19: =Deployment_36M!AA37*Inputs!C50 -> 0 | AB19: =Deployment_36M!AB37*Inputs!C50 -> 0 | AC19: =Deployment_36M!AC37*Inputs!C50 -> 0 | AD19: =Deployment_36M!AD37*Inputs!C50 -> 0 | AE19: =Deployment_36M!AE37*Inputs!C50 -> 0 | AF19: =Deployment_36M!AF37*Inputs!C50 -> 0 | AG19: =Deployment_36M!AG37*Inputs!C50 -> 0 | AH19: =Deployment_36M!AH37*Inputs!C50 -> 0 | AI19: =Deployment_36M!AI37*Inputs!C50 -> 0 | AJ19: =Deployment_36M!AJ37*Inputs!C50 -> 0 | AK19: =Deployment_36M!AK37*Inputs!C50 -> 0 | AL19: =Deployment_36M!AL37*Inputs!C50 -> 0 | AM19: =Deployment_36M!AM37*Inputs!C50 -> 0
A20: Staff hardware basis | B20: ZAR'000 | C20: Per new site FTE | D20: =D11*Inputs!C61 -> 0 | E20: =E11*Inputs!C61 -> 0 | F20: =F11*Inputs!C61 -> 145.25 | G20: =G11*Inputs!C61 -> 75.25 | H20: =H11*Inputs!C61 -> 75.25 | I20: =I11*Inputs!C61 -> 145.25 | J20: =J11*Inputs!C61 -> 0 | K20: =K11*Inputs!C61 -> 0 | L20: =L11*Inputs!C61 -> 0 | M20: =M11*Inputs!C61 -> 0 | N20: =N11*Inputs!C61 -> 0 | O20: =O11*Inputs!C61 -> 0 | P20: =P11*Inputs!C61 -> 0 | Q20: =Q11*Inputs!C61 -> 0 | R20: =R11*Inputs!C61 -> 0 | S20: =S11*Inputs!C61 -> 0 | T20: =T11*Inputs!C61 -> 0 | U20: =U11*Inputs!C61 -> 0 | V20: =V11*Inputs!C61 -> 0 | W20: =W11*Inputs!C61 -> 0 | X20: =X11*Inputs!C61 -> 0 | Y20: =Y11*Inputs!C61 -> 0 | Z20: =Z11*Inputs!C61 -> 0 | AA20: =AA11*Inputs!C61 -> 0 | AB20: =AB11*Inputs!C61 -> 0 | AC20: =AC11*Inputs!C61 -> 0 | AD20: =AD11*Inputs!C61 -> 0 | AE20: =AE11*Inputs!C61 -> 0 | AF20: =AF11*Inputs!C61 -> 0 | AG20: =AG11*Inputs!C61 -> 0 | AH20: =AH11*Inputs!C61 -> 0 | AI20: =AI11*Inputs!C61 -> 0 | AJ20: =AJ11*Inputs!C61 -> 0 | AK20: =AK11*Inputs!C61 -> 0 | AL20: =AL11*Inputs!C61 -> 0 | AM20: =AM11*Inputs!C61 -> 0
A21: Freight basis | B21: ZAR'000 | C21: Per new container | D21: =D9*Inputs!C54*Inputs!C20/1000 -> 0 | E21: =E9*Inputs!C54*Inputs!C20/1000 -> 0 | F21: =F9*Inputs!C54*Inputs!C20/1000 -> 408 | G21: =G9*Inputs!C54*Inputs!C20/1000 -> 272 | H21: =H9*Inputs!C54*Inputs!C20/1000 -> 272 | I21: =I9*Inputs!C54*Inputs!C20/1000 -> 408 | J21: =J9*Inputs!C54*Inputs!C20/1000 -> 0 | K21: =K9*Inputs!C54*Inputs!C20/1000 -> 0 | L21: =L9*Inputs!C54*Inputs!C20/1000 -> 0 | M21: =M9*Inputs!C54*Inputs!C20/1000 -> 0 | N21: =N9*Inputs!C54*Inputs!C20/1000 -> 0 | O21: =O9*Inputs!C54*Inputs!C20/1000 -> 0 | P21: =P9*Inputs!C54*Inputs!C20/1000 -> 0 | Q21: =Q9*Inputs!C54*Inputs!C20/1000 -> 0 | R21: =R9*Inputs!C54*Inputs!C20/1000 -> 0 | S21: =S9*Inputs!C54*Inputs!C20/1000 -> 0 | T21: =T9*Inputs!C54*Inputs!C20/1000 -> 0 | U21: =U9*Inputs!C54*Inputs!C20/1000 -> 0 | V21: =V9*Inputs!C54*Inputs!C20/1000 -> 0 | W21: =W9*Inputs!C54*Inputs!C20/1000 -> 0 | X21: =X9*Inputs!C54*Inputs!C20/1000 -> 0 | Y21: =Y9*Inputs!C54*Inputs!C20/1000 -> 0 | Z21: =Z9*Inputs!C54*Inputs!C20/1000 -> 0 | AA21: =AA9*Inputs!C54*Inputs!C20/1000 -> 0 | AB21: =AB9*Inputs!C54*Inputs!C20/1000 -> 0 | AC21: =AC9*Inputs!C54*Inputs!C20/1000 -> 0 | AD21: =AD9*Inputs!C54*Inputs!C20/1000 -> 0 | AE21: =AE9*Inputs!C54*Inputs!C20/1000 -> 0 | AF21: =AF9*Inputs!C54*Inputs!C20/1000 -> 0 | AG21: =AG9*Inputs!C54*Inputs!C20/1000 -> 0 | AH21: =AH9*Inputs!C54*Inputs!C20/1000 -> 0 | AI21: =AI9*Inputs!C54*Inputs!C20/1000 -> 0 | AJ21: =AJ9*Inputs!C54*Inputs!C20/1000 -> 0 | AK21: =AK9*Inputs!C54*Inputs!C20/1000 -> 0 | AL21: =AL9*Inputs!C54*Inputs!C20/1000 -> 0 | AM21: =AM9*Inputs!C54*Inputs!C20/1000 -> 0
A22: Port / clearing basis | B22: ZAR'000 | C22: Per new container | D22: =D9*Inputs!C55 -> 0 | E22: =E9*Inputs!C55 -> 0 | F22: =F9*Inputs!C55 -> 450 | G22: =G9*Inputs!C55 -> 300 | H22: =H9*Inputs!C55 -> 300 | I22: =I9*Inputs!C55 -> 450 | J22: =J9*Inputs!C55 -> 0 | K22: =K9*Inputs!C55 -> 0 | L22: =L9*Inputs!C55 -> 0 | M22: =M9*Inputs!C55 -> 0 | N22: =N9*Inputs!C55 -> 0 | O22: =O9*Inputs!C55 -> 0 | P22: =P9*Inputs!C55 -> 0 | Q22: =Q9*Inputs!C55 -> 0 | R22: =R9*Inputs!C55 -> 0 | S22: =S9*Inputs!C55 -> 0 | T22: =T9*Inputs!C55 -> 0 | U22: =U9*Inputs!C55 -> 0 | V22: =V9*Inputs!C55 -> 0 | W22: =W9*Inputs!C55 -> 0 | X22: =X9*Inputs!C55 -> 0 | Y22: =Y9*Inputs!C55 -> 0 | Z22: =Z9*Inputs!C55 -> 0 | AA22: =AA9*Inputs!C55 -> 0 | AB22: =AB9*Inputs!C55 -> 0 | AC22: =AC9*Inputs!C55 -> 0 | AD22: =AD9*Inputs!C55 -> 0 | AE22: =AE9*Inputs!C55 -> 0 | AF22: =AF9*Inputs!C55 -> 0 | AG22: =AG9*Inputs!C55 -> 0 | AH22: =AH9*Inputs!C55 -> 0 | AI22: =AI9*Inputs!C55 -> 0 | AJ22: =AJ9*Inputs!C55 -> 0 | AK22: =AK9*Inputs!C55 -> 0 | AL22: =AL9*Inputs!C55 -> 0 | AM22: =AM9*Inputs!C55 -> 0
A23: Inland trucking basis | B23: ZAR'000 | C23: Per new container | D23: =D9*Inputs!C56 -> 0 | E23: =E9*Inputs!C56 -> 0 | F23: =F9*Inputs!C56 -> 210 | G23: =G9*Inputs!C56 -> 140 | H23: =H9*Inputs!C56 -> 140 | I23: =I9*Inputs!C56 -> 210 | J23: =J9*Inputs!C56 -> 0 | K23: =K9*Inputs!C56 -> 0 | L23: =L9*Inputs!C56 -> 0 | M23: =M9*Inputs!C56 -> 0 | N23: =N9*Inputs!C56 -> 0 | O23: =O9*Inputs!C56 -> 0 | P23: =P9*Inputs!C56 -> 0 | Q23: =Q9*Inputs!C56 -> 0 | R23: =R9*Inputs!C56 -> 0 | S23: =S9*Inputs!C56 -> 0 | T23: =T9*Inputs!C56 -> 0 | U23: =U9*Inputs!C56 -> 0 | V23: =V9*Inputs!C56 -> 0 | W23: =W9*Inputs!C56 -> 0 | X23: =X9*Inputs!C56 -> 0 | Y23: =Y9*Inputs!C56 -> 0 | Z23: =Z9*Inputs!C56 -> 0 | AA23: =AA9*Inputs!C56 -> 0 | AB23: =AB9*Inputs!C56 -> 0 | AC23: =AC9*Inputs!C56 -> 0 | AD23: =AD9*Inputs!C56 -> 0 | AE23: =AE9*Inputs!C56 -> 0 | AF23: =AF9*Inputs!C56 -> 0 | AG23: =AG9*Inputs!C56 -> 0 | AH23: =AH9*Inputs!C56 -> 0 | AI23: =AI9*Inputs!C56 -> 0 | AJ23: =AJ9*Inputs!C56 -> 0 | AK23: =AK9*Inputs!C56 -> 0 | AL23: =AL9*Inputs!C56 -> 0 | AM23: =AM9*Inputs!C56 -> 0
A24: Crane / rigging basis | B24: ZAR'000 | C24: Per new container | D24: =D9*Inputs!C57 -> 0 | E24: =E9*Inputs!C57 -> 0 | F24: =F9*Inputs!C57 -> 150 | G24: =G9*Inputs!C57 -> 100 | H24: =H9*Inputs!C57 -> 100 | I24: =I9*Inputs!C57 -> 150 | J24: =J9*Inputs!C57 -> 0 | K24: =K9*Inputs!C57 -> 0 | L24: =L9*Inputs!C57 -> 0 | M24: =M9*Inputs!C57 -> 0 | N24: =N9*Inputs!C57 -> 0 | O24: =O9*Inputs!C57 -> 0 | P24: =P9*Inputs!C57 -> 0 | Q24: =Q9*Inputs!C57 -> 0 | R24: =R9*Inputs!C57 -> 0 | S24: =S9*Inputs!C57 -> 0 | T24: =T9*Inputs!C57 -> 0 | U24: =U9*Inputs!C57 -> 0 | V24: =V9*Inputs!C57 -> 0 | W24: =W9*Inputs!C57 -> 0 | X24: =X9*Inputs!C57 -> 0 | Y24: =Y9*Inputs!C57 -> 0 | Z24: =Z9*Inputs!C57 -> 0 | AA24: =AA9*Inputs!C57 -> 0 | AB24: =AB9*Inputs!C57 -> 0 | AC24: =AC9*Inputs!C57 -> 0 | AD24: =AD9*Inputs!C57 -> 0 | AE24: =AE9*Inputs!C57 -> 0 | AF24: =AF9*Inputs!C57 -> 0 | AG24: =AG9*Inputs!C57 -> 0 | AH24: =AH9*Inputs!C57 -> 0 | AI24: =AI9*Inputs!C57 -> 0 | AJ24: =AJ9*Inputs!C57 -> 0 | AK24: =AK9*Inputs!C57 -> 0 | AL24: =AL9*Inputs!C57 -> 0 | AM24: =AM9*Inputs!C57 -> 0
A25: Cargo insurance basis | B25: ZAR'000 | C25: % of hardware + containers | D25: =(D14+D15)*Inputs!C58 -> 0 | E25: =(E14+E15)*Inputs!C58 -> 0 | F25: =(F14+F15)*Inputs!C58 -> 724.37 | G25: =(G14+G15)*Inputs!C58 -> 664.87 | H25: =(H14+H15)*Inputs!C58 -> 664.87 | I25: =(I14+I15)*Inputs!C58 -> 724.37 | J25: =(J14+J15)*Inputs!C58 -> 0 | K25: =(K14+K15)*Inputs!C58 -> 0 | L25: =(L14+L15)*Inputs!C58 -> 0 | M25: =(M14+M15)*Inputs!C58 -> 0 | N25: =(N14+N15)*Inputs!C58 -> 0 | O25: =(O14+O15)*Inputs!C58 -> 0 | P25: =(P14+P15)*Inputs!C58 -> 0 | Q25: =(Q14+Q15)*Inputs!C58 -> 0 | R25: =(R14+R15)*Inputs!C58 -> 0 | S25: =(S14+S15)*Inputs!C58 -> 0 | T25: =(T14+T15)*Inputs!C58 -> 0 | U25: =(U14+U15)*Inputs!C58 -> 0 | V25: =(V14+V15)*Inputs!C58 -> 0 | W25: =(W14+W15)*Inputs!C58 -> 0 | X25: =(X14+X15)*Inputs!C58 -> 0 | Y25: =(Y14+Y15)*Inputs!C58 -> 0 | Z25: =(Z14+Z15)*Inputs!C58 -> 0 | AA25: =(AA14+AA15)*Inputs!C58 -> 0 | AB25: =(AB14+AB15)*Inputs!C58 -> 0 | AC25: =(AC14+AC15)*Inputs!C58 -> 0 | AD25: =(AD14+AD15)*Inputs!C58 -> 0 | AE25: =(AE14+AE15)*Inputs!C58 -> 0 | AF25: =(AF14+AF15)*Inputs!C58 -> 0 | AG25: =(AG14+AG15)*Inputs!C58 -> 0 | AH25: =(AH14+AH15)*Inputs!C58 -> 0 | AI25: =(AI14+AI15)*Inputs!C58 -> 0 | AJ25: =(AJ14+AJ15)*Inputs!C58 -> 0 | AK25: =(AK14+AK15)*Inputs!C58 -> 0 | AL25: =(AL14+AL15)*Inputs!C58 -> 0 | AM25: =(AM14+AM15)*Inputs!C58 -> 0
A26: Import duty basis | B26: ZAR'000 | C26: % of hardware + containers | D26: =(D14+D15)*Inputs!C59 -> 0 | E26: =(E14+E15)*Inputs!C59 -> 0 | F26: =(F14+F15)*Inputs!C59 -> 3621.85 | G26: =(G14+G15)*Inputs!C59 -> 3324.35 | H26: =(H14+H15)*Inputs!C59 -> 3324.35 | I26: =(I14+I15)*Inputs!C59 -> 3621.85 | J26: =(J14+J15)*Inputs!C59 -> 0 | K26: =(K14+K15)*Inputs!C59 -> 0 | L26: =(L14+L15)*Inputs!C59 -> 0 | M26: =(M14+M15)*Inputs!C59 -> 0 | N26: =(N14+N15)*Inputs!C59 -> 0 | O26: =(O14+O15)*Inputs!C59 -> 0 | P26: =(P14+P15)*Inputs!C59 -> 0 | Q26: =(Q14+Q15)*Inputs!C59 -> 0 | R26: =(R14+R15)*Inputs!C59 -> 0 | S26: =(S14+S15)*Inputs!C59 -> 0 | T26: =(T14+T15)*Inputs!C59 -> 0 | U26: =(U14+U15)*Inputs!C59 -> 0 | V26: =(V14+V15)*Inputs!C59 -> 0 | W26: =(W14+W15)*Inputs!C59 -> 0 | X26: =(X14+X15)*Inputs!C59 -> 0 | Y26: =(Y14+Y15)*Inputs!C59 -> 0 | Z26: =(Z14+Z15)*Inputs!C59 -> 0 | AA26: =(AA14+AA15)*Inputs!C59 -> 0 | AB26: =(AB14+AB15)*Inputs!C59 -> 0 | AC26: =(AC14+AC15)*Inputs!C59 -> 0 | AD26: =(AD14+AD15)*Inputs!C59 -> 0 | AE26: =(AE14+AE15)*Inputs!C59 -> 0 | AF26: =(AF14+AF15)*Inputs!C59 -> 0 | AG26: =(AG14+AG15)*Inputs!C59 -> 0 | AH26: =(AH14+AH15)*Inputs!C59 -> 0 | AI26: =(AI14+AI15)*Inputs!C59 -> 0 | AJ26: =(AJ14+AJ15)*Inputs!C59 -> 0 | AK26: =(AK14+AK15)*Inputs!C59 -> 0 | AL26: =(AL14+AL15)*Inputs!C59 -> 0 | AM26: =(AM14+AM15)*Inputs!C59 -> 0
A27: Office / software / legal setup basis | B27: ZAR'000 | C27: One-off corporate setup | D27: =IF(1=1,Inputs!C51+Inputs!C52+Inputs!C53,0) -> 2450 | E27: =IF(2=1,Inputs!C51+Inputs!C52+Inputs!C53,0) -> 0 | F27: =IF(3=1,Inputs!C51+Inputs!C52+Inputs!C53,0) -> 0 | G27: =IF(4=1,Inputs!C51+Inputs!C52+Inputs!C53,0) -> 0 | H27: =IF(5=1,Inputs!C51+Inputs!C52+Inputs!C53,0) -> 0 | I27: =IF(6=1,Inputs!C51+Inputs!C52+Inputs!C53,0) -> 0 | J27: =IF(7=1,Inputs!C51+Inputs!C52+Inputs!C53,0) -> 0 | K27: =IF(8=1,Inputs!C51+Inputs!C52+Inputs!C53,0) -> 0 | L27: =IF(9=1,Inputs!C51+Inputs!C52+Inputs!C53,0) -> 0 | M27: =IF(10=1,Inputs!C51+Inputs!C52+Inputs!C53,0) -> 0 | N27: =IF(11=1,Inputs!C51+Inputs!C52+Inputs!C53,0) -> 0 | O27: =IF(12=1,Inputs!C51+Inputs!C52+Inputs!C53,0) -> 0 | P27: =IF(13=1,Inputs!C51+Inputs!C52+Inputs!C53,0) -> 0 | Q27: =IF(14=1,Inputs!C51+Inputs!C52+Inputs!C53,0) -> 0 | R27: =IF(15=1,Inputs!C51+Inputs!C52+Inputs!C53,0) -> 0 | S27: =IF(16=1,Inputs!C51+Inputs!C52+Inputs!C53,0) -> 0 | T27: =IF(17=1,Inputs!C51+Inputs!C52+Inputs!C53,0) -> 0 | U27: =IF(18=1,Inputs!C51+Inputs!C52+Inputs!C53,0) -> 0 | V27: =IF(19=1,Inputs!C51+Inputs!C52+Inputs!C53,0) -> 0 | W27: =IF(20=1,Inputs!C51+Inputs!C52+Inputs!C53,0) -> 0 | X27: =IF(21=1,Inputs!C51+Inputs!C52+Inputs!C53,0) -> 0 | Y27: =IF(22=1,Inputs!C51+Inputs!C52+Inputs!C53,0) -> 0 | Z27: =IF(23=1,Inputs!C51+Inputs!C52+Inputs!C53,0) -> 0 | AA27: =IF(24=1,Inputs!C51+Inputs!C52+Inputs!C53,0) -> 0 | AB27: =IF(25=1,Inputs!C51+Inputs!C52+Inputs!C53,0) -> 0 | AC27: =IF(26=1,Inputs!C51+Inputs!C52+Inputs!C53,0) -> 0 | AD27: =IF(27=1,Inputs!C51+Inputs!C52+Inputs!C53,0) -> 0 | AE27: =IF(28=1,Inputs!C51+Inputs!C52+Inputs!C53,0) -> 0 | AF27: =IF(29=1,Inputs!C51+Inputs!C52+Inputs!C53,0) -> 0 | AG27: =IF(30=1,Inputs!C51+Inputs!C52+Inputs!C53,0) -> 0 | AH27: =IF(31=1,Inputs!C51+Inputs!C52+Inputs!C53,0) -> 0 | AI27: =IF(32=1,Inputs!C51+Inputs!C52+Inputs!C53,0) -> 0 | AJ27: =IF(33=1,Inputs!C51+Inputs!C52+Inputs!C53,0) -> 0 | AK27: =IF(34=1,Inputs!C51+Inputs!C52+Inputs!C53,0) -> 0 | AL27: =IF(35=1,Inputs!C51+Inputs!C52+Inputs!C53,0) -> 0 | AM27: =IF(36=1,Inputs!C51+Inputs!C52+Inputs!C53,0) -> 0
A30: ASIC hardware deposit cash | B30: ZAR'000 | C30: Deposit paid before COD | D30: =Inputs!C100*F14 -> 32752.2 | E30: =Inputs!C100*G14 -> 32752.2 | F30: =Inputs!C100*H14 -> 32752.2 | G30: =Inputs!C100*I14 -> 32752.2 | H30: =Inputs!C100*J14 -> 0 | I30: =Inputs!C100*K14 -> 0 | J30: =Inputs!C100*L14 -> 0 | K30: =Inputs!C100*M14 -> 0 | L30: =Inputs!C100*N14 -> 0 | M30: =Inputs!C100*O14 -> 0 | N30: =Inputs!C100*P14 -> 0 | O30: =Inputs!C100*Q14 -> 0 | P30: =Inputs!C100*R14 -> 0 | Q30: =Inputs!C100*S14 -> 0 | R30: =Inputs!C100*T14 -> 0 | S30: =Inputs!C100*U14 -> 0 | T30: =Inputs!C100*V14 -> 0 | U30: =Inputs!C100*W14 -> 0 | V30: =Inputs!C100*X14 -> 0 | W30: =Inputs!C100*Y14 -> 0 | X30: =Inputs!C100*Z14 -> 0 | Y30: =Inputs!C100*AA14 -> 0 | Z30: =Inputs!C100*AB14 -> 0 | AA30: =Inputs!C100*AC14 -> 0 | AB30: =Inputs!C100*AD14 -> 0 | AC30: =Inputs!C100*AE14 -> 0 | AD30: =Inputs!C100*AF14 -> 0 | AE30: =Inputs!C100*AG14 -> 0 | AF30: =Inputs!C100*AH14 -> 0 | AG30: =Inputs!C100*AI14 -> 0 | AH30: =Inputs!C100*AJ14 -> 0 | AI30: =Inputs!C100*AK14 -> 0 | AJ30: =Inputs!C100*AL14 -> 0 | AK30: =Inputs!C100*AM14 -> 0 | AL30: =0 -> 0 | AM30: =0 -> 0
A31: ASIC hardware final cash | B31: ZAR'000 | C31: Final cash paid in COD month | D31: =Inputs!C101*D14 -> 0 | E31: =Inputs!C101*E14 -> 0 | F31: =Inputs!C101*F14 -> 21834.8 | G31: =Inputs!C101*G14 -> 21834.8 | H31: =Inputs!C101*H14 -> 21834.8 | I31: =Inputs!C101*I14 -> 21834.8 | J31: =Inputs!C101*J14 -> 0 | K31: =Inputs!C101*K14 -> 0 | L31: =Inputs!C101*L14 -> 0 | M31: =Inputs!C101*M14 -> 0 | N31: =Inputs!C101*N14 -> 0 | O31: =Inputs!C101*O14 -> 0 | P31: =Inputs!C101*P14 -> 0 | Q31: =Inputs!C101*Q14 -> 0 | R31: =Inputs!C101*R14 -> 0 | S31: =Inputs!C101*S14 -> 0 | T31: =Inputs!C101*T14 -> 0 | U31: =Inputs!C101*U14 -> 0 | V31: =Inputs!C101*V14 -> 0 | W31: =Inputs!C101*W14 -> 0 | X31: =Inputs!C101*X14 -> 0 | Y31: =Inputs!C101*Y14 -> 0 | Z31: =Inputs!C101*Z14 -> 0 | AA31: =Inputs!C101*AA14 -> 0 | AB31: =Inputs!C101*AB14 -> 0 | AC31: =Inputs!C101*AC14 -> 0 | AD31: =Inputs!C101*AD14 -> 0 | AE31: =Inputs!C101*AE14 -> 0 | AF31: =Inputs!C101*AF14 -> 0 | AG31: =Inputs!C101*AG14 -> 0 | AH31: =Inputs!C101*AH14 -> 0 | AI31: =Inputs!C101*AI14 -> 0 | AJ31: =Inputs!C101*AJ14 -> 0 | AK31: =Inputs!C101*AK14 -> 0 | AL31: =Inputs!C101*AL14 -> 0 | AM31: =Inputs!C101*AM14 -> 0
A32: Container deposit cash | B32: ZAR'000 | C32: Deposit paid before COD | D32: =Inputs!C103*F15 -> 3570 | E32: =Inputs!C103*G15 -> 2380 | F32: =Inputs!C103*H15 -> 2380 | G32: =Inputs!C103*I15 -> 3570 | H32: =Inputs!C103*J15 -> 0 | I32: =Inputs!C103*K15 -> 0 | J32: =Inputs!C103*L15 -> 0 | K32: =Inputs!C103*M15 -> 0 | L32: =Inputs!C103*N15 -> 0 | M32: =Inputs!C103*O15 -> 0 | N32: =Inputs!C103*P15 -> 0 | O32: =Inputs!C103*Q15 -> 0 | P32: =Inputs!C103*R15 -> 0 | Q32: =Inputs!C103*S15 -> 0 | R32: =Inputs!C103*T15 -> 0 | S32: =Inputs!C103*U15 -> 0 | T32: =Inputs!C103*V15 -> 0 | U32: =Inputs!C103*W15 -> 0 | V32: =Inputs!C103*X15 -> 0 | W32: =Inputs!C103*Y15 -> 0 | X32: =Inputs!C103*Z15 -> 0 | Y32: =Inputs!C103*AA15 -> 0 | Z32: =Inputs!C103*AB15 -> 0 | AA32: =Inputs!C103*AC15 -> 0 | AB32: =Inputs!C103*AD15 -> 0 | AC32: =Inputs!C103*AE15 -> 0 | AD32: =Inputs!C103*AF15 -> 0 | AE32: =Inputs!C103*AG15 -> 0 | AF32: =Inputs!C103*AH15 -> 0 | AG32: =Inputs!C103*AI15 -> 0 | AH32: =Inputs!C103*AJ15 -> 0 | AI32: =Inputs!C103*AK15 -> 0 | AJ32: =Inputs!C103*AL15 -> 0 | AK32: =Inputs!C103*AM15 -> 0 | AL32: =0 -> 0 | AM32: =0 -> 0
A33: Container progress cash | B33: ZAR'000 | C33: Progress payment before COD | D33: =Inputs!C104*E15 -> 0 | E33: =Inputs!C104*F15 -> 5355 | F33: =Inputs!C104*G15 -> 3570 | G33: =Inputs!C104*H15 -> 3570 | H33: =Inputs!C104*I15 -> 5355 | I33: =Inputs!C104*J15 -> 0 | J33: =Inputs!C104*K15 -> 0 | K33: =Inputs!C104*L15 -> 0 | L33: =Inputs!C104*M15 -> 0 | M33: =Inputs!C104*N15 -> 0 | N33: =Inputs!C104*O15 -> 0 | O33: =Inputs!C104*P15 -> 0 | P33: =Inputs!C104*Q15 -> 0 | Q33: =Inputs!C104*R15 -> 0 | R33: =Inputs!C104*S15 -> 0 | S33: =Inputs!C104*T15 -> 0 | T33: =Inputs!C104*U15 -> 0 | U33: =Inputs!C104*V15 -> 0 | V33: =Inputs!C104*W15 -> 0 | W33: =Inputs!C104*X15 -> 0 | X33: =Inputs!C104*Y15 -> 0 | Y33: =Inputs!C104*Z15 -> 0 | Z33: =Inputs!C104*AA15 -> 0 | AA33: =Inputs!C104*AB15 -> 0 | AB33: =Inputs!C104*AC15 -> 0 | AC33: =Inputs!C104*AD15 -> 0 | AD33: =Inputs!C104*AE15 -> 0 | AE33: =Inputs!C104*AF15 -> 0 | AF33: =Inputs!C104*AG15 -> 0 | AG33: =Inputs!C104*AH15 -> 0 | AH33: =Inputs!C104*AI15 -> 0 | AI33: =Inputs!C104*AJ15 -> 0 | AJ33: =Inputs!C104*AK15 -> 0 | AK33: =Inputs!C104*AL15 -> 0 | AL33: =Inputs!C104*AM15 -> 0 | AM33: =0 -> 0
A34: Container final cash | B34: ZAR'000 | C34: Final paid in COD month | D34: =Inputs!C105*D15 -> 0 | E34: =Inputs!C105*E15 -> 0 | F34: =Inputs!C105*F15 -> 8925 | G34: =Inputs!C105*G15 -> 5950 | H34: =Inputs!C105*H15 -> 5950 | I34: =Inputs!C105*I15 -> 8925 | J34: =Inputs!C105*J15 -> 0 | K34: =Inputs!C105*K15 -> 0 | L34: =Inputs!C105*L15 -> 0 | M34: =Inputs!C105*M15 -> 0 | N34: =Inputs!C105*N15 -> 0 | O34: =Inputs!C105*O15 -> 0 | P34: =Inputs!C105*P15 -> 0 | Q34: =Inputs!C105*Q15 -> 0 | R34: =Inputs!C105*R15 -> 0 | S34: =Inputs!C105*S15 -> 0 | T34: =Inputs!C105*T15 -> 0 | U34: =Inputs!C105*U15 -> 0 | V34: =Inputs!C105*V15 -> 0 | W34: =Inputs!C105*W15 -> 0 | X34: =Inputs!C105*X15 -> 0 | Y34: =Inputs!C105*Y15 -> 0 | Z34: =Inputs!C105*Z15 -> 0 | AA34: =Inputs!C105*AA15 -> 0 | AB34: =Inputs!C105*AB15 -> 0 | AC34: =Inputs!C105*AC15 -> 0 | AD34: =Inputs!C105*AD15 -> 0 | AE34: =Inputs!C105*AE15 -> 0 | AF34: =Inputs!C105*AF15 -> 0 | AG34: =Inputs!C105*AG15 -> 0 | AH34: =Inputs!C105*AH15 -> 0 | AI34: =Inputs!C105*AI15 -> 0 | AJ34: =Inputs!C105*AJ15 -> 0 | AK34: =Inputs!C105*AK15 -> 0 | AL34: =Inputs!C105*AL15 -> 0 | AM34: =Inputs!C105*AM15 -> 0
A35: EPC deposit cash | B35: ZAR'000 | C35: Deposit paid before COD | D35: =Inputs!C107*F16 -> 6661.1366 | E35: =Inputs!C107*G16 -> 2854.7728 | F35: =Inputs!C107*H16 -> 2854.7728 | G35: =Inputs!C107*I16 -> 6661.1366 | H35: =Inputs!C107*J16 -> 0 | I35: =Inputs!C107*K16 -> 0 | J35: =Inputs!C107*L16 -> 0 | K35: =Inputs!C107*M16 -> 0 | L35: =Inputs!C107*N16 -> 0 | M35: =Inputs!C107*O16 -> 0 | N35: =Inputs!C107*P16 -> 0 | O35: =Inputs!C107*Q16 -> 0 | P35: =Inputs!C107*R16 -> 0 | Q35: =Inputs!C107*S16 -> 0 | R35: =Inputs!C107*T16 -> 0 | S35: =Inputs!C107*U16 -> 0 | T35: =Inputs!C107*V16 -> 0 | U35: =Inputs!C107*W16 -> 0 | V35: =Inputs!C107*X16 -> 0 | W35: =Inputs!C107*Y16 -> 0 | X35: =Inputs!C107*Z16 -> 0 | Y35: =Inputs!C107*AA16 -> 0 | Z35: =Inputs!C107*AB16 -> 0 | AA35: =Inputs!C107*AC16 -> 0 | AB35: =Inputs!C107*AD16 -> 0 | AC35: =Inputs!C107*AE16 -> 0 | AD35: =Inputs!C107*AF16 -> 0 | AE35: =Inputs!C107*AG16 -> 0 | AF35: =Inputs!C107*AH16 -> 0 | AG35: =Inputs!C107*AI16 -> 0 | AH35: =Inputs!C107*AJ16 -> 0 | AI35: =Inputs!C107*AK16 -> 0 | AJ35: =Inputs!C107*AL16 -> 0 | AK35: =Inputs!C107*AM16 -> 0 | AL35: =0 -> 0 | AM35: =0 -> 0
A36: EPC progress cash | B36: ZAR'000 | C36: Progress payment before COD | D36: =Inputs!C108*E16 -> 0 | E36: =Inputs!C108*F16 -> 15542.652 | F36: =Inputs!C108*G16 -> 6661.1366 | G36: =Inputs!C108*H16 -> 6661.1366 | H36: =Inputs!C108*I16 -> 15542.652 | I36: =Inputs!C108*J16 -> 0 | J36: =Inputs!C108*K16 -> 0 | K36: =Inputs!C108*L16 -> 0 | L36: =Inputs!C108*M16 -> 0 | M36: =Inputs!C108*N16 -> 0 | N36: =Inputs!C108*O16 -> 0 | O36: =Inputs!C108*P16 -> 0 | P36: =Inputs!C108*Q16 -> 0 | Q36: =Inputs!C108*R16 -> 0 | R36: =Inputs!C108*S16 -> 0 | S36: =Inputs!C108*T16 -> 0 | T36: =Inputs!C108*U16 -> 0 | U36: =Inputs!C108*V16 -> 0 | V36: =Inputs!C108*W16 -> 0 | W36: =Inputs!C108*X16 -> 0 | X36: =Inputs!C108*Y16 -> 0 | Y36: =Inputs!C108*Z16 -> 0 | Z36: =Inputs!C108*AA16 -> 0 | AA36: =Inputs!C108*AB16 -> 0 | AB36: =Inputs!C108*AC16 -> 0 | AC36: =Inputs!C108*AD16 -> 0 | AD36: =Inputs!C108*AE16 -> 0 | AE36: =Inputs!C108*AF16 -> 0 | AF36: =Inputs!C108*AG16 -> 0 | AG36: =Inputs!C108*AH16 -> 0 | AH36: =Inputs!C108*AI16 -> 0 | AI36: =Inputs!C108*AJ16 -> 0 | AJ36: =Inputs!C108*AK16 -> 0 | AK36: =Inputs!C108*AL16 -> 0 | AL36: =Inputs!C108*AM16 -> 0 | AM36: =0 -> 0
A37: EPC final cash | B37: ZAR'000 | C37: Final paid in COD month | D37: =Inputs!C109*D16 -> 0 | E37: =Inputs!C109*E16 -> 0 | F37: =Inputs!C109*F16 -> 17763.031 | G37: =Inputs!C109*G16 -> 7612.7275 | H37: =Inputs!C109*H16 -> 7612.7275 | I37: =Inputs!C109*I16 -> 17763.031 | J37: =Inputs!C109*J16 -> 0 | K37: =Inputs!C109*K16 -> 0 | L37: =Inputs!C109*L16 -> 0 | M37: =Inputs!C109*M16 -> 0 | N37: =Inputs!C109*N16 -> 0 | O37: =Inputs!C109*O16 -> 0 | P37: =Inputs!C109*P16 -> 0 | Q37: =Inputs!C109*Q16 -> 0 | R37: =Inputs!C109*R16 -> 0 | S37: =Inputs!C109*S16 -> 0 | T37: =Inputs!C109*T16 -> 0 | U37: =Inputs!C109*U16 -> 0 | V37: =Inputs!C109*V16 -> 0 | W37: =Inputs!C109*W16 -> 0 | X37: =Inputs!C109*X16 -> 0 | Y37: =Inputs!C109*Y16 -> 0 | Z37: =Inputs!C109*Z16 -> 0 | AA37: =Inputs!C109*AA16 -> 0 | AB37: =Inputs!C109*AB16 -> 0 | AC37: =Inputs!C109*AC16 -> 0 | AD37: =Inputs!C109*AD16 -> 0 | AE37: =Inputs!C109*AE16 -> 0 | AF37: =Inputs!C109*AF16 -> 0 | AG37: =Inputs!C109*AG16 -> 0 | AH37: =Inputs!C109*AH16 -> 0 | AI37: =Inputs!C109*AI16 -> 0 | AJ37: =Inputs!C109*AJ16 -> 0 | AK37: =Inputs!C109*AK16 -> 0 | AL37: =Inputs!C109*AL16 -> 0 | AM37: =Inputs!C109*AM16 -> 0
A38: EPC commissioning cash | B38: ZAR'000 | C38: Paid one month after COD | D38: =0 -> 0 | E38: =Inputs!C110*D16 -> 0 | F38: =Inputs!C110*E16 -> 0 | G38: =Inputs!C110*F16 -> 4440.7577 | H38: =Inputs!C110*G16 -> 1903.1819 | I38: =Inputs!C110*H16 -> 1903.1819 | J38: =Inputs!C110*I16 -> 4440.7577 | K38: =Inputs!C110*J16 -> 0 | L38: =Inputs!C110*K16 -> 0 | M38: =Inputs!C110*L16 -> 0 | N38: =Inputs!C110*M16 -> 0 | O38: =Inputs!C110*N16 -> 0 | P38: =Inputs!C110*O16 -> 0 | Q38: =Inputs!C110*P16 -> 0 | R38: =Inputs!C110*Q16 -> 0 | S38: =Inputs!C110*R16 -> 0 | T38: =Inputs!C110*S16 -> 0 | U38: =Inputs!C110*T16 -> 0 | V38: =Inputs!C110*U16 -> 0 | W38: =Inputs!C110*V16 -> 0 | X38: =Inputs!C110*W16 -> 0 | Y38: =Inputs!C110*X16 -> 0 | Z38: =Inputs!C110*Y16 -> 0 | AA38: =Inputs!C110*Z16 -> 0 | AB38: =Inputs!C110*AA16 -> 0 | AC38: =Inputs!C110*AB16 -> 0 | AD38: =Inputs!C110*AC16 -> 0 | AE38: =Inputs!C110*AD16 -> 0 | AF38: =Inputs!C110*AE16 -> 0 | AG38: =Inputs!C110*AF16 -> 0 | AH38: =Inputs!C110*AG16 -> 0 | AI38: =Inputs!C110*AH16 -> 0 | AJ38: =Inputs!C110*AI16 -> 0 | AK38: =Inputs!C110*AJ16 -> 0 | AL38: =Inputs!C110*AK16 -> 0 | AM38: =Inputs!C110*AL16 -> 0
A39: Solar deposit cash | B39: ZAR'000 | C39: Simplified staged solar payment | D39: =0.2*F17 -> 0 | E39: =0.2*G17 -> 0 | F39: =0.2*H17 -> 14000 | G39: =0.2*I17 -> 0 | H39: =0.2*J17 -> 0 | I39: =0.2*K17 -> 0 | J39: =0.2*L17 -> 0 | K39: =0.2*M17 -> 0 | ... AK39: =0.2*AM17 -> 0 | AL39: =0 -> 0 | AM39: =0 -> 0
A40: Solar progress cash | B40: ZAR'000 | C40: Simplified staged solar payment | D40: =0.3*E17 -> 0 | E40: =0.3*F17 -> 0 | F40: =0.3*G17 -> 0 | G40: =0.3*H17 -> 21000 | H40: =0.3*I17 -> 0 | I40: =0.3*J17 -> 0 | J40: =0.3*K17 -> 0 | K40: =0.3*L17 -> 0 | ... AL40: =0.3*AM17 -> 0 | AM40: =0 -> 0
A41: Solar final cash | B41: ZAR'000 | C41: Simplified staged solar payment | D41: =0.5*D17 -> 0 | E41: =0.5*E17 -> 0 | F41: =0.5*F17 -> 0 | G41: =0.5*G17 -> 0 | H41: =0.5*H17 -> 35000 | I41: =0.5*I17 -> 0 | J41: =0.5*J17 -> 0 | K41: =0.5*K17 -> 0 | ... AM41: =0.5*AM17 -> 0
A42: Initial spare parts cash | B42: ZAR'000 | C42: Paid in COD month | D42: =D18 -> 0 | E42: =E18 -> 0 | F42: =F18 -> 1448.74 | G42: =G18 -> 1329.74 | H42: =H18 -> 1329.74 | I42: =I18 -> 1448.74 | J42: =J18 -> 0 | K42: =K18 -> 0 | ... AM42: =AM18 -> 0
A43: Tools / equipment initial cash | B43: ZAR'000 | C43: Paid on site start | D43: =D19 -> 0 | E43: =E19 -> 0 | F43: =F19 -> 750 | G43: =G19 -> 0 | H43: =H19 -> 0 | I43: =I19 -> 750 | J43: =J19 -> 0 | K43: =K19 -> 0 | ... AM43: =AM19 -> 0
A44: Staff hardware cash | B44: ZAR'000 | C44: Paid on onboarding | D44: =D20 -> 0 | E44: =E20 -> 0 | F44: =F20 -> 145.25 | G44: =G20 -> 75.25 | H44: =H20 -> 75.25 | I44: =I20 -> 145.25 | J44: =J20 -> 0 | K44: =K20 -> 0 | ... AM44: =AM20 -> 0
A45: Freight cash | B45: ZAR'000 | C45: Paid one month before COD | D45: =E21 -> 0 | E45: =F21 -> 408 | F45: =G21 -> 272 | G45: =H21 -> 272 | H45: =I21 -> 408 | I45: =J21 -> 0 | J45: =K21 -> 0 | K45: =L21 -> 0 | ... AL45: =AM21 -> 0 | AM45: =0 -> 0
A46: Port / clearing cash | B46: ZAR'000 | C46: Paid one month before COD | D46: =E22 -> 0 | E46: =F22 -> 450 | F46: =G22 -> 300 | G46: =H22 -> 300 | H46: =I22 -> 450 | I46: =J22 -> 0 | J46: =K22 -> 0 | K46: =L22 -> 0 | ... AL46: =AM22 -> 0 | AM46: =0 -> 0
A47: Inland trucking cash | B47: ZAR'000 | C47: Paid one month before COD | D47: =E23 -> 0 | E47: =F23 -> 210 | F47: =G23 -> 140 | G47: =H23 -> 140 | H47: =I23 -> 210 | I47: =J23 -> 0 | J47: =K23 -> 0 | K47: =L23 -> 0 | ... AL47: =AM23 -> 0 | AM47: =0 -> 0
A48: Crane / rigging cash | B48: ZAR'000 | C48: Paid in COD month | D48: =D24 -> 0 | E48: =E24 -> 0 | F48: =F24 -> 150 | G48: =G24 -> 100 | H48: =H24 -> 100 | I48: =I24 -> 150 | J48: =J24 -> 0 | K48: =K24 -> 0 | ... AM48: =AM24 -> 0
A49: Cargo insurance cash | B49: ZAR'000 | C49: Paid one month before COD | D49: =E25 -> 0 | E49: =F25 -> 724.37 | F49: =G25 -> 664.87 | G49: =H25 -> 664.87 | H49: =I25 -> 724.37 | I49: =J25 -> 0 | J49: =K25 -> 0 | K49: =L25 -> 0 | ... AL49: =AM25 -> 0 | AM49: =0 -> 0
A50: Import duty cash | B50: ZAR'000 | C50: Paid one month before COD | D50: =E26 -> 0 | E50: =F26 -> 3621.85 | F50: =G26 -> 3324.35 | G50: =H26 -> 3324.35 | H50: =I26 -> 3621.85 | I50: =J26 -> 0 | J50: =K26 -> 0 | K50: =L26 -> 0 | ... AL50: =AM26 -> 0 | AM50: =0 -> 0
A51: Office / software / legal setup cash | B51: ZAR'000 | C51: Paid in month 1 | D51: =D27 -> 2450 | E51: =E27 -> 0 | F51: =F27 -> 0 | G51: =G27 -> 0 | H51: =H27 -> 0 | I51: =I27 -> 0 | J51: =J27 -> 0 | K51: =K27 -> 0 | ... AM51: =AM27 -> 0
A52: Total capex cash spend | B52: ZAR'000 | C52: Used in Funding sheet | D52: =SUM(D30:D51) -> 45433.337 | E52: =SUM(E30:E51) -> 64298.845 | F52: =SUM(F30:F51) -> 117936.15 | G52: =SUM(G30:G51) -> 120258.97 | H52: =SUM(H30:H51) -> 100117.57 | I52: =SUM(I30:I51) -> 52920.003 | J52: =SUM(J30:J51) -> 4440.7577 | K52: =SUM(K30:K51) -> 0 | ... AM52: =SUM(AM30:AM51) -> 0
A53: Cumulative capex spend | B53: ZAR'000 | C53: Running total | D53: =D52 -> 45433.337 | E53: =D53+E52 -> 109732.18 | F53: =E53+F52 -> 227668.33 | G53: =F53+G52 -> 347927.3 | H53: =G53+H52 -> 448044.87 | I53: =H53+I52 -> 500964.87 | J53: =I53+J52 -> 505405.63 | K53: =J53+K52 -> 505405.63 | L53: =K53+L52 -> 505405.63 | ... AM53: =AL53+AM52 -> 505405.63

Sheet Funding_36M
A1: Funding_36M | Conservative base-case funding need (BTC revenue only)
A2: Default funding mix is 100% equity. Switch the debt share in Inputs if you want a hybrid capital structure.
A4: Metric | B4: Unit | C4: Notes
A5: Date | B5: date | C5: Linked from deployment | D5: =Deployment_36M!D5 -> 46204 | E5: =Deployment_36M!E5 -> 46235 | F5: =Deployment_36M!F5 -> 46266 | G5: =Deployment_36M!G5 -> 46296 | H5: =Deployment_36M!H5 -> 46327 | I5: =Deployment_36M!I5 -> 46357 | J5: =Deployment_36M!J5 -> 46388 | K5: =Deployment_36M!K5 -> 46419 | ... AM5: =Deployment_36M!AM5 -> 47270
A6: Days in month | B6: days | C6: Linked from deployment | D6: =Deployment_36M!D6 -> 31 | E6: =Deployment_36M!E6 -> 31 | F6: =Deployment_36M!F6 -> 30 | G6: =Deployment_36M!G6 -> 31 | H6: =Deployment_36M!H6 -> 30 | I6: =Deployment_36M!I6 -> 31 | J6: =Deployment_36M!J6 -> 31 | K6: =Deployment_36M!K6 -> 28 | ... AM6: =Deployment_36M!AM6 -> 30
A8: Opening cash before funding | B8: ZAR'000 | C8: Starts at zero by default | D8: =0 -> 0 | E8: =D15 -> 0 | F8: =E15 -> 0 | G8: =F15 -> 0 | H8: =G15 -> 0 | I8: =H15 -> 0 | J8: =I15 -> 0 | K8: =J15 -> 13432.378 | L8: =K15 -> 29503.851 | ... AM8: =AL15 -> 567897.17
A9: Unlevered cash flow before funding | B9: ZAR'000 | C9: Base-case revenue - opex - capex | D9: =Revenue_36M!D20-Opex_36M!D28-Capex_36M!D52 -> -45956.337 | E9: =Revenue_36M!E20-Opex_36M!E28-Capex_36M!E52 -> -64821.845 | F9: =Revenue_36M!F20-Opex_36M!F28-Capex_36M!F52 -> -116872.4 | G9: =Revenue_36M!G20-Opex_36M!G28-Capex_36M!G52 -> -114536.19 | H9: =Revenue_36M!H20-Opex_36M!H28-Capex_36M!H52 -> -90423.49 | I9: =Revenue_36M!I20-Opex_36M!I28-Capex_36M!I52 -> -38277.985 | J9: =Revenue_36M!J20-Opex_36M!J28-Capex_36M!J52 -> 13432.378 | K9: =Revenue_36M!K20-Opex_36M!K28-Capex_36M!K52 -> 16071.473 | ... AM9: =Revenue_36M!AM20-Opex_36M!AM28-Capex_36M!AM52 -> 21651.246
A10: Required net external funding | B10: ZAR'000 | C10: Funding need after opening cash and base-case burn | D10: =MAX(Inputs!C99-(D8+D9),0) -> 45956.337 | E10: =MAX(Inputs!C99-(E8+E9),0) -> 64821.845 | F10: =MAX(Inputs!C99-(F8+F9),0) -> 116872.4 | G10: =MAX(Inputs!C99-(G8+G9),0) -> 114536.19 | H10: =MAX(Inputs!C99-(H8+H9),0) -> 90423.49 | I10: =MAX(Inputs!C99-(I8+I9),0) -> 38277.985 | J10: =MAX(Inputs!C99-(J8+J9),0) -> 0 | K10: =MAX(Inputs!C99-(K8+K9),0) -> 0 | L10: =MAX(Inputs!C99-(L8+L9),0) -> 0 | M10: =MAX(Inputs!C99-(M8+M9),0) -> 0 | N10: =MAX(Inputs!C99-(N8+N9),0) -> 0 | O10: =MAX(Inputs!C99-(O8+O9),0) -> 0 | P10: =MAX(Inputs!C99-(P8+P9),0) -> 0 | Q10: =MAX(Inputs!C99-(Q8+Q9),0) -> 0 | R10: =MAX(Inputs!C99-(R8+R9),0) -> 0 | S10: =MAX(Inputs!C99-(S8+S9),0) -> 0 | T10: =MAX(Inputs!C99-(T8+T9),0) -> 0 | U10: =MAX(Inputs!C99-(U8+U9),0) -> 0 | V10: =MAX(Inputs!C99-(V8+V9),0) -> 0 | W10: =MAX(Inputs!C99-(W8+W9),0) -> 0 | X10: =MAX(Inputs!C99-(X8+X9),0) -> 0 | Y10: =MAX(Inputs!C99-(Y8+Y9),0) -> 0 | Z10: =MAX(Inputs!C99-(Z8+Z9),0) -> 0 | AA10: =MAX(Inputs!C99-(AA8+AA9),0) -> 0 | AB10: =MAX(Inputs!C99-(AB8+AB9),0) -> 0 | AC10: =MAX(Inputs!C99-(AC8+AC9),0) -> 0 | AD10: =MAX(Inputs!C99-(AD8+AD9),0) -> 0 | AE10: =MAX(Inputs!C99-(AE8+AE9),0) -> 0 | AF10: =MAX(Inputs!C99-(AF8+AF9),0) -> 0 | AG10: =MAX(Inputs!C99-(AG8+AG9),0) -> 0 | AH10: =MAX(Inputs!C99-(AH8+AH9),0) -> 0 | AI10: =MAX(Inputs!C99-(AI8+AI9),0) -> 0 | AJ10: =MAX(Inputs!C99-(AJ8+AJ9),0) -> 0 | AK10: =MAX(Inputs!C99-(AK8+AK9),0) -> 0 | AL10: =MAX(Inputs!C99-(AL8+AL9),0) -> 0 | AM10: =MAX(Inputs!C99-(AM8+AM9),0) -> 0
A11: Equity draw | B11: ZAR'000 | C11: Required funding x equity share | D11: =D10*Inputs!C93 -> 45956.337 | E11: =E10*Inputs!C93 -> 64821.845 | F11: =F10*Inputs!C93 -> 116872.4 | G11: =G10*Inputs!C93 -> 114536.19 | H11: =H10*Inputs!C93 -> 90423.49 | I11: =I10*Inputs!C93 -> 38277.985 | J11: =J10*Inputs!C93 -> 0 | K11: =K10*Inputs!C93 -> 0 | L11: =L10*Inputs!C93 -> 0 | M11: =M10*Inputs!C93 -> 0 | N11: =N10*Inputs!C93 -> 0 | O11: =O10*Inputs!C93 -> 0 | P11: =P10*Inputs!C93 -> 0 | Q11: =Q10*Inputs!C93 -> 0 | R11: =R10*Inputs!C93 -> 0 | S11: =S10*Inputs!C93 -> 0 | T11: =T10*Inputs!C93 -> 0 | U11: =U10*Inputs!C93 -> 0 | V11: =V10*Inputs!C93 -> 0 | W11: =W10*Inputs!C93 -> 0 | X11: =X10*Inputs!C93 -> 0 | Y11: =Y10*Inputs!C93 -> 0 | Z11: =Z10*Inputs!C93 -> 0 | AA11: =AA10*Inputs!C93 -> 0 | AB11: =AB10*Inputs!C93 -> 0 | AC11: =AC10*Inputs!C93 -> 0 | AD11: =AD10*Inputs!C93 -> 0 | AE11: =AE10*Inputs!C93 -> 0 | AF11: =AF10*Inputs!C93 -> 0 | AG11: =AG10*Inputs!C93 -> 0 | AH11: =AH10*Inputs!C93 -> 0 | AI11: =AI10*Inputs!C93 -> 0 | AJ11: =AJ10*Inputs!C93 -> 0 | AK11: =AK10*Inputs!C93 -> 0 | AL11: =AL10*Inputs!C93 -> 0 | AM11: =AM10*Inputs!C93 -> 0
A12: Senior debt gross draw | B12: ZAR'000 | C12: Required funding x debt share grossed up for fee | D12: =IF(Inputs!C94=0,0,(D10*Inputs!C94)/(1-Inputs!C98)) -> 0 | E12: =IF(Inputs!C94=0,0,(E10*Inputs!C94)/(1-Inputs!C98)) -> 0 | F12: =IF(Inputs!C94=0,0,(F10*Inputs!C94)/(1-Inputs!C98)) -> 0 | G12: =IF(Inputs!C94=0,0,(G10*Inputs!C94)/(1-Inputs!C98)) -> 0 | H12: =IF(Inputs!C94=0,0,(H10*Inputs!C94)/(1-Inputs!C98)) -> 0 | I12: =IF(Inputs!C94=0,0,(I10*Inputs!C94)/(1-Inputs!C98)) -> 0 | J12: =IF(Inputs!C94=0,0,(J10*Inputs!C94)/(1-Inputs!C98)) -> 0 | K12: =IF(Inputs!C94=0,0,(K10*Inputs!C94)/(1-Inputs!C98)) -> 0 | L12: =IF(Inputs!C94=0,0,(L10*Inputs!C94)/(1-Inputs!C98)) -> 0 | M12: =IF(Inputs!C94=0,0,(M10*Inputs!C94)/(1-Inputs!C98)) -> 0 | N12: =IF(Inputs!C94=0,0,(N10*Inputs!C94)/(1-Inputs!C98)) -> 0 | O12: =IF(Inputs!C94=0,0,(O10*Inputs!C94)/(1-Inputs!C98)) -> 0 | P12: =IF(Inputs!C94=0,0,(P10*Inputs!C94)/(1-Inputs!C98)) -> 0 | Q12: =IF(Inputs!C94=0,0,(Q10*Inputs!C94)/(1-Inputs!C98)) -> 0 | R12: =IF(Inputs!C94=0,0,(R10*Inputs!C94)/(1-Inputs!C98)) -> 0 | S12: =IF(Inputs!C94=0,0,(S10*Inputs!C94)/(1-Inputs!C98)) -> 0 | T12: =IF(Inputs!C94=0,0,(T10*Inputs!C94)/(1-Inputs!C98)) -> 0 | U12: =IF(Inputs!C94=0,0,(U10*Inputs!C94)/(1-Inputs!C98)) -> 0 | V12: =IF(Inputs!C94=0,0,(V10*Inputs!C94)/(1-Inputs!C98)) -> 0 | W12: =IF(Inputs!C94=0,0,(W10*Inputs!C94)/(1-Inputs!C98)) -> 0 | X12: =IF(Inputs!C94=0,0,(X10*Inputs!C94)/(1-Inputs!C98)) -> 0 | Y12: =IF(Inputs!C94=0,0,(Y10*Inputs!C94)/(1-Inputs!C98)) -> 0 | Z12: =IF(Inputs!C94=0,0,(Z10*Inputs!C94)/(1-Inputs!C98)) -> 0 | AA12: =IF(Inputs!C94=0,0,(AA10*Inputs!C94)/(1-Inputs!C98)) -> 0 | AB12: =IF(Inputs!C94=0,0,(AB10*Inputs!C94)/(1-Inputs!C98)) -> 0 | AC12: =IF(Inputs!C94=0,0,(AC10*Inputs!C94)/(1-Inputs!C98)) -> 0 | AD12: =IF(Inputs!C94=0,0,(AD10*Inputs!C94)/(1-Inputs!C98)) -> 0 | AE12: =IF(Inputs!C94=0,0,(AE10*Inputs!C94)/(1-Inputs!C98)) -> 0 | AF12: =IF(Inputs!C94=0,0,(AF10*Inputs!C94)/(1-Inputs!C98)) -> 0 | AG12: =IF(Inputs!C94=0,0,(AG10*Inputs!C94)/(1-Inputs!C98)) -> 0 | AH12: =IF(Inputs!C94=0,0,(AH10*Inputs!C94)/(1-Inputs!C98)) -> 0 | AI12: =IF(Inputs!C94=0,0,(AI10*Inputs!C94)/(1-Inputs!C98)) -> 0 | AJ12: =IF(Inputs!C94=0,0,(AJ10*Inputs!C94)/(1-Inputs!C98)) -> 0 | AK12: =IF(Inputs!C94=0,0,(AK10*Inputs!C94)/(1-Inputs!C98)) -> 0 | AL12: =IF(Inputs!C94=0,0,(AL10*Inputs!C94)/(1-Inputs!C98)) -> 0 | AM12: =IF(Inputs!C94=0,0,(AM10*Inputs!C94)/(1-Inputs!C98)) -> 0
A13: Arrangement fee | B13: ZAR'000 | C13: Gross debt draw x fee | D13: =D12*Inputs!C98 -> 0 | E13: =E12*Inputs!C98 -> 0 | F13: =F12*Inputs!C98 -> 0 | G13: =G12*Inputs!C98 -> 0 | H13: =H12*Inputs!C98 -> 0 | I13: =I12*Inputs!C98 -> 0 | J13: =J12*Inputs!C98 -> 0 | K13: =K12*Inputs!C98 -> 0 | L13: =L12*Inputs!C98 -> 0 | M13: =M12*Inputs!C98 -> 0 | N13: =N12*Inputs!C98 -> 0 | O13: =O12*Inputs!C98 -> 0 | P13: =P12*Inputs!C98 -> 0 | Q13: =Q12*Inputs!C98 -> 0 | R13: =R12*Inputs!C98 -> 0 | S13: =S12*Inputs!C98 -> 0 | T13: =T12*Inputs!C98 -> 0 | U13: =U12*Inputs!C98 -> 0 | V13: =V12*Inputs!C98 -> 0 | W13: =W12*Inputs!C98 -> 0 | X13: =X12*Inputs!C98 -> 0 | Y13: =Y12*Inputs!C98 -> 0 | Z13: =Z12*Inputs!C98 -> 0 | AA13: =AA12*Inputs!C98 -> 0 | AB13: =AB12*Inputs!C98 -> 0 | AC13: =AC12*Inputs!C98 -> 0 | AD13: =AD12*Inputs!C98 -> 0 | AE13: =AE12*Inputs!C98 -> 0 | AF13: =AF12*Inputs!C98 -> 0 | AG13: =AG12*Inputs!C98 -> 0 | AH13: =AH12*Inputs!C98 -> 0 | AI13: =AI12*Inputs!C98 -> 0 | AJ13: =AJ12*Inputs!C98 -> 0 | AK13: =AK12*Inputs!C98 -> 0 | AL13: =AL12*Inputs!C98 -> 0 | AM13: =AM12*Inputs!C98 -> 0
A14: Net external funding input | B14: ZAR'000 | C14: What actually lands as cash | D14: =D11+D12-D13 -> 45956.337 | E14: =E11+E12-E13 -> 64821.845 | F14: =F11+F12-F13 -> 116872.4 | G14: =G11+G12-G13 -> 114536.19 | H14: =H11+H12-H13 -> 90423.49 | I14: =I11+I12-I13 -> 38277.985 | J14: =J11+J12-J13 -> 0 | K14: =K11+K12-K13 -> 0 | ... AM14: =AM11+AM12-AM13 -> 0
A15: Closing cash after funding | B15: ZAR'000 | C15: Cash carried forward | D15: =D8+D9+D14 -> 0 | E15: =E8+E9+E14 -> 0 | F15: =F8+F9+F14 -> 0 | G15: =G8+G9+G14 -> 0 | H15: =H8+H9+H14 -> 0 | I15: =I8+I9+I14 -> 0 | J15: =J8+J9+J14 -> 13432.378 | K15: =K8+K9+K14 -> 29503.851 | ... AM15: =AM8+AM9+AM14 -> 589548.42
A16: Cumulative burn before funding | B16: ZAR'000 | C16: Tracks funding need before financing | D16: =D9 -> -45956.337 | E16: =D16+E9 -> -110778.18 | F16: =E16+F9 -> -227650.58 | G16: =F16+G9 -> -342186.78 | H16: =G16+H9 -> -432610.27 | I16: =H16+I9 -> -470888.25 | J16: =I16+J9 -> -457455.87 | K16: =J16+K9 -> -441384.4 | L16: =K16+L9 -> -423277.99 | ... AM16: =AL16+AM9 -> 118660.17
A17: Peak funding required | B17: ZAR'000 | C17: Running peak of cumulative burn | D17: =MAX(0,-D16) -> 45956.337 | E17: =MAX(D17,-E16) -> 110778.18 | F17: =MAX(E17,-F16) -> 227650.58 | G17: =MAX(F17,-G16) -> 342186.78 | H17: =MAX(G17,-H16) -> 432610.27 | I17: =MAX(H17,-I16) -> 470888.25 | J17: =MAX(I17,-J16) -> 470888.25 | K17: =MAX(J17,-K16) -> 470888.25 | L17: =MAX(K17,-L16) -> 470888.25 | ... AM17: =MAX(AL17,-AM16) -> 470888.25
A18: Cumulative equity drawn | B18: ZAR'000 | C18: Running total | D18: =D11 -> 45956.337 | E18: =D18+E11 -> 110778.18 | F18: =E18+F11 -> 227650.58 | G18: =F18+G11 -> 342186.78 | H18: =G18+H11 -> 432610.27 | I18: =H18+I11 -> 470888.25 | J18: =I18+J11 -> 470888.25 | K18: =J18+K11 -> 470888.25 | L18: =K18+L11 -> 470888.25 | ... AM18: =AL18+AM11 -> 470888.25
A19: Cumulative senior debt drawn | B19: ZAR'000 | C19: Running total | D19: =D12 -> 0 | E19: =D19+E12 -> 0 | F19: =E19+F12 -> 0 | G19: =F19+G12 -> 0 | H19: =G19+H12 -> 0 | I19: =H19+I12 -> 0 | J19: =I19+J12 -> 0 | K19: =J19+K12 -> 0 | L19: =K19+L12 -> 0 | ... AM19: =AL19+AM12 -> 0

Sheet Debt_Schedule
A1: Debt_Schedule | Optional monthly senior debt amortisation
A2: Schedule is formula-driven. Default workbook assumption = 0% debt / 100% equity, but the schedule activates automatically if debt share is changed on Inputs.
A4: Metric | B4: Unit | C4: Notes
D5: =Inputs!C5 -> 46204 | E5: =EDATE(D5,1) -> 46235 | F5: =EDATE(E5,1) -> 46266 | G5: =EDATE(F5,1) -> 46296 | H5: =EDATE(G5,1) -> 46327 | I5: =EDATE(H5,1) -> 46357 | J5: =EDATE(I5,1) -> 46388 | K5: =EDATE(J5,1) -> 46419 | L5: =EDATE(K5,1) -> 46447 | ... BK5: =EDATE(BJ5,1) -> 48000
D6: =DAY(EOMONTH(D5,0)) -> 31 | E6: =DAY(EOMONTH(E5,0)) -> 31 | F6: =DAY(EOMONTH(F5,0)) -> 30 | G6: =DAY(EOMONTH(G5,0)) -> 31 | H6: =DAY(EOMONTH(H5,0)) -> 30 | I6: =DAY(EOMONTH(I5,0)) -> 31 | J6: =DAY(EOMONTH(J5,0)) -> 31 | K6: =DAY(EOMONTH(K5,0)) -> 28 | ... BK6: =DAY(EOMONTH(BK5,0)) -> 30
A8: New gross debt draw | B8: ZAR'000 | C8: Linked from Funding_36M first 36 months; 0 thereafter | D8: =Funding_36M!D12 -> 0 | E8: =Funding_36M!E12 -> 0 | F8: =Funding_36M!F12 -> 0 | G8: =Funding_36M!G12 -> 0 | H8: =Funding_36M!H12 -> 0 | I8: =Funding_36M!I12 -> 0 | J8: =Funding_36M!J12 -> 0 | K8: =Funding_36M!K12 -> 0 | ... AM8: =Funding_36M!AM12 -> 0 | AN8: =0 -> 0 | AO8: =0 -> 0 | AP8: =0 -> 0 | AQ8: =0 -> 0 | AR8: =0 -> 0 | AS8: =0 -> 0 | AT8: =0 -> 0 | AU8: =0 -> 0 | ... BK8: =0 -> 0
A9: Opening balance | B9: ZAR'000 | C9: Prior month closing balance | D9: =0 -> 0 | E9: =D13 -> 0 | F9: =E13 -> 0 | G9: =F13 -> 0 | H9: =G13 -> 0 | I9: =H13 -> 0 | J9: =I13 -> 0 | K9: =J13 -> 0 | L9: =K13 -> 0 | ... BK9: =BJ13 -> 0
A10: Interest accrued | B10: ZAR'000 | C10: Opening balance × monthly rate | D10: =D9*Inputs!C95/12 -> 0 | E10: =E9*Inputs!C95/12 -> 0 | F10: =F9*Inputs!C95/12 -> 0 | G10: =G9*Inputs!C95/12 -> 0 | H10: =H9*Inputs!C95/12 -> 0 | I10: =I9*Inputs!C95/12 -> 0 | J10: =J9*Inputs!C95/12 -> 0 | K10: =K9*Inputs!C95/12 -> 0 | L10: =L9*Inputs!C95/12 -> 0 | M10: =M9*Inputs!C95/12 -> 0 | N10: =N9*Inputs!C95/12 -> 0 | O10: =O9*Inputs!C95/12 -> 0 | P10: =P9*Inputs!C95/12 -> 0 | Q10: =Q9*Inputs!C95/12 -> 0 | R10: =R9*Inputs!C95/12 -> 0 | S10: =S9*Inputs!C95/12 -> 0 | T10: =T9*Inputs!C95/12 -> 0 | U10: =U9*Inputs!C95/12 -> 0 | V10: =V9*Inputs!C95/12 -> 0 | W10: =W9*Inputs!C95/12 -> 0 | X10: =X9*Inputs!C95/12 -> 0 | Y10: =Y9*Inputs!C95/12 -> 0 | Z10: =Z9*Inputs!C95/12 -> 0 | AA10: =AA9*Inputs!C95/12 -> 0 | AB10: =AB9*Inputs!C95/12 -> 0 | AC10: =AC9*Inputs!C95/12 -> 0 | AD10: =AD9*Inputs!C95/12 -> 0 | AE10: =AE9*Inputs!C95/12 -> 0 | AF10: =AF9*Inputs!C95/12 -> 0 | AG10: =AG9*Inputs!C95/12 -> 0 | AH10: =AH9*Inputs!C95/12 -> 0 | AI10: =AI9*Inputs!C95/12 -> 0 | AJ10: =AJ9*Inputs!C95/12 -> 0 | AK10: =AK9*Inputs!C95/12 -> 0 | AL10: =AL9*Inputs!C95/12 -> 0 | AM10: =AM9*Inputs!C95/12 -> 0 | AN10: =AN9*Inputs!C95/12 -> 0 | AO10: =AO9*Inputs!C95/12 -> 0 | AP10: =AP9*Inputs!C95/12 -> 0 | AQ10: =AQ9*Inputs!C95/12 -> 0 | AR10: =AR9*Inputs!C95/12 -> 0 | AS10: =AS9*Inputs!C95/12 -> 0 | AT10: =AT9*Inputs!C95/12 -> 0 | AU10: =AU9*Inputs!C95/12 -> 0 | AV10: =AV9*Inputs!C95/12 -> 0 | AW10: =AW9*Inputs!C95/12 -> 0 | AX10: =AX9*Inputs!C95/12 -> 0 | AY10: =AY9*Inputs!C95/12 -> 0 | AZ10: =AZ9*Inputs!C95/12 -> 0 | BA10: =BA9*Inputs!C95/12 -> 0 | BB10: =BB9*Inputs!C95/12 -> 0 | BC10: =BC9*Inputs!C95/12 -> 0 | BD10: =BD9*Inputs!C95/12 -> 0 | BE10: =BE9*Inputs!C95/12 -> 0 | BF10: =BF9*Inputs!C95/12 -> 0 | BG10: =BG9*Inputs!C95/12 -> 0 | BH10: =BH9*Inputs!C95/12 -> 0 | BI10: =BI9*Inputs!C95/12 -> 0 | BJ10: =BJ9*Inputs!C95/12 -> 0 | BK10: =BK9*Inputs!C95/12 -> 0
A11: Scheduled principal | B11: ZAR'000 | C11: Straight-line after grace period, capped by available balance | D11: =IF(1<=Inputs!C97,0,MIN(MAX(D9+D8+D10,0),MAX(D14/MAX(Inputs!C96-Inputs!C97,1),0))) -> 0 | E11: =IF(2<=Inputs!C97,0,MIN(MAX(E9+E8+E10,0),MAX(E14/MAX(Inputs!C96-Inputs!C97,1),0))) -> 0 | F11: =IF(3<=Inputs!C97,0,MIN(MAX(F9+F8+F10,0),MAX(F14/MAX(Inputs!C96-Inputs!C97,1),0))) -> 0 | G11: =IF(4<=Inputs!C97,0,MIN(MAX(G9+G8+G10,0),MAX(G14/MAX(Inputs!C96-Inputs!C97,1),0))) -> 0 | H11: =IF(5<=Inputs!C97,0,MIN(MAX(H9+H8+H10,0),MAX(H14/MAX(Inputs!C96-Inputs!C97,1),0))) -> 0 | I11: =IF(6<=Inputs!C97,0,MIN(MAX(I9+I8+I10,0),MAX(I14/MAX(Inputs!C96-Inputs!C97,1),0))) -> 0 | J11: =IF(7<=Inputs!C97,0,MIN(MAX(J9+J8+J10,0),MAX(J14/MAX(Inputs!C96-Inputs!C97,1),0))) -> 0 | K11: =IF(8<=Inputs!C97,0,MIN(MAX(K9+K8+K10,0),MAX(K14/MAX(Inputs!C96-Inputs!C97,1),0))) -> 0 | L11: =IF(9<=Inputs!C97,0,MIN(MAX(L9+L8+L10,0),MAX(L14/MAX(Inputs!C96-Inputs!C97,1),0))) -> 0 | M11: =IF(10<=Inputs!C97,0,MIN(MAX(M9+M8+M10,0),MAX(M14/MAX(Inputs!C96-Inputs!C97,1),0))) -> 0 | N11: =IF(11<=Inputs!C97,0,MIN(MAX(N9+N8+N10,0),MAX(N14/MAX(Inputs!C96-Inputs!C97,1),0))) -> 0 | O11: =IF(12<=Inputs!C97,0,MIN(MAX(O9+O8+O10,0),MAX(O14/MAX(Inputs!C96-Inputs!C97,1),0))) -> 0 | P11: =IF(13<=Inputs!C97,0,MIN(MAX(P9+P8+P10,0),MAX(P14/MAX(Inputs!C96-Inputs!C97,1),0))) -> 0 | Q11: =IF(14<=Inputs!C97,0,MIN(MAX(Q9+Q8+Q10,0),MAX(Q14/MAX(Inputs!C96-Inputs!C97,1),0))) -> 0 | R11: =IF(15<=Inputs!C97,0,MIN(MAX(R9+R8+R10,0),MAX(R14/MAX(Inputs!C96-Inputs!C97,1),0))) -> 0 | S11: =IF(16<=Inputs!C97,0,MIN(MAX(S9+S8+S10,0),MAX(S14/MAX(Inputs!C96-Inputs!C97,1),0))) -> 0 | T11: =IF(17<=Inputs!C97,0,MIN(MAX(T9+T8+T10,0),MAX(T14/MAX(Inputs!C96-Inputs!C97,1),0))) -> 0 | U11: =IF(18<=Inputs!C97,0,MIN(MAX(U9+U8+U10,0),MAX(U14/MAX(Inputs!C96-Inputs!C97,1),0))) -> 0 | V11: =IF(19<=Inputs!C97,0,MIN(MAX(V9+V8+V10,0),MAX(V14/MAX(Inputs!C96-Inputs!C97,1),0))) -> 0 | W11: =IF(20<=Inputs!C97,0,MIN(MAX(W9+W8+W10,0),MAX(W14/MAX(Inputs!C96-Inputs!C97,1),0))) -> 0 | X11: =IF(21<=Inputs!C97,0,MIN(MAX(X9+X8+X10,0),MAX(X14/MAX(Inputs!C96-Inputs!C97,1),0))) -> 0 | Y11: =IF(22<=Inputs!C97,0,MIN(MAX(Y9+Y8+Y10,0),MAX(Y14/MAX(Inputs!C96-Inputs!C97,1),0))) -> 0 | Z11: =IF(23<=Inputs!C97,0,MIN(MAX(Z9+Z8+Z10,0),MAX(Z14/MAX(Inputs!C96-Inputs!C97,1),0))) -> 0 | AA11: =IF(24<=Inputs!C97,0,MIN(MAX(AA9+AA8+AA10,0),MAX(AA14/MAX(Inputs!C96-Inputs!C97,1),0))) -> 0 | AB11: =IF(25<=Inputs!C97,0,MIN(MAX(AB9+AB8+AB10,0),MAX(AB14/MAX(Inputs!C96-Inputs!C97,1),0))) -> 0 | AC11: =IF(26<=Inputs!C97,0,MIN(MAX(AC9+AC8+AC10,0),MAX(AC14/MAX(Inputs!C96-Inputs!C97,1),0))) -> 0 | AD11: =IF(27<=Inputs!C97,0,MIN(MAX(AD9+AD8+AD10,0),MAX(AD14/MAX(Inputs!C96-Inputs!C97,1),0))) -> 0 | AE11: =IF(28<=Inputs!C97,0,MIN(MAX(AE9+AE8+AE10,0),MAX(AE14/MAX(Inputs!C96-Inputs!C97,1),0))) -> 0 | AF11: =IF(29<=Inputs!C97,0,MIN(MAX(AF9+AF8+AF10,0),MAX(AF14/MAX(Inputs!C96-Inputs!C97,1),0))) -> 0 | AG11: =IF(30<=Inputs!C97,0,MIN(MAX(AG9+AG8+AG10,0),MAX(AG14/MAX(Inputs!C96-Inputs!C97,1),0))) -> 0 | AH11: =IF(31<=Inputs!C97,0,MIN(MAX(AH9+AH8+AH10,0),MAX(AH14/MAX(Inputs!C96-Inputs!C97,1),0))) -> 0 | AI11: =IF(32<=Inputs!C97,0,MIN(MAX(AI9+AI8+AI10,0),MAX(AI14/MAX(Inputs!C96-Inputs!C97,1),0))) -> 0 | AJ11: =IF(33<=Inputs!C97,0,MIN(MAX(AJ9+AJ8+AJ10,0),MAX(AJ14/MAX(Inputs!C96-Inputs!C97,1),0))) -> 0 | AK11: =IF(34<=Inputs!C97,0,MIN(MAX(AK9+AK8+AK10,0),MAX(AK14/MAX(Inputs!C96-Inputs!C97,1),0))) -> 0 | AL11: =IF(35<=Inputs!C97,0,MIN(MAX(AL9+AL8+AL10,0),MAX(AL14/MAX(Inputs!C96-Inputs!C97,1),0))) -> 0 | AM11: =IF(36<=Inputs!C97,0,MIN(MAX(AM9+AM8+AM10,0),MAX(AM14/MAX(Inputs!C96-Inputs!C97,1),0))) -> 0 | AN11: =IF(37<=Inputs!C97,0,MIN(MAX(AN9+AN8+AN10,0),MAX(AN14/MAX(Inputs!C96-Inputs!C97,1),0))) -> 0 | AO11: =IF(38<=Inputs!C97,0,MIN(MAX(AO9+AO8+AO10,0),MAX(AO14/MAX(Inputs!C96-Inputs!C97,1),0))) -> 0 | AP11: =IF(39<=Inputs!C97,0,MIN(MAX(AP9+AP8+AP10,0),MAX(AP14/MAX(Inputs!C96-Inputs!C97,1),0))) -> 0 | AQ11: =IF(40<=Inputs!C97,0,MIN(MAX(AQ9+AQ8+AQ10,0),MAX(AQ14/MAX(Inputs!C96-Inputs!C97,1),0))) -> 0 | AR11: =IF(41<=Inputs!C97,0,MIN(MAX(AR9+AR8+AR10,0),MAX(AR14/MAX(Inputs!C96-Inputs!C97,1),0))) -> 0 | AS11: =IF(42<=Inputs!C97,0,MIN(MAX(AS9+AS8+AS10,0),MAX(AS14/MAX(Inputs!C96-Inputs!C97,1),0))) -> 0 | AT11: =IF(43<=Inputs!C97,0,MIN(MAX(AT9+AT8+AT10,0),MAX(AT14/MAX(Inputs!C96-Inputs!C97,1),0))) -> 0 | AU11: =IF(44<=Inputs!C97,0,MIN(MAX(AU9+AU8+AU10,0),MAX(AU14/MAX(Inputs!C96-Inputs!C97,1),0))) -> 0 | AV11: =IF(45<=Inputs!C97,0,MIN(MAX(AV9+AV8+AV10,0),MAX(AV14/MAX(Inputs!C96-Inputs!C97,1),0))) -> 0 | AW11: =IF(46<=Inputs!C97,0,MIN(MAX(AW9+AW8+AW10,0),MAX(AW14/MAX(Inputs!C96-Inputs!C97,1),0))) -> 0 | AX11: =IF(47<=Inputs!C97,0,MIN(MAX(AX9+AX8+AX10,0),MAX(AX14/MAX(Inputs!C96-Inputs!C97,1),0))) -> 0 | AY11: =IF(48<=Inputs!C97,0,MIN(MAX(AY9+AY8+AY10,0),MAX(AY14/MAX(Inputs!C96-Inputs!C97,1),0))) -> 0 | AZ11: =IF(49<=Inputs!C97,0,MIN(MAX(AZ9+AZ8+AZ10,0),MAX(AZ14/MAX(Inputs!C96-Inputs!C97,1),0))) -> 0 | BA11: =IF(50<=Inputs!C97,0,MIN(MAX(BA9+BA8+BA10,0),MAX(BA14/MAX(Inputs!C96-Inputs!C97,1),0))) -> 0 | BB11: =IF(51<=Inputs!C97,0,MIN(MAX(BB9+BB8+BB10,0),MAX(BB14/MAX(Inputs!C96-Inputs!C97,1),0))) -> 0 | BC11: =IF(52<=Inputs!C97,0,MIN(MAX(BC9+BC8+BC10,0),MAX(BC14/MAX(Inputs!C96-Inputs!C97,1),0))) -> 0 | BD11: =IF(53<=Inputs!C97,0,MIN(MAX(BD9+BD8+BD10,0),MAX(BD14/MAX(Inputs!C96-Inputs!C97,1),0))) -> 0 | BE11: =IF(54<=Inputs!C97,0,MIN(MAX(BE9+BE8+BE10,0),MAX(BE14/MAX(Inputs!C96-Inputs!C97,1),0))) -> 0 | BF11: =IF(55<=Inputs!C97,0,MIN(MAX(BF9+BF8+BF10,0),MAX(BF14/MAX(Inputs!C96-Inputs!C97,1),0))) -> 0 | BG11: =IF(56<=Inputs!C97,0,MIN(MAX(BG9+BG8+BG10,0),MAX(BG14/MAX(Inputs!C96-Inputs!C97,1),0))) -> 0 | BH11: =IF(57<=Inputs!C97,0,MIN(MAX(BH9+BH8+BH10,0),MAX(BH14/MAX(Inputs!C96-Inputs!C97,1),0))) -> 0 | BI11: =IF(58<=Inputs!C97,0,MIN(MAX(BI9+BI8+BI10,0),MAX(BI14/MAX(Inputs!C96-Inputs!C97,1),0))) -> 0 | BJ11: =IF(59<=Inputs!C97,0,MIN(MAX(BJ9+BJ8+BJ10,0),MAX(BJ14/MAX(Inputs!C96-Inputs!C97,1),0))) -> 0 | BK11: =IF(60<=Inputs!C97,0,MIN(MAX(BK9+BK8+BK10,0),MAX(BK14/MAX(Inputs!C96-Inputs!C97,1),0))) -> 0
A12: Debt service cash | B12: ZAR'000 | C12: Interest + principal | D12: =D10+D11 -> 0 | E12: =E10+E11 -> 0 | F12: =F10+F11 -> 0 | G12: =G10+G11 -> 0 | H12: =H10+H11 -> 0 | I12: =I10+I11 -> 0 | J12: =J10+J11 -> 0 | K12: =K10+K11 -> 0 | ... BK12: =BK10+BK11 -> 0
A13: Closing balance | B13: ZAR'000 | C13: Opening + draws + interest - principal | D13: =MAX(D9+D8+D10-D11,0) -> 0 | E13: =MAX(E9+E8+E10-E11,0) -> 0 | F13: =MAX(F9+F8+F10-F11,0) -> 0 | G13: =MAX(G9+G8+G10-G11,0) -> 0 | H13: =MAX(H9+H8+H10-H11,0) -> 0 | I13: =MAX(I9+I8+I10-I11,0) -> 0 | J13: =MAX(J9+J8+J10-J11,0) -> 0 | K13: =MAX(K9+K8+K10-K11,0) -> 0 | ... BK13: =MAX(BK9+BK8+BK10-BK11,0) -> 0
A14: Cumulative draws | B14: ZAR'000 | C14: Running total | D14: =D8 -> 0 | E14: =D14+E8 -> 0 | F14: =E14+F8 -> 0 | G14: =F14+G8 -> 0 | H14: =G14+H8 -> 0 | I14: =H14+I8 -> 0 | J14: =I14+J8 -> 0 | K14: =J14+K8 -> 0 | L14: =K14+L8 -> 0 | ... BK14: =BJ14+BK8 -> 0
A15: Cumulative interest | B15: ZAR'000 | C15: Running total | D15: =D10 -> 0 | E15: =D15+E10 -> 0 | F15: =E15+F10 -> 0 | G15: =F15+G10 -> 0 | H15: =G15+H10 -> 0 | I15: =H15+I10 -> 0 | J15: =I15+J10 -> 0 | K15: =J15+K10 -> 0 | L15: =K15+L10 -> 0 | ... BK15: =BJ15+BK10 -> 0
A16: Cumulative debt service | B16: ZAR'000 | C16: Running total | D16: =D12 -> 0 | E16: =D16+E12 -> 0 | F16: =E16+F12 -> 0 | G16: =F16+G12 -> 0 | H16: =G16+H12 -> 0 | I16: =H16+I12 -> 0 | J16: =I16+J12 -> 0 | K16: =J16+K12 -> 0 | L16: =K16+L12 -> 0 | ... BK16: =BJ16+BK12 -> 0
A17: DSCR (base revenue) | B17: x | C17: (Revenue base - opex) / debt service | D17: =IF(D12=0,"",MAX((Revenue_36M!D20-Opex_36M!D28)/D12,0)) | E17: =IF(E12=0,"",MAX((Revenue_36M!E20-Opex_36M!E28)/E12,0)) | F17: =IF(F12=0,"",MAX((Revenue_36M!F20-Opex_36M!F28)/F12,0)) | G17: =IF(G12=0,"",MAX((Revenue_36M!G20-Opex_36M!G28)/G12,0)) | H17: =IF(H12=0,"",MAX((Revenue_36M!H20-Opex_36M!H28)/H12,0)) | I17: =IF(I12=0,"",MAX((Revenue_36M!I20-Opex_36M!I28)/I12,0)) | J17: =IF(J12=0,"",MAX((Revenue_36M!J20-Opex_36M!J28)/J12,0)) | K17: =IF(K12=0,"",MAX((Revenue_36M!K20-Opex_36M!K28)/K12,0)) | ... AM17: =IF(AM12=0,"",MAX((Revenue_36M!AM20-Opex_36M!AM28)/AM12,0)) | AN17: ="" | AO17: ="" | AP17: ="" | AQ17: ="" | AR17: ="" | AS17: ="" | AT17: ="" | AU17: ="" | ... BK17: =""
A18: DSCR (upside revenue) | B18: x | C18: (Revenue incl optionality - opex) / debt service | D18: =IF(D12=0,"",MAX((Revenue_36M!D21-Opex_36M!D28)/D12,0)) | E18: =IF(E12=0,"",MAX((Revenue_36M!E21-Opex_36M!E28)/E12,0)) | F18: =IF(F12=0,"",MAX((Revenue_36M!F21-Opex_36M!F28)/F12,0)) | G18: =IF(G12=0,"",MAX((Revenue_36M!G21-Opex_36M!G28)/G12,0)) | H18: =IF(H12=0,"",MAX((Revenue_36M!H21-Opex_36M!H28)/H12,0)) | I18: =IF(I12=0,"",MAX((Revenue_36M!I21-Opex_36M!I28)/I12,0)) | J18: =IF(J12=0,"",MAX((Revenue_36M!J21-Opex_36M!J28)/J12,0)) | K18: =IF(K12=0,"",MAX((Revenue_36M!K21-Opex_36M!K28)/K12,0)) | ... AM18: =IF(AM12=0,"",MAX((Revenue_36M!AM21-Opex_36M!AM28)/AM12,0)) | AN18: ="" | AO18: ="" | AP18: ="" | AQ18: ="" | AR18: ="" | AS18: ="" | AT18: ="" | AU18: ="" | ... BK18: =""

Sheet Annual_Summary
A1: Annual_Summary | 3-year output summary for the standalone 20MW model
A2: This tab is designed for lender / investor pack extraction: ramp, revenue, EBITDA, capex, funding and cash by year.
A4: Metric | B4: Unit | C4: Year 1 | D4: Year 2 | E4: Year 3 | F4: Notes
A6: Closing gross MW | B6: MW | C6: =AVERAGE(Deployment_36M!D21:O21) -> 13.333333 | D6: =AVERAGE(Deployment_36M!P21:AA21) -> 20 | E6: =AVERAGE(Deployment_36M!AB21:AM21) -> 20 | F6: Uses average deployed MW across the year
A7: Year-end gross MW | B7: MW | C7: =Deployment_36M!O8+Deployment_36M!O9 -> 20 | D7: =Deployment_36M!AA8+Deployment_36M!AA9 -> 20 | E7: =Deployment_36M!AM8+Deployment_36M!AM9 -> 20 | F7: Closing MW at the last month of each year
A8: Year-end Grootvlei MW | B8: MW | C8: =Deployment_36M!O8 -> 15 | D8: =Deployment_36M!AA8 -> 15 | E8: =Deployment_36M!AM8 -> 15 | F8: Closing MW in December of each year
A9: Year-end AMSA MW | B9: MW | C9: =Deployment_36M!O9 -> 5 | D9: =Deployment_36M!AA9 -> 5 | E9: =Deployment_36M!AM9 -> 5 | F9: Closing MW in December of each year
A10: Year-end AMSA solar MW | B10: MW | C10: =Deployment_36M!O10 -> 10 | D10: =Deployment_36M!AA10 -> 10 | E10: =Deployment_36M!AM10 -> 10 | F10: Solar MW available by year-end
A11: BTC mined | B11: BTC | C11: =SUM(Revenue_36M!D16:O16) -> 177.7338 | D11: =SUM(Revenue_36M!P16:AA16) -> 247.36135 | E11: =SUM(Revenue_36M!AB16:AM16) -> 224.26714 | F11: Annual BTC production
A12: Revenue (base case) | B12: ZAR'000 | C12: =SUM(Revenue_36M!D20:O20) -> 246952.8 | D12: =SUM(Revenue_36M!P20:AA20) -> 386487.07 | E12: =SUM(Revenue_36M!AB20:AM20) -> 402944.55 | F12: BTC revenue only
A13: Revenue (incl optionality) | B13: ZAR'000 | C13: =SUM(Revenue_36M!D21:O21) -> 246952.8 | D13: =SUM(Revenue_36M!P21:AA21) -> 386487.07 | E13: =SUM(Revenue_36M!AB21:AM21) -> 402944.55 | F13: BTC + DR + hyperscaler if toggled on
A14: Cash opex | B14: ZAR'000 | C14: =SUM(Opex_36M!D28:O28) -> 111101.93 | D14: =SUM(Opex_36M!P28:AA28) -> 153734.63 | E14: =SUM(Opex_36M!AB28:AM28) -> 147482.06 | F14: Annual cash operating expenditure
A15: EBITDA (base case) | B15: ZAR'000 | C15: =SUM(Opex_36M!D29:O29) -> 135850.87 | D15: =SUM(Opex_36M!P29:AA29) -> 232752.44 | E15: =SUM(Opex_36M!AB29:AM29) -> 255462.49 | F15: Base revenue less opex
A16: EBITDA (incl optionality) | B16: ZAR'000 | C16: =SUM(Opex_36M!D30:O30) -> 135850.87 | D16: =SUM(Opex_36M!P30:AA30) -> 232752.44 | E16: =SUM(Opex_36M!AB30:AM30) -> 255462.49 | F16: Upside revenue less opex
A17: Capex cash spend | B17: ZAR'000 | C17: =SUM(Capex_36M!D52:O52) -> 505405.63 | D17: =SUM(Capex_36M!P52:AA52) -> 0 | E17: =SUM(Capex_36M!AB52:AM52) -> 0 | F17: Annual capital deployment
A18: Unlevered cash flow | B18: ZAR'000 | C18: =SUM(Funding_36M!D9:O9) -> -369554.77 | D18: =SUM(Funding_36M!P9:AA9) -> 232752.44 | E18: =SUM(Funding_36M!AB9:AM9) -> 255462.49 | F18: Base revenue less opex and capex
A19: Equity draw | B19: ZAR'000 | C19: =SUM(Funding_36M!D11:O11) -> 470888.25 | D19: =SUM(Funding_36M!P11:AA11) -> 0 | E19: =SUM(Funding_36M!AB11:AM11) -> 0 | F19: External equity funding drawn
A20: Senior debt draw | B20: ZAR'000 | C20: =SUM(Funding_36M!D12:O12) -> 0 | D20: =SUM(Funding_36M!P12:AA12) -> 0 | E20: =SUM(Funding_36M!AB12:AM12) -> 0 | F20: Debt draw — default is 0 in this model
A21: Year-end cash | B21: ZAR'000 | C21: =Funding_36M!O15 -> 101333.48 | D21: =Funding_36M!AA15 -> 334085.92 | E21: =Funding_36M!AM15 -> 589548.42 | F21: Closing cash in December
A24: Headline metrics
A25: Peak funding required | B25: ZAR'000 | C25: =MAX(Funding_36M!D17:AM17) -> 470888.25 | F25: Maximum external funding before cash turns positive
A26: Total equity required | B26: ZAR'000 | C26: =SUM(Funding_36M!D11:AM11) -> 470888.25 | F26: Cumulative equity draw by month 36
A27: Total senior debt drawn | B27: ZAR'000 | C27: =SUM(Funding_36M!D12:AM12) -> 0 | F27: Cumulative senior debt draw by month 36
A28: Phase 1 capex / peak funding multiple | B28: x | C28: =IF(C25=0,"",SUM(Capex_36M!D52:AM52)/C25) -> 1.0733027 | F28: Phase 1 capex divided by peak funding requirement
