Workbook

Sheet README
A1: BitMach Clean Phase 1 Model (v0.1)
A3: Purpose | B3: Clean rebuild workbook for the Phase 1 proof case (10MW Grootvlei + 10MW AMSA).
A5: • This workbook is deliberately cleaner and narrower than the legacy file.
A6: • It is intended as a defendable starting point for an investor-grade operating engine.
A7: • All currency outputs are in ZAR'000 unless a row explicitly says otherwise.
A8: • Yellow cells are inputs. White cells are formulas. Red bars are section headers.
A9: • Demand response revenue is set to zero by default in the base case, consistent with the management memo that treats it as upside / optionality rather than day-one debt support.
A10: • The default hardware basis is Bitmain S21e XP Hyd using the 2026 Bitmain price list discount indication. Replace with executed commercial terms once finalised.
A11: • The model is phase-1 oriented. Build a separate portfolio layer only after the pilot economics are validated.
A14: Source anchors used to seed the rebuild
A15: 31 Mar 2026 management memo | B15: Phase 1 should begin with 10MW Grootvlei + 10MW AMSA, then scale after proof.
A16: Apr 2026 investor presentation | B16: Phase 1 capex shown at USD32m / R544m and financing stack shown as asset-backed + mezz + equity.
A17: 28 Feb 2026 Bitmain price list | B17: Current Bitmain hydro pricing available for S21e XP Hyd and related models.
A18: 25 Mar 2026 TSI cost estimate | B18: Electrical / instrumentation supply & install quote provides a live BOS reference point.

Sheet Assumptions
A1: Global Assumptions
A3: Annual market and macro drivers
A4: Driver | B4: Unit | C4: 2026 | D4: 2027 | E4: 2028 | F4: 2029 | G4: 2030 | H4: 2031 | I4: 2032 | J4: 2033 | K4: 2034 | L4: 2035
A5: FX (ZAR/USD) | B5: ZAR/USD | C5: 17 | D5: =C5 | E5: =D5 | F5: =E5 | G5: =F5 | H5: =G5 | I5: =H5 | J5: =I5 | K5: =J5 | L5: =K5
A6: BTC price | B6: ZAR'000/BTC | C6: 1500 | D6: =C6*(1+C7) | E6: =D6*(1+D7) | F6: =E6*(1+E7) | G6: =F6*(1+F7) | H6: =G6*(1+G7) | I6: =H6*(1+H7) | J6: =I6*(1+I7) | K6: =J6*(1+J7) | L6: =K6*(1+K7)
A7: BTC price growth | B7: % | C7: 0.2 | D7: =MAX(C7-0.02,0.06) | E7: =MAX(D7-0.02,0.06) | F7: =MAX(E7-0.02,0.06) | G7: =MAX(F7-0.02,0.06) | H7: =MAX(G7-0.02,0.06) | I7: =MAX(H7-0.02,0.06) | J7: =MAX(I7-0.02,0.06) | K7: =MAX(J7-0.02,0.06) | L7: =MAX(K7-0.02,0.06)
A8: Network hash | B8: TH/s | C8: 910000000 | D8: =C8*(1+C9) | E8: =D8*(1+D9) | F8: =E8*(1+E9) | G8: =F8*(1+F9) | H8: =G8*(1+G9) | I8: =H8*(1+H9) | J8: =I8*(1+I9) | K8: =J8*(1+J9) | L8: =K8*(1+K9)
A9: Network hash growth | B9: % | C9: 0.1 | D9: =C9 | E9: =D9 | F9: =E9 | G9: =F9 | H9: =G9 | I9: =H9 | J9: =I9 | K9: =J9 | L9: =K9
A10: Block subsidy | B10: BTC/block | C10: 3.125 | D10: =C10 | E10: =D10/2 | F10: =E10 | G10: =F10 | H10: =G10 | I10: =H10/2 | J10: =I10 | K10: =J10 | L10: =K10
A11: Fee factor on subsidy | B11: % | C11: 0.1 | D11: =C11 | E11: =D11 | F11: =E11 | G11: =F11 | H11: =G11 | I11: =H11 | J11: =I11 | K11: =J11 | L11: =K11
A12: Blocks per day | B12: blocks/day | C12: 144 | D12: =C12 | E12: =D12 | F12: =E12 | G12: =F12 | H12: =G12 | I12: =H12 | J12: =I12 | K12: =J12 | L12: =K12
A13: Days per year | B13: days | C13: 365 | D13: =C13 | E13: =D13 | F13: =E13 | G13: =F13 | H13: =G13 | I13: =H13 | J13: =I13 | K13: =J13 | L13: =K13
A14: Tax rate | B14: % | C14: 0.27 | D14: =C14 | E14: =D14 | F14: =E14 | G14: =F14 | H14: =G14 | I14: =H14 | J14: =I14 | K14: =J14 | L14: =K14
A15: General inflation | B15: % | C15: 0.05 | D15: =C15 | E15: =D15 | F15: =E15 | G15: =F15 | H15: =G15 | I15: =H15 | J15: =I15 | K15: =J15 | L15: =K15
A16: Tariff inflation | B16: % | C16: 0.05 | D16: =C16 | E16: =D16 | F16: =E16 | G16: =F16 | H16: =G16 | I16: =H16 | J16: =I16 | K16: =J16 | L16: =K16
A17: Salary inflation | B17: % | C17: 0.05 | D17: =C17 | E17: =D17 | F17: =E17 | G17: =F17 | H17: =G17 | I17: =H17 | J17: =I17 | K17: =J17 | L17: =K17
A20: Case policy
A21: Base case DR revenue included? | B21: 0
A22: Base case trading premium included? | B22: 0
A23: Strategic upside included? | B23: 0

Sheet Hardware
A1: Hardware & Engineering Inputs
A3: Input | B3: Unit | C3: Value
A4: Chosen miner model | B4: text | C4: Bitmain S21e XP Hyd
A5: Hashrate per miner | B5: TH | C5: 430
A6: Power per miner | B6: W | C6: 5590
A7: Miner price | B7: USD / miner | C7: 7310
A8: Cooling / auxiliary load | B8: % | C8: 0.05
A9: Miner losses / downtime | B9: % | C9: 0.03
A10: Maintenance per miner | B10: ZAR / miner / year | C10: 2000
A11: Electrical + BOS capex | B11: ZAR'000 / MW | C11: 5035
A12: Miner useful life | B12: years | C12: 5
A13: BOS useful life | B13: years | C13: 15
A16: Derived metrics
A17: IT MW available from 1 MW envelope | B17: MW | C17: =1/(1+$C$8)
A18: Miners per gross MW | B18: miners/MW | C18: =(1000000/(1+$C$8))/$C$6
A19: Miner capex per gross MW | B19: ZAR'000/MW | C19: =$C$17*$C$7*Assumptions!C5/1000
A20: Total capex per gross MW | B20: ZAR'000/MW | C20: =$C$18+$C$10

Sheet Site_Assumptions
A1: Phase 1 site assumptions
A3: Driver | B3: Unit | C3: 2026 | D3: 2027 | E3: 2028 | F3: 2029 | G3: 2030 | H3: 2031 | I3: 2032 | J3: 2033 | K3: 2034 | L3: 2035
A4: Grootvlei
A5: MW online | B5: MW | C5: 10 | D5: =C5 | E5: =D5 | F5: =E5 | G5: =F5 | H5: =G5 | I5: =H5 | J5: =I5 | K5: =J5 | L5: =K5
A6: Operating hours/day | B6: hours/day | C6: 16 | D6: =C6 | E6: =D6 | F6: =E6 | G6: =F6 | H6: =G6 | I6: =H6 | J6: =I6 | K6: =J6 | L6: =K6
A7: Uptime | B7: % | C7: 0.95 | D7: =C7 | E7: =D7 | F7: =E7 | G7: =F7 | H7: =G7 | I7: =H7 | J7: =I7 | K7: =J7 | L7: =K7
A8: Blended tariff | B8: R/kWh | C8: 1.2 | D8: =C8*(1+C16) | E8: =D8*(1+D16) | F8: =E8*(1+E16) | G8: =F8*(1+F16) | H8: =G8*(1+G16) | I8: =H8*(1+H16) | J8: =I8*(1+I16) | K8: =J8*(1+J16) | L8: =K8*(1+K16)
A9: Demand response rebate | B9: R/kWh | C9: 0 | D9: =C9 | E9: =D9 | F9: =E9 | G9: =F9 | H9: =G9 | I9: =H9 | J9: =I9 | K9: =J9 | L9: =K9
A10: Demand response hours/day | B10: hours/day | C10: 0 | D10: =C10 | E10: =D10 | F10: =E10 | G10: =F10 | H10: =G10 | I10: =H10 | J10: =I10 | K10: =J10 | L10: =K10
A11: Fixed site opex | B11: ZAR'000 / year | C11: 5000 | D11: =C11*(1+C15) | E11: =D11*(1+D15) | F11: =E11*(1+E15) | G11: =F11*(1+F15) | H11: =G11*(1+G15) | I11: =H11*(1+H15) | J11: =I11*(1+I15) | K11: =J11*(1+J15) | L11: =K11*(1+K15)
A12: Rent | B12: ZAR'000 / year | C12: 0 | D12: =C12*(1+C15) | E12: =D12*(1+D15) | F12: =E12*(1+E15) | G12: =F12*(1+F15) | H12: =G12*(1+G15) | I12: =H12*(1+H15) | J12: =I12*(1+I15) | K12: =J12*(1+J15) | L12: =K12*(1+K15)
A13: Staff per MW | B13: employees / MW | C13: 1 | D13: =C13 | E13: =D13 | F13: =E13 | G13: =F13 | H13: =G13 | I13: =H13 | J13: =I13 | K13: =J13 | L13: =K13
A14: Staff cost / employee | B14: ZAR'000 / year | C14: 600 | D14: =C14*(1+C17) | E14: =D14*(1+D17) | F14: =E14*(1+E17) | G14: =F14*(1+F17) | H14: =G14*(1+G17) | I14: =H14*(1+H17) | J14: =I14*(1+I17) | K14: =J14*(1+J17) | L14: =K14*(1+K17)
A15: Other utilities | B15: ZAR'000 / MW / year | C15: 100 | D15: =C15*(1+C15) | E15: =D15*(1+D15) | F15: =E15*(1+E15) | G15: =F15*(1+F15) | H15: =G15*(1+G15) | I15: =H15*(1+H15) | J15: =I15*(1+I15) | K15: =J15*(1+J15) | L15: =K15*(1+K15)
A18: AMSA Vanderbijlpark
A19: MW online | B19: MW | C19: 10 | D19: =C19 | E19: =D19 | F19: =E19 | G19: =F19 | H19: =G19 | I19: =H19 | J19: =I19 | K19: =J19 | L19: =K19
A20: Operating hours/day | B20: hours/day | C20: 16 | D20: =C20 | E20: =D20 | F20: =E20 | G20: =F20 | H20: =G20 | I20: =H20 | J20: =I20 | K20: =J20 | L20: =K20
A21: Uptime | B21: % | C21: 0.95 | D21: =C21 | E21: =D21 | F21: =E21 | G21: =F21 | H21: =G21 | I21: =H21 | J21: =I21 | K21: =J21 | L21: =K21
A22: Blended tariff | B22: R/kWh | C22: 1.2 | D22: =C22*(1+C16) | E22: =D22*(1+D16) | F22: =E22*(1+E16) | G22: =F22*(1+F16) | H22: =G22*(1+G16) | I22: =H22*(1+H16) | J22: =I22*(1+I16) | K22: =J22*(1+J16) | L22: =K22*(1+K16)
A23: Demand response rebate | B23: R/kWh | C23: 0 | D23: =C23 | E23: =D23 | F23: =E23 | G23: =F23 | H23: =G23 | I23: =H23 | J23: =I23 | K23: =J23 | L23: =K23
A24: Demand response hours/day | B24: hours/day | C24: 0 | D24: =C24 | E24: =D24 | F24: =E24 | G24: =F24 | H24: =G24 | I24: =H24 | J24: =I24 | K24: =J24 | L24: =K24
A25: Fixed site opex | B25: ZAR'000 / year | C25: 5000 | D25: =C25*(1+C15) | E25: =D25*(1+D15) | F25: =E25*(1+E15) | G25: =F25*(1+F15) | H25: =G25*(1+G15) | I25: =H25*(1+H15) | J25: =I25*(1+I15) | K25: =J25*(1+J15) | L25: =K25*(1+K15)
A26: Rent | B26: ZAR'000 / year | C26: 0 | D26: =C26*(1+C15) | E26: =D26*(1+D15) | F26: =E26*(1+E15) | G26: =F26*(1+F15) | H26: =G26*(1+G15) | I26: =H26*(1+H15) | J26: =I26*(1+I15) | K26: =J26*(1+J15) | L26: =K26*(1+K15)
A27: Staff per MW | B27: employees / MW | C27: 1 | D27: =C27 | E27: =D27 | F27: =E27 | G27: =F27 | H27: =G27 | I27: =H27 | J27: =I27 | K27: =J27 | L27: =K27
A28: Staff cost / employee | B28: ZAR'000 / year | C28: 600 | D28: =C28*(1+C17) | E28: =D28*(1+D17) | F28: =E28*(1+E17) | G28: =F28*(1+F17) | H28: =G28*(1+G17) | I28: =H28*(1+H17) | J28: =I28*(1+I17) | K28: =J28*(1+J17) | L28: =K28*(1+K17)
A29: Other utilities | B29: ZAR'000 / MW / year | C29: 100 | D29: =C29*(1+C15) | E29: =D29*(1+D15) | F29: =E29*(1+E15) | G29: =F29*(1+F15) | H29: =G29*(1+G15) | I29: =H29*(1+H15) | J29: =I29*(1+I15) | K29: =J29*(1+J15) | L29: =K29*(1+K15)
A32: Total Phase 1 MW | B32: MW | C32: =C5+C19 | D32: =D5+D19 | E32: =E5+E19 | F32: =F5+F19 | G32: =G5+G19 | H32: =H5+H19 | I32: =I5+I19 | J32: =J5+J19 | ... L32: =L5+L19

Sheet Revenue
A1: Revenue Model
A3: Driver | B3: Unit | C3: 2026 | D3: 2027 | E3: 2028 | F3: 2029 | G3: 2030 | H3: 2031 | I3: 2032 | J3: 2033 | K3: 2034 | L3: 2035
A4: Grootvlei
A5: Gross site energy consumed | B5: MWh / year | C5: =Site_Assumptions!C5*Site_Assumptions!C6*Assumptions!C13*Site_Assumptions!C7 | D5: =Site_Assumptions!D5*Site_Assumptions!D6*Assumptions!D13*Site_Assumptions!D7 | E5: =Site_Assumptions!E5*Site_Assumptions!E6*Assumptions!E13*Site_Assumptions!E7 | F5: =Site_Assumptions!F5*Site_Assumptions!F6*Assumptions!F13*Site_Assumptions!F7 | G5: =Site_Assumptions!G5*Site_Assumptions!G6*Assumptions!G13*Site_Assumptions!G7 | H5: =Site_Assumptions!H5*Site_Assumptions!H6*Assumptions!H13*Site_Assumptions!H7 | I5: =Site_Assumptions!I5*Site_Assumptions!I6*Assumptions!I13*Site_Assumptions!I7 | J5: =Site_Assumptions!J5*Site_Assumptions!J6*Assumptions!J13*Site_Assumptions!J7 | ... L5: =Site_Assumptions!L5*Site_Assumptions!L6*Assumptions!L13*Site_Assumptions!L7
A6: Estimated ASIC count | B6: miners | C6: =ROUNDDOWN(((Site_Assumptions!C5*1000000)/(1+Hardware!$C$8))/Hardware!$C$6,0) | D6: =ROUNDDOWN(((Site_Assumptions!D5*1000000)/(1+Hardware!$C$8))/Hardware!$C$6,0) | E6: =ROUNDDOWN(((Site_Assumptions!E5*1000000)/(1+Hardware!$C$8))/Hardware!$C$6,0) | F6: =ROUNDDOWN(((Site_Assumptions!F5*1000000)/(1+Hardware!$C$8))/Hardware!$C$6,0) | G6: =ROUNDDOWN(((Site_Assumptions!G5*1000000)/(1+Hardware!$C$8))/Hardware!$C$6,0) | H6: =ROUNDDOWN(((Site_Assumptions!H5*1000000)/(1+Hardware!$C$8))/Hardware!$C$6,0) | I6: =ROUNDDOWN(((Site_Assumptions!I5*1000000)/(1+Hardware!$C$8))/Hardware!$C$6,0) | J6: =ROUNDDOWN(((Site_Assumptions!J5*1000000)/(1+Hardware!$C$8))/Hardware!$C$6,0) | ... L6: =ROUNDDOWN(((Site_Assumptions!L5*1000000)/(1+Hardware!$C$8))/Hardware!$C$6,0)
A7: Site hashrate | B7: TH/s | C7: =C6*Hardware!$C$5*(1-Hardware!$C$9) | D7: =D6*Hardware!$C$5*(1-Hardware!$C$9) | E7: =E6*Hardware!$C$5*(1-Hardware!$C$9) | F7: =F6*Hardware!$C$5*(1-Hardware!$C$9) | G7: =G6*Hardware!$C$5*(1-Hardware!$C$9) | H7: =H6*Hardware!$C$5*(1-Hardware!$C$9) | I7: =I6*Hardware!$C$5*(1-Hardware!$C$9) | J7: =J6*Hardware!$C$5*(1-Hardware!$C$9) | ... L7: =L6*Hardware!$C$5*(1-Hardware!$C$9)
A8: BTC mined | B8: BTC / year | C8: =(C7/Assumptions!C8)*Assumptions!C12*Assumptions!C13*Assumptions!C10*(1+Assumptions!C11) | D8: =(D7/Assumptions!D8)*Assumptions!D12*Assumptions!D13*Assumptions!D10*(1+Assumptions!D11) | E8: =(E7/Assumptions!E8)*Assumptions!E12*Assumptions!E13*Assumptions!E10*(1+Assumptions!E11) | F8: =(F7/Assumptions!F8)*Assumptions!F12*Assumptions!F13*Assumptions!F10*(1+Assumptions!F11) | G8: =(G7/Assumptions!G8)*Assumptions!G12*Assumptions!G13*Assumptions!G10*(1+Assumptions!G11) | H8: =(H7/Assumptions!H8)*Assumptions!H12*Assumptions!H13*Assumptions!H10*(1+Assumptions!H11) | I8: =(I7/Assumptions!I8)*Assumptions!I12*Assumptions!I13*Assumptions!I10*(1+Assumptions!I11) | J8: =(J7/Assumptions!J8)*Assumptions!J12*Assumptions!J13*Assumptions!J10*(1+Assumptions!J11) | ... L8: =(L7/Assumptions!L8)*Assumptions!L12*Assumptions!L13*Assumptions!L10*(1+Assumptions!L11)
A9: BTC revenue | B9: ZAR'000 | C9: =C8*Assumptions!C6 | D9: =D8*Assumptions!D6 | E9: =E8*Assumptions!E6 | F9: =F8*Assumptions!F6 | G9: =G8*Assumptions!G6 | H9: =H8*Assumptions!H6 | I9: =I8*Assumptions!I6 | J9: =J8*Assumptions!J6 | ... L9: =L8*Assumptions!L6
A10: Demand response revenue | B10: ZAR'000 | C10: =Site_Assumptions!C5*Site_Assumptions!C10*Assumptions!C13*Site_Assumptions!C9*Assumptions!$B$21 | D10: =Site_Assumptions!D5*Site_Assumptions!D10*Assumptions!D13*Site_Assumptions!D9*Assumptions!$B$21 | E10: =Site_Assumptions!E5*Site_Assumptions!E10*Assumptions!E13*Site_Assumptions!E9*Assumptions!$B$21 | F10: =Site_Assumptions!F5*Site_Assumptions!F10*Assumptions!F13*Site_Assumptions!F9*Assumptions!$B$21 | G10: =Site_Assumptions!G5*Site_Assumptions!G10*Assumptions!G13*Site_Assumptions!G9*Assumptions!$B$21 | H10: =Site_Assumptions!H5*Site_Assumptions!H10*Assumptions!H13*Site_Assumptions!H9*Assumptions!$B$21 | I10: =Site_Assumptions!I5*Site_Assumptions!I10*Assumptions!I13*Site_Assumptions!I9*Assumptions!$B$21 | J10: =Site_Assumptions!J5*Site_Assumptions!J10*Assumptions!J13*Site_Assumptions!J9*Assumptions!$B$21 | ... L10: =Site_Assumptions!L5*Site_Assumptions!L10*Assumptions!L13*Site_Assumptions!L9*Assumptions!$B$21
A11: Total revenue | B11: ZAR'000 | C11: =C9+C10 | D11: =D9+D10 | E11: =E9+E10 | F11: =F9+F10 | G11: =G9+G10 | H11: =H9+H10 | I11: =I9+I10 | J11: =J9+J10 | ... L11: =L9+L10
A17: AMSA Vanderbijlpark
A18: Gross site energy consumed | B18: MWh / year | C18: =Site_Assumptions!C19*Site_Assumptions!C20*Assumptions!C13*Site_Assumptions!C21 | D18: =Site_Assumptions!D19*Site_Assumptions!D20*Assumptions!D13*Site_Assumptions!D21 | E18: =Site_Assumptions!E19*Site_Assumptions!E20*Assumptions!E13*Site_Assumptions!E21 | F18: =Site_Assumptions!F19*Site_Assumptions!F20*Assumptions!F13*Site_Assumptions!F21 | G18: =Site_Assumptions!G19*Site_Assumptions!G20*Assumptions!G13*Site_Assumptions!G21 | H18: =Site_Assumptions!H19*Site_Assumptions!H20*Assumptions!H13*Site_Assumptions!H21 | I18: =Site_Assumptions!I19*Site_Assumptions!I20*Assumptions!I13*Site_Assumptions!I21 | J18: =Site_Assumptions!J19*Site_Assumptions!J20*Assumptions!J13*Site_Assumptions!J21 | ... L18: =Site_Assumptions!L19*Site_Assumptions!L20*Assumptions!L13*Site_Assumptions!L21
A19: Estimated ASIC count | B19: miners | C19: =ROUNDDOWN(((Site_Assumptions!C19*1000000)/(1+Hardware!$C$8))/Hardware!$C$6,0) | D19: =ROUNDDOWN(((Site_Assumptions!D19*1000000)/(1+Hardware!$C$8))/Hardware!$C$6,0) | E19: =ROUNDDOWN(((Site_Assumptions!E19*1000000)/(1+Hardware!$C$8))/Hardware!$C$6,0) | F19: =ROUNDDOWN(((Site_Assumptions!F19*1000000)/(1+Hardware!$C$8))/Hardware!$C$6,0) | G19: =ROUNDDOWN(((Site_Assumptions!G19*1000000)/(1+Hardware!$C$8))/Hardware!$C$6,0) | H19: =ROUNDDOWN(((Site_Assumptions!H19*1000000)/(1+Hardware!$C$8))/Hardware!$C$6,0) | I19: =ROUNDDOWN(((Site_Assumptions!I19*1000000)/(1+Hardware!$C$8))/Hardware!$C$6,0) | J19: =ROUNDDOWN(((Site_Assumptions!J19*1000000)/(1+Hardware!$C$8))/Hardware!$C$6,0) | ... L19: =ROUNDDOWN(((Site_Assumptions!L19*1000000)/(1+Hardware!$C$8))/Hardware!$C$6,0)
A20: Site hashrate | B20: TH/s | C20: =C19*Hardware!$C$5*(1-Hardware!$C$9) | D20: =D19*Hardware!$C$5*(1-Hardware!$C$9) | E20: =E19*Hardware!$C$5*(1-Hardware!$C$9) | F20: =F19*Hardware!$C$5*(1-Hardware!$C$9) | G20: =G19*Hardware!$C$5*(1-Hardware!$C$9) | H20: =H19*Hardware!$C$5*(1-Hardware!$C$9) | I20: =I19*Hardware!$C$5*(1-Hardware!$C$9) | J20: =J19*Hardware!$C$5*(1-Hardware!$C$9) | ... L20: =L19*Hardware!$C$5*(1-Hardware!$C$9)
A21: BTC mined | B21: BTC / year | C21: =(C20/Assumptions!C8)*Assumptions!C12*Assumptions!C13*Assumptions!C10*(1+Assumptions!C11) | D21: =(D20/Assumptions!D8)*Assumptions!D12*Assumptions!D13*Assumptions!D10*(1+Assumptions!D11) | E21: =(E20/Assumptions!E8)*Assumptions!E12*Assumptions!E13*Assumptions!E10*(1+Assumptions!E11) | F21: =(F20/Assumptions!F8)*Assumptions!F12*Assumptions!F13*Assumptions!F10*(1+Assumptions!F11) | G21: =(G20/Assumptions!G8)*Assumptions!G12*Assumptions!G13*Assumptions!G10*(1+Assumptions!G11) | H21: =(H20/Assumptions!H8)*Assumptions!H12*Assumptions!H13*Assumptions!H10*(1+Assumptions!H11) | I21: =(I20/Assumptions!I8)*Assumptions!I12*Assumptions!I13*Assumptions!I10*(1+Assumptions!I11) | J21: =(J20/Assumptions!J8)*Assumptions!J12*Assumptions!J13*Assumptions!J10*(1+Assumptions!J11) | ... L21: =(L20/Assumptions!L8)*Assumptions!L12*Assumptions!L13*Assumptions!L10*(1+Assumptions!L11)
A22: BTC revenue | B22: ZAR'000 | C22: =C21*Assumptions!C6 | D22: =D21*Assumptions!D6 | E22: =E21*Assumptions!E6 | F22: =F21*Assumptions!F6 | G22: =G21*Assumptions!G6 | H22: =H21*Assumptions!H6 | I22: =I21*Assumptions!I6 | J22: =J21*Assumptions!J6 | ... L22: =L21*Assumptions!L6
A23: Demand response revenue | B23: ZAR'000 | C23: =Site_Assumptions!C19*Site_Assumptions!C24*Assumptions!C13*Site_Assumptions!C23*Assumptions!$B$21 | D23: =Site_Assumptions!D19*Site_Assumptions!D24*Assumptions!D13*Site_Assumptions!D23*Assumptions!$B$21 | E23: =Site_Assumptions!E19*Site_Assumptions!E24*Assumptions!E13*Site_Assumptions!E23*Assumptions!$B$21 | F23: =Site_Assumptions!F19*Site_Assumptions!F24*Assumptions!F13*Site_Assumptions!F23*Assumptions!$B$21 | G23: =Site_Assumptions!G19*Site_Assumptions!G24*Assumptions!G13*Site_Assumptions!G23*Assumptions!$B$21 | H23: =Site_Assumptions!H19*Site_Assumptions!H24*Assumptions!H13*Site_Assumptions!H23*Assumptions!$B$21 | I23: =Site_Assumptions!I19*Site_Assumptions!I24*Assumptions!I13*Site_Assumptions!I23*Assumptions!$B$21 | J23: =Site_Assumptions!J19*Site_Assumptions!J24*Assumptions!J13*Site_Assumptions!J23*Assumptions!$B$21 | ... L23: =Site_Assumptions!L19*Site_Assumptions!L24*Assumptions!L13*Site_Assumptions!L23*Assumptions!$B$21
A24: Total revenue | B24: ZAR'000 | C24: =C22+C23 | D24: =D22+D23 | E24: =E22+E23 | F24: =F22+F23 | G24: =G22+G23 | H24: =H22+H23 | I24: =I22+I23 | J24: =J22+J23 | ... L24: =L22+L23
A31: Project totals
A32: Gross site energy consumed | B32: MWh / year | C32: =C5+C18 | D32: =D5+D18 | E32: =E5+E18 | F32: =F5+F18 | G32: =G5+G18 | H32: =H5+H18 | I32: =I5+I18 | J32: =J5+J18 | ... L32: =L5+L18
A33: Estimated ASIC count | B33: miners | C33: =C6+C19 | D33: =D6+D19 | E33: =E6+E19 | F33: =F6+F19 | G33: =G6+G19 | H33: =H6+H19 | I33: =I6+I19 | J33: =J6+J19 | ... L33: =L6+L19
A34: Total hashrate | B34: TH/s | C34: =C7+C20 | D34: =D7+D20 | E34: =E7+E20 | F34: =F7+F20 | G34: =G7+G20 | H34: =H7+H20 | I34: =I7+I20 | J34: =J7+J20 | ... L34: =L7+L20
A35: BTC mined | B35: BTC / year | C35: =C8+C21 | D35: =D8+D21 | E35: =E8+E21 | F35: =F8+F21 | G35: =G8+G21 | H35: =H8+H21 | I35: =I8+I21 | J35: =J8+J21 | ... L35: =L8+L21
A36: BTC revenue | B36: ZAR'000 | C36: =C9+C22 | D36: =D9+D22 | E36: =E9+E22 | F36: =F9+F22 | G36: =G9+G22 | H36: =H9+H22 | I36: =I9+I22 | J36: =J9+J22 | ... L36: =L9+L22
A37: Demand response revenue | B37: ZAR'000 | C37: =C10+C23 | D37: =D10+D23 | E37: =E10+E23 | F37: =F10+F23 | G37: =G10+G23 | H37: =H10+H23 | I37: =I10+I23 | J37: =J10+J23 | ... L37: =L10+L23
A38: Total revenue | B38: ZAR'000 | C38: =C11+C24 | D38: =D11+D24 | E38: =E11+E24 | F38: =F11+F24 | G38: =G11+G24 | H38: =H11+H24 | I38: =I11+I24 | J38: =J11+J24 | ... L38: =L11+L24

Sheet Opex
A1: Operating Cost Model
A3: Driver | B3: Unit | C3: 2026 | D3: 2027 | E3: 2028 | F3: 2029 | G3: 2030 | H3: 2031 | I3: 2032 | J3: 2033 | K3: 2034 | L3: 2035
A4: Grootvlei
A5: Energy cost | B5: ZAR'000 | C5: =Site_Assumptions!C5*Site_Assumptions!C6*Assumptions!C13*Site_Assumptions!C8 | D5: =Site_Assumptions!D5*Site_Assumptions!D6*Assumptions!D13*Site_Assumptions!D8 | E5: =Site_Assumptions!E5*Site_Assumptions!E6*Assumptions!E13*Site_Assumptions!E8 | F5: =Site_Assumptions!F5*Site_Assumptions!F6*Assumptions!F13*Site_Assumptions!F8 | G5: =Site_Assumptions!G5*Site_Assumptions!G6*Assumptions!G13*Site_Assumptions!G8 | H5: =Site_Assumptions!H5*Site_Assumptions!H6*Assumptions!H13*Site_Assumptions!H8 | I5: =Site_Assumptions!I5*Site_Assumptions!I6*Assumptions!I13*Site_Assumptions!I8 | J5: =Site_Assumptions!J5*Site_Assumptions!J6*Assumptions!J13*Site_Assumptions!J8 | ... L5: =Site_Assumptions!L5*Site_Assumptions!L6*Assumptions!L13*Site_Assumptions!L8
A6: Staff cost | B6: ZAR'000 | C6: =Site_Assumptions!C5*Site_Assumptions!C13*Site_Assumptions!C14 | D6: =Site_Assumptions!D5*Site_Assumptions!D13*Site_Assumptions!D14 | E6: =Site_Assumptions!E5*Site_Assumptions!E13*Site_Assumptions!E14 | F6: =Site_Assumptions!F5*Site_Assumptions!F13*Site_Assumptions!F14 | G6: =Site_Assumptions!G5*Site_Assumptions!G13*Site_Assumptions!G14 | H6: =Site_Assumptions!H5*Site_Assumptions!H13*Site_Assumptions!H14 | I6: =Site_Assumptions!I5*Site_Assumptions!I13*Site_Assumptions!I14 | J6: =Site_Assumptions!J5*Site_Assumptions!J13*Site_Assumptions!J14 | ... L6: =Site_Assumptions!L5*Site_Assumptions!L13*Site_Assumptions!L14
A7: Maintenance | B7: ZAR'000 | C7: =Revenue!C6*Hardware!$C$10/1000 | D7: =Revenue!D6*Hardware!$C$10/1000 | E7: =Revenue!E6*Hardware!$C$10/1000 | F7: =Revenue!F6*Hardware!$C$10/1000 | G7: =Revenue!G6*Hardware!$C$10/1000 | H7: =Revenue!H6*Hardware!$C$10/1000 | I7: =Revenue!I6*Hardware!$C$10/1000 | J7: =Revenue!J6*Hardware!$C$10/1000 | ... L7: =Revenue!L6*Hardware!$C$10/1000
A8: Fixed site opex | B8: ZAR'000 | C8: =Site_Assumptions!C11 | D8: =Site_Assumptions!D11 | E8: =Site_Assumptions!E11 | F8: =Site_Assumptions!F11 | G8: =Site_Assumptions!G11 | H8: =Site_Assumptions!H11 | I8: =Site_Assumptions!I11 | J8: =Site_Assumptions!J11 | ... L8: =Site_Assumptions!L11
A9: Rent | B9: ZAR'000 | C9: =Site_Assumptions!C12 | D9: =Site_Assumptions!D12 | E9: =Site_Assumptions!E12 | F9: =Site_Assumptions!F12 | G9: =Site_Assumptions!G12 | H9: =Site_Assumptions!H12 | I9: =Site_Assumptions!I12 | J9: =Site_Assumptions!J12 | ... L9: =Site_Assumptions!L12
A10: Other utilities | B10: ZAR'000 | C10: =Site_Assumptions!C5*Site_Assumptions!C15 | D10: =Site_Assumptions!D5*Site_Assumptions!D15 | E10: =Site_Assumptions!E5*Site_Assumptions!E15 | F10: =Site_Assumptions!F5*Site_Assumptions!F15 | G10: =Site_Assumptions!G5*Site_Assumptions!G15 | H10: =Site_Assumptions!H5*Site_Assumptions!H15 | I10: =Site_Assumptions!I5*Site_Assumptions!I15 | J10: =Site_Assumptions!J5*Site_Assumptions!J15 | ... L10: =Site_Assumptions!L5*Site_Assumptions!L15
A11: Total opex | B11: ZAR'000 | C11: =SUM(C5:C10) | D11: =SUM(D5:D10) | E11: =SUM(E5:E10) | F11: =SUM(F5:F10) | G11: =SUM(G5:G10) | H11: =SUM(H5:H10) | I11: =SUM(I5:I10) | J11: =SUM(J5:J10) | ... L11: =SUM(L5:L10)
A12: EBITDA | B12: ZAR'000 | C12: =Revenue!C11-C11 | D12: =Revenue!D11-D11 | E12: =Revenue!E11-E11 | F12: =Revenue!F11-F11 | G12: =Revenue!G11-G11 | H12: =Revenue!H11-H11 | I12: =Revenue!I11-I11 | J12: =Revenue!J11-J11 | ... L12: =Revenue!L11-L11
A17: AMSA Vanderbijlpark
A18: Energy cost | B18: ZAR'000 | C18: =Site_Assumptions!C19*Site_Assumptions!C20*Assumptions!C13*Site_Assumptions!C22 | D18: =Site_Assumptions!D19*Site_Assumptions!D20*Assumptions!D13*Site_Assumptions!D22 | E18: =Site_Assumptions!E19*Site_Assumptions!E20*Assumptions!E13*Site_Assumptions!E22 | F18: =Site_Assumptions!F19*Site_Assumptions!F20*Assumptions!F13*Site_Assumptions!F22 | G18: =Site_Assumptions!G19*Site_Assumptions!G20*Assumptions!G13*Site_Assumptions!G22 | H18: =Site_Assumptions!H19*Site_Assumptions!H20*Assumptions!H13*Site_Assumptions!H22 | I18: =Site_Assumptions!I19*Site_Assumptions!I20*Assumptions!I13*Site_Assumptions!I22 | J18: =Site_Assumptions!J19*Site_Assumptions!J20*Assumptions!J13*Site_Assumptions!J22 | ... L18: =Site_Assumptions!L19*Site_Assumptions!L20*Assumptions!L13*Site_Assumptions!L22
A19: Staff cost | B19: ZAR'000 | C19: =Site_Assumptions!C19*Site_Assumptions!C27*Site_Assumptions!C28 | D19: =Site_Assumptions!D19*Site_Assumptions!D27*Site_Assumptions!D28 | E19: =Site_Assumptions!E19*Site_Assumptions!E27*Site_Assumptions!E28 | F19: =Site_Assumptions!F19*Site_Assumptions!F27*Site_Assumptions!F28 | G19: =Site_Assumptions!G19*Site_Assumptions!G27*Site_Assumptions!G28 | H19: =Site_Assumptions!H19*Site_Assumptions!H27*Site_Assumptions!H28 | I19: =Site_Assumptions!I19*Site_Assumptions!I27*Site_Assumptions!I28 | J19: =Site_Assumptions!J19*Site_Assumptions!J27*Site_Assumptions!J28 | ... L19: =Site_Assumptions!L19*Site_Assumptions!L27*Site_Assumptions!L28
A20: Maintenance | B20: ZAR'000 | C20: =Revenue!C19*Hardware!$C$10/1000 | D20: =Revenue!D19*Hardware!$C$10/1000 | E20: =Revenue!E19*Hardware!$C$10/1000 | F20: =Revenue!F19*Hardware!$C$10/1000 | G20: =Revenue!G19*Hardware!$C$10/1000 | H20: =Revenue!H19*Hardware!$C$10/1000 | I20: =Revenue!I19*Hardware!$C$10/1000 | J20: =Revenue!J19*Hardware!$C$10/1000 | ... L20: =Revenue!L19*Hardware!$C$10/1000
A21: Fixed site opex | B21: ZAR'000 | C21: =Site_Assumptions!C25 | D21: =Site_Assumptions!D25 | E21: =Site_Assumptions!E25 | F21: =Site_Assumptions!F25 | G21: =Site_Assumptions!G25 | H21: =Site_Assumptions!H25 | I21: =Site_Assumptions!I25 | J21: =Site_Assumptions!J25 | ... L21: =Site_Assumptions!L25
A22: Rent | B22: ZAR'000 | C22: =Site_Assumptions!C26 | D22: =Site_Assumptions!D26 | E22: =Site_Assumptions!E26 | F22: =Site_Assumptions!F26 | G22: =Site_Assumptions!G26 | H22: =Site_Assumptions!H26 | I22: =Site_Assumptions!I26 | J22: =Site_Assumptions!J26 | ... L22: =Site_Assumptions!L26
A23: Other utilities | B23: ZAR'000 | C23: =Site_Assumptions!C19*Site_Assumptions!C29 | D23: =Site_Assumptions!D19*Site_Assumptions!D29 | E23: =Site_Assumptions!E19*Site_Assumptions!E29 | F23: =Site_Assumptions!F19*Site_Assumptions!F29 | G23: =Site_Assumptions!G19*Site_Assumptions!G29 | H23: =Site_Assumptions!H19*Site_Assumptions!H29 | I23: =Site_Assumptions!I19*Site_Assumptions!I29 | J23: =Site_Assumptions!J19*Site_Assumptions!J29 | ... L23: =Site_Assumptions!L19*Site_Assumptions!L29
A24: Total opex | B24: ZAR'000 | C24: =SUM(C18:C23) | D24: =SUM(D18:D23) | E24: =SUM(E18:E23) | F24: =SUM(F18:F23) | G24: =SUM(G18:G23) | H24: =SUM(H18:H23) | I24: =SUM(I18:I23) | J24: =SUM(J18:J23) | ... L24: =SUM(L18:L23)
A25: EBITDA | B25: ZAR'000 | C25: =Revenue!C24-C24 | D25: =Revenue!D24-D24 | E25: =Revenue!E24-E24 | F25: =Revenue!F24-F24 | G25: =Revenue!G24-G24 | H25: =Revenue!H24-H24 | I25: =Revenue!I24-I24 | J25: =Revenue!J24-J24 | ... L25: =Revenue!L24-L24
A30: Project totals
A31: Energy cost | B31: ZAR'000 | C31: =C5+C18 | D31: =D5+D18 | E31: =E5+E18 | F31: =F5+F18 | G31: =G5+G18 | H31: =H5+H18 | I31: =I5+I18 | J31: =J5+J18 | ... L31: =L5+L18
A32: Staff cost | B32: ZAR'000 | C32: =C6+C19 | D32: =D6+D19 | E32: =E6+E19 | F32: =F6+F19 | G32: =G6+G19 | H32: =H6+H19 | I32: =I6+I19 | J32: =J6+J19 | ... L32: =L6+L19
A33: Maintenance | B33: ZAR'000 | C33: =C7+C20 | D33: =D7+D20 | E33: =E7+E20 | F33: =F7+F20 | G33: =G7+G20 | H33: =H7+H20 | I33: =I7+I20 | J33: =J7+J20 | ... L33: =L7+L20
A34: Fixed site opex | B34: ZAR'000 | C34: =C8+C21 | D34: =D8+D21 | E34: =E8+E21 | F34: =F8+F21 | G34: =G8+G21 | H34: =H8+H21 | I34: =I8+I21 | J34: =J8+J21 | ... L34: =L8+L21
A35: Rent | B35: ZAR'000 | C35: =C9+C22 | D35: =D9+D22 | E35: =E9+E22 | F35: =F9+F22 | G35: =G9+G22 | H35: =H9+H22 | I35: =I9+I22 | J35: =J9+J22 | ... L35: =L9+L22
A36: Other utilities | B36: ZAR'000 | C36: =C10+C23 | D36: =D10+D23 | E36: =E10+E23 | F36: =F10+F23 | G36: =G10+G23 | H36: =H10+H23 | I36: =I10+I23 | J36: =J10+J23 | ... L36: =L10+L23
A37: Total opex | B37: ZAR'000 | C37: =C11+C24 | D37: =D11+D24 | E37: =E11+E24 | F37: =F11+F24 | G37: =G11+G24 | H37: =H11+H24 | I37: =I11+I24 | J37: =J11+J24 | ... L37: =L11+L24
A38: EBITDA | B38: ZAR'000 | C38: =C12+C25 | D38: =D12+D25 | E38: =E12+E25 | F38: =F12+F25 | G38: =G12+G25 | H38: =H12+H25 | I38: =I12+I25 | J38: =J12+J25 | ... L38: =L12+L25

Sheet Capex
A1: Capex Model
A3: Driver | B3: Unit | C3: 2026 | D3: 2027 | E3: 2028 | F3: 2029 | G3: 2030 | H3: 2031 | I3: 2032 | J3: 2033 | K3: 2034 | L3: 2035
A4: Grootvlei
A5: New MW | B5: MW | C5: =Site_Assumptions!C5 | D5: =MAX(Site_Assumptions!D5-Site_Assumptions!C5,0) | E5: =MAX(Site_Assumptions!E5-Site_Assumptions!D5,0) | F5: =MAX(Site_Assumptions!F5-Site_Assumptions!E5,0) | G5: =MAX(Site_Assumptions!G5-Site_Assumptions!F5,0) | H5: =MAX(Site_Assumptions!H5-Site_Assumptions!G5,0) | I5: =MAX(Site_Assumptions!I5-Site_Assumptions!H5,0) | J5: =MAX(Site_Assumptions!J5-Site_Assumptions!I5,0) | K5: =MAX(Site_Assumptions!K5-Site_Assumptions!J5,0) | L5: =MAX(Site_Assumptions!L5-Site_Assumptions!K5,0)
A6: New ASIC count | B6: miners | C6: =ROUNDDOWN(((C5*1000000)/(1+Hardware!$C$8))/Hardware!$C$6,0) | D6: =ROUNDDOWN(((D5*1000000)/(1+Hardware!$C$8))/Hardware!$C$6,0) | E6: =ROUNDDOWN(((E5*1000000)/(1+Hardware!$C$8))/Hardware!$C$6,0) | F6: =ROUNDDOWN(((F5*1000000)/(1+Hardware!$C$8))/Hardware!$C$6,0) | G6: =ROUNDDOWN(((G5*1000000)/(1+Hardware!$C$8))/Hardware!$C$6,0) | H6: =ROUNDDOWN(((H5*1000000)/(1+Hardware!$C$8))/Hardware!$C$6,0) | I6: =ROUNDDOWN(((I5*1000000)/(1+Hardware!$C$8))/Hardware!$C$6,0) | J6: =ROUNDDOWN(((J5*1000000)/(1+Hardware!$C$8))/Hardware!$C$6,0) | ... L6: =ROUNDDOWN(((L5*1000000)/(1+Hardware!$C$8))/Hardware!$C$6,0)
A7: Miner capex | B7: ZAR'000 | C7: =C6*Hardware!$C$7*Assumptions!C5/1000 | D7: =D6*Hardware!$C$7*Assumptions!D5/1000 | E7: =E6*Hardware!$C$7*Assumptions!E5/1000 | F7: =F6*Hardware!$C$7*Assumptions!F5/1000 | G7: =G6*Hardware!$C$7*Assumptions!G5/1000 | H7: =H6*Hardware!$C$7*Assumptions!H5/1000 | I7: =I6*Hardware!$C$7*Assumptions!I5/1000 | J7: =J6*Hardware!$C$7*Assumptions!J5/1000 | ... L7: =L6*Hardware!$C$7*Assumptions!L5/1000
A8: Electrical + BOS capex | B8: ZAR'000 | C8: =C5*Hardware!$C$11 | D8: =D5*Hardware!$C$11 | E8: =E5*Hardware!$C$11 | F8: =F5*Hardware!$C$11 | G8: =G5*Hardware!$C$11 | H8: =H5*Hardware!$C$11 | I8: =I5*Hardware!$C$11 | J8: =J5*Hardware!$C$11 | ... L8: =L5*Hardware!$C$11
A9: Total capex | B9: ZAR'000 | C9: =SUM(C7:C8) | D9: =SUM(D7:D8) | E9: =SUM(E7:E8) | F9: =SUM(F7:F8) | G9: =SUM(G7:G8) | H9: =SUM(H7:H8) | I9: =SUM(I7:I8) | J9: =SUM(J7:J8) | ... L9: =SUM(L7:L8)
A12: AMSA Vanderbijlpark
A13: New MW | B13: MW | C13: =Site_Assumptions!C19 | D13: =MAX(Site_Assumptions!D19-Site_Assumptions!C19,0) | E13: =MAX(Site_Assumptions!E19-Site_Assumptions!D19,0) | F13: =MAX(Site_Assumptions!F19-Site_Assumptions!E19,0) | G13: =MAX(Site_Assumptions!G19-Site_Assumptions!F19,0) | H13: =MAX(Site_Assumptions!H19-Site_Assumptions!G19,0) | I13: =MAX(Site_Assumptions!I19-Site_Assumptions!H19,0) | J13: =MAX(Site_Assumptions!J19-Site_Assumptions!I19,0) | K13: =MAX(Site_Assumptions!K19-Site_Assumptions!J19,0) | L13: =MAX(Site_Assumptions!L19-Site_Assumptions!K19,0)
A14: New ASIC count | B14: miners | C14: =ROUNDDOWN(((C13*1000000)/(1+Hardware!$C$8))/Hardware!$C$6,0) | D14: =ROUNDDOWN(((D13*1000000)/(1+Hardware!$C$8))/Hardware!$C$6,0) | E14: =ROUNDDOWN(((E13*1000000)/(1+Hardware!$C$8))/Hardware!$C$6,0) | F14: =ROUNDDOWN(((F13*1000000)/(1+Hardware!$C$8))/Hardware!$C$6,0) | G14: =ROUNDDOWN(((G13*1000000)/(1+Hardware!$C$8))/Hardware!$C$6,0) | H14: =ROUNDDOWN(((H13*1000000)/(1+Hardware!$C$8))/Hardware!$C$6,0) | I14: =ROUNDDOWN(((I13*1000000)/(1+Hardware!$C$8))/Hardware!$C$6,0) | J14: =ROUNDDOWN(((J13*1000000)/(1+Hardware!$C$8))/Hardware!$C$6,0) | ... L14: =ROUNDDOWN(((L13*1000000)/(1+Hardware!$C$8))/Hardware!$C$6,0)
A15: Miner capex | B15: ZAR'000 | C15: =C14*Hardware!$C$7*Assumptions!C5/1000 | D15: =D14*Hardware!$C$7*Assumptions!D5/1000 | E15: =E14*Hardware!$C$7*Assumptions!E5/1000 | F15: =F14*Hardware!$C$7*Assumptions!F5/1000 | G15: =G14*Hardware!$C$7*Assumptions!G5/1000 | H15: =H14*Hardware!$C$7*Assumptions!H5/1000 | I15: =I14*Hardware!$C$7*Assumptions!I5/1000 | J15: =J14*Hardware!$C$7*Assumptions!J5/1000 | ... L15: =L14*Hardware!$C$7*Assumptions!L5/1000
A16: Electrical + BOS capex | B16: ZAR'000 | C16: =C13*Hardware!$C$11 | D16: =D13*Hardware!$C$11 | E16: =E13*Hardware!$C$11 | F16: =F13*Hardware!$C$11 | G16: =G13*Hardware!$C$11 | H16: =H13*Hardware!$C$11 | I16: =I13*Hardware!$C$11 | J16: =J13*Hardware!$C$11 | ... L16: =L13*Hardware!$C$11
A17: Total capex | B17: ZAR'000 | C17: =SUM(C15:C16) | D17: =SUM(D15:D16) | E17: =SUM(E15:E16) | F17: =SUM(F15:F16) | G17: =SUM(G15:G16) | H17: =SUM(H15:H16) | I17: =SUM(I15:I16) | J17: =SUM(J15:J16) | ... L17: =SUM(L15:L16)
A20: Project totals
A21: New MW | B21: MW | C21: =C5+C13 | D21: =D5+D13 | E21: =E5+E13 | F21: =F5+F13 | G21: =G5+G13 | H21: =H5+H13 | I21: =I5+I13 | J21: =J5+J13 | ... L21: =L5+L13
A22: New ASIC count | B22: miners | C22: =C6+C14 | D22: =D6+D14 | E22: =E6+E14 | F22: =F6+F14 | G22: =G6+G14 | H22: =H6+H14 | I22: =I6+I14 | J22: =J6+J14 | ... L22: =L6+L14
A23: Miner capex | B23: ZAR'000 | C23: =C7+C15 | D23: =D7+D15 | E23: =E7+E15 | F23: =F7+F15 | G23: =G7+G15 | H23: =H7+H15 | I23: =I7+I15 | J23: =J7+J15 | ... L23: =L7+L15
A24: Electrical + BOS capex | B24: ZAR'000 | C24: =C8+C16 | D24: =D8+D16 | E24: =E8+E16 | F24: =F8+F16 | G24: =G8+G16 | H24: =H8+H16 | I24: =I8+I16 | J24: =J8+J16 | ... L24: =L8+L16
A25: Total capex | B25: ZAR'000 | C25: =C9+C17 | D25: =D9+D17 | E25: =E9+E17 | F25: =F9+F17 | G25: =G9+G17 | H25: =H9+H17 | I25: =I9+I17 | J25: =J9+J17 | ... L25: =L9+L17

Sheet Depreciation
A1: Depreciation Waterfall
A3: Driver | B3: Unit | C3: 2026 | D3: 2027 | E3: 2028 | F3: 2029 | G3: 2030 | H3: 2031 | I3: 2032 | J3: 2033 | K3: 2034 | L3: 2035
A4: Miner depreciation
A5: 2026 miner batch | B5: ZAR'000 / year | C5: =Capex!C23/Hardware!$C$12 | D5: =Capex!C23/Hardware!$C$12 | E5: =Capex!C23/Hardware!$C$12 | F5: =Capex!C23/Hardware!$C$12 | G5: =Capex!C23/Hardware!$C$12 | H5: 0 | I5: 0 | J5: 0 | K5: 0 | L5: 0
A6: 2027 miner batch | B6: ZAR'000 / year | C6: 0 | D6: =Capex!D23/Hardware!$C$12 | E6: =Capex!D23/Hardware!$C$12 | F6: =Capex!D23/Hardware!$C$12 | G6: =Capex!D23/Hardware!$C$12 | H6: =Capex!D23/Hardware!$C$12 | I6: 0 | J6: 0 | K6: 0 | L6: 0
A7: 2028 miner batch | B7: ZAR'000 / year | C7: 0 | D7: 0 | E7: =Capex!E23/Hardware!$C$12 | F7: =Capex!E23/Hardware!$C$12 | G7: =Capex!E23/Hardware!$C$12 | H7: =Capex!E23/Hardware!$C$12 | I7: =Capex!E23/Hardware!$C$12 | J7: 0 | K7: 0 | L7: 0
A8: 2029 miner batch | B8: ZAR'000 / year | C8: 0 | D8: 0 | E8: 0 | F8: =Capex!F23/Hardware!$C$12 | G8: =Capex!F23/Hardware!$C$12 | H8: =Capex!F23/Hardware!$C$12 | I8: =Capex!F23/Hardware!$C$12 | J8: =Capex!F23/Hardware!$C$12 | K8: 0 | L8: 0
A9: 2030 miner batch | B9: ZAR'000 / year | C9: 0 | D9: 0 | E9: 0 | F9: 0 | G9: =Capex!G23/Hardware!$C$12 | H9: =Capex!G23/Hardware!$C$12 | I9: =Capex!G23/Hardware!$C$12 | J9: =Capex!G23/Hardware!$C$12 | K9: =Capex!G23/Hardware!$C$12 | L9: 0
A10: 2031 miner batch | B10: ZAR'000 / year | C10: 0 | D10: 0 | E10: 0 | F10: 0 | G10: 0 | H10: =Capex!H23/Hardware!$C$12 | I10: =Capex!H23/Hardware!$C$12 | J10: =Capex!H23/Hardware!$C$12 | K10: =Capex!H23/Hardware!$C$12 | L10: =Capex!H23/Hardware!$C$12
A11: 2032 miner batch | B11: ZAR'000 / year | C11: 0 | D11: 0 | E11: 0 | F11: 0 | G11: 0 | H11: 0 | I11: =Capex!I23/Hardware!$C$12 | J11: =Capex!I23/Hardware!$C$12 | K11: =Capex!I23/Hardware!$C$12 | L11: =Capex!I23/Hardware!$C$12
A12: 2033 miner batch | B12: ZAR'000 / year | C12: 0 | D12: 0 | E12: 0 | F12: 0 | G12: 0 | H12: 0 | I12: 0 | J12: =Capex!J23/Hardware!$C$12 | K12: =Capex!J23/Hardware!$C$12 | L12: =Capex!J23/Hardware!$C$12
A13: 2034 miner batch | B13: ZAR'000 / year | C13: 0 | D13: 0 | E13: 0 | F13: 0 | G13: 0 | H13: 0 | I13: 0 | J13: 0 | K13: =Capex!K23/Hardware!$C$12 | L13: =Capex!K23/Hardware!$C$12
A14: 2035 miner batch | B14: ZAR'000 / year | C14: 0 | D14: 0 | E14: 0 | F14: 0 | G14: 0 | H14: 0 | I14: 0 | J14: 0 | K14: 0 | L14: =Capex!L23/Hardware!$C$12
A16: Total miner depreciation | B16: ZAR'000 | C16: =SUM(C5:C14) | D16: =SUM(D5:D14) | E16: =SUM(E5:E14) | F16: =SUM(F5:F14) | G16: =SUM(G5:G14) | H16: =SUM(H5:H14) | I16: =SUM(I5:I14) | J16: =SUM(J5:J14) | ... L16: =SUM(L5:L14)
A18: BOS depreciation
A19: 2026 BOS batch | B19: ZAR'000 / year | C19: =Capex!C24/Hardware!$C$13 | D19: =Capex!C24/Hardware!$C$13 | E19: =Capex!C24/Hardware!$C$13 | F19: =Capex!C24/Hardware!$C$13 | G19: =Capex!C24/Hardware!$C$13 | H19: =Capex!C24/Hardware!$C$13 | I19: =Capex!C24/Hardware!$C$13 | J19: =Capex!C24/Hardware!$C$13 | K19: =Capex!C24/Hardware!$C$13 | L19: =Capex!C24/Hardware!$C$13
A20: 2027 BOS batch | B20: ZAR'000 / year | C20: 0 | D20: =Capex!D24/Hardware!$C$13 | E20: =Capex!D24/Hardware!$C$13 | F20: =Capex!D24/Hardware!$C$13 | G20: =Capex!D24/Hardware!$C$13 | H20: =Capex!D24/Hardware!$C$13 | I20: =Capex!D24/Hardware!$C$13 | J20: =Capex!D24/Hardware!$C$13 | K20: =Capex!D24/Hardware!$C$13 | L20: =Capex!D24/Hardware!$C$13
A21: 2028 BOS batch | B21: ZAR'000 / year | C21: 0 | D21: 0 | E21: =Capex!E24/Hardware!$C$13 | F21: =Capex!E24/Hardware!$C$13 | G21: =Capex!E24/Hardware!$C$13 | H21: =Capex!E24/Hardware!$C$13 | I21: =Capex!E24/Hardware!$C$13 | J21: =Capex!E24/Hardware!$C$13 | K21: =Capex!E24/Hardware!$C$13 | L21: =Capex!E24/Hardware!$C$13
A22: 2029 BOS batch | B22: ZAR'000 / year | C22: 0 | D22: 0 | E22: 0 | F22: =Capex!F24/Hardware!$C$13 | G22: =Capex!F24/Hardware!$C$13 | H22: =Capex!F24/Hardware!$C$13 | I22: =Capex!F24/Hardware!$C$13 | J22: =Capex!F24/Hardware!$C$13 | K22: =Capex!F24/Hardware!$C$13 | L22: =Capex!F24/Hardware!$C$13
A23: 2030 BOS batch | B23: ZAR'000 / year | C23: 0 | D23: 0 | E23: 0 | F23: 0 | G23: =Capex!G24/Hardware!$C$13 | H23: =Capex!G24/Hardware!$C$13 | I23: =Capex!G24/Hardware!$C$13 | J23: =Capex!G24/Hardware!$C$13 | K23: =Capex!G24/Hardware!$C$13 | L23: =Capex!G24/Hardware!$C$13
A24: 2031 BOS batch | B24: ZAR'000 / year | C24: 0 | D24: 0 | E24: 0 | F24: 0 | G24: 0 | H24: =Capex!H24/Hardware!$C$13 | I24: =Capex!H24/Hardware!$C$13 | J24: =Capex!H24/Hardware!$C$13 | K24: =Capex!H24/Hardware!$C$13 | L24: =Capex!H24/Hardware!$C$13
A25: 2032 BOS batch | B25: ZAR'000 / year | C25: 0 | D25: 0 | E25: 0 | F25: 0 | G25: 0 | H25: 0 | I25: =Capex!I24/Hardware!$C$13 | J25: =Capex!I24/Hardware!$C$13 | K25: =Capex!I24/Hardware!$C$13 | L25: =Capex!I24/Hardware!$C$13
A26: 2033 BOS batch | B26: ZAR'000 / year | C26: 0 | D26: 0 | E26: 0 | F26: 0 | G26: 0 | H26: 0 | I26: 0 | J26: =Capex!J24/Hardware!$C$13 | K26: =Capex!J24/Hardware!$C$13 | L26: =Capex!J24/Hardware!$C$13
A27: 2034 BOS batch | B27: ZAR'000 / year | C27: 0 | D27: 0 | E27: 0 | F27: 0 | G27: 0 | H27: 0 | I27: 0 | J27: 0 | K27: =Capex!K24/Hardware!$C$13 | L27: =Capex!K24/Hardware!$C$13
A28: 2035 BOS batch | B28: ZAR'000 / year | C28: 0 | D28: 0 | E28: 0 | F28: 0 | G28: 0 | H28: 0 | I28: 0 | J28: 0 | K28: 0 | L28: =Capex!L24/Hardware!$C$13
A30: Total BOS depreciation | B30: ZAR'000 | C30: =SUM(C19:C28) | D30: =SUM(D19:D28) | E30: =SUM(E19:E28) | F30: =SUM(F19:F28) | G30: =SUM(G19:G28) | H30: =SUM(H19:H28) | I30: =SUM(I19:I28) | J30: =SUM(J19:J28) | ... L30: =SUM(L19:L28)
A32: Total depreciation | B32: ZAR'000 | C32: =C16+C30 | D32: =D16+D30 | E32: =E16+E30 | F32: =F16+F30 | G32: =G16+G30 | H32: =H16+H30 | I32: =I16+I30 | J32: =J16+J30 | ... L32: =L16+L30

Sheet Debt
A1: Simple Phase 1 Financing Layer
A3: Funding assumptions | E3: Simplification | F3: Debt schedule is intentionally simple (bullet structures) for Phase 1 proof modelling. Replace with executed facility terms once term sheets are signed.
A4: Asset-backed share | B4: % | C4: 0.4375
A5: Mezz share | B5: % | C5: 0.4375
A6: Equity share | B6: % | C6: 0.125
A7: Asset-backed rate | B7: % | C7: 0.1
A8: Mezz rate | B8: % | C8: 0.1225
A9: Asset-backed tenor | B9: years | C9: 2
A10: Mezz tenor | B10: years | C10: 5
A12: Debt schedule
A13: Driver | B13: Unit | C13: 2026 | D13: 2027 | E13: 2028 | F13: 2029 | G13: 2030 | H13: 2031 | I13: 2032 | J13: 2033 | K13: 2034 | L13: 2035
A14: Asset-backed draw | B14: ZAR'000 | C14: =Capex!C25*$C$4 | D14: =Capex!D25*$C$4 | E14: =Capex!E25*$C$4 | F14: =Capex!F25*$C$4 | G14: =Capex!G25*$C$4 | H14: =Capex!H25*$C$4 | I14: =Capex!I25*$C$4 | J14: =Capex!J25*$C$4 | ... L14: =Capex!L25*$C$4
A15: Mezz draw | B15: ZAR'000 | C15: =Capex!C25*$C$5 | D15: =Capex!D25*$C$5 | E15: =Capex!E25*$C$5 | F15: =Capex!F25*$C$5 | G15: =Capex!G25*$C$5 | H15: =Capex!H25*$C$5 | I15: =Capex!I25*$C$5 | J15: =Capex!J25*$C$5 | ... L15: =Capex!L25*$C$5
A16: Equity funding | B16: ZAR'000 | C16: =Capex!C25*$C$6 | D16: =Capex!D25*$C$6 | E16: =Capex!E25*$C$6 | F16: =Capex!F25*$C$6 | G16: =Capex!G25*$C$6 | H16: =Capex!H25*$C$6 | I16: =Capex!I25*$C$6 | J16: =Capex!J25*$C$6 | ... L16: =Capex!L25*$C$6
A17: Asset-backed opening | B17: ZAR'000 | C17: 0 | D17: =C20 | E17: =D20 | F17: =E20 | G17: =F20 | H17: =G20 | I17: =H20 | J17: =I20 | K17: =J20 | L17: =K20
A18: Asset-backed interest | B18: ZAR'000 | C18: =(C17+C14/2)*$C$7 | D18: =(D17+D14/2)*$C$7 | E18: =(E17+E14/2)*$C$7 | F18: =(F17+F14/2)*$C$7 | G18: =(G17+G14/2)*$C$7 | H18: =(H17+H14/2)*$C$7 | I18: =(I17+I14/2)*$C$7 | J18: =(J17+J14/2)*$C$7 | ... L18: =(L17+L14/2)*$C$7
A19: Asset-backed principal | B19: ZAR'000 | C19: =IF(C$13=2026+$C$9-1,$C$14,0) | D19: =IF(D$13=2026+$C$9-1,$C$14,0) | E19: =IF(E$13=2026+$C$9-1,$C$14,0) | F19: =IF(F$13=2026+$C$9-1,$C$14,0) | G19: =IF(G$13=2026+$C$9-1,$C$14,0) | H19: =IF(H$13=2026+$C$9-1,$C$14,0) | I19: =IF(I$13=2026+$C$9-1,$C$14,0) | J19: =IF(J$13=2026+$C$9-1,$C$14,0) | ... L19: =IF(L$13=2026+$C$9-1,$C$14,0)
A20: Asset-backed closing | B20: ZAR'000 | C20: =C17+C14-C19 | D20: =D17+D14-D19 | E20: =E17+E14-E19 | F20: =F17+F14-F19 | G20: =G17+G14-G19 | H20: =H17+H14-H19 | I20: =I17+I14-I19 | J20: =J17+J14-J19 | ... L20: =L17+L14-L19
A21: Mezz opening | B21: ZAR'000 | C21: 0 | D21: =C24 | E21: =D24 | F21: =E24 | G21: =F24 | H21: =G24 | I21: =H24 | J21: =I24 | K21: =J24 | L21: =K24
A22: Mezz interest | B22: ZAR'000 | C22: =(C21+C15/2)*$C$8 | D22: =(D21+D15/2)*$C$8 | E22: =(E21+E15/2)*$C$8 | F22: =(F21+F15/2)*$C$8 | G22: =(G21+G15/2)*$C$8 | H22: =(H21+H15/2)*$C$8 | I22: =(I21+I15/2)*$C$8 | J22: =(J21+J15/2)*$C$8 | ... L22: =(L21+L15/2)*$C$8
A23: Mezz principal | B23: ZAR'000 | C23: =IF(C$13=2026+$C$10-1,$C$15,0) | D23: =IF(D$13=2026+$C$10-1,$C$15,0) | E23: =IF(E$13=2026+$C$10-1,$C$15,0) | F23: =IF(F$13=2026+$C$10-1,$C$15,0) | G23: =IF(G$13=2026+$C$10-1,$C$15,0) | H23: =IF(H$13=2026+$C$10-1,$C$15,0) | I23: =IF(I$13=2026+$C$10-1,$C$15,0) | J23: =IF(J$13=2026+$C$10-1,$C$15,0) | ... L23: =IF(L$13=2026+$C$10-1,$C$15,0)
A24: Mezz closing | B24: ZAR'000 | C24: =C21+C15-C23 | D24: =D21+D15-D23 | E24: =E21+E15-E23 | F24: =F21+F15-F23 | G24: =G21+G15-G23 | H24: =H21+H15-H23 | I24: =I21+I15-I23 | J24: =J21+J15-J23 | ... L24: =L21+L15-L23
A25: Total interest | B25: ZAR'000 | C25: =C18+C22 | D25: =D18+D22 | E25: =E18+E22 | F25: =F18+F22 | G25: =G18+G22 | H25: =H18+H22 | I25: =I18+I22 | J25: =J18+J22 | ... L25: =L18+L22
A26: Total principal | B26: ZAR'000 | C26: =C19+C23 | D26: =D19+D23 | E26: =E19+E23 | F26: =F19+F23 | G26: =G19+G23 | H26: =H19+H23 | I26: =I19+I23 | J26: =J19+J23 | ... L26: =L19+L23

Sheet Returns
A1: Returns, Cash Flow and Basic Valuation
A3: Driver | B3: Unit | C3: 2026 | D3: 2027 | E3: 2028 | F3: 2029 | G3: 2030 | H3: 2031 | I3: 2032 | J3: 2033 | K3: 2034 | L3: 2035
A4: Total revenue | B4: ZAR'000 | C4: =Revenue!C38 | D4: =Revenue!D38 | E4: =Revenue!E38 | F4: =Revenue!F38 | G4: =Revenue!G38 | H4: =Revenue!H38 | I4: =Revenue!I38 | J4: =Revenue!J38 | ... L4: =Revenue!L38
A5: Total opex | B5: ZAR'000 | C5: =Opex!C37 | D5: =Opex!D37 | E5: =Opex!E37 | F5: =Opex!F37 | G5: =Opex!G37 | H5: =Opex!H37 | I5: =Opex!I37 | J5: =Opex!J37 | ... L5: =Opex!L37
A6: EBITDA | B6: ZAR'000 | C6: =C4-C5 | D6: =D4-D5 | E6: =E4-E5 | F6: =F4-F5 | G6: =G4-G5 | H6: =H4-H5 | I6: =I4-I5 | J6: =J4-J5 | ... L6: =L4-L5
A7: Depreciation | B7: ZAR'000 | C7: =Depreciation!C32 | D7: =Depreciation!D32 | E7: =Depreciation!E32 | F7: =Depreciation!F32 | G7: =Depreciation!G32 | H7: =Depreciation!H32 | I7: =Depreciation!I32 | J7: =Depreciation!J32 | ... L7: =Depreciation!L32
A8: EBIT | B8: ZAR'000 | C8: =C6-C7 | D8: =D6-D7 | E8: =E6-E7 | F8: =F6-F7 | G8: =G6-G7 | H8: =H6-H7 | I8: =I6-I7 | J8: =J6-J7 | ... L8: =L6-L7
A9: Tax | B9: ZAR'000 | C9: =IF(C8>0,C8*Assumptions!C14,0) | D9: =IF(D8>0,D8*Assumptions!D14,0) | E9: =IF(E8>0,E8*Assumptions!E14,0) | F9: =IF(F8>0,F8*Assumptions!F14,0) | G9: =IF(G8>0,G8*Assumptions!G14,0) | H9: =IF(H8>0,H8*Assumptions!H14,0) | I9: =IF(I8>0,I8*Assumptions!I14,0) | J9: =IF(J8>0,J8*Assumptions!J14,0) | ... L9: =IF(L8>0,L8*Assumptions!L14,0)
A10: NOPAT | B10: ZAR'000 | C10: =C8-C9 | D10: =D8-D9 | E10: =E8-E9 | F10: =F8-F9 | G10: =G8-G9 | H10: =H8-H9 | I10: =I8-I9 | J10: =J8-J9 | ... L10: =L8-L9
A11: Capex | B11: ZAR'000 | C11: =Capex!C25 | D11: =Capex!D25 | E11: =Capex!E25 | F11: =Capex!F25 | G11: =Capex!G25 | H11: =Capex!H25 | I11: =Capex!I25 | J11: =Capex!J25 | ... L11: =Capex!L25
A12: Unlevered FCF | B12: ZAR'000 | C12: =C10+C7-C11 | D12: =D10+D7-D11 | E12: =E10+E7-E11 | F12: =F10+F7-F11 | G12: =G10+G7-G11 | H12: =H10+H7-H11 | I12: =I10+I7-I11 | J12: =J10+J7-J11 | ... L12: =L10+L7-L11
A13: Interest | B13: ZAR'000 | C13: =Debt!C25 | D13: =Debt!D25 | E13: =Debt!E25 | F13: =Debt!F25 | G13: =Debt!G25 | H13: =Debt!H25 | I13: =Debt!I25 | J13: =Debt!J25 | ... L13: =Debt!L25
A14: Principal | B14: ZAR'000 | C14: =Debt!C26 | D14: =Debt!D26 | E14: =Debt!E26 | F14: =Debt!F26 | G14: =Debt!G26 | H14: =Debt!H26 | I14: =Debt!I26 | J14: =Debt!J26 | ... L14: =Debt!L26
A15: Debt draws | B15: ZAR'000 | C15: =Debt!C14+Debt!C15 | D15: =Debt!D14+Debt!D15 | E15: =Debt!E14+Debt!E15 | F15: =Debt!F14+Debt!F15 | G15: =Debt!G14+Debt!G15 | H15: =Debt!H14+Debt!H15 | I15: =Debt!I14+Debt!I15 | J15: =Debt!J14+Debt!J15 | ... L15: =Debt!L14+Debt!L15
A16: Cash flow to equity | B16: ZAR'000 | C16: =C6-C9-C11-C13-C14+C15 | D16: =D6-D9-D11-D13-D14+D15 | E16: =E6-E9-E11-E13-E14+E15 | F16: =F6-F9-F11-F13-F14+F15 | G16: =G6-G9-G11-G13-G14+G15 | H16: =H6-H9-H11-H13-H14+H15 | I16: =I6-I9-I11-I13-I14+I15 | J16: =J6-J9-J11-J13-J14+J15 | ... L16: =L6-L9-L11-L13-L14+L15
A17: DSCR | B17: x | C17: =IF((C13+C14)>0,(C6-C9)/(C13+C14),"") | D17: =IF((D13+D14)>0,(D6-D9)/(D13+D14),"") | E17: =IF((E13+E14)>0,(E6-E9)/(E13+E14),"") | F17: =IF((F13+F14)>0,(F6-F9)/(F13+F14),"") | G17: =IF((G13+G14)>0,(G6-G9)/(G13+G14),"") | H17: =IF((H13+H14)>0,(H6-H9)/(H13+H14),"") | I17: =IF((I13+I14)>0,(I6-I9)/(I13+I14),"") | J17: =IF((J13+J14)>0,(J6-J9)/(J13+J14),"") | ... L17: =IF((L13+L14)>0,(L6-L9)/(L13+L14),"")
A20: Summary metrics
A21: Unlevered IRR | B21: =IRR(C12:L12)
A22: Equity IRR | B22: =IRR(C16:L16)
A23: Initial capex benchmark vs R544m | B23: =C11/544000
A24: Year 1 EBITDA margin | B24: =C6/C4

Sheet Checks
A1: Model Integrity Checks
A3: Check | B3: Formula / value | C3: Interpretation | D3: Status
A4: Funding mix sums to 100% | B4: =SUM(Debt!C4:Debt!C6) | C4: PASS if 100% | D4: =IF(ABS(B4-1)<0.0001,"PASS","FAIL")
A5: Phase 1 MW totals 20MW in 2026 | B5: =Site_Assumptions!C32 | C5: PASS if 20 | D5: =IF(B5=20,"PASS","CHECK")
A6: No base case DR revenue | B6: =SUM(Revenue!C37:L37) | C6: PASS if 0 unless intentionally enabled | D6: =IF(B6=0,"PASS","CHECK")
A7: Year 1 capex close to R544m benchmark | B7: =Capex!C25/544000 | C7: 1.00x is aligned | D7: =IF(ABS(B7-1)<0.05,"PASS","CHECK")
A8: No negative debt balances | B8: =MIN(Debt!C20:L20,Debt!C24:L24) | C8: Should be >= 0 | D8: =IF(B8>=0,"PASS","FAIL")
A9: No negative depreciation | B9: =MIN(Depreciation!C32:L32) | C9: Should be >= 0 | D9: =IF(B9>=0,"PASS","FAIL")

Sheet Legacy_Audit_Note
A1: Why this workbook replaces the legacy model
A4: • Legacy workbook contains critical formula errors in the P&L, cash flow and valuation sections.
A5: • Legacy workbook mixes proposal sandboxes, raw source tabs and core model tabs in one file.
A6: • Peer comps depend on workstation-specific add-ins and fail with #NAME? outside that environment.
A7: • The phase strategy in the March 2026 memo is a 10MW + 10MW proof phase, not a generic 20MW-to-2GW ramp from year 1.
A8: • This clean workbook should be treated as the controlled starting point for the next investor model iteration.
