Workbook

Sheet Dashboard
A1: PHASE 1 UNDERWRITING MODEL · ENERGY THAT YIELDS
A2: 20MW proof-of-execution case: 10MW Grootvlei + 10MW AMSA Vanderbijlpark | Funding, commissioning and debt-case underwrite
A4: Selected Case | D4: Phase 1 MW | G4: Site Split | J4: Total Capex
A5: =Controls!$C$4 -> Debt Case | D5: =Controls!$B$32 -> 20 | G5: =Controls!$B$33&" / "&Controls!$B$34&" MW" -> 10 / 10 MW | J5: =SUM(Capex_36M!$O$2:$O$37) -> 511456.86
A6: underwriting scenario | D6: MW (10 GVL + 10 AMSA) | G6: GVL / AMSA | J6: ZAR '000
A9: Peak Funding Req. | D9: Total Equity Drawn | G9: Total Debt Drawn | J9: Peak Debt Balance
A10: =SUM(Funding_36M!$J$2:$J$37)+SUM(Funding_36M!$K$2:$K$37) -> 535535.9 | D10: =SUM(Funding_36M!$J$2:$J$37) -> 68000 | G10: =SUM(Funding_36M!$K$2:$K$37) -> 467535.9 | J10: =MAX(Funding_36M!$T$2:$T$37) -> 482022.09
A11: ZAR '000 (total external) | D11: ZAR '000 | G11: ZAR '000 | J11: ZAR '000
A14: Year-1 EBITDA | D14: 36M Revenue | G14: 36M BTC Mined | J14: Break-even BTC Y1
A15: =Annual_Summary!$C$11 -> 100722.52 | D15: =SUM(Revenue_36M!$P$2:$P$37) -> 578669.44 | G15: =SUM(Revenue_36M!$H$2:$H$37) -> 426.54126 | J15: =Sensitivity!$B$11 -> 42463.035
A16: ZAR '000 | D16: ZAR '000 | G16: BTC | J16: USD/BTC
A19: Min DSCR (12M) | D19: DSCR Covenant | G19: Unlevered IRR | J19: Equity IRR
A20: =MIN(Funding_36M!$AA$14:$AA$37) -> 0.50405629 | D20: =Annual_Summary!$B$26 -> 1.5 | G20: =IFERROR((1+IRR(Funding_36M!$AC$2:$AC$37,0.01))^12-1,"n/a") -> 0.1974839 | J20: =IFERROR((1+IRR(Funding_36M!$AD$2:$AD$37,0.01))^12-1,"n/a") -> 0.31458689
A21: trailing 12-month | D21: indicative minimum | G21: incl. continuation value | J21: levered, continuation value
A24: Closing Cash M36 | D24: Closing Debt M36 | G24: DSRA Funded | J24: Facility Headroom
A25: =INDEX(Funding_36M!$Q$2:$Q$37,36) -> 131624.43 | D25: =INDEX(Funding_36M!$T$2:$T$37,36) -> 482022.09 | G25: =Controls!$B$111 -> 27212.5 | J25: =(Controls!$B$100+Controls!$B$101+Controls!$B$104)-(SUM(Funding_36M!$J$2:$J$37)+SUM(Funding_36M!$K$2:$K$37)) -> 20464.102
A26: ZAR '000 (incl. DSRA) | D26: ZAR '000 | G26: ZAR '000 (restricted) | J26: ZAR '000 vs committed
A29: Capital stack — committed vs drawn (Debt Case)
A30: Tranche | D30: Committed | F30: Drawn | H30: Headroom | J30: Terms
A31: Sponsor equity | D31: =Controls!$B$100 -> 68000 | F31: =SUM(Funding_36M!$J$2:$J$37) -> 68000 | H31: =D31-F31 -> 0 | J31: Drawn first; USD$4M @ R17
A32: Antalpha (asset-backed) | D32: =Controls!$B$101 -> 238000 | F32: =SUM(Funding_36M!$U$2:$U$37) -> 238000 | H32: =D32-F32 -> 0 | J32: 10% USD, 24-mo bullet, Bitmain collateral
A33: DMTN Tranche 1 | D33: =Controls!$B$104 -> 250000 | F33: =SUM(Funding_36M!$V$2:$V$37) -> 229535.9 | H33: =D33-F33 -> 20464.102 | J33: 12.25%, 5yr, convertible to equity at IPO
A34: Total committed | D34: =Controls!$B$100+Controls!$B$101+Controls!$B$104 -> 556000 | F34: =F31+F32+F33 -> 535535.9 | H34: =D34-F34 -> 20464.102 | J34: vs total external funding requirement
A37: Phase 1 capex reconciliation — this model vs deck (p30)
A38: Capex line | D38: This model | F38: Deck (p30) | H38: Variance | J38: Note
A39: ASIC hardware (S21 XP-class) | D39: =SUM(Capex_36M!$G$2:$G$37) -> 218895.24 | F39: 374000 | H39: =D39-F39 -> -155104.76 | J39: Model uses lower USD/TH (see below)
A40: Hydro containers + cooling | D40: =SUM(Capex_36M!$H$2:$H$37) -> 65450 | F40: 102000 | H40: =D40-F40 -> -36550 | J40: Containers only here; cooling in EPC
A41: Electrical / site EPC | D41: =SUM(Capex_36M!$I$2:$I$37) -> 126872 | F41: 51000 | H41: =D41-F41 -> 75872 | J41: Model carries fuller EPC scope
A42: Solar PV (AMSA) | D42: =SUM(Capex_36M!$J$2:$J$37) -> 70000 | F42: 0 | H42: =D42-F42 -> 70000 | J42: Added in model; not in deck p30
A43: Spares + tools + setup | D43: =SUM(Capex_36M!$K$2:$K$37)+SUM(Capex_36M!$L$2:$L$37) -> 8712.9048 | F43: 0 | H43: =D43-F43 -> 8712.9048 | J43: Itemised in model
A44: Logistics + duties | D44: =SUM(Capex_36M!$M$2:$M$37) -> 21526.714 | F44: 0 | H44: =D44-F44 -> 21526.714 | J44: Freight, clearing, duty, insurance
A45: Total Phase 1 capex | D45: =SUM(Capex_36M!$O$2:$O$37) -> 511456.86 | F45: 527000 | H45: =D45-F45 -> -15543.143 | J45: Totals within ~3%; mix differs
A46: Hardware cost basis (USD/TH) | D46: =Controls!$B$46/Controls!$B$43 -> 8.45 | F46: ~$11-15 mkt | J46: Model hardware is optimistic; stress in Sensitivity
A49: Structuring flags and underwriting framing
A50: ■ Antalpha R238m facility is a 24-month BULLET (interest-only). Balance incl. capitalised grace interest ≈ R246m falls due in Month 24 and must be refinanced or converted ahead of the Year-3 thin period.
A51: ■ Min trailing-12M DSCR of ~0.50x in Year 3 is BELOW the indicative 1.50x covenant on a standalone BTC-only basis (block-subsidy halving + rising network difficulty compress EBITDA).
A52: Mitigants modelled / available: 24-month Antalpha bullet retired or refinanced before Year 3; DMTN equitised at IPO (conversion toggle in Controls); first-ranking ASIC / container security; funded DSRA of ~R27m; and demand-response + tariff-relief upside in the Sponsor and Upside cases (DR/AI are off in this Debt Case).
A54: Scope: deliberately limited to the initial 20MW proof phase (10MW Grootvlei + 10MW AMSA Vanderbijlpark). Not the 10-year acceleration case; excludes owned-inference GPU economics (Layer 5). Purpose: show funders procurement, commissioning, capex, the actual capital stack, coverage and milestone gates before scale-up capital is released.
A56: IRR note: Unlevered ~20% / Equity ~31% are indicative and depend on the continuation (terminal) value input in Controls — the proven 20MW platform’s value as it scales per the 10-year master model. At zero continuation value the standalone 36-month BTC-only project does not return capital. IRR is shown across continuation values in the Sensitivity tab.
A58: Charts — annual P&L · monthly funding & cash · 20MW deployment ramp

Sheet Controls
A1: BitMach Phase 1 Underwriting Model
A2: Purpose: lender/infrastructure-fund underwriting model for the initial 20MW proof-of-execution phase. Values are in ZAR '000 unless otherwise stated.
A4: Scenario selector | B4: Selected case | C4: Debt Case | D4: Change via dropdown / type exact case name | G4: Scenario table
G5: Case | H5: BTC growth p.a. | I5: Network growth p.a. | J5: Uptime | K5: DR enabled | L5: DR start month | M5: DR recognition factor | N5: AI/DC pilot enabled | O5: AI start month | P5: Equity share | Q5: Debt rate
A6: Timing | G6: Debt Case | H6: 0.05 | I6: 0.2 | J6: 0.96 | K6: 0 | L6: 99 | M6: 0 | N6: 0 | O6: 99 | P6: 0.35 | Q6: 0.13
A7: Start date | B7: 46204 | C7: Date | D7: First month of Phase 1 funding / rollout schedule. | G7: Sponsor Case | H7: 0.1 | I7: 0.15 | J7: 0.97 | K7: 1 | L7: 13 | M7: 0.35 | N7: 0 | O7: 99 | P7: 0.35 | Q7: 0.13
A8: Scenario BTC growth p.a. | B8: =INDEX($H$6:$H$8,MATCH($C$4,$G$6:$G$8,0)) -> 0.05 | C8: % | D8: Linked to selected scenario. | G8: Upside Case | H8: 0.12 | I8: 0.1 | J8: 0.98 | K8: 1 | L8: 7 | M8: 0.6 | N8: 1 | O8: 18 | P8: 0.3 | Q8: 0.11
A9: Scenario network hash growth p.a. | B9: =INDEX($I$6:$I$8,MATCH($C$4,$G$6:$G$8,0)) -> 0.2 | C9: % | D9: Linked to selected scenario; higher values reduce BitMach share of network rewards.
A10: Scenario uptime | B10: =INDEX($J$6:$J$8,MATCH($C$4,$G$6:$G$8,0)) -> 0.96 | C10: % | D10: Technical uptime assumption before strategic curtailment.
A11: DR enabled | B11: =INDEX($K$6:$K$8,MATCH($C$4,$G$6:$G$8,0)) -> 0 | C11: 0/1 | D11: 0 = excluded from debt underwriting; 1 = included in selected scenario.
A12: DR start month | B12: =INDEX($L$6:$L$8,MATCH($C$4,$G$6:$G$8,0)) -> 99 | C12: Month # | D12: Month when DR revenue is allowed to start in selected scenario.
A13: DR recognition factor | B13: =INDEX($M$6:$M$8,MATCH($C$4,$G$6:$G$8,0)) -> 0 | C13: % | D13: Probability / evidence weighting applied to illustrative DR mechanisms.
A14: AI/DC pilot enabled | B14: =INDEX($N$6:$N$8,MATCH($C$4,$G$6:$G$8,0)) -> 0 | C14: 0/1 | D14: Kept off in underwriting cases; shows optional small pilot only in upside.
A15: AI start month | B15: =INDEX($O$6:$O$8,MATCH($C$4,$G$6:$G$8,0)) -> 99 | C15: Month # | D15: Month when optional AI/DC pilot revenue starts in upside case.
A16: Equity share | B16: =INDEX($P$6:$P$8,MATCH($C$4,$G$6:$G$8,0)) -> 0.35 | C16: % | D16: Equity share of external cash funding requirement.
A17: Debt share | B17: =1-B16 -> 0.65 | C17: % | D17: Debt share of external cash funding requirement.
A18: Debt interest rate | B18: =INDEX($Q$6:$Q$8,MATCH($C$4,$G$6:$G$8,0)) -> 0.13 | C18: % | D18: Indicative senior / structured debt rate.
A19: Debt grace period | B19: 12 | C19: Months | D19: Interest capitalises during grace period; debt service starts after month 12.
A20: Debt tenor | B20: 60 | C20: Months | D20: Indicative amortisation tenor for project debt.
A21: Arrangement fee | B21: 0.01 | C21: % | D21: Deducted from gross debt draw in funding schedule.
A22: Minimum cash buffer | B22: 5000 | C22: ZAR '000 | D22: Minimum operating cash buffer held through the forecast (separate from DSRA below).
A23: BTC / protocol
A24: BTC price start | B24: 75000 | C24: USD/BTC | D24: Starting spot price assumption; stress in Sensitivity tab.
A25: FX rate | B25: 17 | C25: ZAR/USD | D25: Used for BTC revenue and USD-denominated capex.
A26: Network hash start | B26: 900000000 | C26: TH/s | D26: Bitcoin network hash rate starting point.
A27: Block subsidy start | B27: 3.125 | C27: BTC/block | D27: Current subsidy before next halving.
A28: Next halving month | B28: 23 | C28: Month # | D28: Approximate month of next halving within 36-month forecast.
A29: Fee contribution start | B29: 0.12 | C29: % of subsidy | D29: Transaction fee contribution as % of subsidy equivalent in month 1.
A30: Fee contribution monthly increase | B30: 0.0025 | C30: % points | D30: Gradual increase in transaction fee contribution over forecast.
A31: Power / deployment
A32: Phase 1 total mining MW | B32: 20 | C32: MW | D32: Fixed to 10MW Grootvlei + 10MW AMSA Vanderbijlpark.
A33: Grootvlei mining MW | B33: 10 | C33: MW | D33: Phase 1 underwriting site split.
A34: AMSA mining MW | B34: 10 | C34: MW | D34: Phase 1 underwriting site split.
A35: AMSA solar MW | B35: 10 | C35: MW | D35: Solar capacity available for Phase 1 blended power at AMSA.
A36: Mining operating hours | B36: 19 | C36: hours/day | D36: Interruptible mining load profile under Eskom arrangement.
A37: AMSA solar hours | B37: 9 | C37: hours/day | D37: Average solar energy hours used to offset AMSA grid purchases.
A38: Initial Eskom tariff | B38: 1.2 | C38: R/kWh | D38: Agreed / initial tariff assumption for first 18 months.
A39: Post-initial Eskom tariff | B39: 0.6 | C39: R/kWh | D39: Target tariff after initial period.
A40: Initial tariff period | B40: 18 | C40: Months | D40: First 18 months at R1.20/kWh; thereafter R0.60/kWh.
A41: Solar O&M | B41: 0.02 | C41: % capex p.a. | D41: Annual operating cost as % of solar capex.
A42: Hardware / container
A43: Miner hashrate | B43: 700 | C43: TH/unit | D43: Bitmain Antminer S21 XP Imm/Hyd class (matches deck & Antalpha Bitmain collateral). Hashrate per unit is indicative; total economics driven by efficiency (J/TH) and MW.
A44: Miner efficiency | B44: 12.5 | C44: J/TH | D44: Power draw per TH (S21 XP Hydro ~12 J/TH). Miner power = hashrate x efficiency.
A45: Miner power | B45: =B43*B44 -> 8750 | C45: W/unit | D45: Calculated miner power.
A46: Miner price | B46: 5915 | C46: USD/unit | D46: Hardware price assumption; implies USD/TH shown in Capex reconciliation. Update on final Bitmain PO.
A47: Auxiliary load | B47: 0.05 | C47: % | D47: Auxiliary/cooling/parasitic load on top of IT mining load.
A48: Slots per container | B48: 240 | C48: Miners/container | D48: Container density assumption.
A49: Container gross MW | B49: =B48*B45/1000000*(1+B47) -> 2.205 | C49: MW/container | D49: Gross electrical capacity per container incl. auxiliary load.
A50: Container cost | B50: 350000 | C50: USD/container | D50: Hydro container cost assumption.
A51: Capex
A52: Electrical fixed per site | B52: 25376 | C52: ZAR '000/site | D52: Site-start fixed electrical/site integration capex derived from 20MW electrical basis.
A53: Electrical variable per MW | B53: 3806 | C53: ZAR '000/MW | D53: Variable electrical/site integration capex per deployed MW.
A54: Solar capex | B54: 7000 | C54: ZAR '000/MW | D54: Solar PV capex assumption for AMSA Phase 1.
A55: Initial spares | B55: 0.02 | C55: % hardware | D55: Initial spares allowance.
A56: Tools / equipment per site | B56: 750 | C56: ZAR '000/site | D56: Initial tools / site equipment.
A57: Staff hardware per FTE | B57: 35 | C57: ZAR '000/FTE | D57: Laptop/phone/PPE per new employee.
A58: Freight | B58: 8000 | C58: USD/container | D58: Ocean freight per container.
A59: Port / clearing | B59: 150 | C59: ZAR '000/container | D59: Port handling and customs clearing.
A60: Inland trucking | B60: 70 | C60: ZAR '000/container | D60: Inland logistics.
A61: Crane / rigging | B61: 50 | C61: ZAR '000/container | D61: Lifts and site rigging.
A62: Cargo insurance | B62: 0.01 | C62: % hardware+containers | D62: Transit insurance.
A63: Import duty | B63: 0.05 | C63: % hardware+containers | D63: Import duties where applicable.
... A66: Legal setup | B66: 600 | C66: ZAR '000 | D66: Initial legal / contracting cost.
A67: Opex
A68: Fixed corporate FTE | B68: 4 | C68: FTE | D68: Core management / finance / operations team.
A69: Corporate salary | B69: 1000 | C69: ZAR '000/FTE/year | D69: Fully loaded base salary before benefits.
A70: Site management FTE/site | B70: 2 | C70: FTE/site | D70: Site lead / supervisor roles.
A71: Site management salary | B71: 700 | C71: ZAR '000/FTE/year | D71: Site management salary before benefits.
A72: Technicians FTE/MW | B72: 0.35 | C72: FTE/MW | D72: Technician staffing intensity.
A73: Technician salary | B73: 350 | C73: ZAR '000/FTE/year | D73: Technician salary before benefits.
A74: Electricians FTE/MW | B74: 0.08 | C74: FTE/MW | D74: Electrician staffing intensity.
A75: Electrician salary | B75: 450 | C75: ZAR '000/FTE/year | D75: Electrician salary before benefits.
A76: Benefits load | B76: 0.2 | C76: % payroll | D76: Benefits / statutory / payroll burden.
A77: Travel | B77: 0.06 | C77: % payroll | D77: Recurring travel and accommodation as % of payroll.
A78: Mobilisation travel per site | B78: 250 | C78: ZAR '000/site | D78: One-off travel / accommodation for site mobilisation.
A79: SaaS per FTE | B79: 3.5 | C79: ZAR '000/FTE/month | D79: Software subscriptions and monitoring tools.
... A86: Other utilities | B86: 10 | C86: ZAR '000/MW/month | D86: Water / minor utilities / site services.
A87: DR mechanisms
A88: IDR standby rate | B88: 75 | C88: ZAR '000/MW/month | D88: Illustrative capacity payment. Update only once contracted.
A89: DDMP incentive total | B89: 3000 | C89: ZAR '000/MW | D89: Public DDMP-style benchmark over 24-month sustainability period.
A90: DDMP incentive tenor | B90: 24 | C90: Months | D90: Assumed tenor for DDMP-style incentive recognition.
A91: Event revenue rate | B91: 3 | C91: ZAR '000/MW/event | D91: Illustrative curtailment/event value.
A92: Events per month | B92: 2 | C92: Events/month | D92: Illustrative grid events per month.
A93: AI/DC optional pilot
A94: AI/DC pilot MW | B94: 5 | C94: MW | D94: Optional pilot capacity only in Upside Case; not included in debt case.
A95: AI/DC resale tariff | B95: 2.5 | C95: R/kWh | D95: Revenue tariff for customer compute power resale.
A96: AI/DC import premium | B96: 0.2 | C96: R/kWh | D96: Premium on power cost for essential load import.
A97: AI/DC hosting fee | B97: 250 | C97: ZAR '000/MW/month | D97: Non-power hosting / services fee for customer-owned compute.
A99: Capital stack (actual Phase 1 deal) — supersedes generic equity-share / debt-rate above for funding
A100: Equity commitment | B100: 68000 | C100: ZAR '000 | D100: Sponsor equity USD$4M @ R17 (deck p3/p31). Drawn FIRST in funding waterfall.
A101: Antalpha facility limit | B101: 238000 | C101: ZAR '000 | D101: Asset-backed USD$14M @ R17 (deck p32). Up to ~50% of Phase 1 capex; Bitmain ASIC collateral / notarial bond.
A102: Antalpha interest rate | B102: 0.1 | C102: % | D102: USD-denominated asset-backed rate (deck p32).
A103: Antalpha tenor (bullet) | B103: 24 | C103: Months | D103: BULLET: interest-only, principal R-limit due month 24; refinance/convert required (flagged in Funding).
A104: DMTN facility limit | B104: 250000 | C104: ZAR '000 | D104: DMTN Tranche 1 (deck p31). First-ranking security over ASICs/containers/Phase 2 assets.
A105: DMTN interest rate | B105: 0.1225 | C105: % | D105: Prime+2% indicative (deck p31).
A106: DMTN tenor | B106: 60 | C106: Months | D106: 5-year; modelled interest-only in Phase 1; convertible to equity at IPO (20% discount).
A107: DMTN IPO conversion enabled | B107: 0 | C107: 0/1 | D107: 0 = off in Debt Case (conservative). 1 = equitises DMTN at conversion month (removes interest).
A108: DMTN conversion month | B108: 24 | C108: Month # | D108: Assumed IPO / conversion month if enabled.
A109: Construction interest grace | B109: 6 | C109: Months | D109: Interest capitalises during build; cash debt service begins thereafter.
A110: DSRA target (months interest) | B110: 6 | C110: Months | D110: Debt service reserve funded at close; sized on facility-limit interest (non-circular).
...

Sheet Monthly_Deployment
A1: Month # | B1: Date | C1: Month | D1: GVL Close MW | E1: AMSA Close MW | F1: Solar Close MW | G1: GVL Open MW | H1: AMSA Open MW | I1: Solar Open MW | J1: Total Close MW | K1: Avg GVL MW | L1: Avg AMSA MW | M1: Avg Solar MW | N1: Total Avg MW | O1: New Mining MW | P1: New Solar MW | Q1: Active Sites | R1: New Containers | S1: Avg Miners | T1: Effective Hashrate TH/s | U1: GVL Grid MWh | V1: AMSA Grid MWh | W1: AMSA Solar MWh
A2: 1 | B2: =EDATE(Controls!$B$7,A2-1) -> 46204 | C2: =TEXT(B2,"mmm-yy") -> Jul-26 | D2: =IF(A2<2,0,IF(A2=2,Controls!$B$33/2,Controls!$B$33)) -> 0 | E2: =IF(A2<3,0,IF(A2=3,Controls!$B$34/2,Controls!$B$34)) -> 0 | F2: =IF(A2<4,0,Controls!$B$35) -> 0 | G2: =0 -> 0 | H2: =0 -> 0 | I2: =0 -> 0 | J2: =D2+E2 -> 0 | K2: =(G2+D2)/2 -> 0 | L2: =(H2+E2)/2 -> 0 | M2: =(I2+F2)/2 -> 0 | N2: =K2+L2 -> 0 | O2: =MAX(J2,0) -> 0 | P2: =MAX(F2,0) -> 0 | Q2: =--(K2>0)+--(L2>0) -> 0 | R2: =CEILING(O2/Controls!$B$49,1) -> 0 | S2: =IF(Controls!$B$45=0,0,N2/(1+Controls!$B$47)*1000000/Controls!$B$45) -> 0 | T2: =S2*Controls!$B$43*(Controls!$B$36/24)*Controls!$B$10 -> 0 | U2: =K2*Controls!$B$36*DAY(EOMONTH(B2,0))*Controls!$B$10 -> 0 | V2: =MAX(L2*Controls!$B$36-MIN(L2,M2)*Controls!$B$37,0)*DAY(EOMONTH(B2,0))*Controls!$B$10 -> 0 | W2: =MIN(L2,M2)*Controls!$B$37*DAY(EOMONTH(B2,0))*Controls!$B$10 -> 0
A3: 2 | B3: =EDATE(Controls!$B$7,A3-1) -> 46235 | C3: =TEXT(B3,"mmm-yy") -> Aug-26 | D3: =IF(A3<2,0,IF(A3=2,Controls!$B$33/2,Controls!$B$33)) -> 5 | E3: =IF(A3<3,0,IF(A3=3,Controls!$B$34/2,Controls!$B$34)) -> 0 | F3: =IF(A3<4,0,Controls!$B$35) -> 0 | G3: =D2 -> 0 | H3: =E2 -> 0 | I3: =F2 -> 0 | J3: =D3+E3 -> 5 | K3: =(G3+D3)/2 -> 2.5 | L3: =(H3+E3)/2 -> 0 | M3: =(I3+F3)/2 -> 0 | N3: =K3+L3 -> 2.5 | O3: =MAX(J3-J2,0) -> 5 | P3: =MAX(F3-F2,0) -> 0 | Q3: =--(K3>0)+--(L3>0) -> 1 | R3: =CEILING(O3/Controls!$B$49,1) -> 3 | S3: =IF(Controls!$B$45=0,0,N3/(1+Controls!$B$47)*1000000/Controls!$B$45) -> 272.10884 | T3: =S3*Controls!$B$43*(Controls!$B$36/24)*Controls!$B$10 -> 144761.9 | U3: =K3*Controls!$B$36*DAY(EOMONTH(B3,0))*Controls!$B$10 -> 1413.6 | V3: =MAX(L3*Controls!$B$36-MIN(L3,M3)*Controls!$B$37,0)*DAY(EOMONTH(B3,0))*Controls!$B$10 -> 0 | W3: =MIN(L3,M3)*Controls!$B$37*DAY(EOMONTH(B3,0))*Controls!$B$10 -> 0
A4: 3 | B4: =EDATE(Controls!$B$7,A4-1) -> 46266 | C4: =TEXT(B4,"mmm-yy") -> Sept-26 | D4: =IF(A4<2,0,IF(A4=2,Controls!$B$33/2,Controls!$B$33)) -> 10 | E4: =IF(A4<3,0,IF(A4=3,Controls!$B$34/2,Controls!$B$34)) -> 5 | F4: =IF(A4<4,0,Controls!$B$35) -> 0 | G4: =D3 -> 5 | H4: =E3 -> 0 | I4: =F3 -> 0 | J4: =D4+E4 -> 15 | K4: =(G4+D4)/2 -> 7.5 | L4: =(H4+E4)/2 -> 2.5 | M4: =(I4+F4)/2 -> 0 | N4: =K4+L4 -> 10 | O4: =MAX(J4-J3,0) -> 10 | P4: =MAX(F4-F3,0) -> 0 | Q4: =--(K4>0)+--(L4>0) -> 2 | R4: =CEILING(O4/Controls!$B$49,1) -> 5 | S4: =IF(Controls!$B$45=0,0,N4/(1+Controls!$B$47)*1000000/Controls!$B$45) -> 1088.4354 | T4: =S4*Controls!$B$43*(Controls!$B$36/24)*Controls!$B$10 -> 579047.62 | U4: =K4*Controls!$B$36*DAY(EOMONTH(B4,0))*Controls!$B$10 -> 4104 | V4: =MAX(L4*Controls!$B$36-MIN(L4,M4)*Controls!$B$37,0)*DAY(EOMONTH(B4,0))*Controls!$B$10 -> 1368 | W4: =MIN(L4,M4)*Controls!$B$37*DAY(EOMONTH(B4,0))*Controls!$B$10 -> 0
A5: 4 | B5: =EDATE(Controls!$B$7,A5-1) -> 46296 | C5: =TEXT(B5,"mmm-yy") -> Oct-26 | D5: =IF(A5<2,0,IF(A5=2,Controls!$B$33/2,Controls!$B$33)) -> 10 | E5: =IF(A5<3,0,IF(A5=3,Controls!$B$34/2,Controls!$B$34)) -> 10 | F5: =IF(A5<4,0,Controls!$B$35) -> 10 | G5: =D4 -> 10 | H5: =E4 -> 5 | I5: =F4 -> 0 | J5: =D5+E5 -> 20 | K5: =(G5+D5)/2 -> 10 | L5: =(H5+E5)/2 -> 7.5 | M5: =(I5+F5)/2 -> 5 | N5: =K5+L5 -> 17.5 | O5: =MAX(J5-J4,0) -> 5 | P5: =MAX(F5-F4,0) -> 10 | Q5: =--(K5>0)+--(L5>0) -> 2 | R5: =CEILING(O5/Controls!$B$49,1) -> 3 | S5: =IF(Controls!$B$45=0,0,N5/(1+Controls!$B$47)*1000000/Controls!$B$45) -> 1904.7619 | T5: =S5*Controls!$B$43*(Controls!$B$36/24)*Controls!$B$10 -> 1013333.3 | U5: =K5*Controls!$B$36*DAY(EOMONTH(B5,0))*Controls!$B$10 -> 5654.4 | V5: =MAX(L5*Controls!$B$36-MIN(L5,M5)*Controls!$B$37,0)*DAY(EOMONTH(B5,0))*Controls!$B$10 -> 2901.6 | W5: =MIN(L5,M5)*Controls!$B$37*DAY(EOMONTH(B5,0))*Controls!$B$10 -> 1339.2
A6: 5 | B6: =EDATE(Controls!$B$7,A6-1) -> 46327 | C6: =TEXT(B6,"mmm-yy") -> Nov-26 | D6: =IF(A6<2,0,IF(A6=2,Controls!$B$33/2,Controls!$B$33)) -> 10 | E6: =IF(A6<3,0,IF(A6=3,Controls!$B$34/2,Controls!$B$34)) -> 10 | F6: =IF(A6<4,0,Controls!$B$35) -> 10 | G6: =D5 -> 10 | H6: =E5 -> 10 | I6: =F5 -> 10 | J6: =D6+E6 -> 20 | K6: =(G6+D6)/2 -> 10 | L6: =(H6+E6)/2 -> 10 | M6: =(I6+F6)/2 -> 10 | N6: =K6+L6 -> 20 | O6: =MAX(J6-J5,0) -> 0 | P6: =MAX(F6-F5,0) -> 0 | Q6: =--(K6>0)+--(L6>0) -> 2 | R6: =CEILING(O6/Controls!$B$49,1) -> 0 | S6: =IF(Controls!$B$45=0,0,N6/(1+Controls!$B$47)*1000000/Controls!$B$45) -> 2176.8707 | T6: =S6*Controls!$B$43*(Controls!$B$36/24)*Controls!$B$10 -> 1158095.2 | U6: =K6*Controls!$B$36*DAY(EOMONTH(B6,0))*Controls!$B$10 -> 5472 | V6: =MAX(L6*Controls!$B$36-MIN(L6,M6)*Controls!$B$37,0)*DAY(EOMONTH(B6,0))*Controls!$B$10 -> 2880 | W6: =MIN(L6,M6)*Controls!$B$37*DAY(EOMONTH(B6,0))*Controls!$B$10 -> 2592
A7: 6 | B7: =EDATE(Controls!$B$7,A7-1) -> 46357 | C7: =TEXT(B7,"mmm-yy") -> Dec-26 | D7: =IF(A7<2,0,IF(A7=2,Controls!$B$33/2,Controls!$B$33)) -> 10 | E7: =IF(A7<3,0,IF(A7=3,Controls!$B$34/2,Controls!$B$34)) -> 10 | F7: =IF(A7<4,0,Controls!$B$35) -> 10 | G7: =D6 -> 10 | H7: =E6 -> 10 | I7: =F6 -> 10 | J7: =D7+E7 -> 20 | K7: =(G7+D7)/2 -> 10 | L7: =(H7+E7)/2 -> 10 | M7: =(I7+F7)/2 -> 10 | N7: =K7+L7 -> 20 | O7: =MAX(J7-J6,0) -> 0 | P7: =MAX(F7-F6,0) -> 0 | Q7: =--(K7>0)+--(L7>0) -> 2 | R7: =CEILING(O7/Controls!$B$49,1) -> 0 | S7: =IF(Controls!$B$45=0,0,N7/(1+Controls!$B$47)*1000000/Controls!$B$45) -> 2176.8707 | T7: =S7*Controls!$B$43*(Controls!$B$36/24)*Controls!$B$10 -> 1158095.2 | U7: =K7*Controls!$B$36*DAY(EOMONTH(B7,0))*Controls!$B$10 -> 5654.4 | V7: =MAX(L7*Controls!$B$36-MIN(L7,M7)*Controls!$B$37,0)*DAY(EOMONTH(B7,0))*Controls!$B$10 -> 2976 | W7: =MIN(L7,M7)*Controls!$B$37*DAY(EOMONTH(B7,0))*Controls!$B$10 -> 2678.4
A8: 7 | B8: =EDATE(Controls!$B$7,A8-1) -> 46388 | C8: =TEXT(B8,"mmm-yy") -> Jan-27 | D8: =IF(A8<2,0,IF(A8=2,Controls!$B$33/2,Controls!$B$33)) -> 10 | E8: =IF(A8<3,0,IF(A8=3,Controls!$B$34/2,Controls!$B$34)) -> 10 | F8: =IF(A8<4,0,Controls!$B$35) -> 10 | G8: =D7 -> 10 | H8: =E7 -> 10 | I8: =F7 -> 10 | J8: =D8+E8 -> 20 | K8: =(G8+D8)/2 -> 10 | L8: =(H8+E8)/2 -> 10 | M8: =(I8+F8)/2 -> 10 | N8: =K8+L8 -> 20 | O8: =MAX(J8-J7,0) -> 0 | P8: =MAX(F8-F7,0) -> 0 | Q8: =--(K8>0)+--(L8>0) -> 2 | R8: =CEILING(O8/Controls!$B$49,1) -> 0 | S8: =IF(Controls!$B$45=0,0,N8/(1+Controls!$B$47)*1000000/Controls!$B$45) -> 2176.8707 | T8: =S8*Controls!$B$43*(Controls!$B$36/24)*Controls!$B$10 -> 1158095.2 | U8: =K8*Controls!$B$36*DAY(EOMONTH(B8,0))*Controls!$B$10 -> 5654.4 | V8: =MAX(L8*Controls!$B$36-MIN(L8,M8)*Controls!$B$37,0)*DAY(EOMONTH(B8,0))*Controls!$B$10 -> 2976 | W8: =MIN(L8,M8)*Controls!$B$37*DAY(EOMONTH(B8,0))*Controls!$B$10 -> 2678.4
A9: 8 | B9: =EDATE(Controls!$B$7,A9-1) -> 46419 | C9: =TEXT(B9,"mmm-yy") -> Feb-27 | D9: =IF(A9<2,0,IF(A9=2,Controls!$B$33/2,Controls!$B$33)) -> 10 | E9: =IF(A9<3,0,IF(A9=3,Controls!$B$34/2,Controls!$B$34)) -> 10 | F9: =IF(A9<4,0,Controls!$B$35) -> 10 | G9: =D8 -> 10 | H9: =E8 -> 10 | I9: =F8 -> 10 | J9: =D9+E9 -> 20 | K9: =(G9+D9)/2 -> 10 | L9: =(H9+E9)/2 -> 10 | M9: =(I9+F9)/2 -> 10 | N9: =K9+L9 -> 20 | O9: =MAX(J9-J8,0) -> 0 | P9: =MAX(F9-F8,0) -> 0 | Q9: =--(K9>0)+--(L9>0) -> 2 | R9: =CEILING(O9/Controls!$B$49,1) -> 0 | S9: =IF(Controls!$B$45=0,0,N9/(1+Controls!$B$47)*1000000/Controls!$B$45) -> 2176.8707 | T9: =S9*Controls!$B$43*(Controls!$B$36/24)*Controls!$B$10 -> 1158095.2 | U9: =K9*Controls!$B$36*DAY(EOMONTH(B9,0))*Controls!$B$10 -> 5107.2 | V9: =MAX(L9*Controls!$B$36-MIN(L9,M9)*Controls!$B$37,0)*DAY(EOMONTH(B9,0))*Controls!$B$10 -> 2688 | W9: =MIN(L9,M9)*Controls!$B$37*DAY(EOMONTH(B9,0))*Controls!$B$10 -> 2419.2
A10: 9 | B10: =EDATE(Controls!$B$7,A10-1) -> 46447 | C10: =TEXT(B10,"mmm-yy") -> Mar-27 | D10: =IF(A10<2,0,IF(A10=2,Controls!$B$33/2,Controls!$B$33)) -> 10 | E10: =IF(A10<3,0,IF(A10=3,Controls!$B$34/2,Controls!$B$34)) -> 10 | F10: =IF(A10<4,0,Controls!$B$35) -> 10 | G10: =D9 -> 10 | H10: =E9 -> 10 | I10: =F9 -> 10 | J10: =D10+E10 -> 20 | K10: =(G10+D10)/2 -> 10 | L10: =(H10+E10)/2 -> 10 | M10: =(I10+F10)/2 -> 10 | N10: =K10+L10 -> 20 | O10: =MAX(J10-J9,0) -> 0 | P10: =MAX(F10-F9,0) -> 0 | Q10: =--(K10>0)+--(L10>0) -> 2 | R10: =CEILING(O10/Controls!$B$49,1) -> 0 | S10: =IF(Controls!$B$45=0,0,N10/(1+Controls!$B$47)*1000000/Controls!$B$45) -> 2176.8707 | T10: =S10*Controls!$B$43*(Controls!$B$36/24)*Controls!$B$10 -> 1158095.2 | U10: =K10*Controls!$B$36*DAY(EOMONTH(B10,0))*Controls!$B$10 -> 5654.4 | V10: =MAX(L10*Controls!$B$36-MIN(L10,M10)*Controls!$B$37,0)*DAY(EOMONTH(B10,0))*Controls!$B$10 -> 2976 | W10: =MIN(L10,M10)*Controls!$B$37*DAY(EOMONTH(B10,0))*Controls!$B$10 -> 2678.4
A11: 10 | B11: =EDATE(Controls!$B$7,A11-1) -> 46478 | C11: =TEXT(B11,"mmm-yy") -> Apr-27 | D11: =IF(A11<2,0,IF(A11=2,Controls!$B$33/2,Controls!$B$33)) -> 10 | E11: =IF(A11<3,0,IF(A11=3,Controls!$B$34/2,Controls!$B$34)) -> 10 | F11: =IF(A11<4,0,Controls!$B$35) -> 10 | G11: =D10 -> 10 | H11: =E10 -> 10 | I11: =F10 -> 10 | J11: =D11+E11 -> 20 | K11: =(G11+D11)/2 -> 10 | L11: =(H11+E11)/2 -> 10 | M11: =(I11+F11)/2 -> 10 | N11: =K11+L11 -> 20 | O11: =MAX(J11-J10,0) -> 0 | P11: =MAX(F11-F10,0) -> 0 | Q11: =--(K11>0)+--(L11>0) -> 2 | R11: =CEILING(O11/Controls!$B$49,1) -> 0 | S11: =IF(Controls!$B$45=0,0,N11/(1+Controls!$B$47)*1000000/Controls!$B$45) -> 2176.8707 | T11: =S11*Controls!$B$43*(Controls!$B$36/24)*Controls!$B$10 -> 1158095.2 | U11: =K11*Controls!$B$36*DAY(EOMONTH(B11,0))*Controls!$B$10 -> 5472 | V11: =MAX(L11*Controls!$B$36-MIN(L11,M11)*Controls!$B$37,0)*DAY(EOMONTH(B11,0))*Controls!$B$10 -> 2880 | W11: =MIN(L11,M11)*Controls!$B$37*DAY(EOMONTH(B11,0))*Controls!$B$10 -> 2592
A12: 11 | B12: =EDATE(Controls!$B$7,A12-1) -> 46508 | C12: =TEXT(B12,"mmm-yy") -> May-27 | D12: =IF(A12<2,0,IF(A12=2,Controls!$B$33/2,Controls!$B$33)) -> 10 | E12: =IF(A12<3,0,IF(A12=3,Controls!$B$34/2,Controls!$B$34)) -> 10 | F12: =IF(A12<4,0,Controls!$B$35) -> 10 | G12: =D11 -> 10 | H12: =E11 -> 10 | I12: =F11 -> 10 | J12: =D12+E12 -> 20 | K12: =(G12+D12)/2 -> 10 | L12: =(H12+E12)/2 -> 10 | M12: =(I12+F12)/2 -> 10 | N12: =K12+L12 -> 20 | O12: =MAX(J12-J11,0) -> 0 | P12: =MAX(F12-F11,0) -> 0 | Q12: =--(K12>0)+--(L12>0) -> 2 | R12: =CEILING(O12/Controls!$B$49,1) -> 0 | S12: =IF(Controls!$B$45=0,0,N12/(1+Controls!$B$47)*1000000/Controls!$B$45) -> 2176.8707 | T12: =S12*Controls!$B$43*(Controls!$B$36/24)*Controls!$B$10 -> 1158095.2 | U12: =K12*Controls!$B$36*DAY(EOMONTH(B12,0))*Controls!$B$10 -> 5654.4 | V12: =MAX(L12*Controls!$B$36-MIN(L12,M12)*Controls!$B$37,0)*DAY(EOMONTH(B12,0))*Controls!$B$10 -> 2976 | W12: =MIN(L12,M12)*Controls!$B$37*DAY(EOMONTH(B12,0))*Controls!$B$10 -> 2678.4
A13: 12 | B13: =EDATE(Controls!$B$7,A13-1) -> 46539 | C13: =TEXT(B13,"mmm-yy") -> Jun-27 | D13: =IF(A13<2,0,IF(A13=2,Controls!$B$33/2,Controls!$B$33)) -> 10 | E13: =IF(A13<3,0,IF(A13=3,Controls!$B$34/2,Controls!$B$34)) -> 10 | F13: =IF(A13<4,0,Controls!$B$35) -> 10 | G13: =D12 -> 10 | H13: =E12 -> 10 | I13: =F12 -> 10 | J13: =D13+E13 -> 20 | K13: =(G13+D13)/2 -> 10 | L13: =(H13+E13)/2 -> 10 | M13: =(I13+F13)/2 -> 10 | N13: =K13+L13 -> 20 | O13: =MAX(J13-J12,0) -> 0 | P13: =MAX(F13-F12,0) -> 0 | Q13: =--(K13>0)+--(L13>0) -> 2 | R13: =CEILING(O13/Controls!$B$49,1) -> 0 | S13: =IF(Controls!$B$45=0,0,N13/(1+Controls!$B$47)*1000000/Controls!$B$45) -> 2176.8707 | T13: =S13*Controls!$B$43*(Controls!$B$36/24)*Controls!$B$10 -> 1158095.2 | U13: =K13*Controls!$B$36*DAY(EOMONTH(B13,0))*Controls!$B$10 -> 5472 | V13: =MAX(L13*Controls!$B$36-MIN(L13,M13)*Controls!$B$37,0)*DAY(EOMONTH(B13,0))*Controls!$B$10 -> 2880 | W13: =MIN(L13,M13)*Controls!$B$37*DAY(EOMONTH(B13,0))*Controls!$B$10 -> 2592
A14: 13 | B14: =EDATE(Controls!$B$7,A14-1) -> 46569 | C14: =TEXT(B14,"mmm-yy") -> Jul-27 | D14: =IF(A14<2,0,IF(A14=2,Controls!$B$33/2,Controls!$B$33)) -> 10 | E14: =IF(A14<3,0,IF(A14=3,Controls!$B$34/2,Controls!$B$34)) -> 10 | F14: =IF(A14<4,0,Controls!$B$35) -> 10 | G14: =D13 -> 10 | H14: =E13 -> 10 | I14: =F13 -> 10 | J14: =D14+E14 -> 20 | K14: =(G14+D14)/2 -> 10 | L14: =(H14+E14)/2 -> 10 | M14: =(I14+F14)/2 -> 10 | N14: =K14+L14 -> 20 | O14: =MAX(J14-J13,0) -> 0 | P14: =MAX(F14-F13,0) -> 0 | Q14: =--(K14>0)+--(L14>0) -> 2 | R14: =CEILING(O14/Controls!$B$49,1) -> 0 | S14: =IF(Controls!$B$45=0,0,N14/(1+Controls!$B$47)*1000000/Controls!$B$45) -> 2176.8707 | T14: =S14*Controls!$B$43*(Controls!$B$36/24)*Controls!$B$10 -> 1158095.2 | U14: =K14*Controls!$B$36*DAY(EOMONTH(B14,0))*Controls!$B$10 -> 5654.4 | V14: =MAX(L14*Controls!$B$36-MIN(L14,M14)*Controls!$B$37,0)*DAY(EOMONTH(B14,0))*Controls!$B$10 -> 2976 | W14: =MIN(L14,M14)*Controls!$B$37*DAY(EOMONTH(B14,0))*Controls!$B$10 -> 2678.4
... A37: 36 | B37: =EDATE(Controls!$B$7,A37-1) -> 47270 | C37: =TEXT(B37,"mmm-yy") -> Jun-29 | D37: =IF(A37<2,0,IF(A37=2,Controls!$B$33/2,Controls!$B$33)) -> 10 | E37: =IF(A37<3,0,IF(A37=3,Controls!$B$34/2,Controls!$B$34)) -> 10 | F37: =IF(A37<4,0,Controls!$B$35) -> 10 | G37: =D36 -> 10 | H37: =E36 -> 10 | I37: =F36 -> 10 | J37: =D37+E37 -> 20 | K37: =(G37+D37)/2 -> 10 | L37: =(H37+E37)/2 -> 10 | M37: =(I37+F37)/2 -> 10 | N37: =K37+L37 -> 20 | O37: =MAX(J37-J36,0) -> 0 | P37: =MAX(F37-F36,0) -> 0 | Q37: =--(K37>0)+--(L37>0) -> 2 | R37: =CEILING(O37/Controls!$B$49,1) -> 0 | S37: =IF(Controls!$B$45=0,0,N37/(1+Controls!$B$47)*1000000/Controls!$B$45) -> 2176.8707 | T37: =S37*Controls!$B$43*(Controls!$B$36/24)*Controls!$B$10 -> 1158095.2 | U37: =K37*Controls!$B$36*DAY(EOMONTH(B37,0))*Controls!$B$10 -> 5472 | V37: =MAX(L37*Controls!$B$36-MIN(L37,M37)*Controls!$B$37,0)*DAY(EOMONTH(B37,0))*Controls!$B$10 -> 2880 | W37: =MIN(L37,M37)*Controls!$B$37*DAY(EOMONTH(B37,0))*Controls!$B$10 -> 2592

Sheet Revenue_36M
A1: Month # | B1: Month | C1: BTC Price USD | D1: Network Hash TH/s | E1: Subsidy BTC/block | F1: Fee % | G1: Network BTC | H1: BitMach BTC | I1: BTC Revenue | J1: DR Eligible MW | K1: IDR Standby | L1: DDMP-style Incentive | M1: Event Value | N1: Total DR | O1: AI/DC Pilot | P1: Total Revenue
A2: 1 | B2: =Monthly_Deployment!C2 -> Jul-26 | C2: =Controls!$B$24*(1+Controls!$B$8)^((A2-1)/12) -> 75000 | D2: =Controls!$B$26*(1+Controls!$B$9)^((A2-1)/12) -> 900000000 | E2: =IF(A2<Controls!$B$28,Controls!$B$27,Controls!$B$27/2) -> 3.125 | F2: =Controls!$B$29+Controls!$B$30*(A2-1) -> 0.12 | G2: =DAY(EOMONTH(Monthly_Deployment!B2,0))*144*E2*(1+F2) -> 15624 | H2: =IF(D2=0,0,Monthly_Deployment!T2/D2*G2) -> 0 | I2: =H2*C2*Controls!$B$25/1000 -> 0 | J2: =IF(AND(Controls!$B$11=1,A2>=Controls!$B$12),Monthly_Deployment!N2,0) -> 0 | K2: =J2*Controls!$B$88*Controls!$B$13 -> 0 | L2: =J2*Controls!$B$89/Controls!$B$90*Controls!$B$13 -> 0 | M2: =J2*Controls!$B$91*Controls!$B$92*Controls!$B$13 -> 0 | N2: =K2+L2+M2 -> 0 | O2: =IF(AND(Controls!$B$14=1,A2>=Controls!$B$15),Controls!$B$94*24*DAY(EOMONTH(Monthly_Deployment!B2,0))*Controls!$B$95+Controls!$B$94*Controls!$B$97,0) -> 0 | P2: =I2+N2+O2 -> 0
A3: 2 | B3: =Monthly_Deployment!C3 -> Aug-26 | C3: =Controls!$B$24*(1+Controls!$B$8)^((A3-1)/12) -> 75305.559 | D3: =Controls!$B$26*(1+Controls!$B$9)^((A3-1)/12) -> 9.1377852e+08 | E3: =IF(A3<Controls!$B$28,Controls!$B$27,Controls!$B$27/2) -> 3.125 | F3: =Controls!$B$29+Controls!$B$30*(A3-1) -> 0.1225 | G3: =DAY(EOMONTH(Monthly_Deployment!B3,0))*144*E3*(1+F3) -> 15658.875 | H3: =IF(D3=0,0,Monthly_Deployment!T3/D3*G3) -> 2.480698 | I3: =H3*C3*Controls!$B$25/1000 -> 3175.776 | J3: =IF(AND(Controls!$B$11=1,A3>=Controls!$B$12),Monthly_Deployment!N3,0) -> 0 | K3: =J3*Controls!$B$88*Controls!$B$13 -> 0 | L3: =J3*Controls!$B$89/Controls!$B$90*Controls!$B$13 -> 0 | M3: =J3*Controls!$B$91*Controls!$B$92*Controls!$B$13 -> 0 | N3: =K3+L3+M3 -> 0 | O3: =IF(AND(Controls!$B$14=1,A3>=Controls!$B$15),Controls!$B$94*24*DAY(EOMONTH(Monthly_Deployment!B3,0))*Controls!$B$95+Controls!$B$94*Controls!$B$97,0) -> 0 | P3: =I3+N3+O3 -> 3175.776
A4: 3 | B4: =Monthly_Deployment!C4 -> Sept-26 | C4: =Controls!$B$24*(1+Controls!$B$8)^((A4-1)/12) -> 75612.363 | D4: =Controls!$B$26*(1+Controls!$B$9)^((A4-1)/12) -> 9.2776799e+08 | E4: =IF(A4<Controls!$B$28,Controls!$B$27,Controls!$B$27/2) -> 3.125 | F4: =Controls!$B$29+Controls!$B$30*(A4-1) -> 0.125 | G4: =DAY(EOMONTH(Monthly_Deployment!B4,0))*144*E4*(1+F4) -> 15187.5 | H4: =IF(D4=0,0,Monthly_Deployment!T4/D4*G4) -> 9.4789708 | I4: =H4*C4*Controls!$B$25/1000 -> 12184.366 | J4: =IF(AND(Controls!$B$11=1,A4>=Controls!$B$12),Monthly_Deployment!N4,0) -> 0 | K4: =J4*Controls!$B$88*Controls!$B$13 -> 0 | L4: =J4*Controls!$B$89/Controls!$B$90*Controls!$B$13 -> 0 | M4: =J4*Controls!$B$91*Controls!$B$92*Controls!$B$13 -> 0 | N4: =K4+L4+M4 -> 0 | O4: =IF(AND(Controls!$B$14=1,A4>=Controls!$B$15),Controls!$B$94*24*DAY(EOMONTH(Monthly_Deployment!B4,0))*Controls!$B$95+Controls!$B$94*Controls!$B$97,0) -> 0 | P4: =I4+N4+O4 -> 12184.366
A5: 4 | B5: =Monthly_Deployment!C5 -> Oct-26 | C5: =Controls!$B$24*(1+Controls!$B$8)^((A5-1)/12) -> 75920.418 | D5: =Controls!$B$26*(1+Controls!$B$9)^((A5-1)/12) -> 9.4197163e+08 | E5: =IF(A5<Controls!$B$28,Controls!$B$27,Controls!$B$27/2) -> 3.125 | F5: =Controls!$B$29+Controls!$B$30*(A5-1) -> 0.1275 | G5: =DAY(EOMONTH(Monthly_Deployment!B5,0))*144*E5*(1+F5) -> 15728.625 | H5: =IF(D5=0,0,Monthly_Deployment!T5/D5*G5) -> 16.920191 | I5: =H5*C5*Controls!$B$25/1000 -> 21837.996 | J5: =IF(AND(Controls!$B$11=1,A5>=Controls!$B$12),Monthly_Deployment!N5,0) -> 0 | K5: =J5*Controls!$B$88*Controls!$B$13 -> 0 | L5: =J5*Controls!$B$89/Controls!$B$90*Controls!$B$13 -> 0 | M5: =J5*Controls!$B$91*Controls!$B$92*Controls!$B$13 -> 0 | N5: =K5+L5+M5 -> 0 | O5: =IF(AND(Controls!$B$14=1,A5>=Controls!$B$15),Controls!$B$94*24*DAY(EOMONTH(Monthly_Deployment!B5,0))*Controls!$B$95+Controls!$B$94*Controls!$B$97,0) -> 0 | P5: =I5+N5+O5 -> 21837.996
A6: 5 | B6: =Monthly_Deployment!C6 -> Nov-26 | C6: =Controls!$B$24*(1+Controls!$B$8)^((A6-1)/12) -> 76229.727 | D6: =Controls!$B$26*(1+Controls!$B$9)^((A6-1)/12) -> 9.5639271e+08 | E6: =IF(A6<Controls!$B$28,Controls!$B$27,Controls!$B$27/2) -> 3.125 | F6: =Controls!$B$29+Controls!$B$30*(A6-1) -> 0.13 | G6: =DAY(EOMONTH(Monthly_Deployment!B6,0))*144*E6*(1+F6) -> 15255 | H6: =IF(D6=0,0,Monthly_Deployment!T6/D6*G6) -> 18.472268 | I6: =H6*C6*Controls!$B$25/1000 -> 23938.312 | J6: =IF(AND(Controls!$B$11=1,A6>=Controls!$B$12),Monthly_Deployment!N6,0) -> 0 | K6: =J6*Controls!$B$88*Controls!$B$13 -> 0 | L6: =J6*Controls!$B$89/Controls!$B$90*Controls!$B$13 -> 0 | M6: =J6*Controls!$B$91*Controls!$B$92*Controls!$B$13 -> 0 | N6: =K6+L6+M6 -> 0 | O6: =IF(AND(Controls!$B$14=1,A6>=Controls!$B$15),Controls!$B$94*24*DAY(EOMONTH(Monthly_Deployment!B6,0))*Controls!$B$95+Controls!$B$94*Controls!$B$97,0) -> 0 | P6: =I6+N6+O6 -> 23938.312
A7: 6 | B7: =Monthly_Deployment!C7 -> Dec-26 | C7: =Controls!$B$24*(1+Controls!$B$8)^((A7-1)/12) -> 76540.296 | D7: =Controls!$B$26*(1+Controls!$B$9)^((A7-1)/12) -> 9.7103458e+08 | E7: =IF(A7<Controls!$B$28,Controls!$B$27,Controls!$B$27/2) -> 3.125 | F7: =Controls!$B$29+Controls!$B$30*(A7-1) -> 0.1325 | G7: =DAY(EOMONTH(Monthly_Deployment!B7,0))*144*E7*(1+F7) -> 15798.375 | H7: =IF(D7=0,0,Monthly_Deployment!T7/D7*G7) -> 18.841783 | I7: =H7*C7*Controls!$B$25/1000 -> 24516.646 | J7: =IF(AND(Controls!$B$11=1,A7>=Controls!$B$12),Monthly_Deployment!N7,0) -> 0 | K7: =J7*Controls!$B$88*Controls!$B$13 -> 0 | L7: =J7*Controls!$B$89/Controls!$B$90*Controls!$B$13 -> 0 | M7: =J7*Controls!$B$91*Controls!$B$92*Controls!$B$13 -> 0 | N7: =K7+L7+M7 -> 0 | O7: =IF(AND(Controls!$B$14=1,A7>=Controls!$B$15),Controls!$B$94*24*DAY(EOMONTH(Monthly_Deployment!B7,0))*Controls!$B$95+Controls!$B$94*Controls!$B$97,0) -> 0 | P7: =I7+N7+O7 -> 24516.646
A8: 7 | B8: =Monthly_Deployment!C8 -> Jan-27 | C8: =Controls!$B$24*(1+Controls!$B$8)^((A8-1)/12) -> 76852.131 | D8: =Controls!$B$26*(1+Controls!$B$9)^((A8-1)/12) -> 9.859006e+08 | E8: =IF(A8<Controls!$B$28,Controls!$B$27,Controls!$B$27/2) -> 3.125 | F8: =Controls!$B$29+Controls!$B$30*(A8-1) -> 0.135 | G8: =DAY(EOMONTH(Monthly_Deployment!B8,0))*144*E8*(1+F8) -> 15833.25 | H8: =IF(D8=0,0,Monthly_Deployment!T8/D8*G8) -> 18.598641 | I8: =H8*C8*Controls!$B$25/1000 -> 24298.868 | J8: =IF(AND(Controls!$B$11=1,A8>=Controls!$B$12),Monthly_Deployment!N8,0) -> 0 | K8: =J8*Controls!$B$88*Controls!$B$13 -> 0 | L8: =J8*Controls!$B$89/Controls!$B$90*Controls!$B$13 -> 0 | M8: =J8*Controls!$B$91*Controls!$B$92*Controls!$B$13 -> 0 | N8: =K8+L8+M8 -> 0 | O8: =IF(AND(Controls!$B$14=1,A8>=Controls!$B$15),Controls!$B$94*24*DAY(EOMONTH(Monthly_Deployment!B8,0))*Controls!$B$95+Controls!$B$94*Controls!$B$97,0) -> 0 | P8: =I8+N8+O8 -> 24298.868
A9: 8 | B9: =Monthly_Deployment!C9 -> Feb-27 | C9: =Controls!$B$24*(1+Controls!$B$8)^((A9-1)/12) -> 77165.236 | D9: =Controls!$B$26*(1+Controls!$B$9)^((A9-1)/12) -> 1.0009942e+09 | E9: =IF(A9<Controls!$B$28,Controls!$B$27,Controls!$B$27/2) -> 3.125 | F9: =Controls!$B$29+Controls!$B$30*(A9-1) -> 0.1375 | G9: =DAY(EOMONTH(Monthly_Deployment!B9,0))*144*E9*(1+F9) -> 14332.5 | H9: =IF(D9=0,0,Monthly_Deployment!T9/D9*G9) -> 16.581914 | I9: =H9*C9*Controls!$B$25/1000 -> 21752.304 | J9: =IF(AND(Controls!$B$11=1,A9>=Controls!$B$12),Monthly_Deployment!N9,0) -> 0 | K9: =J9*Controls!$B$88*Controls!$B$13 -> 0 | L9: =J9*Controls!$B$89/Controls!$B$90*Controls!$B$13 -> 0 | M9: =J9*Controls!$B$91*Controls!$B$92*Controls!$B$13 -> 0 | N9: =K9+L9+M9 -> 0 | O9: =IF(AND(Controls!$B$14=1,A9>=Controls!$B$15),Controls!$B$94*24*DAY(EOMONTH(Monthly_Deployment!B9,0))*Controls!$B$95+Controls!$B$94*Controls!$B$97,0) -> 0 | P9: =I9+N9+O9 -> 21752.304
A10: 9 | B10: =Monthly_Deployment!C10 -> Mar-27 | C10: =Controls!$B$24*(1+Controls!$B$8)^((A10-1)/12) -> 77479.617 | D10: =Controls!$B$26*(1+Controls!$B$9)^((A10-1)/12) -> 1.0163189e+09 | E10: =IF(A10<Controls!$B$28,Controls!$B$27,Controls!$B$27/2) -> 3.125 | F10: =Controls!$B$29+Controls!$B$30*(A10-1) -> 0.14 | G10: =DAY(EOMONTH(Monthly_Deployment!B10,0))*144*E10*(1+F10) -> 15903 | H10: =IF(D10=0,0,Monthly_Deployment!T10/D10*G10) -> 18.121466 | I10: =H10*C10*Controls!$B$25/1000 -> 23868.752 | J10: =IF(AND(Controls!$B$11=1,A10>=Controls!$B$12),Monthly_Deployment!N10,0) -> 0 | K10: =J10*Controls!$B$88*Controls!$B$13 -> 0 | L10: =J10*Controls!$B$89/Controls!$B$90*Controls!$B$13 -> 0 | M10: =J10*Controls!$B$91*Controls!$B$92*Controls!$B$13 -> 0 | N10: =K10+L10+M10 -> 0 | O10: =IF(AND(Controls!$B$14=1,A10>=Controls!$B$15),Controls!$B$94*24*DAY(EOMONTH(Monthly_Deployment!B10,0))*Controls!$B$95+Controls!$B$94*Controls!$B$97,0) -> 0 | P10: =I10+N10+O10 -> 23868.752
A11: 10 | B11: =Monthly_Deployment!C11 -> Apr-27 | C11: =Controls!$B$24*(1+Controls!$B$8)^((A11-1)/12) -> 77795.278 | D11: =Controls!$B$26*(1+Controls!$B$9)^((A11-1)/12) -> 1.0318782e+09 | E11: =IF(A11<Controls!$B$28,Controls!$B$27,Controls!$B$27/2) -> 3.125 | F11: =Controls!$B$29+Controls!$B$30*(A11-1) -> 0.1425 | G11: =DAY(EOMONTH(Monthly_Deployment!B11,0))*144*E11*(1+F11) -> 15423.75 | H11: =IF(D11=0,0,Monthly_Deployment!T11/D11*G11) -> 17.310348 | I11: =H11*C11*Controls!$B$25/1000 -> 22893.277 | J11: =IF(AND(Controls!$B$11=1,A11>=Controls!$B$12),Monthly_Deployment!N11,0) -> 0 | K11: =J11*Controls!$B$88*Controls!$B$13 -> 0 | L11: =J11*Controls!$B$89/Controls!$B$90*Controls!$B$13 -> 0 | M11: =J11*Controls!$B$91*Controls!$B$92*Controls!$B$13 -> 0 | N11: =K11+L11+M11 -> 0 | O11: =IF(AND(Controls!$B$14=1,A11>=Controls!$B$15),Controls!$B$94*24*DAY(EOMONTH(Monthly_Deployment!B11,0))*Controls!$B$95+Controls!$B$94*Controls!$B$97,0) -> 0 | P11: =I11+N11+O11 -> 22893.277
A12: 11 | B12: =Monthly_Deployment!C12 -> May-27 | C12: =Controls!$B$24*(1+Controls!$B$8)^((A12-1)/12) -> 78112.226 | D12: =Controls!$B$26*(1+Controls!$B$9)^((A12-1)/12) -> 1.0476757e+09 | E12: =IF(A12<Controls!$B$28,Controls!$B$27,Controls!$B$27/2) -> 3.125 | F12: =Controls!$B$29+Controls!$B$30*(A12-1) -> 0.145 | G12: =DAY(EOMONTH(Monthly_Deployment!B12,0))*144*E12*(1+F12) -> 15972.75 | H12: =IF(D12=0,0,Monthly_Deployment!T12/D12*G12) -> 17.656194 | I12: =H12*C12*Controls!$B$25/1000 -> 23445.798 | J12: =IF(AND(Controls!$B$11=1,A12>=Controls!$B$12),Monthly_Deployment!N12,0) -> 0 | K12: =J12*Controls!$B$88*Controls!$B$13 -> 0 | L12: =J12*Controls!$B$89/Controls!$B$90*Controls!$B$13 -> 0 | M12: =J12*Controls!$B$91*Controls!$B$92*Controls!$B$13 -> 0 | N12: =K12+L12+M12 -> 0 | O12: =IF(AND(Controls!$B$14=1,A12>=Controls!$B$15),Controls!$B$94*24*DAY(EOMONTH(Monthly_Deployment!B12,0))*Controls!$B$95+Controls!$B$94*Controls!$B$97,0) -> 0 | P12: =I12+N12+O12 -> 23445.798
A13: 12 | B13: =Monthly_Deployment!C13 -> Jun-27 | C13: =Controls!$B$24*(1+Controls!$B$8)^((A13-1)/12) -> 78430.465 | D13: =Controls!$B$26*(1+Controls!$B$9)^((A13-1)/12) -> 1.0637151e+09 | E13: =IF(A13<Controls!$B$28,Controls!$B$27,Controls!$B$27/2) -> 3.125 | F13: =Controls!$B$29+Controls!$B$30*(A13-1) -> 0.1475 | G13: =DAY(EOMONTH(Monthly_Deployment!B13,0))*144*E13*(1+F13) -> 15491.25 | H13: =IF(D13=0,0,Monthly_Deployment!T13/D13*G13) -> 16.865741 | I13: =H13*C13*Controls!$B$25/1000 -> 22487.394 | J13: =IF(AND(Controls!$B$11=1,A13>=Controls!$B$12),Monthly_Deployment!N13,0) -> 0 | K13: =J13*Controls!$B$88*Controls!$B$13 -> 0 | L13: =J13*Controls!$B$89/Controls!$B$90*Controls!$B$13 -> 0 | M13: =J13*Controls!$B$91*Controls!$B$92*Controls!$B$13 -> 0 | N13: =K13+L13+M13 -> 0 | O13: =IF(AND(Controls!$B$14=1,A13>=Controls!$B$15),Controls!$B$94*24*DAY(EOMONTH(Monthly_Deployment!B13,0))*Controls!$B$95+Controls!$B$94*Controls!$B$97,0) -> 0 | P13: =I13+N13+O13 -> 22487.394
... A37: 36 | B37: =Monthly_Deployment!C37 -> Jun-29 | C37: =Controls!$B$24*(1+Controls!$B$8)^((A37-1)/12) -> 86469.587 | D37: =Controls!$B$26*(1+Controls!$B$9)^((A37-1)/12) -> 1.5317497e+09 | E37: =IF(A37<Controls!$B$28,Controls!$B$27,Controls!$B$27/2) -> 1.5625 | F37: =Controls!$B$29+Controls!$B$30*(A37-1) -> 0.2075 | G37: =DAY(EOMONTH(Monthly_Deployment!B37,0))*144*E37*(1+F37) -> 8150.625 | H37: =IF(D37=0,0,Monthly_Deployment!T37/D37*G37) -> 6.1623644 | I37: =H37*C37*Controls!$B$25/1000 -> 9058.5708 | J37: =IF(AND(Controls!$B$11=1,A37>=Controls!$B$12),Monthly_Deployment!N37,0) -> 0 | K37: =J37*Controls!$B$88*Controls!$B$13 -> 0 | L37: =J37*Controls!$B$89/Controls!$B$90*Controls!$B$13 -> 0 | M37: =J37*Controls!$B$91*Controls!$B$92*Controls!$B$13 -> 0 | N37: =K37+L37+M37 -> 0 | O37: =IF(AND(Controls!$B$14=1,A37>=Controls!$B$15),Controls!$B$94*24*DAY(EOMONTH(Monthly_Deployment!B37,0))*Controls!$B$95+Controls!$B$94*Controls!$B$97,0) -> 0 | P37: =I37+N37+O37 -> 9058.5708

Sheet Opex_36M
A1: Month # | B1: Month | C1: Tariff R/kWh | D1: GVL Grid Cost | E1: AMSA Grid Cost | F1: Solar O&M | G1: Total Energy Cost | H1: Corporate Payroll | I1: Site Payroll | J1: Benefits | K1: Travel | L1: Software/Storage | M1: Legal | N1: Office | O1: Tools/Security/Utilities | P1: Total Cash Opex
A2: 1 | B2: =Monthly_Deployment!C2 -> Jul-26 | C2: =IF(A2<=Controls!$B$40,Controls!$B$38,Controls!$B$39) -> 1.2 | D2: =Monthly_Deployment!U2*C2 -> 0 | E2: =Monthly_Deployment!V2*C2 -> 0 | F2: =Monthly_Deployment!M2*Controls!$B$54*Controls!$B$41/12 -> 0 | G2: =D2+E2+F2 -> 0 | H2: =Controls!$B$68*Controls!$B$69/12 -> 333.33333 | I2: =Monthly_Deployment!Q2*Controls!$B$70*Controls!$B$71/12+Monthly_Deployment!N2*Controls!$B$72*Controls!$B$73/12+Monthly_Deployment!N2*Controls!$B$74*Controls!$B$75/12 -> 0 | J2: =(H2+I2)*Controls!$B$76 -> 66.666667 | K2: =(H2+I2)*Controls!$B$77+Monthly_Deployment!Q2*Controls!$B$78 -> 20 | L2: =(Controls!$B$79*(Controls!$B$68+Monthly_Deployment!Q2*Controls!$B$70+Monthly_Deployment!N2*Controls!$B$72+Monthly_Deployment!N2*Controls!$B$74))+Monthly_Deployment!Q2*Controls!$B$80+Controls!$B$83 -> 18 | M2: =Controls!$B$81 -> 75 | N2: =Controls!$B$82 -> 10 | O2: =Monthly_Deployment!N2*(Controls!$B$84+Controls!$B$86)+Monthly_Deployment!Q2*Controls!$B$85 -> 0 | P2: =G2+H2+I2+J2+K2+L2+M2+N2+O2 -> 523
A3: 2 | B3: =Monthly_Deployment!C3 -> Aug-26 | C3: =IF(A3<=Controls!$B$40,Controls!$B$38,Controls!$B$39) -> 1.2 | D3: =Monthly_Deployment!U3*C3 -> 1696.32 | E3: =Monthly_Deployment!V3*C3 -> 0 | F3: =Monthly_Deployment!M3*Controls!$B$54*Controls!$B$41/12 -> 0 | G3: =D3+E3+F3 -> 1696.32 | H3: =Controls!$B$68*Controls!$B$69/12 -> 333.33333 | I3: =Monthly_Deployment!Q3*Controls!$B$70*Controls!$B$71/12+Monthly_Deployment!N3*Controls!$B$72*Controls!$B$73/12+Monthly_Deployment!N3*Controls!$B$74*Controls!$B$75/12 -> 149.6875 | J3: =(H3+I3)*Controls!$B$76 -> 96.604167 | K3: =(H3+I3)*Controls!$B$77+Monthly_Deployment!Q3*Controls!$B$78 -> 278.98125 | L3: =(Controls!$B$79*(Controls!$B$68+Monthly_Deployment!Q3*Controls!$B$70+Monthly_Deployment!N3*Controls!$B$72+Monthly_Deployment!N3*Controls!$B$74))+Monthly_Deployment!Q3*Controls!$B$80+Controls!$B$83 -> 68.7625 | M3: =Controls!$B$81 -> 75 | N3: =Controls!$B$82 -> 10 | O3: =Monthly_Deployment!N3*(Controls!$B$84+Controls!$B$86)+Monthly_Deployment!Q3*Controls!$B$85 -> 85 | P3: =G3+H3+I3+J3+K3+L3+M3+N3+O3 -> 2793.6887
A4: 3 | B4: =Monthly_Deployment!C4 -> Sept-26 | C4: =IF(A4<=Controls!$B$40,Controls!$B$38,Controls!$B$39) -> 1.2 | D4: =Monthly_Deployment!U4*C4 -> 4924.8 | E4: =Monthly_Deployment!V4*C4 -> 1641.6 | F4: =Monthly_Deployment!M4*Controls!$B$54*Controls!$B$41/12 -> 0 | G4: =D4+E4+F4 -> 6566.4 | H4: =Controls!$B$68*Controls!$B$69/12 -> 333.33333 | I4: =Monthly_Deployment!Q4*Controls!$B$70*Controls!$B$71/12+Monthly_Deployment!N4*Controls!$B$72*Controls!$B$73/12+Monthly_Deployment!N4*Controls!$B$74*Controls!$B$75/12 -> 365.41667 | J4: =(H4+I4)*Controls!$B$76 -> 139.75 | K4: =(H4+I4)*Controls!$B$77+Monthly_Deployment!Q4*Controls!$B$78 -> 541.925 | L4: =(Controls!$B$79*(Controls!$B$68+Monthly_Deployment!Q4*Controls!$B$70+Monthly_Deployment!N4*Controls!$B$72+Monthly_Deployment!N4*Controls!$B$74))+Monthly_Deployment!Q4*Controls!$B$80+Controls!$B$83 -> 127.05 | M4: =Controls!$B$81 -> 75 | N4: =Controls!$B$82 -> 10 | O4: =Monthly_Deployment!N4*(Controls!$B$84+Controls!$B$86)+Monthly_Deployment!Q4*Controls!$B$85 -> 260 | P4: =G4+H4+I4+J4+K4+L4+M4+N4+O4 -> 8418.875
A5: 4 | B5: =Monthly_Deployment!C5 -> Oct-26 | C5: =IF(A5<=Controls!$B$40,Controls!$B$38,Controls!$B$39) -> 1.2 | D5: =Monthly_Deployment!U5*C5 -> 6785.28 | E5: =Monthly_Deployment!V5*C5 -> 3481.92 | F5: =Monthly_Deployment!M5*Controls!$B$54*Controls!$B$41/12 -> 58.333333 | G5: =D5+E5+F5 -> 10325.533 | H5: =Controls!$B$68*Controls!$B$69/12 -> 333.33333 | I5: =Monthly_Deployment!Q5*Controls!$B$70*Controls!$B$71/12+Monthly_Deployment!N5*Controls!$B$72*Controls!$B$73/12+Monthly_Deployment!N5*Controls!$B$74*Controls!$B$75/12 -> 464.47917 | J5: =(H5+I5)*Controls!$B$76 -> 159.5625 | K5: =(H5+I5)*Controls!$B$77+Monthly_Deployment!Q5*Controls!$B$78 -> 547.86875 | L5: =(Controls!$B$79*(Controls!$B$68+Monthly_Deployment!Q5*Controls!$B$70+Monthly_Deployment!N5*Controls!$B$72+Monthly_Deployment!N5*Controls!$B$74))+Monthly_Deployment!Q5*Controls!$B$80+Controls!$B$83 -> 138.3375 | M5: =Controls!$B$81 -> 75 | N5: =Controls!$B$82 -> 10 | O5: =Monthly_Deployment!N5*(Controls!$B$84+Controls!$B$86)+Monthly_Deployment!Q5*Controls!$B$85 -> 395 | P5: =G5+H5+I5+J5+K5+L5+M5+N5+O5 -> 12449.115
A6: 5 | B6: =Monthly_Deployment!C6 -> Nov-26 | C6: =IF(A6<=Controls!$B$40,Controls!$B$38,Controls!$B$39) -> 1.2 | D6: =Monthly_Deployment!U6*C6 -> 6566.4 | E6: =Monthly_Deployment!V6*C6 -> 3456 | F6: =Monthly_Deployment!M6*Controls!$B$54*Controls!$B$41/12 -> 116.66667 | G6: =D6+E6+F6 -> 10139.067 | H6: =Controls!$B$68*Controls!$B$69/12 -> 333.33333 | I6: =Monthly_Deployment!Q6*Controls!$B$70*Controls!$B$71/12+Monthly_Deployment!N6*Controls!$B$72*Controls!$B$73/12+Monthly_Deployment!N6*Controls!$B$74*Controls!$B$75/12 -> 497.5 | J6: =(H6+I6)*Controls!$B$76 -> 166.16667 | K6: =(H6+I6)*Controls!$B$77+Monthly_Deployment!Q6*Controls!$B$78 -> 549.85 | L6: =(Controls!$B$79*(Controls!$B$68+Monthly_Deployment!Q6*Controls!$B$70+Monthly_Deployment!N6*Controls!$B$72+Monthly_Deployment!N6*Controls!$B$74))+Monthly_Deployment!Q6*Controls!$B$80+Controls!$B$83 -> 142.1 | M6: =Controls!$B$81 -> 75 | N6: =Controls!$B$82 -> 10 | O6: =Monthly_Deployment!N6*(Controls!$B$84+Controls!$B$86)+Monthly_Deployment!Q6*Controls!$B$85 -> 440 | P6: =G6+H6+I6+J6+K6+L6+M6+N6+O6 -> 12353.017
A7: 6 | B7: =Monthly_Deployment!C7 -> Dec-26 | C7: =IF(A7<=Controls!$B$40,Controls!$B$38,Controls!$B$39) -> 1.2 | D7: =Monthly_Deployment!U7*C7 -> 6785.28 | E7: =Monthly_Deployment!V7*C7 -> 3571.2 | F7: =Monthly_Deployment!M7*Controls!$B$54*Controls!$B$41/12 -> 116.66667 | G7: =D7+E7+F7 -> 10473.147 | H7: =Controls!$B$68*Controls!$B$69/12 -> 333.33333 | I7: =Monthly_Deployment!Q7*Controls!$B$70*Controls!$B$71/12+Monthly_Deployment!N7*Controls!$B$72*Controls!$B$73/12+Monthly_Deployment!N7*Controls!$B$74*Controls!$B$75/12 -> 497.5 | J7: =(H7+I7)*Controls!$B$76 -> 166.16667 | K7: =(H7+I7)*Controls!$B$77+Monthly_Deployment!Q7*Controls!$B$78 -> 549.85 | L7: =(Controls!$B$79*(Controls!$B$68+Monthly_Deployment!Q7*Controls!$B$70+Monthly_Deployment!N7*Controls!$B$72+Monthly_Deployment!N7*Controls!$B$74))+Monthly_Deployment!Q7*Controls!$B$80+Controls!$B$83 -> 142.1 | M7: =Controls!$B$81 -> 75 | N7: =Controls!$B$82 -> 10 | O7: =Monthly_Deployment!N7*(Controls!$B$84+Controls!$B$86)+Monthly_Deployment!Q7*Controls!$B$85 -> 440 | P7: =G7+H7+I7+J7+K7+L7+M7+N7+O7 -> 12687.097
A8: 7 | B8: =Monthly_Deployment!C8 -> Jan-27 | C8: =IF(A8<=Controls!$B$40,Controls!$B$38,Controls!$B$39) -> 1.2 | D8: =Monthly_Deployment!U8*C8 -> 6785.28 | E8: =Monthly_Deployment!V8*C8 -> 3571.2 | F8: =Monthly_Deployment!M8*Controls!$B$54*Controls!$B$41/12 -> 116.66667 | G8: =D8+E8+F8 -> 10473.147 | H8: =Controls!$B$68*Controls!$B$69/12 -> 333.33333 | I8: =Monthly_Deployment!Q8*Controls!$B$70*Controls!$B$71/12+Monthly_Deployment!N8*Controls!$B$72*Controls!$B$73/12+Monthly_Deployment!N8*Controls!$B$74*Controls!$B$75/12 -> 497.5 | J8: =(H8+I8)*Controls!$B$76 -> 166.16667 | K8: =(H8+I8)*Controls!$B$77+Monthly_Deployment!Q8*Controls!$B$78 -> 549.85 | L8: =(Controls!$B$79*(Controls!$B$68+Monthly_Deployment!Q8*Controls!$B$70+Monthly_Deployment!N8*Controls!$B$72+Monthly_Deployment!N8*Controls!$B$74))+Monthly_Deployment!Q8*Controls!$B$80+Controls!$B$83 -> 142.1 | M8: =Controls!$B$81 -> 75 | N8: =Controls!$B$82 -> 10 | O8: =Monthly_Deployment!N8*(Controls!$B$84+Controls!$B$86)+Monthly_Deployment!Q8*Controls!$B$85 -> 440 | P8: =G8+H8+I8+J8+K8+L8+M8+N8+O8 -> 12687.097
A9: 8 | B9: =Monthly_Deployment!C9 -> Feb-27 | C9: =IF(A9<=Controls!$B$40,Controls!$B$38,Controls!$B$39) -> 1.2 | D9: =Monthly_Deployment!U9*C9 -> 6128.64 | E9: =Monthly_Deployment!V9*C9 -> 3225.6 | F9: =Monthly_Deployment!M9*Controls!$B$54*Controls!$B$41/12 -> 116.66667 | G9: =D9+E9+F9 -> 9470.9067 | H9: =Controls!$B$68*Controls!$B$69/12 -> 333.33333 | I9: =Monthly_Deployment!Q9*Controls!$B$70*Controls!$B$71/12+Monthly_Deployment!N9*Controls!$B$72*Controls!$B$73/12+Monthly_Deployment!N9*Controls!$B$74*Controls!$B$75/12 -> 497.5 | J9: =(H9+I9)*Controls!$B$76 -> 166.16667 | K9: =(H9+I9)*Controls!$B$77+Monthly_Deployment!Q9*Controls!$B$78 -> 549.85 | L9: =(Controls!$B$79*(Controls!$B$68+Monthly_Deployment!Q9*Controls!$B$70+Monthly_Deployment!N9*Controls!$B$72+Monthly_Deployment!N9*Controls!$B$74))+Monthly_Deployment!Q9*Controls!$B$80+Controls!$B$83 -> 142.1 | M9: =Controls!$B$81 -> 75 | N9: =Controls!$B$82 -> 10 | O9: =Monthly_Deployment!N9*(Controls!$B$84+Controls!$B$86)+Monthly_Deployment!Q9*Controls!$B$85 -> 440 | P9: =G9+H9+I9+J9+K9+L9+M9+N9+O9 -> 11684.857
A10: 9 | B10: =Monthly_Deployment!C10 -> Mar-27 | C10: =IF(A10<=Controls!$B$40,Controls!$B$38,Controls!$B$39) -> 1.2 | D10: =Monthly_Deployment!U10*C10 -> 6785.28 | E10: =Monthly_Deployment!V10*C10 -> 3571.2 | F10: =Monthly_Deployment!M10*Controls!$B$54*Controls!$B$41/12 -> 116.66667 | G10: =D10+E10+F10 -> 10473.147 | H10: =Controls!$B$68*Controls!$B$69/12 -> 333.33333 | I10: =Monthly_Deployment!Q10*Controls!$B$70*Controls!$B$71/12+Monthly_Deployment!N10*Controls!$B$72*Controls!$B$73/12+Monthly_Deployment!N10*Controls!$B$74*Controls!$B$75/12 -> 497.5 | J10: =(H10+I10)*Controls!$B$76 -> 166.16667 | K10: =(H10+I10)*Controls!$B$77+Monthly_Deployment!Q10*Controls!$B$78 -> 549.85 | L10: =(Controls!$B$79*(Controls!$B$68+Monthly_Deployment!Q10*Controls!$B$70+Monthly_Deployment!N10*Controls!$B$72+Monthly_Deployment!N10*Controls!$B$74))+Monthly_Deployment!Q10*Controls!$B$80+Controls!$B$83 -> 142.1 | M10: =Controls!$B$81 -> 75 | N10: =Controls!$B$82 -> 10 | O10: =Monthly_Deployment!N10*(Controls!$B$84+Controls!$B$86)+Monthly_Deployment!Q10*Controls!$B$85 -> 440 | P10: =G10+H10+I10+J10+K10+L10+M10+N10+O10 -> 12687.097
A11: 10 | B11: =Monthly_Deployment!C11 -> Apr-27 | C11: =IF(A11<=Controls!$B$40,Controls!$B$38,Controls!$B$39) -> 1.2 | D11: =Monthly_Deployment!U11*C11 -> 6566.4 | E11: =Monthly_Deployment!V11*C11 -> 3456 | F11: =Monthly_Deployment!M11*Controls!$B$54*Controls!$B$41/12 -> 116.66667 | G11: =D11+E11+F11 -> 10139.067 | H11: =Controls!$B$68*Controls!$B$69/12 -> 333.33333 | I11: =Monthly_Deployment!Q11*Controls!$B$70*Controls!$B$71/12+Monthly_Deployment!N11*Controls!$B$72*Controls!$B$73/12+Monthly_Deployment!N11*Controls!$B$74*Controls!$B$75/12 -> 497.5 | J11: =(H11+I11)*Controls!$B$76 -> 166.16667 | K11: =(H11+I11)*Controls!$B$77+Monthly_Deployment!Q11*Controls!$B$78 -> 549.85 | L11: =(Controls!$B$79*(Controls!$B$68+Monthly_Deployment!Q11*Controls!$B$70+Monthly_Deployment!N11*Controls!$B$72+Monthly_Deployment!N11*Controls!$B$74))+Monthly_Deployment!Q11*Controls!$B$80+Controls!$B$83 -> 142.1 | M11: =Controls!$B$81 -> 75 | N11: =Controls!$B$82 -> 10 | O11: =Monthly_Deployment!N11*(Controls!$B$84+Controls!$B$86)+Monthly_Deployment!Q11*Controls!$B$85 -> 440 | P11: =G11+H11+I11+J11+K11+L11+M11+N11+O11 -> 12353.017
A12: 11 | B12: =Monthly_Deployment!C12 -> May-27 | C12: =IF(A12<=Controls!$B$40,Controls!$B$38,Controls!$B$39) -> 1.2 | D12: =Monthly_Deployment!U12*C12 -> 6785.28 | E12: =Monthly_Deployment!V12*C12 -> 3571.2 | F12: =Monthly_Deployment!M12*Controls!$B$54*Controls!$B$41/12 -> 116.66667 | G12: =D12+E12+F12 -> 10473.147 | H12: =Controls!$B$68*Controls!$B$69/12 -> 333.33333 | I12: =Monthly_Deployment!Q12*Controls!$B$70*Controls!$B$71/12+Monthly_Deployment!N12*Controls!$B$72*Controls!$B$73/12+Monthly_Deployment!N12*Controls!$B$74*Controls!$B$75/12 -> 497.5 | J12: =(H12+I12)*Controls!$B$76 -> 166.16667 | K12: =(H12+I12)*Controls!$B$77+Monthly_Deployment!Q12*Controls!$B$78 -> 549.85 | L12: =(Controls!$B$79*(Controls!$B$68+Monthly_Deployment!Q12*Controls!$B$70+Monthly_Deployment!N12*Controls!$B$72+Monthly_Deployment!N12*Controls!$B$74))+Monthly_Deployment!Q12*Controls!$B$80+Controls!$B$83 -> 142.1 | M12: =Controls!$B$81 -> 75 | N12: =Controls!$B$82 -> 10 | O12: =Monthly_Deployment!N12*(Controls!$B$84+Controls!$B$86)+Monthly_Deployment!Q12*Controls!$B$85 -> 440 | P12: =G12+H12+I12+J12+K12+L12+M12+N12+O12 -> 12687.097
A13: 12 | B13: =Monthly_Deployment!C13 -> Jun-27 | C13: =IF(A13<=Controls!$B$40,Controls!$B$38,Controls!$B$39) -> 1.2 | D13: =Monthly_Deployment!U13*C13 -> 6566.4 | E13: =Monthly_Deployment!V13*C13 -> 3456 | F13: =Monthly_Deployment!M13*Controls!$B$54*Controls!$B$41/12 -> 116.66667 | G13: =D13+E13+F13 -> 10139.067 | H13: =Controls!$B$68*Controls!$B$69/12 -> 333.33333 | I13: =Monthly_Deployment!Q13*Controls!$B$70*Controls!$B$71/12+Monthly_Deployment!N13*Controls!$B$72*Controls!$B$73/12+Monthly_Deployment!N13*Controls!$B$74*Controls!$B$75/12 -> 497.5 | J13: =(H13+I13)*Controls!$B$76 -> 166.16667 | K13: =(H13+I13)*Controls!$B$77+Monthly_Deployment!Q13*Controls!$B$78 -> 549.85 | L13: =(Controls!$B$79*(Controls!$B$68+Monthly_Deployment!Q13*Controls!$B$70+Monthly_Deployment!N13*Controls!$B$72+Monthly_Deployment!N13*Controls!$B$74))+Monthly_Deployment!Q13*Controls!$B$80+Controls!$B$83 -> 142.1 | M13: =Controls!$B$81 -> 75 | N13: =Controls!$B$82 -> 10 | O13: =Monthly_Deployment!N13*(Controls!$B$84+Controls!$B$86)+Monthly_Deployment!Q13*Controls!$B$85 -> 440 | P13: =G13+H13+I13+J13+K13+L13+M13+N13+O13 -> 12353.017
... A37: 36 | B37: =Monthly_Deployment!C37 -> Jun-29 | C37: =IF(A37<=Controls!$B$40,Controls!$B$38,Controls!$B$39) -> 0.6 | D37: =Monthly_Deployment!U37*C37 -> 3283.2 | E37: =Monthly_Deployment!V37*C37 -> 1728 | F37: =Monthly_Deployment!M37*Controls!$B$54*Controls!$B$41/12 -> 116.66667 | G37: =D37+E37+F37 -> 5127.8667 | H37: =Controls!$B$68*Controls!$B$69/12 -> 333.33333 | I37: =Monthly_Deployment!Q37*Controls!$B$70*Controls!$B$71/12+Monthly_Deployment!N37*Controls!$B$72*Controls!$B$73/12+Monthly_Deployment!N37*Controls!$B$74*Controls!$B$75/12 -> 497.5 | J37: =(H37+I37)*Controls!$B$76 -> 166.16667 | K37: =(H37+I37)*Controls!$B$77+Monthly_Deployment!Q37*Controls!$B$78 -> 549.85 | L37: =(Controls!$B$79*(Controls!$B$68+Monthly_Deployment!Q37*Controls!$B$70+Monthly_Deployment!N37*Controls!$B$72+Monthly_Deployment!N37*Controls!$B$74))+Monthly_Deployment!Q37*Controls!$B$80+Controls!$B$83 -> 142.1 | M37: =Controls!$B$81 -> 75 | N37: =Controls!$B$82 -> 10 | O37: =Monthly_Deployment!N37*(Controls!$B$84+Controls!$B$86)+Monthly_Deployment!Q37*Controls!$B$85 -> 440 | P37: =G37+H37+I37+J37+K37+L37+M37+N37+O37 -> 7341.8167

Sheet Capex_36M
A1: Month # | B1: Month | C1: New Mining MW | D1: New Solar MW | E1: New Containers | F1: Site Starts | G1: ASIC Hardware | H1: Containers | I1: Electrical EPC | J1: Solar PV | K1: Spares | L1: Tools/Staff/Setup | M1: Logistics/Duties | N1: Total Capex Basis | O1: Capex Cash Spend
A2: 1 | B2: =Monthly_Deployment!C2 -> Jul-26 | C2: =Monthly_Deployment!O2 -> 0 | D2: =Monthly_Deployment!P2 -> 0 | E2: =Monthly_Deployment!R2 -> 0 | F2: =IF(AND(Monthly_Deployment!G2=0,Monthly_Deployment!D2>0),1,0)+IF(AND(Monthly_Deployment!H2=0,Monthly_Deployment!E2>0),1,0) -> 0 | G2: =IF(Controls!$B$45=0,0,C2/(1+Controls!$B$47)*1000000/Controls!$B$45*Controls!$B$46*Controls!$B$25/1000) -> 0 | H2: =E2*Controls!$B$50*Controls!$B$25/1000 -> 0 | I2: =F2*Controls!$B$52+C2*Controls!$B$53 -> 0 | J2: =D2*Controls!$B$54 -> 0 | K2: =G2*Controls!$B$55 -> 0 | L2: =F2*Controls!$B$56+Monthly_Deployment!R2*Controls!$B$57+IF(A2=1,Controls!$B$64+Controls!$B$65+Controls!$B$66,0) -> 2450 | M2: =E2*(Controls!$B$58*Controls!$B$25/1000+Controls!$B$59+Controls!$B$60+Controls!$B$61)+(G2+H2)*(Controls!$B$62+Controls!$B$63) -> 0 | N2: =SUM(G2:M2) -> 2450 | O2: =N2 -> 2450
A3: 2 | B3: =Monthly_Deployment!C3 -> Aug-26 | C3: =Monthly_Deployment!O3 -> 5 | D3: =Monthly_Deployment!P3 -> 0 | E3: =Monthly_Deployment!R3 -> 3 | F3: =IF(AND(Monthly_Deployment!G3=0,Monthly_Deployment!D3>0),1,0)+IF(AND(Monthly_Deployment!H3=0,Monthly_Deployment!E3>0),1,0) -> 1 | G3: =IF(Controls!$B$45=0,0,C3/(1+Controls!$B$47)*1000000/Controls!$B$45*Controls!$B$46*Controls!$B$25/1000) -> 54723.81 | H3: =E3*Controls!$B$50*Controls!$B$25/1000 -> 17850 | I3: =F3*Controls!$B$52+C3*Controls!$B$53 -> 44406 | J3: =D3*Controls!$B$54 -> 0 | K3: =G3*Controls!$B$55 -> 1094.4762 | L3: =F3*Controls!$B$56+Monthly_Deployment!R3*Controls!$B$57+IF(A3=1,Controls!$B$64+Controls!$B$65+Controls!$B$66,0) -> 855 | M3: =E3*(Controls!$B$58*Controls!$B$25/1000+Controls!$B$59+Controls!$B$60+Controls!$B$61)+(G3+H3)*(Controls!$B$62+Controls!$B$63) -> 5572.4286 | N3: =SUM(G3:M3) -> 124501.71 | O3: =N3 -> 124501.71
A4: 3 | B4: =Monthly_Deployment!C4 -> Sept-26 | C4: =Monthly_Deployment!O4 -> 10 | D4: =Monthly_Deployment!P4 -> 0 | E4: =Monthly_Deployment!R4 -> 5 | F4: =IF(AND(Monthly_Deployment!G4=0,Monthly_Deployment!D4>0),1,0)+IF(AND(Monthly_Deployment!H4=0,Monthly_Deployment!E4>0),1,0) -> 1 | G4: =IF(Controls!$B$45=0,0,C4/(1+Controls!$B$47)*1000000/Controls!$B$45*Controls!$B$46*Controls!$B$25/1000) -> 109447.62 | H4: =E4*Controls!$B$50*Controls!$B$25/1000 -> 29750 | I4: =F4*Controls!$B$52+C4*Controls!$B$53 -> 63436 | J4: =D4*Controls!$B$54 -> 0 | K4: =G4*Controls!$B$55 -> 2188.9524 | L4: =F4*Controls!$B$56+Monthly_Deployment!R4*Controls!$B$57+IF(A4=1,Controls!$B$64+Controls!$B$65+Controls!$B$66,0) -> 925 | M4: =E4*(Controls!$B$58*Controls!$B$25/1000+Controls!$B$59+Controls!$B$60+Controls!$B$61)+(G4+H4)*(Controls!$B$62+Controls!$B$63) -> 10381.857 | N4: =SUM(G4:M4) -> 216129.43 | O4: =N4 -> 216129.43
A5: 4 | B5: =Monthly_Deployment!C5 -> Oct-26 | C5: =Monthly_Deployment!O5 -> 5 | D5: =Monthly_Deployment!P5 -> 10 | E5: =Monthly_Deployment!R5 -> 3 | F5: =IF(AND(Monthly_Deployment!G5=0,Monthly_Deployment!D5>0),1,0)+IF(AND(Monthly_Deployment!H5=0,Monthly_Deployment!E5>0),1,0) -> 0 | G5: =IF(Controls!$B$45=0,0,C5/(1+Controls!$B$47)*1000000/Controls!$B$45*Controls!$B$46*Controls!$B$25/1000) -> 54723.81 | H5: =E5*Controls!$B$50*Controls!$B$25/1000 -> 17850 | I5: =F5*Controls!$B$52+C5*Controls!$B$53 -> 19030 | J5: =D5*Controls!$B$54 -> 70000 | K5: =G5*Controls!$B$55 -> 1094.4762 | L5: =F5*Controls!$B$56+Monthly_Deployment!R5*Controls!$B$57+IF(A5=1,Controls!$B$64+Controls!$B$65+Controls!$B$66,0) -> 105 | M5: =E5*(Controls!$B$58*Controls!$B$25/1000+Controls!$B$59+Controls!$B$60+Controls!$B$61)+(G5+H5)*(Controls!$B$62+Controls!$B$63) -> 5572.4286 | N5: =SUM(G5:M5) -> 168375.71 | O5: =N5 -> 168375.71
A6: 5 | B6: =Monthly_Deployment!C6 -> Nov-26 | C6: =Monthly_Deployment!O6 -> 0 | D6: =Monthly_Deployment!P6 -> 0 | E6: =Monthly_Deployment!R6 -> 0 | F6: =IF(AND(Monthly_Deployment!G6=0,Monthly_Deployment!D6>0),1,0)+IF(AND(Monthly_Deployment!H6=0,Monthly_Deployment!E6>0),1,0) -> 0 | G6: =IF(Controls!$B$45=0,0,C6/(1+Controls!$B$47)*1000000/Controls!$B$45*Controls!$B$46*Controls!$B$25/1000) -> 0 | H6: =E6*Controls!$B$50*Controls!$B$25/1000 -> 0 | I6: =F6*Controls!$B$52+C6*Controls!$B$53 -> 0 | J6: =D6*Controls!$B$54 -> 0 | K6: =G6*Controls!$B$55 -> 0 | L6: =F6*Controls!$B$56+Monthly_Deployment!R6*Controls!$B$57+IF(A6=1,Controls!$B$64+Controls!$B$65+Controls!$B$66,0) -> 0 | M6: =E6*(Controls!$B$58*Controls!$B$25/1000+Controls!$B$59+Controls!$B$60+Controls!$B$61)+(G6+H6)*(Controls!$B$62+Controls!$B$63) -> 0 | N6: =SUM(G6:M6) -> 0 | O6: =N6 -> 0
A7: 6 | B7: =Monthly_Deployment!C7 -> Dec-26 | C7: =Monthly_Deployment!O7 -> 0 | D7: =Monthly_Deployment!P7 -> 0 | E7: =Monthly_Deployment!R7 -> 0 | F7: =IF(AND(Monthly_Deployment!G7=0,Monthly_Deployment!D7>0),1,0)+IF(AND(Monthly_Deployment!H7=0,Monthly_Deployment!E7>0),1,0) -> 0 | G7: =IF(Controls!$B$45=0,0,C7/(1+Controls!$B$47)*1000000/Controls!$B$45*Controls!$B$46*Controls!$B$25/1000) -> 0 | H7: =E7*Controls!$B$50*Controls!$B$25/1000 -> 0 | I7: =F7*Controls!$B$52+C7*Controls!$B$53 -> 0 | J7: =D7*Controls!$B$54 -> 0 | K7: =G7*Controls!$B$55 -> 0 | L7: =F7*Controls!$B$56+Monthly_Deployment!R7*Controls!$B$57+IF(A7=1,Controls!$B$64+Controls!$B$65+Controls!$B$66,0) -> 0 | M7: =E7*(Controls!$B$58*Controls!$B$25/1000+Controls!$B$59+Controls!$B$60+Controls!$B$61)+(G7+H7)*(Controls!$B$62+Controls!$B$63) -> 0 | N7: =SUM(G7:M7) -> 0 | O7: =N7 -> 0
A8: 7 | B8: =Monthly_Deployment!C8 -> Jan-27 | C8: =Monthly_Deployment!O8 -> 0 | D8: =Monthly_Deployment!P8 -> 0 | E8: =Monthly_Deployment!R8 -> 0 | F8: =IF(AND(Monthly_Deployment!G8=0,Monthly_Deployment!D8>0),1,0)+IF(AND(Monthly_Deployment!H8=0,Monthly_Deployment!E8>0),1,0) -> 0 | G8: =IF(Controls!$B$45=0,0,C8/(1+Controls!$B$47)*1000000/Controls!$B$45*Controls!$B$46*Controls!$B$25/1000) -> 0 | H8: =E8*Controls!$B$50*Controls!$B$25/1000 -> 0 | I8: =F8*Controls!$B$52+C8*Controls!$B$53 -> 0 | J8: =D8*Controls!$B$54 -> 0 | K8: =G8*Controls!$B$55 -> 0 | L8: =F8*Controls!$B$56+Monthly_Deployment!R8*Controls!$B$57+IF(A8=1,Controls!$B$64+Controls!$B$65+Controls!$B$66,0) -> 0 | M8: =E8*(Controls!$B$58*Controls!$B$25/1000+Controls!$B$59+Controls!$B$60+Controls!$B$61)+(G8+H8)*(Controls!$B$62+Controls!$B$63) -> 0 | N8: =SUM(G8:M8) -> 0 | O8: =N8 -> 0
A9: 8 | B9: =Monthly_Deployment!C9 -> Feb-27 | C9: =Monthly_Deployment!O9 -> 0 | D9: =Monthly_Deployment!P9 -> 0 | E9: =Monthly_Deployment!R9 -> 0 | F9: =IF(AND(Monthly_Deployment!G9=0,Monthly_Deployment!D9>0),1,0)+IF(AND(Monthly_Deployment!H9=0,Monthly_Deployment!E9>0),1,0) -> 0 | G9: =IF(Controls!$B$45=0,0,C9/(1+Controls!$B$47)*1000000/Controls!$B$45*Controls!$B$46*Controls!$B$25/1000) -> 0 | H9: =E9*Controls!$B$50*Controls!$B$25/1000 -> 0 | I9: =F9*Controls!$B$52+C9*Controls!$B$53 -> 0 | J9: =D9*Controls!$B$54 -> 0 | K9: =G9*Controls!$B$55 -> 0 | L9: =F9*Controls!$B$56+Monthly_Deployment!R9*Controls!$B$57+IF(A9=1,Controls!$B$64+Controls!$B$65+Controls!$B$66,0) -> 0 | M9: =E9*(Controls!$B$58*Controls!$B$25/1000+Controls!$B$59+Controls!$B$60+Controls!$B$61)+(G9+H9)*(Controls!$B$62+Controls!$B$63) -> 0 | N9: =SUM(G9:M9) -> 0 | O9: =N9 -> 0
A10: 9 | B10: =Monthly_Deployment!C10 -> Mar-27 | C10: =Monthly_Deployment!O10 -> 0 | D10: =Monthly_Deployment!P10 -> 0 | E10: =Monthly_Deployment!R10 -> 0 | F10: =IF(AND(Monthly_Deployment!G10=0,Monthly_Deployment!D10>0),1,0)+IF(AND(Monthly_Deployment!H10=0,Monthly_Deployment!E10>0),1,0) -> 0 | G10: =IF(Controls!$B$45=0,0,C10/(1+Controls!$B$47)*1000000/Controls!$B$45*Controls!$B$46*Controls!$B$25/1000) -> 0 | H10: =E10*Controls!$B$50*Controls!$B$25/1000 -> 0 | I10: =F10*Controls!$B$52+C10*Controls!$B$53 -> 0 | J10: =D10*Controls!$B$54 -> 0 | K10: =G10*Controls!$B$55 -> 0 | L10: =F10*Controls!$B$56+Monthly_Deployment!R10*Controls!$B$57+IF(A10=1,Controls!$B$64+Controls!$B$65+Controls!$B$66,0) -> 0 | M10: =E10*(Controls!$B$58*Controls!$B$25/1000+Controls!$B$59+Controls!$B$60+Controls!$B$61)+(G10+H10)*(Controls!$B$62+Controls!$B$63) -> 0 | N10: =SUM(G10:M10) -> 0 | O10: =N10 -> 0
A11: 10 | B11: =Monthly_Deployment!C11 -> Apr-27 | C11: =Monthly_Deployment!O11 -> 0 | D11: =Monthly_Deployment!P11 -> 0 | E11: =Monthly_Deployment!R11 -> 0 | F11: =IF(AND(Monthly_Deployment!G11=0,Monthly_Deployment!D11>0),1,0)+IF(AND(Monthly_Deployment!H11=0,Monthly_Deployment!E11>0),1,0) -> 0 | G11: =IF(Controls!$B$45=0,0,C11/(1+Controls!$B$47)*1000000/Controls!$B$45*Controls!$B$46*Controls!$B$25/1000) -> 0 | H11: =E11*Controls!$B$50*Controls!$B$25/1000 -> 0 | I11: =F11*Controls!$B$52+C11*Controls!$B$53 -> 0 | J11: =D11*Controls!$B$54 -> 0 | K11: =G11*Controls!$B$55 -> 0 | L11: =F11*Controls!$B$56+Monthly_Deployment!R11*Controls!$B$57+IF(A11=1,Controls!$B$64+Controls!$B$65+Controls!$B$66,0) -> 0 | M11: =E11*(Controls!$B$58*Controls!$B$25/1000+Controls!$B$59+Controls!$B$60+Controls!$B$61)+(G11+H11)*(Controls!$B$62+Controls!$B$63) -> 0 | N11: =SUM(G11:M11) -> 0 | O11: =N11 -> 0
A12: 11 | B12: =Monthly_Deployment!C12 -> May-27 | C12: =Monthly_Deployment!O12 -> 0 | D12: =Monthly_Deployment!P12 -> 0 | E12: =Monthly_Deployment!R12 -> 0 | F12: =IF(AND(Monthly_Deployment!G12=0,Monthly_Deployment!D12>0),1,0)+IF(AND(Monthly_Deployment!H12=0,Monthly_Deployment!E12>0),1,0) -> 0 | G12: =IF(Controls!$B$45=0,0,C12/(1+Controls!$B$47)*1000000/Controls!$B$45*Controls!$B$46*Controls!$B$25/1000) -> 0 | H12: =E12*Controls!$B$50*Controls!$B$25/1000 -> 0 | I12: =F12*Controls!$B$52+C12*Controls!$B$53 -> 0 | J12: =D12*Controls!$B$54 -> 0 | K12: =G12*Controls!$B$55 -> 0 | L12: =F12*Controls!$B$56+Monthly_Deployment!R12*Controls!$B$57+IF(A12=1,Controls!$B$64+Controls!$B$65+Controls!$B$66,0) -> 0 | M12: =E12*(Controls!$B$58*Controls!$B$25/1000+Controls!$B$59+Controls!$B$60+Controls!$B$61)+(G12+H12)*(Controls!$B$62+Controls!$B$63) -> 0 | N12: =SUM(G12:M12) -> 0 | O12: =N12 -> 0
A13: 12 | B13: =Monthly_Deployment!C13 -> Jun-27 | C13: =Monthly_Deployment!O13 -> 0 | D13: =Monthly_Deployment!P13 -> 0 | E13: =Monthly_Deployment!R13 -> 0 | F13: =IF(AND(Monthly_Deployment!G13=0,Monthly_Deployment!D13>0),1,0)+IF(AND(Monthly_Deployment!H13=0,Monthly_Deployment!E13>0),1,0) -> 0 | G13: =IF(Controls!$B$45=0,0,C13/(1+Controls!$B$47)*1000000/Controls!$B$45*Controls!$B$46*Controls!$B$25/1000) -> 0 | H13: =E13*Controls!$B$50*Controls!$B$25/1000 -> 0 | I13: =F13*Controls!$B$52+C13*Controls!$B$53 -> 0 | J13: =D13*Controls!$B$54 -> 0 | K13: =G13*Controls!$B$55 -> 0 | L13: =F13*Controls!$B$56+Monthly_Deployment!R13*Controls!$B$57+IF(A13=1,Controls!$B$64+Controls!$B$65+Controls!$B$66,0) -> 0 | M13: =E13*(Controls!$B$58*Controls!$B$25/1000+Controls!$B$59+Controls!$B$60+Controls!$B$61)+(G13+H13)*(Controls!$B$62+Controls!$B$63) -> 0 | N13: =SUM(G13:M13) -> 0 | O13: =N13 -> 0
... A37: 36 | B37: =Monthly_Deployment!C37 -> Jun-29 | C37: =Monthly_Deployment!O37 -> 0 | D37: =Monthly_Deployment!P37 -> 0 | E37: =Monthly_Deployment!R37 -> 0 | F37: =IF(AND(Monthly_Deployment!G37=0,Monthly_Deployment!D37>0),1,0)+IF(AND(Monthly_Deployment!H37=0,Monthly_Deployment!E37>0),1,0) -> 0 | G37: =IF(Controls!$B$45=0,0,C37/(1+Controls!$B$47)*1000000/Controls!$B$45*Controls!$B$46*Controls!$B$25/1000) -> 0 | H37: =E37*Controls!$B$50*Controls!$B$25/1000 -> 0 | I37: =F37*Controls!$B$52+C37*Controls!$B$53 -> 0 | J37: =D37*Controls!$B$54 -> 0 | K37: =G37*Controls!$B$55 -> 0 | L37: =F37*Controls!$B$56+Monthly_Deployment!R37*Controls!$B$57+IF(A37=1,Controls!$B$64+Controls!$B$65+Controls!$B$66,0) -> 0 | M37: =E37*(Controls!$B$58*Controls!$B$25/1000+Controls!$B$59+Controls!$B$60+Controls!$B$61)+(G37+H37)*(Controls!$B$62+Controls!$B$63) -> 0 | N37: =SUM(G37:M37) -> 0 | O37: =N37 -> 0

Sheet Funding_36M
A1: Month # | B1: Month | C1: Revenue | D1: Cash Opex | E1: EBITDA | F1: Capex Cash | G1: Unlevered CF | H1: Opening Cash | I1: Required Funding | J1: Equity Draw | K1: Debt Draw Gross | L1: Arrangement Fee | M1: Net Funding | N1: Interest | O1: Principal | P1: Debt Service | Q1: Ending Cash | R1: Opening Debt | S1: Capitalised Interest | T1: Closing Debt | U1: Antalpha Draw | V1: DMTN Draw | W1: Antalpha Interest | X1: DMTN Interest | Y1: Antalpha Close Bal | Z1: DMTN Close Bal | AA1: Trailing-12M DSCR | AB1: Bullet / Conversion | AC1: Unlevered CF (IRR) | AD1: Equity CF (IRR)
A2: 1 | B2: =Monthly_Deployment!C2 -> Jul-26 | C2: =Revenue_36M!P2 -> 0 | D2: =Opex_36M!P2 -> 523 | E2: =C2-D2 -> -523 | F2: =Capex_36M!O2 -> 2450 | G2: =E2-F2 -> -2973 | H2: =0 -> 0 | I2: =MAX(Controls!$B$22+Controls!$B$111-(H2+G2),0)+IF(A2=1,Controls!$B$21*(Controls!$B$101+Controls!$B$104),0) -> 40065.5 | J2: =MIN(I2,Controls!$B$100) -> 40065.5 | K2: =U2+V2 -> 0 | L2: =IF(A2=1,Controls!$B$21*(Controls!$B$101+Controls!$B$104),0) -> 4880 | M2: =J2+K2-L2 -> 35185.5 | N2: =W2+X2 -> 0 | O2: =0 -> 0 | P2: =IF(A2<=Controls!$B$109,0,N2+O2) -> 0 | Q2: =H2+G2+M2-P2 -> 32212.5 | R2: =0 -> 0 | S2: =IF(A2<=Controls!$B$109,N2,0) -> 0 | T2: =Y2+Z2 -> 0 | U2: =MIN(I2-J2,Controls!$B$101) -> 0 | V2: =MIN(I2-J2-U2,Controls!$B$104) -> 0 | W2: =(0+U2/2)*Controls!$B$102/12 -> 0 | X2: =IF(AND(Controls!$B$107=1,A2>=Controls!$B$108),0,(0+V2/2)*Controls!$B$105/12) -> 0 | Y2: =0+U2+IF(A2<=Controls!$B$109,W2,0) -> 0 | Z2: =IF(AND(Controls!$B$107=1,A2>=Controls!$B$108),0,0+V2+IF(A2<=Controls!$B$109,X2,0)) -> 0 | AB2: =IF(A2=Controls!$B$103,"◀ Antalpha bullet due: R"&TEXT(Y2,"#,##0")&"k - refinance/convert",IF(AND(Controls!$B$107=1,A2>=Controls!$B$108)*( A2=Controls!$B$108 ),"◀ DMTN converts to equity","")) | AC2: =G2+IF(A2=36,Controls!$B$113,0) -> -2973 | AD2: =-J2+IF(A2=36,Q2+Controls!$B$113-T2,0) -> -40065.5
A3: 2 | B3: =Monthly_Deployment!C3 -> Aug-26 | C3: =Revenue_36M!P3 -> 3175.776 | D3: =Opex_36M!P3 -> 2793.6887 | E3: =C3-D3 -> 382.08723 | F3: =Capex_36M!O3 -> 124501.71 | G3: =E3-F3 -> -124119.63 | H3: =Q2 -> 32212.5 | I3: =MAX(Controls!$B$22+Controls!$B$111-(H3+G3),0)+IF(A3=1,Controls!$B$21*(Controls!$B$101+Controls!$B$104),0) -> 124119.63 | J3: =MIN(I3,MAX(Controls!$B$100-SUM($J$2:J2),0)) -> 27934.5 | K3: =U3+V3 -> 96185.127 | L3: =IF(A3=1,Controls!$B$21*(Controls!$B$101+Controls!$B$104),0) -> 0 | M3: =J3+K3-L3 -> 124119.63 | N3: =W3+X3 -> 400.77136 | O3: =0 -> 0 | P3: =IF(A3<=Controls!$B$109,0,N3+O3) -> 0 | Q3: =H3+G3+M3-P3 -> 32212.5 | R3: =T2 -> 0 | S3: =IF(A3<=Controls!$B$109,N3,0) -> 400.77136 | T3: =Y3+Z3 -> 96585.898 | U3: =MIN(I3-J3,MAX(Controls!$B$101-SUM($U$2:U2),0)) -> 96185.127 | V3: =MIN(I3-J3-U3,MAX(Controls!$B$104-SUM($V$2:V2),0)) -> 0 | W3: =(Y2+U3/2)*Controls!$B$102/12 -> 400.77136 | X3: =IF(AND(Controls!$B$107=1,A3>=Controls!$B$108),0,(Z2+V3/2)*Controls!$B$105/12) -> 0 | Y3: =Y2+U3+IF(A3<=Controls!$B$109,W3,0) -> 96585.898 | Z3: =IF(AND(Controls!$B$107=1,A3>=Controls!$B$108),0,Z2+V3+IF(A3<=Controls!$B$109,X3,0)) -> 0 | AB3: =IF(A3=Controls!$B$103,"◀ Antalpha bullet due: R"&TEXT(Y3,"#,##0")&"k - refinance/convert",IF(AND(Controls!$B$107=1,A3>=Controls!$B$108)*( A3=Controls!$B$108 ),"◀ DMTN converts to equity","")) | AC3: =G3+IF(A3=36,Controls!$B$113,0) -> -124119.63 | AD3: =-J3+IF(A3=36,Q3+Controls!$B$113-T3,0) -> -27934.5
A4: 3 | B4: =Monthly_Deployment!C4 -> Sept-26 | C4: =Revenue_36M!P4 -> 12184.366 | D4: =Opex_36M!P4 -> 8418.875 | E4: =C4-D4 -> 3765.4906 | F4: =Capex_36M!O4 -> 216129.43 | G4: =E4-F4 -> -212363.94 | H4: =Q3 -> 32212.5 | I4: =MAX(Controls!$B$22+Controls!$B$111-(H4+G4),0)+IF(A4=1,Controls!$B$21*(Controls!$B$101+Controls!$B$104),0) -> 212363.94 | J4: =MIN(I4,MAX(Controls!$B$100-SUM($J$2:J3),0)) -> 0 | K4: =U4+V4 -> 212363.94 | L4: =IF(A4=1,Controls!$B$21*(Controls!$B$101+Controls!$B$104),0) -> 0 | M4: =J4+K4-L4 -> 212363.94 | N4: =W4+X4 -> 1755.872 | O4: =0 -> 0 | P4: =IF(A4<=Controls!$B$109,0,N4+O4) -> 0 | Q4: =H4+G4+M4-P4 -> 32212.5 | R4: =T3 -> 96585.898 | S4: =IF(A4<=Controls!$B$109,N4,0) -> 1755.872 | T4: =Y4+Z4 -> 310705.71 | U4: =MIN(I4-J4,MAX(Controls!$B$101-SUM($U$2:U3),0)) -> 141814.87 | V4: =MIN(I4-J4-U4,MAX(Controls!$B$104-SUM($V$2:V3),0)) -> 70549.065 | W4: =(Y3+U4/2)*Controls!$B$102/12 -> 1395.7778 | X4: =IF(AND(Controls!$B$107=1,A4>=Controls!$B$108),0,(Z3+V4/2)*Controls!$B$105/12) -> 360.09419 | Y4: =Y3+U4+IF(A4<=Controls!$B$109,W4,0) -> 239796.55 | Z4: =IF(AND(Controls!$B$107=1,A4>=Controls!$B$108),0,Z3+V4+IF(A4<=Controls!$B$109,X4,0)) -> 70909.159 | AB4: =IF(A4=Controls!$B$103,"◀ Antalpha bullet due: R"&TEXT(Y4,"#,##0")&"k - refinance/convert",IF(AND(Controls!$B$107=1,A4>=Controls!$B$108)*( A4=Controls!$B$108 ),"◀ DMTN converts to equity","")) | AC4: =G4+IF(A4=36,Controls!$B$113,0) -> -212363.94 | AD4: =-J4+IF(A4=36,Q4+Controls!$B$113-T4,0) -> 0
A5: 4 | B5: =Monthly_Deployment!C5 -> Oct-26 | C5: =Revenue_36M!P5 -> 21837.996 | D5: =Opex_36M!P5 -> 12449.115 | E5: =C5-D5 -> 9388.8811 | F5: =Capex_36M!O5 -> 168375.71 | G5: =E5-F5 -> -158986.83 | H5: =Q4 -> 32212.5 | I5: =MAX(Controls!$B$22+Controls!$B$111-(H5+G5),0)+IF(A5=1,Controls!$B$21*(Controls!$B$101+Controls!$B$104),0) -> 158986.83 | J5: =MIN(I5,MAX(Controls!$B$100-SUM($J$2:J4),0)) -> 0 | K5: =U5+V5 -> 158986.83 | L5: =IF(A5=1,Controls!$B$21*(Controls!$B$101+Controls!$B$104),0) -> 0 | M5: =J5+K5-L5 -> 158986.83 | N5: =W5+X5 -> 3533.6642 | O5: =0 -> 0 | P5: =IF(A5<=Controls!$B$109,0,N5+O5) -> 0 | Q5: =H5+G5+M5-P5 -> 32212.5 | R5: =T4 -> 310705.71 | S5: =IF(A5<=Controls!$B$109,N5,0) -> 3533.6642 | T5: =Y5+Z5 -> 473226.21 | U5: =MIN(I5-J5,MAX(Controls!$B$101-SUM($U$2:U4),0)) -> 0 | V5: =MIN(I5-J5-U5,MAX(Controls!$B$104-SUM($V$2:V4),0)) -> 158986.83 | W5: =(Y4+U5/2)*Controls!$B$102/12 -> 1998.3046 | X5: =IF(AND(Controls!$B$107=1,A5>=Controls!$B$108),0,(Z4+V5/2)*Controls!$B$105/12) -> 1535.3596 | Y5: =Y4+U5+IF(A5<=Controls!$B$109,W5,0) -> 241794.85 | Z5: =IF(AND(Controls!$B$107=1,A5>=Controls!$B$108),0,Z4+V5+IF(A5<=Controls!$B$109,X5,0)) -> 231431.35 | AB5: =IF(A5=Controls!$B$103,"◀ Antalpha bullet due: R"&TEXT(Y5,"#,##0")&"k - refinance/convert",IF(AND(Controls!$B$107=1,A5>=Controls!$B$108)*( A5=Controls!$B$108 ),"◀ DMTN converts to equity","")) | AC5: =G5+IF(A5=36,Controls!$B$113,0) -> -158986.83 | AD5: =-J5+IF(A5=36,Q5+Controls!$B$113-T5,0) -> 0
A6: 5 | B6: =Monthly_Deployment!C6 -> Nov-26 | C6: =Revenue_36M!P6 -> 23938.312 | D6: =Opex_36M!P6 -> 12353.017 | E6: =C6-D6 -> 11585.295 | F6: =Capex_36M!O6 -> 0 | G6: =E6-F6 -> 11585.295 | H6: =Q5 -> 32212.5 | I6: =MAX(Controls!$B$22+Controls!$B$111-(H6+G6),0)+IF(A6=1,Controls!$B$21*(Controls!$B$101+Controls!$B$104),0) -> 0 | J6: =MIN(I6,MAX(Controls!$B$100-SUM($J$2:J5),0)) -> 0 | K6: =U6+V6 -> 0 | L6: =IF(A6=1,Controls!$B$21*(Controls!$B$101+Controls!$B$104),0) -> 0 | M6: =J6+K6-L6 -> 0 | N6: =W6+X6 -> 4377.4855 | O6: =0 -> 0 | P6: =IF(A6<=Controls!$B$109,0,N6+O6) -> 0 | Q6: =H6+G6+M6-P6 -> 43797.795 | R6: =T5 -> 473226.21 | S6: =IF(A6<=Controls!$B$109,N6,0) -> 4377.4855 | T6: =Y6+Z6 -> 477603.69 | U6: =MIN(I6-J6,MAX(Controls!$B$101-SUM($U$2:U5),0)) -> 0 | V6: =MIN(I6-J6-U6,MAX(Controls!$B$104-SUM($V$2:V5),0)) -> 0 | W6: =(Y5+U6/2)*Controls!$B$102/12 -> 2014.9571 | X6: =IF(AND(Controls!$B$107=1,A6>=Controls!$B$108),0,(Z5+V6/2)*Controls!$B$105/12) -> 2362.5284 | Y6: =Y5+U6+IF(A6<=Controls!$B$109,W6,0) -> 243809.81 | Z6: =IF(AND(Controls!$B$107=1,A6>=Controls!$B$108),0,Z5+V6+IF(A6<=Controls!$B$109,X6,0)) -> 233793.88 | AB6: =IF(A6=Controls!$B$103,"◀ Antalpha bullet due: R"&TEXT(Y6,"#,##0")&"k - refinance/convert",IF(AND(Controls!$B$107=1,A6>=Controls!$B$108)*( A6=Controls!$B$108 ),"◀ DMTN converts to equity","")) | AC6: =G6+IF(A6=36,Controls!$B$113,0) -> 11585.295 | AD6: =-J6+IF(A6=36,Q6+Controls!$B$113-T6,0) -> 0
A7: 6 | B7: =Monthly_Deployment!C7 -> Dec-26 | C7: =Revenue_36M!P7 -> 24516.646 | D7: =Opex_36M!P7 -> 12687.097 | E7: =C7-D7 -> 11829.549 | F7: =Capex_36M!O7 -> 0 | G7: =E7-F7 -> 11829.549 | H7: =Q6 -> 43797.795 | I7: =MAX(Controls!$B$22+Controls!$B$111-(H7+G7),0)+IF(A7=1,Controls!$B$21*(Controls!$B$101+Controls!$B$104),0) -> 0 | J7: =MIN(I7,MAX(Controls!$B$100-SUM($J$2:J6),0)) -> 0 | K7: =U7+V7 -> 0 | L7: =IF(A7=1,Controls!$B$21*(Controls!$B$101+Controls!$B$104),0) -> 0 | M7: =J7+K7-L7 -> 0 | N7: =W7+X7 -> 4418.3943 | O7: =0 -> 0 | P7: =IF(A7<=Controls!$B$109,0,N7+O7) -> 0 | Q7: =H7+G7+M7-P7 -> 55627.344 | R7: =T6 -> 477603.69 | S7: =IF(A7<=Controls!$B$109,N7,0) -> 4418.3943 | T7: =Y7+Z7 -> 482022.09 | U7: =MIN(I7-J7,MAX(Controls!$B$101-SUM($U$2:U6),0)) -> 0 | V7: =MIN(I7-J7-U7,MAX(Controls!$B$104-SUM($V$2:V6),0)) -> 0 | W7: =(Y6+U7/2)*Controls!$B$102/12 -> 2031.7484 | X7: =IF(AND(Controls!$B$107=1,A7>=Controls!$B$108),0,(Z6+V7/2)*Controls!$B$105/12) -> 2386.6459 | Y7: =Y6+U7+IF(A7<=Controls!$B$109,W7,0) -> 245841.56 | Z7: =IF(AND(Controls!$B$107=1,A7>=Controls!$B$108),0,Z6+V7+IF(A7<=Controls!$B$109,X7,0)) -> 236180.53 | AB7: =IF(A7=Controls!$B$103,"◀ Antalpha bullet due: R"&TEXT(Y7,"#,##0")&"k - refinance/convert",IF(AND(Controls!$B$107=1,A7>=Controls!$B$108)*( A7=Controls!$B$108 ),"◀ DMTN converts to equity","")) | AC7: =G7+IF(A7=36,Controls!$B$113,0) -> 11829.549 | AD7: =-J7+IF(A7=36,Q7+Controls!$B$113-T7,0) -> 0
A8: 7 | B8: =Monthly_Deployment!C8 -> Jan-27 | C8: =Revenue_36M!P8 -> 24298.868 | D8: =Opex_36M!P8 -> 12687.097 | E8: =C8-D8 -> 11611.772 | F8: =Capex_36M!O8 -> 0 | G8: =E8-F8 -> 11611.772 | H8: =Q7 -> 55627.344 | I8: =MAX(Controls!$B$22+Controls!$B$111-(H8+G8),0)+IF(A8=1,Controls!$B$21*(Controls!$B$101+Controls!$B$104),0) -> 0 | J8: =MIN(I8,MAX(Controls!$B$100-SUM($J$2:J7),0)) -> 0 | K8: =U8+V8 -> 0 | L8: =IF(A8=1,Controls!$B$21*(Controls!$B$101+Controls!$B$104),0) -> 0 | M8: =J8+K8-L8 -> 0 | N8: =W8+X8 -> 4459.6892 | O8: =0 -> 0 | P8: =IF(A8<=Controls!$B$109,0,N8+O8) -> 4459.6892 | Q8: =H8+G8+M8-P8 -> 62779.427 | R8: =T7 -> 482022.09 | S8: =IF(A8<=Controls!$B$109,N8,0) -> 0 | T8: =Y8+Z8 -> 482022.09 | U8: =MIN(I8-J8,MAX(Controls!$B$101-SUM($U$2:U7),0)) -> 0 | V8: =MIN(I8-J8-U8,MAX(Controls!$B$104-SUM($V$2:V7),0)) -> 0 | W8: =(Y7+U8/2)*Controls!$B$102/12 -> 2048.6797 | X8: =IF(AND(Controls!$B$107=1,A8>=Controls!$B$108),0,(Z7+V8/2)*Controls!$B$105/12) -> 2411.0095 | Y8: =Y7+U8+IF(A8<=Controls!$B$109,W8,0) -> 245841.56 | Z8: =IF(AND(Controls!$B$107=1,A8>=Controls!$B$108),0,Z7+V8+IF(A8<=Controls!$B$109,X8,0)) -> 236180.53 | AB8: =IF(A8=Controls!$B$103,"◀ Antalpha bullet due: R"&TEXT(Y8,"#,##0")&"k - refinance/convert",IF(AND(Controls!$B$107=1,A8>=Controls!$B$108)*( A8=Controls!$B$108 ),"◀ DMTN converts to equity","")) | AC8: =G8+IF(A8=36,Controls!$B$113,0) -> 11611.772 | AD8: =-J8+IF(A8=36,Q8+Controls!$B$113-T8,0) -> 0
A9: 8 | B9: =Monthly_Deployment!C9 -> Feb-27 | C9: =Revenue_36M!P9 -> 21752.304 | D9: =Opex_36M!P9 -> 11684.857 | E9: =C9-D9 -> 10067.447 | F9: =Capex_36M!O9 -> 0 | G9: =E9-F9 -> 10067.447 | H9: =Q8 -> 62779.427 | I9: =MAX(Controls!$B$22+Controls!$B$111-(H9+G9),0)+IF(A9=1,Controls!$B$21*(Controls!$B$101+Controls!$B$104),0) -> 0 | J9: =MIN(I9,MAX(Controls!$B$100-SUM($J$2:J8),0)) -> 0 | K9: =U9+V9 -> 0 | L9: =IF(A9=1,Controls!$B$21*(Controls!$B$101+Controls!$B$104),0) -> 0 | M9: =J9+K9-L9 -> 0 | N9: =W9+X9 -> 4459.6892 | O9: =0 -> 0 | P9: =IF(A9<=Controls!$B$109,0,N9+O9) -> 4459.6892 | Q9: =H9+G9+M9-P9 -> 68387.185 | R9: =T8 -> 482022.09 | S9: =IF(A9<=Controls!$B$109,N9,0) -> 0 | T9: =Y9+Z9 -> 482022.09 | U9: =MIN(I9-J9,MAX(Controls!$B$101-SUM($U$2:U8),0)) -> 0 | V9: =MIN(I9-J9-U9,MAX(Controls!$B$104-SUM($V$2:V8),0)) -> 0 | W9: =(Y8+U9/2)*Controls!$B$102/12 -> 2048.6797 | X9: =IF(AND(Controls!$B$107=1,A9>=Controls!$B$108),0,(Z8+V9/2)*Controls!$B$105/12) -> 2411.0095 | Y9: =Y8+U9+IF(A9<=Controls!$B$109,W9,0) -> 245841.56 | Z9: =IF(AND(Controls!$B$107=1,A9>=Controls!$B$108),0,Z8+V9+IF(A9<=Controls!$B$109,X9,0)) -> 236180.53 | AB9: =IF(A9=Controls!$B$103,"◀ Antalpha bullet due: R"&TEXT(Y9,"#,##0")&"k - refinance/convert",IF(AND(Controls!$B$107=1,A9>=Controls!$B$108)*( A9=Controls!$B$108 ),"◀ DMTN converts to equity","")) | AC9: =G9+IF(A9=36,Controls!$B$113,0) -> 10067.447 | AD9: =-J9+IF(A9=36,Q9+Controls!$B$113-T9,0) -> 0
A10: 9 | B10: =Monthly_Deployment!C10 -> Mar-27 | C10: =Revenue_36M!P10 -> 23868.752 | D10: =Opex_36M!P10 -> 12687.097 | E10: =C10-D10 -> 11181.655 | F10: =Capex_36M!O10 -> 0 | G10: =E10-F10 -> 11181.655 | H10: =Q9 -> 68387.185 | I10: =MAX(Controls!$B$22+Controls!$B$111-(H10+G10),0)+IF(A10=1,Controls!$B$21*(Controls!$B$101+Controls!$B$104),0) -> 0 | J10: =MIN(I10,MAX(Controls!$B$100-SUM($J$2:J9),0)) -> 0 | K10: =U10+V10 -> 0 | L10: =IF(A10=1,Controls!$B$21*(Controls!$B$101+Controls!$B$104),0) -> 0 | M10: =J10+K10-L10 -> 0 | N10: =W10+X10 -> 4459.6892 | O10: =0 -> 0 | P10: =IF(A10<=Controls!$B$109,0,N10+O10) -> 4459.6892 | Q10: =H10+G10+M10-P10 -> 75109.151 | R10: =T9 -> 482022.09 | S10: =IF(A10<=Controls!$B$109,N10,0) -> 0 | T10: =Y10+Z10 -> 482022.09 | U10: =MIN(I10-J10,MAX(Controls!$B$101-SUM($U$2:U9),0)) -> 0 | V10: =MIN(I10-J10-U10,MAX(Controls!$B$104-SUM($V$2:V9),0)) -> 0 | W10: =(Y9+U10/2)*Controls!$B$102/12 -> 2048.6797 | X10: =IF(AND(Controls!$B$107=1,A10>=Controls!$B$108),0,(Z9+V10/2)*Controls!$B$105/12) -> 2411.0095 | Y10: =Y9+U10+IF(A10<=Controls!$B$109,W10,0) -> 245841.56 | Z10: =IF(AND(Controls!$B$107=1,A10>=Controls!$B$108),0,Z9+V10+IF(A10<=Controls!$B$109,X10,0)) -> 236180.53 | AB10: =IF(A10=Controls!$B$103,"◀ Antalpha bullet due: R"&TEXT(Y10,"#,##0")&"k - refinance/convert",IF(AND(Controls!$B$107=1,A10>=Controls!$B$108)*( A10=Controls!$B$108 ),"◀ DMTN converts to equity","")) | AC10: =G10+IF(A10=36,Controls!$B$113,0) -> 11181.655 | AD10: =-J10+IF(A10=36,Q10+Controls!$B$113-T10,0) -> 0
A11: 10 | B11: =Monthly_Deployment!C11 -> Apr-27 | C11: =Revenue_36M!P11 -> 22893.277 | D11: =Opex_36M!P11 -> 12353.017 | E11: =C11-D11 -> 10540.261 | F11: =Capex_36M!O11 -> 0 | G11: =E11-F11 -> 10540.261 | H11: =Q10 -> 75109.151 | I11: =MAX(Controls!$B$22+Controls!$B$111-(H11+G11),0)+IF(A11=1,Controls!$B$21*(Controls!$B$101+Controls!$B$104),0) -> 0 | J11: =MIN(I11,MAX(Controls!$B$100-SUM($J$2:J10),0)) -> 0 | K11: =U11+V11 -> 0 | L11: =IF(A11=1,Controls!$B$21*(Controls!$B$101+Controls!$B$104),0) -> 0 | M11: =J11+K11-L11 -> 0 | N11: =W11+X11 -> 4459.6892 | O11: =0 -> 0 | P11: =IF(A11<=Controls!$B$109,0,N11+O11) -> 4459.6892 | Q11: =H11+G11+M11-P11 -> 81189.722 | R11: =T10 -> 482022.09 | S11: =IF(A11<=Controls!$B$109,N11,0) -> 0 | T11: =Y11+Z11 -> 482022.09 | U11: =MIN(I11-J11,MAX(Controls!$B$101-SUM($U$2:U10),0)) -> 0 | V11: =MIN(I11-J11-U11,MAX(Controls!$B$104-SUM($V$2:V10),0)) -> 0 | W11: =(Y10+U11/2)*Controls!$B$102/12 -> 2048.6797 | X11: =IF(AND(Controls!$B$107=1,A11>=Controls!$B$108),0,(Z10+V11/2)*Controls!$B$105/12) -> 2411.0095 | Y11: =Y10+U11+IF(A11<=Controls!$B$109,W11,0) -> 245841.56 | Z11: =IF(AND(Controls!$B$107=1,A11>=Controls!$B$108),0,Z10+V11+IF(A11<=Controls!$B$109,X11,0)) -> 236180.53 | AB11: =IF(A11=Controls!$B$103,"◀ Antalpha bullet due: R"&TEXT(Y11,"#,##0")&"k - refinance/convert",IF(AND(Controls!$B$107=1,A11>=Controls!$B$108)*( A11=Controls!$B$108 ),"◀ DMTN converts to equity","")) | AC11: =G11+IF(A11=36,Controls!$B$113,0) -> 10540.261 | AD11: =-J11+IF(A11=36,Q11+Controls!$B$113-T11,0) -> 0
A12: 11 | B12: =Monthly_Deployment!C12 -> May-27 | C12: =Revenue_36M!P12 -> 23445.798 | D12: =Opex_36M!P12 -> 12687.097 | E12: =C12-D12 -> 10758.702 | F12: =Capex_36M!O12 -> 0 | G12: =E12-F12 -> 10758.702 | H12: =Q11 -> 81189.722 | I12: =MAX(Controls!$B$22+Controls!$B$111-(H12+G12),0)+IF(A12=1,Controls!$B$21*(Controls!$B$101+Controls!$B$104),0) -> 0 | J12: =MIN(I12,MAX(Controls!$B$100-SUM($J$2:J11),0)) -> 0 | K12: =U12+V12 -> 0 | L12: =IF(A12=1,Controls!$B$21*(Controls!$B$101+Controls!$B$104),0) -> 0 | M12: =J12+K12-L12 -> 0 | N12: =W12+X12 -> 4459.6892 | O12: =0 -> 0 | P12: =IF(A12<=Controls!$B$109,0,N12+O12) -> 4459.6892 | Q12: =H12+G12+M12-P12 -> 87488.735 | R12: =T11 -> 482022.09 | S12: =IF(A12<=Controls!$B$109,N12,0) -> 0 | T12: =Y12+Z12 -> 482022.09 | U12: =MIN(I12-J12,MAX(Controls!$B$101-SUM($U$2:U11),0)) -> 0 | V12: =MIN(I12-J12-U12,MAX(Controls!$B$104-SUM($V$2:V11),0)) -> 0 | W12: =(Y11+U12/2)*Controls!$B$102/12 -> 2048.6797 | X12: =IF(AND(Controls!$B$107=1,A12>=Controls!$B$108),0,(Z11+V12/2)*Controls!$B$105/12) -> 2411.0095 | Y12: =Y11+U12+IF(A12<=Controls!$B$109,W12,0) -> 245841.56 | Z12: =IF(AND(Controls!$B$107=1,A12>=Controls!$B$108),0,Z11+V12+IF(A12<=Controls!$B$109,X12,0)) -> 236180.53 | AB12: =IF(A12=Controls!$B$103,"◀ Antalpha bullet due: R"&TEXT(Y12,"#,##0")&"k - refinance/convert",IF(AND(Controls!$B$107=1,A12>=Controls!$B$108)*( A12=Controls!$B$108 ),"◀ DMTN converts to equity","")) | AC12: =G12+IF(A12=36,Controls!$B$113,0) -> 10758.702 | AD12: =-J12+IF(A12=36,Q12+Controls!$B$113-T12,0) -> 0
A13: 12 | B13: =Monthly_Deployment!C13 -> Jun-27 | C13: =Revenue_36M!P13 -> 22487.394 | D13: =Opex_36M!P13 -> 12353.017 | E13: =C13-D13 -> 10134.377 | F13: =Capex_36M!O13 -> 0 | G13: =E13-F13 -> 10134.377 | H13: =Q12 -> 87488.735 | I13: =MAX(Controls!$B$22+Controls!$B$111-(H13+G13),0)+IF(A13=1,Controls!$B$21*(Controls!$B$101+Controls!$B$104),0) -> 0 | J13: =MIN(I13,MAX(Controls!$B$100-SUM($J$2:J12),0)) -> 0 | K13: =U13+V13 -> 0 | L13: =IF(A13=1,Controls!$B$21*(Controls!$B$101+Controls!$B$104),0) -> 0 | M13: =J13+K13-L13 -> 0 | N13: =W13+X13 -> 4459.6892 | O13: =0 -> 0 | P13: =IF(A13<=Controls!$B$109,0,N13+O13) -> 4459.6892 | Q13: =H13+G13+M13-P13 -> 93163.423 | R13: =T12 -> 482022.09 | S13: =IF(A13<=Controls!$B$109,N13,0) -> 0 | T13: =Y13+Z13 -> 482022.09 | U13: =MIN(I13-J13,MAX(Controls!$B$101-SUM($U$2:U12),0)) -> 0 | V13: =MIN(I13-J13-U13,MAX(Controls!$B$104-SUM($V$2:V12),0)) -> 0 | W13: =(Y12+U13/2)*Controls!$B$102/12 -> 2048.6797 | X13: =IF(AND(Controls!$B$107=1,A13>=Controls!$B$108),0,(Z12+V13/2)*Controls!$B$105/12) -> 2411.0095 | Y13: =Y12+U13+IF(A13<=Controls!$B$109,W13,0) -> 245841.56 | Z13: =IF(AND(Controls!$B$107=1,A13>=Controls!$B$108),0,Z12+V13+IF(A13<=Controls!$B$109,X13,0)) -> 236180.53 | AB13: =IF(A13=Controls!$B$103,"◀ Antalpha bullet due: R"&TEXT(Y13,"#,##0")&"k - refinance/convert",IF(AND(Controls!$B$107=1,A13>=Controls!$B$108)*( A13=Controls!$B$108 ),"◀ DMTN converts to equity","")) | AC13: =G13+IF(A13=36,Controls!$B$113,0) -> 10134.377 | AD13: =-J13+IF(A13=36,Q13+Controls!$B$113-T13,0) -> 0
A14: 13 | B14: =Monthly_Deployment!C14 -> Jul-27 | C14: =Revenue_36M!P14 -> 23029.9 | D14: =Opex_36M!P14 -> 12687.097 | E14: =C14-D14 -> 10342.803 | F14: =Capex_36M!O14 -> 0 | G14: =E14-F14 -> 10342.803 | H14: =Q13 -> 93163.423 | I14: =MAX(Controls!$B$22+Controls!$B$111-(H14+G14),0)+IF(A14=1,Controls!$B$21*(Controls!$B$101+Controls!$B$104),0) -> 0 | J14: =MIN(I14,MAX(Controls!$B$100-SUM($J$2:J13),0)) -> 0 | K14: =U14+V14 -> 0 | L14: =IF(A14=1,Controls!$B$21*(Controls!$B$101+Controls!$B$104),0) -> 0 | M14: =J14+K14-L14 -> 0 | N14: =W14+X14 -> 4459.6892 | O14: =0 -> 0 | P14: =IF(A14<=Controls!$B$109,0,N14+O14) -> 4459.6892 | Q14: =H14+G14+M14-P14 -> 99046.537 | R14: =T13 -> 482022.09 | S14: =IF(A14<=Controls!$B$109,N14,0) -> 0 | T14: =Y14+Z14 -> 482022.09 | U14: =MIN(I14-J14,MAX(Controls!$B$101-SUM($U$2:U13),0)) -> 0 | V14: =MIN(I14-J14-U14,MAX(Controls!$B$104-SUM($V$2:V13),0)) -> 0 | W14: =(Y13+U14/2)*Controls!$B$102/12 -> 2048.6797 | X14: =IF(AND(Controls!$B$107=1,A14>=Controls!$B$108),0,(Z13+V14/2)*Controls!$B$105/12) -> 2411.0095 | Y14: =Y13+U14+IF(A14<=Controls!$B$109,W14,0) -> 245841.56 | Z14: =IF(AND(Controls!$B$107=1,A14>=Controls!$B$108),0,Z13+V14+IF(A14<=Controls!$B$109,X14,0)) -> 236180.53 | AA14: =IF(SUM($P$3:P14)=0,"",SUM($E$3:E14)/SUM($P$3:P14)) -> 3.5745066 | AB14: =IF(A14=Controls!$B$103,"◀ Antalpha bullet due: R"&TEXT(Y14,"#,##0")&"k - refinance/convert",IF(AND(Controls!$B$107=1,A14>=Controls!$B$108)*( A14=Controls!$B$108 ),"◀ DMTN converts to equity","")) | AC14: =G14+IF(A14=36,Controls!$B$113,0) -> 10342.803 | AD14: =-J14+IF(A14=36,Q14+Controls!$B$113-T14,0) -> 0
A15: 14 | B15: =Monthly_Deployment!C15 -> Aug-27 | C15: =Revenue_36M!P15 -> 22824.564 | D15: =Opex_36M!P15 -> 12687.097 | E15: =C15-D15 -> 10137.467 | F15: =Capex_36M!O15 -> 0 | G15: =E15-F15 -> 10137.467 | H15: =Q14 -> 99046.537 | I15: =MAX(Controls!$B$22+Controls!$B$111-(H15+G15),0)+IF(A15=1,Controls!$B$21*(Controls!$B$101+Controls!$B$104),0) -> 0 | J15: =MIN(I15,MAX(Controls!$B$100-SUM($J$2:J14),0)) -> 0 | K15: =U15+V15 -> 0 | L15: =IF(A15=1,Controls!$B$21*(Controls!$B$101+Controls!$B$104),0) -> 0 | M15: =J15+K15-L15 -> 0 | N15: =W15+X15 -> 4459.6892 | O15: =0 -> 0 | P15: =IF(A15<=Controls!$B$109,0,N15+O15) -> 4459.6892 | Q15: =H15+G15+M15-P15 -> 104724.31 | R15: =T14 -> 482022.09 | S15: =IF(A15<=Controls!$B$109,N15,0) -> 0 | T15: =Y15+Z15 -> 482022.09 | U15: =MIN(I15-J15,MAX(Controls!$B$101-SUM($U$2:U14),0)) -> 0 | V15: =MIN(I15-J15-U15,MAX(Controls!$B$104-SUM($V$2:V14),0)) -> 0 | W15: =(Y14+U15/2)*Controls!$B$102/12 -> 2048.6797 | X15: =IF(AND(Controls!$B$107=1,A15>=Controls!$B$108),0,(Z14+V15/2)*Controls!$B$105/12) -> 2411.0095 | Y15: =Y14+U15+IF(A15<=Controls!$B$109,W15,0) -> 245841.56 | Z15: =IF(AND(Controls!$B$107=1,A15>=Controls!$B$108),0,Z14+V15+IF(A15<=Controls!$B$109,X15,0)) -> 236180.53 | AA15: =IF(SUM($P$4:P15)=0,"",SUM($E$4:E15)/SUM($P$4:P15)) -> 3.4011255 | AB15: =IF(A15=Controls!$B$103,"◀ Antalpha bullet due: R"&TEXT(Y15,"#,##0")&"k - refinance/convert",IF(AND(Controls!$B$107=1,A15>=Controls!$B$108)*( A15=Controls!$B$108 ),"◀ DMTN converts to equity","")) | AC15: =G15+IF(A15=36,Controls!$B$113,0) -> 10137.467 | AD15: =-J15+IF(A15=36,Q15+Controls!$B$113-T15,0) -> 0
A16: 15 | B16: =Monthly_Deployment!C16 -> Sept-27 | C16: =Revenue_36M!P16 -> 21891.244 | D16: =Opex_36M!P16 -> 12353.017 | E16: =C16-D16 -> 9538.2269 | F16: =Capex_36M!O16 -> 0 | G16: =E16-F16 -> 9538.2269 | H16: =Q15 -> 104724.31 | I16: =MAX(Controls!$B$22+Controls!$B$111-(H16+G16),0)+IF(A16=1,Controls!$B$21*(Controls!$B$101+Controls!$B$104),0) -> 0 | J16: =MIN(I16,MAX(Controls!$B$100-SUM($J$2:J15),0)) -> 0 | K16: =U16+V16 -> 0 | L16: =IF(A16=1,Controls!$B$21*(Controls!$B$101+Controls!$B$104),0) -> 0 | M16: =J16+K16-L16 -> 0 | N16: =W16+X16 -> 4459.6892 | O16: =0 -> 0 | P16: =IF(A16<=Controls!$B$109,0,N16+O16) -> 4459.6892 | Q16: =H16+G16+M16-P16 -> 109802.85 | R16: =T15 -> 482022.09 | S16: =IF(A16<=Controls!$B$109,N16,0) -> 0 | T16: =Y16+Z16 -> 482022.09 | U16: =MIN(I16-J16,MAX(Controls!$B$101-SUM($U$2:U15),0)) -> 0 | V16: =MIN(I16-J16-U16,MAX(Controls!$B$104-SUM($V$2:V15),0)) -> 0 | W16: =(Y15+U16/2)*Controls!$B$102/12 -> 2048.6797 | X16: =IF(AND(Controls!$B$107=1,A16>=Controls!$B$108),0,(Z15+V16/2)*Controls!$B$105/12) -> 2411.0095 | Y16: =Y15+U16+IF(A16<=Controls!$B$109,W16,0) -> 245841.56 | Z16: =IF(AND(Controls!$B$107=1,A16>=Controls!$B$108),0,Z15+V16+IF(A16<=Controls!$B$109,X16,0)) -> 236180.53 | AA16: =IF(SUM($P$5:P16)=0,"",SUM($E$5:E16)/SUM($P$5:P16)) -> 3.1670477 | AB16: =IF(A16=Controls!$B$103,"◀ Antalpha bullet due: R"&TEXT(Y16,"#,##0")&"k - refinance/convert",IF(AND(Controls!$B$107=1,A16>=Controls!$B$108)*( A16=Controls!$B$108 ),"◀ DMTN converts to equity","")) | AC16: =G16+IF(A16=36,Controls!$B$113,0) -> 9538.2269 | AD16: =-J16+IF(A16=36,Q16+Controls!$B$113-T16,0) -> 0
A17: 16 | B17: =Monthly_Deployment!C17 -> Oct-27 | C17: =Revenue_36M!P17 -> 22419.051 | D17: =Opex_36M!P17 -> 12687.097 | E17: =C17-D17 -> 9731.9543 | F17: =Capex_36M!O17 -> 0 | G17: =E17-F17 -> 9731.9543 | H17: =Q16 -> 109802.85 | I17: =MAX(Controls!$B$22+Controls!$B$111-(H17+G17),0)+IF(A17=1,Controls!$B$21*(Controls!$B$101+Controls!$B$104),0) -> 0 | J17: =MIN(I17,MAX(Controls!$B$100-SUM($J$2:J16),0)) -> 0 | K17: =U17+V17 -> 0 | L17: =IF(A17=1,Controls!$B$21*(Controls!$B$101+Controls!$B$104),0) -> 0 | M17: =J17+K17-L17 -> 0 | N17: =W17+X17 -> 4459.6892 | O17: =0 -> 0 | P17: =IF(A17<=Controls!$B$109,0,N17+O17) -> 4459.6892 | Q17: =H17+G17+M17-P17 -> 115075.12 | R17: =T16 -> 482022.09 | S17: =IF(A17<=Controls!$B$109,N17,0) -> 0 | T17: =Y17+Z17 -> 482022.09 | U17: =MIN(I17-J17,MAX(Controls!$B$101-SUM($U$2:U16),0)) -> 0 | V17: =MIN(I17-J17-U17,MAX(Controls!$B$104-SUM($V$2:V16),0)) -> 0 | W17: =(Y16+U17/2)*Controls!$B$102/12 -> 2048.6797 | X17: =IF(AND(Controls!$B$107=1,A17>=Controls!$B$108),0,(Z16+V17/2)*Controls!$B$105/12) -> 2411.0095 | Y17: =Y16+U17+IF(A17<=Controls!$B$109,W17,0) -> 245841.56 | Z17: =IF(AND(Controls!$B$107=1,A17>=Controls!$B$108),0,Z16+V17+IF(A17<=Controls!$B$109,X17,0)) -> 236180.53 | AA17: =IF(SUM($P$6:P17)=0,"",SUM($E$6:E17)/SUM($P$6:P17)) -> 2.8580357 | AB17: =IF(A17=Controls!$B$103,"◀ Antalpha bullet due: R"&TEXT(Y17,"#,##0")&"k - refinance/convert",IF(AND(Controls!$B$107=1,A17>=Controls!$B$108)*( A17=Controls!$B$108 ),"◀ DMTN converts to equity","")) | AC17: =G17+IF(A17=36,Controls!$B$113,0) -> 9731.9543 | AD17: =-J17+IF(A17=36,Q17+Controls!$B$113-T17,0) -> 0
A18: 17 | B18: =Monthly_Deployment!C18 -> Nov-27 | C18: =Revenue_36M!P18 -> 21502.112 | D18: =Opex_36M!P18 -> 12353.017 | E18: =C18-D18 -> 9149.095 | F18: =Capex_36M!O18 -> 0 | G18: =E18-F18 -> 9149.095 | H18: =Q17 -> 115075.12 | I18: =MAX(Controls!$B$22+Controls!$B$111-(H18+G18),0)+IF(A18=1,Controls!$B$21*(Controls!$B$101+Controls!$B$104),0) -> 0 | J18: =MIN(I18,MAX(Controls!$B$100-SUM($J$2:J17),0)) -> 0 | K18: =U18+V18 -> 0 | L18: =IF(A18=1,Controls!$B$21*(Controls!$B$101+Controls!$B$104),0) -> 0 | M18: =J18+K18-L18 -> 0 | N18: =W18+X18 -> 4459.6892 | O18: =0 -> 0 | P18: =IF(A18<=Controls!$B$109,0,N18+O18) -> 4459.6892 | Q18: =H18+G18+M18-P18 -> 119764.52 | R18: =T17 -> 482022.09 | S18: =IF(A18<=Controls!$B$109,N18,0) -> 0 | T18: =Y18+Z18 -> 482022.09 | U18: =MIN(I18-J18,MAX(Controls!$B$101-SUM($U$2:U17),0)) -> 0 | V18: =MIN(I18-J18-U18,MAX(Controls!$B$104-SUM($V$2:V17),0)) -> 0 | W18: =(Y17+U18/2)*Controls!$B$102/12 -> 2048.6797 | X18: =IF(AND(Controls!$B$107=1,A18>=Controls!$B$108),0,(Z17+V18/2)*Controls!$B$105/12) -> 2411.0095 | Y18: =Y17+U18+IF(A18<=Controls!$B$109,W18,0) -> 245841.56 | Z18: =IF(AND(Controls!$B$107=1,A18>=Controls!$B$108),0,Z17+V18+IF(A18<=Controls!$B$109,X18,0)) -> 236180.53 | AA18: =IF(SUM($P$7:P18)=0,"",SUM($E$7:E18)/SUM($P$7:P18)) -> 2.5485533 | AB18: =IF(A18=Controls!$B$103,"◀ Antalpha bullet due: R"&TEXT(Y18,"#,##0")&"k - refinance/convert",IF(AND(Controls!$B$107=1,A18>=Controls!$B$108)*( A18=Controls!$B$108 ),"◀ DMTN converts to equity","")) | AC18: =G18+IF(A18=36,Controls!$B$113,0) -> 9149.095 | AD18: =-J18+IF(A18=36,Q18+Controls!$B$113-T18,0) -> 0
A19: 18 | B19: =Monthly_Deployment!C19 -> Dec-27 | C19: =Revenue_36M!P19 -> 22020.332 | D19: =Opex_36M!P19 -> 12687.097 | E19: =C19-D19 -> 9333.2353 | F19: =Capex_36M!O19 -> 0 | G19: =E19-F19 -> 9333.2353 | H19: =Q18 -> 119764.52 | I19: =MAX(Controls!$B$22+Controls!$B$111-(H19+G19),0)+IF(A19=1,Controls!$B$21*(Controls!$B$101+Controls!$B$104),0) -> 0 | J19: =MIN(I19,MAX(Controls!$B$100-SUM($J$2:J18),0)) -> 0 | K19: =U19+V19 -> 0 | L19: =IF(A19=1,Controls!$B$21*(Controls!$B$101+Controls!$B$104),0) -> 0 | M19: =J19+K19-L19 -> 0 | N19: =W19+X19 -> 4459.6892 | O19: =0 -> 0 | P19: =IF(A19<=Controls!$B$109,0,N19+O19) -> 4459.6892 | Q19: =H19+G19+M19-P19 -> 124638.07 | R19: =T18 -> 482022.09 | S19: =IF(A19<=Controls!$B$109,N19,0) -> 0 | T19: =Y19+Z19 -> 482022.09 | U19: =MIN(I19-J19,MAX(Controls!$B$101-SUM($U$2:U18),0)) -> 0 | V19: =MIN(I19-J19-U19,MAX(Controls!$B$104-SUM($V$2:V18),0)) -> 0 | W19: =(Y18+U19/2)*Controls!$B$102/12 -> 2048.6797 | X19: =IF(AND(Controls!$B$107=1,A19>=Controls!$B$108),0,(Z18+V19/2)*Controls!$B$105/12) -> 2411.0095 | Y19: =Y18+U19+IF(A19<=Controls!$B$109,W19,0) -> 245841.56 | Z19: =IF(AND(Controls!$B$107=1,A19>=Controls!$B$108),0,Z18+V19+IF(A19<=Controls!$B$109,X19,0)) -> 236180.53 | AA19: =IF(SUM($P$8:P19)=0,"",SUM($E$8:E19)/SUM($P$8:P19)) -> 2.2895279 | AB19: =IF(A19=Controls!$B$103,"◀ Antalpha bullet due: R"&TEXT(Y19,"#,##0")&"k - refinance/convert",IF(AND(Controls!$B$107=1,A19>=Controls!$B$108)*( A19=Controls!$B$108 ),"◀ DMTN converts to equity","")) | AC19: =G19+IF(A19=36,Controls!$B$113,0) -> 9333.2353 | AD19: =-J19+IF(A19=36,Q19+Controls!$B$113-T19,0) -> 0
A20: 19 | B20: =Monthly_Deployment!C20 -> Jan-28 | C20: =Revenue_36M!P20 -> 21823.488 | D20: =Opex_36M!P20 -> 7508.8567 | E20: =C20-D20 -> 14314.631 | F20: =Capex_36M!O20 -> 0 | G20: =E20-F20 -> 14314.631 | H20: =Q19 -> 124638.07 | I20: =MAX(Controls!$B$22+Controls!$B$111-(H20+G20),0)+IF(A20=1,Controls!$B$21*(Controls!$B$101+Controls!$B$104),0) -> 0 | J20: =MIN(I20,MAX(Controls!$B$100-SUM($J$2:J19),0)) -> 0 | K20: =U20+V20 -> 0 | L20: =IF(A20=1,Controls!$B$21*(Controls!$B$101+Controls!$B$104),0) -> 0 | M20: =J20+K20-L20 -> 0 | N20: =W20+X20 -> 4459.6892 | O20: =0 -> 0 | P20: =IF(A20<=Controls!$B$109,0,N20+O20) -> 4459.6892 | Q20: =H20+G20+M20-P20 -> 134493.01 | R20: =T19 -> 482022.09 | S20: =IF(A20<=Controls!$B$109,N20,0) -> 0 | T20: =Y20+Z20 -> 482022.09 | U20: =MIN(I20-J20,MAX(Controls!$B$101-SUM($U$2:U19),0)) -> 0 | V20: =MIN(I20-J20-U20,MAX(Controls!$B$104-SUM($V$2:V19),0)) -> 0 | W20: =(Y19+U20/2)*Controls!$B$102/12 -> 2048.6797 | X20: =IF(AND(Controls!$B$107=1,A20>=Controls!$B$108),0,(Z19+V20/2)*Controls!$B$105/12) -> 2411.0095 | Y20: =Y19+U20+IF(A20<=Controls!$B$109,W20,0) -> 245841.56 | Z20: =IF(AND(Controls!$B$107=1,A20>=Controls!$B$108),0,Z19+V20+IF(A20<=Controls!$B$109,X20,0)) -> 236180.53 | AA20: =IF(SUM($P$9:P20)=0,"",SUM($E$9:E20)/SUM($P$9:P20)) -> 2.3400333 | AB20: =IF(A20=Controls!$B$103,"◀ Antalpha bullet due: R"&TEXT(Y20,"#,##0")&"k - refinance/convert",IF(AND(Controls!$B$107=1,A20>=Controls!$B$108)*( A20=Controls!$B$108 ),"◀ DMTN converts to equity","")) | AC20: =G20+IF(A20=36,Controls!$B$113,0) -> 14314.631 | AD20: =-J20+IF(A20=36,Q20+Controls!$B$113-T20,0) -> 0
A21: 20 | B21: =Monthly_Deployment!C21 -> Feb-28 | C21: =Revenue_36M!P21 -> 20232.93 | D21: =Opex_36M!P21 -> 7174.7767 | E21: =C21-D21 -> 13058.153 | F21: =Capex_36M!O21 -> 0 | G21: =E21-F21 -> 13058.153 | H21: =Q20 -> 134493.01 | I21: =MAX(Controls!$B$22+Controls!$B$111-(H21+G21),0)+IF(A21=1,Controls!$B$21*(Controls!$B$101+Controls!$B$104),0) -> 0 | J21: =MIN(I21,MAX(Controls!$B$100-SUM($J$2:J20),0)) -> 0 | K21: =U21+V21 -> 0 | L21: =IF(A21=1,Controls!$B$21*(Controls!$B$101+Controls!$B$104),0) -> 0 | M21: =J21+K21-L21 -> 0 | N21: =W21+X21 -> 4459.6892 | O21: =0 -> 0 | P21: =IF(A21<=Controls!$B$109,0,N21+O21) -> 4459.6892 | Q21: =H21+G21+M21-P21 -> 143091.48 | R21: =T20 -> 482022.09 | S21: =IF(A21<=Controls!$B$109,N21,0) -> 0 | T21: =Y21+Z21 -> 482022.09 | U21: =MIN(I21-J21,MAX(Controls!$B$101-SUM($U$2:U20),0)) -> 0 | V21: =MIN(I21-J21-U21,MAX(Controls!$B$104-SUM($V$2:V20),0)) -> 0 | W21: =(Y20+U21/2)*Controls!$B$102/12 -> 2048.6797 | X21: =IF(AND(Controls!$B$107=1,A21>=Controls!$B$108),0,(Z20+V21/2)*Controls!$B$105/12) -> 2411.0095 | Y21: =Y20+U21+IF(A21<=Controls!$B$109,W21,0) -> 245841.56 | Z21: =IF(AND(Controls!$B$107=1,A21>=Controls!$B$108),0,Z20+V21+IF(A21<=Controls!$B$109,X21,0)) -> 236180.53 | AA21: =IF(SUM($P$10:P21)=0,"",SUM($E$10:E21)/SUM($P$10:P21)) -> 2.3959174 | AB21: =IF(A21=Controls!$B$103,"◀ Antalpha bullet due: R"&TEXT(Y21,"#,##0")&"k - refinance/convert",IF(AND(Controls!$B$107=1,A21>=Controls!$B$108)*( A21=Controls!$B$108 ),"◀ DMTN converts to equity","")) | AC21: =G21+IF(A21=36,Controls!$B$113,0) -> 13058.153 | AD21: =-J21+IF(A21=36,Q21+Controls!$B$113-T21,0) -> 0
A22: 21 | B22: =Monthly_Deployment!C22 -> Mar-28 | C22: =Revenue_36M!P22 -> 21434.767 | D22: =Opex_36M!P22 -> 7508.8567 | E22: =C22-D22 -> 13925.911 | F22: =Capex_36M!O22 -> 0 | G22: =E22-F22 -> 13925.911 | H22: =Q21 -> 143091.48 | I22: =MAX(Controls!$B$22+Controls!$B$111-(H22+G22),0)+IF(A22=1,Controls!$B$21*(Controls!$B$101+Controls!$B$104),0) -> 0 | J22: =MIN(I22,MAX(Controls!$B$100-SUM($J$2:J21),0)) -> 0 | K22: =U22+V22 -> 0 | L22: =IF(A22=1,Controls!$B$21*(Controls!$B$101+Controls!$B$104),0) -> 0 | M22: =J22+K22-L22 -> 0 | N22: =W22+X22 -> 4459.6892 | O22: =0 -> 0 | P22: =IF(A22<=Controls!$B$109,0,N22+O22) -> 4459.6892 | Q22: =H22+G22+M22-P22 -> 152557.7 | R22: =T21 -> 482022.09 | S22: =IF(A22<=Controls!$B$109,N22,0) -> 0 | T22: =Y22+Z22 -> 482022.09 | U22: =MIN(I22-J22,MAX(Controls!$B$101-SUM($U$2:U21),0)) -> 0 | V22: =MIN(I22-J22-U22,MAX(Controls!$B$104-SUM($V$2:V21),0)) -> 0 | W22: =(Y21+U22/2)*Controls!$B$102/12 -> 2048.6797 | X22: =IF(AND(Controls!$B$107=1,A22>=Controls!$B$108),0,(Z21+V22/2)*Controls!$B$105/12) -> 2411.0095 | Y22: =Y21+U22+IF(A22<=Controls!$B$109,W22,0) -> 245841.56 | Z22: =IF(AND(Controls!$B$107=1,A22>=Controls!$B$108),0,Z21+V22+IF(A22<=Controls!$B$109,X22,0)) -> 236180.53 | AA22: =IF(SUM($P$11:P22)=0,"",SUM($E$11:E22)/SUM($P$11:P22)) -> 2.4471963 | AB22: =IF(A22=Controls!$B$103,"◀ Antalpha bullet due: R"&TEXT(Y22,"#,##0")&"k - refinance/convert",IF(AND(Controls!$B$107=1,A22>=Controls!$B$108)*( A22=Controls!$B$108 ),"◀ DMTN converts to equity","")) | AC22: =G22+IF(A22=36,Controls!$B$113,0) -> 13925.911 | AD22: =-J22+IF(A22=36,Q22+Controls!$B$113-T22,0) -> 0
A23: 22 | B23: =Monthly_Deployment!C23 -> Apr-28 | C23: =Revenue_36M!P23 -> 20557.612 | D23: =Opex_36M!P23 -> 7341.8167 | E23: =C23-D23 -> 13215.795 | F23: =Capex_36M!O23 -> 0 | G23: =E23-F23 -> 13215.795 | H23: =Q22 -> 152557.7 | I23: =MAX(Controls!$B$22+Controls!$B$111-(H23+G23),0)+IF(A23=1,Controls!$B$21*(Controls!$B$101+Controls!$B$104),0) -> 0 | J23: =MIN(I23,MAX(Controls!$B$100-SUM($J$2:J22),0)) -> 0 | K23: =U23+V23 -> 0 | L23: =IF(A23=1,Controls!$B$21*(Controls!$B$101+Controls!$B$104),0) -> 0 | M23: =J23+K23-L23 -> 0 | N23: =W23+X23 -> 4459.6892 | O23: =0 -> 0 | P23: =IF(A23<=Controls!$B$109,0,N23+O23) -> 4459.6892 | Q23: =H23+G23+M23-P23 -> 161313.8 | R23: =T22 -> 482022.09 | S23: =IF(A23<=Controls!$B$109,N23,0) -> 0 | T23: =Y23+Z23 -> 482022.09 | U23: =MIN(I23-J23,MAX(Controls!$B$101-SUM($U$2:U22),0)) -> 0 | V23: =MIN(I23-J23-U23,MAX(Controls!$B$104-SUM($V$2:V22),0)) -> 0 | W23: =(Y22+U23/2)*Controls!$B$102/12 -> 2048.6797 | X23: =IF(AND(Controls!$B$107=1,A23>=Controls!$B$108),0,(Z22+V23/2)*Controls!$B$105/12) -> 2411.0095 | Y23: =Y22+U23+IF(A23<=Controls!$B$109,W23,0) -> 245841.56 | Z23: =IF(AND(Controls!$B$107=1,A23>=Controls!$B$108),0,Z22+V23+IF(A23<=Controls!$B$109,X23,0)) -> 236180.53 | AA23: =IF(SUM($P$12:P23)=0,"",SUM($E$12:E23)/SUM($P$12:P23)) -> 2.497191 | AB23: =IF(A23=Controls!$B$103,"◀ Antalpha bullet due: R"&TEXT(Y23,"#,##0")&"k - refinance/convert",IF(AND(Controls!$B$107=1,A23>=Controls!$B$108)*( A23=Controls!$B$108 ),"◀ DMTN converts to equity","")) | AC23: =G23+IF(A23=36,Controls!$B$113,0) -> 13215.795 | AD23: =-J23+IF(A23=36,Q23+Controls!$B$113-T23,0) -> 0
A24: 23 | B24: =Monthly_Deployment!C24 -> May-28 | C24: =Revenue_36M!P24 -> 10526.293 | D24: =Opex_36M!P24 -> 7508.8567 | E24: =C24-D24 -> 3017.4365 | F24: =Capex_36M!O24 -> 0 | G24: =E24-F24 -> 3017.4365 | H24: =Q23 -> 161313.8 | I24: =MAX(Controls!$B$22+Controls!$B$111-(H24+G24),0)+IF(A24=1,Controls!$B$21*(Controls!$B$101+Controls!$B$104),0) -> 0 | J24: =MIN(I24,MAX(Controls!$B$100-SUM($J$2:J23),0)) -> 0 | K24: =U24+V24 -> 0 | L24: =IF(A24=1,Controls!$B$21*(Controls!$B$101+Controls!$B$104),0) -> 0 | M24: =J24+K24-L24 -> 0 | N24: =W24+X24 -> 4459.6892 | O24: =0 -> 0 | P24: =IF(A24<=Controls!$B$109,0,N24+O24) -> 4459.6892 | Q24: =H24+G24+M24-P24 -> 159871.55 | R24: =T23 -> 482022.09 | S24: =IF(A24<=Controls!$B$109,N24,0) -> 0 | T24: =Y24+Z24 -> 482022.09 | U24: =MIN(I24-J24,MAX(Controls!$B$101-SUM($U$2:U23),0)) -> 0 | V24: =MIN(I24-J24-U24,MAX(Controls!$B$104-SUM($V$2:V23),0)) -> 0 | W24: =(Y23+U24/2)*Controls!$B$102/12 -> 2048.6797 | X24: =IF(AND(Controls!$B$107=1,A24>=Controls!$B$108),0,(Z23+V24/2)*Controls!$B$105/12) -> 2411.0095 | Y24: =Y23+U24+IF(A24<=Controls!$B$109,W24,0) -> 245841.56 | Z24: =IF(AND(Controls!$B$107=1,A24>=Controls!$B$108),0,Z23+V24+IF(A24<=Controls!$B$109,X24,0)) -> 236180.53 | AA24: =IF(SUM($P$13:P24)=0,"",SUM($E$13:E24)/SUM($P$13:P24)) -> 2.3525385 | AB24: =IF(A24=Controls!$B$103,"◀ Antalpha bullet due: R"&TEXT(Y24,"#,##0")&"k - refinance/convert",IF(AND(Controls!$B$107=1,A24>=Controls!$B$108)*( A24=Controls!$B$108 ),"◀ DMTN converts to equity","")) | AC24: =G24+IF(A24=36,Controls!$B$113,0) -> 3017.4365 | AD24: =-J24+IF(A24=36,Q24+Controls!$B$113-T24,0) -> 0
A25: 24 | B25: =Monthly_Deployment!C25 -> Jun-28 | C25: =Revenue_36M!P25 -> 10095.444 | D25: =Opex_36M!P25 -> 7341.8167 | E25: =C25-D25 -> 2753.627 | F25: =Capex_36M!O25 -> 0 | G25: =E25-F25 -> 2753.627 | H25: =Q24 -> 159871.55 | I25: =MAX(Controls!$B$22+Controls!$B$111-(H25+G25),0)+IF(A25=1,Controls!$B$21*(Controls!$B$101+Controls!$B$104),0) -> 0 | J25: =MIN(I25,MAX(Controls!$B$100-SUM($J$2:J24),0)) -> 0 | K25: =U25+V25 -> 0 | L25: =IF(A25=1,Controls!$B$21*(Controls!$B$101+Controls!$B$104),0) -> 0 | M25: =J25+K25-L25 -> 0 | N25: =W25+X25 -> 4459.6892 | O25: =0 -> 0 | P25: =IF(A25<=Controls!$B$109,0,N25+O25) -> 4459.6892 | Q25: =H25+G25+M25-P25 -> 158165.49 | R25: =T24 -> 482022.09 | S25: =IF(A25<=Controls!$B$109,N25,0) -> 0 | T25: =Y25+Z25 -> 482022.09 | U25: =MIN(I25-J25,MAX(Controls!$B$101-SUM($U$2:U24),0)) -> 0 | V25: =MIN(I25-J25-U25,MAX(Controls!$B$104-SUM($V$2:V24),0)) -> 0 | W25: =(Y24+U25/2)*Controls!$B$102/12 -> 2048.6797 | X25: =IF(AND(Controls!$B$107=1,A25>=Controls!$B$108),0,(Z24+V25/2)*Controls!$B$105/12) -> 2411.0095 | Y25: =Y24+U25+IF(A25<=Controls!$B$109,W25,0) -> 245841.56 | Z25: =IF(AND(Controls!$B$107=1,A25>=Controls!$B$108),0,Z24+V25+IF(A25<=Controls!$B$109,X25,0)) -> 236180.53 | AA25: =IF(SUM($P$14:P25)=0,"",SUM($E$14:E25)/SUM($P$14:P25)) -> 2.2146225 | AB25: =IF(A25=Controls!$B$103,"◀ Antalpha bullet due: R"&TEXT(Y25,"#,##0")&"k - refinance/convert",IF(AND(Controls!$B$107=1,A25>=Controls!$B$108)*( A25=Controls!$B$108 ),"◀ DMTN converts to equity","")) -> ◀ Antalpha bullet due: R245,842k - refinance/convert | AC25: =G25+IF(A25=36,Controls!$B$113,0) -> 2753.627 | AD25: =-J25+IF(A25=36,Q25+Controls!$B$113-T25,0) -> 0
A26: 25 | B26: =Monthly_Deployment!C26 -> Jul-28 | C26: =Revenue_36M!P26 -> 10338.423 | D26: =Opex_36M!P26 -> 7508.8567 | E26: =C26-D26 -> 2829.5658 | F26: =Capex_36M!O26 -> 0 | G26: =E26-F26 -> 2829.5658 | H26: =Q25 -> 158165.49 | I26: =MAX(Controls!$B$22+Controls!$B$111-(H26+G26),0)+IF(A26=1,Controls!$B$21*(Controls!$B$101+Controls!$B$104),0) -> 0 | J26: =MIN(I26,MAX(Controls!$B$100-SUM($J$2:J25),0)) -> 0 | K26: =U26+V26 -> 0 | L26: =IF(A26=1,Controls!$B$21*(Controls!$B$101+Controls!$B$104),0) -> 0 | M26: =J26+K26-L26 -> 0 | N26: =W26+X26 -> 4459.6892 | O26: =0 -> 0 | P26: =IF(A26<=Controls!$B$109,0,N26+O26) -> 4459.6892 | Q26: =H26+G26+M26-P26 -> 156535.36 | R26: =T25 -> 482022.09 | S26: =IF(A26<=Controls!$B$109,N26,0) -> 0 | T26: =Y26+Z26 -> 482022.09 | U26: =MIN(I26-J26,MAX(Controls!$B$101-SUM($U$2:U25),0)) -> 0 | V26: =MIN(I26-J26-U26,MAX(Controls!$B$104-SUM($V$2:V25),0)) -> 0 | W26: =(Y25+U26/2)*Controls!$B$102/12 -> 2048.6797 | X26: =IF(AND(Controls!$B$107=1,A26>=Controls!$B$108),0,(Z25+V26/2)*Controls!$B$105/12) -> 2411.0095 | Y26: =Y25+U26+IF(A26<=Controls!$B$109,W26,0) -> 245841.56 | Z26: =IF(AND(Controls!$B$107=1,A26>=Controls!$B$108),0,Z25+V26+IF(A26<=Controls!$B$109,X26,0)) -> 236180.53 | AA26: =IF(SUM($P$15:P26)=0,"",SUM($E$15:E26)/SUM($P$15:P26)) -> 2.0742308 | AB26: =IF(A26=Controls!$B$103,"◀ Antalpha bullet due: R"&TEXT(Y26,"#,##0")&"k - refinance/convert",IF(AND(Controls!$B$107=1,A26>=Controls!$B$108)*( A26=Controls!$B$108 ),"◀ DMTN converts to equity","")) | AC26: =G26+IF(A26=36,Controls!$B$113,0) -> 2829.5658 | AD26: =-J26+IF(A26=36,Q26+Controls!$B$113-T26,0) -> 0
A27: 26 | B27: =Monthly_Deployment!C27 -> Aug-28 | C27: =Revenue_36M!P27 -> 10245.679 | D27: =Opex_36M!P27 -> 7508.8567 | E27: =C27-D27 -> 2736.8226 | F27: =Capex_36M!O27 -> 0 | G27: =E27-F27 -> 2736.8226 | H27: =Q26 -> 156535.36 | I27: =MAX(Controls!$B$22+Controls!$B$111-(H27+G27),0)+IF(A27=1,Controls!$B$21*(Controls!$B$101+Controls!$B$104),0) -> 0 | J27: =MIN(I27,MAX(Controls!$B$100-SUM($J$2:J26),0)) -> 0 | K27: =U27+V27 -> 0 | L27: =IF(A27=1,Controls!$B$21*(Controls!$B$101+Controls!$B$104),0) -> 0 | M27: =J27+K27-L27 -> 0 | N27: =W27+X27 -> 4459.6892 | O27: =0 -> 0 | P27: =IF(A27<=Controls!$B$109,0,N27+O27) -> 4459.6892 | Q27: =H27+G27+M27-P27 -> 154812.5 | R27: =T26 -> 482022.09 | S27: =IF(A27<=Controls!$B$109,N27,0) -> 0 | T27: =Y27+Z27 -> 482022.09 | U27: =MIN(I27-J27,MAX(Controls!$B$101-SUM($U$2:U26),0)) -> 0 | V27: =MIN(I27-J27-U27,MAX(Controls!$B$104-SUM($V$2:V26),0)) -> 0 | W27: =(Y26+U27/2)*Controls!$B$102/12 -> 2048.6797 | X27: =IF(AND(Controls!$B$107=1,A27>=Controls!$B$108),0,(Z26+V27/2)*Controls!$B$105/12) -> 2411.0095 | Y27: =Y26+U27+IF(A27<=Controls!$B$109,W27,0) -> 245841.56 | Z27: =IF(AND(Controls!$B$107=1,A27>=Controls!$B$108),0,Z26+V27+IF(A27<=Controls!$B$109,X27,0)) -> 236180.53 | AA27: =IF(SUM($P$16:P27)=0,"",SUM($E$16:E27)/SUM($P$16:P27)) -> 1.9359431 | AB27: =IF(A27=Controls!$B$103,"◀ Antalpha bullet due: R"&TEXT(Y27,"#,##0")&"k - refinance/convert",IF(AND(Controls!$B$107=1,A27>=Controls!$B$108)*( A27=Controls!$B$108 ),"◀ DMTN converts to equity","")) | AC27: =G27+IF(A27=36,Controls!$B$113,0) -> 2736.8226 | AD27: =-J27+IF(A27=36,Q27+Controls!$B$113-T27,0) -> 0
A28: 27 | B28: =Monthly_Deployment!C28 -> Sept-28 | C28: =Revenue_36M!P28 -> 9826.1832 | D28: =Opex_36M!P28 -> 7341.8167 | E28: =C28-D28 -> 2484.3665 | F28: =Capex_36M!O28 -> 0 | G28: =E28-F28 -> 2484.3665 | H28: =Q27 -> 154812.5 | I28: =MAX(Controls!$B$22+Controls!$B$111-(H28+G28),0)+IF(A28=1,Controls!$B$21*(Controls!$B$101+Controls!$B$104),0) -> 0 | J28: =MIN(I28,MAX(Controls!$B$100-SUM($J$2:J27),0)) -> 0 | K28: =U28+V28 -> 0 | L28: =IF(A28=1,Controls!$B$21*(Controls!$B$101+Controls!$B$104),0) -> 0 | M28: =J28+K28-L28 -> 0 | N28: =W28+X28 -> 4459.6892 | O28: =0 -> 0 | P28: =IF(A28<=Controls!$B$109,0,N28+O28) -> 4459.6892 | Q28: =H28+G28+M28-P28 -> 152837.18 | R28: =T27 -> 482022.09 | S28: =IF(A28<=Controls!$B$109,N28,0) -> 0 | T28: =Y28+Z28 -> 482022.09 | U28: =MIN(I28-J28,MAX(Controls!$B$101-SUM($U$2:U27),0)) -> 0 | V28: =MIN(I28-J28-U28,MAX(Controls!$B$104-SUM($V$2:V27),0)) -> 0 | W28: =(Y27+U28/2)*Controls!$B$102/12 -> 2048.6797 | X28: =IF(AND(Controls!$B$107=1,A28>=Controls!$B$108),0,(Z27+V28/2)*Controls!$B$105/12) -> 2411.0095 | Y28: =Y27+U28+IF(A28<=Controls!$B$109,W28,0) -> 245841.56 | Z28: =IF(AND(Controls!$B$107=1,A28>=Controls!$B$108),0,Z27+V28+IF(A28<=Controls!$B$109,X28,0)) -> 236180.53 | AA28: =IF(SUM($P$17:P28)=0,"",SUM($E$17:E28)/SUM($P$17:P28)) -> 1.8041353 | AB28: =IF(A28=Controls!$B$103,"◀ Antalpha bullet due: R"&TEXT(Y28,"#,##0")&"k - refinance/convert",IF(AND(Controls!$B$107=1,A28>=Controls!$B$108)*( A28=Controls!$B$108 ),"◀ DMTN converts to equity","")) | AC28: =G28+IF(A28=36,Controls!$B$113,0) -> 2484.3665 | AD28: =-J28+IF(A28=36,Q28+Controls!$B$113-T28,0) -> 0
A29: 28 | B29: =Monthly_Deployment!C29 -> Oct-28 | C29: =Revenue_36M!P29 -> 10062.547 | D29: =Opex_36M!P29 -> 7508.8567 | E29: =C29-D29 -> 2553.6898 | F29: =Capex_36M!O29 -> 0 | G29: =E29-F29 -> 2553.6898 | H29: =Q28 -> 152837.18 | I29: =MAX(Controls!$B$22+Controls!$B$111-(H29+G29),0)+IF(A29=1,Controls!$B$21*(Controls!$B$101+Controls!$B$104),0) -> 0 | J29: =MIN(I29,MAX(Controls!$B$100-SUM($J$2:J28),0)) -> 0 | K29: =U29+V29 -> 0 | L29: =IF(A29=1,Controls!$B$21*(Controls!$B$101+Controls!$B$104),0) -> 0 | M29: =J29+K29-L29 -> 0 | N29: =W29+X29 -> 4459.6892 | O29: =0 -> 0 | P29: =IF(A29<=Controls!$B$109,0,N29+O29) -> 4459.6892 | Q29: =H29+G29+M29-P29 -> 150931.18 | R29: =T28 -> 482022.09 | S29: =IF(A29<=Controls!$B$109,N29,0) -> 0 | T29: =Y29+Z29 -> 482022.09 | U29: =MIN(I29-J29,MAX(Controls!$B$101-SUM($U$2:U28),0)) -> 0 | V29: =MIN(I29-J29-U29,MAX(Controls!$B$104-SUM($V$2:V28),0)) -> 0 | W29: =(Y28+U29/2)*Controls!$B$102/12 -> 2048.6797 | X29: =IF(AND(Controls!$B$107=1,A29>=Controls!$B$108),0,(Z28+V29/2)*Controls!$B$105/12) -> 2411.0095 | Y29: =Y28+U29+IF(A29<=Controls!$B$109,W29,0) -> 245841.56 | Z29: =IF(AND(Controls!$B$107=1,A29>=Controls!$B$108),0,Z28+V29+IF(A29<=Controls!$B$109,X29,0)) -> 236180.53 | AA29: =IF(SUM($P$18:P29)=0,"",SUM($E$18:E29)/SUM($P$18:P29)) -> 1.6700029 | AB29: =IF(A29=Controls!$B$103,"◀ Antalpha bullet due: R"&TEXT(Y29,"#,##0")&"k - refinance/convert",IF(AND(Controls!$B$107=1,A29>=Controls!$B$108)*( A29=Controls!$B$108 ),"◀ DMTN converts to equity","")) | AC29: =G29+IF(A29=36,Controls!$B$113,0) -> 2553.6898 | AD29: =-J29+IF(A29=36,Q29+Controls!$B$113-T29,0) -> 0
A30: 29 | B30: =Monthly_Deployment!C30 -> Nov-28 | C30: =Revenue_36M!P30 -> 9650.4628 | D30: =Opex_36M!P30 -> 7341.8167 | E30: =C30-D30 -> 2308.6462 | F30: =Capex_36M!O30 -> 0 | G30: =E30-F30 -> 2308.6462 | H30: =Q29 -> 150931.18 | I30: =MAX(Controls!$B$22+Controls!$B$111-(H30+G30),0)+IF(A30=1,Controls!$B$21*(Controls!$B$101+Controls!$B$104),0) -> 0 | J30: =MIN(I30,MAX(Controls!$B$100-SUM($J$2:J29),0)) -> 0 | K30: =U30+V30 -> 0 | L30: =IF(A30=1,Controls!$B$21*(Controls!$B$101+Controls!$B$104),0) -> 0 | M30: =J30+K30-L30 -> 0 | N30: =W30+X30 -> 4459.6892 | O30: =0 -> 0 | P30: =IF(A30<=Controls!$B$109,0,N30+O30) -> 4459.6892 | Q30: =H30+G30+M30-P30 -> 148780.13 | R30: =T29 -> 482022.09 | S30: =IF(A30<=Controls!$B$109,N30,0) -> 0 | T30: =Y30+Z30 -> 482022.09 | U30: =MIN(I30-J30,MAX(Controls!$B$101-SUM($U$2:U29),0)) -> 0 | V30: =MIN(I30-J30-U30,MAX(Controls!$B$104-SUM($V$2:V29),0)) -> 0 | W30: =(Y29+U30/2)*Controls!$B$102/12 -> 2048.6797 | X30: =IF(AND(Controls!$B$107=1,A30>=Controls!$B$108),0,(Z29+V30/2)*Controls!$B$105/12) -> 2411.0095 | Y30: =Y29+U30+IF(A30<=Controls!$B$109,W30,0) -> 245841.56 | Z30: =IF(AND(Controls!$B$107=1,A30>=Controls!$B$108),0,Z29+V30+IF(A30<=Controls!$B$109,X30,0)) -> 236180.53 | AA30: =IF(SUM($P$19:P30)=0,"",SUM($E$19:E30)/SUM($P$19:P30)) -> 1.542183 | AB30: =IF(A30=Controls!$B$103,"◀ Antalpha bullet due: R"&TEXT(Y30,"#,##0")&"k - refinance/convert",IF(AND(Controls!$B$107=1,A30>=Controls!$B$108)*( A30=Controls!$B$108 ),"◀ DMTN converts to equity","")) | AC30: =G30+IF(A30=36,Controls!$B$113,0) -> 2308.6462 | AD30: =-J30+IF(A30=36,Q30+Controls!$B$113-T30,0) -> 0
A31: 30 | B31: =Monthly_Deployment!C31 -> Dec-28 | C31: =Revenue_36M!P31 -> 9882.5119 | D31: =Opex_36M!P31 -> 7508.8567 | E31: =C31-D31 -> 2373.6552 | F31: =Capex_36M!O31 -> 0 | G31: =E31-F31 -> 2373.6552 | H31: =Q30 -> 148780.13 | I31: =MAX(Controls!$B$22+Controls!$B$111-(H31+G31),0)+IF(A31=1,Controls!$B$21*(Controls!$B$101+Controls!$B$104),0) -> 0 | J31: =MIN(I31,MAX(Controls!$B$100-SUM($J$2:J30),0)) -> 0 | K31: =U31+V31 -> 0 | L31: =IF(A31=1,Controls!$B$21*(Controls!$B$101+Controls!$B$104),0) -> 0 | M31: =J31+K31-L31 -> 0 | N31: =W31+X31 -> 4459.6892 | O31: =0 -> 0 | P31: =IF(A31<=Controls!$B$109,0,N31+O31) -> 4459.6892 | Q31: =H31+G31+M31-P31 -> 146694.1 | R31: =T30 -> 482022.09 | S31: =IF(A31<=Controls!$B$109,N31,0) -> 0 | T31: =Y31+Z31 -> 482022.09 | U31: =MIN(I31-J31,MAX(Controls!$B$101-SUM($U$2:U30),0)) -> 0 | V31: =MIN(I31-J31-U31,MAX(Controls!$B$104-SUM($V$2:V30),0)) -> 0 | W31: =(Y30+U31/2)*Controls!$B$102/12 -> 2048.6797 | X31: =IF(AND(Controls!$B$107=1,A31>=Controls!$B$108),0,(Z30+V31/2)*Controls!$B$105/12) -> 2411.0095 | Y31: =Y30+U31+IF(A31<=Controls!$B$109,W31,0) -> 245841.56 | Z31: =IF(AND(Controls!$B$107=1,A31>=Controls!$B$108),0,Z30+V31+IF(A31<=Controls!$B$109,X31,0)) -> 236180.53 | AA31: =IF(SUM($P$20:P31)=0,"",SUM($E$20:E31)/SUM($P$20:P31)) -> 1.4121369 | AB31: =IF(A31=Controls!$B$103,"◀ Antalpha bullet due: R"&TEXT(Y31,"#,##0")&"k - refinance/convert",IF(AND(Controls!$B$107=1,A31>=Controls!$B$108)*( A31=Controls!$B$108 ),"◀ DMTN converts to equity","")) | AC31: =G31+IF(A31=36,Controls!$B$113,0) -> 2373.6552 | AD31: =-J31+IF(A31=36,Q31+Controls!$B$113-T31,0) -> 0
A32: 31 | B32: =Monthly_Deployment!C32 -> Jan-29 | C32: =Revenue_36M!P32 -> 9793.6415 | D32: =Opex_36M!P32 -> 7508.8567 | E32: =C32-D32 -> 2284.7848 | F32: =Capex_36M!O32 -> 0 | G32: =E32-F32 -> 2284.7848 | H32: =Q31 -> 146694.1 | I32: =MAX(Controls!$B$22+Controls!$B$111-(H32+G32),0)+IF(A32=1,Controls!$B$21*(Controls!$B$101+Controls!$B$104),0) -> 0 | J32: =MIN(I32,MAX(Controls!$B$100-SUM($J$2:J31),0)) -> 0 | K32: =U32+V32 -> 0 | L32: =IF(A32=1,Controls!$B$21*(Controls!$B$101+Controls!$B$104),0) -> 0 | M32: =J32+K32-L32 -> 0 | N32: =W32+X32 -> 4459.6892 | O32: =0 -> 0 | P32: =IF(A32<=Controls!$B$109,0,N32+O32) -> 4459.6892 | Q32: =H32+G32+M32-P32 -> 144519.19 | R32: =T31 -> 482022.09 | S32: =IF(A32<=Controls!$B$109,N32,0) -> 0 | T32: =Y32+Z32 -> 482022.09 | U32: =MIN(I32-J32,MAX(Controls!$B$101-SUM($U$2:U31),0)) -> 0 | V32: =MIN(I32-J32-U32,MAX(Controls!$B$104-SUM($V$2:V31),0)) -> 0 | W32: =(Y31+U32/2)*Controls!$B$102/12 -> 2048.6797 | X32: =IF(AND(Controls!$B$107=1,A32>=Controls!$B$108),0,(Z31+V32/2)*Controls!$B$105/12) -> 2411.0095 | Y32: =Y31+U32+IF(A32<=Controls!$B$109,W32,0) -> 245841.56 | Z32: =IF(AND(Controls!$B$107=1,A32>=Controls!$B$108),0,Z31+V32+IF(A32<=Controls!$B$109,X32,0)) -> 236180.53 | AA32: =IF(SUM($P$21:P32)=0,"",SUM($E$21:E32)/SUM($P$21:P32)) -> 1.1873483 | AB32: =IF(A32=Controls!$B$103,"◀ Antalpha bullet due: R"&TEXT(Y32,"#,##0")&"k - refinance/convert",IF(AND(Controls!$B$107=1,A32>=Controls!$B$108)*( A32=Controls!$B$108 ),"◀ DMTN converts to equity","")) | AC32: =G32+IF(A32=36,Controls!$B$113,0) -> 2284.7848 | AD32: =-J32+IF(A32=36,Q32+Controls!$B$113-T32,0) -> 0
A33: 32 | B33: =Monthly_Deployment!C33 -> Feb-29 | C33: =Revenue_36M!P33 -> 8766.2831 | D33: =Opex_36M!P33 -> 7007.7367 | E33: =C33-D33 -> 1758.5465 | F33: =Capex_36M!O33 -> 0 | G33: =E33-F33 -> 1758.5465 | H33: =Q32 -> 144519.19 | I33: =MAX(Controls!$B$22+Controls!$B$111-(H33+G33),0)+IF(A33=1,Controls!$B$21*(Controls!$B$101+Controls!$B$104),0) -> 0 | J33: =MIN(I33,MAX(Controls!$B$100-SUM($J$2:J32),0)) -> 0 | K33: =U33+V33 -> 0 | L33: =IF(A33=1,Controls!$B$21*(Controls!$B$101+Controls!$B$104),0) -> 0 | M33: =J33+K33-L33 -> 0 | N33: =W33+X33 -> 4459.6892 | O33: =0 -> 0 | P33: =IF(A33<=Controls!$B$109,0,N33+O33) -> 4459.6892 | Q33: =H33+G33+M33-P33 -> 141818.05 | R33: =T32 -> 482022.09 | S33: =IF(A33<=Controls!$B$109,N33,0) -> 0 | T33: =Y33+Z33 -> 482022.09 | U33: =MIN(I33-J33,MAX(Controls!$B$101-SUM($U$2:U32),0)) -> 0 | V33: =MIN(I33-J33-U33,MAX(Controls!$B$104-SUM($V$2:V32),0)) -> 0 | W33: =(Y32+U33/2)*Controls!$B$102/12 -> 2048.6797 | X33: =IF(AND(Controls!$B$107=1,A33>=Controls!$B$108),0,(Z32+V33/2)*Controls!$B$105/12) -> 2411.0095 | Y33: =Y32+U33+IF(A33<=Controls!$B$109,W33,0) -> 245841.56 | Z33: =IF(AND(Controls!$B$107=1,A33>=Controls!$B$108),0,Z32+V33+IF(A33<=Controls!$B$109,X33,0)) -> 236180.53 | AA33: =IF(SUM($P$22:P33)=0,"",SUM($E$22:E33)/SUM($P$22:P33)) -> 0.97620493 | AB33: =IF(A33=Controls!$B$103,"◀ Antalpha bullet due: R"&TEXT(Y33,"#,##0")&"k - refinance/convert",IF(AND(Controls!$B$107=1,A33>=Controls!$B$108)*( A33=Controls!$B$108 ),"◀ DMTN converts to equity","")) | AC33: =G33+IF(A33=36,Controls!$B$113,0) -> 1758.5465 | AD33: =-J33+IF(A33=36,Q33+Controls!$B$113-T33,0) -> 0
A34: 33 | B34: =Monthly_Deployment!C34 -> Mar-29 | C34: =Revenue_36M!P34 -> 9618.1649 | D34: =Opex_36M!P34 -> 7508.8567 | E34: =C34-D34 -> 2109.3082 | F34: =Capex_36M!O34 -> 0 | G34: =E34-F34 -> 2109.3082 | H34: =Q33 -> 141818.05 | I34: =MAX(Controls!$B$22+Controls!$B$111-(H34+G34),0)+IF(A34=1,Controls!$B$21*(Controls!$B$101+Controls!$B$104),0) -> 0 | J34: =MIN(I34,MAX(Controls!$B$100-SUM($J$2:J33),0)) -> 0 | K34: =U34+V34 -> 0 | L34: =IF(A34=1,Controls!$B$21*(Controls!$B$101+Controls!$B$104),0) -> 0 | M34: =J34+K34-L34 -> 0 | N34: =W34+X34 -> 4459.6892 | O34: =0 -> 0 | P34: =IF(A34<=Controls!$B$109,0,N34+O34) -> 4459.6892 | Q34: =H34+G34+M34-P34 -> 139467.67 | R34: =T33 -> 482022.09 | S34: =IF(A34<=Controls!$B$109,N34,0) -> 0 | T34: =Y34+Z34 -> 482022.09 | U34: =MIN(I34-J34,MAX(Controls!$B$101-SUM($U$2:U33),0)) -> 0 | V34: =MIN(I34-J34-U34,MAX(Controls!$B$104-SUM($V$2:V33),0)) -> 0 | W34: =(Y33+U34/2)*Controls!$B$102/12 -> 2048.6797 | X34: =IF(AND(Controls!$B$107=1,A34>=Controls!$B$108),0,(Z33+V34/2)*Controls!$B$105/12) -> 2411.0095 | Y34: =Y33+U34+IF(A34<=Controls!$B$109,W34,0) -> 245841.56 | Z34: =IF(AND(Controls!$B$107=1,A34>=Controls!$B$108),0,Z33+V34+IF(A34<=Controls!$B$109,X34,0)) -> 236180.53 | AA34: =IF(SUM($P$23:P34)=0,"",SUM($E$23:E34)/SUM($P$23:P34)) -> 0.755401 | AB34: =IF(A34=Controls!$B$103,"◀ Antalpha bullet due: R"&TEXT(Y34,"#,##0")&"k - refinance/convert",IF(AND(Controls!$B$107=1,A34>=Controls!$B$108)*( A34=Controls!$B$108 ),"◀ DMTN converts to equity","")) | AC34: =G34+IF(A34=36,Controls!$B$113,0) -> 2109.3082 | AD34: =-J34+IF(A34=36,Q34+Controls!$B$113-T34,0) -> 0
A35: 34 | B35: =Monthly_Deployment!C35 -> Apr-29 | C35: =Revenue_36M!P35 -> 9224.0777 | D35: =Opex_36M!P35 -> 7341.8167 | E35: =C35-D35 -> 1882.2611 | F35: =Capex_36M!O35 -> 0 | G35: =E35-F35 -> 1882.2611 | H35: =Q34 -> 139467.67 | I35: =MAX(Controls!$B$22+Controls!$B$111-(H35+G35),0)+IF(A35=1,Controls!$B$21*(Controls!$B$101+Controls!$B$104),0) -> 0 | J35: =MIN(I35,MAX(Controls!$B$100-SUM($J$2:J34),0)) -> 0 | K35: =U35+V35 -> 0 | L35: =IF(A35=1,Controls!$B$21*(Controls!$B$101+Controls!$B$104),0) -> 0 | M35: =J35+K35-L35 -> 0 | N35: =W35+X35 -> 4459.6892 | O35: =0 -> 0 | P35: =IF(A35<=Controls!$B$109,0,N35+O35) -> 4459.6892 | Q35: =H35+G35+M35-P35 -> 136890.24 | R35: =T34 -> 482022.09 | S35: =IF(A35<=Controls!$B$109,N35,0) -> 0 | T35: =Y35+Z35 -> 482022.09 | U35: =MIN(I35-J35,MAX(Controls!$B$101-SUM($U$2:U34),0)) -> 0 | V35: =MIN(I35-J35-U35,MAX(Controls!$B$104-SUM($V$2:V34),0)) -> 0 | W35: =(Y34+U35/2)*Controls!$B$102/12 -> 2048.6797 | X35: =IF(AND(Controls!$B$107=1,A35>=Controls!$B$108),0,(Z34+V35/2)*Controls!$B$105/12) -> 2411.0095 | Y35: =Y34+U35+IF(A35<=Controls!$B$109,W35,0) -> 245841.56 | Z35: =IF(AND(Controls!$B$107=1,A35>=Controls!$B$108),0,Z34+V35+IF(A35<=Controls!$B$109,X35,0)) -> 236180.53 | AA35: =IF(SUM($P$24:P35)=0,"",SUM($E$24:E35)/SUM($P$24:P35)) -> 0.54362365 | AB35: =IF(A35=Controls!$B$103,"◀ Antalpha bullet due: R"&TEXT(Y35,"#,##0")&"k - refinance/convert",IF(AND(Controls!$B$107=1,A35>=Controls!$B$108)*( A35=Controls!$B$108 ),"◀ DMTN converts to equity","")) | AC35: =G35+IF(A35=36,Controls!$B$113,0) -> 1882.2611 | AD35: =-J35+IF(A35=36,Q35+Controls!$B$113-T35,0) -> 0
A36: 35 | B36: =Monthly_Deployment!C36 -> May-29 | C36: =Revenue_36M!P36 -> 9445.6684 | D36: =Opex_36M!P36 -> 7508.8567 | E36: =C36-D36 -> 1936.8117 | F36: =Capex_36M!O36 -> 0 | G36: =E36-F36 -> 1936.8117 | H36: =Q35 -> 136890.24 | I36: =MAX(Controls!$B$22+Controls!$B$111-(H36+G36),0)+IF(A36=1,Controls!$B$21*(Controls!$B$101+Controls!$B$104),0) -> 0 | J36: =MIN(I36,MAX(Controls!$B$100-SUM($J$2:J35),0)) -> 0 | K36: =U36+V36 -> 0 | L36: =IF(A36=1,Controls!$B$21*(Controls!$B$101+Controls!$B$104),0) -> 0 | M36: =J36+K36-L36 -> 0 | N36: =W36+X36 -> 4459.6892 | O36: =0 -> 0 | P36: =IF(A36<=Controls!$B$109,0,N36+O36) -> 4459.6892 | Q36: =H36+G36+M36-P36 -> 134367.37 | R36: =T35 -> 482022.09 | S36: =IF(A36<=Controls!$B$109,N36,0) -> 0 | T36: =Y36+Z36 -> 482022.09 | U36: =MIN(I36-J36,MAX(Controls!$B$101-SUM($U$2:U35),0)) -> 0 | V36: =MIN(I36-J36-U36,MAX(Controls!$B$104-SUM($V$2:V35),0)) -> 0 | W36: =(Y35+U36/2)*Controls!$B$102/12 -> 2048.6797 | X36: =IF(AND(Controls!$B$107=1,A36>=Controls!$B$108),0,(Z35+V36/2)*Controls!$B$105/12) -> 2411.0095 | Y36: =Y35+U36+IF(A36<=Controls!$B$109,W36,0) -> 245841.56 | Z36: =IF(AND(Controls!$B$107=1,A36>=Controls!$B$108),0,Z35+V36+IF(A36<=Controls!$B$109,X36,0)) -> 236180.53 | AA36: =IF(SUM($P$25:P36)=0,"",SUM($E$25:E36)/SUM($P$25:P36)) -> 0.5234312 | AB36: =IF(A36=Controls!$B$103,"◀ Antalpha bullet due: R"&TEXT(Y36,"#,##0")&"k - refinance/convert",IF(AND(Controls!$B$107=1,A36>=Controls!$B$108)*( A36=Controls!$B$108 ),"◀ DMTN converts to equity","")) | AC36: =G36+IF(A36=36,Controls!$B$113,0) -> 1936.8117 | AD36: =-J36+IF(A36=36,Q36+Controls!$B$113-T36,0) -> 0
A37: 36 | B37: =Monthly_Deployment!C37 -> Jun-29 | C37: =Revenue_36M!P37 -> 9058.5708 | D37: =Opex_36M!P37 -> 7341.8167 | E37: =C37-D37 -> 1716.7542 | F37: =Capex_36M!O37 -> 0 | G37: =E37-F37 -> 1716.7542 | H37: =Q36 -> 134367.37 | I37: =MAX(Controls!$B$22+Controls!$B$111-(H37+G37),0)+IF(A37=1,Controls!$B$21*(Controls!$B$101+Controls!$B$104),0) -> 0 | J37: =MIN(I37,MAX(Controls!$B$100-SUM($J$2:J36),0)) -> 0 | K37: =U37+V37 -> 0 | L37: =IF(A37=1,Controls!$B$21*(Controls!$B$101+Controls!$B$104),0) -> 0 | M37: =J37+K37-L37 -> 0 | N37: =W37+X37 -> 4459.6892 | O37: =0 -> 0 | P37: =IF(A37<=Controls!$B$109,0,N37+O37) -> 4459.6892 | Q37: =H37+G37+M37-P37 -> 131624.43 | R37: =T36 -> 482022.09 | S37: =IF(A37<=Controls!$B$109,N37,0) -> 0 | T37: =Y37+Z37 -> 482022.09 | U37: =MIN(I37-J37,MAX(Controls!$B$101-SUM($U$2:U36),0)) -> 0 | V37: =MIN(I37-J37-U37,MAX(Controls!$B$104-SUM($V$2:V36),0)) -> 0 | W37: =(Y36+U37/2)*Controls!$B$102/12 -> 2048.6797 | X37: =IF(AND(Controls!$B$107=1,A37>=Controls!$B$108),0,(Z36+V37/2)*Controls!$B$105/12) -> 2411.0095 | Y37: =Y36+U37+IF(A37<=Controls!$B$109,W37,0) -> 245841.56 | Z37: =IF(AND(Controls!$B$107=1,A37>=Controls!$B$108),0,Z36+V37+IF(A37<=Controls!$B$109,X37,0)) -> 236180.53 | AA37: =IF(SUM($P$26:P37)=0,"",SUM($E$26:E37)/SUM($P$26:P37)) -> 0.50405629 | AB37: =IF(A37=Controls!$B$103,"◀ Antalpha bullet due: R"&TEXT(Y37,"#,##0")&"k - refinance/convert",IF(AND(Controls!$B$107=1,A37>=Controls!$B$108)*( A37=Controls!$B$108 ),"◀ DMTN converts to equity","")) | AC37: =G37+IF(A37=36,Controls!$B$113,0) -> 501716.75 | AD37: =-J37+IF(A37=36,Q37+Controls!$B$113-T37,0) -> 149602.34

Sheet Annual_Summary
A1: Annual Summary
A3: Metric | B3: Units | C3: Year 1 | D3: Year 2 | E3: Year 3
A4: Closing Mining MW | B4: MW | C4: =INDEX(Monthly_Deployment!$J$2:$J$37,12) -> 20 | D4: =INDEX(Monthly_Deployment!$J$2:$J$37,24) -> 20 | E4: =INDEX(Monthly_Deployment!$J$2:$J$37,36) -> 20
A5: BTC mined | B5: BTC | C5: =SUM(Revenue_36M!$H$2:$H$13) -> 171.32822 | D5: =SUM(Revenue_36M!$H$14:$H$25) -> 174.52605 | E5: =SUM(Revenue_36M!$H$26:$H$37) -> 80.686997
A6: BTC revenue | B6: ZAR '000 | C6: =SUM(Revenue_36M!$I$2:$I$13) -> 224399.49 | D6: =SUM(Revenue_36M!$I$14:$I$25) -> 238357.74 | E6: =SUM(Revenue_36M!$I$26:$I$37) -> 115912.21
A7: DR revenue | B7: ZAR '000 | C7: =SUM(Revenue_36M!$N$2:$N$13) -> 0 | D7: =SUM(Revenue_36M!$N$14:$N$25) -> 0 | E7: =SUM(Revenue_36M!$N$26:$N$37) -> 0
A8: AI/DC pilot revenue | B8: ZAR '000 | C8: =SUM(Revenue_36M!$O$2:$O$13) -> 0 | D8: =SUM(Revenue_36M!$O$14:$O$25) -> 0 | E8: =SUM(Revenue_36M!$O$26:$O$37) -> 0
A9: Total revenue | B9: ZAR '000 | C9: =SUM(Revenue_36M!$P$2:$P$13) -> 224399.49 | D9: =SUM(Revenue_36M!$P$14:$P$25) -> 238357.74 | E9: =SUM(Revenue_36M!$P$26:$P$37) -> 115912.21
A10: Cash opex | B10: ZAR '000 | C10: =SUM(Opex_36M!$P$2:$P$13) -> 123676.97 | D10: =SUM(Opex_36M!$P$14:$P$25) -> 119839.4 | E10: =SUM(Opex_36M!$P$26:$P$37) -> 88937
A11: EBITDA | B11: ZAR '000 | C11: =SUM(Funding_36M!$E$2:$E$13) -> 100722.52 | D11: =SUM(Funding_36M!$E$14:$E$25) -> 118518.34 | E11: =SUM(Funding_36M!$E$26:$E$37) -> 26975.213
A12: Capex cash | B12: ZAR '000 | C12: =SUM(Capex_36M!$O$2:$O$13) -> 511456.86 | D12: =SUM(Capex_36M!$O$14:$O$25) -> 0 | E12: =SUM(Capex_36M!$O$26:$O$37) -> 0
A13: Unlevered FCF | B13: ZAR '000 | C13: =SUM(Funding_36M!$G$2:$G$13) -> -410734.34 | D13: =SUM(Funding_36M!$G$14:$G$25) -> 118518.34 | E13: =SUM(Funding_36M!$G$26:$G$37) -> 26975.213
A14: Equity Draw | B14: ZAR '000 | C14: =SUM(Funding_36M!$J$2:$J$13) -> 68000 | D14: =SUM(Funding_36M!$J$14:$J$25) -> 0 | E14: =SUM(Funding_36M!$J$26:$J$37) -> 0
A15: Debt Draw | B15: ZAR '000 | C15: =SUM(Funding_36M!$K$2:$K$13) -> 467535.9 | D15: =SUM(Funding_36M!$K$14:$K$25) -> 0 | E15: =SUM(Funding_36M!$K$26:$K$37) -> 0
A16: Closing Cash | B16: ZAR '000 | C16: =INDEX(Funding_36M!$Q$2:$Q$37,12) -> 93163.423 | D16: =INDEX(Funding_36M!$Q$2:$Q$37,24) -> 158165.49 | E16: =INDEX(Funding_36M!$Q$2:$Q$37,36) -> 131624.43
A17: Closing Debt | B17: ZAR '000 | C17: =INDEX(Funding_36M!$T$2:$T$37,12) -> 482022.09 | D17: =INDEX(Funding_36M!$T$2:$T$37,24) -> 482022.09 | E17: =INDEX(Funding_36M!$T$2:$T$37,36) -> 482022.09
A18: Annual DSCR (interest-only) | B18: x | C18: =IF(SUM(Funding_36M!$P$2:$P$13)=0,0,SUM(Funding_36M!$E$2:$E$13)/SUM(Funding_36M!$P$2:$P$13)) -> 3.764183 | D18: =IF(SUM(Funding_36M!$P$14:$P$25)=0,0,SUM(Funding_36M!$E$14:$E$25)/SUM(Funding_36M!$P$14:$P$25)) -> 2.2146225 | E18: =IF(SUM(Funding_36M!$P$26:$P$37)=0,0,SUM(Funding_36M!$E$26:$E$37)/SUM(Funding_36M!$P$26:$P$37)) -> 0.50405629
A19: Cash interest paid | B19: ZAR '000 | C19: =SUM(Funding_36M!$N$2:$N$13) -> 41244.323 | D19: =SUM(Funding_36M!$N$14:$N$25) -> 53516.27 | E19: =SUM(Funding_36M!$N$26:$N$37) -> 53516.27
A20: Cash debt service | B20: ZAR '000 | C20: =SUM(Funding_36M!$P$2:$P$13) -> 26758.135 | D20: =SUM(Funding_36M!$P$14:$P$25) -> 53516.27 | E20: =SUM(Funding_36M!$P$26:$P$37) -> 53516.27
A21: Antalpha closing balance | B21: ZAR '000 | C21: =INDEX(Funding_36M!$Y$2:$Y$37,12) -> 245841.56 | D21: =INDEX(Funding_36M!$Y$2:$Y$37,24) -> 245841.56 | E21: =INDEX(Funding_36M!$Y$2:$Y$37,36) -> 245841.56
A22: DMTN closing balance | B22: ZAR '000 | C22: =INDEX(Funding_36M!$Z$2:$Z$37,12) -> 236180.53 | D22: =INDEX(Funding_36M!$Z$2:$Z$37,24) -> 236180.53 | E22: =INDEX(Funding_36M!$Z$2:$Z$37,36) -> 236180.53
A24: Coverage summary (Debt Case)
A25: Min trailing-12M DSCR | B25: =MIN(Funding_36M!$AA$14:$AA$37) -> 0.50405629
A26: DSCR covenant (min) | B26: 1.5 | C26: Indicative DMTN covenant
A27: Min DSCR vs covenant | B27: =IF(B25>=B26,"PASS","BELOW COVENANT in stress year") -> BELOW COVENANT in stress year
A28: Antalpha bullet refinance (M24) | B28: =INDEX(Funding_36M!$Y$2:$Y$37,24) -> 245841.56 | C28: Refinance / convert before Year-3 thin period
A30: Note: standalone BTC-only coverage falls below 1.0x in Year 3 (subsidy halving + rising difficulty). Mitigants: 24-month Antalpha bullet retired/refinanced before Year 3; DMTN equitised at IPO (toggle in Controls); first-ranking ASIC security; funded DSRA; and DR / tariff-relief upside in the Sponsor and Upside cases.

Sheet Milestones
A1: Phase 1 underwriting milestones and scale-up gating
A3: Gate | B3: Target timing | C3: Evidence expected | D3: Model consequence | E3: Current status | F3: Owner | G3: Next action | H3: Investor use
A4: Capital close | B4: Month 0 | C4: Executed subscription / funding availability | D4: Procurement and EPC deposits released | E4: In progress | F4: Finance | G4: Finalise first-close documents | H4: Confirms project start
A5: Grootvlei 10MW energised | B5: Month 3 | C5: Eskom energisation / commissioning sign-off | D5: GVL BTC revenue begins | E5: Planned | F5: Operations | G5: EPC and protection workstream | H5: Proof of physical execution
A6: AMSA 10MW energised | B6: Month 4 | C6: AMSA site energisation and access package | D6: AMSA BTC revenue begins | E6: Planned | F6: Operations | G6: Conclude AMSA Phase 1 package | H6: Proves dual-node model
A7: Real-time telemetry & curtailment proof | B7: Month 6-9 | C7: SCADA logs, curtailment response report, Eskom/NTCSA telemetry test | D7: DR revenue may move from excluded to scenario-supported | E7: Planned | F7: Technical | G7: Implement telemetry reporting pack | H7: Unlocks infrastructure capital
A8: Tariff reduction pathway | B8: Month 12-18 | C8: Demonstrated grid value, tariff engagement, demand-response evidence | D8: Post-initial tariff assumptions are validated | E8: Planned | F8: Commercial | G8: Quantify system value and tariff submission | H8: Supports scale-up economics
A9: Institutional scale-up approval | B9: Month 12+ | C9: Investor IC approval against live KPIs | D9: Scale-up model / 10Y platform case becomes funding source | E9: Pending | F9: Board | G9: Prepare scale-up data room | H9: Unlocks next capital tranche
A10: AI/DC customer validation | B10: Month 18+ | C10: Term sheet or pilot hosting customer | D10: AI/DC pilot revenue may be activated in upside case only | E10: Future option | F10: Commercial | G10: Develop hosting partner pipeline | H10: Demonstrates layer 4 economics

Sheet Sensitivity
A1: Phase 1 underwriting sensitivities | N1: IRR engine (helper) — monthly cash flows by terminal value; referenced by the table above
N2: Month | O2: Unlev op CF | P2: Equity op CF | Q2: U:0k | R2: U:250k | S2: U:500k | T2: U:750k | U2: U:1000k | V2: E:0k | W2: E:250k | X2: E:500k | Y2: E:750k | Z2: E:1000k
A3: Scenario metric | B3: Value | D3: Indicative 36-month BTC revenue (ZAR'000) | N3: 1 | O3: =Funding_36M!$G2 -> -2973 | P3: =-Funding_36M!$J2+IF(1=36,Funding_36M!$Q2-Funding_36M!$T2,0) -> -40065.5 | Q3: =O3+IF(1=36,0,0) -> -2973 | R3: =O3+IF(1=36,250000,0) -> -2973 | S3: =O3+IF(1=36,500000,0) -> -2973 | T3: =O3+IF(1=36,750000,0) -> -2973 | U3: =O3+IF(1=36,1000000,0) -> -2973 | V3: =P3+IF(1=36,0,0) -> -40065.5 | W3: =P3+IF(1=36,250000,0) -> -40065.5 | X3: =P3+IF(1=36,500000,0) -> -40065.5 | Y3: =P3+IF(1=36,750000,0) -> -40065.5 | Z3: =P3+IF(1=36,1000000,0) -> -40065.5
A4: Selected case | B4: =Controls!$C$4 -> Debt Case | D4: Network ↓ \ BTC price growth → | E4: 0 | F4: 0.05 | G4: 0.1 | H4: 0.15 | I4: 0.2 | J4: 0.25 | N4: 2 | O4: =Funding_36M!$G3 -> -124119.63 | P4: =-Funding_36M!$J3+IF(2=36,Funding_36M!$Q3-Funding_36M!$T3,0) -> -27934.5 | Q4: =O4+IF(2=36,0,0) -> -124119.63 | R4: =O4+IF(2=36,250000,0) -> -124119.63 | S4: =O4+IF(2=36,500000,0) -> -124119.63 | T4: =O4+IF(2=36,750000,0) -> -124119.63 | U4: =O4+IF(2=36,1000000,0) -> -124119.63 | V4: =P4+IF(2=36,0,0) -> -27934.5 | W4: =P4+IF(2=36,250000,0) -> -27934.5 | X4: =P4+IF(2=36,500000,0) -> -27934.5 | Y4: =P4+IF(2=36,750000,0) -> -27934.5 | Z4: =P4+IF(2=36,1000000,0) -> -27934.5
A5: Peak external funding (total) | B5: =SUM(Funding_36M!$J$2:$J$37)+SUM(Funding_36M!$K$2:$K$37) -> 535535.9 | D5: 0.1 | E5: =SUMPRODUCT(Monthly_Deployment!$T$2:$T$37,Revenue_36M!$G$2:$G$37,(1+E$4)^((Revenue_36M!$A$2:$A$37-1)/12),(1/(1+$D5))^((Revenue_36M!$A$2:$A$37-1)/12))/Controls!$B$26*Controls!$B$24*Controls!$B$25/1000 -> 608063.19 | F5: =SUMPRODUCT(Monthly_Deployment!$T$2:$T$37,Revenue_36M!$G$2:$G$37,(1+F$4)^((Revenue_36M!$A$2:$A$37-1)/12),(1/(1+$D5))^((Revenue_36M!$A$2:$A$37-1)/12))/Controls!$B$26*Controls!$B$24*Controls!$B$25/1000 -> 648535.46 | G5: =SUMPRODUCT(Monthly_Deployment!$T$2:$T$37,Revenue_36M!$G$2:$G$37,(1+G$4)^((Revenue_36M!$A$2:$A$37-1)/12),(1/(1+$D5))^((Revenue_36M!$A$2:$A$37-1)/12))/Controls!$B$26*Controls!$B$24*Controls!$B$25/1000 -> 690499.71 | H5: =SUMPRODUCT(Monthly_Deployment!$T$2:$T$37,Revenue_36M!$G$2:$G$37,(1+H$4)^((Revenue_36M!$A$2:$A$37-1)/12),(1/(1+$D5))^((Revenue_36M!$A$2:$A$37-1)/12))/Controls!$B$26*Controls!$B$24*Controls!$B$25/1000 -> 733986.21 | I5: =SUMPRODUCT(Monthly_Deployment!$T$2:$T$37,Revenue_36M!$G$2:$G$37,(1+I$4)^((Revenue_36M!$A$2:$A$37-1)/12),(1/(1+$D5))^((Revenue_36M!$A$2:$A$37-1)/12))/Controls!$B$26*Controls!$B$24*Controls!$B$25/1000 -> 779024.52 | J5: =SUMPRODUCT(Monthly_Deployment!$T$2:$T$37,Revenue_36M!$G$2:$G$37,(1+J$4)^((Revenue_36M!$A$2:$A$37-1)/12),(1/(1+$D5))^((Revenue_36M!$A$2:$A$37-1)/12))/Controls!$B$26*Controls!$B$24*Controls!$B$25/1000 -> 825643.61 | N5: 3 | O5: =Funding_36M!$G4 -> -212363.94 | P5: =-Funding_36M!$J4+IF(3=36,Funding_36M!$Q4-Funding_36M!$T4,0) -> 0 | Q5: =O5+IF(3=36,0,0) -> -212363.94 | R5: =O5+IF(3=36,250000,0) -> -212363.94 | S5: =O5+IF(3=36,500000,0) -> -212363.94 | T5: =O5+IF(3=36,750000,0) -> -212363.94 | U5: =O5+IF(3=36,1000000,0) -> -212363.94 | V5: =P5+IF(3=36,0,0) -> 0 | W5: =P5+IF(3=36,250000,0) -> 0 | X5: =P5+IF(3=36,500000,0) -> 0 | Y5: =P5+IF(3=36,750000,0) -> 0 | Z5: =P5+IF(3=36,1000000,0) -> 0
A6: 36M revenue | B6: =SUM(Revenue_36M!$P$2:$P$37) -> 578669.44 | D6: 0.15 | E6: =SUMPRODUCT(Monthly_Deployment!$T$2:$T$37,Revenue_36M!$G$2:$G$37,(1+E$4)^((Revenue_36M!$A$2:$A$37-1)/12),(1/(1+$D6))^((Revenue_36M!$A$2:$A$37-1)/12))/Controls!$B$26*Controls!$B$24*Controls!$B$25/1000 -> 574058.53 | F6: =SUMPRODUCT(Monthly_Deployment!$T$2:$T$37,Revenue_36M!$G$2:$G$37,(1+F$4)^((Revenue_36M!$A$2:$A$37-1)/12),(1/(1+$D6))^((Revenue_36M!$A$2:$A$37-1)/12))/Controls!$B$26*Controls!$B$24*Controls!$B$25/1000 -> 611524.07 | G6: =SUMPRODUCT(Monthly_Deployment!$T$2:$T$37,Revenue_36M!$G$2:$G$37,(1+G$4)^((Revenue_36M!$A$2:$A$37-1)/12),(1/(1+$D6))^((Revenue_36M!$A$2:$A$37-1)/12))/Controls!$B$26*Controls!$B$24*Controls!$B$25/1000 -> 650328.75 | H6: =SUMPRODUCT(Monthly_Deployment!$T$2:$T$37,Revenue_36M!$G$2:$G$37,(1+H$4)^((Revenue_36M!$A$2:$A$37-1)/12),(1/(1+$D6))^((Revenue_36M!$A$2:$A$37-1)/12))/Controls!$B$26*Controls!$B$24*Controls!$B$25/1000 -> 690499.71 | I6: =SUMPRODUCT(Monthly_Deployment!$T$2:$T$37,Revenue_36M!$G$2:$G$37,(1+I$4)^((Revenue_36M!$A$2:$A$37-1)/12),(1/(1+$D6))^((Revenue_36M!$A$2:$A$37-1)/12))/Controls!$B$26*Controls!$B$24*Controls!$B$25/1000 -> 732063.43 | J6: =SUMPRODUCT(Monthly_Deployment!$T$2:$T$37,Revenue_36M!$G$2:$G$37,(1+J$4)^((Revenue_36M!$A$2:$A$37-1)/12),(1/(1+$D6))^((Revenue_36M!$A$2:$A$37-1)/12))/Controls!$B$26*Controls!$B$24*Controls!$B$25/1000 -> 775045.8 | N6: 4 | O6: =Funding_36M!$G5 -> -158986.83 | P6: =-Funding_36M!$J5+IF(4=36,Funding_36M!$Q5-Funding_36M!$T5,0) -> 0 | Q6: =O6+IF(4=36,0,0) -> -158986.83 | R6: =O6+IF(4=36,250000,0) -> -158986.83 | S6: =O6+IF(4=36,500000,0) -> -158986.83 | T6: =O6+IF(4=36,750000,0) -> -158986.83 | U6: =O6+IF(4=36,1000000,0) -> -158986.83 | V6: =P6+IF(4=36,0,0) -> 0 | W6: =P6+IF(4=36,250000,0) -> 0 | X6: =P6+IF(4=36,500000,0) -> 0 | Y6: =P6+IF(4=36,750000,0) -> 0 | Z6: =P6+IF(4=36,1000000,0) -> 0
A7: 36M EBITDA | B7: =SUM(Funding_36M!$E$2:$E$37) -> 246216.07 | D7: 0.2 | E7: =SUMPRODUCT(Monthly_Deployment!$T$2:$T$37,Revenue_36M!$G$2:$G$37,(1+E$4)^((Revenue_36M!$A$2:$A$37-1)/12),(1/(1+$D7))^((Revenue_36M!$A$2:$A$37-1)/12))/Controls!$B$26*Controls!$B$24*Controls!$B$25/1000 -> 543840.11 | F7: =SUMPRODUCT(Monthly_Deployment!$T$2:$T$37,Revenue_36M!$G$2:$G$37,(1+F$4)^((Revenue_36M!$A$2:$A$37-1)/12),(1/(1+$D7))^((Revenue_36M!$A$2:$A$37-1)/12))/Controls!$B$26*Controls!$B$24*Controls!$B$25/1000 -> 578669.44 | G7: =SUMPRODUCT(Monthly_Deployment!$T$2:$T$37,Revenue_36M!$G$2:$G$37,(1+G$4)^((Revenue_36M!$A$2:$A$37-1)/12),(1/(1+$D7))^((Revenue_36M!$A$2:$A$37-1)/12))/Controls!$B$26*Controls!$B$24*Controls!$B$25/1000 -> 614706.26 | H7: =SUMPRODUCT(Monthly_Deployment!$T$2:$T$37,Revenue_36M!$G$2:$G$37,(1+H$4)^((Revenue_36M!$A$2:$A$37-1)/12),(1/(1+$D7))^((Revenue_36M!$A$2:$A$37-1)/12))/Controls!$B$26*Controls!$B$24*Controls!$B$25/1000 -> 651975.07 | I7: =SUMPRODUCT(Monthly_Deployment!$T$2:$T$37,Revenue_36M!$G$2:$G$37,(1+I$4)^((Revenue_36M!$A$2:$A$37-1)/12),(1/(1+$D7))^((Revenue_36M!$A$2:$A$37-1)/12))/Controls!$B$26*Controls!$B$24*Controls!$B$25/1000 -> 690499.71 | J7: =SUMPRODUCT(Monthly_Deployment!$T$2:$T$37,Revenue_36M!$G$2:$G$37,(1+J$4)^((Revenue_36M!$A$2:$A$37-1)/12),(1/(1+$D7))^((Revenue_36M!$A$2:$A$37-1)/12))/Controls!$B$26*Controls!$B$24*Controls!$B$25/1000 -> 730303.46 | N7: 5 | O7: =Funding_36M!$G6 -> 11585.295 | P7: =-Funding_36M!$J6+IF(5=36,Funding_36M!$Q6-Funding_36M!$T6,0) -> 0 | Q7: =O7+IF(5=36,0,0) -> 11585.295 | R7: =O7+IF(5=36,250000,0) -> 11585.295 | S7: =O7+IF(5=36,500000,0) -> 11585.295 | T7: =O7+IF(5=36,750000,0) -> 11585.295 | U7: =O7+IF(5=36,1000000,0) -> 11585.295 | V7: =P7+IF(5=36,0,0) -> 0 | W7: =P7+IF(5=36,250000,0) -> 0 | X7: =P7+IF(5=36,500000,0) -> 0 | Y7: =P7+IF(5=36,750000,0) -> 0 | Z7: =P7+IF(5=36,1000000,0) -> 0
A8: 36M unlevered FCF (excl. terminal) | B8: =SUM(Funding_36M!$G$2:$G$37) -> -265240.79 | D8: 0.25 | E8: =SUMPRODUCT(Monthly_Deployment!$T$2:$T$37,Revenue_36M!$G$2:$G$37,(1+E$4)^((Revenue_36M!$A$2:$A$37-1)/12),(1/(1+$D8))^((Revenue_36M!$A$2:$A$37-1)/12))/Controls!$B$26*Controls!$B$24*Controls!$B$25/1000 -> 516829.12 | F8: =SUMPRODUCT(Monthly_Deployment!$T$2:$T$37,Revenue_36M!$G$2:$G$37,(1+F$4)^((Revenue_36M!$A$2:$A$37-1)/12),(1/(1+$D8))^((Revenue_36M!$A$2:$A$37-1)/12))/Controls!$B$26*Controls!$B$24*Controls!$B$25/1000 -> 549332.68 | G8: =SUMPRODUCT(Monthly_Deployment!$T$2:$T$37,Revenue_36M!$G$2:$G$37,(1+G$4)^((Revenue_36M!$A$2:$A$37-1)/12),(1/(1+$D8))^((Revenue_36M!$A$2:$A$37-1)/12))/Controls!$B$26*Controls!$B$24*Controls!$B$25/1000 -> 582929.61 | H8: =SUMPRODUCT(Monthly_Deployment!$T$2:$T$37,Revenue_36M!$G$2:$G$37,(1+H$4)^((Revenue_36M!$A$2:$A$37-1)/12),(1/(1+$D8))^((Revenue_36M!$A$2:$A$37-1)/12))/Controls!$B$26*Controls!$B$24*Controls!$B$25/1000 -> 617642.11 | I8: =SUMPRODUCT(Monthly_Deployment!$T$2:$T$37,Revenue_36M!$G$2:$G$37,(1+I$4)^((Revenue_36M!$A$2:$A$37-1)/12),(1/(1+$D8))^((Revenue_36M!$A$2:$A$37-1)/12))/Controls!$B$26*Controls!$B$24*Controls!$B$25/1000 -> 653491.79 | J8: =SUMPRODUCT(Monthly_Deployment!$T$2:$T$37,Revenue_36M!$G$2:$G$37,(1+J$4)^((Revenue_36M!$A$2:$A$37-1)/12),(1/(1+$D8))^((Revenue_36M!$A$2:$A$37-1)/12))/Controls!$B$26*Controls!$B$24*Controls!$B$25/1000 -> 690499.71 | N8: 6 | O8: =Funding_36M!$G7 -> 11829.549 | P8: =-Funding_36M!$J7+IF(6=36,Funding_36M!$Q7-Funding_36M!$T7,0) -> 0 | Q8: =O8+IF(6=36,0,0) -> 11829.549 | R8: =O8+IF(6=36,250000,0) -> 11829.549 | S8: =O8+IF(6=36,500000,0) -> 11829.549 | T8: =O8+IF(6=36,750000,0) -> 11829.549 | U8: =O8+IF(6=36,1000000,0) -> 11829.549 | V8: =P8+IF(6=36,0,0) -> 0 | W8: =P8+IF(6=36,250000,0) -> 0 | X8: =P8+IF(6=36,500000,0) -> 0 | Y8: =P8+IF(6=36,750000,0) -> 0 | Z8: =P8+IF(6=36,1000000,0) -> 0
A9: Closing cash M36 | B9: =INDEX(Funding_36M!$Q$2:$Q$37,36) -> 131624.43 | D9: 0.3 | E9: =SUMPRODUCT(Monthly_Deployment!$T$2:$T$37,Revenue_36M!$G$2:$G$37,(1+E$4)^((Revenue_36M!$A$2:$A$37-1)/12),(1/(1+$D9))^((Revenue_36M!$A$2:$A$37-1)/12))/Controls!$B$26*Controls!$B$24*Controls!$B$25/1000 -> 492556.01 | F9: =SUMPRODUCT(Monthly_Deployment!$T$2:$T$37,Revenue_36M!$G$2:$G$37,(1+F$4)^((Revenue_36M!$A$2:$A$37-1)/12),(1/(1+$D9))^((Revenue_36M!$A$2:$A$37-1)/12))/Controls!$B$26*Controls!$B$24*Controls!$B$25/1000 -> 522995.95 | G9: =SUMPRODUCT(Monthly_Deployment!$T$2:$T$37,Revenue_36M!$G$2:$G$37,(1+G$4)^((Revenue_36M!$A$2:$A$37-1)/12),(1/(1+$D9))^((Revenue_36M!$A$2:$A$37-1)/12))/Controls!$B$26*Controls!$B$24*Controls!$B$25/1000 -> 554429.71 | H9: =SUMPRODUCT(Monthly_Deployment!$T$2:$T$37,Revenue_36M!$G$2:$G$37,(1+H$4)^((Revenue_36M!$A$2:$A$37-1)/12),(1/(1+$D9))^((Revenue_36M!$A$2:$A$37-1)/12))/Controls!$B$26*Controls!$B$24*Controls!$B$25/1000 -> 586877.55 | I9: =SUMPRODUCT(Monthly_Deployment!$T$2:$T$37,Revenue_36M!$G$2:$G$37,(1+I$4)^((Revenue_36M!$A$2:$A$37-1)/12),(1/(1+$D9))^((Revenue_36M!$A$2:$A$37-1)/12))/Controls!$B$26*Controls!$B$24*Controls!$B$25/1000 -> 620359.14 | J9: =SUMPRODUCT(Monthly_Deployment!$T$2:$T$37,Revenue_36M!$G$2:$G$37,(1+J$4)^((Revenue_36M!$A$2:$A$37-1)/12),(1/(1+$D9))^((Revenue_36M!$A$2:$A$37-1)/12))/Controls!$B$26*Controls!$B$24*Controls!$B$25/1000 -> 654893.62 | N9: 7 | O9: =Funding_36M!$G8 -> 11611.772 | P9: =-Funding_36M!$J8+IF(7=36,Funding_36M!$Q8-Funding_36M!$T8,0) -> 0 | Q9: =O9+IF(7=36,0,0) -> 11611.772 | R9: =O9+IF(7=36,250000,0) -> 11611.772 | S9: =O9+IF(7=36,500000,0) -> 11611.772 | T9: =O9+IF(7=36,750000,0) -> 11611.772 | U9: =O9+IF(7=36,1000000,0) -> 11611.772 | V9: =P9+IF(7=36,0,0) -> 0 | W9: =P9+IF(7=36,250000,0) -> 0 | X9: =P9+IF(7=36,500000,0) -> 0 | Y9: =P9+IF(7=36,750000,0) -> 0 | Z9: =P9+IF(7=36,1000000,0) -> 0
A10: Closing debt M36 | B10: =INDEX(Funding_36M!$T$2:$T$37,36) -> 482022.09 | D10: ● Debt Case base = 5% BTC / 20% network (cell highlighted). DR & AI excluded. | N10: 8 | O10: =Funding_36M!$G9 -> 10067.447 | P10: =-Funding_36M!$J9+IF(8=36,Funding_36M!$Q9-Funding_36M!$T9,0) -> 0 | Q10: =O10+IF(8=36,0,0) -> 10067.447 | R10: =O10+IF(8=36,250000,0) -> 10067.447 | S10: =O10+IF(8=36,500000,0) -> 10067.447 | T10: =O10+IF(8=36,750000,0) -> 10067.447 | U10: =O10+IF(8=36,1000000,0) -> 10067.447 | V10: =P10+IF(8=36,0,0) -> 0 | W10: =P10+IF(8=36,250000,0) -> 0 | X10: =P10+IF(8=36,500000,0) -> 0 | Y10: =P10+IF(8=36,750000,0) -> 0 | Z10: =P10+IF(8=36,1000000,0) -> 0
A11: Break-even BTC price Year 1 | B11: =IF(SUM(Revenue_36M!$H$2:$H$13)=0,0,SUM(Opex_36M!$P$2:$P$13)*1000/SUM(Revenue_36M!$H$2:$H$13)/Controls!$B$25) -> 42463.035 | N11: 9 | O11: =Funding_36M!$G10 -> 11181.655 | P11: =-Funding_36M!$J10+IF(9=36,Funding_36M!$Q10-Funding_36M!$T10,0) -> 0 | Q11: =O11+IF(9=36,0,0) -> 11181.655 | R11: =O11+IF(9=36,250000,0) -> 11181.655 | S11: =O11+IF(9=36,500000,0) -> 11181.655 | T11: =O11+IF(9=36,750000,0) -> 11181.655 | U11: =O11+IF(9=36,1000000,0) -> 11181.655 | V11: =P11+IF(9=36,0,0) -> 0 | W11: =P11+IF(9=36,250000,0) -> 0 | X11: =P11+IF(9=36,500000,0) -> 0 | Y11: =P11+IF(9=36,750000,0) -> 0 | Z11: =P11+IF(9=36,1000000,0) -> 0
A12: Min trailing-12M DSCR | B12: =MIN(Funding_36M!$AA$14:$AA$37) -> 0.50405629 | N12: 10 | O12: =Funding_36M!$G11 -> 10540.261 | P12: =-Funding_36M!$J11+IF(10=36,Funding_36M!$Q11-Funding_36M!$T11,0) -> 0 | Q12: =O12+IF(10=36,0,0) -> 10540.261 | R12: =O12+IF(10=36,250000,0) -> 10540.261 | S12: =O12+IF(10=36,500000,0) -> 10540.261 | T12: =O12+IF(10=36,750000,0) -> 10540.261 | U12: =O12+IF(10=36,1000000,0) -> 10540.261 | V12: =P12+IF(10=36,0,0) -> 0 | W12: =P12+IF(10=36,250000,0) -> 0 | X12: =P12+IF(10=36,500000,0) -> 0 | Y12: =P12+IF(10=36,750000,0) -> 0 | Z12: =P12+IF(10=36,1000000,0) -> 0
A13: Unlevered IRR (base terminal value) | B13: =IFERROR((1+IRR(Funding_36M!$AC$2:$AC$37,0.01))^12-1,"n/a") -> 0.1974839 | N13: 11 | O13: =Funding_36M!$G12 -> 10758.702 | P13: =-Funding_36M!$J12+IF(11=36,Funding_36M!$Q12-Funding_36M!$T12,0) -> 0 | Q13: =O13+IF(11=36,0,0) -> 10758.702 | R13: =O13+IF(11=36,250000,0) -> 10758.702 | S13: =O13+IF(11=36,500000,0) -> 10758.702 | T13: =O13+IF(11=36,750000,0) -> 10758.702 | U13: =O13+IF(11=36,1000000,0) -> 10758.702 | V13: =P13+IF(11=36,0,0) -> 0 | W13: =P13+IF(11=36,250000,0) -> 0 | X13: =P13+IF(11=36,500000,0) -> 0 | Y13: =P13+IF(11=36,750000,0) -> 0 | Z13: =P13+IF(11=36,1000000,0) -> 0
A14: Equity IRR (base terminal value) | B14: =IFERROR((1+IRR(Funding_36M!$AD$2:$AD$37,0.01))^12-1,"n/a") -> 0.31458689 | N14: 12 | O14: =Funding_36M!$G13 -> 10134.377 | P14: =-Funding_36M!$J13+IF(12=36,Funding_36M!$Q13-Funding_36M!$T13,0) -> 0 | Q14: =O14+IF(12=36,0,0) -> 10134.377 | R14: =O14+IF(12=36,250000,0) -> 10134.377 | S14: =O14+IF(12=36,500000,0) -> 10134.377 | T14: =O14+IF(12=36,750000,0) -> 10134.377 | U14: =O14+IF(12=36,1000000,0) -> 10134.377 | V14: =P14+IF(12=36,0,0) -> 0 | W14: =P14+IF(12=36,250000,0) -> 0 | X14: =P14+IF(12=36,500000,0) -> 0 | Y14: =P14+IF(12=36,750000,0) -> 0 | Z14: =P14+IF(12=36,1000000,0) -> 0
N15: 13 | O15: =Funding_36M!$G14 -> 10342.803 | P15: =-Funding_36M!$J14+IF(13=36,Funding_36M!$Q14-Funding_36M!$T14,0) -> 0 | Q15: =O15+IF(13=36,0,0) -> 10342.803 | R15: =O15+IF(13=36,250000,0) -> 10342.803 | S15: =O15+IF(13=36,500000,0) -> 10342.803 | T15: =O15+IF(13=36,750000,0) -> 10342.803 | U15: =O15+IF(13=36,1000000,0) -> 10342.803 | V15: =P15+IF(13=36,0,0) -> 0 | W15: =P15+IF(13=36,250000,0) -> 0 | X15: =P15+IF(13=36,500000,0) -> 0 | Y15: =P15+IF(13=36,750000,0) -> 0 | Z15: =P15+IF(13=36,1000000,0) -> 0
A16: Single-factor sensitivities — IC asks: FX · energy escalation · hardware cost · terminal value | N16: 14 | O16: =Funding_36M!$G15 -> 10137.467 | P16: =-Funding_36M!$J15+IF(14=36,Funding_36M!$Q15-Funding_36M!$T15,0) -> 0 | Q16: =O16+IF(14=36,0,0) -> 10137.467 | R16: =O16+IF(14=36,250000,0) -> 10137.467 | S16: =O16+IF(14=36,500000,0) -> 10137.467 | T16: =O16+IF(14=36,750000,0) -> 10137.467 | U16: =O16+IF(14=36,1000000,0) -> 10137.467 | V16: =P16+IF(14=36,0,0) -> 0 | W16: =P16+IF(14=36,250000,0) -> 0 | X16: =P16+IF(14=36,500000,0) -> 0 | Y16: =P16+IF(14=36,750000,0) -> 0 | Z16: =P16+IF(14=36,1000000,0) -> 0
N17: 15 | O17: =Funding_36M!$G16 -> 9538.2269 | P17: =-Funding_36M!$J16+IF(15=36,Funding_36M!$Q16-Funding_36M!$T16,0) -> 0 | Q17: =O17+IF(15=36,0,0) -> 9538.2269 | R17: =O17+IF(15=36,250000,0) -> 9538.2269 | S17: =O17+IF(15=36,500000,0) -> 9538.2269 | T17: =O17+IF(15=36,750000,0) -> 9538.2269 | U17: =O17+IF(15=36,1000000,0) -> 9538.2269 | V17: =P17+IF(15=36,0,0) -> 0 | W17: =P17+IF(15=36,250000,0) -> 0 | X17: =P17+IF(15=36,500000,0) -> 0 | Y17: =P17+IF(15=36,750000,0) -> 0 | Z17: =P17+IF(15=36,1000000,0) -> 0
A18: FX rate (ZAR/USD) | B18: 15 | C18: 16 | D18: 17 | E18: 18 | F18: 19 | G18: 20 | N18: 16 | O18: =Funding_36M!$G17 -> 9731.9543 | P18: =-Funding_36M!$J17+IF(16=36,Funding_36M!$Q17-Funding_36M!$T17,0) -> 0 | Q18: =O18+IF(16=36,0,0) -> 9731.9543 | R18: =O18+IF(16=36,250000,0) -> 9731.9543 | S18: =O18+IF(16=36,500000,0) -> 9731.9543 | T18: =O18+IF(16=36,750000,0) -> 9731.9543 | U18: =O18+IF(16=36,1000000,0) -> 9731.9543 | V18: =P18+IF(16=36,0,0) -> 0 | W18: =P18+IF(16=36,250000,0) -> 0 | X18: =P18+IF(16=36,500000,0) -> 0 | Y18: =P18+IF(16=36,750000,0) -> 0 | Z18: =P18+IF(16=36,1000000,0) -> 0
A19: 36M BTC revenue (ZAR'000) | B19: =$B$6/Controls!$B$25*B18 -> 510590.68 | C19: =$B$6/Controls!$B$25*C18 -> 544630.06 | D19: =$B$6/Controls!$B$25*D18 -> 578669.44 | E19: =$B$6/Controls!$B$25*E18 -> 612708.82 | F19: =$B$6/Controls!$B$25*F18 -> 646748.19 | G19: =$B$6/Controls!$B$25*G18 -> 680787.57 | I19: Revenue ∝ FX; ZAR opex unaffected. Hardware/containers (USD) capex also scales with FX (see hardware table). | N19: 17 | O19: =Funding_36M!$G18 -> 9149.095 | P19: =-Funding_36M!$J18+IF(17=36,Funding_36M!$Q18-Funding_36M!$T18,0) -> 0 | Q19: =O19+IF(17=36,0,0) -> 9149.095 | R19: =O19+IF(17=36,250000,0) -> 9149.095 | S19: =O19+IF(17=36,500000,0) -> 9149.095 | T19: =O19+IF(17=36,750000,0) -> 9149.095 | U19: =O19+IF(17=36,1000000,0) -> 9149.095 | V19: =P19+IF(17=36,0,0) -> 0 | W19: =P19+IF(17=36,250000,0) -> 0 | X19: =P19+IF(17=36,500000,0) -> 0 | Y19: =P19+IF(17=36,750000,0) -> 0 | Z19: =P19+IF(17=36,1000000,0) -> 0
A20: 36M EBITDA (ZAR'000) | B20: =$B$7+$B$6*(B18/Controls!$B$25-1) -> 178137.31 | C20: =$B$7+$B$6*(C18/Controls!$B$25-1) -> 212176.69 | D20: =$B$7+$B$6*(D18/Controls!$B$25-1) -> 246216.07 | E20: =$B$7+$B$6*(E18/Controls!$B$25-1) -> 280255.44 | F20: =$B$7+$B$6*(F18/Controls!$B$25-1) -> 314294.82 | G20: =$B$7+$B$6*(G18/Controls!$B$25-1) -> 348334.2 | N20: 18 | O20: =Funding_36M!$G19 -> 9333.2353 | P20: =-Funding_36M!$J19+IF(18=36,Funding_36M!$Q19-Funding_36M!$T19,0) -> 0 | Q20: =O20+IF(18=36,0,0) -> 9333.2353 | R20: =O20+IF(18=36,250000,0) -> 9333.2353 | S20: =O20+IF(18=36,500000,0) -> 9333.2353 | T20: =O20+IF(18=36,750000,0) -> 9333.2353 | U20: =O20+IF(18=36,1000000,0) -> 9333.2353 | V20: =P20+IF(18=36,0,0) -> 0 | W20: =P20+IF(18=36,250000,0) -> 0 | X20: =P20+IF(18=36,500000,0) -> 0 | Y20: =P20+IF(18=36,750000,0) -> 0 | Z20: =P20+IF(18=36,1000000,0) -> 0
N21: 19 | O21: =Funding_36M!$G20 -> 14314.631 | P21: =-Funding_36M!$J20+IF(19=36,Funding_36M!$Q20-Funding_36M!$T20,0) -> 0 | Q21: =O21+IF(19=36,0,0) -> 14314.631 | R21: =O21+IF(19=36,250000,0) -> 14314.631 | S21: =O21+IF(19=36,500000,0) -> 14314.631 | T21: =O21+IF(19=36,750000,0) -> 14314.631 | U21: =O21+IF(19=36,1000000,0) -> 14314.631 | V21: =P21+IF(19=36,0,0) -> 0 | W21: =P21+IF(19=36,250000,0) -> 0 | X21: =P21+IF(19=36,500000,0) -> 0 | Y21: =P21+IF(19=36,750000,0) -> 0 | Z21: =P21+IF(19=36,1000000,0) -> 0
A22: Initial Eskom tariff, first 18 months (R/kWh) — post-initial held at R0.60 | B22: 0.8 | C22: 1 | D22: 1.2 | E22: 1.4 | F22: 1.6 | N22: 20 | O22: =Funding_36M!$G21 -> 13058.153 | P22: =-Funding_36M!$J21+IF(20=36,Funding_36M!$Q21-Funding_36M!$T21,0) -> 0 | Q22: =O22+IF(20=36,0,0) -> 13058.153 | R22: =O22+IF(20=36,250000,0) -> 13058.153 | S22: =O22+IF(20=36,500000,0) -> 13058.153 | T22: =O22+IF(20=36,750000,0) -> 13058.153 | U22: =O22+IF(20=36,1000000,0) -> 13058.153 | V22: =P22+IF(20=36,0,0) -> 0 | W22: =P22+IF(20=36,250000,0) -> 0 | X22: =P22+IF(20=36,500000,0) -> 0 | Y22: =P22+IF(20=36,750000,0) -> 0 | Z22: =P22+IF(20=36,1000000,0) -> 0
A23: 36M grid energy cost (ZAR'000) | B23: =SUMPRODUCT((Monthly_Deployment!$A$2:$A$37<=Controls!$B$40)*(Monthly_Deployment!$U$2:$U$37+Monthly_Deployment!$V$2:$V$37))*B22+SUMPRODUCT((Monthly_Deployment!$A$2:$A$37>Controls!$B$40)*(Monthly_Deployment!$U$2:$U$37+Monthly_Deployment!$V$2:$V$37))*Controls!$B$39 -> 198602.88 | C23: =SUMPRODUCT((Monthly_Deployment!$A$2:$A$37<=Controls!$B$40)*(Monthly_Deployment!$U$2:$U$37+Monthly_Deployment!$V$2:$V$37))*C22+SUMPRODUCT((Monthly_Deployment!$A$2:$A$37>Controls!$B$40)*(Monthly_Deployment!$U$2:$U$37+Monthly_Deployment!$V$2:$V$37))*Controls!$B$39 -> 225410.88 | D23: =SUMPRODUCT((Monthly_Deployment!$A$2:$A$37<=Controls!$B$40)*(Monthly_Deployment!$U$2:$U$37+Monthly_Deployment!$V$2:$V$37))*D22+SUMPRODUCT((Monthly_Deployment!$A$2:$A$37>Controls!$B$40)*(Monthly_Deployment!$U$2:$U$37+Monthly_Deployment!$V$2:$V$37))*Controls!$B$39 -> 252218.88 | E23: =SUMPRODUCT((Monthly_Deployment!$A$2:$A$37<=Controls!$B$40)*(Monthly_Deployment!$U$2:$U$37+Monthly_Deployment!$V$2:$V$37))*E22+SUMPRODUCT((Monthly_Deployment!$A$2:$A$37>Controls!$B$40)*(Monthly_Deployment!$U$2:$U$37+Monthly_Deployment!$V$2:$V$37))*Controls!$B$39 -> 279026.88 | F23: =SUMPRODUCT((Monthly_Deployment!$A$2:$A$37<=Controls!$B$40)*(Monthly_Deployment!$U$2:$U$37+Monthly_Deployment!$V$2:$V$37))*F22+SUMPRODUCT((Monthly_Deployment!$A$2:$A$37>Controls!$B$40)*(Monthly_Deployment!$U$2:$U$37+Monthly_Deployment!$V$2:$V$37))*Controls!$B$39 -> 305834.88 | H23: Energy cost ∝ tariff; EBITDA absorbs the difference vs the modelled R1.20 base. | N23: 21 | O23: =Funding_36M!$G22 -> 13925.911 | P23: =-Funding_36M!$J22+IF(21=36,Funding_36M!$Q22-Funding_36M!$T22,0) -> 0 | Q23: =O23+IF(21=36,0,0) -> 13925.911 | R23: =O23+IF(21=36,250000,0) -> 13925.911 | S23: =O23+IF(21=36,500000,0) -> 13925.911 | T23: =O23+IF(21=36,750000,0) -> 13925.911 | U23: =O23+IF(21=36,1000000,0) -> 13925.911 | V23: =P23+IF(21=36,0,0) -> 0 | W23: =P23+IF(21=36,250000,0) -> 0 | X23: =P23+IF(21=36,500000,0) -> 0 | Y23: =P23+IF(21=36,750000,0) -> 0 | Z23: =P23+IF(21=36,1000000,0) -> 0
A24: 36M EBITDA (ZAR'000) | B24: =$B$7+((SUM(Opex_36M!$D$2:$D$37)+SUM(Opex_36M!$E$2:$E$37))-B23) -> 299832.07 | C24: =$B$7+((SUM(Opex_36M!$D$2:$D$37)+SUM(Opex_36M!$E$2:$E$37))-C23) -> 273024.07 | D24: =$B$7+((SUM(Opex_36M!$D$2:$D$37)+SUM(Opex_36M!$E$2:$E$37))-D23) -> 246216.07 | E24: =$B$7+((SUM(Opex_36M!$D$2:$D$37)+SUM(Opex_36M!$E$2:$E$37))-E23) -> 219408.07 | F24: =$B$7+((SUM(Opex_36M!$D$2:$D$37)+SUM(Opex_36M!$E$2:$E$37))-F23) -> 192600.07 | N24: 22 | O24: =Funding_36M!$G23 -> 13215.795 | P24: =-Funding_36M!$J23+IF(22=36,Funding_36M!$Q23-Funding_36M!$T23,0) -> 0 | Q24: =O24+IF(22=36,0,0) -> 13215.795 | R24: =O24+IF(22=36,250000,0) -> 13215.795 | S24: =O24+IF(22=36,500000,0) -> 13215.795 | T24: =O24+IF(22=36,750000,0) -> 13215.795 | U24: =O24+IF(22=36,1000000,0) -> 13215.795 | V24: =P24+IF(22=36,0,0) -> 0 | W24: =P24+IF(22=36,250000,0) -> 0 | X24: =P24+IF(22=36,500000,0) -> 0 | Y24: =P24+IF(22=36,750000,0) -> 0 | Z24: =P24+IF(22=36,1000000,0) -> 0
N25: 23 | O25: =Funding_36M!$G24 -> 3017.4365 | P25: =-Funding_36M!$J24+IF(23=36,Funding_36M!$Q24-Funding_36M!$T24,0) -> 0 | Q25: =O25+IF(23=36,0,0) -> 3017.4365 | R25: =O25+IF(23=36,250000,0) -> 3017.4365 | S25: =O25+IF(23=36,500000,0) -> 3017.4365 | T25: =O25+IF(23=36,750000,0) -> 3017.4365 | U25: =O25+IF(23=36,1000000,0) -> 3017.4365 | V25: =P25+IF(23=36,0,0) -> 0 | W25: =P25+IF(23=36,250000,0) -> 0 | X25: =P25+IF(23=36,500000,0) -> 0 | Y25: =P25+IF(23=36,750000,0) -> 0 | Z25: =P25+IF(23=36,1000000,0) -> 0
A26: Hardware cost (USD per TH) — base implies $8.45/TH | B26: 6 | C26: 8 | D26: 8.45 | E26: 10 | F26: 12 | G26: 15 | N26: 24 | O26: =Funding_36M!$G25 -> 2753.627 | P26: =-Funding_36M!$J25+IF(24=36,Funding_36M!$Q25-Funding_36M!$T25,0) -> 0 | Q26: =O26+IF(24=36,0,0) -> 2753.627 | R26: =O26+IF(24=36,250000,0) -> 2753.627 | S26: =O26+IF(24=36,500000,0) -> 2753.627 | T26: =O26+IF(24=36,750000,0) -> 2753.627 | U26: =O26+IF(24=36,1000000,0) -> 2753.627 | V26: =P26+IF(24=36,0,0) -> 0 | W26: =P26+IF(24=36,250000,0) -> 0 | X26: =P26+IF(24=36,500000,0) -> 0 | Y26: =P26+IF(24=36,750000,0) -> 0 | Z26: =P26+IF(24=36,1000000,0) -> 0
A27: Total ASIC capex (ZAR'000) | B27: =SUM(Capex_36M!$G$2:$G$37)/(Controls!$B$46/Controls!$B$43)*B26 -> 155428.57 | C27: =SUM(Capex_36M!$G$2:$G$37)/(Controls!$B$46/Controls!$B$43)*C26 -> 207238.1 | D27: =SUM(Capex_36M!$G$2:$G$37)/(Controls!$B$46/Controls!$B$43)*D26 -> 218895.24 | E27: =SUM(Capex_36M!$G$2:$G$37)/(Controls!$B$46/Controls!$B$43)*E26 -> 259047.62 | F27: =SUM(Capex_36M!$G$2:$G$37)/(Controls!$B$46/Controls!$B$43)*F26 -> 310857.14 | G27: =SUM(Capex_36M!$G$2:$G$37)/(Controls!$B$46/Controls!$B$43)*G26 -> 388571.43 | H27: ASIC ∝ USD/TH. Negative headroom = committed facilities undersized at that hardware price. | N27: 25 | O27: =Funding_36M!$G26 -> 2829.5658 | P27: =-Funding_36M!$J26+IF(25=36,Funding_36M!$Q26-Funding_36M!$T26,0) -> 0 | Q27: =O27+IF(25=36,0,0) -> 2829.5658 | R27: =O27+IF(25=36,250000,0) -> 2829.5658 | S27: =O27+IF(25=36,500000,0) -> 2829.5658 | T27: =O27+IF(25=36,750000,0) -> 2829.5658 | U27: =O27+IF(25=36,1000000,0) -> 2829.5658 | V27: =P27+IF(25=36,0,0) -> 0 | W27: =P27+IF(25=36,250000,0) -> 0 | X27: =P27+IF(25=36,500000,0) -> 0 | Y27: =P27+IF(25=36,750000,0) -> 0 | Z27: =P27+IF(25=36,1000000,0) -> 0
A28: Total Phase 1 capex (ZAR'000) | B28: =SUM(Capex_36M!$O$2:$O$37)+(B27-SUM(Capex_36M!$G$2:$G$37))*(1+Controls!$B$55) -> 446720.86 | C28: =SUM(Capex_36M!$O$2:$O$37)+(C27-SUM(Capex_36M!$G$2:$G$37))*(1+Controls!$B$55) -> 499566.57 | D28: =SUM(Capex_36M!$O$2:$O$37)+(D27-SUM(Capex_36M!$G$2:$G$37))*(1+Controls!$B$55) -> 511456.86 | E28: =SUM(Capex_36M!$O$2:$O$37)+(E27-SUM(Capex_36M!$G$2:$G$37))*(1+Controls!$B$55) -> 552412.29 | F28: =SUM(Capex_36M!$O$2:$O$37)+(F27-SUM(Capex_36M!$G$2:$G$37))*(1+Controls!$B$55) -> 605258 | G28: =SUM(Capex_36M!$O$2:$O$37)+(G27-SUM(Capex_36M!$G$2:$G$37))*(1+Controls!$B$55) -> 684526.57 | N28: 26 | O28: =Funding_36M!$G27 -> 2736.8226 | P28: =-Funding_36M!$J27+IF(26=36,Funding_36M!$Q27-Funding_36M!$T27,0) -> 0 | Q28: =O28+IF(26=36,0,0) -> 2736.8226 | R28: =O28+IF(26=36,250000,0) -> 2736.8226 | S28: =O28+IF(26=36,500000,0) -> 2736.8226 | T28: =O28+IF(26=36,750000,0) -> 2736.8226 | U28: =O28+IF(26=36,1000000,0) -> 2736.8226 | V28: =P28+IF(26=36,0,0) -> 0 | W28: =P28+IF(26=36,250000,0) -> 0 | X28: =P28+IF(26=36,500000,0) -> 0 | Y28: =P28+IF(26=36,750000,0) -> 0 | Z28: =P28+IF(26=36,1000000,0) -> 0
A29: Headroom vs committed, ex-fees (ZAR'000) | B29: =(Controls!$B$100+Controls!$B$101+Controls!$B$104)-B28-Controls!$B$111 -> 82066.643 | C29: =(Controls!$B$100+Controls!$B$101+Controls!$B$104)-C28-Controls!$B$111 -> 29220.929 | D29: =(Controls!$B$100+Controls!$B$101+Controls!$B$104)-D28-Controls!$B$111 -> 17330.643 | E29: =(Controls!$B$100+Controls!$B$101+Controls!$B$104)-E28-Controls!$B$111 -> -23624.786 | F29: =(Controls!$B$100+Controls!$B$101+Controls!$B$104)-F28-Controls!$B$111 -> -76470.5 | G29: =(Controls!$B$100+Controls!$B$101+Controls!$B$104)-G28-Controls!$B$111 -> -155739.07 | N29: 27 | O29: =Funding_36M!$G28 -> 2484.3665 | P29: =-Funding_36M!$J28+IF(27=36,Funding_36M!$Q28-Funding_36M!$T28,0) -> 0 | Q29: =O29+IF(27=36,0,0) -> 2484.3665 | R29: =O29+IF(27=36,250000,0) -> 2484.3665 | S29: =O29+IF(27=36,500000,0) -> 2484.3665 | T29: =O29+IF(27=36,750000,0) -> 2484.3665 | U29: =O29+IF(27=36,1000000,0) -> 2484.3665 | V29: =P29+IF(27=36,0,0) -> 0 | W29: =P29+IF(27=36,250000,0) -> 0 | X29: =P29+IF(27=36,500000,0) -> 0 | Y29: =P29+IF(27=36,750000,0) -> 0 | Z29: =P29+IF(27=36,1000000,0) -> 0
N30: 28 | O30: =Funding_36M!$G29 -> 2553.6898 | P30: =-Funding_36M!$J29+IF(28=36,Funding_36M!$Q29-Funding_36M!$T29,0) -> 0 | Q30: =O30+IF(28=36,0,0) -> 2553.6898 | R30: =O30+IF(28=36,250000,0) -> 2553.6898 | S30: =O30+IF(28=36,500000,0) -> 2553.6898 | T30: =O30+IF(28=36,750000,0) -> 2553.6898 | U30: =O30+IF(28=36,1000000,0) -> 2553.6898 | V30: =P30+IF(28=36,0,0) -> 0 | W30: =P30+IF(28=36,250000,0) -> 0 | X30: =P30+IF(28=36,500000,0) -> 0 | Y30: =P30+IF(28=36,750000,0) -> 0 | Z30: =P30+IF(28=36,1000000,0) -> 0
A31: Terminal (continuation) value → IRR — base = R500,000k (Controls) | N31: 29 | O31: =Funding_36M!$G30 -> 2308.6462 | P31: =-Funding_36M!$J30+IF(29=36,Funding_36M!$Q30-Funding_36M!$T30,0) -> 0 | Q31: =O31+IF(29=36,0,0) -> 2308.6462 | R31: =O31+IF(29=36,250000,0) -> 2308.6462 | S31: =O31+IF(29=36,500000,0) -> 2308.6462 | T31: =O31+IF(29=36,750000,0) -> 2308.6462 | U31: =O31+IF(29=36,1000000,0) -> 2308.6462 | V31: =P31+IF(29=36,0,0) -> 0 | W31: =P31+IF(29=36,250000,0) -> 0 | X31: =P31+IF(29=36,500000,0) -> 0 | Y31: =P31+IF(29=36,750000,0) -> 0 | Z31: =P31+IF(29=36,1000000,0) -> 0
A32: Terminal EV (ZAR'000) | B32: 0 | C32: 250000 | D32: 500000 | E32: 750000 | F32: 1000000 | N32: 30 | O32: =Funding_36M!$G31 -> 2373.6552 | P32: =-Funding_36M!$J31+IF(30=36,Funding_36M!$Q31-Funding_36M!$T31,0) -> 0 | Q32: =O32+IF(30=36,0,0) -> 2373.6552 | R32: =O32+IF(30=36,250000,0) -> 2373.6552 | S32: =O32+IF(30=36,500000,0) -> 2373.6552 | T32: =O32+IF(30=36,750000,0) -> 2373.6552 | U32: =O32+IF(30=36,1000000,0) -> 2373.6552 | V32: =P32+IF(30=36,0,0) -> 0 | W32: =P32+IF(30=36,250000,0) -> 0 | X32: =P32+IF(30=36,500000,0) -> 0 | Y32: =P32+IF(30=36,750000,0) -> 0 | Z32: =P32+IF(30=36,1000000,0) -> 0
A33: Unlevered IRR | B33: =IFERROR((1+IRR(Q3:Q38,0.01))^12-1,"n/a") -> -0.47066251 | C33: =IFERROR((1+IRR(R3:R38,0.01))^12-1,"n/a") -> -0.015865172 | D33: =IFERROR((1+IRR(S3:S38,0.01))^12-1,"n/a") -> 0.1974839 | E33: =IFERROR((1+IRR(T3:T38,0.01))^12-1,"n/a") -> 0.35343712 | F33: =IFERROR((1+IRR(U3:U38,0.01))^12-1,"n/a") -> 0.48024804 | N33: 31 | O33: =Funding_36M!$G32 -> 2284.7848 | P33: =-Funding_36M!$J32+IF(31=36,Funding_36M!$Q32-Funding_36M!$T32,0) -> 0 | Q33: =O33+IF(31=36,0,0) -> 2284.7848 | R33: =O33+IF(31=36,250000,0) -> 2284.7848 | S33: =O33+IF(31=36,500000,0) -> 2284.7848 | T33: =O33+IF(31=36,750000,0) -> 2284.7848 | U33: =O33+IF(31=36,1000000,0) -> 2284.7848 | V33: =P33+IF(31=36,0,0) -> 0 | W33: =P33+IF(31=36,250000,0) -> 0 | X33: =P33+IF(31=36,500000,0) -> 0 | Y33: =P33+IF(31=36,750000,0) -> 0 | Z33: =P33+IF(31=36,1000000,0) -> 0
A34: Equity IRR | B34: =IFERROR((1+IRR(V3:V38,0.01))^12-1,"n/a") -> n/a | C34: =IFERROR((1+IRR(W3:W38,0.01))^12-1,"n/a") -> n/a | D34: =IFERROR((1+IRR(X3:X38,0.01))^12-1,"n/a") -> 0.31458689 | E34: =IFERROR((1+IRR(Y3:Y38,0.01))^12-1,"n/a") -> 0.84834135 | F34: =IFERROR((1+IRR(Z3:Z38,0.01))^12-1,"n/a") -> 1.187567 | N34: 32 | O34: =Funding_36M!$G33 -> 1758.5465 | P34: =-Funding_36M!$J33+IF(32=36,Funding_36M!$Q33-Funding_36M!$T33,0) -> 0 | Q34: =O34+IF(32=36,0,0) -> 1758.5465 | R34: =O34+IF(32=36,250000,0) -> 1758.5465 | S34: =O34+IF(32=36,500000,0) -> 1758.5465 | T34: =O34+IF(32=36,750000,0) -> 1758.5465 | U34: =O34+IF(32=36,1000000,0) -> 1758.5465 | V34: =P34+IF(32=36,0,0) -> 0 | W34: =P34+IF(32=36,250000,0) -> 0 | X34: =P34+IF(32=36,500000,0) -> 0 | Y34: =P34+IF(32=36,750000,0) -> 0 | Z34: =P34+IF(32=36,1000000,0) -> 0
A35: "n/a" = capital not recovered within 36 months on a standalone basis. Same monthly cash flows as Funding_36M. | N35: 33 | O35: =Funding_36M!$G34 -> 2109.3082 | P35: =-Funding_36M!$J34+IF(33=36,Funding_36M!$Q34-Funding_36M!$T34,0) -> 0 | Q35: =O35+IF(33=36,0,0) -> 2109.3082 | R35: =O35+IF(33=36,250000,0) -> 2109.3082 | S35: =O35+IF(33=36,500000,0) -> 2109.3082 | T35: =O35+IF(33=36,750000,0) -> 2109.3082 | U35: =O35+IF(33=36,1000000,0) -> 2109.3082 | V35: =P35+IF(33=36,0,0) -> 0 | W35: =P35+IF(33=36,250000,0) -> 0 | X35: =P35+IF(33=36,500000,0) -> 0 | Y35: =P35+IF(33=36,750000,0) -> 0 | Z35: =P35+IF(33=36,1000000,0) -> 0
N36: 34 | O36: =Funding_36M!$G35 -> 1882.2611 | P36: =-Funding_36M!$J35+IF(34=36,Funding_36M!$Q35-Funding_36M!$T35,0) -> 0 | Q36: =O36+IF(34=36,0,0) -> 1882.2611 | R36: =O36+IF(34=36,250000,0) -> 1882.2611 | S36: =O36+IF(34=36,500000,0) -> 1882.2611 | T36: =O36+IF(34=36,750000,0) -> 1882.2611 | U36: =O36+IF(34=36,1000000,0) -> 1882.2611 | V36: =P36+IF(34=36,0,0) -> 0 | W36: =P36+IF(34=36,250000,0) -> 0 | X36: =P36+IF(34=36,500000,0) -> 0 | Y36: =P36+IF(34=36,750000,0) -> 0 | Z36: =P36+IF(34=36,1000000,0) -> 0
N37: 35 | O37: =Funding_36M!$G36 -> 1936.8117 | P37: =-Funding_36M!$J36+IF(35=36,Funding_36M!$Q36-Funding_36M!$T36,0) -> 0 | Q37: =O37+IF(35=36,0,0) -> 1936.8117 | R37: =O37+IF(35=36,250000,0) -> 1936.8117 | S37: =O37+IF(35=36,500000,0) -> 1936.8117 | T37: =O37+IF(35=36,750000,0) -> 1936.8117 | U37: =O37+IF(35=36,1000000,0) -> 1936.8117 | V37: =P37+IF(35=36,0,0) -> 0 | W37: =P37+IF(35=36,250000,0) -> 0 | X37: =P37+IF(35=36,500000,0) -> 0 | Y37: =P37+IF(35=36,750000,0) -> 0 | Z37: =P37+IF(35=36,1000000,0) -> 0
N38: 36 | O38: =Funding_36M!$G37 -> 1716.7542 | P38: =-Funding_36M!$J37+IF(36=36,Funding_36M!$Q37-Funding_36M!$T37,0) -> -350397.66 | Q38: =O38+IF(36=36,0,0) -> 1716.7542 | R38: =O38+IF(36=36,250000,0) -> 251716.75 | S38: =O38+IF(36=36,500000,0) -> 501716.75 | T38: =O38+IF(36=36,750000,0) -> 751716.75 | U38: =O38+IF(36=36,1000000,0) -> 1001716.8 | V38: =P38+IF(36=36,0,0) -> -350397.66 | W38: =P38+IF(36=36,250000,0) -> -100397.66 | X38: =P38+IF(36=36,500000,0) -> 149602.34 | Y38: =P38+IF(36=36,750000,0) -> 399602.34 | Z38: =P38+IF(36=36,1000000,0) -> 649602.34
